Workbook

Sheet ControlPanel
A1: 季度复核工作模型 | B1: 当前输入/状态 | C1: 含义
A2: 起点季度 | B2: 20240630 | C2: WF_START_PERIOD；原始CSV已有季度整数
A3: 终点季度 | B3: 20250630 | C3: WF_END_PERIOD；须晚于起点
A4: 核查容量 | B4: 8 | C4: WF_REVIEW_SLOTS；3–12整数
A5: 模型有效 | B5: =AND(COUNTIF(Periods!$A$2:$A$15,WF_START_PERIOD)=1,COUNTIF(Periods!$A$2:$A$15,WF_END_PERIOD)=1,WF_START_PERIOD<WF_END_PERIOD,ISNUMBER(WF_REVIEW_SLOTS),WF_REVIEW_SLOTS=INT(WF_REVIEW_SLOTS),WF_REVIEW_SLOTS>=3,WF_REVIEW_SLOTS<=12,SUM(BankCalc!$E$2:$E$55)>=WF_REVIEW_SLOTS,COUNTIFS(BankCalc!$G$2:$G$55,"VT",BankCalc!$E$2:$E$55,1)>0,COUNTIFS(BankCalc!$G$2:$G$55,"NH",BankCalc!$E$2:$E$55,1)>0,COUNTIFS(BankCalc!$G$2:$G$55,"ME",BankCalc!$E$2:$E$55,1)>0) -> TRUE | C5: FALSE时没有可执行名单；请修正季度或容量
A6: 原始金额未修订 | B6: =SUM(RawFinancials!$AD$2:$AD$747)=0 -> TRUE | C6: 逐行检查三项金额；空值与数值0不同
A7: 静态快照仍适用 | B7: =AND(WF_START_PERIOD=20240630,WF_END_PERIOD=20250630,WF_REVIEW_SLOTS=8,WF_RAW_UNCHANGED) -> TRUE | C7: Word和CSV为默认输入+原始金额快照，FALSE时必须重新导出
A8: 实际核查数 | B8: =COUNT(Priority!$B$2:$B$13) -> 8 | C8: 12行读取接口，当前容量以外为空
A9: 需核实的资本比率0 | B9: 原样保留并逐行标记 | C9: 0不能单独支持“资本为零”，也不擅自转缺失
A10: 可编辑副本 | B10: RawFinancials仅三项金额可修订 | C10: ASSET、P9ASSET、NAASSET；原始CSV始终只读
A11: 使用提示 | B11: =IF(WF_MODEL_VALID,"当前模型有效；解释仍需贷款级补证","输入无效，请修正季度或名额；不得使用旧名单") -> 当前模型有效；解释仍需贷款级补证 | C11: 派生比率是复核代理，不是监管评级

Sheet DataAudit
A1: check | B1: CERT | C1: value
A2: financial_rows | C2: 746
A3: unique_banks | C3: 54
A4: quarters | C4: 14
A5: duplicate_bank_quarters | C5: 0
A6: institution_rows | C6: 355
A7: duplicate_institution_CERT | C7: 0
A8: unmatched_financial_rows | C8: 0
A9: ambiguous_financial_rows | C9: 0
A10: zero_or_missing_assets | C10: 0
A11: missing_proxy | C11: 0
A12: missing_quarters | B12: 4255 | C12: none
A13: missing_quarters | B13: 4256 | C13: none
A14: missing_quarters | B14: 6271 | C14: none
A15: missing_quarters | B15: 6275 | C15: none
A16: missing_quarters | B16: 6280 | C16: none
A17: missing_quarters | B17: 11971 | C17: none
A18: missing_quarters | B18: 12874 | C18: none
A19: missing_quarters | B19: 13063 | C19: none
A20: missing_quarters | B20: 14134 | C20: none
A21: missing_quarters | B21: 14136 | C21: none
A22: missing_quarters | B22: 14140 | C22: none
A23: missing_quarters | B23: 14158 | C23: none
... A65: missing_quarters | B65: 59298 | C65: 20220331,20220630
A66: institution_snapshot_RUNDATE | C66: 10/09/2026
A67: institution_snapshot_RISDATE | C67: 06/30/2026
A68: current_invalid_proxy_rows | C68: =COUNTIF(RawFinancials!$AA$2:$AA$747,0) -> 0
A69: current_revised_amount_rows | C69: =SUM(RawFinancials!$AD$2:$AD$747) -> 0
A70: invalid_rows_locator | C70: RawFinancials: proxy_valid=0，原始行号在source_row；不补零
A71: capital_ratio_raw_zero | C71: BankQuarter capital_zero_note逐行标记；需核实适用/报告口径，保留原0

Sheet Sources
A1: source | B1: locator | C1: reference | D1: use
A2: fdic_api_documentation.html | B2: Financial API Definitions (YAML format) | C2: https://api.fdic.gov/banks/docs/risview_properties.yaml | D2: 网页实际引用；下游材料用于本题同一业务决定。
A3: financial_definitions.yaml | B3: ASSET, NAASSET, P9ASSET, ROA, RBCRWAJ | C3: FDIC API Financial definitions | D3: ROA为已年化百分数；P9ASSET与NAASSET为资产口径代理，非监管评级。
A4: institution_definitions.yaml | B4: CERT, ACTIVE | C4: FDIC API Institution definitions | D4: CERT主键与更晚机构快照；不按ACTIVE删除历史。
A5: FDIC_RMS_Manual_3.2_Loans.pdf | B5: Loan Review Systems；本地PDF页1,3,4,5,8 | C5: Section 3.2 Loans | D5: 复核贷款质量、集中风险、分类、还款及内部贷款审查，代理指标不足以独立评级。
A6: instruction.md | B6: 金额口径与核查名额规则 | C6: 本次桌面练习明确设定 | D6: 金额千美元、先州覆盖后区域高值；排序门槛不是监管规定。

Sheet Periods
A1: REPDTE
A2: 20220331
A3: 20220630
A4: 20220930
A5: 20221231
A6: 20230331
A7: 20230630
A8: 20230930
A9: 20231231
A10: 20240331
A11: 20240630
A12: 20240930
A13: 20241231
... A15: 20250630

Sheet OriginalFinancials
A1: source_row | B1: ASSET | C1: CERT | D1: DEP | E1: ELNATRY | F1: EQ | G1: EQV | H1: ID | I1: LNATRESR | J1: LNCI | K1: LNCON | L1: LNLSGR | M1: LNLSNET | N1: LNRE | O1: NAASSET | P1: NAMEFULL | Q1: NCLNLSR | R1: NIMY | S1: NTLNLS | T1: P3ASSET | U1: P9ASSET | V1: RBCRWAJ | W1: REPDTE | X1: ROA | Y1: ROE | Z1: STALP
A2: 2 | B2: 3688993 | C2: 11971 | D2: 3055632 | E2: 0.08 | F2: 461681 | G2: 12.515096 | H2: 11971_20220331 | I2: 0.87265551 | J2: 201303 | K2: 7873 | L2: 2657406 | M2: 2634216 | N2: 2317079 | O2: 9213 | P2: BAR HARBOR BANK & TRUST | Q2: 0.37841414 | R2: 3.0067421 | S2: -95 | T2: 4642 | U2: 843 | V2: 13.678961 | W2: 20220331 | X2: 1.1162343 | Y2: 8.77 | Z2: ME
A3: 3 | B3: 964163 | C3: 12874 | D3: 854194 | E3: 0 | F3: 97916 | G3: 10.155544 | H3: 12874_20220331 | I3: 1.0653481 | J3: 138143 | K3: 5249 | L3: 732906 | M3: 725098 | N3: 577596 | O3: 1069 | P3: KATAHDIN TRUST COMPANY | Q3: 0.14585772 | R3: 3.4019504 | S3: -5 | T3: 374 | U3: 0 | V3: 15.601603 | W3: 20220331 | X3: 0.83149732 | Y3: 7.95 | Z3: ME
A4: 4 | B4: 1784835 | C4: 13063 | D4: 1619076 | E4: 0 | F4: 148181 | G4: 8.302224 | H4: 13063_20220331 | I4: 1.21801 | J4: 55361 | K4: 837 | L4: 1223389 | M4: 1208488 | N4: 1160807 | O4: 408 | P4: KENNEBUNK SAVINGS BANK | Q4: 0.1311112 | R4: 3.2711148 | S4: -5 | T4: 3 | U4: 1196 | V4: 0 | W4: 20220331 | X4: 0.48237313 | Y4: 5.56 | Z4: ME
A5: 5 | B5: 869402 | C5: 14134 | D5: 737795 | E5: 0.1 | F5: 101808 | G5: 11.710118 | H5: 14134_20220331 | I5: 1.4014366 | J5: 27870 | K5: 26813 | L5: 596388 | M5: 588030 | N5: 516229 | O5: 8014 | P5: PASSUMPSIC SAVINGS BANK | Q5: 1.3437561 | R5: 2.742438 | S5: 19 | T5: 4990 | U5: 0 | V5: 17.570983 | W5: 20220331 | X5: -0.38729339 | Y5: -3.23 | Z5: VT
A6: 6 | B6: 222692 | C6: 14136 | D6: 199279 | E6: 0.08 | F6: 18834 | G6: 8.457421 | H6: 14136_20220331 | I6: 1.1501745 | J6: 12518 | K6: 11422 | L6: 121199 | M6: 119805 | N6: 96809 | O6: 174 | P6: WELLS RIVER SAVINGS BANK | Q6: 0.67079761 | R6: 3.42237 | S6: 7 | T6: 803 | U6: 639 | V6: 17.27622 | W6: 20220331 | X6: 0.19954922 | Y6: 2.14 | Z6: VT
A7: 7 | B7: 1414510 | C7: 14140 | D7: 1199427 | E7: 0 | F7: 123854 | G7: 8.755965 | H7: 14140_20220331 | I7: 1.1077738 | J7: 82518 | K7: 1318 | L7: 957867 | M7: 947256 | N7: 866005 | O7: 5589 | P7: NORTHFIELD SAVINGS BANK | Q7: 0.58348393 | R7: 2.9698131 | S7: 9 | T7: 785 | U7: 0 | V7: 0 | W7: 20220331 | X7: 0.66212632 | Y7: 7.07 | Z7: VT
A8: 8 | B8: 1232701 | C8: 14158 | D8: 1137254 | E8: 0 | F8: 85105 | G8: 6.9039451 | H8: 14158_20220331 | I8: 1.0031734 | J8: 44549 | K8: 2157 | L8: 830963 | M8: 822627 | N8: 698008 | O8: 4405 | P8: UNION BANK | Q8: 0.55766623 | R8: 3.1853735 | S8: 0 | T8: 1620 | U8: 229 | V8: 14.788126 | W8: 20220331 | X8: 0.88329132 | Y8: 11.64 | Z8: VT
A9: 9 | B9: 384095 | C9: 14168 | D9: 345364 | E9: 0 | F9: 34244 | G9: 8.9155027 | H9: 14168_20220331 | I9: 1.5327875 | J9: 9537 | K9: 8111 | L9: 191155 | M9: 188225 | N9: 161619 | O9: 1188 | P9: PEOPLES TRUST COMPANY OF ST. ALBANS | Q9: 0.62148518 | R9: 2.4184591 | S9: 34 | T9: 187 | U9: 0 | V9: 19.824643 | W9: 20220331 | X9: 0.13578832 | Y9: 1.45 | Z9: VT
A10: 10 | B10: 1221074 | C10: 14240 | D10: 1020645 | E10: 0 | F10: 102113 | G10: 8.3625562 | H10: 14240_20220331 | I10: 1.1483381 | J10: 29648 | K10: 17990 | L10: 824670 | M10: 815200 | N10: 705835 | O10: 2204 | P10: NORTHWAY BANK | Q10: 0.26725842 | R10: 2.8194207 | S10: -4 | T10: 1936 | U10: 0 | V10: 15.106992 | W10: 20220331 | X10: 0.069811881 | Y10: 0.79 | Z10: NH
A11: 11 | B11: 836644 | C11: 17115 | D11: 738943 | E11: -0.08 | F11: 83239 | G11: 9.949154 | H11: 17115_20220331 | I11: 1.167132 | J11: 43003 | K11: 3606 | L11: 656481 | M11: 648819 | N11: 608827 | O11: 164 | P11: PARTNERS BANK OF NEW ENGLAND | Q11: 0.024981683 | R11: 3.5126362 | S11: 240 | T11: 62 | U11: 0 | V11: 15.606469 | W11: 20220331 | X11: 1.1149693 | Y11: 11.05 | Z11: ME
A12: 12 | B12: 1291920 | C12: 17180 | D12: 1121172 | E12: 0.06 | F12: 126979 | G12: 9.8287046 | H12: 17180_20220331 | I12: 0.98616206 | J12: 44797 | K12: 141431 | L12: 1143017 | M12: 1131745 | N12: 937482 | O12: 5753 | P12: MEREDITH VILLAGE SAVINGS BANK | Q12: 0.5033171 | R12: 3.5699932 | S12: 36 | T12: 1540 | U12: 0 | V12: 16.056943 | W12: 20220331 | X12: 0.80278929 | Y12: 8.11 | Z12: NH
A13: 13 | B13: 352255 | C13: 17443 | D13: 302135 | E13: 0.06 | F13: 42822 | G13: 12.156534 | H13: 17443_20220331 | I13: 0.85841907 | J13: 0 | K13: 1909 | L13: 188952 | M13: 187330 | N13: 186037 | O13: 842 | P13: PISCATAQUA SAVINGS BANK | Q13: 0.44561582 | R13: 2.0122179 | S13: 0 | T13: 2524 | U13: 0 | V13: 0 | W13: 20220331 | X13: 0.61925341 | Y13: 4.79 | Z13: NH
... A747: 747 | B747: 87770 | C747: 6280 | D747: 77256 | E747: 0.09 | F747: 9949 | G747: 11.335308 | H747: 6280_20250630 | I747: 1.2995896 | J747: 3899 | K747: 1311 | L747: 73100 | M747: 72150 | N747: 64947 | O747: 1455 | P747: THE FIRST NATIONAL BANK OF ORWELL | Q747: 1.9904241 | R747: 4.5394341 | S747: 0 | T747: 592 | U747: 0 | V747: 0 | W747: 20250630 | X747: 1.3665403 | Y747: 12.13 | Z747: VT

Sheet RawFinancials
A1: source_row | B1: ASSET | C1: CERT | D1: DEP | E1: ELNATRY | F1: EQ | G1: EQV | H1: ID | I1: LNATRESR | J1: LNCI | K1: LNCON | L1: LNLSGR | M1: LNLSNET | N1: LNRE | O1: NAASSET | P1: NAMEFULL | Q1: NCLNLSR | R1: NIMY | S1: NTLNLS | T1: P3ASSET | U1: P9ASSET | V1: RBCRWAJ | W1: REPDTE | X1: ROA | Y1: ROE | Z1: STALP | AA1: proxy_valid | AB1: proxy_numerator | AC1: proxy_pct | AD1: amount_changed | AE1: capital_zero_note
A2: 2 | B2: 3688993 | C2: 11971 | D2: 3055632 | E2: 0.08 | F2: 461681 | G2: 12.515096 | H2: 11971_20220331 | I2: 0.87265551 | J2: 201303 | K2: 7873 | L2: 2657406 | M2: 2634216 | N2: 2317079 | O2: 9213 | P2: BAR HARBOR BANK & TRUST | Q2: 0.37841414 | R2: 3.0067421 | S2: -95 | T2: 4642 | U2: 843 | V2: 13.678961 | W2: 20220331 | X2: 1.1162343 | Y2: 8.77 | Z2: ME | AA2: =IF(AND(ISNUMBER(B2),B2>0,ISNUMBER(U2),U2>=0,ISNUMBER(O2),O2>=0),1,0) -> 1 | AB2: =IF(AA2=1,U2+O2,0) -> 10056 | AC2: =IF(AA2=1,100*AB2/B2,"") -> 0.27259472 | AD2: =IF(AND(AND(ISNUMBER(B2),B2=OriginalFinancials!B2),AND(ISNUMBER(U2),U2=OriginalFinancials!U2),AND(ISNUMBER(O2),O2=OriginalFinancials!O2)),0,1) -> 0 | AE2: =IF(V2=0,"原始0：需核实适用/报告口径","")
A3: 3 | B3: 964163 | C3: 12874 | D3: 854194 | E3: 0 | F3: 97916 | G3: 10.155544 | H3: 12874_20220331 | I3: 1.0653481 | J3: 138143 | K3: 5249 | L3: 732906 | M3: 725098 | N3: 577596 | O3: 1069 | P3: KATAHDIN TRUST COMPANY | Q3: 0.14585772 | R3: 3.4019504 | S3: -5 | T3: 374 | U3: 0 | V3: 15.601603 | W3: 20220331 | X3: 0.83149732 | Y3: 7.95 | Z3: ME | AA3: =IF(AND(ISNUMBER(B3),B3>0,ISNUMBER(U3),U3>=0,ISNUMBER(O3),O3>=0),1,0) -> 1 | AB3: =IF(AA3=1,U3+O3,0) -> 1069 | AC3: =IF(AA3=1,100*AB3/B3,"") -> 0.11087337 | AD3: =IF(AND(AND(ISNUMBER(B3),B3=OriginalFinancials!B3),AND(ISNUMBER(U3),U3=OriginalFinancials!U3),AND(ISNUMBER(O3),O3=OriginalFinancials!O3)),0,1) -> 0 | AE3: =IF(V3=0,"原始0：需核实适用/报告口径","")
A4: 4 | B4: 1784835 | C4: 13063 | D4: 1619076 | E4: 0 | F4: 148181 | G4: 8.302224 | H4: 13063_20220331 | I4: 1.21801 | J4: 55361 | K4: 837 | L4: 1223389 | M4: 1208488 | N4: 1160807 | O4: 408 | P4: KENNEBUNK SAVINGS BANK | Q4: 0.1311112 | R4: 3.2711148 | S4: -5 | T4: 3 | U4: 1196 | V4: 0 | W4: 20220331 | X4: 0.48237313 | Y4: 5.56 | Z4: ME | AA4: =IF(AND(ISNUMBER(B4),B4>0,ISNUMBER(U4),U4>=0,ISNUMBER(O4),O4>=0),1,0) -> 1 | AB4: =IF(AA4=1,U4+O4,0) -> 1604 | AC4: =IF(AA4=1,100*AB4/B4,"") -> 0.089868251 | AD4: =IF(AND(AND(ISNUMBER(B4),B4=OriginalFinancials!B4),AND(ISNUMBER(U4),U4=OriginalFinancials!U4),AND(ISNUMBER(O4),O4=OriginalFinancials!O4)),0,1) -> 0 | AE4: =IF(V4=0,"原始0：需核实适用/报告口径","") -> 原始0：需核实适用/报告口径
A5: 5 | B5: 869402 | C5: 14134 | D5: 737795 | E5: 0.1 | F5: 101808 | G5: 11.710118 | H5: 14134_20220331 | I5: 1.4014366 | J5: 27870 | K5: 26813 | L5: 596388 | M5: 588030 | N5: 516229 | O5: 8014 | P5: PASSUMPSIC SAVINGS BANK | Q5: 1.3437561 | R5: 2.742438 | S5: 19 | T5: 4990 | U5: 0 | V5: 17.570983 | W5: 20220331 | X5: -0.38729339 | Y5: -3.23 | Z5: VT | AA5: =IF(AND(ISNUMBER(B5),B5>0,ISNUMBER(U5),U5>=0,ISNUMBER(O5),O5>=0),1,0) -> 1 | AB5: =IF(AA5=1,U5+O5,0) -> 8014 | AC5: =IF(AA5=1,100*AB5/B5,"") -> 0.92178302 | AD5: =IF(AND(AND(ISNUMBER(B5),B5=OriginalFinancials!B5),AND(ISNUMBER(U5),U5=OriginalFinancials!U5),AND(ISNUMBER(O5),O5=OriginalFinancials!O5)),0,1) -> 0 | AE5: =IF(V5=0,"原始0：需核实适用/报告口径","")
A6: 6 | B6: 222692 | C6: 14136 | D6: 199279 | E6: 0.08 | F6: 18834 | G6: 8.457421 | H6: 14136_20220331 | I6: 1.1501745 | J6: 12518 | K6: 11422 | L6: 121199 | M6: 119805 | N6: 96809 | O6: 174 | P6: WELLS RIVER SAVINGS BANK | Q6: 0.67079761 | R6: 3.42237 | S6: 7 | T6: 803 | U6: 639 | V6: 17.27622 | W6: 20220331 | X6: 0.19954922 | Y6: 2.14 | Z6: VT | AA6: =IF(AND(ISNUMBER(B6),B6>0,ISNUMBER(U6),U6>=0,ISNUMBER(O6),O6>=0),1,0) -> 1 | AB6: =IF(AA6=1,U6+O6,0) -> 813 | AC6: =IF(AA6=1,100*AB6/B6,"") -> 0.36507822 | AD6: =IF(AND(AND(ISNUMBER(B6),B6=OriginalFinancials!B6),AND(ISNUMBER(U6),U6=OriginalFinancials!U6),AND(ISNUMBER(O6),O6=OriginalFinancials!O6)),0,1) -> 0 | AE6: =IF(V6=0,"原始0：需核实适用/报告口径","")
A7: 7 | B7: 1414510 | C7: 14140 | D7: 1199427 | E7: 0 | F7: 123854 | G7: 8.755965 | H7: 14140_20220331 | I7: 1.1077738 | J7: 82518 | K7: 1318 | L7: 957867 | M7: 947256 | N7: 866005 | O7: 5589 | P7: NORTHFIELD SAVINGS BANK | Q7: 0.58348393 | R7: 2.9698131 | S7: 9 | T7: 785 | U7: 0 | V7: 0 | W7: 20220331 | X7: 0.66212632 | Y7: 7.07 | Z7: VT | AA7: =IF(AND(ISNUMBER(B7),B7>0,ISNUMBER(U7),U7>=0,ISNUMBER(O7),O7>=0),1,0) -> 1 | AB7: =IF(AA7=1,U7+O7,0) -> 5589 | AC7: =IF(AA7=1,100*AB7/B7,"") -> 0.39511916 | AD7: =IF(AND(AND(ISNUMBER(B7),B7=OriginalFinancials!B7),AND(ISNUMBER(U7),U7=OriginalFinancials!U7),AND(ISNUMBER(O7),O7=OriginalFinancials!O7)),0,1) -> 0 | AE7: =IF(V7=0,"原始0：需核实适用/报告口径","") -> 原始0：需核实适用/报告口径
A8: 8 | B8: 1232701 | C8: 14158 | D8: 1137254 | E8: 0 | F8: 85105 | G8: 6.9039451 | H8: 14158_20220331 | I8: 1.0031734 | J8: 44549 | K8: 2157 | L8: 830963 | M8: 822627 | N8: 698008 | O8: 4405 | P8: UNION BANK | Q8: 0.55766623 | R8: 3.1853735 | S8: 0 | T8: 1620 | U8: 229 | V8: 14.788126 | W8: 20220331 | X8: 0.88329132 | Y8: 11.64 | Z8: VT | AA8: =IF(AND(ISNUMBER(B8),B8>0,ISNUMBER(U8),U8>=0,ISNUMBER(O8),O8>=0),1,0) -> 1 | AB8: =IF(AA8=1,U8+O8,0) -> 4634 | AC8: =IF(AA8=1,100*AB8/B8,"") -> 0.37592247 | AD8: =IF(AND(AND(ISNUMBER(B8),B8=OriginalFinancials!B8),AND(ISNUMBER(U8),U8=OriginalFinancials!U8),AND(ISNUMBER(O8),O8=OriginalFinancials!O8)),0,1) -> 0 | AE8: =IF(V8=0,"原始0：需核实适用/报告口径","")
A9: 9 | B9: 384095 | C9: 14168 | D9: 345364 | E9: 0 | F9: 34244 | G9: 8.9155027 | H9: 14168_20220331 | I9: 1.5327875 | J9: 9537 | K9: 8111 | L9: 191155 | M9: 188225 | N9: 161619 | O9: 1188 | P9: PEOPLES TRUST COMPANY OF ST. ALBANS | Q9: 0.62148518 | R9: 2.4184591 | S9: 34 | T9: 187 | U9: 0 | V9: 19.824643 | W9: 20220331 | X9: 0.13578832 | Y9: 1.45 | Z9: VT | AA9: =IF(AND(ISNUMBER(B9),B9>0,ISNUMBER(U9),U9>=0,ISNUMBER(O9),O9>=0),1,0) -> 1 | AB9: =IF(AA9=1,U9+O9,0) -> 1188 | AC9: =IF(AA9=1,100*AB9/B9,"") -> 0.30929848 | AD9: =IF(AND(AND(ISNUMBER(B9),B9=OriginalFinancials!B9),AND(ISNUMBER(U9),U9=OriginalFinancials!U9),AND(ISNUMBER(O9),O9=OriginalFinancials!O9)),0,1) -> 0 | AE9: =IF(V9=0,"原始0：需核实适用/报告口径","")
A10: 10 | B10: 1221074 | C10: 14240 | D10: 1020645 | E10: 0 | F10: 102113 | G10: 8.3625562 | H10: 14240_20220331 | I10: 1.1483381 | J10: 29648 | K10: 17990 | L10: 824670 | M10: 815200 | N10: 705835 | O10: 2204 | P10: NORTHWAY BANK | Q10: 0.26725842 | R10: 2.8194207 | S10: -4 | T10: 1936 | U10: 0 | V10: 15.106992 | W10: 20220331 | X10: 0.069811881 | Y10: 0.79 | Z10: NH | AA10: =IF(AND(ISNUMBER(B10),B10>0,ISNUMBER(U10),U10>=0,ISNUMBER(O10),O10>=0),1,0) -> 1 | AB10: =IF(AA10=1,U10+O10,0) -> 2204 | AC10: =IF(AA10=1,100*AB10/B10,"") -> 0.18049684 | AD10: =IF(AND(AND(ISNUMBER(B10),B10=OriginalFinancials!B10),AND(ISNUMBER(U10),U10=OriginalFinancials!U10),AND(ISNUMBER(O10),O10=OriginalFinancials!O10)),0,1) -> 0 | AE10: =IF(V10=0,"原始0：需核实适用/报告口径","")
A11: 11 | B11: 836644 | C11: 17115 | D11: 738943 | E11: -0.08 | F11: 83239 | G11: 9.949154 | H11: 17115_20220331 | I11: 1.167132 | J11: 43003 | K11: 3606 | L11: 656481 | M11: 648819 | N11: 608827 | O11: 164 | P11: PARTNERS BANK OF NEW ENGLAND | Q11: 0.024981683 | R11: 3.5126362 | S11: 240 | T11: 62 | U11: 0 | V11: 15.606469 | W11: 20220331 | X11: 1.1149693 | Y11: 11.05 | Z11: ME | AA11: =IF(AND(ISNUMBER(B11),B11>0,ISNUMBER(U11),U11>=0,ISNUMBER(O11),O11>=0),1,0) -> 1 | AB11: =IF(AA11=1,U11+O11,0) -> 164 | AC11: =IF(AA11=1,100*AB11/B11,"") -> 0.019602125 | AD11: =IF(AND(AND(ISNUMBER(B11),B11=OriginalFinancials!B11),AND(ISNUMBER(U11),U11=OriginalFinancials!U11),AND(ISNUMBER(O11),O11=OriginalFinancials!O11)),0,1) -> 0 | AE11: =IF(V11=0,"原始0：需核实适用/报告口径","")
A12: 12 | B12: 1291920 | C12: 17180 | D12: 1121172 | E12: 0.06 | F12: 126979 | G12: 9.8287046 | H12: 17180_20220331 | I12: 0.98616206 | J12: 44797 | K12: 141431 | L12: 1143017 | M12: 1131745 | N12: 937482 | O12: 5753 | P12: MEREDITH VILLAGE SAVINGS BANK | Q12: 0.5033171 | R12: 3.5699932 | S12: 36 | T12: 1540 | U12: 0 | V12: 16.056943 | W12: 20220331 | X12: 0.80278929 | Y12: 8.11 | Z12: NH | AA12: =IF(AND(ISNUMBER(B12),B12>0,ISNUMBER(U12),U12>=0,ISNUMBER(O12),O12>=0),1,0) -> 1 | AB12: =IF(AA12=1,U12+O12,0) -> 5753 | AC12: =IF(AA12=1,100*AB12/B12,"") -> 0.44530621 | AD12: =IF(AND(AND(ISNUMBER(B12),B12=OriginalFinancials!B12),AND(ISNUMBER(U12),U12=OriginalFinancials!U12),AND(ISNUMBER(O12),O12=OriginalFinancials!O12)),0,1) -> 0 | AE12: =IF(V12=0,"原始0：需核实适用/报告口径","")
A13: 13 | B13: 352255 | C13: 17443 | D13: 302135 | E13: 0.06 | F13: 42822 | G13: 12.156534 | H13: 17443_20220331 | I13: 0.85841907 | J13: 0 | K13: 1909 | L13: 188952 | M13: 187330 | N13: 186037 | O13: 842 | P13: PISCATAQUA SAVINGS BANK | Q13: 0.44561582 | R13: 2.0122179 | S13: 0 | T13: 2524 | U13: 0 | V13: 0 | W13: 20220331 | X13: 0.61925341 | Y13: 4.79 | Z13: NH | AA13: =IF(AND(ISNUMBER(B13),B13>0,ISNUMBER(U13),U13>=0,ISNUMBER(O13),O13>=0),1,0) -> 1 | AB13: =IF(AA13=1,U13+O13,0) -> 842 | AC13: =IF(AA13=1,100*AB13/B13,"") -> 0.23903138 | AD13: =IF(AND(AND(ISNUMBER(B13),B13=OriginalFinancials!B13),AND(ISNUMBER(U13),U13=OriginalFinancials!U13),AND(ISNUMBER(O13),O13=OriginalFinancials!O13)),0,1) -> 0 | AE13: =IF(V13=0,"原始0：需核实适用/报告口径","") -> 原始0：需核实适用/报告口径
... A747: 747 | B747: 87770 | C747: 6280 | D747: 77256 | E747: 0.09 | F747: 9949 | G747: 11.335308 | H747: 6280_20250630 | I747: 1.2995896 | J747: 3899 | K747: 1311 | L747: 73100 | M747: 72150 | N747: 64947 | O747: 1455 | P747: THE FIRST NATIONAL BANK OF ORWELL | Q747: 1.9904241 | R747: 4.5394341 | S747: 0 | T747: 592 | U747: 0 | V747: 0 | W747: 20250630 | X747: 1.3665403 | Y747: 12.13 | Z747: VT | AA747: =IF(AND(ISNUMBER(B747),B747>0,ISNUMBER(U747),U747>=0,ISNUMBER(O747),O747>=0),1,0) -> 1 | AB747: =IF(AA747=1,U747+O747,0) -> 1455 | AC747: =IF(AA747=1,100*AB747/B747,"") -> 1.6577418 | AD747: =IF(AND(AND(ISNUMBER(B747),B747=OriginalFinancials!B747),AND(ISNUMBER(U747),U747=OriginalFinancials!U747),AND(ISNUMBER(O747),O747=OriginalFinancials!O747)),0,1) -> 0 | AE747: =IF(V747=0,"原始0：需核实适用/报告口径","") -> 原始0：需核实适用/报告口径

Sheet BankQuarter
A1: source_row | B1: ASSET | C1: CERT | D1: DEP | E1: ELNATRY | F1: EQ | G1: EQV | H1: ID | I1: LNATRESR | J1: LNCI | K1: LNCON | L1: LNLSGR | M1: LNLSNET | N1: LNRE | O1: NAASSET | P1: NAMEFULL | Q1: NCLNLSR | R1: NIMY | S1: NTLNLS | T1: P3ASSET | U1: P9ASSET | V1: RBCRWAJ | W1: REPDTE | X1: ROA | Y1: ROE | Z1: STALP | AA1: proxy_valid | AB1: proxy_numerator | AC1: proxy_pct | AD1: RE_loan_share_pct | AE1: equity_asset_pct | AF1: capital_zero_note
A2: =IF(ISBLANK(RawFinancials!A2),"",RawFinancials!A2) -> 2 | B2: =IF(ISBLANK(RawFinancials!B2),"",RawFinancials!B2) -> 3688993 | C2: =IF(ISBLANK(RawFinancials!C2),"",RawFinancials!C2) -> 11971 | D2: =IF(ISBLANK(RawFinancials!D2),"",RawFinancials!D2) -> 3055632 | E2: =IF(ISBLANK(RawFinancials!E2),"",RawFinancials!E2) -> 0.08 | F2: =IF(ISBLANK(RawFinancials!F2),"",RawFinancials!F2) -> 461681 | G2: =IF(ISBLANK(RawFinancials!G2),"",RawFinancials!G2) -> 12.515096 | H2: =IF(ISBLANK(RawFinancials!H2),"",RawFinancials!H2) -> 11971_20220331 | ... Z2: =IF(ISBLANK(RawFinancials!Z2),"",RawFinancials!Z2) -> ME | AA2: =RawFinancials!AA2 -> 1 | AB2: =RawFinancials!AB2 -> 10056 | AC2: =RawFinancials!AC2 -> 0.27259472 | AD2: =IF(L2>0,100*N2/L2,"") -> 87.193263 | AE2: =IF(B2>0,100*F2/B2,"") -> 12.515096 | AF2: =RawFinancials!AE2
A3: =IF(ISBLANK(RawFinancials!A3),"",RawFinancials!A3) -> 3 | B3: =IF(ISBLANK(RawFinancials!B3),"",RawFinancials!B3) -> 964163 | C3: =IF(ISBLANK(RawFinancials!C3),"",RawFinancials!C3) -> 12874 | D3: =IF(ISBLANK(RawFinancials!D3),"",RawFinancials!D3) -> 854194 | E3: =IF(ISBLANK(RawFinancials!E3),"",RawFinancials!E3) -> 0 | F3: =IF(ISBLANK(RawFinancials!F3),"",RawFinancials!F3) -> 97916 | G3: =IF(ISBLANK(RawFinancials!G3),"",RawFinancials!G3) -> 10.155544 | H3: =IF(ISBLANK(RawFinancials!H3),"",RawFinancials!H3) -> 12874_20220331 | ... Z3: =IF(ISBLANK(RawFinancials!Z3),"",RawFinancials!Z3) -> ME | AA3: =RawFinancials!AA3 -> 1 | AB3: =RawFinancials!AB3 -> 1069 | AC3: =RawFinancials!AC3 -> 0.11087337 | AD3: =IF(L3>0,100*N3/L3,"") -> 78.809015 | AE3: =IF(B3>0,100*F3/B3,"") -> 10.155544 | AF3: =RawFinancials!AE3
A4: =IF(ISBLANK(RawFinancials!A4),"",RawFinancials!A4) -> 4 | B4: =IF(ISBLANK(RawFinancials!B4),"",RawFinancials!B4) -> 1784835 | C4: =IF(ISBLANK(RawFinancials!C4),"",RawFinancials!C4) -> 13063 | D4: =IF(ISBLANK(RawFinancials!D4),"",RawFinancials!D4) -> 1619076 | E4: =IF(ISBLANK(RawFinancials!E4),"",RawFinancials!E4) -> 0 | F4: =IF(ISBLANK(RawFinancials!F4),"",RawFinancials!F4) -> 148181 | G4: =IF(ISBLANK(RawFinancials!G4),"",RawFinancials!G4) -> 8.302224 | H4: =IF(ISBLANK(RawFinancials!H4),"",RawFinancials!H4) -> 13063_20220331 | ... Z4: =IF(ISBLANK(RawFinancials!Z4),"",RawFinancials!Z4) -> ME | AA4: =RawFinancials!AA4 -> 1 | AB4: =RawFinancials!AB4 -> 1604 | AC4: =RawFinancials!AC4 -> 0.089868251 | AD4: =IF(L4>0,100*N4/L4,"") -> 94.884538 | AE4: =IF(B4>0,100*F4/B4,"") -> 8.302224 | AF4: =RawFinancials!AE4 -> 原始0：需核实适用/报告口径
A5: =IF(ISBLANK(RawFinancials!A5),"",RawFinancials!A5) -> 5 | B5: =IF(ISBLANK(RawFinancials!B5),"",RawFinancials!B5) -> 869402 | C5: =IF(ISBLANK(RawFinancials!C5),"",RawFinancials!C5) -> 14134 | D5: =IF(ISBLANK(RawFinancials!D5),"",RawFinancials!D5) -> 737795 | E5: =IF(ISBLANK(RawFinancials!E5),"",RawFinancials!E5) -> 0.1 | F5: =IF(ISBLANK(RawFinancials!F5),"",RawFinancials!F5) -> 101808 | G5: =IF(ISBLANK(RawFinancials!G5),"",RawFinancials!G5) -> 11.710118 | H5: =IF(ISBLANK(RawFinancials!H5),"",RawFinancials!H5) -> 14134_20220331 | ... Z5: =IF(ISBLANK(RawFinancials!Z5),"",RawFinancials!Z5) -> VT | AA5: =RawFinancials!AA5 -> 1 | AB5: =RawFinancials!AB5 -> 8014 | AC5: =RawFinancials!AC5 -> 0.92178302 | AD5: =IF(L5>0,100*N5/L5,"") -> 86.559253 | AE5: =IF(B5>0,100*F5/B5,"") -> 11.710118 | AF5: =RawFinancials!AE5
A6: =IF(ISBLANK(RawFinancials!A6),"",RawFinancials!A6) -> 6 | B6: =IF(ISBLANK(RawFinancials!B6),"",RawFinancials!B6) -> 222692 | C6: =IF(ISBLANK(RawFinancials!C6),"",RawFinancials!C6) -> 14136 | D6: =IF(ISBLANK(RawFinancials!D6),"",RawFinancials!D6) -> 199279 | E6: =IF(ISBLANK(RawFinancials!E6),"",RawFinancials!E6) -> 0.08 | F6: =IF(ISBLANK(RawFinancials!F6),"",RawFinancials!F6) -> 18834 | G6: =IF(ISBLANK(RawFinancials!G6),"",RawFinancials!G6) -> 8.457421 | H6: =IF(ISBLANK(RawFinancials!H6),"",RawFinancials!H6) -> 14136_20220331 | ... Z6: =IF(ISBLANK(RawFinancials!Z6),"",RawFinancials!Z6) -> VT | AA6: =RawFinancials!AA6 -> 1 | AB6: =RawFinancials!AB6 -> 813 | AC6: =RawFinancials!AC6 -> 0.36507822 | AD6: =IF(L6>0,100*N6/L6,"") -> 79.876072 | AE6: =IF(B6>0,100*F6/B6,"") -> 8.457421 | AF6: =RawFinancials!AE6
A7: =IF(ISBLANK(RawFinancials!A7),"",RawFinancials!A7) -> 7 | B7: =IF(ISBLANK(RawFinancials!B7),"",RawFinancials!B7) -> 1414510 | C7: =IF(ISBLANK(RawFinancials!C7),"",RawFinancials!C7) -> 14140 | D7: =IF(ISBLANK(RawFinancials!D7),"",RawFinancials!D7) -> 1199427 | E7: =IF(ISBLANK(RawFinancials!E7),"",RawFinancials!E7) -> 0 | F7: =IF(ISBLANK(RawFinancials!F7),"",RawFinancials!F7) -> 123854 | G7: =IF(ISBLANK(RawFinancials!G7),"",RawFinancials!G7) -> 8.755965 | H7: =IF(ISBLANK(RawFinancials!H7),"",RawFinancials!H7) -> 14140_20220331 | ... Z7: =IF(ISBLANK(RawFinancials!Z7),"",RawFinancials!Z7) -> VT | AA7: =RawFinancials!AA7 -> 1 | AB7: =RawFinancials!AB7 -> 5589 | AC7: =RawFinancials!AC7 -> 0.39511916 | AD7: =IF(L7>0,100*N7/L7,"") -> 90.409733 | AE7: =IF(B7>0,100*F7/B7,"") -> 8.755965 | AF7: =RawFinancials!AE7 -> 原始0：需核实适用/报告口径
A8: =IF(ISBLANK(RawFinancials!A8),"",RawFinancials!A8) -> 8 | B8: =IF(ISBLANK(RawFinancials!B8),"",RawFinancials!B8) -> 1232701 | C8: =IF(ISBLANK(RawFinancials!C8),"",RawFinancials!C8) -> 14158 | D8: =IF(ISBLANK(RawFinancials!D8),"",RawFinancials!D8) -> 1137254 | E8: =IF(ISBLANK(RawFinancials!E8),"",RawFinancials!E8) -> 0 | F8: =IF(ISBLANK(RawFinancials!F8),"",RawFinancials!F8) -> 85105 | G8: =IF(ISBLANK(RawFinancials!G8),"",RawFinancials!G8) -> 6.9039451 | H8: =IF(ISBLANK(RawFinancials!H8),"",RawFinancials!H8) -> 14158_20220331 | ... Z8: =IF(ISBLANK(RawFinancials!Z8),"",RawFinancials!Z8) -> VT | AA8: =RawFinancials!AA8 -> 1 | AB8: =RawFinancials!AB8 -> 4634 | AC8: =RawFinancials!AC8 -> 0.37592247 | AD8: =IF(L8>0,100*N8/L8,"") -> 83.999889 | AE8: =IF(B8>0,100*F8/B8,"") -> 6.9039451 | AF8: =RawFinancials!AE8
A9: =IF(ISBLANK(RawFinancials!A9),"",RawFinancials!A9) -> 9 | B9: =IF(ISBLANK(RawFinancials!B9),"",RawFinancials!B9) -> 384095 | C9: =IF(ISBLANK(RawFinancials!C9),"",RawFinancials!C9) -> 14168 | D9: =IF(ISBLANK(RawFinancials!D9),"",RawFinancials!D9) -> 345364 | E9: =IF(ISBLANK(RawFinancials!E9),"",RawFinancials!E9) -> 0 | F9: =IF(ISBLANK(RawFinancials!F9),"",RawFinancials!F9) -> 34244 | G9: =IF(ISBLANK(RawFinancials!G9),"",RawFinancials!G9) -> 8.9155027 | H9: =IF(ISBLANK(RawFinancials!H9),"",RawFinancials!H9) -> 14168_20220331 | ... Z9: =IF(ISBLANK(RawFinancials!Z9),"",RawFinancials!Z9) -> VT | AA9: =RawFinancials!AA9 -> 1 | AB9: =RawFinancials!AB9 -> 1188 | AC9: =RawFinancials!AC9 -> 0.30929848 | AD9: =IF(L9>0,100*N9/L9,"") -> 84.548665 | AE9: =IF(B9>0,100*F9/B9,"") -> 8.9155027 | AF9: =RawFinancials!AE9
A10: =IF(ISBLANK(RawFinancials!A10),"",RawFinancials!A10) -> 10 | B10: =IF(ISBLANK(RawFinancials!B10),"",RawFinancials!B10) -> 1221074 | C10: =IF(ISBLANK(RawFinancials!C10),"",RawFinancials!C10) -> 14240 | D10: =IF(ISBLANK(RawFinancials!D10),"",RawFinancials!D10) -> 1020645 | E10: =IF(ISBLANK(RawFinancials!E10),"",RawFinancials!E10) -> 0 | F10: =IF(ISBLANK(RawFinancials!F10),"",RawFinancials!F10) -> 102113 | G10: =IF(ISBLANK(RawFinancials!G10),"",RawFinancials!G10) -> 8.3625562 | H10: =IF(ISBLANK(RawFinancials!H10),"",RawFinancials!H10) -> 14240_20220331 | ... Z10: =IF(ISBLANK(RawFinancials!Z10),"",RawFinancials!Z10) -> NH | AA10: =RawFinancials!AA10 -> 1 | AB10: =RawFinancials!AB10 -> 2204 | AC10: =RawFinancials!AC10 -> 0.18049684 | AD10: =IF(L10>0,100*N10/L10,"") -> 85.589994 | AE10: =IF(B10>0,100*F10/B10,"") -> 8.3625562 | AF10: =RawFinancials!AE10
A11: =IF(ISBLANK(RawFinancials!A11),"",RawFinancials!A11) -> 11 | B11: =IF(ISBLANK(RawFinancials!B11),"",RawFinancials!B11) -> 836644 | C11: =IF(ISBLANK(RawFinancials!C11),"",RawFinancials!C11) -> 17115 | D11: =IF(ISBLANK(RawFinancials!D11),"",RawFinancials!D11) -> 738943 | E11: =IF(ISBLANK(RawFinancials!E11),"",RawFinancials!E11) -> -0.08 | F11: =IF(ISBLANK(RawFinancials!F11),"",RawFinancials!F11) -> 83239 | G11: =IF(ISBLANK(RawFinancials!G11),"",RawFinancials!G11) -> 9.949154 | H11: =IF(ISBLANK(RawFinancials!H11),"",RawFinancials!H11) -> 17115_20220331 | ... Z11: =IF(ISBLANK(RawFinancials!Z11),"",RawFinancials!Z11) -> ME | AA11: =RawFinancials!AA11 -> 1 | AB11: =RawFinancials!AB11 -> 164 | AC11: =RawFinancials!AC11 -> 0.019602125 | AD11: =IF(L11>0,100*N11/L11,"") -> 92.740993 | AE11: =IF(B11>0,100*F11/B11,"") -> 9.949154 | AF11: =RawFinancials!AE11
A12: =IF(ISBLANK(RawFinancials!A12),"",RawFinancials!A12) -> 12 | B12: =IF(ISBLANK(RawFinancials!B12),"",RawFinancials!B12) -> 1291920 | C12: =IF(ISBLANK(RawFinancials!C12),"",RawFinancials!C12) -> 17180 | D12: =IF(ISBLANK(RawFinancials!D12),"",RawFinancials!D12) -> 1121172 | E12: =IF(ISBLANK(RawFinancials!E12),"",RawFinancials!E12) -> 0.06 | F12: =IF(ISBLANK(RawFinancials!F12),"",RawFinancials!F12) -> 126979 | G12: =IF(ISBLANK(RawFinancials!G12),"",RawFinancials!G12) -> 9.8287046 | H12: =IF(ISBLANK(RawFinancials!H12),"",RawFinancials!H12) -> 17180_20220331 | ... Z12: =IF(ISBLANK(RawFinancials!Z12),"",RawFinancials!Z12) -> NH | AA12: =RawFinancials!AA12 -> 1 | AB12: =RawFinancials!AB12 -> 5753 | AC12: =RawFinancials!AC12 -> 0.44530621 | AD12: =IF(L12>0,100*N12/L12,"") -> 82.018203 | AE12: =IF(B12>0,100*F12/B12,"") -> 9.8287046 | AF12: =RawFinancials!AE12
A13: =IF(ISBLANK(RawFinancials!A13),"",RawFinancials!A13) -> 13 | B13: =IF(ISBLANK(RawFinancials!B13),"",RawFinancials!B13) -> 352255 | C13: =IF(ISBLANK(RawFinancials!C13),"",RawFinancials!C13) -> 17443 | D13: =IF(ISBLANK(RawFinancials!D13),"",RawFinancials!D13) -> 302135 | E13: =IF(ISBLANK(RawFinancials!E13),"",RawFinancials!E13) -> 0.06 | F13: =IF(ISBLANK(RawFinancials!F13),"",RawFinancials!F13) -> 42822 | G13: =IF(ISBLANK(RawFinancials!G13),"",RawFinancials!G13) -> 12.156534 | H13: =IF(ISBLANK(RawFinancials!H13),"",RawFinancials!H13) -> 17443_20220331 | ... Z13: =IF(ISBLANK(RawFinancials!Z13),"",RawFinancials!Z13) -> NH | AA13: =RawFinancials!AA13 -> 1 | AB13: =RawFinancials!AB13 -> 842 | AC13: =RawFinancials!AC13 -> 0.23903138 | AD13: =IF(L13>0,100*N13/L13,"") -> 98.45728 | AE13: =IF(B13>0,100*F13/B13,"") -> 12.156534 | AF13: =RawFinancials!AE13 -> 原始0：需核实适用/报告口径
... A747: =IF(ISBLANK(RawFinancials!A747),"",RawFinancials!A747) -> 747 | B747: =IF(ISBLANK(RawFinancials!B747),"",RawFinancials!B747) -> 87770 | C747: =IF(ISBLANK(RawFinancials!C747),"",RawFinancials!C747) -> 6280 | D747: =IF(ISBLANK(RawFinancials!D747),"",RawFinancials!D747) -> 77256 | E747: =IF(ISBLANK(RawFinancials!E747),"",RawFinancials!E747) -> 0.09 | F747: =IF(ISBLANK(RawFinancials!F747),"",RawFinancials!F747) -> 9949 | G747: =IF(ISBLANK(RawFinancials!G747),"",RawFinancials!G747) -> 11.335308 | H747: =IF(ISBLANK(RawFinancials!H747),"",RawFinancials!H747) -> 6280_20250630 | ... Z747: =IF(ISBLANK(RawFinancials!Z747),"",RawFinancials!Z747) -> VT | AA747: =RawFinancials!AA747 -> 1 | AB747: =RawFinancials!AB747 -> 1455 | AC747: =RawFinancials!AC747 -> 1.6577418 | AD747: =IF(L747>0,100*N747/L747,"") -> 88.846785 | AE747: =IF(B747>0,100*F747/B747,"") -> 11.335308 | AF747: =RawFinancials!AE747 -> 原始0：需核实适用/报告口径

Sheet BankCalc
A1: CERT | B1: start_row | C1: end_row | D1: start_valid | E1: end_valid | F1: start_state | G1: end_state | H1: start_asset | I1: start_num | J1: start_proxy | K1: end_asset | L1: end_num | M1: end_proxy | N1: common | O1: weight | P1: weighted_start | Q1: weighted_end | R1: end_global_rank | S1: state_leader | T1: fill_rank | U1: allocation_order | V1: bank | W1: entering | X1: exiting | Y1: entering_assets | Z1: exiting_assets
A2: 4255 | B2: =SUMIFS(RawFinancials!$A$2:$A$747,RawFinancials!$C$2:$C$747,A2,RawFinancials!$W$2:$W$747,WF_START_PERIOD) -> 527 | C2: =SUMIFS(RawFinancials!$A$2:$A$747,RawFinancials!$C$2:$C$747,A2,RawFinancials!$W$2:$W$747,WF_END_PERIOD) -> 739 | D2: =COUNTIFS(RawFinancials!$C$2:$C$747,A2,RawFinancials!$W$2:$W$747,WF_START_PERIOD,RawFinancials!$AA$2:$AA$747,1) -> 1 | E2: =COUNTIFS(RawFinancials!$C$2:$C$747,A2,RawFinancials!$W$2:$W$747,WF_END_PERIOD,RawFinancials!$AA$2:$AA$747,1) -> 1 | F2: =IF(B2>0,INDEX(RawFinancials!$Z:$Z,B2),"") -> ME | G2: =IF(C2>0,INDEX(RawFinancials!$Z:$Z,C2),"") -> ME | H2: =SUMIFS(RawFinancials!$B$2:$B$747,RawFinancials!$C$2:$C$747,A2,RawFinancials!$W$2:$W$747,WF_START_PERIOD,RawFinancials!$AA$2:$AA$747,1) -> 5709625 | I2: =SUMIFS(RawFinancials!$AB$2:$AB$747,RawFinancials!$C$2:$C$747,A2,RawFinancials!$W$2:$W$747,WF_START_PERIOD,RawFinancials!$AA$2:$AA$747,1) -> 7795 | J2: =IF(D2=1,100*I2/H2,"") -> 0.13652385 | K2: =SUMIFS(RawFinancials!$B$2:$B$747,RawFinancials!$C$2:$C$747,A2,RawFinancials!$W$2:$W$747,WF_END_PERIOD,RawFinancials!$AA$2:$AA$747,1) -> 6902692 | L2: =SUMIFS(RawFinancials!$AB$2:$AB$747,RawFinancials!$C$2:$C$747,A2,RawFinancials!$W$2:$W$747,WF_END_PERIOD,RawFinancials!$AA$2:$AA$747,1) -> 18177 | M2: =IF(E2=1,100*L2/K2,"") -> 0.26333204 | N2: =D2*E2 -> 1 | O2: =IF(N2=1,H2,0) -> 5709625 | P2: =IF(N2=1,H2*J2,0) -> 779500 | Q2: =IF(N2=1,H2*M2,0) -> 1503527.2 | R2: =IF(E2=1,1+COUNTIFS($E$2:$E$55,1,$M$2:$M$55,">"&M2)+COUNTIFS($E$2:$E$55,1,$M$2:$M$55,M2,$A$2:$A$55,"<"&A2),0) -> 27 | S2: =IF(E2=1,IF(COUNTIFS($E$2:$E$55,1,$G$2:$G$55,G2,$M$2:$M$55,">"&M2)+COUNTIFS($E$2:$E$55,1,$G$2:$G$55,G2,$M$2:$M$55,M2,$A$2:$A$55,"<"&A2)=0,1,0),0) -> 0 | T2: =IF(AND(E2=1,S2=0),1+COUNTIFS($E$2:$E$55,1,$S$2:$S$55,0,$R$2:$R$55,"<"&R2),0) -> 24 | U2: =IF(E2=1,IF(S2=1,IF(G2="VT",1,IF(G2="NH",2,3)),3+T2),0) -> 27 | V2: =IF(C2>0,INDEX(RawFinancials!$P:$P,C2),IF(B2>0,INDEX(RawFinancials!$P:$P,B2),"")) -> THE CAMDEN NATIONAL BANK | W2: =E2*(1-D2) -> 0 | X2: =D2*(1-E2) -> 0 | Y2: =W2*K2 -> 0 | Z2: =X2*H2 -> 0
A3: 4256 | B3: =SUMIFS(RawFinancials!$A$2:$A$747,RawFinancials!$C$2:$C$747,A3,RawFinancials!$W$2:$W$747,WF_START_PERIOD) -> 528 | C3: =SUMIFS(RawFinancials!$A$2:$A$747,RawFinancials!$C$2:$C$747,A3,RawFinancials!$W$2:$W$747,WF_END_PERIOD) -> 740 | D3: =COUNTIFS(RawFinancials!$C$2:$C$747,A3,RawFinancials!$W$2:$W$747,WF_START_PERIOD,RawFinancials!$AA$2:$AA$747,1) -> 1 | E3: =COUNTIFS(RawFinancials!$C$2:$C$747,A3,RawFinancials!$W$2:$W$747,WF_END_PERIOD,RawFinancials!$AA$2:$AA$747,1) -> 1 | F3: =IF(B3>0,INDEX(RawFinancials!$Z:$Z,B3),"") -> ME | G3: =IF(C3>0,INDEX(RawFinancials!$Z:$Z,C3),"") -> ME | H3: =SUMIFS(RawFinancials!$B$2:$B$747,RawFinancials!$C$2:$C$747,A3,RawFinancials!$W$2:$W$747,WF_START_PERIOD,RawFinancials!$AA$2:$AA$747,1) -> 3049270 | I3: =SUMIFS(RawFinancials!$AB$2:$AB$747,RawFinancials!$C$2:$C$747,A3,RawFinancials!$W$2:$W$747,WF_START_PERIOD,RawFinancials!$AA$2:$AA$747,1) -> 2651 | J3: =IF(D3=1,100*I3/H3,"") -> 0.086938841 | K3: =SUMIFS(RawFinancials!$B$2:$B$747,RawFinancials!$C$2:$C$747,A3,RawFinancials!$W$2:$W$747,WF_END_PERIOD,RawFinancials!$AA$2:$AA$747,1) -> 3164056 | L3: =SUMIFS(RawFinancials!$AB$2:$AB$747,RawFinancials!$C$2:$C$747,A3,RawFinancials!$W$2:$W$747,WF_END_PERIOD,RawFinancials!$AA$2:$AA$747,1) -> 6496 | M3: =IF(E3=1,100*L3/K3,"") -> 0.2053061 | N3: =D3*E3 -> 1 | O3: =IF(N3=1,H3,0) -> 3049270 | P3: =IF(N3=1,H3*J3,0) -> 265100 | Q3: =IF(N3=1,H3*M3,0) -> 626033.73 | R3: =IF(E3=1,1+COUNTIFS($E$2:$E$55,1,$M$2:$M$55,">"&M3)+COUNTIFS($E$2:$E$55,1,$M$2:$M$55,M3,$A$2:$A$55,"<"&A3),0) -> 31 | S3: =IF(E3=1,IF(COUNTIFS($E$2:$E$55,1,$G$2:$G$55,G3,$M$2:$M$55,">"&M3)+COUNTIFS($E$2:$E$55,1,$G$2:$G$55,G3,$M$2:$M$55,M3,$A$2:$A$55,"<"&A3)=0,1,0),0) -> 0 | T3: =IF(AND(E3=1,S3=0),1+COUNTIFS($E$2:$E$55,1,$S$2:$S$55,0,$R$2:$R$55,"<"&R3),0) -> 28 | U3: =IF(E3=1,IF(S3=1,IF(G3="VT",1,IF(G3="NH",2,3)),3+T3),0) -> 31 | V3: =IF(C3>0,INDEX(RawFinancials!$P:$P,C3),IF(B3>0,INDEX(RawFinancials!$P:$P,B3),"")) -> FIRST NATIONAL BANK | W3: =E3*(1-D3) -> 0 | X3: =D3*(1-E3) -> 0 | Y3: =W3*K3 -> 0 | Z3: =X3*H3 -> 0
A4: 6271 | B4: =SUMIFS(RawFinancials!$A$2:$A$747,RawFinancials!$C$2:$C$747,A4,RawFinancials!$W$2:$W$747,WF_START_PERIOD) -> 533 | C4: =SUMIFS(RawFinancials!$A$2:$A$747,RawFinancials!$C$2:$C$747,A4,RawFinancials!$W$2:$W$747,WF_END_PERIOD) -> 745 | D4: =COUNTIFS(RawFinancials!$C$2:$C$747,A4,RawFinancials!$W$2:$W$747,WF_START_PERIOD,RawFinancials!$AA$2:$AA$747,1) -> 1 | E4: =COUNTIFS(RawFinancials!$C$2:$C$747,A4,RawFinancials!$W$2:$W$747,WF_END_PERIOD,RawFinancials!$AA$2:$AA$747,1) -> 1 | F4: =IF(B4>0,INDEX(RawFinancials!$Z:$Z,B4),"") -> VT | G4: =IF(C4>0,INDEX(RawFinancials!$Z:$Z,C4),"") -> VT | H4: =SUMIFS(RawFinancials!$B$2:$B$747,RawFinancials!$C$2:$C$747,A4,RawFinancials!$W$2:$W$747,WF_START_PERIOD,RawFinancials!$AA$2:$AA$747,1) -> 1099892 | I4: =SUMIFS(RawFinancials!$AB$2:$AB$747,RawFinancials!$C$2:$C$747,A4,RawFinancials!$W$2:$W$747,WF_START_PERIOD,RawFinancials!$AA$2:$AA$747,1) -> 6486 | J4: =IF(D4=1,100*I4/H4,"") -> 0.58969426 | K4: =SUMIFS(RawFinancials!$B$2:$B$747,RawFinancials!$C$2:$C$747,A4,RawFinancials!$W$2:$W$747,WF_END_PERIOD,RawFinancials!$AA$2:$AA$747,1) -> 1166044 | L4: =SUMIFS(RawFinancials!$AB$2:$AB$747,RawFinancials!$C$2:$C$747,A4,RawFinancials!$W$2:$W$747,WF_END_PERIOD,RawFinancials!$AA$2:$AA$747,1) -> 9231 | M4: =IF(E4=1,100*L4/K4,"") -> 0.79165109 | N4: =D4*E4 -> 1 | O4: =IF(N4=1,H4,0) -> 1099892 | P4: =IF(N4=1,H4*J4,0) -> 648600 | Q4: =IF(N4=1,H4*M4,0) -> 870730.7 | R4: =IF(E4=1,1+COUNTIFS($E$2:$E$55,1,$M$2:$M$55,">"&M4)+COUNTIFS($E$2:$E$55,1,$M$2:$M$55,M4,$A$2:$A$55,"<"&A4),0) -> 9 | S4: =IF(E4=1,IF(COUNTIFS($E$2:$E$55,1,$G$2:$G$55,G4,$M$2:$M$55,">"&M4)+COUNTIFS($E$2:$E$55,1,$G$2:$G$55,G4,$M$2:$M$55,M4,$A$2:$A$55,"<"&A4)=0,1,0),0) -> 0 | T4: =IF(AND(E4=1,S4=0),1+COUNTIFS($E$2:$E$55,1,$S$2:$S$55,0,$R$2:$R$55,"<"&R4),0) -> 6 | U4: =IF(E4=1,IF(S4=1,IF(G4="VT",1,IF(G4="NH",2,3)),3+T4),0) -> 9 | V4: =IF(C4>0,INDEX(RawFinancials!$P:$P,C4),IF(B4>0,INDEX(RawFinancials!$P:$P,B4),"")) -> COMMUNITY NATIONAL BANK | W4: =E4*(1-D4) -> 0 | X4: =D4*(1-E4) -> 0 | Y4: =W4*K4 -> 0 | Z4: =X4*H4 -> 0
A5: 6275 | B5: =SUMIFS(RawFinancials!$A$2:$A$747,RawFinancials!$C$2:$C$747,A5,RawFinancials!$W$2:$W$747,WF_START_PERIOD) -> 534 | C5: =SUMIFS(RawFinancials!$A$2:$A$747,RawFinancials!$C$2:$C$747,A5,RawFinancials!$W$2:$W$747,WF_END_PERIOD) -> 746 | D5: =COUNTIFS(RawFinancials!$C$2:$C$747,A5,RawFinancials!$W$2:$W$747,WF_START_PERIOD,RawFinancials!$AA$2:$AA$747,1) -> 1 | E5: =COUNTIFS(RawFinancials!$C$2:$C$747,A5,RawFinancials!$W$2:$W$747,WF_END_PERIOD,RawFinancials!$AA$2:$AA$747,1) -> 1 | F5: =IF(B5>0,INDEX(RawFinancials!$Z:$Z,B5),"") -> VT | G5: =IF(C5>0,INDEX(RawFinancials!$Z:$Z,C5),"") -> VT | H5: =SUMIFS(RawFinancials!$B$2:$B$747,RawFinancials!$C$2:$C$747,A5,RawFinancials!$W$2:$W$747,WF_START_PERIOD,RawFinancials!$AA$2:$AA$747,1) -> 555322 | I5: =SUMIFS(RawFinancials!$AB$2:$AB$747,RawFinancials!$C$2:$C$747,A5,RawFinancials!$W$2:$W$747,WF_START_PERIOD,RawFinancials!$AA$2:$AA$747,1) -> 1132 | J5: =IF(D5=1,100*I5/H5,"") -> 0.2038457 | K5: =SUMIFS(RawFinancials!$B$2:$B$747,RawFinancials!$C$2:$C$747,A5,RawFinancials!$W$2:$W$747,WF_END_PERIOD,RawFinancials!$AA$2:$AA$747,1) -> 552605 | L5: =SUMIFS(RawFinancials!$AB$2:$AB$747,RawFinancials!$C$2:$C$747,A5,RawFinancials!$W$2:$W$747,WF_END_PERIOD,RawFinancials!$AA$2:$AA$747,1) -> 652 | M5: =IF(E5=1,100*L5/K5,"") -> 0.11798663 | N5: =D5*E5 -> 1 | O5: =IF(N5=1,H5,0) -> 555322 | P5: =IF(N5=1,H5*J5,0) -> 113200 | Q5: =IF(N5=1,H5*M5,0) -> 65520.57 | R5: =IF(E5=1,1+COUNTIFS($E$2:$E$55,1,$M$2:$M$55,">"&M5)+COUNTIFS($E$2:$E$55,1,$M$2:$M$55,M5,$A$2:$A$55,"<"&A5),0) -> 37 | S5: =IF(E5=1,IF(COUNTIFS($E$2:$E$55,1,$G$2:$G$55,G5,$M$2:$M$55,">"&M5)+COUNTIFS($E$2:$E$55,1,$G$2:$G$55,G5,$M$2:$M$55,M5,$A$2:$A$55,"<"&A5)=0,1,0),0) -> 0 | T5: =IF(AND(E5=1,S5=0),1+COUNTIFS($E$2:$E$55,1,$S$2:$S$55,0,$R$2:$R$55,"<"&R5),0) -> 34 | U5: =IF(E5=1,IF(S5=1,IF(G5="VT",1,IF(G5="NH",2,3)),3+T5),0) -> 37 | V5: =IF(C5>0,INDEX(RawFinancials!$P:$P,C5),IF(B5>0,INDEX(RawFinancials!$P:$P,B5),"")) -> THE NATIONAL BANK OF MIDDLEBURY | W5: =E5*(1-D5) -> 0 | X5: =D5*(1-E5) -> 0 | Y5: =W5*K5 -> 0 | Z5: =X5*H5 -> 0
A6: 6280 | B6: =SUMIFS(RawFinancials!$A$2:$A$747,RawFinancials!$C$2:$C$747,A6,RawFinancials!$W$2:$W$747,WF_START_PERIOD) -> 535 | C6: =SUMIFS(RawFinancials!$A$2:$A$747,RawFinancials!$C$2:$C$747,A6,RawFinancials!$W$2:$W$747,WF_END_PERIOD) -> 747 | D6: =COUNTIFS(RawFinancials!$C$2:$C$747,A6,RawFinancials!$W$2:$W$747,WF_START_PERIOD,RawFinancials!$AA$2:$AA$747,1) -> 1 | E6: =COUNTIFS(RawFinancials!$C$2:$C$747,A6,RawFinancials!$W$2:$W$747,WF_END_PERIOD,RawFinancials!$AA$2:$AA$747,1) -> 1 | F6: =IF(B6>0,INDEX(RawFinancials!$Z:$Z,B6),"") -> VT | G6: =IF(C6>0,INDEX(RawFinancials!$Z:$Z,C6),"") -> VT | H6: =SUMIFS(RawFinancials!$B$2:$B$747,RawFinancials!$C$2:$C$747,A6,RawFinancials!$W$2:$W$747,WF_START_PERIOD,RawFinancials!$AA$2:$AA$747,1) -> 81265 | I6: =SUMIFS(RawFinancials!$AB$2:$AB$747,RawFinancials!$C$2:$C$747,A6,RawFinancials!$W$2:$W$747,WF_START_PERIOD,RawFinancials!$AA$2:$AA$747,1) -> 1206 | J6: =IF(D6=1,100*I6/H6,"") -> 1.4840337 | K6: =SUMIFS(RawFinancials!$B$2:$B$747,RawFinancials!$C$2:$C$747,A6,RawFinancials!$W$2:$W$747,WF_END_PERIOD,RawFinancials!$AA$2:$AA$747,1) -> 87770 | L6: =SUMIFS(RawFinancials!$AB$2:$AB$747,RawFinancials!$C$2:$C$747,A6,RawFinancials!$W$2:$W$747,WF_END_PERIOD,RawFinancials!$AA$2:$AA$747,1) -> 1455 | M6: =IF(E6=1,100*L6/K6,"") -> 1.6577418 | N6: =D6*E6 -> 1 | O6: =IF(N6=1,H6,0) -> 81265 | P6: =IF(N6=1,H6*J6,0) -> 120600 | Q6: =IF(N6=1,H6*M6,0) -> 134716.39 | R6: =IF(E6=1,1+COUNTIFS($E$2:$E$55,1,$M$2:$M$55,">"&M6)+COUNTIFS($E$2:$E$55,1,$M$2:$M$55,M6,$A$2:$A$55,"<"&A6),0) -> 4 | S6: =IF(E6=1,IF(COUNTIFS($E$2:$E$55,1,$G$2:$G$55,G6,$M$2:$M$55,">"&M6)+COUNTIFS($E$2:$E$55,1,$G$2:$G$55,G6,$M$2:$M$55,M6,$A$2:$A$55,"<"&A6)=0,1,0),0) -> 1 | T6: =IF(AND(E6=1,S6=0),1+COUNTIFS($E$2:$E$55,1,$S$2:$S$55,0,$R$2:$R$55,"<"&R6),0) -> 0 | U6: =IF(E6=1,IF(S6=1,IF(G6="VT",1,IF(G6="NH",2,3)),3+T6),0) -> 1 | V6: =IF(C6>0,INDEX(RawFinancials!$P:$P,C6),IF(B6>0,INDEX(RawFinancials!$P:$P,B6),"")) -> THE FIRST NATIONAL BANK OF ORWELL | W6: =E6*(1-D6) -> 0 | X6: =D6*(1-E6) -> 0 | Y6: =W6*K6 -> 0 | Z6: =X6*H6 -> 0
A7: 11971 | B7: =SUMIFS(RawFinancials!$A$2:$A$747,RawFinancials!$C$2:$C$747,A7,RawFinancials!$W$2:$W$747,WF_START_PERIOD) -> 482 | C7: =SUMIFS(RawFinancials!$A$2:$A$747,RawFinancials!$C$2:$C$747,A7,RawFinancials!$W$2:$W$747,WF_END_PERIOD) -> 696 | D7: =COUNTIFS(RawFinancials!$C$2:$C$747,A7,RawFinancials!$W$2:$W$747,WF_START_PERIOD,RawFinancials!$AA$2:$AA$747,1) -> 1 | E7: =COUNTIFS(RawFinancials!$C$2:$C$747,A7,RawFinancials!$W$2:$W$747,WF_END_PERIOD,RawFinancials!$AA$2:$AA$747,1) -> 1 | F7: =IF(B7>0,INDEX(RawFinancials!$Z:$Z,B7),"") -> ME | G7: =IF(C7>0,INDEX(RawFinancials!$Z:$Z,C7),"") -> ME | H7: =SUMIFS(RawFinancials!$B$2:$B$747,RawFinancials!$C$2:$C$747,A7,RawFinancials!$W$2:$W$747,WF_START_PERIOD,RawFinancials!$AA$2:$AA$747,1) -> 4030143 | I7: =SUMIFS(RawFinancials!$AB$2:$AB$747,RawFinancials!$C$2:$C$747,A7,RawFinancials!$W$2:$W$747,WF_START_PERIOD,RawFinancials!$AA$2:$AA$747,1) -> 6310 | J7: =IF(D7=1,100*I7/H7,"") -> 0.15657013 | K7: =SUMIFS(RawFinancials!$B$2:$B$747,RawFinancials!$C$2:$C$747,A7,RawFinancials!$W$2:$W$747,WF_END_PERIOD,RawFinancials!$AA$2:$AA$747,1) -> 4106441 | L7: =SUMIFS(RawFinancials!$AB$2:$AB$747,RawFinancials!$C$2:$C$747,A7,RawFinancials!$W$2:$W$747,WF_END_PERIOD,RawFinancials!$AA$2:$AA$747,1) -> 10161 | M7: =IF(E7=1,100*L7/K7,"") -> 0.24744055 | N7: =D7*E7 -> 1 | O7: =IF(N7=1,H7,0) -> 4030143 | P7: =IF(N7=1,H7*J7,0) -> 631000 | Q7: =IF(N7=1,H7*M7,0) -> 997220.78 | R7: =IF(E7=1,1+COUNTIFS($E$2:$E$55,1,$M$2:$M$55,">"&M7)+COUNTIFS($E$2:$E$55,1,$M$2:$M$55,M7,$A$2:$A$55,"<"&A7),0) -> 28 | S7: =IF(E7=1,IF(COUNTIFS($E$2:$E$55,1,$G$2:$G$55,G7,$M$2:$M$55,">"&M7)+COUNTIFS($E$2:$E$55,1,$G$2:$G$55,G7,$M$2:$M$55,M7,$A$2:$A$55,"<"&A7)=0,1,0),0) -> 0 | T7: =IF(AND(E7=1,S7=0),1+COUNTIFS($E$2:$E$55,1,$S$2:$S$55,0,$R$2:$R$55,"<"&R7),0) -> 25 | U7: =IF(E7=1,IF(S7=1,IF(G7="VT",1,IF(G7="NH",2,3)),3+T7),0) -> 28 | V7: =IF(C7>0,INDEX(RawFinancials!$P:$P,C7),IF(B7>0,INDEX(RawFinancials!$P:$P,B7),"")) -> BAR HARBOR BANK & TRUST | W7: =E7*(1-D7) -> 0 | X7: =D7*(1-E7) -> 0 | Y7: =W7*K7 -> 0 | Z7: =X7*H7 -> 0
A8: 12874 | B8: =SUMIFS(RawFinancials!$A$2:$A$747,RawFinancials!$C$2:$C$747,A8,RawFinancials!$W$2:$W$747,WF_START_PERIOD) -> 483 | C8: =SUMIFS(RawFinancials!$A$2:$A$747,RawFinancials!$C$2:$C$747,A8,RawFinancials!$W$2:$W$747,WF_END_PERIOD) -> 697 | D8: =COUNTIFS(RawFinancials!$C$2:$C$747,A8,RawFinancials!$W$2:$W$747,WF_START_PERIOD,RawFinancials!$AA$2:$AA$747,1) -> 1 | E8: =COUNTIFS(RawFinancials!$C$2:$C$747,A8,RawFinancials!$W$2:$W$747,WF_END_PERIOD,RawFinancials!$AA$2:$AA$747,1) -> 1 | F8: =IF(B8>0,INDEX(RawFinancials!$Z:$Z,B8),"") -> ME | G8: =IF(C8>0,INDEX(RawFinancials!$Z:$Z,C8),"") -> ME | H8: =SUMIFS(RawFinancials!$B$2:$B$747,RawFinancials!$C$2:$C$747,A8,RawFinancials!$W$2:$W$747,WF_START_PERIOD,RawFinancials!$AA$2:$AA$747,1) -> 1036850 | I8: =SUMIFS(RawFinancials!$AB$2:$AB$747,RawFinancials!$C$2:$C$747,A8,RawFinancials!$W$2:$W$747,WF_START_PERIOD,RawFinancials!$AA$2:$AA$747,1) -> 1516 | J8: =IF(D8=1,100*I8/H8,"") -> 0.14621208 | K8: =SUMIFS(RawFinancials!$B$2:$B$747,RawFinancials!$C$2:$C$747,A8,RawFinancials!$W$2:$W$747,WF_END_PERIOD,RawFinancials!$AA$2:$AA$747,1) -> 1085692 | L8: =SUMIFS(RawFinancials!$AB$2:$AB$747,RawFinancials!$C$2:$C$747,A8,RawFinancials!$W$2:$W$747,WF_END_PERIOD,RawFinancials!$AA$2:$AA$747,1) -> 1392 | M8: =IF(E8=1,100*L8/K8,"") -> 0.12821316 | N8: =D8*E8 -> 1 | O8: =IF(N8=1,H8,0) -> 1036850 | P8: =IF(N8=1,H8*J8,0) -> 151600 | Q8: =IF(N8=1,H8*M8,0) -> 132937.81 | R8: =IF(E8=1,1+COUNTIFS($E$2:$E$55,1,$M$2:$M$55,">"&M8)+COUNTIFS($E$2:$E$55,1,$M$2:$M$55,M8,$A$2:$A$55,"<"&A8),0) -> 34 | S8: =IF(E8=1,IF(COUNTIFS($E$2:$E$55,1,$G$2:$G$55,G8,$M$2:$M$55,">"&M8)+COUNTIFS($E$2:$E$55,1,$G$2:$G$55,G8,$M$2:$M$55,M8,$A$2:$A$55,"<"&A8)=0,1,0),0) -> 0 | T8: =IF(AND(E8=1,S8=0),1+COUNTIFS($E$2:$E$55,1,$S$2:$S$55,0,$R$2:$R$55,"<"&R8),0) -> 31 | U8: =IF(E8=1,IF(S8=1,IF(G8="VT",1,IF(G8="NH",2,3)),3+T8),0) -> 34 | V8: =IF(C8>0,INDEX(RawFinancials!$P:$P,C8),IF(B8>0,INDEX(RawFinancials!$P:$P,B8),"")) -> KATAHDIN TRUST COMPANY | W8: =E8*(1-D8) -> 0 | X8: =D8*(1-E8) -> 0 | Y8: =W8*K8 -> 0 | Z8: =X8*H8 -> 0
A9: 13063 | B9: =SUMIFS(RawFinancials!$A$2:$A$747,RawFinancials!$C$2:$C$747,A9,RawFinancials!$W$2:$W$747,WF_START_PERIOD) -> 484 | C9: =SUMIFS(RawFinancials!$A$2:$A$747,RawFinancials!$C$2:$C$747,A9,RawFinancials!$W$2:$W$747,WF_END_PERIOD) -> 698 | D9: =COUNTIFS(RawFinancials!$C$2:$C$747,A9,RawFinancials!$W$2:$W$747,WF_START_PERIOD,RawFinancials!$AA$2:$AA$747,1) -> 1 | E9: =COUNTIFS(RawFinancials!$C$2:$C$747,A9,RawFinancials!$W$2:$W$747,WF_END_PERIOD,RawFinancials!$AA$2:$AA$747,1) -> 1 | F9: =IF(B9>0,INDEX(RawFinancials!$Z:$Z,B9),"") -> ME | G9: =IF(C9>0,INDEX(RawFinancials!$Z:$Z,C9),"") -> ME | H9: =SUMIFS(RawFinancials!$B$2:$B$747,RawFinancials!$C$2:$C$747,A9,RawFinancials!$W$2:$W$747,WF_START_PERIOD,RawFinancials!$AA$2:$AA$747,1) -> 1848882 | I9: =SUMIFS(RawFinancials!$AB$2:$AB$747,RawFinancials!$C$2:$C$747,A9,RawFinancials!$W$2:$W$747,WF_START_PERIOD,RawFinancials!$AA$2:$AA$747,1) -> 701 | J9: =IF(D9=1,100*I9/H9,"") -> 0.037914805 | K9: =SUMIFS(RawFinancials!$B$2:$B$747,RawFinancials!$C$2:$C$747,A9,RawFinancials!$W$2:$W$747,WF_END_PERIOD,RawFinancials!$AA$2:$AA$747,1) -> 1933479 | L9: =SUMIFS(RawFinancials!$AB$2:$AB$747,RawFinancials!$C$2:$C$747,A9,RawFinancials!$W$2:$W$747,WF_END_PERIOD,RawFinancials!$AA$2:$AA$747,1) -> 2446 | M9: =IF(E9=1,100*L9/K9,"") -> 0.12650771 | N9: =D9*E9 -> 1 | O9: =IF(N9=1,H9,0) -> 1848882 | P9: =IF(N9=1,H9*J9,0) -> 70100 | Q9: =IF(N9=1,H9*M9,0) -> 233897.83 | R9: =IF(E9=1,1+COUNTIFS($E$2:$E$55,1,$M$2:$M$55,">"&M9)+COUNTIFS($E$2:$E$55,1,$M$2:$M$55,M9,$A$2:$A$55,"<"&A9),0) -> 35 | S9: =IF(E9=1,IF(COUNTIFS($E$2:$E$55,1,$G$2:$G$55,G9,$M$2:$M$55,">"&M9)+COUNTIFS($E$2:$E$55,1,$G$2:$G$55,G9,$M$2:$M$55,M9,$A$2:$A$55,"<"&A9)=0,1,0),0) -> 0 | T9: =IF(AND(E9=1,S9=0),1+COUNTIFS($E$2:$E$55,1,$S$2:$S$55,0,$R$2:$R$55,"<"&R9),0) -> 32 | U9: =IF(E9=1,IF(S9=1,IF(G9="VT",1,IF(G9="NH",2,3)),3+T9),0) -> 35 | V9: =IF(C9>0,INDEX(RawFinancials!$P:$P,C9),IF(B9>0,INDEX(RawFinancials!$P:$P,B9),"")) -> KENNEBUNK SAVINGS BANK | W9: =E9*(1-D9) -> 0 | X9: =D9*(1-E9) -> 0 | Y9: =W9*K9 -> 0 | Z9: =X9*H9 -> 0
A10: 14134 | B10: =SUMIFS(RawFinancials!$A$2:$A$747,RawFinancials!$C$2:$C$747,A10,RawFinancials!$W$2:$W$747,WF_START_PERIOD) -> 485 | C10: =SUMIFS(RawFinancials!$A$2:$A$747,RawFinancials!$C$2:$C$747,A10,RawFinancials!$W$2:$W$747,WF_END_PERIOD) -> 699 | D10: =COUNTIFS(RawFinancials!$C$2:$C$747,A10,RawFinancials!$W$2:$W$747,WF_START_PERIOD,RawFinancials!$AA$2:$AA$747,1) -> 1 | E10: =COUNTIFS(RawFinancials!$C$2:$C$747,A10,RawFinancials!$W$2:$W$747,WF_END_PERIOD,RawFinancials!$AA$2:$AA$747,1) -> 1 | F10: =IF(B10>0,INDEX(RawFinancials!$Z:$Z,B10),"") -> VT | G10: =IF(C10>0,INDEX(RawFinancials!$Z:$Z,C10),"") -> VT | H10: =SUMIFS(RawFinancials!$B$2:$B$747,RawFinancials!$C$2:$C$747,A10,RawFinancials!$W$2:$W$747,WF_START_PERIOD,RawFinancials!$AA$2:$AA$747,1) -> 842999 | I10: =SUMIFS(RawFinancials!$AB$2:$AB$747,RawFinancials!$C$2:$C$747,A10,RawFinancials!$W$2:$W$747,WF_START_PERIOD,RawFinancials!$AA$2:$AA$747,1) -> 9888 | J10: =IF(D10=1,100*I10/H10,"") -> 1.1729551 | K10: =SUMIFS(RawFinancials!$B$2:$B$747,RawFinancials!$C$2:$C$747,A10,RawFinancials!$W$2:$W$747,WF_END_PERIOD,RawFinancials!$AA$2:$AA$747,1) -> 882477 | L10: =SUMIFS(RawFinancials!$AB$2:$AB$747,RawFinancials!$C$2:$C$747,A10,RawFinancials!$W$2:$W$747,WF_END_PERIOD,RawFinancials!$AA$2:$AA$747,1) -> 2713 | M10: =IF(E10=1,100*L10/K10,"") -> 0.30743011 | N10: =D10*E10 -> 1 | O10: =IF(N10=1,H10,0) -> 842999 | P10: =IF(N10=1,H10*J10,0) -> 988800 | Q10: =IF(N10=1,H10*M10,0) -> 259163.27 | R10: =IF(E10=1,1+COUNTIFS($E$2:$E$55,1,$M$2:$M$55,">"&M10)+COUNTIFS($E$2:$E$55,1,$M$2:$M$55,M10,$A$2:$A$55,"<"&A10),0) -> 23 | S10: =IF(E10=1,IF(COUNTIFS($E$2:$E$55,1,$G$2:$G$55,G10,$M$2:$M$55,">"&M10)+COUNTIFS($E$2:$E$55,1,$G$2:$G$55,G10,$M$2:$M$55,M10,$A$2:$A$55,"<"&A10)=0,1,0),0) -> 0 | T10: =IF(AND(E10=1,S10=0),1+COUNTIFS($E$2:$E$55,1,$S$2:$S$55,0,$R$2:$R$55,"<"&R10),0) -> 20 | U10: =IF(E10=1,IF(S10=1,IF(G10="VT",1,IF(G10="NH",2,3)),3+T10),0) -> 23 | V10: =IF(C10>0,INDEX(RawFinancials!$P:$P,C10),IF(B10>0,INDEX(RawFinancials!$P:$P,B10),"")) -> PASSUMPSIC SAVINGS BANK | W10: =E10*(1-D10) -> 0 | X10: =D10*(1-E10) -> 0 | Y10: =W10*K10 -> 0 | Z10: =X10*H10 -> 0
A11: 14136 | B11: =SUMIFS(RawFinancials!$A$2:$A$747,RawFinancials!$C$2:$C$747,A11,RawFinancials!$W$2:$W$747,WF_START_PERIOD) -> 486 | C11: =SUMIFS(RawFinancials!$A$2:$A$747,RawFinancials!$C$2:$C$747,A11,RawFinancials!$W$2:$W$747,WF_END_PERIOD) -> 700 | D11: =COUNTIFS(RawFinancials!$C$2:$C$747,A11,RawFinancials!$W$2:$W$747,WF_START_PERIOD,RawFinancials!$AA$2:$AA$747,1) -> 1 | E11: =COUNTIFS(RawFinancials!$C$2:$C$747,A11,RawFinancials!$W$2:$W$747,WF_END_PERIOD,RawFinancials!$AA$2:$AA$747,1) -> 1 | F11: =IF(B11>0,INDEX(RawFinancials!$Z:$Z,B11),"") -> VT | G11: =IF(C11>0,INDEX(RawFinancials!$Z:$Z,C11),"") -> VT | H11: =SUMIFS(RawFinancials!$B$2:$B$747,RawFinancials!$C$2:$C$747,A11,RawFinancials!$W$2:$W$747,WF_START_PERIOD,RawFinancials!$AA$2:$AA$747,1) -> 234689 | I11: =SUMIFS(RawFinancials!$AB$2:$AB$747,RawFinancials!$C$2:$C$747,A11,RawFinancials!$W$2:$W$747,WF_START_PERIOD,RawFinancials!$AA$2:$AA$747,1) -> 754 | J11: =IF(D11=1,100*I11/H11,"") -> 0.32127624 | K11: =SUMIFS(RawFinancials!$B$2:$B$747,RawFinancials!$C$2:$C$747,A11,RawFinancials!$W$2:$W$747,WF_END_PERIOD,RawFinancials!$AA$2:$AA$747,1) -> 247991 | L11: =SUMIFS(RawFinancials!$AB$2:$AB$747,RawFinancials!$C$2:$C$747,A11,RawFinancials!$W$2:$W$747,WF_END_PERIOD,RawFinancials!$AA$2:$AA$747,1) -> 1077 | M11: =IF(E11=1,100*L11/K11,"") -> 0.43428995 | N11: =D11*E11 -> 1 | O11: =IF(N11=1,H11,0) -> 234689 | P11: =IF(N11=1,H11*J11,0) -> 75400 | Q11: =IF(N11=1,H11*M11,0) -> 101923.08 | R11: =IF(E11=1,1+COUNTIFS($E$2:$E$55,1,$M$2:$M$55,">"&M11)+COUNTIFS($E$2:$E$55,1,$M$2:$M$55,M11,$A$2:$A$55,"<"&A11),0) -> 16 | S11: =IF(E11=1,IF(COUNTIFS($E$2:$E$55,1,$G$2:$G$55,G11,$M$2:$M$55,">"&M11)+COUNTIFS($E$2:$E$55,1,$G$2:$G$55,G11,$M$2:$M$55,M11,$A$2:$A$55,"<"&A11)=0,1,0),0) -> 0 | T11: =IF(AND(E11=1,S11=0),1+COUNTIFS($E$2:$E$55,1,$S$2:$S$55,0,$R$2:$R$55,"<"&R11),0) -> 13 | U11: =IF(E11=1,IF(S11=1,IF(G11="VT",1,IF(G11="NH",2,3)),3+T11),0) -> 16 | V11: =IF(C11>0,INDEX(RawFinancials!$P:$P,C11),IF(B11>0,INDEX(RawFinancials!$P:$P,B11),"")) -> WELLS RIVER SAVINGS BANK | W11: =E11*(1-D11) -> 0 | X11: =D11*(1-E11) -> 0 | Y11: =W11*K11 -> 0 | Z11: =X11*H11 -> 0
A12: 14140 | B12: =SUMIFS(RawFinancials!$A$2:$A$747,RawFinancials!$C$2:$C$747,A12,RawFinancials!$W$2:$W$747,WF_START_PERIOD) -> 487 | C12: =SUMIFS(RawFinancials!$A$2:$A$747,RawFinancials!$C$2:$C$747,A12,RawFinancials!$W$2:$W$747,WF_END_PERIOD) -> 701 | D12: =COUNTIFS(RawFinancials!$C$2:$C$747,A12,RawFinancials!$W$2:$W$747,WF_START_PERIOD,RawFinancials!$AA$2:$AA$747,1) -> 1 | E12: =COUNTIFS(RawFinancials!$C$2:$C$747,A12,RawFinancials!$W$2:$W$747,WF_END_PERIOD,RawFinancials!$AA$2:$AA$747,1) -> 1 | F12: =IF(B12>0,INDEX(RawFinancials!$Z:$Z,B12),"") -> VT | G12: =IF(C12>0,INDEX(RawFinancials!$Z:$Z,C12),"") -> VT | H12: =SUMIFS(RawFinancials!$B$2:$B$747,RawFinancials!$C$2:$C$747,A12,RawFinancials!$W$2:$W$747,WF_START_PERIOD,RawFinancials!$AA$2:$AA$747,1) -> 1498757 | I12: =SUMIFS(RawFinancials!$AB$2:$AB$747,RawFinancials!$C$2:$C$747,A12,RawFinancials!$W$2:$W$747,WF_START_PERIOD,RawFinancials!$AA$2:$AA$747,1) -> 2046 | J12: =IF(D12=1,100*I12/H12,"") -> 0.13651312 | K12: =SUMIFS(RawFinancials!$B$2:$B$747,RawFinancials!$C$2:$C$747,A12,RawFinancials!$W$2:$W$747,WF_END_PERIOD,RawFinancials!$AA$2:$AA$747,1) -> 1560737 | L12: =SUMIFS(RawFinancials!$AB$2:$AB$747,RawFinancials!$C$2:$C$747,A12,RawFinancials!$W$2:$W$747,WF_END_PERIOD,RawFinancials!$AA$2:$AA$747,1) -> 7436 | M12: =IF(E12=1,100*L12/K12,"") -> 0.47644158 | N12: =D12*E12 -> 1 | O12: =IF(N12=1,H12,0) -> 1498757 | P12: =IF(N12=1,H12*J12,0) -> 204600 | Q12: =IF(N12=1,H12*M12,0) -> 714070.15 | R12: =IF(E12=1,1+COUNTIFS($E$2:$E$55,1,$M$2:$M$55,">"&M12)+COUNTIFS($E$2:$E$55,1,$M$2:$M$55,M12,$A$2:$A$55,"<"&A12),0) -> 14 | S12: =IF(E12=1,IF(COUNTIFS($E$2:$E$55,1,$G$2:$G$55,G12,$M$2:$M$55,">"&M12)+COUNTIFS($E$2:$E$55,1,$G$2:$G$55,G12,$M$2:$M$55,M12,$A$2:$A$55,"<"&A12)=0,1,0),0) -> 0 | T12: =IF(AND(E12=1,S12=0),1+COUNTIFS($E$2:$E$55,1,$S$2:$S$55,0,$R$2:$R$55,"<"&R12),0) -> 11 | U12: =IF(E12=1,IF(S12=1,IF(G12="VT",1,IF(G12="NH",2,3)),3+T12),0) -> 14 | V12: =IF(C12>0,INDEX(RawFinancials!$P:$P,C12),IF(B12>0,INDEX(RawFinancials!$P:$P,B12),"")) -> NORTHFIELD SAVINGS BANK | W12: =E12*(1-D12) -> 0 | X12: =D12*(1-E12) -> 0 | Y12: =W12*K12 -> 0 | Z12: =X12*H12 -> 0
A13: 14158 | B13: =SUMIFS(RawFinancials!$A$2:$A$747,RawFinancials!$C$2:$C$747,A13,RawFinancials!$W$2:$W$747,WF_START_PERIOD) -> 488 | C13: =SUMIFS(RawFinancials!$A$2:$A$747,RawFinancials!$C$2:$C$747,A13,RawFinancials!$W$2:$W$747,WF_END_PERIOD) -> 702 | D13: =COUNTIFS(RawFinancials!$C$2:$C$747,A13,RawFinancials!$W$2:$W$747,WF_START_PERIOD,RawFinancials!$AA$2:$AA$747,1) -> 1 | E13: =COUNTIFS(RawFinancials!$C$2:$C$747,A13,RawFinancials!$W$2:$W$747,WF_END_PERIOD,RawFinancials!$AA$2:$AA$747,1) -> 1 | F13: =IF(B13>0,INDEX(RawFinancials!$Z:$Z,B13),"") -> VT | G13: =IF(C13>0,INDEX(RawFinancials!$Z:$Z,C13),"") -> VT | H13: =SUMIFS(RawFinancials!$B$2:$B$747,RawFinancials!$C$2:$C$747,A13,RawFinancials!$W$2:$W$747,WF_START_PERIOD,RawFinancials!$AA$2:$AA$747,1) -> 1397831 | I13: =SUMIFS(RawFinancials!$AB$2:$AB$747,RawFinancials!$C$2:$C$747,A13,RawFinancials!$W$2:$W$747,WF_START_PERIOD,RawFinancials!$AA$2:$AA$747,1) -> 1928 | J13: =IF(D13=1,100*I13/H13,"") -> 0.13792798 | K13: =SUMIFS(RawFinancials!$B$2:$B$747,RawFinancials!$C$2:$C$747,A13,RawFinancials!$W$2:$W$747,WF_END_PERIOD,RawFinancials!$AA$2:$AA$747,1) -> 1479452 | L13: =SUMIFS(RawFinancials!$AB$2:$AB$747,RawFinancials!$C$2:$C$747,A13,RawFinancials!$W$2:$W$747,WF_END_PERIOD,RawFinancials!$AA$2:$AA$747,1) -> 15261 | M13: =IF(E13=1,100*L13/K13,"") -> 1.0315306 | N13: =D13*E13 -> 1 | O13: =IF(N13=1,H13,0) -> 1397831 | P13: =IF(N13=1,H13*J13,0) -> 192800 | Q13: =IF(N13=1,H13*M13,0) -> 1441905.4 | R13: =IF(E13=1,1+COUNTIFS($E$2:$E$55,1,$M$2:$M$55,">"&M13)+COUNTIFS($E$2:$E$55,1,$M$2:$M$55,M13,$A$2:$A$55,"<"&A13),0) -> 7 | S13: =IF(E13=1,IF(COUNTIFS($E$2:$E$55,1,$G$2:$G$55,G13,$M$2:$M$55,">"&M13)+COUNTIFS($E$2:$E$55,1,$G$2:$G$55,G13,$M$2:$M$55,M13,$A$2:$A$55,"<"&A13)=0,1,0),0) -> 0 | T13: =IF(AND(E13=1,S13=0),1+COUNTIFS($E$2:$E$55,1,$S$2:$S$55,0,$R$2:$R$55,"<"&R13),0) -> 4 | U13: =IF(E13=1,IF(S13=1,IF(G13="VT",1,IF(G13="NH",2,3)),3+T13),0) -> 7 | V13: =IF(C13>0,INDEX(RawFinancials!$P:$P,C13),IF(B13>0,INDEX(RawFinancials!$P:$P,B13),"")) -> UNION BANK | W13: =E13*(1-D13) -> 0 | X13: =D13*(1-E13) -> 0 | Y13: =W13*K13 -> 0 | Z13: =X13*H13 -> 0
... A55: 59298 | B55: =SUMIFS(RawFinancials!$A$2:$A$747,RawFinancials!$C$2:$C$747,A55,RawFinancials!$W$2:$W$747,WF_START_PERIOD) -> 532 | C55: =SUMIFS(RawFinancials!$A$2:$A$747,RawFinancials!$C$2:$C$747,A55,RawFinancials!$W$2:$W$747,WF_END_PERIOD) -> 744 | D55: =COUNTIFS(RawFinancials!$C$2:$C$747,A55,RawFinancials!$W$2:$W$747,WF_START_PERIOD,RawFinancials!$AA$2:$AA$747,1) -> 1 | E55: =COUNTIFS(RawFinancials!$C$2:$C$747,A55,RawFinancials!$W$2:$W$747,WF_END_PERIOD,RawFinancials!$AA$2:$AA$747,1) -> 1 | F55: =IF(B55>0,INDEX(RawFinancials!$Z:$Z,B55),"") -> VT | G55: =IF(C55>0,INDEX(RawFinancials!$Z:$Z,C55),"") -> VT | H55: =SUMIFS(RawFinancials!$B$2:$B$747,RawFinancials!$C$2:$C$747,A55,RawFinancials!$W$2:$W$747,WF_START_PERIOD,RawFinancials!$AA$2:$AA$747,1) -> 218470 | I55: =SUMIFS(RawFinancials!$AB$2:$AB$747,RawFinancials!$C$2:$C$747,A55,RawFinancials!$W$2:$W$747,WF_START_PERIOD,RawFinancials!$AA$2:$AA$747,1) -> 0 | J55: =IF(D55=1,100*I55/H55,"") -> 0 | K55: =SUMIFS(RawFinancials!$B$2:$B$747,RawFinancials!$C$2:$C$747,A55,RawFinancials!$W$2:$W$747,WF_END_PERIOD,RawFinancials!$AA$2:$AA$747,1) -> 269483 | L55: =SUMIFS(RawFinancials!$AB$2:$AB$747,RawFinancials!$C$2:$C$747,A55,RawFinancials!$W$2:$W$747,WF_END_PERIOD,RawFinancials!$AA$2:$AA$747,1) -> 0 | M55: =IF(E55=1,100*L55/K55,"") -> 0 | N55: =D55*E55 -> 1 | O55: =IF(N55=1,H55,0) -> 218470 | P55: =IF(N55=1,H55*J55,0) -> 0 | Q55: =IF(N55=1,H55*M55,0) -> 0 | R55: =IF(E55=1,1+COUNTIFS($E$2:$E$55,1,$M$2:$M$55,">"&M55)+COUNTIFS($E$2:$E$55,1,$M$2:$M$55,M55,$A$2:$A$55,"<"&A55),0) -> 52 | S55: =IF(E55=1,IF(COUNTIFS($E$2:$E$55,1,$G$2:$G$55,G55,$M$2:$M$55,">"&M55)+COUNTIFS($E$2:$E$55,1,$G$2:$G$55,G55,$M$2:$M$55,M55,$A$2:$A$55,"<"&A55)=0,1,0),0) -> 0 | T55: =IF(AND(E55=1,S55=0),1+COUNTIFS($E$2:$E$55,1,$S$2:$S$55,0,$R$2:$R$55,"<"&R55),0) -> 49 | U55: =IF(E55=1,IF(S55=1,IF(G55="VT",1,IF(G55="NH",2,3)),3+T55),0) -> 52 | V55: =IF(C55>0,INDEX(RawFinancials!$P:$P,C55),IF(B55>0,INDEX(RawFinancials!$P:$P,B55),"")) -> BANK OF BURLINGTON | W55: =E55*(1-D55) -> 0 | X55: =D55*(1-E55) -> 0 | Y55: =W55*K55 -> 0 | Z55: =X55*H55 -> 0

Sheet EndpointBridge
A1: state | B1: start_banks | C1: end_banks | D1: common_banks | E1: observed_start_pct | F1: observed_end_pct | G1: observed_change_pp | H1: fixed_start_pct | I1: fixed_end_pct | J1: fixed_change_pp | K1: scope_reweight_residual_pp | L1: entering_N | M1: exiting_N | N1: entering_end_assets | O1: exiting_start_assets | P1: entering_CERT | Q1: exiting_CERT
A2: ALL | B2: =IF(WF_MODEL_VALID,SUM(BankCalc!$D$2:$D$55),"") -> 54 | C2: =IF(WF_MODEL_VALID,SUM(BankCalc!$E$2:$E$55),"") -> 52 | D2: =IF(WF_MODEL_VALID,SUM(BankCalc!$N$2:$N$55),"") -> 52 | E2: =IF(WF_MODEL_VALID,IFERROR(100*SUMIFS(RawFinancials!$AB$2:$AB$747,RawFinancials!$W$2:$W$747,WF_START_PERIOD,RawFinancials!$AA$2:$AA$747,1)/SUMIFS(RawFinancials!$B$2:$B$747,RawFinancials!$W$2:$W$747,WF_START_PERIOD,RawFinancials!$AA$2:$AA$747,1),""),"") -> 0.29856647 | F2: =IF(WF_MODEL_VALID,IFERROR(100*SUMIFS(RawFinancials!$AB$2:$AB$747,RawFinancials!$W$2:$W$747,WF_END_PERIOD,RawFinancials!$AA$2:$AA$747,1)/SUMIFS(RawFinancials!$B$2:$B$747,RawFinancials!$W$2:$W$747,WF_END_PERIOD,RawFinancials!$AA$2:$AA$747,1),""),"") -> 0.36819314 | G2: =IF(WF_MODEL_VALID,F2-E2,"") -> 0.069626673 | H2: =IF(WF_MODEL_VALID,IFERROR(SUM(BankCalc!$P$2:$P$55)/SUM(BankCalc!$O$2:$O$55),""),"") -> 0.2943426 | I2: =IF(WF_MODEL_VALID,IFERROR(SUM(BankCalc!$Q$2:$Q$55)/SUM(BankCalc!$O$2:$O$55),""),"") -> 0.35737369 | J2: =IF(WF_MODEL_VALID,I2-H2,"") -> 0.063031091 | K2: =IF(WF_MODEL_VALID,G2-J2,"") -> 0.0065955818 | L2: =IF(WF_MODEL_VALID,SUM(BankCalc!$W$2:$W$55),"") -> 0 | M2: =IF(WF_MODEL_VALID,SUM(BankCalc!$X$2:$X$55),"") -> 2 | N2: =IF(WF_MODEL_VALID,SUM(BankCalc!$Y$2:$Y$55),"") -> 0 | O2: =IF(WF_MODEL_VALID,SUM(BankCalc!$Z$2:$Z$55),"") -> 2924280 | P2: =IF(WF_MODEL_VALID,IF(AND(BankCalc!W2=1),BankCalc!A2&",","")&IF(AND(BankCalc!W3=1),BankCalc!A3&",","")&IF(AND(BankCalc!W4=1),BankCalc!A4&",","")&IF(AND(BankCalc!W5=1),BankCalc!A5&",","")&IF(AND(BankCalc!W6=1),BankCalc!A6&",","")&IF(AND(BankCalc!W7=1),BankCalc!A7&",","")&IF(AND(BankCalc!W8=1),BankCalc!A8&",","")&IF(AND(BankCalc!W9=1),BankCalc!A9&",","")&IF(AND(BankCalc!W10=1),BankCalc!A10&",","")&IF(AND(BankCalc!W11=1),BankCalc!A11&",","")&IF(AND(BankCalc!W12=1),BankCalc!A12&",","")&IF(AND(BankCalc!W13=1),BankCalc!A13&",","")&IF(AND(BankCalc!W14=1),BankCalc!A14&",","")&IF(AND(BankCalc!W15=1),BankCalc!A15&",","")&IF(AND(BankCalc!W16=1),BankCalc!A16&",","")&IF(AND(BankCalc!W17=1),BankCalc!A17&",","")&IF(AND(BankCalc!W18=1),BankCalc!A18&",","")&IF(AND(BankCalc!W19=1),BankCalc!A19&",","")&IF(AND(BankCalc!W20=1),BankCalc!A20&",","")&IF(AND(BankCalc!W21=1),BankCalc!A21&",","")&IF(AND(BankCalc!W22=1),BankCalc!A22&",","")&IF(AND(BankCalc!W23=1),BankCalc!A23&",","")&IF(AND(BankCalc!W24=1),BankCalc!A24&",","")&IF(AND(BankCalc!W25=1),BankCalc!A25&",","")&IF(AND(BankCalc!W26=1),BankCalc!A26&",","")&IF(AND(BankCalc!W27=1),BankCalc!A27&",","")&IF(AND(BankCalc!W28=1),BankCalc!A28&",","")&IF(AND(BankCalc!W29=1),BankCalc!A29&",","")&IF(AND(BankCalc!W30=1),BankCalc!A30&",","")&IF(AND(BankCalc!W31=1),BankCalc!A31&",","")&IF(AND(BankCalc!W32=1),BankCalc!A32&",","")&IF(AND(BankCalc!W33=1),BankCalc!A33&",","")&IF(AND(BankCalc!W34=1),BankCalc!A34&",","")&IF(AND(BankCalc!W35=1),BankCalc!A35&",","")&IF(AND(BankCalc!W36=1),BankCalc!A36&",","")&IF(AND(BankCalc!W37=1),BankCalc!A37&",","")&IF(AND(BankCalc!W38=1),BankCalc!A38&",","")&IF(AND(BankCalc!W39=1),BankCalc!A39&",","")&IF(AND(BankCalc!W40=1),BankCalc!A40&",","")&IF(AND(BankCalc!W41=1),BankCalc!A41&",","")&IF(AND(BankCalc!W42=1),BankCalc!A42&",","")&IF(AND(BankCalc!W43=1),BankCalc!A43&",","")&IF(AND(BankCalc!W44=1),BankCalc!A44&",","")&IF(AND(BankCalc!W45=1),BankCalc!A45&",","")&IF(AND(BankCalc!W46=1),BankCalc!A46&",","")&IF(AND(BankCalc!W47=1),BankCalc!A47&",","")&IF(AND(BankCalc!W48=1),BankCalc!A48&",","")&IF(AND(BankCalc!W49=1),BankCalc!A49&",","")&IF(AND(BankCalc!W50=1),BankCalc!A50&",","")&IF(AND(BankCalc!W51=1),BankCalc!A51&",","")&IF(AND(BankCalc!W52=1),BankCalc!A52&",","")&IF(AND(BankCalc!W53=1),BankCalc!A53&",","")&IF(AND(BankCalc!W54=1),BankCalc!A54&",","")&IF(AND(BankCalc!W55=1),BankCalc!A55&",",""),"") | Q2: =IF(WF_MODEL_VALID,IF(AND(BankCalc!X2=1),BankCalc!A2&",","")&IF(AND(BankCalc!X3=1),BankCalc!A3&",","")&IF(AND(BankCalc!X4=1),BankCalc!A4&",","")&IF(AND(BankCalc!X5=1),BankCalc!A5&",","")&IF(AND(BankCalc!X6=1),BankCalc!A6&",","")&IF(AND(BankCalc!X7=1),BankCalc!A7&",","")&IF(AND(BankCalc!X8=1),BankCalc!A8&",","")&IF(AND(BankCalc!X9=1),BankCalc!A9&",","")&IF(AND(BankCalc!X10=1),BankCalc!A10&",","")&IF(AND(BankCalc!X11=1),BankCalc!A11&",","")&IF(AND(BankCalc!X12=1),BankCalc!A12&",","")&IF(AND(BankCalc!X13=1),BankCalc!A13&",","")&IF(AND(BankCalc!X14=1),BankCalc!A14&",","")&IF(AND(BankCalc!X15=1),BankCalc!A15&",","")&IF(AND(BankCalc!X16=1),BankCalc!A16&",","")&IF(AND(BankCalc!X17=1),BankCalc!A17&",","")&IF(AND(BankCalc!X18=1),BankCalc!A18&",","")&IF(AND(BankCalc!X19=1),BankCalc!A19&",","")&IF(AND(BankCalc!X20=1),BankCalc!A20&",","")&IF(AND(BankCalc!X21=1),BankCalc!A21&",","")&IF(AND(BankCalc!X22=1),BankCalc!A22&",","")&IF(AND(BankCalc!X23=1),BankCalc!A23&",","")&IF(AND(BankCalc!X24=1),BankCalc!A24&",","")&IF(AND(BankCalc!X25=1),BankCalc!A25&",","")&IF(AND(BankCalc!X26=1),BankCalc!A26&",","")&IF(AND(BankCalc!X27=1),BankCalc!A27&",","")&IF(AND(BankCalc!X28=1),BankCalc!A28&",","")&IF(AND(BankCalc!X29=1),BankCalc!A29&",","")&IF(AND(BankCalc!X30=1),BankCalc!A30&",","")&IF(AND(BankCalc!X31=1),BankCalc!A31&",","")&IF(AND(BankCalc!X32=1),BankCalc!A32&",","")&IF(AND(BankCalc!X33=1),BankCalc!A33&",","")&IF(AND(BankCalc!X34=1),BankCalc!A34&",","")&IF(AND(BankCalc!X35=1),BankCalc!A35&",","")&IF(AND(BankCalc!X36=1),BankCalc!A36&",","")&IF(AND(BankCalc!X37=1),BankCalc!A37&",","")&IF(AND(BankCalc!X38=1),BankCalc!A38&",","")&IF(AND(BankCalc!X39=1),BankCalc!A39&",","")&IF(AND(BankCalc!X40=1),BankCalc!A40&",","")&IF(AND(BankCalc!X41=1),BankCalc!A41&",","")&IF(AND(BankCalc!X42=1),BankCalc!A42&",","")&IF(AND(BankCalc!X43=1),BankCalc!A43&",","")&IF(AND(BankCalc!X44=1),BankCalc!A44&",","")&IF(AND(BankCalc!X45=1),BankCalc!A45&",","")&IF(AND(BankCalc!X46=1),BankCalc!A46&",","")&IF(AND(BankCalc!X47=1),BankCalc!A47&",","")&IF(AND(BankCalc!X48=1),BankCalc!A48&",","")&IF(AND(BankCalc!X49=1),BankCalc!A49&",","")&IF(AND(BankCalc!X50=1),BankCalc!A50&",","")&IF(AND(BankCalc!X51=1),BankCalc!A51&",","")&IF(AND(BankCalc!X52=1),BankCalc!A52&",","")&IF(AND(BankCalc!X53=1),BankCalc!A53&",","")&IF(AND(BankCalc!X54=1),BankCalc!A54&",","")&IF(AND(BankCalc!X55=1),BankCalc!A55&",",""),"") -> 14240,17748,
A3: ME | B3: =IF(WF_MODEL_VALID,SUMIF(BankCalc!$F$2:$F$55,"ME",BankCalc!$D$2:$D$55),"") -> 23 | C3: =IF(WF_MODEL_VALID,SUMIF(BankCalc!$G$2:$G$55,"ME",BankCalc!$E$2:$E$55),"") -> 22 | D3: =IF(WF_MODEL_VALID,SUMIF(BankCalc!$G$2:$G$55,"ME",BankCalc!$N$2:$N$55),"") -> 22 | E3: =IF(WF_MODEL_VALID,IFERROR(100*SUMIFS(RawFinancials!$AB$2:$AB$747,RawFinancials!$W$2:$W$747,WF_START_PERIOD,RawFinancials!$AA$2:$AA$747,1,RawFinancials!$Z$2:$Z$747,"ME")/SUMIFS(RawFinancials!$B$2:$B$747,RawFinancials!$W$2:$W$747,WF_START_PERIOD,RawFinancials!$AA$2:$AA$747,1,RawFinancials!$Z$2:$Z$747,"ME"),""),"") -> 0.26419985 | F3: =IF(WF_MODEL_VALID,IFERROR(100*SUMIFS(RawFinancials!$AB$2:$AB$747,RawFinancials!$W$2:$W$747,WF_END_PERIOD,RawFinancials!$AA$2:$AA$747,1,RawFinancials!$Z$2:$Z$747,"ME")/SUMIFS(RawFinancials!$B$2:$B$747,RawFinancials!$W$2:$W$747,WF_END_PERIOD,RawFinancials!$AA$2:$AA$747,1,RawFinancials!$Z$2:$Z$747,"ME"),""),"") -> 0.36737741 | G3: =IF(WF_MODEL_VALID,F3-E3,"") -> 0.10317756 | H3: =IF(WF_MODEL_VALID,IFERROR(SUMIF(BankCalc!$G$2:$G$55,"ME",BankCalc!$P$2:$P$55)/SUMIF(BankCalc!$G$2:$G$55,"ME",BankCalc!$O$2:$O$55),""),"") -> 0.25554764 | I3: =IF(WF_MODEL_VALID,IFERROR(SUMIF(BankCalc!$G$2:$G$55,"ME",BankCalc!$Q$2:$Q$55)/SUMIF(BankCalc!$G$2:$G$55,"ME",BankCalc!$O$2:$O$55),""),"") -> 0.35303711 | J3: =IF(WF_MODEL_VALID,I3-H3,"") -> 0.097489475 | K3: =IF(WF_MODEL_VALID,G3-J3,"") -> 0.0056880831 | L3: =IF(WF_MODEL_VALID,SUMIF(BankCalc!$G$2:$G$55,"ME",BankCalc!$W$2:$W$55),"") -> 0 | M3: =IF(WF_MODEL_VALID,SUMIF(BankCalc!$F$2:$F$55,"ME",BankCalc!$X$2:$X$55),"") -> 1 | N3: =IF(WF_MODEL_VALID,SUMIF(BankCalc!$G$2:$G$55,"ME",BankCalc!$Y$2:$Y$55),"") -> 0 | O3: =IF(WF_MODEL_VALID,SUMIF(BankCalc!$F$2:$F$55,"ME",BankCalc!$Z$2:$Z$55),"") -> 1653584 | P3: =IF(WF_MODEL_VALID,IF(AND(BankCalc!W2=1,BankCalc!G2="ME"),BankCalc!A2&",","")&IF(AND(BankCalc!W3=1,BankCalc!G3="ME"),BankCalc!A3&",","")&IF(AND(BankCalc!W4=1,BankCalc!G4="ME"),BankCalc!A4&",","")&IF(AND(BankCalc!W5=1,BankCalc!G5="ME"),BankCalc!A5&",","")&IF(AND(BankCalc!W6=1,BankCalc!G6="ME"),BankCalc!A6&",","")&IF(AND(BankCalc!W7=1,BankCalc!G7="ME"),BankCalc!A7&",","")&IF(AND(BankCalc!W8=1,BankCalc!G8="ME"),BankCalc!A8&",","")&IF(AND(BankCalc!W9=1,BankCalc!G9="ME"),BankCalc!A9&",","")&IF(AND(BankCalc!W10=1,BankCalc!G10="ME"),BankCalc!A10&",","")&IF(AND(BankCalc!W11=1,BankCalc!G11="ME"),BankCalc!A11&",","")&IF(AND(BankCalc!W12=1,BankCalc!G12="ME"),BankCalc!A12&",","")&IF(AND(BankCalc!W13=1,BankCalc!G13="ME"),BankCalc!A13&",","")&IF(AND(BankCalc!W14=1,BankCalc!G14="ME"),BankCalc!A14&",","")&IF(AND(BankCalc!W15=1,BankCalc!G15="ME"),BankCalc!A15&",","")&IF(AND(BankCalc!W16=1,BankCalc!G16="ME"),BankCalc!A16&",","")&IF(AND(BankCalc!W17=1,BankCalc!G17="ME"),BankCalc!A17&",","")&IF(AND(BankCalc!W18=1,BankCalc!G18="ME"),BankCalc!A18&",","")&IF(AND(BankCalc!W19=1,BankCalc!G19="ME"),BankCalc!A19&",","")&IF(AND(BankCalc!W20=1,BankCalc!G20="ME"),BankCalc!A20&",","")&IF(AND(BankCalc!W21=1,BankCalc!G21="ME"),BankCalc!A21&",","")&IF(AND(BankCalc!W22=1,BankCalc!G22="ME"),BankCalc!A22&",","")&IF(AND(BankCalc!W23=1,BankCalc!G23="ME"),BankCalc!A23&",","")&IF(AND(BankCalc!W24=1,BankCalc!G24="ME"),BankCalc!A24&",","")&IF(AND(BankCalc!W25=1,BankCalc!G25="ME"),BankCalc!A25&",","")&IF(AND(BankCalc!W26=1,BankCalc!G26="ME"),BankCalc!A26&",","")&IF(AND(BankCalc!W27=1,BankCalc!G27="ME"),BankCalc!A27&",","")&IF(AND(BankCalc!W28=1,BankCalc!G28="ME"),BankCalc!A28&",","")&IF(AND(BankCalc!W29=1,BankCalc!G29="ME"),BankCalc!A29&",","")&IF(AND(BankCalc!W30=1,BankCalc!G30="ME"),BankCalc!A30&",","")&IF(AND(BankCalc!W31=1,BankCalc!G31="ME"),BankCalc!A31&",","")&IF(AND(BankCalc!W32=1,BankCalc!G32="ME"),BankCalc!A32&",","")&IF(AND(BankCalc!W33=1,BankCalc!G33="ME"),BankCalc!A33&",","")&IF(AND(BankCalc!W34=1,BankCalc!G34="ME"),BankCalc!A34&",","")&IF(AND(BankCalc!W35=1,BankCalc!G35="ME"),BankCalc!A35&",","")&IF(AND(BankCalc!W36=1,BankCalc!G36="ME"),BankCalc!A36&",","")&IF(AND(BankCalc!W37=1,BankCalc!G37="ME"),BankCalc!A37&",","")&IF(AND(BankCalc!W38=1,BankCalc!G38="ME"),BankCalc!A38&",","")&IF(AND(BankCalc!W39=1,BankCalc!G39="ME"),BankCalc!A39&",","")&IF(AND(BankCalc!W40=1,BankCalc!G40="ME"),BankCalc!A40&",","")&IF(AND(BankCalc!W41=1,BankCalc!G41="ME"),BankCalc!A41&",","")&IF(AND(BankCalc!W42=1,BankCalc!G42="ME"),BankCalc!A42&",","")&IF(AND(BankCalc!W43=1,BankCalc!G43="ME"),BankCalc!A43&",","")&IF(AND(BankCalc!W44=1,BankCalc!G44="ME"),BankCalc!A44&",","")&IF(AND(BankCalc!W45=1,BankCalc!G45="ME"),BankCalc!A45&",","")&IF(AND(BankCalc!W46=1,BankCalc!G46="ME"),BankCalc!A46&",","")&IF(AND(BankCalc!W47=1,BankCalc!G47="ME"),BankCalc!A47&",","")&IF(AND(BankCalc!W48=1,BankCalc!G48="ME"),BankCalc!A48&",","")&IF(AND(BankCalc!W49=1,BankCalc!G49="ME"),BankCalc!A49&",","")&IF(AND(BankCalc!W50=1,BankCalc!G50="ME"),BankCalc!A50&",","")&IF(AND(BankCalc!W51=1,BankCalc!G51="ME"),BankCalc!A51&",","")&IF(AND(BankCalc!W52=1,BankCalc!G52="ME"),BankCalc!A52&",","")&IF(AND(BankCalc!W53=1,BankCalc!G53="ME"),BankCalc!A53&",","")&IF(AND(BankCalc!W54=1,BankCalc!G54="ME"),BankCalc!A54&",","")&IF(AND(BankCalc!W55=1,BankCalc!G55="ME"),BankCalc!A55&",",""),"") | Q3: =IF(WF_MODEL_VALID,IF(AND(BankCalc!X2=1,BankCalc!F2="ME"),BankCalc!A2&",","")&IF(AND(BankCalc!X3=1,BankCalc!F3="ME"),BankCalc!A3&",","")&IF(AND(BankCalc!X4=1,BankCalc!F4="ME"),BankCalc!A4&",","")&IF(AND(BankCalc!X5=1,BankCalc!F5="ME"),BankCalc!A5&",","")&IF(AND(BankCalc!X6=1,BankCalc!F6="ME"),BankCalc!A6&",","")&IF(AND(BankCalc!X7=1,BankCalc!F7="ME"),BankCalc!A7&",","")&IF(AND(BankCalc!X8=1,BankCalc!F8="ME"),BankCalc!A8&",","")&IF(AND(BankCalc!X9=1,BankCalc!F9="ME"),BankCalc!A9&",","")&IF(AND(BankCalc!X10=1,BankCalc!F10="ME"),BankCalc!A10&",","")&IF(AND(BankCalc!X11=1,BankCalc!F11="ME"),BankCalc!A11&",","")&IF(AND(BankCalc!X12=1,BankCalc!F12="ME"),BankCalc!A12&",","")&IF(AND(BankCalc!X13=1,BankCalc!F13="ME"),BankCalc!A13&",","")&IF(AND(BankCalc!X14=1,BankCalc!F14="ME"),BankCalc!A14&",","")&IF(AND(BankCalc!X15=1,BankCalc!F15="ME"),BankCalc!A15&",","")&IF(AND(BankCalc!X16=1,BankCalc!F16="ME"),BankCalc!A16&",","")&IF(AND(BankCalc!X17=1,BankCalc!F17="ME"),BankCalc!A17&",","")&IF(AND(BankCalc!X18=1,BankCalc!F18="ME"),BankCalc!A18&",","")&IF(AND(BankCalc!X19=1,BankCalc!F19="ME"),BankCalc!A19&",","")&IF(AND(BankCalc!X20=1,BankCalc!F20="ME"),BankCalc!A20&",","")&IF(AND(BankCalc!X21=1,BankCalc!F21="ME"),BankCalc!A21&",","")&IF(AND(BankCalc!X22=1,BankCalc!F22="ME"),BankCalc!A22&",","")&IF(AND(BankCalc!X23=1,BankCalc!F23="ME"),BankCalc!A23&",","")&IF(AND(BankCalc!X24=1,BankCalc!F24="ME"),BankCalc!A24&",","")&IF(AND(BankCalc!X25=1,BankCalc!F25="ME"),BankCalc!A25&",","")&IF(AND(BankCalc!X26=1,BankCalc!F26="ME"),BankCalc!A26&",","")&IF(AND(BankCalc!X27=1,BankCalc!F27="ME"),BankCalc!A27&",","")&IF(AND(BankCalc!X28=1,BankCalc!F28="ME"),BankCalc!A28&",","")&IF(AND(BankCalc!X29=1,BankCalc!F29="ME"),BankCalc!A29&",","")&IF(AND(BankCalc!X30=1,BankCalc!F30="ME"),BankCalc!A30&",","")&IF(AND(BankCalc!X31=1,BankCalc!F31="ME"),BankCalc!A31&",","")&IF(AND(BankCalc!X32=1,BankCalc!F32="ME"),BankCalc!A32&",","")&IF(AND(BankCalc!X33=1,BankCalc!F33="ME"),BankCalc!A33&",","")&IF(AND(BankCalc!X34=1,BankCalc!F34="ME"),BankCalc!A34&",","")&IF(AND(BankCalc!X35=1,BankCalc!F35="ME"),BankCalc!A35&",","")&IF(AND(BankCalc!X36=1,BankCalc!F36="ME"),BankCalc!A36&",","")&IF(AND(BankCalc!X37=1,BankCalc!F37="ME"),BankCalc!A37&",","")&IF(AND(BankCalc!X38=1,BankCalc!F38="ME"),BankCalc!A38&",","")&IF(AND(BankCalc!X39=1,BankCalc!F39="ME"),BankCalc!A39&",","")&IF(AND(BankCalc!X40=1,BankCalc!F40="ME"),BankCalc!A40&",","")&IF(AND(BankCalc!X41=1,BankCalc!F41="ME"),BankCalc!A41&",","")&IF(AND(BankCalc!X42=1,BankCalc!F42="ME"),BankCalc!A42&",","")&IF(AND(BankCalc!X43=1,BankCalc!F43="ME"),BankCalc!A43&",","")&IF(AND(BankCalc!X44=1,BankCalc!F44="ME"),BankCalc!A44&",","")&IF(AND(BankCalc!X45=1,BankCalc!F45="ME"),BankCalc!A45&",","")&IF(AND(BankCalc!X46=1,BankCalc!F46="ME"),BankCalc!A46&",","")&IF(AND(BankCalc!X47=1,BankCalc!F47="ME"),BankCalc!A47&",","")&IF(AND(BankCalc!X48=1,BankCalc!F48="ME"),BankCalc!A48&",","")&IF(AND(BankCalc!X49=1,BankCalc!F49="ME"),BankCalc!A49&",","")&IF(AND(BankCalc!X50=1,BankCalc!F50="ME"),BankCalc!A50&",","")&IF(AND(BankCalc!X51=1,BankCalc!F51="ME"),BankCalc!A51&",","")&IF(AND(BankCalc!X52=1,BankCalc!F52="ME"),BankCalc!A52&",","")&IF(AND(BankCalc!X53=1,BankCalc!F53="ME"),BankCalc!A53&",","")&IF(AND(BankCalc!X54=1,BankCalc!F54="ME"),BankCalc!A54&",","")&IF(AND(BankCalc!X55=1,BankCalc!F55="ME"),BankCalc!A55&",",""),"") -> 17748,
A4: NH | B4: =IF(WF_MODEL_VALID,SUMIF(BankCalc!$F$2:$F$55,"NH",BankCalc!$D$2:$D$55),"") -> 19 | C4: =IF(WF_MODEL_VALID,SUMIF(BankCalc!$G$2:$G$55,"NH",BankCalc!$E$2:$E$55),"") -> 18 | D4: =IF(WF_MODEL_VALID,SUMIF(BankCalc!$G$2:$G$55,"NH",BankCalc!$N$2:$N$55),"") -> 18 | E4: =IF(WF_MODEL_VALID,IFERROR(100*SUMIFS(RawFinancials!$AB$2:$AB$747,RawFinancials!$W$2:$W$747,WF_START_PERIOD,RawFinancials!$AA$2:$AA$747,1,RawFinancials!$Z$2:$Z$747,"NH")/SUMIFS(RawFinancials!$B$2:$B$747,RawFinancials!$W$2:$W$747,WF_START_PERIOD,RawFinancials!$AA$2:$AA$747,1,RawFinancials!$Z$2:$Z$747,"NH"),""),"") -> 0.36509033 | F4: =IF(WF_MODEL_VALID,IFERROR(100*SUMIFS(RawFinancials!$AB$2:$AB$747,RawFinancials!$W$2:$W$747,WF_END_PERIOD,RawFinancials!$AA$2:$AA$747,1,RawFinancials!$Z$2:$Z$747,"NH")/SUMIFS(RawFinancials!$B$2:$B$747,RawFinancials!$W$2:$W$747,WF_END_PERIOD,RawFinancials!$AA$2:$AA$747,1,RawFinancials!$Z$2:$Z$747,"NH"),""),"") -> 0.30595397 | G4: =IF(WF_MODEL_VALID,F4-E4,"") -> -0.059136359 | H4: =IF(WF_MODEL_VALID,IFERROR(SUMIF(BankCalc!$G$2:$G$55,"NH",BankCalc!$P$2:$P$55)/SUMIF(BankCalc!$G$2:$G$55,"NH",BankCalc!$O$2:$O$55),""),"") -> 0.37186264 | I4: =IF(WF_MODEL_VALID,IFERROR(SUMIF(BankCalc!$G$2:$G$55,"NH",BankCalc!$Q$2:$Q$55)/SUMIF(BankCalc!$G$2:$G$55,"NH",BankCalc!$O$2:$O$55),""),"") -> 0.29904611 | J4: =IF(WF_MODEL_VALID,I4-H4,"") -> -0.072816535 | K4: =IF(WF_MODEL_VALID,G4-J4,"") -> 0.013680176 | L4: =IF(WF_MODEL_VALID,SUMIF(BankCalc!$G$2:$G$55,"NH",BankCalc!$W$2:$W$55),"") -> 0 | M4: =IF(WF_MODEL_VALID,SUMIF(BankCalc!$F$2:$F$55,"NH",BankCalc!$X$2:$X$55),"") -> 1 | N4: =IF(WF_MODEL_VALID,SUMIF(BankCalc!$G$2:$G$55,"NH",BankCalc!$Y$2:$Y$55),"") -> 0 | O4: =IF(WF_MODEL_VALID,SUMIF(BankCalc!$F$2:$F$55,"NH",BankCalc!$Z$2:$Z$55),"") -> 1270696 | P4: =IF(WF_MODEL_VALID,IF(AND(BankCalc!W2=1,BankCalc!G2="NH"),BankCalc!A2&",","")&IF(AND(BankCalc!W3=1,BankCalc!G3="NH"),BankCalc!A3&",","")&IF(AND(BankCalc!W4=1,BankCalc!G4="NH"),BankCalc!A4&",","")&IF(AND(BankCalc!W5=1,BankCalc!G5="NH"),BankCalc!A5&",","")&IF(AND(BankCalc!W6=1,BankCalc!G6="NH"),BankCalc!A6&",","")&IF(AND(BankCalc!W7=1,BankCalc!G7="NH"),BankCalc!A7&",","")&IF(AND(BankCalc!W8=1,BankCalc!G8="NH"),BankCalc!A8&",","")&IF(AND(BankCalc!W9=1,BankCalc!G9="NH"),BankCalc!A9&",","")&IF(AND(BankCalc!W10=1,BankCalc!G10="NH"),BankCalc!A10&",","")&IF(AND(BankCalc!W11=1,BankCalc!G11="NH"),BankCalc!A11&",","")&IF(AND(BankCalc!W12=1,BankCalc!G12="NH"),BankCalc!A12&",","")&IF(AND(BankCalc!W13=1,BankCalc!G13="NH"),BankCalc!A13&",","")&IF(AND(BankCalc!W14=1,BankCalc!G14="NH"),BankCalc!A14&",","")&IF(AND(BankCalc!W15=1,BankCalc!G15="NH"),BankCalc!A15&",","")&IF(AND(BankCalc!W16=1,BankCalc!G16="NH"),BankCalc!A16&",","")&IF(AND(BankCalc!W17=1,BankCalc!G17="NH"),BankCalc!A17&",","")&IF(AND(BankCalc!W18=1,BankCalc!G18="NH"),BankCalc!A18&",","")&IF(AND(BankCalc!W19=1,BankCalc!G19="NH"),BankCalc!A19&",","")&IF(AND(BankCalc!W20=1,BankCalc!G20="NH"),BankCalc!A20&",","")&IF(AND(BankCalc!W21=1,BankCalc!G21="NH"),BankCalc!A21&",","")&IF(AND(BankCalc!W22=1,BankCalc!G22="NH"),BankCalc!A22&",","")&IF(AND(BankCalc!W23=1,BankCalc!G23="NH"),BankCalc!A23&",","")&IF(AND(BankCalc!W24=1,BankCalc!G24="NH"),BankCalc!A24&",","")&IF(AND(BankCalc!W25=1,BankCalc!G25="NH"),BankCalc!A25&",","")&IF(AND(BankCalc!W26=1,BankCalc!G26="NH"),BankCalc!A26&",","")&IF(AND(BankCalc!W27=1,BankCalc!G27="NH"),BankCalc!A27&",","")&IF(AND(BankCalc!W28=1,BankCalc!G28="NH"),BankCalc!A28&",","")&IF(AND(BankCalc!W29=1,BankCalc!G29="NH"),BankCalc!A29&",","")&IF(AND(BankCalc!W30=1,BankCalc!G30="NH"),BankCalc!A30&",","")&IF(AND(BankCalc!W31=1,BankCalc!G31="NH"),BankCalc!A31&",","")&IF(AND(BankCalc!W32=1,BankCalc!G32="NH"),BankCalc!A32&",","")&IF(AND(BankCalc!W33=1,BankCalc!G33="NH"),BankCalc!A33&",","")&IF(AND(BankCalc!W34=1,BankCalc!G34="NH"),BankCalc!A34&",","")&IF(AND(BankCalc!W35=1,BankCalc!G35="NH"),BankCalc!A35&",","")&IF(AND(BankCalc!W36=1,BankCalc!G36="NH"),BankCalc!A36&",","")&IF(AND(BankCalc!W37=1,BankCalc!G37="NH"),BankCalc!A37&",","")&IF(AND(BankCalc!W38=1,BankCalc!G38="NH"),BankCalc!A38&",","")&IF(AND(BankCalc!W39=1,BankCalc!G39="NH"),BankCalc!A39&",","")&IF(AND(BankCalc!W40=1,BankCalc!G40="NH"),BankCalc!A40&",","")&IF(AND(BankCalc!W41=1,BankCalc!G41="NH"),BankCalc!A41&",","")&IF(AND(BankCalc!W42=1,BankCalc!G42="NH"),BankCalc!A42&",","")&IF(AND(BankCalc!W43=1,BankCalc!G43="NH"),BankCalc!A43&",","")&IF(AND(BankCalc!W44=1,BankCalc!G44="NH"),BankCalc!A44&",","")&IF(AND(BankCalc!W45=1,BankCalc!G45="NH"),BankCalc!A45&",","")&IF(AND(BankCalc!W46=1,BankCalc!G46="NH"),BankCalc!A46&",","")&IF(AND(BankCalc!W47=1,BankCalc!G47="NH"),BankCalc!A47&",","")&IF(AND(BankCalc!W48=1,BankCalc!G48="NH"),BankCalc!A48&",","")&IF(AND(BankCalc!W49=1,BankCalc!G49="NH"),BankCalc!A49&",","")&IF(AND(BankCalc!W50=1,BankCalc!G50="NH"),BankCalc!A50&",","")&IF(AND(BankCalc!W51=1,BankCalc!G51="NH"),BankCalc!A51&",","")&IF(AND(BankCalc!W52=1,BankCalc!G52="NH"),BankCalc!A52&",","")&IF(AND(BankCalc!W53=1,BankCalc!G53="NH"),BankCalc!A53&",","")&IF(AND(BankCalc!W54=1,BankCalc!G54="NH"),BankCalc!A54&",","")&IF(AND(BankCalc!W55=1,BankCalc!G55="NH"),BankCalc!A55&",",""),"") | Q4: =IF(WF_MODEL_VALID,IF(AND(BankCalc!X2=1,BankCalc!F2="NH"),BankCalc!A2&",","")&IF(AND(BankCalc!X3=1,BankCalc!F3="NH"),BankCalc!A3&",","")&IF(AND(BankCalc!X4=1,BankCalc!F4="NH"),BankCalc!A4&",","")&IF(AND(BankCalc!X5=1,BankCalc!F5="NH"),BankCalc!A5&",","")&IF(AND(BankCalc!X6=1,BankCalc!F6="NH"),BankCalc!A6&",","")&IF(AND(BankCalc!X7=1,BankCalc!F7="NH"),BankCalc!A7&",","")&IF(AND(BankCalc!X8=1,BankCalc!F8="NH"),BankCalc!A8&",","")&IF(AND(BankCalc!X9=1,BankCalc!F9="NH"),BankCalc!A9&",","")&IF(AND(BankCalc!X10=1,BankCalc!F10="NH"),BankCalc!A10&",","")&IF(AND(BankCalc!X11=1,BankCalc!F11="NH"),BankCalc!A11&",","")&IF(AND(BankCalc!X12=1,BankCalc!F12="NH"),BankCalc!A12&",","")&IF(AND(BankCalc!X13=1,BankCalc!F13="NH"),BankCalc!A13&",","")&IF(AND(BankCalc!X14=1,BankCalc!F14="NH"),BankCalc!A14&",","")&IF(AND(BankCalc!X15=1,BankCalc!F15="NH"),BankCalc!A15&",","")&IF(AND(BankCalc!X16=1,BankCalc!F16="NH"),BankCalc!A16&",","")&IF(AND(BankCalc!X17=1,BankCalc!F17="NH"),BankCalc!A17&",","")&IF(AND(BankCalc!X18=1,BankCalc!F18="NH"),BankCalc!A18&",","")&IF(AND(BankCalc!X19=1,BankCalc!F19="NH"),BankCalc!A19&",","")&IF(AND(BankCalc!X20=1,BankCalc!F20="NH"),BankCalc!A20&",","")&IF(AND(BankCalc!X21=1,BankCalc!F21="NH"),BankCalc!A21&",","")&IF(AND(BankCalc!X22=1,BankCalc!F22="NH"),BankCalc!A22&",","")&IF(AND(BankCalc!X23=1,BankCalc!F23="NH"),BankCalc!A23&",","")&IF(AND(BankCalc!X24=1,BankCalc!F24="NH"),BankCalc!A24&",","")&IF(AND(BankCalc!X25=1,BankCalc!F25="NH"),BankCalc!A25&",","")&IF(AND(BankCalc!X26=1,BankCalc!F26="NH"),BankCalc!A26&",","")&IF(AND(BankCalc!X27=1,BankCalc!F27="NH"),BankCalc!A27&",","")&IF(AND(BankCalc!X28=1,BankCalc!F28="NH"),BankCalc!A28&",","")&IF(AND(BankCalc!X29=1,BankCalc!F29="NH"),BankCalc!A29&",","")&IF(AND(BankCalc!X30=1,BankCalc!F30="NH"),BankCalc!A30&",","")&IF(AND(BankCalc!X31=1,BankCalc!F31="NH"),BankCalc!A31&",","")&IF(AND(BankCalc!X32=1,BankCalc!F32="NH"),BankCalc!A32&",","")&IF(AND(BankCalc!X33=1,BankCalc!F33="NH"),BankCalc!A33&",","")&IF(AND(BankCalc!X34=1,BankCalc!F34="NH"),BankCalc!A34&",","")&IF(AND(BankCalc!X35=1,BankCalc!F35="NH"),BankCalc!A35&",","")&IF(AND(BankCalc!X36=1,BankCalc!F36="NH"),BankCalc!A36&",","")&IF(AND(BankCalc!X37=1,BankCalc!F37="NH"),BankCalc!A37&",","")&IF(AND(BankCalc!X38=1,BankCalc!F38="NH"),BankCalc!A38&",","")&IF(AND(BankCalc!X39=1,BankCalc!F39="NH"),BankCalc!A39&",","")&IF(AND(BankCalc!X40=1,BankCalc!F40="NH"),BankCalc!A40&",","")&IF(AND(BankCalc!X41=1,BankCalc!F41="NH"),BankCalc!A41&",","")&IF(AND(BankCalc!X42=1,BankCalc!F42="NH"),BankCalc!A42&",","")&IF(AND(BankCalc!X43=1,BankCalc!F43="NH"),BankCalc!A43&",","")&IF(AND(BankCalc!X44=1,BankCalc!F44="NH"),BankCalc!A44&",","")&IF(AND(BankCalc!X45=1,BankCalc!F45="NH"),BankCalc!A45&",","")&IF(AND(BankCalc!X46=1,BankCalc!F46="NH"),BankCalc!A46&",","")&IF(AND(BankCalc!X47=1,BankCalc!F47="NH"),BankCalc!A47&",","")&IF(AND(BankCalc!X48=1,BankCalc!F48="NH"),BankCalc!A48&",","")&IF(AND(BankCalc!X49=1,BankCalc!F49="NH"),BankCalc!A49&",","")&IF(AND(BankCalc!X50=1,BankCalc!F50="NH"),BankCalc!A50&",","")&IF(AND(BankCalc!X51=1,BankCalc!F51="NH"),BankCalc!A51&",","")&IF(AND(BankCalc!X52=1,BankCalc!F52="NH"),BankCalc!A52&",","")&IF(AND(BankCalc!X53=1,BankCalc!F53="NH"),BankCalc!A53&",","")&IF(AND(BankCalc!X54=1,BankCalc!F54="NH"),BankCalc!A54&",","")&IF(AND(BankCalc!X55=1,BankCalc!F55="NH"),BankCalc!A55&",",""),"") -> 14240,
A5: VT | B5: =IF(WF_MODEL_VALID,SUMIF(BankCalc!$F$2:$F$55,"VT",BankCalc!$D$2:$D$55),"") -> 12 | C5: =IF(WF_MODEL_VALID,SUMIF(BankCalc!$G$2:$G$55,"VT",BankCalc!$E$2:$E$55),"") -> 12 | D5: =IF(WF_MODEL_VALID,SUMIF(BankCalc!$G$2:$G$55,"VT",BankCalc!$N$2:$N$55),"") -> 12 | E5: =IF(WF_MODEL_VALID,IFERROR(100*SUMIFS(RawFinancials!$AB$2:$AB$747,RawFinancials!$W$2:$W$747,WF_START_PERIOD,RawFinancials!$AA$2:$AA$747,1,RawFinancials!$Z$2:$Z$747,"VT")/SUMIFS(RawFinancials!$B$2:$B$747,RawFinancials!$W$2:$W$747,WF_START_PERIOD,RawFinancials!$AA$2:$AA$747,1,RawFinancials!$Z$2:$Z$747,"VT"),""),"") -> 0.33860386 | F5: =IF(WF_MODEL_VALID,IFERROR(100*SUMIFS(RawFinancials!$AB$2:$AB$747,RawFinancials!$W$2:$W$747,WF_END_PERIOD,RawFinancials!$AA$2:$AA$747,1,RawFinancials!$Z$2:$Z$747,"VT")/SUMIFS(RawFinancials!$B$2:$B$747,RawFinancials!$W$2:$W$747,WF_END_PERIOD,RawFinancials!$AA$2:$AA$747,1,RawFinancials!$Z$2:$Z$747,"VT"),""),"") -> 0.49473123 | G5: =IF(WF_MODEL_VALID,F5-E5,"") -> 0.15612738 | H5: =IF(WF_MODEL_VALID,IFERROR(SUMIF(BankCalc!$G$2:$G$55,"VT",BankCalc!$P$2:$P$55)/SUMIF(BankCalc!$G$2:$G$55,"VT",BankCalc!$O$2:$O$55),""),"") -> 0.33860386 | I5: =IF(WF_MODEL_VALID,IFERROR(SUMIF(BankCalc!$G$2:$G$55,"VT",BankCalc!$Q$2:$Q$55)/SUMIF(BankCalc!$G$2:$G$55,"VT",BankCalc!$O$2:$O$55),""),"") -> 0.49541724 | J5: =IF(WF_MODEL_VALID,I5-H5,"") -> 0.15681339 | K5: =IF(WF_MODEL_VALID,G5-J5,"") -> -0.00068601043 | L5: =IF(WF_MODEL_VALID,SUMIF(BankCalc!$G$2:$G$55,"VT",BankCalc!$W$2:$W$55),"") -> 0 | M5: =IF(WF_MODEL_VALID,SUMIF(BankCalc!$F$2:$F$55,"VT",BankCalc!$X$2:$X$55),"") -> 0 | N5: =IF(WF_MODEL_VALID,SUMIF(BankCalc!$G$2:$G$55,"VT",BankCalc!$Y$2:$Y$55),"") -> 0 | O5: =IF(WF_MODEL_VALID,SUMIF(BankCalc!$F$2:$F$55,"VT",BankCalc!$Z$2:$Z$55),"") -> 0 | P5: =IF(WF_MODEL_VALID,IF(AND(BankCalc!W2=1,BankCalc!G2="VT"),BankCalc!A2&",","")&IF(AND(BankCalc!W3=1,BankCalc!G3="VT"),BankCalc!A3&",","")&IF(AND(BankCalc!W4=1,BankCalc!G4="VT"),BankCalc!A4&",","")&IF(AND(BankCalc!W5=1,BankCalc!G5="VT"),BankCalc!A5&",","")&IF(AND(BankCalc!W6=1,BankCalc!G6="VT"),BankCalc!A6&",","")&IF(AND(BankCalc!W7=1,BankCalc!G7="VT"),BankCalc!A7&",","")&IF(AND(BankCalc!W8=1,BankCalc!G8="VT"),BankCalc!A8&",","")&IF(AND(BankCalc!W9=1,BankCalc!G9="VT"),BankCalc!A9&",","")&IF(AND(BankCalc!W10=1,BankCalc!G10="VT"),BankCalc!A10&",","")&IF(AND(BankCalc!W11=1,BankCalc!G11="VT"),BankCalc!A11&",","")&IF(AND(BankCalc!W12=1,BankCalc!G12="VT"),BankCalc!A12&",","")&IF(AND(BankCalc!W13=1,BankCalc!G13="VT"),BankCalc!A13&",","")&IF(AND(BankCalc!W14=1,BankCalc!G14="VT"),BankCalc!A14&",","")&IF(AND(BankCalc!W15=1,BankCalc!G15="VT"),BankCalc!A15&",","")&IF(AND(BankCalc!W16=1,BankCalc!G16="VT"),BankCalc!A16&",","")&IF(AND(BankCalc!W17=1,BankCalc!G17="VT"),BankCalc!A17&",","")&IF(AND(BankCalc!W18=1,BankCalc!G18="VT"),BankCalc!A18&",","")&IF(AND(BankCalc!W19=1,BankCalc!G19="VT"),BankCalc!A19&",","")&IF(AND(BankCalc!W20=1,BankCalc!G20="VT"),BankCalc!A20&",","")&IF(AND(BankCalc!W21=1,BankCalc!G21="VT"),BankCalc!A21&",","")&IF(AND(BankCalc!W22=1,BankCalc!G22="VT"),BankCalc!A22&",","")&IF(AND(BankCalc!W23=1,BankCalc!G23="VT"),BankCalc!A23&",","")&IF(AND(BankCalc!W24=1,BankCalc!G24="VT"),BankCalc!A24&",","")&IF(AND(BankCalc!W25=1,BankCalc!G25="VT"),BankCalc!A25&",","")&IF(AND(BankCalc!W26=1,BankCalc!G26="VT"),BankCalc!A26&",","")&IF(AND(BankCalc!W27=1,BankCalc!G27="VT"),BankCalc!A27&",","")&IF(AND(BankCalc!W28=1,BankCalc!G28="VT"),BankCalc!A28&",","")&IF(AND(BankCalc!W29=1,BankCalc!G29="VT"),BankCalc!A29&",","")&IF(AND(BankCalc!W30=1,BankCalc!G30="VT"),BankCalc!A30&",","")&IF(AND(BankCalc!W31=1,BankCalc!G31="VT"),BankCalc!A31&",","")&IF(AND(BankCalc!W32=1,BankCalc!G32="VT"),BankCalc!A32&",","")&IF(AND(BankCalc!W33=1,BankCalc!G33="VT"),BankCalc!A33&",","")&IF(AND(BankCalc!W34=1,BankCalc!G34="VT"),BankCalc!A34&",","")&IF(AND(BankCalc!W35=1,BankCalc!G35="VT"),BankCalc!A35&",","")&IF(AND(BankCalc!W36=1,BankCalc!G36="VT"),BankCalc!A36&",","")&IF(AND(BankCalc!W37=1,BankCalc!G37="VT"),BankCalc!A37&",","")&IF(AND(BankCalc!W38=1,BankCalc!G38="VT"),BankCalc!A38&",","")&IF(AND(BankCalc!W39=1,BankCalc!G39="VT"),BankCalc!A39&",","")&IF(AND(BankCalc!W40=1,BankCalc!G40="VT"),BankCalc!A40&",","")&IF(AND(BankCalc!W41=1,BankCalc!G41="VT"),BankCalc!A41&",","")&IF(AND(BankCalc!W42=1,BankCalc!G42="VT"),BankCalc!A42&",","")&IF(AND(BankCalc!W43=1,BankCalc!G43="VT"),BankCalc!A43&",","")&IF(AND(BankCalc!W44=1,BankCalc!G44="VT"),BankCalc!A44&",","")&IF(AND(BankCalc!W45=1,BankCalc!G45="VT"),BankCalc!A45&",","")&IF(AND(BankCalc!W46=1,BankCalc!G46="VT"),BankCalc!A46&",","")&IF(AND(BankCalc!W47=1,BankCalc!G47="VT"),BankCalc!A47&",","")&IF(AND(BankCalc!W48=1,BankCalc!G48="VT"),BankCalc!A48&",","")&IF(AND(BankCalc!W49=1,BankCalc!G49="VT"),BankCalc!A49&",","")&IF(AND(BankCalc!W50=1,BankCalc!G50="VT"),BankCalc!A50&",","")&IF(AND(BankCalc!W51=1,BankCalc!G51="VT"),BankCalc!A51&",","")&IF(AND(BankCalc!W52=1,BankCalc!G52="VT"),BankCalc!A52&",","")&IF(AND(BankCalc!W53=1,BankCalc!G53="VT"),BankCalc!A53&",","")&IF(AND(BankCalc!W54=1,BankCalc!G54="VT"),BankCalc!A54&",","")&IF(AND(BankCalc!W55=1,BankCalc!G55="VT"),BankCalc!A55&",",""),"") | Q5: =IF(WF_MODEL_VALID,IF(AND(BankCalc!X2=1,BankCalc!F2="VT"),BankCalc!A2&",","")&IF(AND(BankCalc!X3=1,BankCalc!F3="VT"),BankCalc!A3&",","")&IF(AND(BankCalc!X4=1,BankCalc!F4="VT"),BankCalc!A4&",","")&IF(AND(BankCalc!X5=1,BankCalc!F5="VT"),BankCalc!A5&",","")&IF(AND(BankCalc!X6=1,BankCalc!F6="VT"),BankCalc!A6&",","")&IF(AND(BankCalc!X7=1,BankCalc!F7="VT"),BankCalc!A7&",","")&IF(AND(BankCalc!X8=1,BankCalc!F8="VT"),BankCalc!A8&",","")&IF(AND(BankCalc!X9=1,BankCalc!F9="VT"),BankCalc!A9&",","")&IF(AND(BankCalc!X10=1,BankCalc!F10="VT"),BankCalc!A10&",","")&IF(AND(BankCalc!X11=1,BankCalc!F11="VT"),BankCalc!A11&",","")&IF(AND(BankCalc!X12=1,BankCalc!F12="VT"),BankCalc!A12&",","")&IF(AND(BankCalc!X13=1,BankCalc!F13="VT"),BankCalc!A13&",","")&IF(AND(BankCalc!X14=1,BankCalc!F14="VT"),BankCalc!A14&",","")&IF(AND(BankCalc!X15=1,BankCalc!F15="VT"),BankCalc!A15&",","")&IF(AND(BankCalc!X16=1,BankCalc!F16="VT"),BankCalc!A16&",","")&IF(AND(BankCalc!X17=1,BankCalc!F17="VT"),BankCalc!A17&",","")&IF(AND(BankCalc!X18=1,BankCalc!F18="VT"),BankCalc!A18&",","")&IF(AND(BankCalc!X19=1,BankCalc!F19="VT"),BankCalc!A19&",","")&IF(AND(BankCalc!X20=1,BankCalc!F20="VT"),BankCalc!A20&",","")&IF(AND(BankCalc!X21=1,BankCalc!F21="VT"),BankCalc!A21&",","")&IF(AND(BankCalc!X22=1,BankCalc!F22="VT"),BankCalc!A22&",","")&IF(AND(BankCalc!X23=1,BankCalc!F23="VT"),BankCalc!A23&",","")&IF(AND(BankCalc!X24=1,BankCalc!F24="VT"),BankCalc!A24&",","")&IF(AND(BankCalc!X25=1,BankCalc!F25="VT"),BankCalc!A25&",","")&IF(AND(BankCalc!X26=1,BankCalc!F26="VT"),BankCalc!A26&",","")&IF(AND(BankCalc!X27=1,BankCalc!F27="VT"),BankCalc!A27&",","")&IF(AND(BankCalc!X28=1,BankCalc!F28="VT"),BankCalc!A28&",","")&IF(AND(BankCalc!X29=1,BankCalc!F29="VT"),BankCalc!A29&",","")&IF(AND(BankCalc!X30=1,BankCalc!F30="VT"),BankCalc!A30&",","")&IF(AND(BankCalc!X31=1,BankCalc!F31="VT"),BankCalc!A31&",","")&IF(AND(BankCalc!X32=1,BankCalc!F32="VT"),BankCalc!A32&",","")&IF(AND(BankCalc!X33=1,BankCalc!F33="VT"),BankCalc!A33&",","")&IF(AND(BankCalc!X34=1,BankCalc!F34="VT"),BankCalc!A34&",","")&IF(AND(BankCalc!X35=1,BankCalc!F35="VT"),BankCalc!A35&",","")&IF(AND(BankCalc!X36=1,BankCalc!F36="VT"),BankCalc!A36&",","")&IF(AND(BankCalc!X37=1,BankCalc!F37="VT"),BankCalc!A37&",","")&IF(AND(BankCalc!X38=1,BankCalc!F38="VT"),BankCalc!A38&",","")&IF(AND(BankCalc!X39=1,BankCalc!F39="VT"),BankCalc!A39&",","")&IF(AND(BankCalc!X40=1,BankCalc!F40="VT"),BankCalc!A40&",","")&IF(AND(BankCalc!X41=1,BankCalc!F41="VT"),BankCalc!A41&",","")&IF(AND(BankCalc!X42=1,BankCalc!F42="VT"),BankCalc!A42&",","")&IF(AND(BankCalc!X43=1,BankCalc!F43="VT"),BankCalc!A43&",","")&IF(AND(BankCalc!X44=1,BankCalc!F44="VT"),BankCalc!A44&",","")&IF(AND(BankCalc!X45=1,BankCalc!F45="VT"),BankCalc!A45&",","")&IF(AND(BankCalc!X46=1,BankCalc!F46="VT"),BankCalc!A46&",","")&IF(AND(BankCalc!X47=1,BankCalc!F47="VT"),BankCalc!A47&",","")&IF(AND(BankCalc!X48=1,BankCalc!F48="VT"),BankCalc!A48&",","")&IF(AND(BankCalc!X49=1,BankCalc!F49="VT"),BankCalc!A49&",","")&IF(AND(BankCalc!X50=1,BankCalc!F50="VT"),BankCalc!A50&",","")&IF(AND(BankCalc!X51=1,BankCalc!F51="VT"),BankCalc!A51&",","")&IF(AND(BankCalc!X52=1,BankCalc!F52="VT"),BankCalc!A52&",","")&IF(AND(BankCalc!X53=1,BankCalc!F53="VT"),BankCalc!A53&",","")&IF(AND(BankCalc!X54=1,BankCalc!F54="VT"),BankCalc!A54&",","")&IF(AND(BankCalc!X55=1,BankCalc!F55="VT"),BankCalc!A55&",",""),"")

Sheet PeerQuarter
A1: REPDTE | B1: state | C1: banks | D1: ASSET_thousand | E1: proxy_numerator_thousand | F1: proxy_pct
A2: 20220331 | B2: ALL | C2: =COUNTIFS(RawFinancials!$W$2:$W$747,A2,RawFinancials!$AA$2:$AA$747,1) -> 51 | D2: =SUMIFS(RawFinancials!$B$2:$B$747,RawFinancials!$W$2:$W$747,A2,RawFinancials!$AA$2:$AA$747,1) -> 59852474 | E2: =SUMIFS(RawFinancials!$AB$2:$AB$747,RawFinancials!$W$2:$W$747,A2,RawFinancials!$AA$2:$AA$747,1) -> 136841 | F2: =IF(D2>0,100*E2/D2,"") -> 0.22863048
A3: 20220331 | B3: ME | C3: =COUNTIFS(RawFinancials!$W$2:$W$747,A3,RawFinancials!$AA$2:$AA$747,1,RawFinancials!$Z$2:$Z$747,B3) -> 23 | D3: =SUMIFS(RawFinancials!$B$2:$B$747,RawFinancials!$W$2:$W$747,A3,RawFinancials!$AA$2:$AA$747,1,RawFinancials!$Z$2:$Z$747,B3) -> 37324757 | E3: =SUMIFS(RawFinancials!$AB$2:$AB$747,RawFinancials!$W$2:$W$747,A3,RawFinancials!$AA$2:$AA$747,1,RawFinancials!$Z$2:$Z$747,B3) -> 79744 | F3: =IF(D3>0,100*E3/D3,"") -> 0.21364908
A4: 20220331 | B4: NH | C4: =COUNTIFS(RawFinancials!$W$2:$W$747,A4,RawFinancials!$AA$2:$AA$747,1,RawFinancials!$Z$2:$Z$747,B4) -> 17 | D4: =SUMIFS(RawFinancials!$B$2:$B$747,RawFinancials!$W$2:$W$747,A4,RawFinancials!$AA$2:$AA$747,1,RawFinancials!$Z$2:$Z$747,B4) -> 15167858 | E4: =SUMIFS(RawFinancials!$AB$2:$AB$747,RawFinancials!$W$2:$W$747,A4,RawFinancials!$AA$2:$AA$747,1,RawFinancials!$Z$2:$Z$747,B4) -> 23673 | F4: =IF(D4>0,100*E4/D4,"") -> 0.15607345
A5: 20220331 | B5: VT | C5: =COUNTIFS(RawFinancials!$W$2:$W$747,A5,RawFinancials!$AA$2:$AA$747,1,RawFinancials!$Z$2:$Z$747,B5) -> 11 | D5: =SUMIFS(RawFinancials!$B$2:$B$747,RawFinancials!$W$2:$W$747,A5,RawFinancials!$AA$2:$AA$747,1,RawFinancials!$Z$2:$Z$747,B5) -> 7359859 | E5: =SUMIFS(RawFinancials!$AB$2:$AB$747,RawFinancials!$W$2:$W$747,A5,RawFinancials!$AA$2:$AA$747,1,RawFinancials!$Z$2:$Z$747,B5) -> 33424 | F5: =IF(D5>0,100*E5/D5,"") -> 0.45413914
A6: 20220630 | B6: ALL | C6: =COUNTIFS(RawFinancials!$W$2:$W$747,A6,RawFinancials!$AA$2:$AA$747,1) -> 52 | D6: =SUMIFS(RawFinancials!$B$2:$B$747,RawFinancials!$W$2:$W$747,A6,RawFinancials!$AA$2:$AA$747,1) -> 60747875 | E6: =SUMIFS(RawFinancials!$AB$2:$AB$747,RawFinancials!$W$2:$W$747,A6,RawFinancials!$AA$2:$AA$747,1) -> 116533 | F6: =IF(D6>0,100*E6/D6,"") -> 0.19183058
A7: 20220630 | B7: ME | C7: =COUNTIFS(RawFinancials!$W$2:$W$747,A7,RawFinancials!$AA$2:$AA$747,1,RawFinancials!$Z$2:$Z$747,B7) -> 23 | D7: =SUMIFS(RawFinancials!$B$2:$B$747,RawFinancials!$W$2:$W$747,A7,RawFinancials!$AA$2:$AA$747,1,RawFinancials!$Z$2:$Z$747,B7) -> 38015500 | E7: =SUMIFS(RawFinancials!$AB$2:$AB$747,RawFinancials!$W$2:$W$747,A7,RawFinancials!$AA$2:$AA$747,1,RawFinancials!$Z$2:$Z$747,B7) -> 66628 | F7: =IF(D7>0,100*E7/D7,"") -> 0.17526535
A8: 20220630 | B8: NH | C8: =COUNTIFS(RawFinancials!$W$2:$W$747,A8,RawFinancials!$AA$2:$AA$747,1,RawFinancials!$Z$2:$Z$747,B8) -> 18 | D8: =SUMIFS(RawFinancials!$B$2:$B$747,RawFinancials!$W$2:$W$747,A8,RawFinancials!$AA$2:$AA$747,1,RawFinancials!$Z$2:$Z$747,B8) -> 15488639 | E8: =SUMIFS(RawFinancials!$AB$2:$AB$747,RawFinancials!$W$2:$W$747,A8,RawFinancials!$AA$2:$AA$747,1,RawFinancials!$Z$2:$Z$747,B8) -> 22048 | F8: =IF(D8>0,100*E8/D8,"") -> 0.1423495
A9: 20220630 | B9: VT | C9: =COUNTIFS(RawFinancials!$W$2:$W$747,A9,RawFinancials!$AA$2:$AA$747,1,RawFinancials!$Z$2:$Z$747,B9) -> 11 | D9: =SUMIFS(RawFinancials!$B$2:$B$747,RawFinancials!$W$2:$W$747,A9,RawFinancials!$AA$2:$AA$747,1,RawFinancials!$Z$2:$Z$747,B9) -> 7243736 | E9: =SUMIFS(RawFinancials!$AB$2:$AB$747,RawFinancials!$W$2:$W$747,A9,RawFinancials!$AA$2:$AA$747,1,RawFinancials!$Z$2:$Z$747,B9) -> 27857 | F9: =IF(D9>0,100*E9/D9,"") -> 0.38456675
A10: 20220930 | B10: ALL | C10: =COUNTIFS(RawFinancials!$W$2:$W$747,A10,RawFinancials!$AA$2:$AA$747,1) -> 53 | D10: =SUMIFS(RawFinancials!$B$2:$B$747,RawFinancials!$W$2:$W$747,A10,RawFinancials!$AA$2:$AA$747,1) -> 62354271 | E10: =SUMIFS(RawFinancials!$AB$2:$AB$747,RawFinancials!$W$2:$W$747,A10,RawFinancials!$AA$2:$AA$747,1) -> 109246 | F10: =IF(D10>0,100*E10/D10,"") -> 0.17520211
A11: 20220930 | B11: ME | C11: =COUNTIFS(RawFinancials!$W$2:$W$747,A11,RawFinancials!$AA$2:$AA$747,1,RawFinancials!$Z$2:$Z$747,B11) -> 23 | D11: =SUMIFS(RawFinancials!$B$2:$B$747,RawFinancials!$W$2:$W$747,A11,RawFinancials!$AA$2:$AA$747,1,RawFinancials!$Z$2:$Z$747,B11) -> 38997566 | E11: =SUMIFS(RawFinancials!$AB$2:$AB$747,RawFinancials!$W$2:$W$747,A11,RawFinancials!$AA$2:$AA$747,1,RawFinancials!$Z$2:$Z$747,B11) -> 58678 | F11: =IF(D11>0,100*E11/D11,"") -> 0.1504658
A12: 20220930 | B12: NH | C12: =COUNTIFS(RawFinancials!$W$2:$W$747,A12,RawFinancials!$AA$2:$AA$747,1,RawFinancials!$Z$2:$Z$747,B12) -> 18 | D12: =SUMIFS(RawFinancials!$B$2:$B$747,RawFinancials!$W$2:$W$747,A12,RawFinancials!$AA$2:$AA$747,1,RawFinancials!$Z$2:$Z$747,B12) -> 15915289 | E12: =SUMIFS(RawFinancials!$AB$2:$AB$747,RawFinancials!$W$2:$W$747,A12,RawFinancials!$AA$2:$AA$747,1,RawFinancials!$Z$2:$Z$747,B12) -> 21146 | F12: =IF(D12>0,100*E12/D12,"") -> 0.13286595
A13: 20220930 | B13: VT | C13: =COUNTIFS(RawFinancials!$W$2:$W$747,A13,RawFinancials!$AA$2:$AA$747,1,RawFinancials!$Z$2:$Z$747,B13) -> 12 | D13: =SUMIFS(RawFinancials!$B$2:$B$747,RawFinancials!$W$2:$W$747,A13,RawFinancials!$AA$2:$AA$747,1,RawFinancials!$Z$2:$Z$747,B13) -> 7441416 | E13: =SUMIFS(RawFinancials!$AB$2:$AB$747,RawFinancials!$W$2:$W$747,A13,RawFinancials!$AA$2:$AA$747,1,RawFinancials!$Z$2:$Z$747,B13) -> 29422 | F13: =IF(D13>0,100*E13/D13,"") -> 0.39538174
A14: 20221231 | B14: ALL | C14: =COUNTIFS(RawFinancials!$W$2:$W$747,A14,RawFinancials!$AA$2:$AA$747,1) -> 54 | D14: =SUMIFS(RawFinancials!$B$2:$B$747,RawFinancials!$W$2:$W$747,A14,RawFinancials!$AA$2:$AA$747,1) -> 64502953 | E14: =SUMIFS(RawFinancials!$AB$2:$AB$747,RawFinancials!$W$2:$W$747,A14,RawFinancials!$AA$2:$AA$747,1) -> 123030 | F14: =IF(D14>0,100*E14/D14,"") -> 0.19073545
A15: 20221231 | B15: ME | C15: =COUNTIFS(RawFinancials!$W$2:$W$747,A15,RawFinancials!$AA$2:$AA$747,1,RawFinancials!$Z$2:$Z$747,B15) -> 23 | D15: =SUMIFS(RawFinancials!$B$2:$B$747,RawFinancials!$W$2:$W$747,A15,RawFinancials!$AA$2:$AA$747,1,RawFinancials!$Z$2:$Z$747,B15) -> 40711151 | E15: =SUMIFS(RawFinancials!$AB$2:$AB$747,RawFinancials!$W$2:$W$747,A15,RawFinancials!$AA$2:$AA$747,1,RawFinancials!$Z$2:$Z$747,B15) -> 69279 | F15: =IF(D15>0,100*E15/D15,"") -> 0.17017205
A16: 20221231 | B16: NH | C16: =COUNTIFS(RawFinancials!$W$2:$W$747,A16,RawFinancials!$AA$2:$AA$747,1,RawFinancials!$Z$2:$Z$747,B16) -> 19 | D16: =SUMIFS(RawFinancials!$B$2:$B$747,RawFinancials!$W$2:$W$747,A16,RawFinancials!$AA$2:$AA$747,1,RawFinancials!$Z$2:$Z$747,B16) -> 16241743 | E16: =SUMIFS(RawFinancials!$AB$2:$AB$747,RawFinancials!$W$2:$W$747,A16,RawFinancials!$AA$2:$AA$747,1,RawFinancials!$Z$2:$Z$747,B16) -> 20482 | F16: =IF(D16>0,100*E16/D16,"") -> 0.12610715
A17: 20221231 | B17: VT | C17: =COUNTIFS(RawFinancials!$W$2:$W$747,A17,RawFinancials!$AA$2:$AA$747,1,RawFinancials!$Z$2:$Z$747,B17) -> 12 | D17: =SUMIFS(RawFinancials!$B$2:$B$747,RawFinancials!$W$2:$W$747,A17,RawFinancials!$AA$2:$AA$747,1,RawFinancials!$Z$2:$Z$747,B17) -> 7550059 | E17: =SUMIFS(RawFinancials!$AB$2:$AB$747,RawFinancials!$W$2:$W$747,A17,RawFinancials!$AA$2:$AA$747,1,RawFinancials!$Z$2:$Z$747,B17) -> 33269 | F17: =IF(D17>0,100*E17/D17,"") -> 0.44064556
A18: 20230331 | B18: ALL | C18: =COUNTIFS(RawFinancials!$W$2:$W$747,A18,RawFinancials!$AA$2:$AA$747,1) -> 54 | D18: =SUMIFS(RawFinancials!$B$2:$B$747,RawFinancials!$W$2:$W$747,A18,RawFinancials!$AA$2:$AA$747,1) -> 65286835 | E18: =SUMIFS(RawFinancials!$AB$2:$AB$747,RawFinancials!$W$2:$W$747,A18,RawFinancials!$AA$2:$AA$747,1) -> 126451 | F18: =IF(D18>0,100*E18/D18,"") -> 0.1936853
A19: 20230331 | B19: ME | C19: =COUNTIFS(RawFinancials!$W$2:$W$747,A19,RawFinancials!$AA$2:$AA$747,1,RawFinancials!$Z$2:$Z$747,B19) -> 23 | D19: =SUMIFS(RawFinancials!$B$2:$B$747,RawFinancials!$W$2:$W$747,A19,RawFinancials!$AA$2:$AA$747,1,RawFinancials!$Z$2:$Z$747,B19) -> 41248817 | E19: =SUMIFS(RawFinancials!$AB$2:$AB$747,RawFinancials!$W$2:$W$747,A19,RawFinancials!$AA$2:$AA$747,1,RawFinancials!$Z$2:$Z$747,B19) -> 72471 | F19: =IF(D19>0,100*E19/D19,"") -> 0.17569231
A20: 20230331 | B20: NH | C20: =COUNTIFS(RawFinancials!$W$2:$W$747,A20,RawFinancials!$AA$2:$AA$747,1,RawFinancials!$Z$2:$Z$747,B20) -> 19 | D20: =SUMIFS(RawFinancials!$B$2:$B$747,RawFinancials!$W$2:$W$747,A20,RawFinancials!$AA$2:$AA$747,1,RawFinancials!$Z$2:$Z$747,B20) -> 16492351 | E20: =SUMIFS(RawFinancials!$AB$2:$AB$747,RawFinancials!$W$2:$W$747,A20,RawFinancials!$AA$2:$AA$747,1,RawFinancials!$Z$2:$Z$747,B20) -> 21816 | F20: =IF(D20>0,100*E20/D20,"") -> 0.1322795
A21: 20230331 | B21: VT | C21: =COUNTIFS(RawFinancials!$W$2:$W$747,A21,RawFinancials!$AA$2:$AA$747,1,RawFinancials!$Z$2:$Z$747,B21) -> 12 | D21: =SUMIFS(RawFinancials!$B$2:$B$747,RawFinancials!$W$2:$W$747,A21,RawFinancials!$AA$2:$AA$747,1,RawFinancials!$Z$2:$Z$747,B21) -> 7545667 | E21: =SUMIFS(RawFinancials!$AB$2:$AB$747,RawFinancials!$W$2:$W$747,A21,RawFinancials!$AA$2:$AA$747,1,RawFinancials!$Z$2:$Z$747,B21) -> 32164 | F21: =IF(D21>0,100*E21/D21,"") -> 0.42625788
A22: 20230630 | B22: ALL | C22: =COUNTIFS(RawFinancials!$W$2:$W$747,A22,RawFinancials!$AA$2:$AA$747,1) -> 54 | D22: =SUMIFS(RawFinancials!$B$2:$B$747,RawFinancials!$W$2:$W$747,A22,RawFinancials!$AA$2:$AA$747,1) -> 66103367 | E22: =SUMIFS(RawFinancials!$AB$2:$AB$747,RawFinancials!$W$2:$W$747,A22,RawFinancials!$AA$2:$AA$747,1) -> 138756 | F22: =IF(D22>0,100*E22/D22,"") -> 0.20990761
A23: 20230630 | B23: ME | C23: =COUNTIFS(RawFinancials!$W$2:$W$747,A23,RawFinancials!$AA$2:$AA$747,1,RawFinancials!$Z$2:$Z$747,B23) -> 23 | D23: =SUMIFS(RawFinancials!$B$2:$B$747,RawFinancials!$W$2:$W$747,A23,RawFinancials!$AA$2:$AA$747,1,RawFinancials!$Z$2:$Z$747,B23) -> 41636903 | E23: =SUMIFS(RawFinancials!$AB$2:$AB$747,RawFinancials!$W$2:$W$747,A23,RawFinancials!$AA$2:$AA$747,1,RawFinancials!$Z$2:$Z$747,B23) -> 74941 | F23: =IF(D23>0,100*E23/D23,"") -> 0.17998697
A24: 20230630 | B24: NH | C24: =COUNTIFS(RawFinancials!$W$2:$W$747,A24,RawFinancials!$AA$2:$AA$747,1,RawFinancials!$Z$2:$Z$747,B24) -> 19 | D24: =SUMIFS(RawFinancials!$B$2:$B$747,RawFinancials!$W$2:$W$747,A24,RawFinancials!$AA$2:$AA$747,1,RawFinancials!$Z$2:$Z$747,B24) -> 16868331 | E24: =SUMIFS(RawFinancials!$AB$2:$AB$747,RawFinancials!$W$2:$W$747,A24,RawFinancials!$AA$2:$AA$747,1,RawFinancials!$Z$2:$Z$747,B24) -> 30872 | F24: =IF(D24>0,100*E24/D24,"") -> 0.18301751
A25: 20230630 | B25: VT | C25: =COUNTIFS(RawFinancials!$W$2:$W$747,A25,RawFinancials!$AA$2:$AA$747,1,RawFinancials!$Z$2:$Z$747,B25) -> 12 | D25: =SUMIFS(RawFinancials!$B$2:$B$747,RawFinancials!$W$2:$W$747,A25,RawFinancials!$AA$2:$AA$747,1,RawFinancials!$Z$2:$Z$747,B25) -> 7598133 | E25: =SUMIFS(RawFinancials!$AB$2:$AB$747,RawFinancials!$W$2:$W$747,A25,RawFinancials!$AA$2:$AA$747,1,RawFinancials!$Z$2:$Z$747,B25) -> 32943 | F25: =IF(D25>0,100*E25/D25,"") -> 0.43356704
A26: 20230930 | B26: ALL | C26: =COUNTIFS(RawFinancials!$W$2:$W$747,A26,RawFinancials!$AA$2:$AA$747,1) -> 54 | D26: =SUMIFS(RawFinancials!$B$2:$B$747,RawFinancials!$W$2:$W$747,A26,RawFinancials!$AA$2:$AA$747,1) -> 66427421 | E26: =SUMIFS(RawFinancials!$AB$2:$AB$747,RawFinancials!$W$2:$W$747,A26,RawFinancials!$AA$2:$AA$747,1) -> 143883 | F26: =IF(D26>0,100*E26/D26,"") -> 0.21660182
A27: 20230930 | B27: ME | C27: =COUNTIFS(RawFinancials!$W$2:$W$747,A27,RawFinancials!$AA$2:$AA$747,1,RawFinancials!$Z$2:$Z$747,B27) -> 23 | D27: =SUMIFS(RawFinancials!$B$2:$B$747,RawFinancials!$W$2:$W$747,A27,RawFinancials!$AA$2:$AA$747,1,RawFinancials!$Z$2:$Z$747,B27) -> 41707922 | E27: =SUMIFS(RawFinancials!$AB$2:$AB$747,RawFinancials!$W$2:$W$747,A27,RawFinancials!$AA$2:$AA$747,1,RawFinancials!$Z$2:$Z$747,B27) -> 76406 | F27: =IF(D27>0,100*E27/D27,"") -> 0.18319302
A28: 20230930 | B28: NH | C28: =COUNTIFS(RawFinancials!$W$2:$W$747,A28,RawFinancials!$AA$2:$AA$747,1,RawFinancials!$Z$2:$Z$747,B28) -> 19 | D28: =SUMIFS(RawFinancials!$B$2:$B$747,RawFinancials!$W$2:$W$747,A28,RawFinancials!$AA$2:$AA$747,1,RawFinancials!$Z$2:$Z$747,B28) -> 16937411 | E28: =SUMIFS(RawFinancials!$AB$2:$AB$747,RawFinancials!$W$2:$W$747,A28,RawFinancials!$AA$2:$AA$747,1,RawFinancials!$Z$2:$Z$747,B28) -> 33535 | F28: =IF(D28>0,100*E28/D28,"") -> 0.19799366
A29: 20230930 | B29: VT | C29: =COUNTIFS(RawFinancials!$W$2:$W$747,A29,RawFinancials!$AA$2:$AA$747,1,RawFinancials!$Z$2:$Z$747,B29) -> 12 | D29: =SUMIFS(RawFinancials!$B$2:$B$747,RawFinancials!$W$2:$W$747,A29,RawFinancials!$AA$2:$AA$747,1,RawFinancials!$Z$2:$Z$747,B29) -> 7782088 | E29: =SUMIFS(RawFinancials!$AB$2:$AB$747,RawFinancials!$W$2:$W$747,A29,RawFinancials!$AA$2:$AA$747,1,RawFinancials!$Z$2:$Z$747,B29) -> 33942 | F29: =IF(D29>0,100*E29/D29,"") -> 0.43615544
A30: 20231231 | B30: ALL | C30: =COUNTIFS(RawFinancials!$W$2:$W$747,A30,RawFinancials!$AA$2:$AA$747,1) -> 54 | D30: =SUMIFS(RawFinancials!$B$2:$B$747,RawFinancials!$W$2:$W$747,A30,RawFinancials!$AA$2:$AA$747,1) -> 67228962 | E30: =SUMIFS(RawFinancials!$AB$2:$AB$747,RawFinancials!$W$2:$W$747,A30,RawFinancials!$AA$2:$AA$747,1) -> 158668 | F30: =IF(D30>0,100*E30/D30,"") -> 0.23601138
A31: 20231231 | B31: ME | C31: =COUNTIFS(RawFinancials!$W$2:$W$747,A31,RawFinancials!$AA$2:$AA$747,1,RawFinancials!$Z$2:$Z$747,B31) -> 23 | D31: =SUMIFS(RawFinancials!$B$2:$B$747,RawFinancials!$W$2:$W$747,A31,RawFinancials!$AA$2:$AA$747,1,RawFinancials!$Z$2:$Z$747,B31) -> 42110091 | E31: =SUMIFS(RawFinancials!$AB$2:$AB$747,RawFinancials!$W$2:$W$747,A31,RawFinancials!$AA$2:$AA$747,1,RawFinancials!$Z$2:$Z$747,B31) -> 96144 | F31: =IF(D31>0,100*E31/D31,"") -> 0.22831582
A32: 20231231 | B32: NH | C32: =COUNTIFS(RawFinancials!$W$2:$W$747,A32,RawFinancials!$AA$2:$AA$747,1,RawFinancials!$Z$2:$Z$747,B32) -> 19 | D32: =SUMIFS(RawFinancials!$B$2:$B$747,RawFinancials!$W$2:$W$747,A32,RawFinancials!$AA$2:$AA$747,1,RawFinancials!$Z$2:$Z$747,B32) -> 17110799 | E32: =SUMIFS(RawFinancials!$AB$2:$AB$747,RawFinancials!$W$2:$W$747,A32,RawFinancials!$AA$2:$AA$747,1,RawFinancials!$Z$2:$Z$747,B32) -> 30295 | F32: =IF(D32>0,100*E32/D32,"") -> 0.17705193
A33: 20231231 | B33: VT | C33: =COUNTIFS(RawFinancials!$W$2:$W$747,A33,RawFinancials!$AA$2:$AA$747,1,RawFinancials!$Z$2:$Z$747,B33) -> 12 | D33: =SUMIFS(RawFinancials!$B$2:$B$747,RawFinancials!$W$2:$W$747,A33,RawFinancials!$AA$2:$AA$747,1,RawFinancials!$Z$2:$Z$747,B33) -> 8008072 | E33: =SUMIFS(RawFinancials!$AB$2:$AB$747,RawFinancials!$W$2:$W$747,A33,RawFinancials!$AA$2:$AA$747,1,RawFinancials!$Z$2:$Z$747,B33) -> 32229 | F33: =IF(D33>0,100*E33/D33,"") -> 0.40245642
A34: 20240331 | B34: ALL | C34: =COUNTIFS(RawFinancials!$W$2:$W$747,A34,RawFinancials!$AA$2:$AA$747,1) -> 54 | D34: =SUMIFS(RawFinancials!$B$2:$B$747,RawFinancials!$W$2:$W$747,A34,RawFinancials!$AA$2:$AA$747,1) -> 67408258 | E34: =SUMIFS(RawFinancials!$AB$2:$AB$747,RawFinancials!$W$2:$W$747,A34,RawFinancials!$AA$2:$AA$747,1) -> 199761 | F34: =IF(D34>0,100*E34/D34,"") -> 0.296345
A35: 20240331 | B35: ME | C35: =COUNTIFS(RawFinancials!$W$2:$W$747,A35,RawFinancials!$AA$2:$AA$747,1,RawFinancials!$Z$2:$Z$747,B35) -> 23 | D35: =SUMIFS(RawFinancials!$B$2:$B$747,RawFinancials!$W$2:$W$747,A35,RawFinancials!$AA$2:$AA$747,1,RawFinancials!$Z$2:$Z$747,B35) -> 42291921 | E35: =SUMIFS(RawFinancials!$AB$2:$AB$747,RawFinancials!$W$2:$W$747,A35,RawFinancials!$AA$2:$AA$747,1,RawFinancials!$Z$2:$Z$747,B35) -> 103921 | F35: =IF(D35>0,100*E35/D35,"") -> 0.24572305
A36: 20240331 | B36: NH | C36: =COUNTIFS(RawFinancials!$W$2:$W$747,A36,RawFinancials!$AA$2:$AA$747,1,RawFinancials!$Z$2:$Z$747,B36) -> 19 | D36: =SUMIFS(RawFinancials!$B$2:$B$747,RawFinancials!$W$2:$W$747,A36,RawFinancials!$AA$2:$AA$747,1,RawFinancials!$Z$2:$Z$747,B36) -> 17104248 | E36: =SUMIFS(RawFinancials!$AB$2:$AB$747,RawFinancials!$W$2:$W$747,A36,RawFinancials!$AA$2:$AA$747,1,RawFinancials!$Z$2:$Z$747,B36) -> 62757 | F36: =IF(D36>0,100*E36/D36,"") -> 0.36690885
A37: 20240331 | B37: VT | C37: =COUNTIFS(RawFinancials!$W$2:$W$747,A37,RawFinancials!$AA$2:$AA$747,1,RawFinancials!$Z$2:$Z$747,B37) -> 12 | D37: =SUMIFS(RawFinancials!$B$2:$B$747,RawFinancials!$W$2:$W$747,A37,RawFinancials!$AA$2:$AA$747,1,RawFinancials!$Z$2:$Z$747,B37) -> 8012089 | E37: =SUMIFS(RawFinancials!$AB$2:$AB$747,RawFinancials!$W$2:$W$747,A37,RawFinancials!$AA$2:$AA$747,1,RawFinancials!$Z$2:$Z$747,B37) -> 33083 | F37: =IF(D37>0,100*E37/D37,"") -> 0.41291354
A38: 20240630 | B38: ALL | C38: =COUNTIFS(RawFinancials!$W$2:$W$747,A38,RawFinancials!$AA$2:$AA$747,1) -> 54 | D38: =SUMIFS(RawFinancials!$B$2:$B$747,RawFinancials!$W$2:$W$747,A38,RawFinancials!$AA$2:$AA$747,1) -> 68174434 | E38: =SUMIFS(RawFinancials!$AB$2:$AB$747,RawFinancials!$W$2:$W$747,A38,RawFinancials!$AA$2:$AA$747,1) -> 203546 | F38: =IF(D38>0,100*E38/D38,"") -> 0.29856647
A39: 20240630 | B39: ME | C39: =COUNTIFS(RawFinancials!$W$2:$W$747,A39,RawFinancials!$AA$2:$AA$747,1,RawFinancials!$Z$2:$Z$747,B39) -> 23 | D39: =SUMIFS(RawFinancials!$B$2:$B$747,RawFinancials!$W$2:$W$747,A39,RawFinancials!$AA$2:$AA$747,1,RawFinancials!$Z$2:$Z$747,B39) -> 42836512 | E39: =SUMIFS(RawFinancials!$AB$2:$AB$747,RawFinancials!$W$2:$W$747,A39,RawFinancials!$AA$2:$AA$747,1,RawFinancials!$Z$2:$Z$747,B39) -> 113174 | F39: =IF(D39>0,100*E39/D39,"") -> 0.26419985
A40: 20240630 | B40: NH | C40: =COUNTIFS(RawFinancials!$W$2:$W$747,A40,RawFinancials!$AA$2:$AA$747,1,RawFinancials!$Z$2:$Z$747,B40) -> 19 | D40: =SUMIFS(RawFinancials!$B$2:$B$747,RawFinancials!$W$2:$W$747,A40,RawFinancials!$AA$2:$AA$747,1,RawFinancials!$Z$2:$Z$747,B40) -> 17279833 | E40: =SUMIFS(RawFinancials!$AB$2:$AB$747,RawFinancials!$W$2:$W$747,A40,RawFinancials!$AA$2:$AA$747,1,RawFinancials!$Z$2:$Z$747,B40) -> 63087 | F40: =IF(D40>0,100*E40/D40,"") -> 0.36509033
A41: 20240630 | B41: VT | C41: =COUNTIFS(RawFinancials!$W$2:$W$747,A41,RawFinancials!$AA$2:$AA$747,1,RawFinancials!$Z$2:$Z$747,B41) -> 12 | D41: =SUMIFS(RawFinancials!$B$2:$B$747,RawFinancials!$W$2:$W$747,A41,RawFinancials!$AA$2:$AA$747,1,RawFinancials!$Z$2:$Z$747,B41) -> 8058089 | E41: =SUMIFS(RawFinancials!$AB$2:$AB$747,RawFinancials!$W$2:$W$747,A41,RawFinancials!$AA$2:$AA$747,1,RawFinancials!$Z$2:$Z$747,B41) -> 27285 | F41: =IF(D41>0,100*E41/D41,"") -> 0.33860386
A42: 20240930 | B42: ALL | C42: =COUNTIFS(RawFinancials!$W$2:$W$747,A42,RawFinancials!$AA$2:$AA$747,1) -> 54 | D42: =SUMIFS(RawFinancials!$B$2:$B$747,RawFinancials!$W$2:$W$747,A42,RawFinancials!$AA$2:$AA$747,1) -> 69727725 | E42: =SUMIFS(RawFinancials!$AB$2:$AB$747,RawFinancials!$W$2:$W$747,A42,RawFinancials!$AA$2:$AA$747,1) -> 202918 | F42: =IF(D42>0,100*E42/D42,"") -> 0.2910148
A43: 20240930 | B43: ME | C43: =COUNTIFS(RawFinancials!$W$2:$W$747,A43,RawFinancials!$AA$2:$AA$747,1,RawFinancials!$Z$2:$Z$747,B43) -> 23 | D43: =SUMIFS(RawFinancials!$B$2:$B$747,RawFinancials!$W$2:$W$747,A43,RawFinancials!$AA$2:$AA$747,1,RawFinancials!$Z$2:$Z$747,B43) -> 43857564 | E43: =SUMIFS(RawFinancials!$AB$2:$AB$747,RawFinancials!$W$2:$W$747,A43,RawFinancials!$AA$2:$AA$747,1,RawFinancials!$Z$2:$Z$747,B43) -> 111386 | F43: =IF(D43>0,100*E43/D43,"") -> 0.25397215
A44: 20240930 | B44: NH | C44: =COUNTIFS(RawFinancials!$W$2:$W$747,A44,RawFinancials!$AA$2:$AA$747,1,RawFinancials!$Z$2:$Z$747,B44) -> 19 | D44: =SUMIFS(RawFinancials!$B$2:$B$747,RawFinancials!$W$2:$W$747,A44,RawFinancials!$AA$2:$AA$747,1,RawFinancials!$Z$2:$Z$747,B44) -> 17448405 | E44: =SUMIFS(RawFinancials!$AB$2:$AB$747,RawFinancials!$W$2:$W$747,A44,RawFinancials!$AA$2:$AA$747,1,RawFinancials!$Z$2:$Z$747,B44) -> 66699 | F44: =IF(D44>0,100*E44/D44,"") -> 0.38226417
A45: 20240930 | B45: VT | C45: =COUNTIFS(RawFinancials!$W$2:$W$747,A45,RawFinancials!$AA$2:$AA$747,1,RawFinancials!$Z$2:$Z$747,B45) -> 12 | D45: =SUMIFS(RawFinancials!$B$2:$B$747,RawFinancials!$W$2:$W$747,A45,RawFinancials!$AA$2:$AA$747,1,RawFinancials!$Z$2:$Z$747,B45) -> 8421756 | E45: =SUMIFS(RawFinancials!$AB$2:$AB$747,RawFinancials!$W$2:$W$747,A45,RawFinancials!$AA$2:$AA$747,1,RawFinancials!$Z$2:$Z$747,B45) -> 24833 | F45: =IF(D45>0,100*E45/D45,"") -> 0.29486725
A46: 20241231 | B46: ALL | C46: =COUNTIFS(RawFinancials!$W$2:$W$747,A46,RawFinancials!$AA$2:$AA$747,1) -> 54 | D46: =SUMIFS(RawFinancials!$B$2:$B$747,RawFinancials!$W$2:$W$747,A46,RawFinancials!$AA$2:$AA$747,1) -> 70110166 | E46: =SUMIFS(RawFinancials!$AB$2:$AB$747,RawFinancials!$W$2:$W$747,A46,RawFinancials!$AA$2:$AA$747,1) -> 197476 | F46: =IF(D46>0,100*E46/D46,"") -> 0.28166529
A47: 20241231 | B47: ME | C47: =COUNTIFS(RawFinancials!$W$2:$W$747,A47,RawFinancials!$AA$2:$AA$747,1,RawFinancials!$Z$2:$Z$747,B47) -> 23 | D47: =SUMIFS(RawFinancials!$B$2:$B$747,RawFinancials!$W$2:$W$747,A47,RawFinancials!$AA$2:$AA$747,1,RawFinancials!$Z$2:$Z$747,B47) -> 44159558 | E47: =SUMIFS(RawFinancials!$AB$2:$AB$747,RawFinancials!$W$2:$W$747,A47,RawFinancials!$AA$2:$AA$747,1,RawFinancials!$Z$2:$Z$747,B47) -> 105164 | F47: =IF(D47>0,100*E47/D47,"") -> 0.2381455
A48: 20241231 | B48: NH | C48: =COUNTIFS(RawFinancials!$W$2:$W$747,A48,RawFinancials!$AA$2:$AA$747,1,RawFinancials!$Z$2:$Z$747,B48) -> 19 | D48: =SUMIFS(RawFinancials!$B$2:$B$747,RawFinancials!$W$2:$W$747,A48,RawFinancials!$AA$2:$AA$747,1,RawFinancials!$Z$2:$Z$747,B48) -> 17386962 | E48: =SUMIFS(RawFinancials!$AB$2:$AB$747,RawFinancials!$W$2:$W$747,A48,RawFinancials!$AA$2:$AA$747,1,RawFinancials!$Z$2:$Z$747,B48) -> 64887 | F48: =IF(D48>0,100*E48/D48,"") -> 0.37319343
A49: 20241231 | B49: VT | C49: =COUNTIFS(RawFinancials!$W$2:$W$747,A49,RawFinancials!$AA$2:$AA$747,1,RawFinancials!$Z$2:$Z$747,B49) -> 12 | D49: =SUMIFS(RawFinancials!$B$2:$B$747,RawFinancials!$W$2:$W$747,A49,RawFinancials!$AA$2:$AA$747,1,RawFinancials!$Z$2:$Z$747,B49) -> 8563646 | E49: =SUMIFS(RawFinancials!$AB$2:$AB$747,RawFinancials!$W$2:$W$747,A49,RawFinancials!$AA$2:$AA$747,1,RawFinancials!$Z$2:$Z$747,B49) -> 27425 | F49: =IF(D49>0,100*E49/D49,"") -> 0.32024911
A50: 20250331 | B50: ALL | C50: =COUNTIFS(RawFinancials!$W$2:$W$747,A50,RawFinancials!$AA$2:$AA$747,1) -> 52 | D50: =SUMIFS(RawFinancials!$B$2:$B$747,RawFinancials!$W$2:$W$747,A50,RawFinancials!$AA$2:$AA$747,1) -> 70509303 | E50: =SUMIFS(RawFinancials!$AB$2:$AB$747,RawFinancials!$W$2:$W$747,A50,RawFinancials!$AA$2:$AA$747,1) -> 206872 | F50: =IF(D50>0,100*E50/D50,"") -> 0.29339675
A51: 20250331 | B51: ME | C51: =COUNTIFS(RawFinancials!$W$2:$W$747,A51,RawFinancials!$AA$2:$AA$747,1,RawFinancials!$Z$2:$Z$747,B51) -> 22 | D51: =SUMIFS(RawFinancials!$B$2:$B$747,RawFinancials!$W$2:$W$747,A51,RawFinancials!$AA$2:$AA$747,1,RawFinancials!$Z$2:$Z$747,B51) -> 45509746 | E51: =SUMIFS(RawFinancials!$AB$2:$AB$747,RawFinancials!$W$2:$W$747,A51,RawFinancials!$AA$2:$AA$747,1,RawFinancials!$Z$2:$Z$747,B51) -> 118037 | F51: =IF(D51>0,100*E51/D51,"") -> 0.25936642
A52: 20250331 | B52: NH | C52: =COUNTIFS(RawFinancials!$W$2:$W$747,A52,RawFinancials!$AA$2:$AA$747,1,RawFinancials!$Z$2:$Z$747,B52) -> 18 | D52: =SUMIFS(RawFinancials!$B$2:$B$747,RawFinancials!$W$2:$W$747,A52,RawFinancials!$AA$2:$AA$747,1,RawFinancials!$Z$2:$Z$747,B52) -> 16458416 | E52: =SUMIFS(RawFinancials!$AB$2:$AB$747,RawFinancials!$W$2:$W$747,A52,RawFinancials!$AA$2:$AA$747,1,RawFinancials!$Z$2:$Z$747,B52) -> 47401 | F52: =IF(D52>0,100*E52/D52,"") -> 0.28800463
A53: 20250331 | B53: VT | C53: =COUNTIFS(RawFinancials!$W$2:$W$747,A53,RawFinancials!$AA$2:$AA$747,1,RawFinancials!$Z$2:$Z$747,B53) -> 12 | D53: =SUMIFS(RawFinancials!$B$2:$B$747,RawFinancials!$W$2:$W$747,A53,RawFinancials!$AA$2:$AA$747,1,RawFinancials!$Z$2:$Z$747,B53) -> 8541141 | E53: =SUMIFS(RawFinancials!$AB$2:$AB$747,RawFinancials!$W$2:$W$747,A53,RawFinancials!$AA$2:$AA$747,1,RawFinancials!$Z$2:$Z$747,B53) -> 41434 | F53: =IF(D53>0,100*E53/D53,"") -> 0.48511083
A54: 20250630 | B54: ALL | C54: =COUNTIFS(RawFinancials!$W$2:$W$747,A54,RawFinancials!$AA$2:$AA$747,1) -> 52 | D54: =SUMIFS(RawFinancials!$B$2:$B$747,RawFinancials!$W$2:$W$747,A54,RawFinancials!$AA$2:$AA$747,1) -> 71266944 | E54: =SUMIFS(RawFinancials!$AB$2:$AB$747,RawFinancials!$W$2:$W$747,A54,RawFinancials!$AA$2:$AA$747,1) -> 262400 | F54: =IF(D54>0,100*E54/D54,"") -> 0.36819314
A55: 20250630 | B55: ME | C55: =COUNTIFS(RawFinancials!$W$2:$W$747,A55,RawFinancials!$AA$2:$AA$747,1,RawFinancials!$Z$2:$Z$747,B55) -> 22 | D55: =SUMIFS(RawFinancials!$B$2:$B$747,RawFinancials!$W$2:$W$747,A55,RawFinancials!$AA$2:$AA$747,1,RawFinancials!$Z$2:$Z$747,B55) -> 46035765 | E55: =SUMIFS(RawFinancials!$AB$2:$AB$747,RawFinancials!$W$2:$W$747,A55,RawFinancials!$AA$2:$AA$747,1,RawFinancials!$Z$2:$Z$747,B55) -> 169125 | F55: =IF(D55>0,100*E55/D55,"") -> 0.36737741
A56: 20250630 | B56: NH | C56: =COUNTIFS(RawFinancials!$W$2:$W$747,A56,RawFinancials!$AA$2:$AA$747,1,RawFinancials!$Z$2:$Z$747,B56) -> 18 | D56: =SUMIFS(RawFinancials!$B$2:$B$747,RawFinancials!$W$2:$W$747,A56,RawFinancials!$AA$2:$AA$747,1,RawFinancials!$Z$2:$Z$747,B56) -> 16713625 | E56: =SUMIFS(RawFinancials!$AB$2:$AB$747,RawFinancials!$W$2:$W$747,A56,RawFinancials!$AA$2:$AA$747,1,RawFinancials!$Z$2:$Z$747,B56) -> 51136 | F56: =IF(D56>0,100*E56/D56,"") -> 0.30595397
A57: 20250630 | B57: VT | C57: =COUNTIFS(RawFinancials!$W$2:$W$747,A57,RawFinancials!$AA$2:$AA$747,1,RawFinancials!$Z$2:$Z$747,B57) -> 12 | D57: =SUMIFS(RawFinancials!$B$2:$B$747,RawFinancials!$W$2:$W$747,A57,RawFinancials!$AA$2:$AA$747,1,RawFinancials!$Z$2:$Z$747,B57) -> 8517554 | E57: =SUMIFS(RawFinancials!$AB$2:$AB$747,RawFinancials!$W$2:$W$747,A57,RawFinancials!$AA$2:$AA$747,1,RawFinancials!$Z$2:$Z$747,B57) -> 42139 | F57: =IF(D57>0,100*E57/D57,"") -> 0.49473123

Sheet Priority
A1: rank | B1: CERT | C1: state | D1: bank | E1: proxy_pct | F1: prior_proxy_pct | G1: change_pp | H1: RE_loan_share_pct | I1: equity_asset_pct | J1: ROA_pct | K1: RBCRWAJ_pct | L1: source_row | M1: prior_source_row | N1: reason | O1: request | P1: owner | Q1: due | R1: capital_note | S1: calc_row
A2: 1 | B2: =IF($S2>0,INDEX(BankCalc!$A:$A,$S2),"") -> 6280 | C2: =IF($S2>0,INDEX(BankCalc!$G:$G,$S2),"") -> VT | D2: =IF($S2>0,INDEX(BankCalc!$V:$V,$S2),"") -> THE FIRST NATIONAL BANK OF ORWELL | E2: =IF($S2>0,INDEX(BankCalc!$M:$M,$S2),"") -> 1.6577418 | F2: =IF($S2>0,INDEX(BankCalc!$J:$J,$S2),"") -> 1.4840337 | G2: =IF(AND(ISNUMBER(E2),ISNUMBER(F2)),E2-F2,"") -> 0.17370811 | H2: =IF($S2>0,IF(INDEX(RawFinancials!$L:$L,L2)>0,100*INDEX(RawFinancials!$N:$N,L2)/INDEX(RawFinancials!$L:$L,L2),""),"") -> 88.846785 | I2: =IF($S2>0,100*INDEX(RawFinancials!$F:$F,L2)/INDEX(RawFinancials!$B:$B,L2),"") -> 11.335308 | J2: =IF($S2>0,INDEX(RawFinancials!$X:$X,L2),"") -> 1.3665403 | K2: =IF($S2>0,INDEX(RawFinancials!$V:$V,L2),"") -> 0 | L2: =IF($S2>0,INDEX(BankCalc!$C:$C,$S2),"") -> 747 | M2: =IF($S2>0,INDEX(BankCalc!$B:$B,$S2),"") -> 535 | N2: =IF($S2>0,"当前有效资产代理率、州覆盖与容量排序；原因待查","") -> 当前有效资产代理率、州覆盖与容量排序；原因待查 | O2: =IF($S2>0,"提供逾期/非应计台账、还款与分类、房地产集中度及估值；解释盈利和资本变化","") -> 提供逾期/非应计台账、还款与分类、房地产集中度及估值；解释盈利和资本变化 | P2: =IF($S2>0,"信用复核负责人","") -> 信用复核负责人 | Q2: =IF($S2>0,"委员会后5个工作日内提交初核包","") -> 委员会后5个工作日内提交初核包 | R2: =IF($S2>0,IF(K2=0,"原始0：需核实适用/报告口径",""),"") -> 原始0：需核实适用/报告口径 | S2: =IF(AND(WF_MODEL_VALID,A2<=WF_REVIEW_SLOTS),MATCH(A2,BankCalc!$U$2:$U$55,0)+1,0) -> 6
A3: 2 | B3: =IF($S3>0,INDEX(BankCalc!$A:$A,$S3),"") -> 59289 | C3: =IF($S3>0,INDEX(BankCalc!$G:$G,$S3),"") -> NH | D3: =IF($S3>0,INDEX(BankCalc!$V:$V,$S3),"") -> WALDEN MUTUAL BANK | E3: =IF($S3>0,INDEX(BankCalc!$M:$M,$S3),"") -> 1.9419005 | F3: =IF($S3>0,INDEX(BankCalc!$J:$J,$S3),"") -> 0.30778236 | G3: =IF(AND(ISNUMBER(E3),ISNUMBER(F3)),E3-F3,"") -> 1.6341182 | H3: =IF($S3>0,IF(INDEX(RawFinancials!$L:$L,L3)>0,100*INDEX(RawFinancials!$N:$N,L3)/INDEX(RawFinancials!$L:$L,L3),""),"") -> 36.175662 | I3: =IF($S3>0,100*INDEX(RawFinancials!$F:$F,L3)/INDEX(RawFinancials!$B:$B,L3),"") -> 10.752718 | J3: =IF($S3>0,INDEX(RawFinancials!$X:$X,L3),"") -> -0.2399886 | K3: =IF($S3>0,INDEX(RawFinancials!$V:$V,L3),"") -> 0 | L3: =IF($S3>0,INDEX(BankCalc!$C:$C,$S3),"") -> 743 | M3: =IF($S3>0,INDEX(BankCalc!$B:$B,$S3),"") -> 531 | N3: =IF($S3>0,"当前有效资产代理率、州覆盖与容量排序；原因待查","") -> 当前有效资产代理率、州覆盖与容量排序；原因待查 | O3: =IF($S3>0,"提供逾期/非应计台账、还款与分类、房地产集中度及估值；解释盈利和资本变化","") -> 提供逾期/非应计台账、还款与分类、房地产集中度及估值；解释盈利和资本变化 | P3: =IF($S3>0,"信用复核负责人","") -> 信用复核负责人 | Q3: =IF($S3>0,"委员会后5个工作日内提交初核包","") -> 委员会后5个工作日内提交初核包 | R3: =IF($S3>0,IF(K3=0,"原始0：需核实适用/报告口径",""),"") -> 原始0：需核实适用/报告口径 | S3: =IF(AND(WF_MODEL_VALID,A3<=WF_REVIEW_SLOTS),MATCH(A3,BankCalc!$U$2:$U$55,0)+1,0) -> 54
A4: 3 | B4: =IF($S4>0,INDEX(BankCalc!$A:$A,$S4),"") -> 29636 | C4: =IF($S4>0,INDEX(BankCalc!$G:$G,$S4),"") -> ME | D4: =IF($S4>0,INDEX(BankCalc!$V:$V,$S4),"") -> FIRST FEDERAL SAVINGS AND LOAN ASSOCIATION OF BATH | E4: =IF($S4>0,INDEX(BankCalc!$M:$M,$S4),"") -> 1.6715794 | F4: =IF($S4>0,INDEX(BankCalc!$J:$J,$S4),"") -> 1.5150759 | G4: =IF(AND(ISNUMBER(E4),ISNUMBER(F4)),E4-F4,"") -> 0.15650351 | H4: =IF($S4>0,IF(INDEX(RawFinancials!$L:$L,L4)>0,100*INDEX(RawFinancials!$N:$N,L4)/INDEX(RawFinancials!$L:$L,L4),""),"") -> 97.763348 | I4: =IF($S4>0,100*INDEX(RawFinancials!$F:$F,L4)/INDEX(RawFinancials!$B:$B,L4),"") -> 14.897641 | J4: =IF($S4>0,INDEX(RawFinancials!$X:$X,L4),"") -> 0.23461911 | K4: =IF($S4>0,INDEX(RawFinancials!$V:$V,L4),"") -> 27.167214 | L4: =IF($S4>0,INDEX(BankCalc!$C:$C,$S4),"") -> 732 | M4: =IF($S4>0,INDEX(BankCalc!$B:$B,$S4),"") -> 520 | N4: =IF($S4>0,"当前有效资产代理率、州覆盖与容量排序；原因待查","") -> 当前有效资产代理率、州覆盖与容量排序；原因待查 | O4: =IF($S4>0,"提供逾期/非应计台账、还款与分类、房地产集中度及估值；解释盈利和资本变化","") -> 提供逾期/非应计台账、还款与分类、房地产集中度及估值；解释盈利和资本变化 | P4: =IF($S4>0,"信用复核负责人","") -> 信用复核负责人 | Q4: =IF($S4>0,"委员会后5个工作日内提交初核包","") -> 委员会后5个工作日内提交初核包 | R4: =IF($S4>0,IF(K4=0,"原始0：需核实适用/报告口径",""),"") | S4: =IF(AND(WF_MODEL_VALID,A4<=WF_REVIEW_SLOTS),MATCH(A4,BankCalc!$U$2:$U$55,0)+1,0) -> 45
A5: 4 | B5: =IF($S5>0,INDEX(BankCalc!$A:$A,$S5),"") -> 59086 | C5: =IF($S5>0,INDEX(BankCalc!$G:$G,$S5),"") -> NH | D5: =IF($S5>0,INDEX(BankCalc!$V:$V,$S5),"") -> PRIMARY BANK | E5: =IF($S5>0,INDEX(BankCalc!$M:$M,$S5),"") -> 1.9079604 | F5: =IF($S5>0,INDEX(BankCalc!$J:$J,$S5),"") -> 0.57239486 | G5: =IF(AND(ISNUMBER(E5),ISNUMBER(F5)),E5-F5,"") -> 1.3355655 | H5: =IF($S5>0,IF(INDEX(RawFinancials!$L:$L,L5)>0,100*INDEX(RawFinancials!$N:$N,L5)/INDEX(RawFinancials!$L:$L,L5),""),"") -> 80.008981 | I5: =IF($S5>0,100*INDEX(RawFinancials!$F:$F,L5)/INDEX(RawFinancials!$B:$B,L5),"") -> 14.600147 | J5: =IF($S5>0,INDEX(RawFinancials!$X:$X,L5),"") -> 1.556918 | K5: =IF($S5>0,INDEX(RawFinancials!$V:$V,L5),"") -> 16.78059 | L5: =IF($S5>0,INDEX(BankCalc!$C:$C,$S5),"") -> 741 | M5: =IF($S5>0,INDEX(BankCalc!$B:$B,$S5),"") -> 529 | N5: =IF($S5>0,"当前有效资产代理率、州覆盖与容量排序；原因待查","") -> 当前有效资产代理率、州覆盖与容量排序；原因待查 | O5: =IF($S5>0,"提供逾期/非应计台账、还款与分类、房地产集中度及估值；解释盈利和资本变化","") -> 提供逾期/非应计台账、还款与分类、房地产集中度及估值；解释盈利和资本变化 | P5: =IF($S5>0,"信用复核负责人","") -> 信用复核负责人 | Q5: =IF($S5>0,"委员会后5个工作日内提交初核包","") -> 委员会后5个工作日内提交初核包 | R5: =IF($S5>0,IF(K5=0,"原始0：需核实适用/报告口径",""),"") | S5: =IF(AND(WF_MODEL_VALID,A5<=WF_REVIEW_SLOTS),MATCH(A5,BankCalc!$U$2:$U$55,0)+1,0) -> 52
A6: 5 | B6: =IF($S6>0,INDEX(BankCalc!$A:$A,$S6),"") -> 30878 | C6: =IF($S6>0,INDEX(BankCalc!$G:$G,$S6),"") -> ME | D6: =IF($S6>0,INDEX(BankCalc!$V:$V,$S6),"") -> BAR HARBOR SAVINGS AND LOAN ASSOCIATION | E6: =IF($S6>0,INDEX(BankCalc!$M:$M,$S6),"") -> 1.3679241 | F6: =IF($S6>0,INDEX(BankCalc!$J:$J,$S6),"") -> 1.7771084 | G6: =IF(AND(ISNUMBER(E6),ISNUMBER(F6)),E6-F6,"") -> -0.40918438 | H6: =IF($S6>0,IF(INDEX(RawFinancials!$L:$L,L6)>0,100*INDEX(RawFinancials!$N:$N,L6)/INDEX(RawFinancials!$L:$L,L6),""),"") -> 99.795434 | I6: =IF($S6>0,100*INDEX(RawFinancials!$F:$F,L6)/INDEX(RawFinancials!$B:$B,L6),"") -> 12.022162 | J6: =IF($S6>0,INDEX(RawFinancials!$X:$X,L6),"") -> 0.0020154179 | K6: =IF($S6>0,INDEX(RawFinancials!$V:$V,L6),"") -> 0 | L6: =IF($S6>0,INDEX(BankCalc!$C:$C,$S6),"") -> 736 | M6: =IF($S6>0,INDEX(BankCalc!$B:$B,$S6),"") -> 524 | N6: =IF($S6>0,"当前有效资产代理率、州覆盖与容量排序；原因待查","") -> 当前有效资产代理率、州覆盖与容量排序；原因待查 | O6: =IF($S6>0,"提供逾期/非应计台账、还款与分类、房地产集中度及估值；解释盈利和资本变化","") -> 提供逾期/非应计台账、还款与分类、房地产集中度及估值；解释盈利和资本变化 | P6: =IF($S6>0,"信用复核负责人","") -> 信用复核负责人 | Q6: =IF($S6>0,"委员会后5个工作日内提交初核包","") -> 委员会后5个工作日内提交初核包 | R6: =IF($S6>0,IF(K6=0,"原始0：需核实适用/报告口径",""),"") -> 原始0：需核实适用/报告口径 | S6: =IF(AND(WF_MODEL_VALID,A6<=WF_REVIEW_SLOTS),MATCH(A6,BankCalc!$U$2:$U$55,0)+1,0) -> 49
A7: 6 | B7: =IF($S7>0,INDEX(BankCalc!$A:$A,$S7),"") -> 19836 | C7: =IF($S7>0,INDEX(BankCalc!$G:$G,$S7),"") -> ME | D7: =IF($S7>0,INDEX(BankCalc!$V:$V,$S7),"") -> FRANKLIN SAVINGS BANK | E7: =IF($S7>0,INDEX(BankCalc!$M:$M,$S7),"") -> 1.1152219 | F7: =IF($S7>0,INDEX(BankCalc!$J:$J,$S7),"") -> 0.81498664 | G7: =IF(AND(ISNUMBER(E7),ISNUMBER(F7)),E7-F7,"") -> 0.3002353 | H7: =IF($S7>0,IF(INDEX(RawFinancials!$L:$L,L7)>0,100*INDEX(RawFinancials!$N:$N,L7)/INDEX(RawFinancials!$L:$L,L7),""),"") -> 91.345024 | I7: =IF($S7>0,100*INDEX(RawFinancials!$F:$F,L7)/INDEX(RawFinancials!$B:$B,L7),"") -> 17.275876 | J7: =IF($S7>0,INDEX(RawFinancials!$X:$X,L7),"") -> 0.83954125 | K7: =IF($S7>0,INDEX(RawFinancials!$V:$V,L7),"") -> 23.054852 | L7: =IF($S7>0,INDEX(BankCalc!$C:$C,$S7),"") -> 725 | M7: =IF($S7>0,INDEX(BankCalc!$B:$B,$S7),"") -> 513 | N7: =IF($S7>0,"当前有效资产代理率、州覆盖与容量排序；原因待查","") -> 当前有效资产代理率、州覆盖与容量排序；原因待查 | O7: =IF($S7>0,"提供逾期/非应计台账、还款与分类、房地产集中度及估值；解释盈利和资本变化","") -> 提供逾期/非应计台账、还款与分类、房地产集中度及估值；解释盈利和资本变化 | P7: =IF($S7>0,"信用复核负责人","") -> 信用复核负责人 | Q7: =IF($S7>0,"委员会后5个工作日内提交初核包","") -> 委员会后5个工作日内提交初核包 | R7: =IF($S7>0,IF(K7=0,"原始0：需核实适用/报告口径",""),"") | S7: =IF(AND(WF_MODEL_VALID,A7<=WF_REVIEW_SLOTS),MATCH(A7,BankCalc!$U$2:$U$55,0)+1,0) -> 38
A8: 7 | B8: =IF($S8>0,INDEX(BankCalc!$A:$A,$S8),"") -> 14158 | C8: =IF($S8>0,INDEX(BankCalc!$G:$G,$S8),"") -> VT | D8: =IF($S8>0,INDEX(BankCalc!$V:$V,$S8),"") -> UNION BANK | E8: =IF($S8>0,INDEX(BankCalc!$M:$M,$S8),"") -> 1.0315306 | F8: =IF($S8>0,INDEX(BankCalc!$J:$J,$S8),"") -> 0.13792798 | G8: =IF(AND(ISNUMBER(E8),ISNUMBER(F8)),E8-F8,"") -> 0.89360262 | H8: =IF($S8>0,IF(INDEX(RawFinancials!$L:$L,L8)>0,100*INDEX(RawFinancials!$N:$N,L8)/INDEX(RawFinancials!$L:$L,L8),""),"") -> 92.585155 | I8: =IF($S8>0,100*INDEX(RawFinancials!$F:$F,L8)/INDEX(RawFinancials!$B:$B,L8),"") -> 5.8481789 | J8: =IF($S8>0,INDEX(RawFinancials!$X:$X,L8),"") -> 0.70486927 | K8: =IF($S8>0,INDEX(RawFinancials!$V:$V,L8),"") -> 12.623433 | L8: =IF($S8>0,INDEX(BankCalc!$C:$C,$S8),"") -> 702 | M8: =IF($S8>0,INDEX(BankCalc!$B:$B,$S8),"") -> 488 | N8: =IF($S8>0,"当前有效资产代理率、州覆盖与容量排序；原因待查","") -> 当前有效资产代理率、州覆盖与容量排序；原因待查 | O8: =IF($S8>0,"提供逾期/非应计台账、还款与分类、房地产集中度及估值；解释盈利和资本变化","") -> 提供逾期/非应计台账、还款与分类、房地产集中度及估值；解释盈利和资本变化 | P8: =IF($S8>0,"信用复核负责人","") -> 信用复核负责人 | Q8: =IF($S8>0,"委员会后5个工作日内提交初核包","") -> 委员会后5个工作日内提交初核包 | R8: =IF($S8>0,IF(K8=0,"原始0：需核实适用/报告口径",""),"") | S8: =IF(AND(WF_MODEL_VALID,A8<=WF_REVIEW_SLOTS),MATCH(A8,BankCalc!$U$2:$U$55,0)+1,0) -> 13
A9: 8 | B9: =IF($S9>0,INDEX(BankCalc!$A:$A,$S9),"") -> 19690 | C9: =IF($S9>0,INDEX(BankCalc!$G:$G,$S9),"") -> ME | D9: =IF($S9>0,INDEX(BankCalc!$V:$V,$S9),"") -> NORTHEAST BANK | E9: =IF($S9>0,INDEX(BankCalc!$M:$M,$S9),"") -> 0.81819199 | F9: =IF($S9>0,INDEX(BankCalc!$J:$J,$S9),"") -> 0.90224037 | G9: =IF(AND(ISNUMBER(E9),ISNUMBER(F9)),E9-F9,"") -> -0.084048377 | H9: =IF($S9>0,IF(INDEX(RawFinancials!$L:$L,L9)>0,100*INDEX(RawFinancials!$N:$N,L9)/INDEX(RawFinancials!$L:$L,L9),""),"") -> 75.272634 | I9: =IF($S9>0,100*INDEX(RawFinancials!$F:$F,L9)/INDEX(RawFinancials!$B:$B,L9),"") -> 11.551251 | J9: =IF($S9>0,INDEX(RawFinancials!$X:$X,L9),"") -> 2.0918421 | K9: =IF($S9>0,INDEX(RawFinancials!$V:$V,L9),"") -> 14.696581 | L9: =IF($S9>0,INDEX(BankCalc!$C:$C,$S9),"") -> 724 | M9: =IF($S9>0,INDEX(BankCalc!$B:$B,$S9),"") -> 512 | N9: =IF($S9>0,"当前有效资产代理率、州覆盖与容量排序；原因待查","") -> 当前有效资产代理率、州覆盖与容量排序；原因待查 | O9: =IF($S9>0,"提供逾期/非应计台账、还款与分类、房地产集中度及估值；解释盈利和资本变化","") -> 提供逾期/非应计台账、还款与分类、房地产集中度及估值；解释盈利和资本变化 | P9: =IF($S9>0,"信用复核负责人","") -> 信用复核负责人 | Q9: =IF($S9>0,"委员会后5个工作日内提交初核包","") -> 委员会后5个工作日内提交初核包 | R9: =IF($S9>0,IF(K9=0,"原始0：需核实适用/报告口径",""),"") | S9: =IF(AND(WF_MODEL_VALID,A9<=WF_REVIEW_SLOTS),MATCH(A9,BankCalc!$U$2:$U$55,0)+1,0) -> 37
A10: 9 | B10: =IF($S10>0,INDEX(BankCalc!$A:$A,$S10),"") | C10: =IF($S10>0,INDEX(BankCalc!$G:$G,$S10),"") | D10: =IF($S10>0,INDEX(BankCalc!$V:$V,$S10),"") | E10: =IF($S10>0,INDEX(BankCalc!$M:$M,$S10),"") | F10: =IF($S10>0,INDEX(BankCalc!$J:$J,$S10),"") | G10: =IF(AND(ISNUMBER(E10),ISNUMBER(F10)),E10-F10,"") | H10: =IF($S10>0,IF(INDEX(RawFinancials!$L:$L,L10)>0,100*INDEX(RawFinancials!$N:$N,L10)/INDEX(RawFinancials!$L:$L,L10),""),"") | I10: =IF($S10>0,100*INDEX(RawFinancials!$F:$F,L10)/INDEX(RawFinancials!$B:$B,L10),"") | J10: =IF($S10>0,INDEX(RawFinancials!$X:$X,L10),"") | K10: =IF($S10>0,INDEX(RawFinancials!$V:$V,L10),"") | L10: =IF($S10>0,INDEX(BankCalc!$C:$C,$S10),"") | M10: =IF($S10>0,INDEX(BankCalc!$B:$B,$S10),"") | N10: =IF($S10>0,"当前有效资产代理率、州覆盖与容量排序；原因待查","") | O10: =IF($S10>0,"提供逾期/非应计台账、还款与分类、房地产集中度及估值；解释盈利和资本变化","") | P10: =IF($S10>0,"信用复核负责人","") | Q10: =IF($S10>0,"委员会后5个工作日内提交初核包","") | R10: =IF($S10>0,IF(K10=0,"原始0：需核实适用/报告口径",""),"") | S10: =IF(AND(WF_MODEL_VALID,A10<=WF_REVIEW_SLOTS),MATCH(A10,BankCalc!$U$2:$U$55,0)+1,0) -> 0
A11: 10 | B11: =IF($S11>0,INDEX(BankCalc!$A:$A,$S11),"") | C11: =IF($S11>0,INDEX(BankCalc!$G:$G,$S11),"") | D11: =IF($S11>0,INDEX(BankCalc!$V:$V,$S11),"") | E11: =IF($S11>0,INDEX(BankCalc!$M:$M,$S11),"") | F11: =IF($S11>0,INDEX(BankCalc!$J:$J,$S11),"") | G11: =IF(AND(ISNUMBER(E11),ISNUMBER(F11)),E11-F11,"") | H11: =IF($S11>0,IF(INDEX(RawFinancials!$L:$L,L11)>0,100*INDEX(RawFinancials!$N:$N,L11)/INDEX(RawFinancials!$L:$L,L11),""),"") | I11: =IF($S11>0,100*INDEX(RawFinancials!$F:$F,L11)/INDEX(RawFinancials!$B:$B,L11),"") | J11: =IF($S11>0,INDEX(RawFinancials!$X:$X,L11),"") | K11: =IF($S11>0,INDEX(RawFinancials!$V:$V,L11),"") | L11: =IF($S11>0,INDEX(BankCalc!$C:$C,$S11),"") | M11: =IF($S11>0,INDEX(BankCalc!$B:$B,$S11),"") | N11: =IF($S11>0,"当前有效资产代理率、州覆盖与容量排序；原因待查","") | O11: =IF($S11>0,"提供逾期/非应计台账、还款与分类、房地产集中度及估值；解释盈利和资本变化","") | P11: =IF($S11>0,"信用复核负责人","") | Q11: =IF($S11>0,"委员会后5个工作日内提交初核包","") | R11: =IF($S11>0,IF(K11=0,"原始0：需核实适用/报告口径",""),"") | S11: =IF(AND(WF_MODEL_VALID,A11<=WF_REVIEW_SLOTS),MATCH(A11,BankCalc!$U$2:$U$55,0)+1,0) -> 0
A12: 11 | B12: =IF($S12>0,INDEX(BankCalc!$A:$A,$S12),"") | C12: =IF($S12>0,INDEX(BankCalc!$G:$G,$S12),"") | D12: =IF($S12>0,INDEX(BankCalc!$V:$V,$S12),"") | E12: =IF($S12>0,INDEX(BankCalc!$M:$M,$S12),"") | F12: =IF($S12>0,INDEX(BankCalc!$J:$J,$S12),"") | G12: =IF(AND(ISNUMBER(E12),ISNUMBER(F12)),E12-F12,"") | H12: =IF($S12>0,IF(INDEX(RawFinancials!$L:$L,L12)>0,100*INDEX(RawFinancials!$N:$N,L12)/INDEX(RawFinancials!$L:$L,L12),""),"") | I12: =IF($S12>0,100*INDEX(RawFinancials!$F:$F,L12)/INDEX(RawFinancials!$B:$B,L12),"") | J12: =IF($S12>0,INDEX(RawFinancials!$X:$X,L12),"") | K12: =IF($S12>0,INDEX(RawFinancials!$V:$V,L12),"") | L12: =IF($S12>0,INDEX(BankCalc!$C:$C,$S12),"") | M12: =IF($S12>0,INDEX(BankCalc!$B:$B,$S12),"") | N12: =IF($S12>0,"当前有效资产代理率、州覆盖与容量排序；原因待查","") | O12: =IF($S12>0,"提供逾期/非应计台账、还款与分类、房地产集中度及估值；解释盈利和资本变化","") | P12: =IF($S12>0,"信用复核负责人","") | Q12: =IF($S12>0,"委员会后5个工作日内提交初核包","") | R12: =IF($S12>0,IF(K12=0,"原始0：需核实适用/报告口径",""),"") | S12: =IF(AND(WF_MODEL_VALID,A12<=WF_REVIEW_SLOTS),MATCH(A12,BankCalc!$U$2:$U$55,0)+1,0) -> 0
A13: 12 | B13: =IF($S13>0,INDEX(BankCalc!$A:$A,$S13),"") | C13: =IF($S13>0,INDEX(BankCalc!$G:$G,$S13),"") | D13: =IF($S13>0,INDEX(BankCalc!$V:$V,$S13),"") | E13: =IF($S13>0,INDEX(BankCalc!$M:$M,$S13),"") | F13: =IF($S13>0,INDEX(BankCalc!$J:$J,$S13),"") | G13: =IF(AND(ISNUMBER(E13),ISNUMBER(F13)),E13-F13,"") | H13: =IF($S13>0,IF(INDEX(RawFinancials!$L:$L,L13)>0,100*INDEX(RawFinancials!$N:$N,L13)/INDEX(RawFinancials!$L:$L,L13),""),"") | I13: =IF($S13>0,100*INDEX(RawFinancials!$F:$F,L13)/INDEX(RawFinancials!$B:$B,L13),"") | J13: =IF($S13>0,INDEX(RawFinancials!$X:$X,L13),"") | K13: =IF($S13>0,INDEX(RawFinancials!$V:$V,L13),"") | L13: =IF($S13>0,INDEX(BankCalc!$C:$C,$S13),"") | M13: =IF($S13>0,INDEX(BankCalc!$B:$B,$S13),"") | N13: =IF($S13>0,"当前有效资产代理率、州覆盖与容量排序；原因待查","") | O13: =IF($S13>0,"提供逾期/非应计台账、还款与分类、房地产集中度及估值；解释盈利和资本变化","") | P13: =IF($S13>0,"信用复核负责人","") | Q13: =IF($S13>0,"委员会后5个工作日内提交初核包","") | R13: =IF($S13>0,IF(K13=0,"原始0：需核实适用/报告口径",""),"") | S13: =IF(AND(WF_MODEL_VALID,A13<=WF_REVIEW_SLOTS),MATCH(A13,BankCalc!$U$2:$U$55,0)+1,0) -> 0
