Workbook

Sheet Parameters
A1: USDA RURAL DEVELOPMENT — CENTRALIZED TRAINING BUDGET (Nov 29 – Dec 1, 2026)
A2: Adjust the yellow cells. Daily, Options, Historical and Thresholds sheets recompute automatically. No internet pricing is pulled; quotes are a 2026-10-24 snapshot.
A4: Parameter | B4: Value | C4: Allowed range / note | D4: Unit
A5: Approved budget ceiling (incl. reserve) | B5: 53000 | C5: 0 – 100,000 (incl. reserve) | D5: USD
A6: Airfare adjustment factor | B6: 1 | C6: 0.5 – 2.0; stress scenario = factor × 1.20
A7: Contingency reserve rate | B7: 0.05 | C7: 0 – 20% of base subtotal
A8: Nov 29 breakfast provided by government? | B8: No | C8: Yes/No — 'Yes' adds NO new purchase
A9: Attendee count (headcount) | B9: =INDEX(Candidate_Model!C:C,Decision!B12) -> 24 | C9: Automatically selected conditional headcount; no claim of business necessity.
A10: Lodging nights | B10: =MAX(0,B14-B13) -> 4 | C10: Automatically recalculated from arrival / departure; no fixed 4-night assumption | D10: nights
A11: Internal lodging-tax rate (budget est.) | B11: 0.12 | C11: 12% of reimbursable lodging — planning only
A12: Registration fee per person | B12: 180 | C12: Incl. lunches Nov 29/30 & Dec 1 | D12: USD
A13: Arrival date | B13: 46354 | C13: Day before training; must fully attend
A14: Departure date | B14: 46358 | C14: Day after training
A15: Training dates (fixed) | B15: 2026-11-29 → 2026-12-01 | C15: Catered dates unchanged
A18: Key regulatory basis:
A19: Use actual room quote, never truncate over-cap quote to reimbursement cap. Internal 12% tax is a task assumption.
A20: FTR301-11.17/.18/.101: hotel complimentary meals do not reduce M&IE; government meals do; travel days 75%, then full meal deductions, minimum incidentals.
A21: Tea/coffee/fruit refreshments do not reduce M&IE. Registration already purchases the three training lunches: no second procurement charge.
A22: Government meals reduce traveler M&IE; net traveler M&IE AND agency catering estimates are both included in this budget.
A23: RD2036-A, 07/19/2024, sec2036.74: compare sites and verify approval requirements; see Sources and approval_register.csv.
A24: • Over-cap hotels are NOT compliant recommendations without written actual-expense authorization (301-11.300/.301); none is held.
A30: SNAPSHOT: Word, CSV, PPT and approval PDF are static. Change parameters -> recalculate, recheck quote validity and re-export all four. Blank unknowns are NOT zero-cost quotes.
A34: Quote applicability | B34: =IF(AND(B13=DATE(2026,11,28),B14=DATE(2026,12,2)),"DATED SNAPSHOT; inventory unheld","STALE: RE-QUOTE; computed costs are old-price estimates") -> DATED SNAPSHOT; inventory unheld
A35: Priority city for Daily detail | B35: =INDEX(Candidate_Model!B:B,Decision!B12) -> Boston
A36: Full attendance / period coverage | B36: =IF(AND(B13<=DATE(2026,11,28),B14>=DATE(2026,12,2),B14>B13,B14-B13<=365),"VALID DATE STRUCTURE","NOT VERIFIED FOR FULL TRAINING OR OUTSIDE DAILY GRID") -> VALID DATE STRUCTURE

Sheet CityData
A1: EXISTING QUOTE ANCHORS, corrected against real screenshots; single-seat/room planning only, not approved or held
A2: City | B2: Dest airport | C2: Flight RT /person, origin in airline/source field | D2: Flight airline | E2: Hotel (budgeted) | F2: Hotel nightly (excl tax) | G2: Displayed score normalized /10 (source scale in HotelQuality) | H2: Review count visible in retained capture | I2: Breakfast incl? | J2: FY27 cap Nov night | K2: FY27 cap Dec1 night | L2: MIE (FY27)
A3: Boston | B3: BOS | C3: 311 | D3: See Google Flights screenshot, DCA | E3: DoubleTree by Hilton Boston Bayside | F3: 108 | G3: 8.6 | H3: 449 | I3: Unknown | J3: 213 | K3: 213 | L3: 92
A4: Chicago | B4: ORD | C4: 270 | D4: See Google Flights screenshot, DCA | E4: Embassy Suites by Hilton Chicago O’Hare Rosemont | F4: 158 | G4: 8.2 | H4: 3418 | I4: Agoda158: free breakfast shown; single occupancy UNVERIFIED | J4: 232 | K4: 148 | L4: 92
A5: Denver | B5: DEN | C5: 578 | D5: See Google Flights screenshot, IAD | E5: Home2 Suites by Hilton Denver Downtown Convention Center | F5: 109 | G5: 9 | H5: 94 | I5: Yes | J5: 170 | K5: 170 | L5: 92
A6: Phoenix | B6: PHX | C6: 499 | D6: See Google Flights screenshot, IAD | E6: Hampton Inn & Suites Phoenix North/Happy Valley | F6: 150 | G6: 9.4 | H6: 116 | I6: Yes | J6: 165 | K6: 165 | L6: 86
A7: Seattle | B7: SEA | C7: 590 | D7: See Google Flights screenshot, IAD | E7: Country Inn & Suites by Radisson Seattle-Tacoma International Airport | F7: 101 | G7: 8.6 | H7: 2018 | I7: Booking101: free breakfast shown; 2 guests, single occupancy UNVERIFIED | J7: 188 | K7: 188 | L7: 92
A9: Meal planning rates (GSA FY2027 M&IE components, internal catering estimate):
A10: City | B10: Breakfast $ | C10: Lunch $ | D10: Dinner $
A11: Boston | B11: 23 | C11: 26 | D11: 38
A12: Chicago | B12: 23 | C12: 26 | D12: 38
A13: Denver | B13: 23 | C13: 26 | D13: 38
A14: Phoenix | B14: 22 | C14: 23 | D14: 36
A15: Seattle | B15: 23 | C15: 26 | D15: 38
A17: Personal ground planning allowances: HQ comparison base, road travel for early flights; not claimed home addresses/receipts. Venue transfer still unquoted.
A18: City | B18: Airport↔hotel RT $ | C18: Home↔DCA RT $
A19: Boston | B19: 40 | C19: 80
A20: Chicago | B20: 40 | C20: 80
A21: Denver | B21: 60 | C21: 160
A22: Phoenix | B22: 50 | C22: 160
A23: Seattle | B23: 60 | C23: 160
A25: Shared/fixed & light-refreshment planning inputs (to be quoted — see Sources):
A26: Venue quote not provided: use independent Unknowns inputs, never a shared fictitious supplier price. | B26: 0
A27: Venue days | B27: 3
A28: Light refreshments per person/day (301-74.7) | B28: 15
A29: Refreshment days | B29: 3

Sheet Daily
A1: DAILY PARTIAL COST DETAIL — priority for evidence completion, not approved recommendation
A2: Recommended city: | B2: =Parameters!B35 -> Boston | C2: (change to Boston/Chicago/Denver/Phoenix/Seattle — pulls that city's anchor data)
A4: Per-person building blocks
A5: Round-trip airfare (× airfare factor) | B5: =INDEX(Candidate_Model!D:D,Decision!B12)*FFAC -> 311
A6: Lodging — room only (nightly × nights) | B6: =INDEX(Candidate_Model!E:E,Decision!B12)*NIGHTS -> 432
A7: Lodging tax (internal est.) | B7: =B6*TAXRATE -> 51.84
A8: Registration fee (incl. 3 lunches) | B8: =REGFEE -> 180
A9: Agency dinners (Nov 28 & Dec 1) | B9: =2*INDEX(CityData!$D$11:$D$15,MATCH(Daily!$B$2,CityData!$A$11:$A$15,0)) -> 76
A10: Agency lunch (Dec 2 travel-home day) | B10: =INDEX(CityData!$C$11:$C$15,MATCH(Daily!$B$2,CityData!$A$11:$A$15,0)) -> 26
A11: Extra hotel breakfast: NOT a verified rate; enter Unknowns if required | B11: 0
A12: Government-breakfast toggle changes net MIE below, not new procurement | B12: 0
A13: Light refreshments (coffee/fruit/water) | B13: =REFRPP*REFRDAYS -> 45
A14: Ground transport (airport↔hotel + home↔DCA) | B14: =INDEX(Candidate_Model!F:F,Decision!B12) -> 120
A15: PER-PERSON SUBTOTAL | B15: =SUM(B5:B14)+B31 -> 1475.84
A17: Shared / fixed costs (per event)
A18: Additional unknown cost scenario for selected city/headcount | B18: =SUM(INDEX(Candidate_Model!I:I,Decision!B12)) -> 0
A19: FIXED SUBTOTAL | B19: =B18 -> 0
A21: EVENT TOTALS (at chosen headcount)
A22: Headcount (param) | B22: =HEADCOUNT -> 24
A23: Variable total (per-person × headcount) | B23: =B15*HEADCOUNT -> 35420.16
A24: Base subtotal (variable + fixed) | B24: =B23+B19 -> 35420.16
A25: Contingency reserve | B25: =B24*RESRATE -> 1771.008
A26: GRAND TOTAL (base + reserve) | B26: =B24+B25 -> 37191.168
A27: Budget ceiling | B27: =CEILING -> 53000
A28: Within budget? | B28: =IF(B26<=CEILING,"YES — within ceiling","NO — exceeds ceiling") -> YES — within ceiling
A29: Headroom for unquoted/TBD base costs | B29: =CEILING/(1+RESRATE)-B24 -> 15056.03
A31: Net traveler MIE /person (included in B15 and event budget) | B31: =SUM(INDEX(MIE_Daily!$B$2:$AO$367,0,5+8*(MATCH(B2,CityData!A3:A7,0)-1))) -> 234
A33: All displayed totals are partial estimates with unresolved U, not complete approved costs.
A34: Selected combination ID (qualified first, otherwise evidence priority) | B34: =INDEX(Candidate_Model!A:A,Decision!B12) -> P01
A35: Date | B35: Net traveler MIE/person | C35: Lodging+tax/person | D35: Headcount | E35: MIE group | F35: Lodging group | G35: Note
A36: =MIE_Daily!A2 -> 46354 | B36: =INDEX(MIE_Daily!$B$2:$AO$367,ROW()-35,5+8*(MATCH($B$2,CityData!$A$3:$A$7,0)-1)) -> 31 | C36: =IF(AND(A36<>"",A36<Parameters!$B$14),INDEX(Candidate_Model!E:E,Decision!B12)*(1+TAXRATE),0) -> 120.96 | D36: =HEADCOUNT -> 24 | E36: =B36*D36 -> 744 | F36: =C36*D36 -> 2903.04 | G36: Government meals on fixed calendar dates; hotel breakfast/refreshments not deducted.
A37: =MIE_Daily!A3 -> 46355 | B37: =INDEX(MIE_Daily!$B$2:$AO$367,ROW()-35,5+8*(MATCH($B$2,CityData!$A$3:$A$7,0)-1)) -> 66 | C37: =IF(AND(A37<>"",A37<Parameters!$B$14),INDEX(Candidate_Model!E:E,Decision!B12)*(1+TAXRATE),0) -> 120.96 | D37: =HEADCOUNT -> 24 | E37: =B37*D37 -> 1584 | F37: =C37*D37 -> 2903.04 | G37: Government meals on fixed calendar dates; hotel breakfast/refreshments not deducted.
A38: =MIE_Daily!A4 -> 46356 | B38: =INDEX(MIE_Daily!$B$2:$AO$367,ROW()-35,5+8*(MATCH($B$2,CityData!$A$3:$A$7,0)-1)) -> 66 | C38: =IF(AND(A38<>"",A38<Parameters!$B$14),INDEX(Candidate_Model!E:E,Decision!B12)*(1+TAXRATE),0) -> 120.96 | D38: =HEADCOUNT -> 24 | E38: =B38*D38 -> 1584 | F38: =C38*D38 -> 2903.04 | G38: Government meals on fixed calendar dates; hotel breakfast/refreshments not deducted.
A39: =MIE_Daily!A5 -> 46357 | B39: =INDEX(MIE_Daily!$B$2:$AO$367,ROW()-35,5+8*(MATCH($B$2,CityData!$A$3:$A$7,0)-1)) -> 28 | C39: =IF(AND(A39<>"",A39<Parameters!$B$14),INDEX(Candidate_Model!E:E,Decision!B12)*(1+TAXRATE),0) -> 120.96 | D39: =HEADCOUNT -> 24 | E39: =B39*D39 -> 672 | F39: =C39*D39 -> 2903.04 | G39: Government meals on fixed calendar dates; hotel breakfast/refreshments not deducted.
A40: =MIE_Daily!A6 -> 46358 | B40: =INDEX(MIE_Daily!$B$2:$AO$367,ROW()-35,5+8*(MATCH($B$2,CityData!$A$3:$A$7,0)-1)) -> 43 | C40: =IF(AND(A40<>"",A40<Parameters!$B$14),INDEX(Candidate_Model!E:E,Decision!B12)*(1+TAXRATE),0) -> 0 | D40: =HEADCOUNT -> 24 | E40: =B40*D40 -> 1032 | F40: =C40*D40 -> 0 | G40: Government meals on fixed calendar dates; hotel breakfast/refreshments not deducted.
A41: =MIE_Daily!A7 | B41: =INDEX(MIE_Daily!$B$2:$AO$367,ROW()-35,5+8*(MATCH($B$2,CityData!$A$3:$A$7,0)-1)) -> 0 | C41: =IF(AND(A41<>"",A41<Parameters!$B$14),INDEX(Candidate_Model!E:E,Decision!B12)*(1+TAXRATE),0) -> 0 | D41: =HEADCOUNT -> 24 | E41: =B41*D41 -> 0 | F41: =C41*D41 -> 0 | G41: Government meals on fixed calendar dates; hotel breakfast/refreshments not deducted.
A42: =MIE_Daily!A8 | B42: =INDEX(MIE_Daily!$B$2:$AO$367,ROW()-35,5+8*(MATCH($B$2,CityData!$A$3:$A$7,0)-1)) -> 0 | C42: =IF(AND(A42<>"",A42<Parameters!$B$14),INDEX(Candidate_Model!E:E,Decision!B12)*(1+TAXRATE),0) -> 0 | D42: =HEADCOUNT -> 24 | E42: =B42*D42 -> 0 | F42: =C42*D42 -> 0 | G42: Government meals on fixed calendar dates; hotel breakfast/refreshments not deducted.
A43: =MIE_Daily!A9 | B43: =INDEX(MIE_Daily!$B$2:$AO$367,ROW()-35,5+8*(MATCH($B$2,CityData!$A$3:$A$7,0)-1)) -> 0 | C43: =IF(AND(A43<>"",A43<Parameters!$B$14),INDEX(Candidate_Model!E:E,Decision!B12)*(1+TAXRATE),0) -> 0 | D43: =HEADCOUNT -> 24 | E43: =B43*D43 -> 0 | F43: =C43*D43 -> 0 | G43: Government meals on fixed calendar dates; hotel breakfast/refreshments not deducted.
A44: =MIE_Daily!A10 | B44: =INDEX(MIE_Daily!$B$2:$AO$367,ROW()-35,5+8*(MATCH($B$2,CityData!$A$3:$A$7,0)-1)) -> 0 | C44: =IF(AND(A44<>"",A44<Parameters!$B$14),INDEX(Candidate_Model!E:E,Decision!B12)*(1+TAXRATE),0) -> 0 | D44: =HEADCOUNT -> 24 | E44: =B44*D44 -> 0 | F44: =C44*D44 -> 0 | G44: Government meals on fixed calendar dates; hotel breakfast/refreshments not deducted.
A45: =MIE_Daily!A11 | B45: =INDEX(MIE_Daily!$B$2:$AO$367,ROW()-35,5+8*(MATCH($B$2,CityData!$A$3:$A$7,0)-1)) -> 0 | C45: =IF(AND(A45<>"",A45<Parameters!$B$14),INDEX(Candidate_Model!E:E,Decision!B12)*(1+TAXRATE),0) -> 0 | D45: =HEADCOUNT -> 24 | E45: =B45*D45 -> 0 | F45: =C45*D45 -> 0 | G45: Government meals on fixed calendar dates; hotel breakfast/refreshments not deducted.
A46: =MIE_Daily!A12 | B46: =INDEX(MIE_Daily!$B$2:$AO$367,ROW()-35,5+8*(MATCH($B$2,CityData!$A$3:$A$7,0)-1)) -> 0 | C46: =IF(AND(A46<>"",A46<Parameters!$B$14),INDEX(Candidate_Model!E:E,Decision!B12)*(1+TAXRATE),0) -> 0 | D46: =HEADCOUNT -> 24 | E46: =B46*D46 -> 0 | F46: =C46*D46 -> 0 | G46: Government meals on fixed calendar dates; hotel breakfast/refreshments not deducted.
A47: =MIE_Daily!A13 | B47: =INDEX(MIE_Daily!$B$2:$AO$367,ROW()-35,5+8*(MATCH($B$2,CityData!$A$3:$A$7,0)-1)) -> 0 | C47: =IF(AND(A47<>"",A47<Parameters!$B$14),INDEX(Candidate_Model!E:E,Decision!B12)*(1+TAXRATE),0) -> 0 | D47: =HEADCOUNT -> 24 | E47: =B47*D47 -> 0 | F47: =C47*D47 -> 0 | G47: Government meals on fixed calendar dates; hotel breakfast/refreshments not deducted.
A48: =MIE_Daily!A14 | B48: =INDEX(MIE_Daily!$B$2:$AO$367,ROW()-35,5+8*(MATCH($B$2,CityData!$A$3:$A$7,0)-1)) -> 0 | C48: =IF(AND(A48<>"",A48<Parameters!$B$14),INDEX(Candidate_Model!E:E,Decision!B12)*(1+TAXRATE),0) -> 0 | D48: =HEADCOUNT -> 24 | E48: =B48*D48 -> 0 | F48: =C48*D48 -> 0 | G48: Government meals on fixed calendar dates; hotel breakfast/refreshments not deducted.
A49: =MIE_Daily!A15 | B49: =INDEX(MIE_Daily!$B$2:$AO$367,ROW()-35,5+8*(MATCH($B$2,CityData!$A$3:$A$7,0)-1)) -> 0 | C49: =IF(AND(A49<>"",A49<Parameters!$B$14),INDEX(Candidate_Model!E:E,Decision!B12)*(1+TAXRATE),0) -> 0 | D49: =HEADCOUNT -> 24 | E49: =B49*D49 -> 0 | F49: =C49*D49 -> 0 | G49: Government meals on fixed calendar dates; hotel breakfast/refreshments not deducted.
A50: =MIE_Daily!A16 | B50: =INDEX(MIE_Daily!$B$2:$AO$367,ROW()-35,5+8*(MATCH($B$2,CityData!$A$3:$A$7,0)-1)) -> 0 | C50: =IF(AND(A50<>"",A50<Parameters!$B$14),INDEX(Candidate_Model!E:E,Decision!B12)*(1+TAXRATE),0) -> 0 | D50: =HEADCOUNT -> 24 | E50: =B50*D50 -> 0 | F50: =C50*D50 -> 0 | G50: Government meals on fixed calendar dates; hotel breakfast/refreshments not deducted.
A51: =MIE_Daily!A17 | B51: =INDEX(MIE_Daily!$B$2:$AO$367,ROW()-35,5+8*(MATCH($B$2,CityData!$A$3:$A$7,0)-1)) -> 0 | C51: =IF(AND(A51<>"",A51<Parameters!$B$14),INDEX(Candidate_Model!E:E,Decision!B12)*(1+TAXRATE),0) -> 0 | D51: =HEADCOUNT -> 24 | E51: =B51*D51 -> 0 | F51: =C51*D51 -> 0 | G51: Government meals on fixed calendar dates; hotel breakfast/refreshments not deducted.
A52: =MIE_Daily!A18 | B52: =INDEX(MIE_Daily!$B$2:$AO$367,ROW()-35,5+8*(MATCH($B$2,CityData!$A$3:$A$7,0)-1)) -> 0 | C52: =IF(AND(A52<>"",A52<Parameters!$B$14),INDEX(Candidate_Model!E:E,Decision!B12)*(1+TAXRATE),0) -> 0 | D52: =HEADCOUNT -> 24 | E52: =B52*D52 -> 0 | F52: =C52*D52 -> 0 | G52: Government meals on fixed calendar dates; hotel breakfast/refreshments not deducted.
A53: =MIE_Daily!A19 | B53: =INDEX(MIE_Daily!$B$2:$AO$367,ROW()-35,5+8*(MATCH($B$2,CityData!$A$3:$A$7,0)-1)) -> 0 | C53: =IF(AND(A53<>"",A53<Parameters!$B$14),INDEX(Candidate_Model!E:E,Decision!B12)*(1+TAXRATE),0) -> 0 | D53: =HEADCOUNT -> 24 | E53: =B53*D53 -> 0 | F53: =C53*D53 -> 0 | G53: Government meals on fixed calendar dates; hotel breakfast/refreshments not deducted.
A54: =MIE_Daily!A20 | B54: =INDEX(MIE_Daily!$B$2:$AO$367,ROW()-35,5+8*(MATCH($B$2,CityData!$A$3:$A$7,0)-1)) -> 0 | C54: =IF(AND(A54<>"",A54<Parameters!$B$14),INDEX(Candidate_Model!E:E,Decision!B12)*(1+TAXRATE),0) -> 0 | D54: =HEADCOUNT -> 24 | E54: =B54*D54 -> 0 | F54: =C54*D54 -> 0 | G54: Government meals on fixed calendar dates; hotel breakfast/refreshments not deducted.
A55: =MIE_Daily!A21 | B55: =INDEX(MIE_Daily!$B$2:$AO$367,ROW()-35,5+8*(MATCH($B$2,CityData!$A$3:$A$7,0)-1)) -> 0 | C55: =IF(AND(A55<>"",A55<Parameters!$B$14),INDEX(Candidate_Model!E:E,Decision!B12)*(1+TAXRATE),0) -> 0 | D55: =HEADCOUNT -> 24 | E55: =B55*D55 -> 0 | F55: =C55*D55 -> 0 | G55: Government meals on fixed calendar dates; hotel breakfast/refreshments not deducted.
A56: =MIE_Daily!A22 | B56: =INDEX(MIE_Daily!$B$2:$AO$367,ROW()-35,5+8*(MATCH($B$2,CityData!$A$3:$A$7,0)-1)) -> 0 | C56: =IF(AND(A56<>"",A56<Parameters!$B$14),INDEX(Candidate_Model!E:E,Decision!B12)*(1+TAXRATE),0) -> 0 | D56: =HEADCOUNT -> 24 | E56: =B56*D56 -> 0 | F56: =C56*D56 -> 0 | G56: Government meals on fixed calendar dates; hotel breakfast/refreshments not deducted.
A57: =MIE_Daily!A23 | B57: =INDEX(MIE_Daily!$B$2:$AO$367,ROW()-35,5+8*(MATCH($B$2,CityData!$A$3:$A$7,0)-1)) -> 0 | C57: =IF(AND(A57<>"",A57<Parameters!$B$14),INDEX(Candidate_Model!E:E,Decision!B12)*(1+TAXRATE),0) -> 0 | D57: =HEADCOUNT -> 24 | E57: =B57*D57 -> 0 | F57: =C57*D57 -> 0 | G57: Government meals on fixed calendar dates; hotel breakfast/refreshments not deducted.
A58: =MIE_Daily!A24 | B58: =INDEX(MIE_Daily!$B$2:$AO$367,ROW()-35,5+8*(MATCH($B$2,CityData!$A$3:$A$7,0)-1)) -> 0 | C58: =IF(AND(A58<>"",A58<Parameters!$B$14),INDEX(Candidate_Model!E:E,Decision!B12)*(1+TAXRATE),0) -> 0 | D58: =HEADCOUNT -> 24 | E58: =B58*D58 -> 0 | F58: =C58*D58 -> 0 | G58: Government meals on fixed calendar dates; hotel breakfast/refreshments not deducted.
A59: =MIE_Daily!A25 | B59: =INDEX(MIE_Daily!$B$2:$AO$367,ROW()-35,5+8*(MATCH($B$2,CityData!$A$3:$A$7,0)-1)) -> 0 | C59: =IF(AND(A59<>"",A59<Parameters!$B$14),INDEX(Candidate_Model!E:E,Decision!B12)*(1+TAXRATE),0) -> 0 | D59: =HEADCOUNT -> 24 | E59: =B59*D59 -> 0 | F59: =C59*D59 -> 0 | G59: Government meals on fixed calendar dates; hotel breakfast/refreshments not deducted.
A60: =MIE_Daily!A26 | B60: =INDEX(MIE_Daily!$B$2:$AO$367,ROW()-35,5+8*(MATCH($B$2,CityData!$A$3:$A$7,0)-1)) -> 0 | C60: =IF(AND(A60<>"",A60<Parameters!$B$14),INDEX(Candidate_Model!E:E,Decision!B12)*(1+TAXRATE),0) -> 0 | D60: =HEADCOUNT -> 24 | E60: =B60*D60 -> 0 | F60: =C60*D60 -> 0 | G60: Government meals on fixed calendar dates; hotel breakfast/refreshments not deducted.
A61: =MIE_Daily!A27 | B61: =INDEX(MIE_Daily!$B$2:$AO$367,ROW()-35,5+8*(MATCH($B$2,CityData!$A$3:$A$7,0)-1)) -> 0 | C61: =IF(AND(A61<>"",A61<Parameters!$B$14),INDEX(Candidate_Model!E:E,Decision!B12)*(1+TAXRATE),0) -> 0 | D61: =HEADCOUNT -> 24 | E61: =B61*D61 -> 0 | F61: =C61*D61 -> 0 | G61: Government meals on fixed calendar dates; hotel breakfast/refreshments not deducted.
A62: =MIE_Daily!A28 | B62: =INDEX(MIE_Daily!$B$2:$AO$367,ROW()-35,5+8*(MATCH($B$2,CityData!$A$3:$A$7,0)-1)) -> 0 | C62: =IF(AND(A62<>"",A62<Parameters!$B$14),INDEX(Candidate_Model!E:E,Decision!B12)*(1+TAXRATE),0) -> 0 | D62: =HEADCOUNT -> 24 | E62: =B62*D62 -> 0 | F62: =C62*D62 -> 0 | G62: Government meals on fixed calendar dates; hotel breakfast/refreshments not deducted.
A63: =MIE_Daily!A29 | B63: =INDEX(MIE_Daily!$B$2:$AO$367,ROW()-35,5+8*(MATCH($B$2,CityData!$A$3:$A$7,0)-1)) -> 0 | C63: =IF(AND(A63<>"",A63<Parameters!$B$14),INDEX(Candidate_Model!E:E,Decision!B12)*(1+TAXRATE),0) -> 0 | D63: =HEADCOUNT -> 24 | E63: =B63*D63 -> 0 | F63: =C63*D63 -> 0 | G63: Government meals on fixed calendar dates; hotel breakfast/refreshments not deducted.
A64: =MIE_Daily!A30 | B64: =INDEX(MIE_Daily!$B$2:$AO$367,ROW()-35,5+8*(MATCH($B$2,CityData!$A$3:$A$7,0)-1)) -> 0 | C64: =IF(AND(A64<>"",A64<Parameters!$B$14),INDEX(Candidate_Model!E:E,Decision!B12)*(1+TAXRATE),0) -> 0 | D64: =HEADCOUNT -> 24 | E64: =B64*D64 -> 0 | F64: =C64*D64 -> 0 | G64: Government meals on fixed calendar dates; hotel breakfast/refreshments not deducted.
A65: =MIE_Daily!A31 | B65: =INDEX(MIE_Daily!$B$2:$AO$367,ROW()-35,5+8*(MATCH($B$2,CityData!$A$3:$A$7,0)-1)) -> 0 | C65: =IF(AND(A65<>"",A65<Parameters!$B$14),INDEX(Candidate_Model!E:E,Decision!B12)*(1+TAXRATE),0) -> 0 | D65: =HEADCOUNT -> 24 | E65: =B65*D65 -> 0 | F65: =C65*D65 -> 0 | G65: Government meals on fixed calendar dates; hotel breakfast/refreshments not deducted.
A66: =MIE_Daily!A32 | B66: =INDEX(MIE_Daily!$B$2:$AO$367,ROW()-35,5+8*(MATCH($B$2,CityData!$A$3:$A$7,0)-1)) -> 0 | C66: =IF(AND(A66<>"",A66<Parameters!$B$14),INDEX(Candidate_Model!E:E,Decision!B12)*(1+TAXRATE),0) -> 0 | D66: =HEADCOUNT -> 24 | E66: =B66*D66 -> 0 | F66: =C66*D66 -> 0 | G66: Government meals on fixed calendar dates; hotel breakfast/refreshments not deducted.
A67: =MIE_Daily!A33 | B67: =INDEX(MIE_Daily!$B$2:$AO$367,ROW()-35,5+8*(MATCH($B$2,CityData!$A$3:$A$7,0)-1)) -> 0 | C67: =IF(AND(A67<>"",A67<Parameters!$B$14),INDEX(Candidate_Model!E:E,Decision!B12)*(1+TAXRATE),0) -> 0 | D67: =HEADCOUNT -> 24 | E67: =B67*D67 -> 0 | F67: =C67*D67 -> 0 | G67: Government meals on fixed calendar dates; hotel breakfast/refreshments not deducted.
A68: =MIE_Daily!A34 | B68: =INDEX(MIE_Daily!$B$2:$AO$367,ROW()-35,5+8*(MATCH($B$2,CityData!$A$3:$A$7,0)-1)) -> 0 | C68: =IF(AND(A68<>"",A68<Parameters!$B$14),INDEX(Candidate_Model!E:E,Decision!B12)*(1+TAXRATE),0) -> 0 | D68: =HEADCOUNT -> 24 | E68: =B68*D68 -> 0 | F68: =C68*D68 -> 0 | G68: Government meals on fixed calendar dates; hotel breakfast/refreshments not deducted.
A69: =MIE_Daily!A35 | B69: =INDEX(MIE_Daily!$B$2:$AO$367,ROW()-35,5+8*(MATCH($B$2,CityData!$A$3:$A$7,0)-1)) -> 0 | C69: =IF(AND(A69<>"",A69<Parameters!$B$14),INDEX(Candidate_Model!E:E,Decision!B12)*(1+TAXRATE),0) -> 0 | D69: =HEADCOUNT -> 24 | E69: =B69*D69 -> 0 | F69: =C69*D69 -> 0 | G69: Government meals on fixed calendar dates; hotel breakfast/refreshments not deducted.
A70: =MIE_Daily!A36 | B70: =INDEX(MIE_Daily!$B$2:$AO$367,ROW()-35,5+8*(MATCH($B$2,CityData!$A$3:$A$7,0)-1)) -> 0 | C70: =IF(AND(A70<>"",A70<Parameters!$B$14),INDEX(Candidate_Model!E:E,Decision!B12)*(1+TAXRATE),0) -> 0 | D70: =HEADCOUNT -> 24 | E70: =B70*D70 -> 0 | F70: =C70*D70 -> 0 | G70: Government meals on fixed calendar dates; hotel breakfast/refreshments not deducted.
A71: =MIE_Daily!A37 | B71: =INDEX(MIE_Daily!$B$2:$AO$367,ROW()-35,5+8*(MATCH($B$2,CityData!$A$3:$A$7,0)-1)) -> 0 | C71: =IF(AND(A71<>"",A71<Parameters!$B$14),INDEX(Candidate_Model!E:E,Decision!B12)*(1+TAXRATE),0) -> 0 | D71: =HEADCOUNT -> 24 | E71: =B71*D71 -> 0 | F71: =C71*D71 -> 0 | G71: Government meals on fixed calendar dates; hotel breakfast/refreshments not deducted.
A72: =MIE_Daily!A38 | B72: =INDEX(MIE_Daily!$B$2:$AO$367,ROW()-35,5+8*(MATCH($B$2,CityData!$A$3:$A$7,0)-1)) -> 0 | C72: =IF(AND(A72<>"",A72<Parameters!$B$14),INDEX(Candidate_Model!E:E,Decision!B12)*(1+TAXRATE),0) -> 0 | D72: =HEADCOUNT -> 24 | E72: =B72*D72 -> 0 | F72: =C72*D72 -> 0 | G72: Government meals on fixed calendar dates; hotel breakfast/refreshments not deducted.
A73: =MIE_Daily!A39 | B73: =INDEX(MIE_Daily!$B$2:$AO$367,ROW()-35,5+8*(MATCH($B$2,CityData!$A$3:$A$7,0)-1)) -> 0 | C73: =IF(AND(A73<>"",A73<Parameters!$B$14),INDEX(Candidate_Model!E:E,Decision!B12)*(1+TAXRATE),0) -> 0 | D73: =HEADCOUNT -> 24 | E73: =B73*D73 -> 0 | F73: =C73*D73 -> 0 | G73: Government meals on fixed calendar dates; hotel breakfast/refreshments not deducted.
A74: =MIE_Daily!A40 | B74: =INDEX(MIE_Daily!$B$2:$AO$367,ROW()-35,5+8*(MATCH($B$2,CityData!$A$3:$A$7,0)-1)) -> 0 | C74: =IF(AND(A74<>"",A74<Parameters!$B$14),INDEX(Candidate_Model!E:E,Decision!B12)*(1+TAXRATE),0) -> 0 | D74: =HEADCOUNT -> 24 | E74: =B74*D74 -> 0 | F74: =C74*D74 -> 0 | G74: Government meals on fixed calendar dates; hotel breakfast/refreshments not deducted.
A75: =MIE_Daily!A41 | B75: =INDEX(MIE_Daily!$B$2:$AO$367,ROW()-35,5+8*(MATCH($B$2,CityData!$A$3:$A$7,0)-1)) -> 0 | C75: =IF(AND(A75<>"",A75<Parameters!$B$14),INDEX(Candidate_Model!E:E,Decision!B12)*(1+TAXRATE),0) -> 0 | D75: =HEADCOUNT -> 24 | E75: =B75*D75 -> 0 | F75: =C75*D75 -> 0 | G75: Government meals on fixed calendar dates; hotel breakfast/refreshments not deducted.
A76: =MIE_Daily!A42 | B76: =INDEX(MIE_Daily!$B$2:$AO$367,ROW()-35,5+8*(MATCH($B$2,CityData!$A$3:$A$7,0)-1)) -> 0 | C76: =IF(AND(A76<>"",A76<Parameters!$B$14),INDEX(Candidate_Model!E:E,Decision!B12)*(1+TAXRATE),0) -> 0 | D76: =HEADCOUNT -> 24 | E76: =B76*D76 -> 0 | F76: =C76*D76 -> 0 | G76: Government meals on fixed calendar dates; hotel breakfast/refreshments not deducted.
A77: =MIE_Daily!A43 | B77: =INDEX(MIE_Daily!$B$2:$AO$367,ROW()-35,5+8*(MATCH($B$2,CityData!$A$3:$A$7,0)-1)) -> 0 | C77: =IF(AND(A77<>"",A77<Parameters!$B$14),INDEX(Candidate_Model!E:E,Decision!B12)*(1+TAXRATE),0) -> 0 | D77: =HEADCOUNT -> 24 | E77: =B77*D77 -> 0 | F77: =C77*D77 -> 0 | G77: Government meals on fixed calendar dates; hotel breakfast/refreshments not deducted.
A78: =MIE_Daily!A44 | B78: =INDEX(MIE_Daily!$B$2:$AO$367,ROW()-35,5+8*(MATCH($B$2,CityData!$A$3:$A$7,0)-1)) -> 0 | C78: =IF(AND(A78<>"",A78<Parameters!$B$14),INDEX(Candidate_Model!E:E,Decision!B12)*(1+TAXRATE),0) -> 0 | D78: =HEADCOUNT -> 24 | E78: =B78*D78 -> 0 | F78: =C78*D78 -> 0 | G78: Government meals on fixed calendar dates; hotel breakfast/refreshments not deducted.
A79: =MIE_Daily!A45 | B79: =INDEX(MIE_Daily!$B$2:$AO$367,ROW()-35,5+8*(MATCH($B$2,CityData!$A$3:$A$7,0)-1)) -> 0 | C79: =IF(AND(A79<>"",A79<Parameters!$B$14),INDEX(Candidate_Model!E:E,Decision!B12)*(1+TAXRATE),0) -> 0 | D79: =HEADCOUNT -> 24 | E79: =B79*D79 -> 0 | F79: =C79*D79 -> 0 | G79: Government meals on fixed calendar dates; hotel breakfast/refreshments not deducted.
A80: =MIE_Daily!A46 | B80: =INDEX(MIE_Daily!$B$2:$AO$367,ROW()-35,5+8*(MATCH($B$2,CityData!$A$3:$A$7,0)-1)) -> 0 | C80: =IF(AND(A80<>"",A80<Parameters!$B$14),INDEX(Candidate_Model!E:E,Decision!B12)*(1+TAXRATE),0) -> 0 | D80: =HEADCOUNT -> 24 | E80: =B80*D80 -> 0 | F80: =C80*D80 -> 0 | G80: Government meals on fixed calendar dates; hotel breakfast/refreshments not deducted.
A81: =MIE_Daily!A47 | B81: =INDEX(MIE_Daily!$B$2:$AO$367,ROW()-35,5+8*(MATCH($B$2,CityData!$A$3:$A$7,0)-1)) -> 0 | C81: =IF(AND(A81<>"",A81<Parameters!$B$14),INDEX(Candidate_Model!E:E,Decision!B12)*(1+TAXRATE),0) -> 0 | D81: =HEADCOUNT -> 24 | E81: =B81*D81 -> 0 | F81: =C81*D81 -> 0 | G81: Government meals on fixed calendar dates; hotel breakfast/refreshments not deducted.
A82: =MIE_Daily!A48 | B82: =INDEX(MIE_Daily!$B$2:$AO$367,ROW()-35,5+8*(MATCH($B$2,CityData!$A$3:$A$7,0)-1)) -> 0 | C82: =IF(AND(A82<>"",A82<Parameters!$B$14),INDEX(Candidate_Model!E:E,Decision!B12)*(1+TAXRATE),0) -> 0 | D82: =HEADCOUNT -> 24 | E82: =B82*D82 -> 0 | F82: =C82*D82 -> 0 | G82: Government meals on fixed calendar dates; hotel breakfast/refreshments not deducted.
A83: =MIE_Daily!A49 | B83: =INDEX(MIE_Daily!$B$2:$AO$367,ROW()-35,5+8*(MATCH($B$2,CityData!$A$3:$A$7,0)-1)) -> 0 | C83: =IF(AND(A83<>"",A83<Parameters!$B$14),INDEX(Candidate_Model!E:E,Decision!B12)*(1+TAXRATE),0) -> 0 | D83: =HEADCOUNT -> 24 | E83: =B83*D83 -> 0 | F83: =C83*D83 -> 0 | G83: Government meals on fixed calendar dates; hotel breakfast/refreshments not deducted.
A84: =MIE_Daily!A50 | B84: =INDEX(MIE_Daily!$B$2:$AO$367,ROW()-35,5+8*(MATCH($B$2,CityData!$A$3:$A$7,0)-1)) -> 0 | C84: =IF(AND(A84<>"",A84<Parameters!$B$14),INDEX(Candidate_Model!E:E,Decision!B12)*(1+TAXRATE),0) -> 0 | D84: =HEADCOUNT -> 24 | E84: =B84*D84 -> 0 | F84: =C84*D84 -> 0 | G84: Government meals on fixed calendar dates; hotel breakfast/refreshments not deducted.
A85: =MIE_Daily!A51 | B85: =INDEX(MIE_Daily!$B$2:$AO$367,ROW()-35,5+8*(MATCH($B$2,CityData!$A$3:$A$7,0)-1)) -> 0 | C85: =IF(AND(A85<>"",A85<Parameters!$B$14),INDEX(Candidate_Model!E:E,Decision!B12)*(1+TAXRATE),0) -> 0 | D85: =HEADCOUNT -> 24 | E85: =B85*D85 -> 0 | F85: =C85*D85 -> 0 | G85: Government meals on fixed calendar dates; hotel breakfast/refreshments not deducted.
A86: =MIE_Daily!A52 | B86: =INDEX(MIE_Daily!$B$2:$AO$367,ROW()-35,5+8*(MATCH($B$2,CityData!$A$3:$A$7,0)-1)) -> 0 | C86: =IF(AND(A86<>"",A86<Parameters!$B$14),INDEX(Candidate_Model!E:E,Decision!B12)*(1+TAXRATE),0) -> 0 | D86: =HEADCOUNT -> 24 | E86: =B86*D86 -> 0 | F86: =C86*D86 -> 0 | G86: Government meals on fixed calendar dates; hotel breakfast/refreshments not deducted.
A87: =MIE_Daily!A53 | B87: =INDEX(MIE_Daily!$B$2:$AO$367,ROW()-35,5+8*(MATCH($B$2,CityData!$A$3:$A$7,0)-1)) -> 0 | C87: =IF(AND(A87<>"",A87<Parameters!$B$14),INDEX(Candidate_Model!E:E,Decision!B12)*(1+TAXRATE),0) -> 0 | D87: =HEADCOUNT -> 24 | E87: =B87*D87 -> 0 | F87: =C87*D87 -> 0 | G87: Government meals on fixed calendar dates; hotel breakfast/refreshments not deducted.
A88: =MIE_Daily!A54 | B88: =INDEX(MIE_Daily!$B$2:$AO$367,ROW()-35,5+8*(MATCH($B$2,CityData!$A$3:$A$7,0)-1)) -> 0 | C88: =IF(AND(A88<>"",A88<Parameters!$B$14),INDEX(Candidate_Model!E:E,Decision!B12)*(1+TAXRATE),0) -> 0 | D88: =HEADCOUNT -> 24 | E88: =B88*D88 -> 0 | F88: =C88*D88 -> 0 | G88: Government meals on fixed calendar dates; hotel breakfast/refreshments not deducted.
A89: =MIE_Daily!A55 | B89: =INDEX(MIE_Daily!$B$2:$AO$367,ROW()-35,5+8*(MATCH($B$2,CityData!$A$3:$A$7,0)-1)) -> 0 | C89: =IF(AND(A89<>"",A89<Parameters!$B$14),INDEX(Candidate_Model!E:E,Decision!B12)*(1+TAXRATE),0) -> 0 | D89: =HEADCOUNT -> 24 | E89: =B89*D89 -> 0 | F89: =C89*D89 -> 0 | G89: Government meals on fixed calendar dates; hotel breakfast/refreshments not deducted.
A90: =MIE_Daily!A56 | B90: =INDEX(MIE_Daily!$B$2:$AO$367,ROW()-35,5+8*(MATCH($B$2,CityData!$A$3:$A$7,0)-1)) -> 0 | C90: =IF(AND(A90<>"",A90<Parameters!$B$14),INDEX(Candidate_Model!E:E,Decision!B12)*(1+TAXRATE),0) -> 0 | D90: =HEADCOUNT -> 24 | E90: =B90*D90 -> 0 | F90: =C90*D90 -> 0 | G90: Government meals on fixed calendar dates; hotel breakfast/refreshments not deducted.
A91: =MIE_Daily!A57 | B91: =INDEX(MIE_Daily!$B$2:$AO$367,ROW()-35,5+8*(MATCH($B$2,CityData!$A$3:$A$7,0)-1)) -> 0 | C91: =IF(AND(A91<>"",A91<Parameters!$B$14),INDEX(Candidate_Model!E:E,Decision!B12)*(1+TAXRATE),0) -> 0 | D91: =HEADCOUNT -> 24 | E91: =B91*D91 -> 0 | F91: =C91*D91 -> 0 | G91: Government meals on fixed calendar dates; hotel breakfast/refreshments not deducted.
A92: =MIE_Daily!A58 | B92: =INDEX(MIE_Daily!$B$2:$AO$367,ROW()-35,5+8*(MATCH($B$2,CityData!$A$3:$A$7,0)-1)) -> 0 | C92: =IF(AND(A92<>"",A92<Parameters!$B$14),INDEX(Candidate_Model!E:E,Decision!B12)*(1+TAXRATE),0) -> 0 | D92: =HEADCOUNT -> 24 | E92: =B92*D92 -> 0 | F92: =C92*D92 -> 0 | G92: Government meals on fixed calendar dates; hotel breakfast/refreshments not deducted.
A93: =MIE_Daily!A59 | B93: =INDEX(MIE_Daily!$B$2:$AO$367,ROW()-35,5+8*(MATCH($B$2,CityData!$A$3:$A$7,0)-1)) -> 0 | C93: =IF(AND(A93<>"",A93<Parameters!$B$14),INDEX(Candidate_Model!E:E,Decision!B12)*(1+TAXRATE),0) -> 0 | D93: =HEADCOUNT -> 24 | E93: =B93*D93 -> 0 | F93: =C93*D93 -> 0 | G93: Government meals on fixed calendar dates; hotel breakfast/refreshments not deducted.
A94: =MIE_Daily!A60 | B94: =INDEX(MIE_Daily!$B$2:$AO$367,ROW()-35,5+8*(MATCH($B$2,CityData!$A$3:$A$7,0)-1)) -> 0 | C94: =IF(AND(A94<>"",A94<Parameters!$B$14),INDEX(Candidate_Model!E:E,Decision!B12)*(1+TAXRATE),0) -> 0 | D94: =HEADCOUNT -> 24 | E94: =B94*D94 -> 0 | F94: =C94*D94 -> 0 | G94: Government meals on fixed calendar dates; hotel breakfast/refreshments not deducted.
A95: =MIE_Daily!A61 | B95: =INDEX(MIE_Daily!$B$2:$AO$367,ROW()-35,5+8*(MATCH($B$2,CityData!$A$3:$A$7,0)-1)) -> 0 | C95: =IF(AND(A95<>"",A95<Parameters!$B$14),INDEX(Candidate_Model!E:E,Decision!B12)*(1+TAXRATE),0) -> 0 | D95: =HEADCOUNT -> 24 | E95: =B95*D95 -> 0 | F95: =C95*D95 -> 0 | G95: Government meals on fixed calendar dates; hotel breakfast/refreshments not deducted.
A96: =MIE_Daily!A62 | B96: =INDEX(MIE_Daily!$B$2:$AO$367,ROW()-35,5+8*(MATCH($B$2,CityData!$A$3:$A$7,0)-1)) -> 0 | C96: =IF(AND(A96<>"",A96<Parameters!$B$14),INDEX(Candidate_Model!E:E,Decision!B12)*(1+TAXRATE),0) -> 0 | D96: =HEADCOUNT -> 24 | E96: =B96*D96 -> 0 | F96: =C96*D96 -> 0 | G96: Government meals on fixed calendar dates; hotel breakfast/refreshments not deducted.
A97: =MIE_Daily!A63 | B97: =INDEX(MIE_Daily!$B$2:$AO$367,ROW()-35,5+8*(MATCH($B$2,CityData!$A$3:$A$7,0)-1)) -> 0 | C97: =IF(AND(A97<>"",A97<Parameters!$B$14),INDEX(Candidate_Model!E:E,Decision!B12)*(1+TAXRATE),0) -> 0 | D97: =HEADCOUNT -> 24 | E97: =B97*D97 -> 0 | F97: =C97*D97 -> 0 | G97: Government meals on fixed calendar dates; hotel breakfast/refreshments not deducted.
A98: =MIE_Daily!A64 | B98: =INDEX(MIE_Daily!$B$2:$AO$367,ROW()-35,5+8*(MATCH($B$2,CityData!$A$3:$A$7,0)-1)) -> 0 | C98: =IF(AND(A98<>"",A98<Parameters!$B$14),INDEX(Candidate_Model!E:E,Decision!B12)*(1+TAXRATE),0) -> 0 | D98: =HEADCOUNT -> 24 | E98: =B98*D98 -> 0 | F98: =C98*D98 -> 0 | G98: Government meals on fixed calendar dates; hotel breakfast/refreshments not deducted.
A99: =MIE_Daily!A65 | B99: =INDEX(MIE_Daily!$B$2:$AO$367,ROW()-35,5+8*(MATCH($B$2,CityData!$A$3:$A$7,0)-1)) -> 0 | C99: =IF(AND(A99<>"",A99<Parameters!$B$14),INDEX(Candidate_Model!E:E,Decision!B12)*(1+TAXRATE),0) -> 0 | D99: =HEADCOUNT -> 24 | E99: =B99*D99 -> 0 | F99: =C99*D99 -> 0 | G99: Government meals on fixed calendar dates; hotel breakfast/refreshments not deducted.
A100: =MIE_Daily!A66 | B100: =INDEX(MIE_Daily!$B$2:$AO$367,ROW()-35,5+8*(MATCH($B$2,CityData!$A$3:$A$7,0)-1)) -> 0 | C100: =IF(AND(A100<>"",A100<Parameters!$B$14),INDEX(Candidate_Model!E:E,Decision!B12)*(1+TAXRATE),0) -> 0 | D100: =HEADCOUNT -> 24 | E100: =B100*D100 -> 0 | F100: =C100*D100 -> 0 | G100: Government meals on fixed calendar dates; hotel breakfast/refreshments not deducted.
A101: =MIE_Daily!A67 | B101: =INDEX(MIE_Daily!$B$2:$AO$367,ROW()-35,5+8*(MATCH($B$2,CityData!$A$3:$A$7,0)-1)) -> 0 | C101: =IF(AND(A101<>"",A101<Parameters!$B$14),INDEX(Candidate_Model!E:E,Decision!B12)*(1+TAXRATE),0) -> 0 | D101: =HEADCOUNT -> 24 | E101: =B101*D101 -> 0 | F101: =C101*D101 -> 0 | G101: Government meals on fixed calendar dates; hotel breakfast/refreshments not deducted.
A102: =MIE_Daily!A68 | B102: =INDEX(MIE_Daily!$B$2:$AO$367,ROW()-35,5+8*(MATCH($B$2,CityData!$A$3:$A$7,0)-1)) -> 0 | C102: =IF(AND(A102<>"",A102<Parameters!$B$14),INDEX(Candidate_Model!E:E,Decision!B12)*(1+TAXRATE),0) -> 0 | D102: =HEADCOUNT -> 24 | E102: =B102*D102 -> 0 | F102: =C102*D102 -> 0 | G102: Government meals on fixed calendar dates; hotel breakfast/refreshments not deducted.
A103: =MIE_Daily!A69 | B103: =INDEX(MIE_Daily!$B$2:$AO$367,ROW()-35,5+8*(MATCH($B$2,CityData!$A$3:$A$7,0)-1)) -> 0 | C103: =IF(AND(A103<>"",A103<Parameters!$B$14),INDEX(Candidate_Model!E:E,Decision!B12)*(1+TAXRATE),0) -> 0 | D103: =HEADCOUNT -> 24 | E103: =B103*D103 -> 0 | F103: =C103*D103 -> 0 | G103: Government meals on fixed calendar dates; hotel breakfast/refreshments not deducted.
A104: =MIE_Daily!A70 | B104: =INDEX(MIE_Daily!$B$2:$AO$367,ROW()-35,5+8*(MATCH($B$2,CityData!$A$3:$A$7,0)-1)) -> 0 | C104: =IF(AND(A104<>"",A104<Parameters!$B$14),INDEX(Candidate_Model!E:E,Decision!B12)*(1+TAXRATE),0) -> 0 | D104: =HEADCOUNT -> 24 | E104: =B104*D104 -> 0 | F104: =C104*D104 -> 0 | G104: Government meals on fixed calendar dates; hotel breakfast/refreshments not deducted.
A105: =MIE_Daily!A71 | B105: =INDEX(MIE_Daily!$B$2:$AO$367,ROW()-35,5+8*(MATCH($B$2,CityData!$A$3:$A$7,0)-1)) -> 0 | C105: =IF(AND(A105<>"",A105<Parameters!$B$14),INDEX(Candidate_Model!E:E,Decision!B12)*(1+TAXRATE),0) -> 0 | D105: =HEADCOUNT -> 24 | E105: =B105*D105 -> 0 | F105: =C105*D105 -> 0 | G105: Government meals on fixed calendar dates; hotel breakfast/refreshments not deducted.
...

Sheet Options
A1: OPTIONS COMPARISON — 5 candidate cities × 18/24 attendees (base & +20% airfare stress)
A2: Per-person & event totals built from the same formulas as Daily. 'Stress' applies airfare ×1.20 on top of the airfare factor. Decision rule: fit ceiling → more people → lower total-with-reserve → alphabetical.
A4: City | B4: Head-count | C4: Airfare RT×fac | D4: Lodging+tax / person (dynamic nights) | E4: Reg | F4: Agency meals+bkfst | G4: Refresh. | H4: Ground | I4: Per-person | J4: Variable ×N | K4: Entered additional unquoted base U | L4: Partial/scenario base K+entered U | M4: Reserve | N4: Partial/scenario total incl reserve | O4: Net traveler MIE /person | P4: Known/estimated K excluding U | Q4: Entered U scenario | R4: Lodging compliant | S4: Dated quote applies | T4: Qualified feasible | U4: Conditional cost feasible | V4: Qualified rank | W4: Conditional rank | X4: Airfare total A | Y4: Max additional U @base | Z4: Max additional U @+20% | AA4: Stress total | AB4: Cost scope / unresolved
A5: Boston | B5: 24 | C5: =INDEX(CityData!$C:$C,MATCH(A5,CityData!$A:$A,0))*FFAC -> 311 | D5: =SUM(MIE_Daily!G2:G367) -> 483.84 | E5: =REGFEE -> 180 | F5: =INDEX(CityData!$D$11:$D$15,MATCH(A5,CityData!$A$11:$A$15,0))*(IF(AND(Parameters!$B$13<=DATE(2026,11,28),Parameters!$B$14>=DATE(2026,11,28)),1,0)+IF(AND(Parameters!$B$13<=DATE(2026,12,1),Parameters!$B$14>=DATE(2026,12,1)),1,0))+INDEX(CityData!$C$11:$C$15,MATCH(A5,CityData!$A$11:$A$15,0))*IF(AND(Parameters!$B$13<=DATE(2026,12,2),Parameters!$B$14>=DATE(2026,12,2)),1,0) -> 102 | G5: =REFRPP*REFRDAYS -> 45 | H5: =INDEX(CityData!$B$19:$B$23,MATCH(A5,CityData!$A$19:$A$23,0))+INDEX(CityData!$C$19:$C$23,MATCH(A5,CityData!$A$19:$A$23,0)) -> 120 | I5: =SUM(C5:H5)+O5 -> 1475.84 | J5: =I5*B5 -> 35420.16 | K5: =SUM(Unknowns!B2,Unknowns!G2)+B5*(NIGHTS*SUM(Unknowns!C2)+SUM(Unknowns!D2:F2)) -> 0 | L5: =J5+K5 -> 35420.16 | M5: =L5*RESRATE -> 1771.008 | N5: =L5+M5 -> 37191.168 | O5: =SUM(MIE_Daily!F2:F367) -> 234 | P5: =J5 -> 35420.16 | Q5: =K5 -> 0 | R5: =MIN(MIE_Daily!I2:I367) -> 1 | S5: =IF(AND(Parameters!$B$13=DATE(2026,11,28),Parameters!$B$14=DATE(2026,12,2)),1,0) -> 1 | T5: =IF(AND(R5=1,S5=1,Unknowns!H2=1,Unknowns!I2=1,N5<=CEILING,Parameters!$B$36="VALID DATE STRUCTURE"),1,0) -> 0 | U5: =IF(AND(R5=1,S5=1,N5<=CEILING,Parameters!$B$36="VALID DATE STRUCTURE"),1,0) -> 1 | V5: =IF(T5=0,99999,1+SUMPRODUCT($T$5:$T$14,--($B$5:$B$14>B5))+SUMPRODUCT($T$5:$T$14,--($B$5:$B$14=B5),--($N$5:$N$14<N5))+SUMPRODUCT($T$5:$T$14,--($B$5:$B$14=B5),--($N$5:$N$14=N5),--($A$5:$A$14<A5))) -> 99999 | W5: =IF(U5=0,99999,1+SUMPRODUCT($U$5:$U$14,--($B$5:$B$14>B5))+SUMPRODUCT($U$5:$U$14,--($B$5:$B$14=B5),--($N$5:$N$14<N5))+SUMPRODUCT($U$5:$U$14,--($B$5:$B$14=B5),--($N$5:$N$14=N5),--($A$5:$A$14<A5))) -> 1 | X5: =C5*B5 -> 7464 | Y5: =CEILING/(1+RESRATE)-P5 -> 15056.03 | Z5: =Y5-0.2*X5 -> 13563.23 | AA5: =(L5+0.2*X5)*(1+RESRATE) -> 38758.608 | AB5: Partial at entered U only; U_Boston,24 remains independently unknown; no qualified recommendation. Group inventory, occupancy, breakfast, fees, venue/local transfers pending as applicable.
A6: Boston | B6: 18 | C6: =INDEX(CityData!$C:$C,MATCH(A6,CityData!$A:$A,0))*FFAC -> 311 | D6: =SUM(MIE_Daily!G2:G367) -> 483.84 | E6: =REGFEE -> 180 | F6: =INDEX(CityData!$D$11:$D$15,MATCH(A6,CityData!$A$11:$A$15,0))*(IF(AND(Parameters!$B$13<=DATE(2026,11,28),Parameters!$B$14>=DATE(2026,11,28)),1,0)+IF(AND(Parameters!$B$13<=DATE(2026,12,1),Parameters!$B$14>=DATE(2026,12,1)),1,0))+INDEX(CityData!$C$11:$C$15,MATCH(A6,CityData!$A$11:$A$15,0))*IF(AND(Parameters!$B$13<=DATE(2026,12,2),Parameters!$B$14>=DATE(2026,12,2)),1,0) -> 102 | G6: =REFRPP*REFRDAYS -> 45 | H6: =INDEX(CityData!$B$19:$B$23,MATCH(A6,CityData!$A$19:$A$23,0))+INDEX(CityData!$C$19:$C$23,MATCH(A6,CityData!$A$19:$A$23,0)) -> 120 | I6: =SUM(C6:H6)+O6 -> 1475.84 | J6: =I6*B6 -> 26565.12 | K6: =SUM(Unknowns!B2,Unknowns!G2)+B6*(NIGHTS*SUM(Unknowns!C2)+SUM(Unknowns!D2:F2)) -> 0 | L6: =J6+K6 -> 26565.12 | M6: =L6*RESRATE -> 1328.256 | N6: =L6+M6 -> 27893.376 | O6: =SUM(MIE_Daily!F2:F367) -> 234 | P6: =J6 -> 26565.12 | Q6: =K6 -> 0 | R6: =MIN(MIE_Daily!I2:I367) -> 1 | S6: =IF(AND(Parameters!$B$13=DATE(2026,11,28),Parameters!$B$14=DATE(2026,12,2)),1,0) -> 1 | T6: =IF(AND(R6=1,S6=1,Unknowns!H2=1,Unknowns!I2=1,N6<=CEILING,Parameters!$B$36="VALID DATE STRUCTURE"),1,0) -> 0 | U6: =IF(AND(R6=1,S6=1,N6<=CEILING,Parameters!$B$36="VALID DATE STRUCTURE"),1,0) -> 1 | V6: =IF(T6=0,99999,1+SUMPRODUCT($T$5:$T$14,--($B$5:$B$14>B6))+SUMPRODUCT($T$5:$T$14,--($B$5:$B$14=B6),--($N$5:$N$14<N6))+SUMPRODUCT($T$5:$T$14,--($B$5:$B$14=B6),--($N$5:$N$14=N6),--($A$5:$A$14<A6))) -> 99999 | W6: =IF(U6=0,99999,1+SUMPRODUCT($U$5:$U$14,--($B$5:$B$14>B6))+SUMPRODUCT($U$5:$U$14,--($B$5:$B$14=B6),--($N$5:$N$14<N6))+SUMPRODUCT($U$5:$U$14,--($B$5:$B$14=B6),--($N$5:$N$14=N6),--($A$5:$A$14<A6))) -> 5 | X6: =C6*B6 -> 5598 | Y6: =CEILING/(1+RESRATE)-P6 -> 23911.07 | Z6: =Y6-0.2*X6 -> 22791.47 | AA6: =(L6+0.2*X6)*(1+RESRATE) -> 29068.956 | AB6: Partial at entered U only; U_Boston,18 remains independently unknown; no qualified recommendation. Group inventory, occupancy, breakfast, fees, venue/local transfers pending as applicable.
A7: Chicago | B7: 24 | C7: =INDEX(CityData!$C:$C,MATCH(A7,CityData!$A:$A,0))*FFAC -> 270 | D7: =SUM(MIE_Daily!O2:O367) -> 707.84 | E7: =REGFEE -> 180 | F7: =INDEX(CityData!$D$11:$D$15,MATCH(A7,CityData!$A$11:$A$15,0))*(IF(AND(Parameters!$B$13<=DATE(2026,11,28),Parameters!$B$14>=DATE(2026,11,28)),1,0)+IF(AND(Parameters!$B$13<=DATE(2026,12,1),Parameters!$B$14>=DATE(2026,12,1)),1,0))+INDEX(CityData!$C$11:$C$15,MATCH(A7,CityData!$A$11:$A$15,0))*IF(AND(Parameters!$B$13<=DATE(2026,12,2),Parameters!$B$14>=DATE(2026,12,2)),1,0) -> 102 | G7: =REFRPP*REFRDAYS -> 45 | H7: =INDEX(CityData!$B$19:$B$23,MATCH(A7,CityData!$A$19:$A$23,0))+INDEX(CityData!$C$19:$C$23,MATCH(A7,CityData!$A$19:$A$23,0)) -> 120 | I7: =SUM(C7:H7)+O7 -> 1658.84 | J7: =I7*B7 -> 39812.16 | K7: =SUM(Unknowns!B3,Unknowns!G3)+B7*(NIGHTS*SUM(Unknowns!C3)+SUM(Unknowns!D3:F3)) -> 0 | L7: =J7+K7 -> 39812.16 | M7: =L7*RESRATE -> 1990.608 | N7: =L7+M7 -> 41802.768 | O7: =SUM(MIE_Daily!N2:N367) -> 234 | P7: =J7 -> 39812.16 | Q7: =K7 -> 0 | R7: =MIN(MIE_Daily!Q2:Q367) -> 0 | S7: =IF(AND(Parameters!$B$13=DATE(2026,11,28),Parameters!$B$14=DATE(2026,12,2)),1,0) -> 1 | T7: =IF(AND(R7=1,S7=1,Unknowns!H3=1,Unknowns!I3=1,N7<=CEILING,Parameters!$B$36="VALID DATE STRUCTURE"),1,0) -> 0 | U7: =IF(AND(R7=1,S7=1,N7<=CEILING,Parameters!$B$36="VALID DATE STRUCTURE"),1,0) -> 0 | V7: =IF(T7=0,99999,1+SUMPRODUCT($T$5:$T$14,--($B$5:$B$14>B7))+SUMPRODUCT($T$5:$T$14,--($B$5:$B$14=B7),--($N$5:$N$14<N7))+SUMPRODUCT($T$5:$T$14,--($B$5:$B$14=B7),--($N$5:$N$14=N7),--($A$5:$A$14<A7))) -> 99999 | W7: =IF(U7=0,99999,1+SUMPRODUCT($U$5:$U$14,--($B$5:$B$14>B7))+SUMPRODUCT($U$5:$U$14,--($B$5:$B$14=B7),--($N$5:$N$14<N7))+SUMPRODUCT($U$5:$U$14,--($B$5:$B$14=B7),--($N$5:$N$14=N7),--($A$5:$A$14<A7))) -> 99999 | X7: =C7*B7 -> 6480 | Y7: =CEILING/(1+RESRATE)-P7 -> 10664.03 | Z7: =Y7-0.2*X7 -> 9368.0305 | AA7: =(L7+0.2*X7)*(1+RESRATE) -> 43163.568 | AB7: Partial at entered U only; U_Chicago,24 remains independently unknown; no qualified recommendation. Group inventory, occupancy, breakfast, fees, venue/local transfers pending as applicable.
A8: Chicago | B8: 18 | C8: =INDEX(CityData!$C:$C,MATCH(A8,CityData!$A:$A,0))*FFAC -> 270 | D8: =SUM(MIE_Daily!O2:O367) -> 707.84 | E8: =REGFEE -> 180 | F8: =INDEX(CityData!$D$11:$D$15,MATCH(A8,CityData!$A$11:$A$15,0))*(IF(AND(Parameters!$B$13<=DATE(2026,11,28),Parameters!$B$14>=DATE(2026,11,28)),1,0)+IF(AND(Parameters!$B$13<=DATE(2026,12,1),Parameters!$B$14>=DATE(2026,12,1)),1,0))+INDEX(CityData!$C$11:$C$15,MATCH(A8,CityData!$A$11:$A$15,0))*IF(AND(Parameters!$B$13<=DATE(2026,12,2),Parameters!$B$14>=DATE(2026,12,2)),1,0) -> 102 | G8: =REFRPP*REFRDAYS -> 45 | H8: =INDEX(CityData!$B$19:$B$23,MATCH(A8,CityData!$A$19:$A$23,0))+INDEX(CityData!$C$19:$C$23,MATCH(A8,CityData!$A$19:$A$23,0)) -> 120 | I8: =SUM(C8:H8)+O8 -> 1658.84 | J8: =I8*B8 -> 29859.12 | K8: =SUM(Unknowns!B3,Unknowns!G3)+B8*(NIGHTS*SUM(Unknowns!C3)+SUM(Unknowns!D3:F3)) -> 0 | L8: =J8+K8 -> 29859.12 | M8: =L8*RESRATE -> 1492.956 | N8: =L8+M8 -> 31352.076 | O8: =SUM(MIE_Daily!N2:N367) -> 234 | P8: =J8 -> 29859.12 | Q8: =K8 -> 0 | R8: =MIN(MIE_Daily!Q2:Q367) -> 0 | S8: =IF(AND(Parameters!$B$13=DATE(2026,11,28),Parameters!$B$14=DATE(2026,12,2)),1,0) -> 1 | T8: =IF(AND(R8=1,S8=1,Unknowns!H3=1,Unknowns!I3=1,N8<=CEILING,Parameters!$B$36="VALID DATE STRUCTURE"),1,0) -> 0 | U8: =IF(AND(R8=1,S8=1,N8<=CEILING,Parameters!$B$36="VALID DATE STRUCTURE"),1,0) -> 0 | V8: =IF(T8=0,99999,1+SUMPRODUCT($T$5:$T$14,--($B$5:$B$14>B8))+SUMPRODUCT($T$5:$T$14,--($B$5:$B$14=B8),--($N$5:$N$14<N8))+SUMPRODUCT($T$5:$T$14,--($B$5:$B$14=B8),--($N$5:$N$14=N8),--($A$5:$A$14<A8))) -> 99999 | W8: =IF(U8=0,99999,1+SUMPRODUCT($U$5:$U$14,--($B$5:$B$14>B8))+SUMPRODUCT($U$5:$U$14,--($B$5:$B$14=B8),--($N$5:$N$14<N8))+SUMPRODUCT($U$5:$U$14,--($B$5:$B$14=B8),--($N$5:$N$14=N8),--($A$5:$A$14<A8))) -> 99999 | X8: =C8*B8 -> 4860 | Y8: =CEILING/(1+RESRATE)-P8 -> 20617.07 | Z8: =Y8-0.2*X8 -> 19645.07 | AA8: =(L8+0.2*X8)*(1+RESRATE) -> 32372.676 | AB8: Partial at entered U only; U_Chicago,18 remains independently unknown; no qualified recommendation. Group inventory, occupancy, breakfast, fees, venue/local transfers pending as applicable.
A9: Denver | B9: 24 | C9: =INDEX(CityData!$C:$C,MATCH(A9,CityData!$A:$A,0))*FFAC -> 578 | D9: =SUM(MIE_Daily!W2:W367) -> 488.32 | E9: =REGFEE -> 180 | F9: =INDEX(CityData!$D$11:$D$15,MATCH(A9,CityData!$A$11:$A$15,0))*(IF(AND(Parameters!$B$13<=DATE(2026,11,28),Parameters!$B$14>=DATE(2026,11,28)),1,0)+IF(AND(Parameters!$B$13<=DATE(2026,12,1),Parameters!$B$14>=DATE(2026,12,1)),1,0))+INDEX(CityData!$C$11:$C$15,MATCH(A9,CityData!$A$11:$A$15,0))*IF(AND(Parameters!$B$13<=DATE(2026,12,2),Parameters!$B$14>=DATE(2026,12,2)),1,0) -> 102 | G9: =REFRPP*REFRDAYS -> 45 | H9: =INDEX(CityData!$B$19:$B$23,MATCH(A9,CityData!$A$19:$A$23,0))+INDEX(CityData!$C$19:$C$23,MATCH(A9,CityData!$A$19:$A$23,0)) -> 220 | I9: =SUM(C9:H9)+O9 -> 1847.32 | J9: =I9*B9 -> 44335.68 | K9: =SUM(Unknowns!B4,Unknowns!G4)+B9*(NIGHTS*SUM(Unknowns!C4)+SUM(Unknowns!D4:F4)) -> 0 | L9: =J9+K9 -> 44335.68 | M9: =L9*RESRATE -> 2216.784 | N9: =L9+M9 -> 46552.464 | O9: =SUM(MIE_Daily!V2:V367) -> 234 | P9: =J9 -> 44335.68 | Q9: =K9 -> 0 | R9: =MIN(MIE_Daily!Y2:Y367) -> 1 | S9: =IF(AND(Parameters!$B$13=DATE(2026,11,28),Parameters!$B$14=DATE(2026,12,2)),1,0) -> 1 | T9: =IF(AND(R9=1,S9=1,Unknowns!H4=1,Unknowns!I4=1,N9<=CEILING,Parameters!$B$36="VALID DATE STRUCTURE"),1,0) -> 0 | U9: =IF(AND(R9=1,S9=1,N9<=CEILING,Parameters!$B$36="VALID DATE STRUCTURE"),1,0) -> 1 | V9: =IF(T9=0,99999,1+SUMPRODUCT($T$5:$T$14,--($B$5:$B$14>B9))+SUMPRODUCT($T$5:$T$14,--($B$5:$B$14=B9),--($N$5:$N$14<N9))+SUMPRODUCT($T$5:$T$14,--($B$5:$B$14=B9),--($N$5:$N$14=N9),--($A$5:$A$14<A9))) -> 99999 | W9: =IF(U9=0,99999,1+SUMPRODUCT($U$5:$U$14,--($B$5:$B$14>B9))+SUMPRODUCT($U$5:$U$14,--($B$5:$B$14=B9),--($N$5:$N$14<N9))+SUMPRODUCT($U$5:$U$14,--($B$5:$B$14=B9),--($N$5:$N$14=N9),--($A$5:$A$14<A9))) -> 3 | X9: =C9*B9 -> 13872 | Y9: =CEILING/(1+RESRATE)-P9 -> 6140.5105 | Z9: =Y9-0.2*X9 -> 3366.1105 | AA9: =(L9+0.2*X9)*(1+RESRATE) -> 49465.584 | AB9: Partial at entered U only; U_Denver,24 remains independently unknown; no qualified recommendation. Group inventory, occupancy, breakfast, fees, venue/local transfers pending as applicable.
A10: Denver | B10: 18 | C10: =INDEX(CityData!$C:$C,MATCH(A10,CityData!$A:$A,0))*FFAC -> 578 | D10: =SUM(MIE_Daily!W2:W367) -> 488.32 | E10: =REGFEE -> 180 | F10: =INDEX(CityData!$D$11:$D$15,MATCH(A10,CityData!$A$11:$A$15,0))*(IF(AND(Parameters!$B$13<=DATE(2026,11,28),Parameters!$B$14>=DATE(2026,11,28)),1,0)+IF(AND(Parameters!$B$13<=DATE(2026,12,1),Parameters!$B$14>=DATE(2026,12,1)),1,0))+INDEX(CityData!$C$11:$C$15,MATCH(A10,CityData!$A$11:$A$15,0))*IF(AND(Parameters!$B$13<=DATE(2026,12,2),Parameters!$B$14>=DATE(2026,12,2)),1,0) -> 102 | G10: =REFRPP*REFRDAYS -> 45 | H10: =INDEX(CityData!$B$19:$B$23,MATCH(A10,CityData!$A$19:$A$23,0))+INDEX(CityData!$C$19:$C$23,MATCH(A10,CityData!$A$19:$A$23,0)) -> 220 | I10: =SUM(C10:H10)+O10 -> 1847.32 | J10: =I10*B10 -> 33251.76 | K10: =SUM(Unknowns!B4,Unknowns!G4)+B10*(NIGHTS*SUM(Unknowns!C4)+SUM(Unknowns!D4:F4)) -> 0 | L10: =J10+K10 -> 33251.76 | M10: =L10*RESRATE -> 1662.588 | N10: =L10+M10 -> 34914.348 | O10: =SUM(MIE_Daily!V2:V367) -> 234 | P10: =J10 -> 33251.76 | Q10: =K10 -> 0 | R10: =MIN(MIE_Daily!Y2:Y367) -> 1 | S10: =IF(AND(Parameters!$B$13=DATE(2026,11,28),Parameters!$B$14=DATE(2026,12,2)),1,0) -> 1 | T10: =IF(AND(R10=1,S10=1,Unknowns!H4=1,Unknowns!I4=1,N10<=CEILING,Parameters!$B$36="VALID DATE STRUCTURE"),1,0) -> 0 | U10: =IF(AND(R10=1,S10=1,N10<=CEILING,Parameters!$B$36="VALID DATE STRUCTURE"),1,0) -> 1 | V10: =IF(T10=0,99999,1+SUMPRODUCT($T$5:$T$14,--($B$5:$B$14>B10))+SUMPRODUCT($T$5:$T$14,--($B$5:$B$14=B10),--($N$5:$N$14<N10))+SUMPRODUCT($T$5:$T$14,--($B$5:$B$14=B10),--($N$5:$N$14=N10),--($A$5:$A$14<A10))) -> 99999 | W10: =IF(U10=0,99999,1+SUMPRODUCT($U$5:$U$14,--($B$5:$B$14>B10))+SUMPRODUCT($U$5:$U$14,--($B$5:$B$14=B10),--($N$5:$N$14<N10))+SUMPRODUCT($U$5:$U$14,--($B$5:$B$14=B10),--($N$5:$N$14=N10),--($A$5:$A$14<A10))) -> 7 | X10: =C10*B10 -> 10404 | Y10: =CEILING/(1+RESRATE)-P10 -> 17224.43 | Z10: =Y10-0.2*X10 -> 15143.63 | AA10: =(L10+0.2*X10)*(1+RESRATE) -> 37099.188 | AB10: Partial at entered U only; U_Denver,18 remains independently unknown; no qualified recommendation. Group inventory, occupancy, breakfast, fees, venue/local transfers pending as applicable.
A11: Phoenix | B11: 24 | C11: =INDEX(CityData!$C:$C,MATCH(A11,CityData!$A:$A,0))*FFAC -> 499 | D11: =SUM(MIE_Daily!AE2:AE367) -> 672 | E11: =REGFEE -> 180 | F11: =INDEX(CityData!$D$11:$D$15,MATCH(A11,CityData!$A$11:$A$15,0))*(IF(AND(Parameters!$B$13<=DATE(2026,11,28),Parameters!$B$14>=DATE(2026,11,28)),1,0)+IF(AND(Parameters!$B$13<=DATE(2026,12,1),Parameters!$B$14>=DATE(2026,12,1)),1,0))+INDEX(CityData!$C$11:$C$15,MATCH(A11,CityData!$A$11:$A$15,0))*IF(AND(Parameters!$B$13<=DATE(2026,12,2),Parameters!$B$14>=DATE(2026,12,2)),1,0) -> 95 | G11: =REFRPP*REFRDAYS -> 45 | H11: =INDEX(CityData!$B$19:$B$23,MATCH(A11,CityData!$A$19:$A$23,0))+INDEX(CityData!$C$19:$C$23,MATCH(A11,CityData!$A$19:$A$23,0)) -> 210 | I11: =SUM(C11:H11)+O11 -> 1924 | J11: =I11*B11 -> 46176 | K11: =SUM(Unknowns!B5,Unknowns!G5)+B11*(NIGHTS*SUM(Unknowns!C5)+SUM(Unknowns!D5:F5)) -> 0 | L11: =J11+K11 -> 46176 | M11: =L11*RESRATE -> 2308.8 | N11: =L11+M11 -> 48484.8 | O11: =SUM(MIE_Daily!AD2:AD367) -> 223 | P11: =J11 -> 46176 | Q11: =K11 -> 0 | R11: =MIN(MIE_Daily!AG2:AG367) -> 1 | S11: =IF(AND(Parameters!$B$13=DATE(2026,11,28),Parameters!$B$14=DATE(2026,12,2)),1,0) -> 1 | T11: =IF(AND(R11=1,S11=1,Unknowns!H5=1,Unknowns!I5=1,N11<=CEILING,Parameters!$B$36="VALID DATE STRUCTURE"),1,0) -> 0 | U11: =IF(AND(R11=1,S11=1,N11<=CEILING,Parameters!$B$36="VALID DATE STRUCTURE"),1,0) -> 1 | V11: =IF(T11=0,99999,1+SUMPRODUCT($T$5:$T$14,--($B$5:$B$14>B11))+SUMPRODUCT($T$5:$T$14,--($B$5:$B$14=B11),--($N$5:$N$14<N11))+SUMPRODUCT($T$5:$T$14,--($B$5:$B$14=B11),--($N$5:$N$14=N11),--($A$5:$A$14<A11))) -> 99999 | W11: =IF(U11=0,99999,1+SUMPRODUCT($U$5:$U$14,--($B$5:$B$14>B11))+SUMPRODUCT($U$5:$U$14,--($B$5:$B$14=B11),--($N$5:$N$14<N11))+SUMPRODUCT($U$5:$U$14,--($B$5:$B$14=B11),--($N$5:$N$14=N11),--($A$5:$A$14<A11))) -> 4 | X11: =C11*B11 -> 11976 | Y11: =CEILING/(1+RESRATE)-P11 -> 4300.1905 | Z11: =Y11-0.2*X11 -> 1904.9905 | AA11: =(L11+0.2*X11)*(1+RESRATE) -> 50999.76 | AB11: Partial at entered U only; U_Phoenix,24 remains independently unknown; no qualified recommendation. Group inventory, occupancy, breakfast, fees, venue/local transfers pending as applicable.
A12: Phoenix | B12: 18 | C12: =INDEX(CityData!$C:$C,MATCH(A12,CityData!$A:$A,0))*FFAC -> 499 | D12: =SUM(MIE_Daily!AE2:AE367) -> 672 | E12: =REGFEE -> 180 | F12: =INDEX(CityData!$D$11:$D$15,MATCH(A12,CityData!$A$11:$A$15,0))*(IF(AND(Parameters!$B$13<=DATE(2026,11,28),Parameters!$B$14>=DATE(2026,11,28)),1,0)+IF(AND(Parameters!$B$13<=DATE(2026,12,1),Parameters!$B$14>=DATE(2026,12,1)),1,0))+INDEX(CityData!$C$11:$C$15,MATCH(A12,CityData!$A$11:$A$15,0))*IF(AND(Parameters!$B$13<=DATE(2026,12,2),Parameters!$B$14>=DATE(2026,12,2)),1,0) -> 95 | G12: =REFRPP*REFRDAYS -> 45 | H12: =INDEX(CityData!$B$19:$B$23,MATCH(A12,CityData!$A$19:$A$23,0))+INDEX(CityData!$C$19:$C$23,MATCH(A12,CityData!$A$19:$A$23,0)) -> 210 | I12: =SUM(C12:H12)+O12 -> 1924 | J12: =I12*B12 -> 34632 | K12: =SUM(Unknowns!B5,Unknowns!G5)+B12*(NIGHTS*SUM(Unknowns!C5)+SUM(Unknowns!D5:F5)) -> 0 | L12: =J12+K12 -> 34632 | M12: =L12*RESRATE -> 1731.6 | N12: =L12+M12 -> 36363.6 | O12: =SUM(MIE_Daily!AD2:AD367) -> 223 | P12: =J12 -> 34632 | Q12: =K12 -> 0 | R12: =MIN(MIE_Daily!AG2:AG367) -> 1 | S12: =IF(AND(Parameters!$B$13=DATE(2026,11,28),Parameters!$B$14=DATE(2026,12,2)),1,0) -> 1 | T12: =IF(AND(R12=1,S12=1,Unknowns!H5=1,Unknowns!I5=1,N12<=CEILING,Parameters!$B$36="VALID DATE STRUCTURE"),1,0) -> 0 | U12: =IF(AND(R12=1,S12=1,N12<=CEILING,Parameters!$B$36="VALID DATE STRUCTURE"),1,0) -> 1 | V12: =IF(T12=0,99999,1+SUMPRODUCT($T$5:$T$14,--($B$5:$B$14>B12))+SUMPRODUCT($T$5:$T$14,--($B$5:$B$14=B12),--($N$5:$N$14<N12))+SUMPRODUCT($T$5:$T$14,--($B$5:$B$14=B12),--($N$5:$N$14=N12),--($A$5:$A$14<A12))) -> 99999 | W12: =IF(U12=0,99999,1+SUMPRODUCT($U$5:$U$14,--($B$5:$B$14>B12))+SUMPRODUCT($U$5:$U$14,--($B$5:$B$14=B12),--($N$5:$N$14<N12))+SUMPRODUCT($U$5:$U$14,--($B$5:$B$14=B12),--($N$5:$N$14=N12),--($A$5:$A$14<A12))) -> 8 | X12: =C12*B12 -> 8982 | Y12: =CEILING/(1+RESRATE)-P12 -> 15844.19 | Z12: =Y12-0.2*X12 -> 14047.79 | AA12: =(L12+0.2*X12)*(1+RESRATE) -> 38249.82 | AB12: Partial at entered U only; U_Phoenix,18 remains independently unknown; no qualified recommendation. Group inventory, occupancy, breakfast, fees, venue/local transfers pending as applicable.
A13: Seattle | B13: 24 | C13: =INDEX(CityData!$C:$C,MATCH(A13,CityData!$A:$A,0))*FFAC -> 590 | D13: =SUM(MIE_Daily!AM2:AM367) -> 452.48 | E13: =REGFEE -> 180 | F13: =INDEX(CityData!$D$11:$D$15,MATCH(A13,CityData!$A$11:$A$15,0))*(IF(AND(Parameters!$B$13<=DATE(2026,11,28),Parameters!$B$14>=DATE(2026,11,28)),1,0)+IF(AND(Parameters!$B$13<=DATE(2026,12,1),Parameters!$B$14>=DATE(2026,12,1)),1,0))+INDEX(CityData!$C$11:$C$15,MATCH(A13,CityData!$A$11:$A$15,0))*IF(AND(Parameters!$B$13<=DATE(2026,12,2),Parameters!$B$14>=DATE(2026,12,2)),1,0) -> 102 | G13: =REFRPP*REFRDAYS -> 45 | H13: =INDEX(CityData!$B$19:$B$23,MATCH(A13,CityData!$A$19:$A$23,0))+INDEX(CityData!$C$19:$C$23,MATCH(A13,CityData!$A$19:$A$23,0)) -> 220 | I13: =SUM(C13:H13)+O13 -> 1823.48 | J13: =I13*B13 -> 43763.52 | K13: =SUM(Unknowns!B6,Unknowns!G6)+B13*(NIGHTS*SUM(Unknowns!C6)+SUM(Unknowns!D6:F6)) -> 0 | L13: =J13+K13 -> 43763.52 | M13: =L13*RESRATE -> 2188.176 | N13: =L13+M13 -> 45951.696 | O13: =SUM(MIE_Daily!AL2:AL367) -> 234 | P13: =J13 -> 43763.52 | Q13: =K13 -> 0 | R13: =MIN(MIE_Daily!AO2:AO367) -> 1 | S13: =IF(AND(Parameters!$B$13=DATE(2026,11,28),Parameters!$B$14=DATE(2026,12,2)),1,0) -> 1 | T13: =IF(AND(R13=1,S13=1,Unknowns!H6=1,Unknowns!I6=1,N13<=CEILING,Parameters!$B$36="VALID DATE STRUCTURE"),1,0) -> 0 | U13: =IF(AND(R13=1,S13=1,N13<=CEILING,Parameters!$B$36="VALID DATE STRUCTURE"),1,0) -> 1 | V13: =IF(T13=0,99999,1+SUMPRODUCT($T$5:$T$14,--($B$5:$B$14>B13))+SUMPRODUCT($T$5:$T$14,--($B$5:$B$14=B13),--($N$5:$N$14<N13))+SUMPRODUCT($T$5:$T$14,--($B$5:$B$14=B13),--($N$5:$N$14=N13),--($A$5:$A$14<A13))) -> 99999 | W13: =IF(U13=0,99999,1+SUMPRODUCT($U$5:$U$14,--($B$5:$B$14>B13))+SUMPRODUCT($U$5:$U$14,--($B$5:$B$14=B13),--($N$5:$N$14<N13))+SUMPRODUCT($U$5:$U$14,--($B$5:$B$14=B13),--($N$5:$N$14=N13),--($A$5:$A$14<A13))) -> 2 | X13: =C13*B13 -> 14160 | Y13: =CEILING/(1+RESRATE)-P13 -> 6712.6705 | Z13: =Y13-0.2*X13 -> 3880.6705 | AA13: =(L13+0.2*X13)*(1+RESRATE) -> 48925.296 | AB13: Partial at entered U only; U_Seattle,24 remains independently unknown; no qualified recommendation. Group inventory, occupancy, breakfast, fees, venue/local transfers pending as applicable.
A14: Seattle | B14: 18 | C14: =INDEX(CityData!$C:$C,MATCH(A14,CityData!$A:$A,0))*FFAC -> 590 | D14: =SUM(MIE_Daily!AM2:AM367) -> 452.48 | E14: =REGFEE -> 180 | F14: =INDEX(CityData!$D$11:$D$15,MATCH(A14,CityData!$A$11:$A$15,0))*(IF(AND(Parameters!$B$13<=DATE(2026,11,28),Parameters!$B$14>=DATE(2026,11,28)),1,0)+IF(AND(Parameters!$B$13<=DATE(2026,12,1),Parameters!$B$14>=DATE(2026,12,1)),1,0))+INDEX(CityData!$C$11:$C$15,MATCH(A14,CityData!$A$11:$A$15,0))*IF(AND(Parameters!$B$13<=DATE(2026,12,2),Parameters!$B$14>=DATE(2026,12,2)),1,0) -> 102 | G14: =REFRPP*REFRDAYS -> 45 | H14: =INDEX(CityData!$B$19:$B$23,MATCH(A14,CityData!$A$19:$A$23,0))+INDEX(CityData!$C$19:$C$23,MATCH(A14,CityData!$A$19:$A$23,0)) -> 220 | I14: =SUM(C14:H14)+O14 -> 1823.48 | J14: =I14*B14 -> 32822.64 | K14: =SUM(Unknowns!B6,Unknowns!G6)+B14*(NIGHTS*SUM(Unknowns!C6)+SUM(Unknowns!D6:F6)) -> 0 | L14: =J14+K14 -> 32822.64 | M14: =L14*RESRATE -> 1641.132 | N14: =L14+M14 -> 34463.772 | O14: =SUM(MIE_Daily!AL2:AL367) -> 234 | P14: =J14 -> 32822.64 | Q14: =K14 -> 0 | R14: =MIN(MIE_Daily!AO2:AO367) -> 1 | S14: =IF(AND(Parameters!$B$13=DATE(2026,11,28),Parameters!$B$14=DATE(2026,12,2)),1,0) -> 1 | T14: =IF(AND(R14=1,S14=1,Unknowns!H6=1,Unknowns!I6=1,N14<=CEILING,Parameters!$B$36="VALID DATE STRUCTURE"),1,0) -> 0 | U14: =IF(AND(R14=1,S14=1,N14<=CEILING,Parameters!$B$36="VALID DATE STRUCTURE"),1,0) -> 1 | V14: =IF(T14=0,99999,1+SUMPRODUCT($T$5:$T$14,--($B$5:$B$14>B14))+SUMPRODUCT($T$5:$T$14,--($B$5:$B$14=B14),--($N$5:$N$14<N14))+SUMPRODUCT($T$5:$T$14,--($B$5:$B$14=B14),--($N$5:$N$14=N14),--($A$5:$A$14<A14))) -> 99999 | W14: =IF(U14=0,99999,1+SUMPRODUCT($U$5:$U$14,--($B$5:$B$14>B14))+SUMPRODUCT($U$5:$U$14,--($B$5:$B$14=B14),--($N$5:$N$14<N14))+SUMPRODUCT($U$5:$U$14,--($B$5:$B$14=B14),--($N$5:$N$14=N14),--($A$5:$A$14<A14))) -> 6 | X14: =C14*B14 -> 10620 | Y14: =CEILING/(1+RESRATE)-P14 -> 17653.55 | Z14: =Y14-0.2*X14 -> 15529.55 | AA14: =(L14+0.2*X14)*(1+RESRATE) -> 36693.972 | AB14: Partial at entered U only; U_Seattle,18 remains independently unknown; no qualified recommendation. Group inventory, occupancy, breakfast, fees, venue/local transfers pending as applicable.
A17: STRESS: airfare × 1.20 (on top of airfare factor)
A18: City | B18: Headcount | C18: Per-person (stress) | D18: Base (stress) | E18: TOTAL (stress) | F18: Within ceiling?
A19: Boston | B19: 24 | C19: =I5+C5*0.2 -> 1538.04 | D19: =(I5+C5*0.2)*B5+K5 -> 36912.96 | E19: =AA5 -> 38758.608 | F19: =IF(E19<=CEILING,"YES","NO") -> YES
A20: Boston | B20: 18 | C20: =I6+C6*0.2 -> 1538.04 | D20: =(I6+C6*0.2)*B6+K6 -> 27684.72 | E20: =AA6 -> 29068.956 | F20: =IF(E20<=CEILING,"YES","NO") -> YES
A21: Chicago | B21: 24 | C21: =I7+C7*0.2 -> 1712.84 | D21: =(I7+C7*0.2)*B7+K7 -> 41108.16 | E21: =AA7 -> 43163.568 | F21: =IF(E21<=CEILING,"YES","NO") -> YES
A22: Chicago | B22: 18 | C22: =I8+C8*0.2 -> 1712.84 | D22: =(I8+C8*0.2)*B8+K8 -> 30831.12 | E22: =AA8 -> 32372.676 | F22: =IF(E22<=CEILING,"YES","NO") -> YES
A23: Denver | B23: 24 | C23: =I9+C9*0.2 -> 1962.92 | D23: =(I9+C9*0.2)*B9+K9 -> 47110.08 | E23: =AA9 -> 49465.584 | F23: =IF(E23<=CEILING,"YES","NO") -> YES
A24: Denver | B24: 18 | C24: =I10+C10*0.2 -> 1962.92 | D24: =(I10+C10*0.2)*B10+K10 -> 35332.56 | E24: =AA10 -> 37099.188 | F24: =IF(E24<=CEILING,"YES","NO") -> YES
A25: Phoenix | B25: 24 | C25: =I11+C11*0.2 -> 2023.8 | D25: =(I11+C11*0.2)*B11+K11 -> 48571.2 | E25: =AA11 -> 50999.76 | F25: =IF(E25<=CEILING,"YES","NO") -> YES
A26: Phoenix | B26: 18 | C26: =I12+C12*0.2 -> 2023.8 | D26: =(I12+C12*0.2)*B12+K12 -> 36428.4 | E26: =AA12 -> 38249.82 | F26: =IF(E26<=CEILING,"YES","NO") -> YES
A27: Seattle | B27: 24 | C27: =I13+C13*0.2 -> 1941.48 | D27: =(I13+C13*0.2)*B13+K13 -> 46595.52 | E27: =AA13 -> 48925.296 | F27: =IF(E27<=CEILING,"YES","NO") -> YES
A28: Seattle | B28: 18 | C28: =I14+C14*0.2 -> 1941.48 | D28: =(I14+C14*0.2)*B14+K14 -> 34946.64 | E28: =AA14 -> 36693.972 | F28: =IF(E28<=CEILING,"YES","NO") -> YES

Sheet Historical
A1: HISTORICAL PER-DIEM CROSS-CHECK — FY2025 / FY2026 / FY2027 (same month/day, same market rates)
A2: Historical reference only (not actual past quotes, not for this reimbursement). Shows how each FY's lodging cap and M&IE would affect lodging compliance and the per-diem comparison, holding headcount, dates and market quotes constant.
A4: City | B4: Market room/night (held) | C4: FY | D4: Lodging cap — Nov night | E4: Lodging cap — Dec 1 night | F4: M&IE | G4: 4-night cap sum | H4: Compliant each night? | I4: Room 4n vs cap sum | J4: Notes
A5: Boston | B5: 108 | C5: FY2025 | D5: 209 | E5: 209 | F5: 92 | G5: =3*D5+E5 -> 836 | H5: =IF(AND(B5<=D5,B5<=E5),"YES","NO: OVER CAP, NOT BOOKABLE WITHOUT AUTHORIZATION") -> YES | I5: =4*B5 -> 432
A6: Boston | B6: 108 | C6: FY2026 | D6: 209 | E6: 209 | F6: 92 | G6: =3*D6+E6 -> 836 | H6: =IF(AND(B6<=D6,B6<=E6),"YES","NO: OVER CAP, NOT BOOKABLE WITHOUT AUTHORIZATION") -> YES | I6: =4*B6 -> 432
A7: Boston | B7: 108 | C7: FY2027 | D7: 213 | E7: 213 | F7: 92 | G7: =3*D7+E7 -> 852 | H7: =IF(AND(B7<=D7,B7<=E7),"YES","NO: OVER CAP, NOT BOOKABLE WITHOUT AUTHORIZATION") -> YES | I7: =4*B7 -> 432
A8: Chicago | B8: =CityData!F4 -> 158 | C8: FY2025 | D8: 223 | E8: 142 | F8: 92 | G8: =3*D8+E8 -> 811 | H8: =IF(AND(B8<=D8,B8<=E8),"YES","NO: OVER CAP, NOT BOOKABLE WITHOUT AUTHORIZATION") -> NO: OVER CAP, NOT BOOKABLE WITHOUT AUTHORIZATION | I8: =4*B8 -> 632 | J8: Dec-1 cap < $145 → NON-compliant this FY (FY27 only compliant)
A9: Chicago | B9: =CityData!F4 -> 158 | C9: FY2026 | D9: 223 | E9: 142 | F9: 92 | G9: =3*D9+E9 -> 811 | H9: =IF(AND(B9<=D9,B9<=E9),"YES","NO: OVER CAP, NOT BOOKABLE WITHOUT AUTHORIZATION") -> NO: OVER CAP, NOT BOOKABLE WITHOUT AUTHORIZATION | I9: =4*B9 -> 632 | J9: Dec-1 cap < $145 → NON-compliant this FY (FY27 only compliant)
A10: Chicago | B10: =CityData!F4 -> 158 | C10: FY2027 | D10: 232 | E10: 148 | F10: 92 | G10: =3*D10+E10 -> 844 | H10: =IF(AND(B10<=D10,B10<=E10),"YES","NO: OVER CAP, NOT BOOKABLE WITHOUT AUTHORIZATION") -> NO: OVER CAP, NOT BOOKABLE WITHOUT AUTHORIZATION | I10: =4*B10 -> 632
A11: Denver | B11: 109 | C11: FY2025 | D11: 165 | E11: 165 | F11: 92 | G11: =3*D11+E11 -> 660 | H11: =IF(AND(B11<=D11,B11<=E11),"YES","NO: OVER CAP, NOT BOOKABLE WITHOUT AUTHORIZATION") -> YES | I11: =4*B11 -> 436
A12: Denver | B12: 109 | C12: FY2026 | D12: 165 | E12: 165 | F12: 92 | G12: =3*D12+E12 -> 660 | H12: =IF(AND(B12<=D12,B12<=E12),"YES","NO: OVER CAP, NOT BOOKABLE WITHOUT AUTHORIZATION") -> YES | I12: =4*B12 -> 436
A13: Denver | B13: 109 | C13: FY2027 | D13: 170 | E13: 170 | F13: 92 | G13: =3*D13+E13 -> 680 | H13: =IF(AND(B13<=D13,B13<=E13),"YES","NO: OVER CAP, NOT BOOKABLE WITHOUT AUTHORIZATION") -> YES | I13: =4*B13 -> 436
A14: Phoenix | B14: 150 | C14: FY2025 | D14: 160 | E14: 160 | F14: 86 | G14: =3*D14+E14 -> 640 | H14: =IF(AND(B14<=D14,B14<=E14),"YES","NO: OVER CAP, NOT BOOKABLE WITHOUT AUTHORIZATION") -> YES | I14: =4*B14 -> 600 | J14: Rate $150 ≤ cap but little headroom
A15: Phoenix | B15: 150 | C15: FY2026 | D15: 160 | E15: 160 | F15: 86 | G15: =3*D15+E15 -> 640 | H15: =IF(AND(B15<=D15,B15<=E15),"YES","NO: OVER CAP, NOT BOOKABLE WITHOUT AUTHORIZATION") -> YES | I15: =4*B15 -> 600 | J15: Rate $150 ≤ cap but little headroom
A16: Phoenix | B16: 150 | C16: FY2027 | D16: 165 | E16: 165 | F16: 86 | G16: =3*D16+E16 -> 660 | H16: =IF(AND(B16<=D16,B16<=E16),"YES","NO: OVER CAP, NOT BOOKABLE WITHOUT AUTHORIZATION") -> YES | I16: =4*B16 -> 600 | J16: Rate $150 ≤ cap but little headroom
A17: Seattle | B17: 101 | C17: FY2025 | D17: 188 | E17: 188 | F17: 92 | G17: =3*D17+E17 -> 752 | H17: =IF(AND(B17<=D17,B17<=E17),"YES","NO: OVER CAP, NOT BOOKABLE WITHOUT AUTHORIZATION") -> YES | I17: =4*B17 -> 404
A18: Seattle | B18: 101 | C18: FY2026 | D18: 188 | E18: 188 | F18: 92 | G18: =3*D18+E18 -> 752 | H18: =IF(AND(B18<=D18,B18<=E18),"YES","NO: OVER CAP, NOT BOOKABLE WITHOUT AUTHORIZATION") -> YES | I18: =4*B18 -> 404
A19: Seattle | B19: 101 | C19: FY2027 | D19: 188 | E19: 188 | F19: 92 | G19: =3*D19+E19 -> 752 | H19: =IF(AND(B19<=D19,B19<=E19),"YES","NO: OVER CAP, NOT BOOKABLE WITHOUT AUTHORIZATION") -> YES | I19: =4*B19 -> 404
A21: Impact summary:
A22: • Lodging caps rose modestly FY25→FY27 (Boston +4, Chicago +9/+6, Denver +5, Phoenix +5, Seattle flat). M&IE unchanged.
A23: Chicago158 exceeds Dec1 FY27 cap148 and historical cap142; it cannot be used as a compliant recommendation.
A24: Billabook101 is archived without breakfast binding. Agoda158 and Booking159 explicitly show breakfast but exceed cap.
A25: Historical_Impact quantifies both previous FYs × both headcounts × all5cities. Same observed market quotes, not actual historical offers.
A26: • FY2027 is the applicable year (travel Nov 29–Dec 1 2026 = FY27, eff. Oct 1 2026). FY25/26 shown for historical contrast only.

Sheet Thresholds
A1: THRESHOLDS, STRESS & SEGMENTED ACTIONS
A2: Decision metrics for airfare increases (0–20%) and unquoted-cost movements. Recomputes from Options/Daily.
A4: Metric | B4: Value | C4: Basis / condition
A5: Qualified recommendation | B5: =Decision!B2 -> NO QUALIFIED RECOMMENDATION | C5: No qualified recommendation until admission and exact quote conditions verified.
A6: Priority estimate (not approval) | B6: =Decision!B3&" / "&Decision!B4 -> Boston / 24 | C6: Conditional ranking at entered U; U values not confirmed zero.
A7: Priority partial total | B7: =Decision!B6 -> 37191.168 | C7: All5cities and both headcounts in Options.
A8: Priority candidate maximum additional base U | B8: =INDEX(Candidate_Model!U:U,MATCH(Decision!B11,Candidate_Model!A:A,0)) -> 15056.03 | C8: Budget/(1+reserve)-known/estimated K, not reserve-inclusive budget remainder.
A9: Priority Umax +20% | B9: =INDEX(Candidate_Model!V:V,MATCH(Decision!B11,Candidate_Model!A:A,0)) -> 13563.23 | C9: Pressure on currently adjusted airfare.
A10: Next candidate maximum additional base U | B10: =INDEX(Candidate_Model!U2:U45,MATCH(2,Candidate_Model!T2:T45,0)) -> 13928.03 | C10: Most competitive conditional backup among primary anchors.
A11: Next candidate Umax +20% | B11: =INDEX(Candidate_Model!V2:V45,MATCH(2,Candidate_Model!T2:T45,0)) -> 12209.63 | C11: Same basis.
A12: Chicago-Boston equal-U intersection p | B12: =IF(Options!X7=Options!X5,IF(Options!P5=Options!P7,"ALL p TIE: alphabetical Boston","PARALLEL: no finite crossing"),(Options!P5-Options!P7)/(Options!X7-Options!X5)) -> 4.4634146 | C12: Diagnostic arithmetic for the EXCLUDED Chicago158 quote only; not an eligible switch. Current selection and bounds: Candidate_Model / Boundary_All. No authorized above-cap exception.
A13: General optimum region | B13: See Boundary_Checks all10 candidates | C13: Cost_i=(1+reserve)*(K_i+p*A_i+U_i). Region for selected same-size i: U_i-U_j <= K_j-K_i+p*(A_j-A_i) for EVERY eligible j; strict inequality if j alphabetically earlier.
A14: Keep Chicago24 | B14: Uchi<=Umaxchi(p), all same-size inequalities hold | C14: All dates, price compliance and quality/quote admission must also hold. Any unresolved cheaper combination remains a competitor, not removed.
A15: Keep current evidence priority | B15: Apply ALL eligible competitor inequalities in Boundary_All; never include archived101 or over-cap158/159. | C15: Boston remains breakfast/quality/occupancy pending; this is partial-cost evidence priority, not a qualified recommendation.
A16: Drop to18 | B16: ALL admitted24 totals>budget or unavailable; at least one admitted18 total<=budget | C16: Recalculate per-person and fixed/unknown components separately; no proportional scaling of event total.
A17: Neither size executable | B17: No admitted budget-feasible18 or24, or admission evidence absent | C17: Currently admission evidence absent: no qualified recommendation. Evidence priority may still be given without claiming approval.
A18: Negative Umax test @budget30000 | B18: =30000/(1+RESRATE)-Options!P7 -> -11240.731 | C18: Negative means known/estimated K already exceeds budget; never truncate to zero.
A19: Negative Umax stress @30000 | B19: =30000/(1+RESRATE)-Options!P7-0.2*Options!X7 -> -12536.731 | C19: Recompute after any parameter change.
A20: Historical effect | B20: See Historical_Impact 20 units | C20: Same quotes and MIE tiers -> numerical zero delta; caps and candidate eligibility evaluated separately.
A21: Quote applicability | B21: =Parameters!B34 -> DATED SNAPSHOT; inventory unheld | C21: Old-price recalculation on changed dates is not a new quote.
A23: Unknown-difference switch p* (Chicago24 vs Boston24) | B23: =IF(Options!X5=Options!X7,IF(Options!Q7-Options!Q5=Options!P5-Options!P7,"ALL p TIE: alphabetical Boston","PARALLEL: no finite crossing"),((Options!Q7-Options!Q5)-(Options!P5-Options!P7))/(Options!X5-Options!X7)) -> 4.4634146 | C23: Diagnostic arithmetic for the EXCLUDED Chicago158 quote only; not an eligible switch. Current selection and bounds: Candidate_Model / Boundary_All. No authorized above-cap exception.
A24: 18-person switching condition | B24: =Options!P6-Options!P8 -> -3294 | C24: Diagnostic arithmetic for the EXCLUDED Chicago158 quote only; not an eligible switch. Current selection and bounds: Candidate_Model / Boundary_All. No authorized above-cap exception.
A25: Direction of crossing | B25: Chicago airfare slope6480 < Boston7464 | C25: Diagnostic arithmetic for the EXCLUDED Chicago158 quote only; not an eligible switch. Current selection and bounds: Candidate_Model / Boundary_All. No authorized above-cap exception.
A26: Additional captured joint alternatives | B26: Joint_Alternatives: 15 component alternatives ×2headcounts | C26: All44 combinations enter Candidate_Model/Decision; archived101 and above-cap158/159 excluded. Boundary_All contains current priority comparisons.
A27: Conditional no-crossing proof with all recorded alternatives | B27: For EVERY same-headcount primary/alternative j require Uchi-Uj <= (Kj-Kchi)+p*(Aj-Achi) | C27: Use Boundary_All recomputed from current44 combinations. Boundaries are conditional on independent unknowns; excluded quotes do not enter the feasible minimum.

Sheet Itinerary
A1: RETAINED ITINERARY STRUCTURE — Boston priority for evidence completion; no qualified recommendation
A2: Boston P01: DCA-BOS Nov28, trainingNov29-Dec1, returnDec2, four nights. Primary dated flight311, backupA19 flight358. Exact booking, breakfast, occupancy and quality remain pending. Chicago158/159 above-cap excluded.
A4: Item | B4: Detail | C4: Date | D4: Connects to
A5: Outbound flight | B5: DCA → BOS, dated Google Flights Delta311, Nov28 06:00–07:38; verify before ticketing | C5: 2026-11-28 | D5: Arrive BOS afternoon → hotel check-in same day
A6: Hotel check-in | B6: DoubleTree by Hilton Boston Bayside — displayed108; breakfast condition unresolved | C6: 2026-11-28 | D6: Airport-hotel ground allowance included; check actual shuttle and venue address
A7: Training Day 1 | B7: Full day (lunch via registration) | C7: 2026-11-29 | D7: On-site; breakfast at hotel
A8: Training Day 2 | B8: Full day (lunch via registration) | C8: 2026-11-30 | D8: On-site
A9: Training Day 3 | B9: Full day (lunch via registration) | C9: 2026-12-01 | D9: Agency dinner Dec 1 evening
A10: Return flight | B10: BOS → DCA, Dec2 Delta14:29–16:20 (P01). A19 uses alternative AA358; exact meal/transfer timings remain to verify. | C10: 2026-12-02 | D10: Checkout Dec 2 → BOS airport → DCA
A11: Agency catered | B11: Dinner Nov 28, Dinner Dec 1, Lunch Dec 2 | C11: various | D11: Budgeted in Daily/Options
A13: Execution conditions (venue/date/capacity not yet verified):
A14: • Meeting venue address & 24-seat capacity for Nov 29–Dec 1 NOT yet confirmed — list as execution condition (see Register).
A15: • Hotel room block of 24 single rooms at quoted rate NOT confirmed; single-occupancy quote used as whole-group estimate only.
A16: • Flight fares are per-person public quotes (single seat); group inventory at same fare not guaranteed.
A17: Fare class, baggage, refund terms, group seats and room inventory are unheld and must be rechecked.

Sheet Sources
A1: SOURCES, QUERY TIMES & APPLICABILITY
A3: # | B3: Item | C3: Source / platform | D3: URL | E3: Queried (UTC) | F3: Applicable dates / notes
A4: 1 | B4: Flights DCA↔ORD (Chicago) $270 AA nonstop | C4: ITA Matrix (Google) | D4: https://matrix.itasoftware.com | E4: 2026-10-24 | F4: RT Nov 28–Dec 2 2026, 1 adult; public fare, basic econ possible
A5: 2 | B5: Flights DCA↔BOS (Boston) $358 AA nonstop | C5: ITA Matrix (Google) | D5: https://matrix.itasoftware.com | E5: 2026-10-24 | F5: RT Nov 28–Dec 2 2026, 1 adult
A6: 3 | B6: Flights DCA↔PHX (Phoenix) $581 AA nonstop | C6: ITA Matrix (Google) | D6: https://matrix.itasoftware.com | E6: 2026-10-24 | F6: RT Nov 28–Dec 2 2026, 1 adult
A7: 4 | B7: Flights DCA↔DEN (Denver) $741 Frontier / $940 United | C7: ITA Matrix (Google) | D7: https://matrix.itasoftware.com | E7: 2026-10-24 | F7: RT; Frontier basic; United more flexible
A8: 5 | B8: Flights DCA↔SEA (Seattle) $977 nonstop / $982 1-stop | C8: ITA Matrix (Google) | D8: https://matrix.itasoftware.com | E8: 2026-10-24 | F8: RT Nov 28–Dec 2 2026, 1 adult
A9: 6 | B9: Boston hotel — DoubleTree Hilton Boston Bayside $108/n, 8.6/10 (449 rev), breakfast | C9: Trip.com (US) | D9: https://us.trip.com/hotels/list?cityId=26848 | E9: 2026-10-24 | F9: 4 nights, 1 room/1 adult; total $501 incl taxes&fees
A10: 7 | B10: Boston alt — Hilton Boston Park Plaza $205/n, 8.8 (170), breakfast | C10: Trip.com (US) | D10: https://us.trip.com/hotels/list?cityId=26848 | E10: 2026-10-24 | F10: Central; ≤$213 FY27 cap
A11: 8 | B11: Chicago hotel — Warwick Allerton $145/n, 8.6 (399) | C11: Trip.com (US) | D11: https://us.trip.com/hotels/list?cityId=549 | E11: 2026-10-24 | F11: ≤ $148 Dec-1 FY27 cap; total $668 incl tax
A12: 9 | B12: Denver hotel — Home2 Suites Hilton Downtown $109/n, 9.0 (94), breakfast | C12: Trip.com (US) | D12: https://us.trip.com/hotels/list?cityId=20099 | E12: 2026-10-24 | F12: ≤$170 cap
A13: 10 | B13: Phoenix hotel — Hampton Inn & Suites $150/n, 9.4 (116), breakfast | C13: Trip.com (US) | D13: https://us.trip.com/hotels/list?cityId=25938 | E13: 2026-10-24 | F13: ≤$165 cap (thin margin)
A14: 11 | B14: DISCARDED: Seattle103 hotel identity not supported by original screenshot | C14: Trip.com (US) | D14: https://us.trip.com/hotels/list?cityId=511 | E14: 2026-10-24 | F14: Not used; replaced by Country Inn101 dated Google Hotels evidence. Breakfast/occupancy conditions still pending.
A15: 12 | B15: FY2027 per-diem (lodging & M&IE) | C15: GSA / input file | D15: FY2027_PerDiemRates_Validated090126.xlsx | E15: file (read) | F15: Eff. Oct 1 2026 — APPLICABLE year
... A21: 18 | B21: FX note | C21: N/A — all prices captured in USD | D21: ITA Matrix & us.trip.com default USD | E21: 2026-10-24 | F21: No currency conversion applied
A23: Price scope: original market quotes kept as snapshots. Internal12% lodging tax replaces tax planning basis; other mandatory fees not disclosed remain unresolved. No full verified recommendation.
A27: SRC-EXPERT | B27: Corrected flight/room anchors | C27: Original dated model captures, not new quotes | D27: See PPT flight and hotel pages | E27: 2026-10-24 | F27: Qwen real flight captures supplement Claude. Old Seattle103 identity abandoned. Single-room2guests quotes not verified single occupancy.
A28: RD-2036A | B28: Applicable agency instruction | C28: USDA RD official | D28: https://www.rd.usda.gov/media/file/download/2036a.pdf | E28: 2026-10-24 | F28: Effective07/19/24 sec2036.74(a,b): sites/mission/necessity/remote/procurement. Agency cost>20k OCFO advance approval. Old templateOCFO7k/OIG20k/HR933 not automatically current.
A29: MIE-CURRENT | B29: Current CONUS breakdown applicability | C29: GSA official | D29: https://www.gsa.gov/travel/plan-a-trip/per-diem-rates/mie-breakdowns | E29: 2026-10-24 | F29: 92=23/26/38/5;86=22/23/36/5, matches supplied categories; hotel complimentary meals do not reduce MIE.
A30: AIRPORT | B30: Connection routes and published fare range | C30: WMATA official | D30: https://www.wmata.com/rider-guide/airport-and-rail/ | E30: 2026-10-24 | F30: Metro2.25–6.75 one-way published; our early-flight ROAD allowances80/160/200RT are internal assumptions, not this page taxi tariffs.
A31: SCOPE | B31: Unquoted costs and qualifications | C31: Unknowns sheet | D31: Internal estimation, not supplier quote | E31: 2026-10-24 | F31: Independent Ucity,n; default blanks not zero facts. Catering and refresh already estimated, delta inputs adjust them; no registration-lunch double charge.
A32: GROUND-ROAD | B32: Official road taxi information vs internal allowance | C32: MWAA / WMATC / BWI | D32: https://www.flyreagan.com/parking-transportation/taxi-service ; https://www.wmatc.gov/order/new/taxicabfares/WashingtonFlyerTaxi.pdf ; https://bwiairport.com/to-from-bwi/transportation/taxis/ | E32: 2026-10-24 | F32: Published metered/airport fare basis checked.80/160/200RT are disclosed internal planning allowances; traffic, waiting, fuel and personal route details remain unknown.
A33: QUOTE-CORRECTION | B33: Chicago/Seattle offer conditions | C33: Original unmodified Google Hotels screenshots | D33: PPT original image11 and image21 | E33: 2026-10-24 | F33: CHI Billabook101 unbound breakfast archived; Agoda158/Booking159 breakfast shown over cap. SEA Booking101 breakfast shown but2guests; single occupancy unresolved.

Sheet Rates
A1: Key | B1: FY | C1: City | D1: Month | E1: Lodging cap | F1: MIE | G1: Original file | H1: Sheet | I1: Row/location
A2: 2025|Phoenix|1 | B2: 2025 | C2: Phoenix | D2: 1 | E2: 160 | F2: 86 | G2: FY2025_PerDiemMasterRatesFile.xlsx | H2: Master | I2: 18 / Phoenix / Scottsdale
A3: 2025|Phoenix|2 | B3: 2025 | C3: Phoenix | D3: 2 | E3: 229 | F3: 86 | G3: FY2025_PerDiemMasterRatesFile.xlsx | H3: Master | I3: 19 / Phoenix / Scottsdale
A4: 2025|Phoenix|3 | B4: 2025 | C4: Phoenix | D4: 3 | E4: 229 | F4: 86 | G4: FY2025_PerDiemMasterRatesFile.xlsx | H4: Master | I4: 19 / Phoenix / Scottsdale
A5: 2025|Phoenix|4 | B5: 2025 | C5: Phoenix | D5: 4 | E5: 161 | F5: 86 | G5: FY2025_PerDiemMasterRatesFile.xlsx | H5: Master | I5: 20 / Phoenix / Scottsdale
A6: 2025|Phoenix|5 | B6: 2025 | C6: Phoenix | D6: 5 | E6: 161 | F6: 86 | G6: FY2025_PerDiemMasterRatesFile.xlsx | H6: Master | I6: 20 / Phoenix / Scottsdale
A7: 2025|Phoenix|6 | B7: 2025 | C7: Phoenix | D7: 6 | E7: 113 | F7: 86 | G7: FY2025_PerDiemMasterRatesFile.xlsx | H7: Master | I7: 21 / Phoenix / Scottsdale
A8: 2025|Phoenix|7 | B8: 2025 | C8: Phoenix | D8: 7 | E8: 113 | F8: 86 | G8: FY2025_PerDiemMasterRatesFile.xlsx | H8: Master | I8: 21 / Phoenix / Scottsdale
A9: 2025|Phoenix|8 | B9: 2025 | C9: Phoenix | D9: 8 | E9: 113 | F9: 86 | G9: FY2025_PerDiemMasterRatesFile.xlsx | H9: Master | I9: 21 / Phoenix / Scottsdale
A10: 2025|Phoenix|9 | B10: 2025 | C10: Phoenix | D10: 9 | E10: 160 | F10: 86 | G10: FY2025_PerDiemMasterRatesFile.xlsx | H10: Master | I10: 22 / Phoenix / Scottsdale
A11: 2025|Phoenix|10 | B11: 2025 | C11: Phoenix | D11: 10 | E11: 160 | F11: 86 | G11: FY2025_PerDiemMasterRatesFile.xlsx | H11: Master | I11: 18 / Phoenix / Scottsdale
A12: 2025|Phoenix|11 | B12: 2025 | C12: Phoenix | D12: 11 | E12: 160 | F12: 86 | G12: FY2025_PerDiemMasterRatesFile.xlsx | H12: Master | I12: 18 / Phoenix / Scottsdale
A13: 2025|Phoenix|12 | B13: 2025 | C13: Phoenix | D13: 12 | E13: 160 | F13: 86 | G13: FY2025_PerDiemMasterRatesFile.xlsx | H13: Master | I13: 18 / Phoenix / Scottsdale
... A181: 2027|Seattle|12 | B181: 2027 | C181: Seattle | D181: 12 | E181: 188 | F181: 92 | G181: FY2027_PerDiemRates_Validated090126.xlsx | H181: Sheet1 | I181: 627 / Seattle

Sheet MIE_Components
A1: MIE total | B1: Breakfast | C1: Lunch | D1: Dinner | E1: Incidental | F1: Basis
A2: 68 | B2: 16 | C2: 19 | D2: 28 | E2: 5 | F2: Supplied FY2025 breakdown, checked against GSA current CONUS breakdown; not OCONUS
A3: 74 | B3: 18 | C3: 20 | D3: 31 | E3: 5 | F3: Supplied FY2025 breakdown, checked against GSA current CONUS breakdown; not OCONUS
A4: 80 | B4: 20 | C4: 22 | D4: 33 | E4: 5 | F4: Supplied FY2025 breakdown, checked against GSA current CONUS breakdown; not OCONUS
A5: 86 | B5: 22 | C5: 23 | D5: 36 | E5: 5 | F5: Supplied FY2025 breakdown, checked against GSA current CONUS breakdown; not OCONUS
A6: 92 | B6: 23 | C6: 26 | D6: 38 | E6: 5 | F6: Supplied FY2025 breakdown, checked against GSA current CONUS breakdown; not OCONUS

Sheet Unknowns
A1: City | B1: Venue fixed/event USD | C1: Breakfast extra USD/person/night | D1: Venue ground USD/person/trip | E1: Catering adjustment USD/person | F1: Refreshment adjustment USD/person | G1: Other fixed USD | H1: Quality admission (0/1) | I1: Quote/conditions complete (0/1) | J1: Status / billing basis
A2: Boston | H2: 0 | I2: 0 | J2: Blank=unquoted. Independent city inputs; catering/refresh entries adjust existing planning allowances, not duplicate purchases. 1 flags only after evidence, not current facts.
A3: Chicago | H3: 0 | I3: 0 | J3: Blank=unquoted. Independent city inputs; catering/refresh entries adjust existing planning allowances, not duplicate purchases. 1 flags only after evidence, not current facts.
A4: Denver | H4: 0 | I4: 0 | J4: Blank=unquoted. Independent city inputs; catering/refresh entries adjust existing planning allowances, not duplicate purchases. 1 flags only after evidence, not current facts.
A5: Phoenix | H5: 0 | I5: 0 | J5: Blank=unquoted. Independent city inputs; catering/refresh entries adjust existing planning allowances, not duplicate purchases. 1 flags only after evidence, not current facts.
A6: Seattle | H6: 0 | I6: 0 | J6: Blank=unquoted. Independent city inputs; catering/refresh entries adjust existing planning allowances, not duplicate purchases. 1 flags only after evidence, not current facts.

Sheet MIE_Daily
A1: Date | B1: Boston MIE rate | C1: Boston Breakfast | D1: Boston Lunch | E1: Boston Dinner | F1: Boston Net MIE | G1: Boston Room+12% tax | H1: Boston Room cap | I1: Boston Night compliant | J1: Chicago MIE rate | K1: Chicago Breakfast | L1: Chicago Lunch | M1: Chicago Dinner | N1: Chicago Net MIE | O1: Chicago Room+12% tax | P1: Chicago Room cap | Q1: Chicago Night compliant | R1: Denver MIE rate | S1: Denver Breakfast | T1: Denver Lunch | U1: Denver Dinner | V1: Denver Net MIE | W1: Denver Room+12% tax | X1: Denver Room cap | Y1: Denver Night compliant | Z1: Phoenix MIE rate | AA1: Phoenix Breakfast | AB1: Phoenix Lunch | AC1: Phoenix Dinner | AD1: Phoenix Net MIE | AE1: Phoenix Room+12% tax | AF1: Phoenix Room cap | AG1: Phoenix Night compliant | AH1: Seattle MIE rate | AI1: Seattle Breakfast | AJ1: Seattle Lunch | AK1: Seattle Dinner | AL1: Seattle Net MIE | AM1: Seattle Room+12% tax | AN1: Seattle Room cap | AO1: Seattle Night compliant
A2: =IF(AND(Parameters!$B$14>=Parameters!$B$13,ROW()-2<=Parameters!$B$14-Parameters!$B$13),Parameters!$B$13+ROW()-2,"") -> 46354 | B2: =IF($A2="",0,IFERROR(VLOOKUP((YEAR($A2)+IF(MONTH($A2)>=10,1,0))&"|Boston|"&MONTH($A2),Rates!$A$2:$I$181,6,FALSE()),0)) -> 92 | C2: =IF(B2=0,0,VLOOKUP(B2,MIE_Components!$A$2:$F$6,2,FALSE())) -> 23 | D2: =IF(B2=0,0,VLOOKUP(B2,MIE_Components!$A$2:$F$6,3,FALSE())) -> 26 | E2: =IF(B2=0,0,VLOOKUP(B2,MIE_Components!$A$2:$F$6,4,FALSE())) -> 38 | F2: =IF(OR($A2="",B2=0),0,MAX(5,B2*IF(OR($A2=Parameters!$B$13,$A2=Parameters!$B$14),0.75,1)-(IF(AND($A2=DATE(2026,11,29),NOV29BF="Yes"),C2,0)+IF(OR($A2=DATE(2026,11,29),$A2=DATE(2026,11,30),$A2=DATE(2026,12,1),$A2=DATE(2026,12,2)),D2,0)+IF(OR($A2=DATE(2026,11,28),$A2=DATE(2026,12,1)),E2,0)))) -> 31 | G2: =IF(AND($A2<>"",$A2<Parameters!$B$14),CityData!F3*(1+TAXRATE),0) -> 120.96 | H2: =IF($A2="",0,IFERROR(VLOOKUP((YEAR($A2)+IF(MONTH($A2)>=10,1,0))&"|Boston|"&MONTH($A2),Rates!$A$2:$I$181,5,FALSE()),0)) -> 213 | I2: =IF(OR($A2="",$A2>=Parameters!$B$14),1,IF(AND(H2>0,CityData!F3<=H2),1,0)) -> 1 | J2: =IF($A2="",0,IFERROR(VLOOKUP((YEAR($A2)+IF(MONTH($A2)>=10,1,0))&"|Chicago|"&MONTH($A2),Rates!$A$2:$I$181,6,FALSE()),0)) -> 92 | K2: =IF(J2=0,0,VLOOKUP(J2,MIE_Components!$A$2:$F$6,2,FALSE())) -> 23 | L2: =IF(J2=0,0,VLOOKUP(J2,MIE_Components!$A$2:$F$6,3,FALSE())) -> 26 | M2: =IF(J2=0,0,VLOOKUP(J2,MIE_Components!$A$2:$F$6,4,FALSE())) -> 38 | N2: =IF(OR($A2="",J2=0),0,MAX(5,J2*IF(OR($A2=Parameters!$B$13,$A2=Parameters!$B$14),0.75,1)-(IF(AND($A2=DATE(2026,11,29),NOV29BF="Yes"),K2,0)+IF(OR($A2=DATE(2026,11,29),$A2=DATE(2026,11,30),$A2=DATE(2026,12,1),$A2=DATE(2026,12,2)),L2,0)+IF(OR($A2=DATE(2026,11,28),$A2=DATE(2026,12,1)),M2,0)))) -> 31 | O2: =IF(AND($A2<>"",$A2<Parameters!$B$14),CityData!F4*(1+TAXRATE),0) -> 176.96 | P2: =IF($A2="",0,IFERROR(VLOOKUP((YEAR($A2)+IF(MONTH($A2)>=10,1,0))&"|Chicago|"&MONTH($A2),Rates!$A$2:$I$181,5,FALSE()),0)) -> 232 | Q2: =IF(OR($A2="",$A2>=Parameters!$B$14),1,IF(AND(P2>0,CityData!F4<=P2),1,0)) -> 1 | R2: =IF($A2="",0,IFERROR(VLOOKUP((YEAR($A2)+IF(MONTH($A2)>=10,1,0))&"|Denver|"&MONTH($A2),Rates!$A$2:$I$181,6,FALSE()),0)) -> 92 | S2: =IF(R2=0,0,VLOOKUP(R2,MIE_Components!$A$2:$F$6,2,FALSE())) -> 23 | T2: =IF(R2=0,0,VLOOKUP(R2,MIE_Components!$A$2:$F$6,3,FALSE())) -> 26 | U2: =IF(R2=0,0,VLOOKUP(R2,MIE_Components!$A$2:$F$6,4,FALSE())) -> 38 | V2: =IF(OR($A2="",R2=0),0,MAX(5,R2*IF(OR($A2=Parameters!$B$13,$A2=Parameters!$B$14),0.75,1)-(IF(AND($A2=DATE(2026,11,29),NOV29BF="Yes"),S2,0)+IF(OR($A2=DATE(2026,11,29),$A2=DATE(2026,11,30),$A2=DATE(2026,12,1),$A2=DATE(2026,12,2)),T2,0)+IF(OR($A2=DATE(2026,11,28),$A2=DATE(2026,12,1)),U2,0)))) -> 31 | W2: =IF(AND($A2<>"",$A2<Parameters!$B$14),CityData!F5*(1+TAXRATE),0) -> 122.08 | X2: =IF($A2="",0,IFERROR(VLOOKUP((YEAR($A2)+IF(MONTH($A2)>=10,1,0))&"|Denver|"&MONTH($A2),Rates!$A$2:$I$181,5,FALSE()),0)) -> 170 | Y2: =IF(OR($A2="",$A2>=Parameters!$B$14),1,IF(AND(X2>0,CityData!F5<=X2),1,0)) -> 1 | Z2: =IF($A2="",0,IFERROR(VLOOKUP((YEAR($A2)+IF(MONTH($A2)>=10,1,0))&"|Phoenix|"&MONTH($A2),Rates!$A$2:$I$181,6,FALSE()),0)) -> 86 | AA2: =IF(Z2=0,0,VLOOKUP(Z2,MIE_Components!$A$2:$F$6,2,FALSE())) -> 22 | AB2: =IF(Z2=0,0,VLOOKUP(Z2,MIE_Components!$A$2:$F$6,3,FALSE())) -> 23 | AC2: =IF(Z2=0,0,VLOOKUP(Z2,MIE_Components!$A$2:$F$6,4,FALSE())) -> 36 | AD2: =IF(OR($A2="",Z2=0),0,MAX(5,Z2*IF(OR($A2=Parameters!$B$13,$A2=Parameters!$B$14),0.75,1)-(IF(AND($A2=DATE(2026,11,29),NOV29BF="Yes"),AA2,0)+IF(OR($A2=DATE(2026,11,29),$A2=DATE(2026,11,30),$A2=DATE(2026,12,1),$A2=DATE(2026,12,2)),AB2,0)+IF(OR($A2=DATE(2026,11,28),$A2=DATE(2026,12,1)),AC2,0)))) -> 28.5 | AE2: =IF(AND($A2<>"",$A2<Parameters!$B$14),CityData!F6*(1+TAXRATE),0) -> 168 | AF2: =IF($A2="",0,IFERROR(VLOOKUP((YEAR($A2)+IF(MONTH($A2)>=10,1,0))&"|Phoenix|"&MONTH($A2),Rates!$A$2:$I$181,5,FALSE()),0)) -> 165 | AG2: =IF(OR($A2="",$A2>=Parameters!$B$14),1,IF(AND(AF2>0,CityData!F6<=AF2),1,0)) -> 1 | AH2: =IF($A2="",0,IFERROR(VLOOKUP((YEAR($A2)+IF(MONTH($A2)>=10,1,0))&"|Seattle|"&MONTH($A2),Rates!$A$2:$I$181,6,FALSE()),0)) -> 92 | AI2: =IF(AH2=0,0,VLOOKUP(AH2,MIE_Components!$A$2:$F$6,2,FALSE())) -> 23 | AJ2: =IF(AH2=0,0,VLOOKUP(AH2,MIE_Components!$A$2:$F$6,3,FALSE())) -> 26 | AK2: =IF(AH2=0,0,VLOOKUP(AH2,MIE_Components!$A$2:$F$6,4,FALSE())) -> 38 | AL2: =IF(OR($A2="",AH2=0),0,MAX(5,AH2*IF(OR($A2=Parameters!$B$13,$A2=Parameters!$B$14),0.75,1)-(IF(AND($A2=DATE(2026,11,29),NOV29BF="Yes"),AI2,0)+IF(OR($A2=DATE(2026,11,29),$A2=DATE(2026,11,30),$A2=DATE(2026,12,1),$A2=DATE(2026,12,2)),AJ2,0)+IF(OR($A2=DATE(2026,11,28),$A2=DATE(2026,12,1)),AK2,0)))) -> 31 | AM2: =IF(AND($A2<>"",$A2<Parameters!$B$14),CityData!F7*(1+TAXRATE),0) -> 113.12 | AN2: =IF($A2="",0,IFERROR(VLOOKUP((YEAR($A2)+IF(MONTH($A2)>=10,1,0))&"|Seattle|"&MONTH($A2),Rates!$A$2:$I$181,5,FALSE()),0)) -> 188 | AO2: =IF(OR($A2="",$A2>=Parameters!$B$14),1,IF(AND(AN2>0,CityData!F7<=AN2),1,0)) -> 1
A3: =IF(AND(Parameters!$B$14>=Parameters!$B$13,ROW()-2<=Parameters!$B$14-Parameters!$B$13),Parameters!$B$13+ROW()-2,"") -> 46355 | B3: =IF($A3="",0,IFERROR(VLOOKUP((YEAR($A3)+IF(MONTH($A3)>=10,1,0))&"|Boston|"&MONTH($A3),Rates!$A$2:$I$181,6,FALSE()),0)) -> 92 | C3: =IF(B3=0,0,VLOOKUP(B3,MIE_Components!$A$2:$F$6,2,FALSE())) -> 23 | D3: =IF(B3=0,0,VLOOKUP(B3,MIE_Components!$A$2:$F$6,3,FALSE())) -> 26 | E3: =IF(B3=0,0,VLOOKUP(B3,MIE_Components!$A$2:$F$6,4,FALSE())) -> 38 | F3: =IF(OR($A3="",B3=0),0,MAX(5,B3*IF(OR($A3=Parameters!$B$13,$A3=Parameters!$B$14),0.75,1)-(IF(AND($A3=DATE(2026,11,29),NOV29BF="Yes"),C3,0)+IF(OR($A3=DATE(2026,11,29),$A3=DATE(2026,11,30),$A3=DATE(2026,12,1),$A3=DATE(2026,12,2)),D3,0)+IF(OR($A3=DATE(2026,11,28),$A3=DATE(2026,12,1)),E3,0)))) -> 66 | G3: =IF(AND($A3<>"",$A3<Parameters!$B$14),CityData!F3*(1+TAXRATE),0) -> 120.96 | H3: =IF($A3="",0,IFERROR(VLOOKUP((YEAR($A3)+IF(MONTH($A3)>=10,1,0))&"|Boston|"&MONTH($A3),Rates!$A$2:$I$181,5,FALSE()),0)) -> 213 | I3: =IF(OR($A3="",$A3>=Parameters!$B$14),1,IF(AND(H3>0,CityData!F3<=H3),1,0)) -> 1 | J3: =IF($A3="",0,IFERROR(VLOOKUP((YEAR($A3)+IF(MONTH($A3)>=10,1,0))&"|Chicago|"&MONTH($A3),Rates!$A$2:$I$181,6,FALSE()),0)) -> 92 | K3: =IF(J3=0,0,VLOOKUP(J3,MIE_Components!$A$2:$F$6,2,FALSE())) -> 23 | L3: =IF(J3=0,0,VLOOKUP(J3,MIE_Components!$A$2:$F$6,3,FALSE())) -> 26 | M3: =IF(J3=0,0,VLOOKUP(J3,MIE_Components!$A$2:$F$6,4,FALSE())) -> 38 | N3: =IF(OR($A3="",J3=0),0,MAX(5,J3*IF(OR($A3=Parameters!$B$13,$A3=Parameters!$B$14),0.75,1)-(IF(AND($A3=DATE(2026,11,29),NOV29BF="Yes"),K3,0)+IF(OR($A3=DATE(2026,11,29),$A3=DATE(2026,11,30),$A3=DATE(2026,12,1),$A3=DATE(2026,12,2)),L3,0)+IF(OR($A3=DATE(2026,11,28),$A3=DATE(2026,12,1)),M3,0)))) -> 66 | O3: =IF(AND($A3<>"",$A3<Parameters!$B$14),CityData!F4*(1+TAXRATE),0) -> 176.96 | P3: =IF($A3="",0,IFERROR(VLOOKUP((YEAR($A3)+IF(MONTH($A3)>=10,1,0))&"|Chicago|"&MONTH($A3),Rates!$A$2:$I$181,5,FALSE()),0)) -> 232 | Q3: =IF(OR($A3="",$A3>=Parameters!$B$14),1,IF(AND(P3>0,CityData!F4<=P3),1,0)) -> 1 | R3: =IF($A3="",0,IFERROR(VLOOKUP((YEAR($A3)+IF(MONTH($A3)>=10,1,0))&"|Denver|"&MONTH($A3),Rates!$A$2:$I$181,6,FALSE()),0)) -> 92 | S3: =IF(R3=0,0,VLOOKUP(R3,MIE_Components!$A$2:$F$6,2,FALSE())) -> 23 | T3: =IF(R3=0,0,VLOOKUP(R3,MIE_Components!$A$2:$F$6,3,FALSE())) -> 26 | U3: =IF(R3=0,0,VLOOKUP(R3,MIE_Components!$A$2:$F$6,4,FALSE())) -> 38 | V3: =IF(OR($A3="",R3=0),0,MAX(5,R3*IF(OR($A3=Parameters!$B$13,$A3=Parameters!$B$14),0.75,1)-(IF(AND($A3=DATE(2026,11,29),NOV29BF="Yes"),S3,0)+IF(OR($A3=DATE(2026,11,29),$A3=DATE(2026,11,30),$A3=DATE(2026,12,1),$A3=DATE(2026,12,2)),T3,0)+IF(OR($A3=DATE(2026,11,28),$A3=DATE(2026,12,1)),U3,0)))) -> 66 | W3: =IF(AND($A3<>"",$A3<Parameters!$B$14),CityData!F5*(1+TAXRATE),0) -> 122.08 | X3: =IF($A3="",0,IFERROR(VLOOKUP((YEAR($A3)+IF(MONTH($A3)>=10,1,0))&"|Denver|"&MONTH($A3),Rates!$A$2:$I$181,5,FALSE()),0)) -> 170 | Y3: =IF(OR($A3="",$A3>=Parameters!$B$14),1,IF(AND(X3>0,CityData!F5<=X3),1,0)) -> 1 | Z3: =IF($A3="",0,IFERROR(VLOOKUP((YEAR($A3)+IF(MONTH($A3)>=10,1,0))&"|Phoenix|"&MONTH($A3),Rates!$A$2:$I$181,6,FALSE()),0)) -> 86 | AA3: =IF(Z3=0,0,VLOOKUP(Z3,MIE_Components!$A$2:$F$6,2,FALSE())) -> 22 | AB3: =IF(Z3=0,0,VLOOKUP(Z3,MIE_Components!$A$2:$F$6,3,FALSE())) -> 23 | AC3: =IF(Z3=0,0,VLOOKUP(Z3,MIE_Components!$A$2:$F$6,4,FALSE())) -> 36 | AD3: =IF(OR($A3="",Z3=0),0,MAX(5,Z3*IF(OR($A3=Parameters!$B$13,$A3=Parameters!$B$14),0.75,1)-(IF(AND($A3=DATE(2026,11,29),NOV29BF="Yes"),AA3,0)+IF(OR($A3=DATE(2026,11,29),$A3=DATE(2026,11,30),$A3=DATE(2026,12,1),$A3=DATE(2026,12,2)),AB3,0)+IF(OR($A3=DATE(2026,11,28),$A3=DATE(2026,12,1)),AC3,0)))) -> 63 | AE3: =IF(AND($A3<>"",$A3<Parameters!$B$14),CityData!F6*(1+TAXRATE),0) -> 168 | AF3: =IF($A3="",0,IFERROR(VLOOKUP((YEAR($A3)+IF(MONTH($A3)>=10,1,0))&"|Phoenix|"&MONTH($A3),Rates!$A$2:$I$181,5,FALSE()),0)) -> 165 | AG3: =IF(OR($A3="",$A3>=Parameters!$B$14),1,IF(AND(AF3>0,CityData!F6<=AF3),1,0)) -> 1 | AH3: =IF($A3="",0,IFERROR(VLOOKUP((YEAR($A3)+IF(MONTH($A3)>=10,1,0))&"|Seattle|"&MONTH($A3),Rates!$A$2:$I$181,6,FALSE()),0)) -> 92 | AI3: =IF(AH3=0,0,VLOOKUP(AH3,MIE_Components!$A$2:$F$6,2,FALSE())) -> 23 | AJ3: =IF(AH3=0,0,VLOOKUP(AH3,MIE_Components!$A$2:$F$6,3,FALSE())) -> 26 | AK3: =IF(AH3=0,0,VLOOKUP(AH3,MIE_Components!$A$2:$F$6,4,FALSE())) -> 38 | AL3: =IF(OR($A3="",AH3=0),0,MAX(5,AH3*IF(OR($A3=Parameters!$B$13,$A3=Parameters!$B$14),0.75,1)-(IF(AND($A3=DATE(2026,11,29),NOV29BF="Yes"),AI3,0)+IF(OR($A3=DATE(2026,11,29),$A3=DATE(2026,11,30),$A3=DATE(2026,12,1),$A3=DATE(2026,12,2)),AJ3,0)+IF(OR($A3=DATE(2026,11,28),$A3=DATE(2026,12,1)),AK3,0)))) -> 66 | AM3: =IF(AND($A3<>"",$A3<Parameters!$B$14),CityData!F7*(1+TAXRATE),0) -> 113.12 | AN3: =IF($A3="",0,IFERROR(VLOOKUP((YEAR($A3)+IF(MONTH($A3)>=10,1,0))&"|Seattle|"&MONTH($A3),Rates!$A$2:$I$181,5,FALSE()),0)) -> 188 | AO3: =IF(OR($A3="",$A3>=Parameters!$B$14),1,IF(AND(AN3>0,CityData!F7<=AN3),1,0)) -> 1
A4: =IF(AND(Parameters!$B$14>=Parameters!$B$13,ROW()-2<=Parameters!$B$14-Parameters!$B$13),Parameters!$B$13+ROW()-2,"") -> 46356 | B4: =IF($A4="",0,IFERROR(VLOOKUP((YEAR($A4)+IF(MONTH($A4)>=10,1,0))&"|Boston|"&MONTH($A4),Rates!$A$2:$I$181,6,FALSE()),0)) -> 92 | C4: =IF(B4=0,0,VLOOKUP(B4,MIE_Components!$A$2:$F$6,2,FALSE())) -> 23 | D4: =IF(B4=0,0,VLOOKUP(B4,MIE_Components!$A$2:$F$6,3,FALSE())) -> 26 | E4: =IF(B4=0,0,VLOOKUP(B4,MIE_Components!$A$2:$F$6,4,FALSE())) -> 38 | F4: =IF(OR($A4="",B4=0),0,MAX(5,B4*IF(OR($A4=Parameters!$B$13,$A4=Parameters!$B$14),0.75,1)-(IF(AND($A4=DATE(2026,11,29),NOV29BF="Yes"),C4,0)+IF(OR($A4=DATE(2026,11,29),$A4=DATE(2026,11,30),$A4=DATE(2026,12,1),$A4=DATE(2026,12,2)),D4,0)+IF(OR($A4=DATE(2026,11,28),$A4=DATE(2026,12,1)),E4,0)))) -> 66 | G4: =IF(AND($A4<>"",$A4<Parameters!$B$14),CityData!F3*(1+TAXRATE),0) -> 120.96 | H4: =IF($A4="",0,IFERROR(VLOOKUP((YEAR($A4)+IF(MONTH($A4)>=10,1,0))&"|Boston|"&MONTH($A4),Rates!$A$2:$I$181,5,FALSE()),0)) -> 213 | I4: =IF(OR($A4="",$A4>=Parameters!$B$14),1,IF(AND(H4>0,CityData!F3<=H4),1,0)) -> 1 | J4: =IF($A4="",0,IFERROR(VLOOKUP((YEAR($A4)+IF(MONTH($A4)>=10,1,0))&"|Chicago|"&MONTH($A4),Rates!$A$2:$I$181,6,FALSE()),0)) -> 92 | K4: =IF(J4=0,0,VLOOKUP(J4,MIE_Components!$A$2:$F$6,2,FALSE())) -> 23 | L4: =IF(J4=0,0,VLOOKUP(J4,MIE_Components!$A$2:$F$6,3,FALSE())) -> 26 | M4: =IF(J4=0,0,VLOOKUP(J4,MIE_Components!$A$2:$F$6,4,FALSE())) -> 38 | N4: =IF(OR($A4="",J4=0),0,MAX(5,J4*IF(OR($A4=Parameters!$B$13,$A4=Parameters!$B$14),0.75,1)-(IF(AND($A4=DATE(2026,11,29),NOV29BF="Yes"),K4,0)+IF(OR($A4=DATE(2026,11,29),$A4=DATE(2026,11,30),$A4=DATE(2026,12,1),$A4=DATE(2026,12,2)),L4,0)+IF(OR($A4=DATE(2026,11,28),$A4=DATE(2026,12,1)),M4,0)))) -> 66 | O4: =IF(AND($A4<>"",$A4<Parameters!$B$14),CityData!F4*(1+TAXRATE),0) -> 176.96 | P4: =IF($A4="",0,IFERROR(VLOOKUP((YEAR($A4)+IF(MONTH($A4)>=10,1,0))&"|Chicago|"&MONTH($A4),Rates!$A$2:$I$181,5,FALSE()),0)) -> 232 | Q4: =IF(OR($A4="",$A4>=Parameters!$B$14),1,IF(AND(P4>0,CityData!F4<=P4),1,0)) -> 1 | R4: =IF($A4="",0,IFERROR(VLOOKUP((YEAR($A4)+IF(MONTH($A4)>=10,1,0))&"|Denver|"&MONTH($A4),Rates!$A$2:$I$181,6,FALSE()),0)) -> 92 | S4: =IF(R4=0,0,VLOOKUP(R4,MIE_Components!$A$2:$F$6,2,FALSE())) -> 23 | T4: =IF(R4=0,0,VLOOKUP(R4,MIE_Components!$A$2:$F$6,3,FALSE())) -> 26 | U4: =IF(R4=0,0,VLOOKUP(R4,MIE_Components!$A$2:$F$6,4,FALSE())) -> 38 | V4: =IF(OR($A4="",R4=0),0,MAX(5,R4*IF(OR($A4=Parameters!$B$13,$A4=Parameters!$B$14),0.75,1)-(IF(AND($A4=DATE(2026,11,29),NOV29BF="Yes"),S4,0)+IF(OR($A4=DATE(2026,11,29),$A4=DATE(2026,11,30),$A4=DATE(2026,12,1),$A4=DATE(2026,12,2)),T4,0)+IF(OR($A4=DATE(2026,11,28),$A4=DATE(2026,12,1)),U4,0)))) -> 66 | W4: =IF(AND($A4<>"",$A4<Parameters!$B$14),CityData!F5*(1+TAXRATE),0) -> 122.08 | X4: =IF($A4="",0,IFERROR(VLOOKUP((YEAR($A4)+IF(MONTH($A4)>=10,1,0))&"|Denver|"&MONTH($A4),Rates!$A$2:$I$181,5,FALSE()),0)) -> 170 | Y4: =IF(OR($A4="",$A4>=Parameters!$B$14),1,IF(AND(X4>0,CityData!F5<=X4),1,0)) -> 1 | Z4: =IF($A4="",0,IFERROR(VLOOKUP((YEAR($A4)+IF(MONTH($A4)>=10,1,0))&"|Phoenix|"&MONTH($A4),Rates!$A$2:$I$181,6,FALSE()),0)) -> 86 | AA4: =IF(Z4=0,0,VLOOKUP(Z4,MIE_Components!$A$2:$F$6,2,FALSE())) -> 22 | AB4: =IF(Z4=0,0,VLOOKUP(Z4,MIE_Components!$A$2:$F$6,3,FALSE())) -> 23 | AC4: =IF(Z4=0,0,VLOOKUP(Z4,MIE_Components!$A$2:$F$6,4,FALSE())) -> 36 | AD4: =IF(OR($A4="",Z4=0),0,MAX(5,Z4*IF(OR($A4=Parameters!$B$13,$A4=Parameters!$B$14),0.75,1)-(IF(AND($A4=DATE(2026,11,29),NOV29BF="Yes"),AA4,0)+IF(OR($A4=DATE(2026,11,29),$A4=DATE(2026,11,30),$A4=DATE(2026,12,1),$A4=DATE(2026,12,2)),AB4,0)+IF(OR($A4=DATE(2026,11,28),$A4=DATE(2026,12,1)),AC4,0)))) -> 63 | AE4: =IF(AND($A4<>"",$A4<Parameters!$B$14),CityData!F6*(1+TAXRATE),0) -> 168 | AF4: =IF($A4="",0,IFERROR(VLOOKUP((YEAR($A4)+IF(MONTH($A4)>=10,1,0))&"|Phoenix|"&MONTH($A4),Rates!$A$2:$I$181,5,FALSE()),0)) -> 165 | AG4: =IF(OR($A4="",$A4>=Parameters!$B$14),1,IF(AND(AF4>0,CityData!F6<=AF4),1,0)) -> 1 | AH4: =IF($A4="",0,IFERROR(VLOOKUP((YEAR($A4)+IF(MONTH($A4)>=10,1,0))&"|Seattle|"&MONTH($A4),Rates!$A$2:$I$181,6,FALSE()),0)) -> 92 | AI4: =IF(AH4=0,0,VLOOKUP(AH4,MIE_Components!$A$2:$F$6,2,FALSE())) -> 23 | AJ4: =IF(AH4=0,0,VLOOKUP(AH4,MIE_Components!$A$2:$F$6,3,FALSE())) -> 26 | AK4: =IF(AH4=0,0,VLOOKUP(AH4,MIE_Components!$A$2:$F$6,4,FALSE())) -> 38 | AL4: =IF(OR($A4="",AH4=0),0,MAX(5,AH4*IF(OR($A4=Parameters!$B$13,$A4=Parameters!$B$14),0.75,1)-(IF(AND($A4=DATE(2026,11,29),NOV29BF="Yes"),AI4,0)+IF(OR($A4=DATE(2026,11,29),$A4=DATE(2026,11,30),$A4=DATE(2026,12,1),$A4=DATE(2026,12,2)),AJ4,0)+IF(OR($A4=DATE(2026,11,28),$A4=DATE(2026,12,1)),AK4,0)))) -> 66 | AM4: =IF(AND($A4<>"",$A4<Parameters!$B$14),CityData!F7*(1+TAXRATE),0) -> 113.12 | AN4: =IF($A4="",0,IFERROR(VLOOKUP((YEAR($A4)+IF(MONTH($A4)>=10,1,0))&"|Seattle|"&MONTH($A4),Rates!$A$2:$I$181,5,FALSE()),0)) -> 188 | AO4: =IF(OR($A4="",$A4>=Parameters!$B$14),1,IF(AND(AN4>0,CityData!F7<=AN4),1,0)) -> 1
A5: =IF(AND(Parameters!$B$14>=Parameters!$B$13,ROW()-2<=Parameters!$B$14-Parameters!$B$13),Parameters!$B$13+ROW()-2,"") -> 46357 | B5: =IF($A5="",0,IFERROR(VLOOKUP((YEAR($A5)+IF(MONTH($A5)>=10,1,0))&"|Boston|"&MONTH($A5),Rates!$A$2:$I$181,6,FALSE()),0)) -> 92 | C5: =IF(B5=0,0,VLOOKUP(B5,MIE_Components!$A$2:$F$6,2,FALSE())) -> 23 | D5: =IF(B5=0,0,VLOOKUP(B5,MIE_Components!$A$2:$F$6,3,FALSE())) -> 26 | E5: =IF(B5=0,0,VLOOKUP(B5,MIE_Components!$A$2:$F$6,4,FALSE())) -> 38 | F5: =IF(OR($A5="",B5=0),0,MAX(5,B5*IF(OR($A5=Parameters!$B$13,$A5=Parameters!$B$14),0.75,1)-(IF(AND($A5=DATE(2026,11,29),NOV29BF="Yes"),C5,0)+IF(OR($A5=DATE(2026,11,29),$A5=DATE(2026,11,30),$A5=DATE(2026,12,1),$A5=DATE(2026,12,2)),D5,0)+IF(OR($A5=DATE(2026,11,28),$A5=DATE(2026,12,1)),E5,0)))) -> 28 | G5: =IF(AND($A5<>"",$A5<Parameters!$B$14),CityData!F3*(1+TAXRATE),0) -> 120.96 | H5: =IF($A5="",0,IFERROR(VLOOKUP((YEAR($A5)+IF(MONTH($A5)>=10,1,0))&"|Boston|"&MONTH($A5),Rates!$A$2:$I$181,5,FALSE()),0)) -> 213 | I5: =IF(OR($A5="",$A5>=Parameters!$B$14),1,IF(AND(H5>0,CityData!F3<=H5),1,0)) -> 1 | J5: =IF($A5="",0,IFERROR(VLOOKUP((YEAR($A5)+IF(MONTH($A5)>=10,1,0))&"|Chicago|"&MONTH($A5),Rates!$A$2:$I$181,6,FALSE()),0)) -> 92 | K5: =IF(J5=0,0,VLOOKUP(J5,MIE_Components!$A$2:$F$6,2,FALSE())) -> 23 | L5: =IF(J5=0,0,VLOOKUP(J5,MIE_Components!$A$2:$F$6,3,FALSE())) -> 26 | M5: =IF(J5=0,0,VLOOKUP(J5,MIE_Components!$A$2:$F$6,4,FALSE())) -> 38 | N5: =IF(OR($A5="",J5=0),0,MAX(5,J5*IF(OR($A5=Parameters!$B$13,$A5=Parameters!$B$14),0.75,1)-(IF(AND($A5=DATE(2026,11,29),NOV29BF="Yes"),K5,0)+IF(OR($A5=DATE(2026,11,29),$A5=DATE(2026,11,30),$A5=DATE(2026,12,1),$A5=DATE(2026,12,2)),L5,0)+IF(OR($A5=DATE(2026,11,28),$A5=DATE(2026,12,1)),M5,0)))) -> 28 | O5: =IF(AND($A5<>"",$A5<Parameters!$B$14),CityData!F4*(1+TAXRATE),0) -> 176.96 | P5: =IF($A5="",0,IFERROR(VLOOKUP((YEAR($A5)+IF(MONTH($A5)>=10,1,0))&"|Chicago|"&MONTH($A5),Rates!$A$2:$I$181,5,FALSE()),0)) -> 148 | Q5: =IF(OR($A5="",$A5>=Parameters!$B$14),1,IF(AND(P5>0,CityData!F4<=P5),1,0)) -> 0 | R5: =IF($A5="",0,IFERROR(VLOOKUP((YEAR($A5)+IF(MONTH($A5)>=10,1,0))&"|Denver|"&MONTH($A5),Rates!$A$2:$I$181,6,FALSE()),0)) -> 92 | S5: =IF(R5=0,0,VLOOKUP(R5,MIE_Components!$A$2:$F$6,2,FALSE())) -> 23 | T5: =IF(R5=0,0,VLOOKUP(R5,MIE_Components!$A$2:$F$6,3,FALSE())) -> 26 | U5: =IF(R5=0,0,VLOOKUP(R5,MIE_Components!$A$2:$F$6,4,FALSE())) -> 38 | V5: =IF(OR($A5="",R5=0),0,MAX(5,R5*IF(OR($A5=Parameters!$B$13,$A5=Parameters!$B$14),0.75,1)-(IF(AND($A5=DATE(2026,11,29),NOV29BF="Yes"),S5,0)+IF(OR($A5=DATE(2026,11,29),$A5=DATE(2026,11,30),$A5=DATE(2026,12,1),$A5=DATE(2026,12,2)),T5,0)+IF(OR($A5=DATE(2026,11,28),$A5=DATE(2026,12,1)),U5,0)))) -> 28 | W5: =IF(AND($A5<>"",$A5<Parameters!$B$14),CityData!F5*(1+TAXRATE),0) -> 122.08 | X5: =IF($A5="",0,IFERROR(VLOOKUP((YEAR($A5)+IF(MONTH($A5)>=10,1,0))&"|Denver|"&MONTH($A5),Rates!$A$2:$I$181,5,FALSE()),0)) -> 170 | Y5: =IF(OR($A5="",$A5>=Parameters!$B$14),1,IF(AND(X5>0,CityData!F5<=X5),1,0)) -> 1 | Z5: =IF($A5="",0,IFERROR(VLOOKUP((YEAR($A5)+IF(MONTH($A5)>=10,1,0))&"|Phoenix|"&MONTH($A5),Rates!$A$2:$I$181,6,FALSE()),0)) -> 86 | AA5: =IF(Z5=0,0,VLOOKUP(Z5,MIE_Components!$A$2:$F$6,2,FALSE())) -> 22 | AB5: =IF(Z5=0,0,VLOOKUP(Z5,MIE_Components!$A$2:$F$6,3,FALSE())) -> 23 | AC5: =IF(Z5=0,0,VLOOKUP(Z5,MIE_Components!$A$2:$F$6,4,FALSE())) -> 36 | AD5: =IF(OR($A5="",Z5=0),0,MAX(5,Z5*IF(OR($A5=Parameters!$B$13,$A5=Parameters!$B$14),0.75,1)-(IF(AND($A5=DATE(2026,11,29),NOV29BF="Yes"),AA5,0)+IF(OR($A5=DATE(2026,11,29),$A5=DATE(2026,11,30),$A5=DATE(2026,12,1),$A5=DATE(2026,12,2)),AB5,0)+IF(OR($A5=DATE(2026,11,28),$A5=DATE(2026,12,1)),AC5,0)))) -> 27 | AE5: =IF(AND($A5<>"",$A5<Parameters!$B$14),CityData!F6*(1+TAXRATE),0) -> 168 | AF5: =IF($A5="",0,IFERROR(VLOOKUP((YEAR($A5)+IF(MONTH($A5)>=10,1,0))&"|Phoenix|"&MONTH($A5),Rates!$A$2:$I$181,5,FALSE()),0)) -> 165 | AG5: =IF(OR($A5="",$A5>=Parameters!$B$14),1,IF(AND(AF5>0,CityData!F6<=AF5),1,0)) -> 1 | AH5: =IF($A5="",0,IFERROR(VLOOKUP((YEAR($A5)+IF(MONTH($A5)>=10,1,0))&"|Seattle|"&MONTH($A5),Rates!$A$2:$I$181,6,FALSE()),0)) -> 92 | AI5: =IF(AH5=0,0,VLOOKUP(AH5,MIE_Components!$A$2:$F$6,2,FALSE())) -> 23 | AJ5: =IF(AH5=0,0,VLOOKUP(AH5,MIE_Components!$A$2:$F$6,3,FALSE())) -> 26 | AK5: =IF(AH5=0,0,VLOOKUP(AH5,MIE_Components!$A$2:$F$6,4,FALSE())) -> 38 | AL5: =IF(OR($A5="",AH5=0),0,MAX(5,AH5*IF(OR($A5=Parameters!$B$13,$A5=Parameters!$B$14),0.75,1)-(IF(AND($A5=DATE(2026,11,29),NOV29BF="Yes"),AI5,0)+IF(OR($A5=DATE(2026,11,29),$A5=DATE(2026,11,30),$A5=DATE(2026,12,1),$A5=DATE(2026,12,2)),AJ5,0)+IF(OR($A5=DATE(2026,11,28),$A5=DATE(2026,12,1)),AK5,0)))) -> 28 | AM5: =IF(AND($A5<>"",$A5<Parameters!$B$14),CityData!F7*(1+TAXRATE),0) -> 113.12 | AN5: =IF($A5="",0,IFERROR(VLOOKUP((YEAR($A5)+IF(MONTH($A5)>=10,1,0))&"|Seattle|"&MONTH($A5),Rates!$A$2:$I$181,5,FALSE()),0)) -> 188 | AO5: =IF(OR($A5="",$A5>=Parameters!$B$14),1,IF(AND(AN5>0,CityData!F7<=AN5),1,0)) -> 1
A6: =IF(AND(Parameters!$B$14>=Parameters!$B$13,ROW()-2<=Parameters!$B$14-Parameters!$B$13),Parameters!$B$13+ROW()-2,"") -> 46358 | B6: =IF($A6="",0,IFERROR(VLOOKUP((YEAR($A6)+IF(MONTH($A6)>=10,1,0))&"|Boston|"&MONTH($A6),Rates!$A$2:$I$181,6,FALSE()),0)) -> 92 | C6: =IF(B6=0,0,VLOOKUP(B6,MIE_Components!$A$2:$F$6,2,FALSE())) -> 23 | D6: =IF(B6=0,0,VLOOKUP(B6,MIE_Components!$A$2:$F$6,3,FALSE())) -> 26 | E6: =IF(B6=0,0,VLOOKUP(B6,MIE_Components!$A$2:$F$6,4,FALSE())) -> 38 | F6: =IF(OR($A6="",B6=0),0,MAX(5,B6*IF(OR($A6=Parameters!$B$13,$A6=Parameters!$B$14),0.75,1)-(IF(AND($A6=DATE(2026,11,29),NOV29BF="Yes"),C6,0)+IF(OR($A6=DATE(2026,11,29),$A6=DATE(2026,11,30),$A6=DATE(2026,12,1),$A6=DATE(2026,12,2)),D6,0)+IF(OR($A6=DATE(2026,11,28),$A6=DATE(2026,12,1)),E6,0)))) -> 43 | G6: =IF(AND($A6<>"",$A6<Parameters!$B$14),CityData!F3*(1+TAXRATE),0) -> 0 | H6: =IF($A6="",0,IFERROR(VLOOKUP((YEAR($A6)+IF(MONTH($A6)>=10,1,0))&"|Boston|"&MONTH($A6),Rates!$A$2:$I$181,5,FALSE()),0)) -> 213 | I6: =IF(OR($A6="",$A6>=Parameters!$B$14),1,IF(AND(H6>0,CityData!F3<=H6),1,0)) -> 1 | J6: =IF($A6="",0,IFERROR(VLOOKUP((YEAR($A6)+IF(MONTH($A6)>=10,1,0))&"|Chicago|"&MONTH($A6),Rates!$A$2:$I$181,6,FALSE()),0)) -> 92 | K6: =IF(J6=0,0,VLOOKUP(J6,MIE_Components!$A$2:$F$6,2,FALSE())) -> 23 | L6: =IF(J6=0,0,VLOOKUP(J6,MIE_Components!$A$2:$F$6,3,FALSE())) -> 26 | M6: =IF(J6=0,0,VLOOKUP(J6,MIE_Components!$A$2:$F$6,4,FALSE())) -> 38 | N6: =IF(OR($A6="",J6=0),0,MAX(5,J6*IF(OR($A6=Parameters!$B$13,$A6=Parameters!$B$14),0.75,1)-(IF(AND($A6=DATE(2026,11,29),NOV29BF="Yes"),K6,0)+IF(OR($A6=DATE(2026,11,29),$A6=DATE(2026,11,30),$A6=DATE(2026,12,1),$A6=DATE(2026,12,2)),L6,0)+IF(OR($A6=DATE(2026,11,28),$A6=DATE(2026,12,1)),M6,0)))) -> 43 | O6: =IF(AND($A6<>"",$A6<Parameters!$B$14),CityData!F4*(1+TAXRATE),0) -> 0 | P6: =IF($A6="",0,IFERROR(VLOOKUP((YEAR($A6)+IF(MONTH($A6)>=10,1,0))&"|Chicago|"&MONTH($A6),Rates!$A$2:$I$181,5,FALSE()),0)) -> 148 | Q6: =IF(OR($A6="",$A6>=Parameters!$B$14),1,IF(AND(P6>0,CityData!F4<=P6),1,0)) -> 1 | R6: =IF($A6="",0,IFERROR(VLOOKUP((YEAR($A6)+IF(MONTH($A6)>=10,1,0))&"|Denver|"&MONTH($A6),Rates!$A$2:$I$181,6,FALSE()),0)) -> 92 | S6: =IF(R6=0,0,VLOOKUP(R6,MIE_Components!$A$2:$F$6,2,FALSE())) -> 23 | T6: =IF(R6=0,0,VLOOKUP(R6,MIE_Components!$A$2:$F$6,3,FALSE())) -> 26 | U6: =IF(R6=0,0,VLOOKUP(R6,MIE_Components!$A$2:$F$6,4,FALSE())) -> 38 | V6: =IF(OR($A6="",R6=0),0,MAX(5,R6*IF(OR($A6=Parameters!$B$13,$A6=Parameters!$B$14),0.75,1)-(IF(AND($A6=DATE(2026,11,29),NOV29BF="Yes"),S6,0)+IF(OR($A6=DATE(2026,11,29),$A6=DATE(2026,11,30),$A6=DATE(2026,12,1),$A6=DATE(2026,12,2)),T6,0)+IF(OR($A6=DATE(2026,11,28),$A6=DATE(2026,12,1)),U6,0)))) -> 43 | W6: =IF(AND($A6<>"",$A6<Parameters!$B$14),CityData!F5*(1+TAXRATE),0) -> 0 | X6: =IF($A6="",0,IFERROR(VLOOKUP((YEAR($A6)+IF(MONTH($A6)>=10,1,0))&"|Denver|"&MONTH($A6),Rates!$A$2:$I$181,5,FALSE()),0)) -> 170 | Y6: =IF(OR($A6="",$A6>=Parameters!$B$14),1,IF(AND(X6>0,CityData!F5<=X6),1,0)) -> 1 | Z6: =IF($A6="",0,IFERROR(VLOOKUP((YEAR($A6)+IF(MONTH($A6)>=10,1,0))&"|Phoenix|"&MONTH($A6),Rates!$A$2:$I$181,6,FALSE()),0)) -> 86 | AA6: =IF(Z6=0,0,VLOOKUP(Z6,MIE_Components!$A$2:$F$6,2,FALSE())) -> 22 | AB6: =IF(Z6=0,0,VLOOKUP(Z6,MIE_Components!$A$2:$F$6,3,FALSE())) -> 23 | AC6: =IF(Z6=0,0,VLOOKUP(Z6,MIE_Components!$A$2:$F$6,4,FALSE())) -> 36 | AD6: =IF(OR($A6="",Z6=0),0,MAX(5,Z6*IF(OR($A6=Parameters!$B$13,$A6=Parameters!$B$14),0.75,1)-(IF(AND($A6=DATE(2026,11,29),NOV29BF="Yes"),AA6,0)+IF(OR($A6=DATE(2026,11,29),$A6=DATE(2026,11,30),$A6=DATE(2026,12,1),$A6=DATE(2026,12,2)),AB6,0)+IF(OR($A6=DATE(2026,11,28),$A6=DATE(2026,12,1)),AC6,0)))) -> 41.5 | AE6: =IF(AND($A6<>"",$A6<Parameters!$B$14),CityData!F6*(1+TAXRATE),0) -> 0 | AF6: =IF($A6="",0,IFERROR(VLOOKUP((YEAR($A6)+IF(MONTH($A6)>=10,1,0))&"|Phoenix|"&MONTH($A6),Rates!$A$2:$I$181,5,FALSE()),0)) -> 165 | AG6: =IF(OR($A6="",$A6>=Parameters!$B$14),1,IF(AND(AF6>0,CityData!F6<=AF6),1,0)) -> 1 | AH6: =IF($A6="",0,IFERROR(VLOOKUP((YEAR($A6)+IF(MONTH($A6)>=10,1,0))&"|Seattle|"&MONTH($A6),Rates!$A$2:$I$181,6,FALSE()),0)) -> 92 | AI6: =IF(AH6=0,0,VLOOKUP(AH6,MIE_Components!$A$2:$F$6,2,FALSE())) -> 23 | AJ6: =IF(AH6=0,0,VLOOKUP(AH6,MIE_Components!$A$2:$F$6,3,FALSE())) -> 26 | AK6: =IF(AH6=0,0,VLOOKUP(AH6,MIE_Components!$A$2:$F$6,4,FALSE())) -> 38 | AL6: =IF(OR($A6="",AH6=0),0,MAX(5,AH6*IF(OR($A6=Parameters!$B$13,$A6=Parameters!$B$14),0.75,1)-(IF(AND($A6=DATE(2026,11,29),NOV29BF="Yes"),AI6,0)+IF(OR($A6=DATE(2026,11,29),$A6=DATE(2026,11,30),$A6=DATE(2026,12,1),$A6=DATE(2026,12,2)),AJ6,0)+IF(OR($A6=DATE(2026,11,28),$A6=DATE(2026,12,1)),AK6,0)))) -> 43 | AM6: =IF(AND($A6<>"",$A6<Parameters!$B$14),CityData!F7*(1+TAXRATE),0) -> 0 | AN6: =IF($A6="",0,IFERROR(VLOOKUP((YEAR($A6)+IF(MONTH($A6)>=10,1,0))&"|Seattle|"&MONTH($A6),Rates!$A$2:$I$181,5,FALSE()),0)) -> 188 | AO6: =IF(OR($A6="",$A6>=Parameters!$B$14),1,IF(AND(AN6>0,CityData!F7<=AN6),1,0)) -> 1
A7: =IF(AND(Parameters!$B$14>=Parameters!$B$13,ROW()-2<=Parameters!$B$14-Parameters!$B$13),Parameters!$B$13+ROW()-2,"") | B7: =IF($A7="",0,IFERROR(VLOOKUP((YEAR($A7)+IF(MONTH($A7)>=10,1,0))&"|Boston|"&MONTH($A7),Rates!$A$2:$I$181,6,FALSE()),0)) -> 0 | C7: =IF(B7=0,0,VLOOKUP(B7,MIE_Components!$A$2:$F$6,2,FALSE())) -> 0 | D7: =IF(B7=0,0,VLOOKUP(B7,MIE_Components!$A$2:$F$6,3,FALSE())) -> 0 | E7: =IF(B7=0,0,VLOOKUP(B7,MIE_Components!$A$2:$F$6,4,FALSE())) -> 0 | F7: =IF(OR($A7="",B7=0),0,MAX(5,B7*IF(OR($A7=Parameters!$B$13,$A7=Parameters!$B$14),0.75,1)-(IF(AND($A7=DATE(2026,11,29),NOV29BF="Yes"),C7,0)+IF(OR($A7=DATE(2026,11,29),$A7=DATE(2026,11,30),$A7=DATE(2026,12,1),$A7=DATE(2026,12,2)),D7,0)+IF(OR($A7=DATE(2026,11,28),$A7=DATE(2026,12,1)),E7,0)))) -> 0 | G7: =IF(AND($A7<>"",$A7<Parameters!$B$14),CityData!F3*(1+TAXRATE),0) -> 0 | H7: =IF($A7="",0,IFERROR(VLOOKUP((YEAR($A7)+IF(MONTH($A7)>=10,1,0))&"|Boston|"&MONTH($A7),Rates!$A$2:$I$181,5,FALSE()),0)) -> 0 | I7: =IF(OR($A7="",$A7>=Parameters!$B$14),1,IF(AND(H7>0,CityData!F3<=H7),1,0)) -> 1 | J7: =IF($A7="",0,IFERROR(VLOOKUP((YEAR($A7)+IF(MONTH($A7)>=10,1,0))&"|Chicago|"&MONTH($A7),Rates!$A$2:$I$181,6,FALSE()),0)) -> 0 | K7: =IF(J7=0,0,VLOOKUP(J7,MIE_Components!$A$2:$F$6,2,FALSE())) -> 0 | L7: =IF(J7=0,0,VLOOKUP(J7,MIE_Components!$A$2:$F$6,3,FALSE())) -> 0 | M7: =IF(J7=0,0,VLOOKUP(J7,MIE_Components!$A$2:$F$6,4,FALSE())) -> 0 | N7: =IF(OR($A7="",J7=0),0,MAX(5,J7*IF(OR($A7=Parameters!$B$13,$A7=Parameters!$B$14),0.75,1)-(IF(AND($A7=DATE(2026,11,29),NOV29BF="Yes"),K7,0)+IF(OR($A7=DATE(2026,11,29),$A7=DATE(2026,11,30),$A7=DATE(2026,12,1),$A7=DATE(2026,12,2)),L7,0)+IF(OR($A7=DATE(2026,11,28),$A7=DATE(2026,12,1)),M7,0)))) -> 0 | O7: =IF(AND($A7<>"",$A7<Parameters!$B$14),CityData!F4*(1+TAXRATE),0) -> 0 | P7: =IF($A7="",0,IFERROR(VLOOKUP((YEAR($A7)+IF(MONTH($A7)>=10,1,0))&"|Chicago|"&MONTH($A7),Rates!$A$2:$I$181,5,FALSE()),0)) -> 0 | Q7: =IF(OR($A7="",$A7>=Parameters!$B$14),1,IF(AND(P7>0,CityData!F4<=P7),1,0)) -> 1 | R7: =IF($A7="",0,IFERROR(VLOOKUP((YEAR($A7)+IF(MONTH($A7)>=10,1,0))&"|Denver|"&MONTH($A7),Rates!$A$2:$I$181,6,FALSE()),0)) -> 0 | S7: =IF(R7=0,0,VLOOKUP(R7,MIE_Components!$A$2:$F$6,2,FALSE())) -> 0 | T7: =IF(R7=0,0,VLOOKUP(R7,MIE_Components!$A$2:$F$6,3,FALSE())) -> 0 | U7: =IF(R7=0,0,VLOOKUP(R7,MIE_Components!$A$2:$F$6,4,FALSE())) -> 0 | V7: =IF(OR($A7="",R7=0),0,MAX(5,R7*IF(OR($A7=Parameters!$B$13,$A7=Parameters!$B$14),0.75,1)-(IF(AND($A7=DATE(2026,11,29),NOV29BF="Yes"),S7,0)+IF(OR($A7=DATE(2026,11,29),$A7=DATE(2026,11,30),$A7=DATE(2026,12,1),$A7=DATE(2026,12,2)),T7,0)+IF(OR($A7=DATE(2026,11,28),$A7=DATE(2026,12,1)),U7,0)))) -> 0 | W7: =IF(AND($A7<>"",$A7<Parameters!$B$14),CityData!F5*(1+TAXRATE),0) -> 0 | X7: =IF($A7="",0,IFERROR(VLOOKUP((YEAR($A7)+IF(MONTH($A7)>=10,1,0))&"|Denver|"&MONTH($A7),Rates!$A$2:$I$181,5,FALSE()),0)) -> 0 | Y7: =IF(OR($A7="",$A7>=Parameters!$B$14),1,IF(AND(X7>0,CityData!F5<=X7),1,0)) -> 1 | Z7: =IF($A7="",0,IFERROR(VLOOKUP((YEAR($A7)+IF(MONTH($A7)>=10,1,0))&"|Phoenix|"&MONTH($A7),Rates!$A$2:$I$181,6,FALSE()),0)) -> 0 | AA7: =IF(Z7=0,0,VLOOKUP(Z7,MIE_Components!$A$2:$F$6,2,FALSE())) -> 0 | AB7: =IF(Z7=0,0,VLOOKUP(Z7,MIE_Components!$A$2:$F$6,3,FALSE())) -> 0 | AC7: =IF(Z7=0,0,VLOOKUP(Z7,MIE_Components!$A$2:$F$6,4,FALSE())) -> 0 | AD7: =IF(OR($A7="",Z7=0),0,MAX(5,Z7*IF(OR($A7=Parameters!$B$13,$A7=Parameters!$B$14),0.75,1)-(IF(AND($A7=DATE(2026,11,29),NOV29BF="Yes"),AA7,0)+IF(OR($A7=DATE(2026,11,29),$A7=DATE(2026,11,30),$A7=DATE(2026,12,1),$A7=DATE(2026,12,2)),AB7,0)+IF(OR($A7=DATE(2026,11,28),$A7=DATE(2026,12,1)),AC7,0)))) -> 0 | AE7: =IF(AND($A7<>"",$A7<Parameters!$B$14),CityData!F6*(1+TAXRATE),0) -> 0 | AF7: =IF($A7="",0,IFERROR(VLOOKUP((YEAR($A7)+IF(MONTH($A7)>=10,1,0))&"|Phoenix|"&MONTH($A7),Rates!$A$2:$I$181,5,FALSE()),0)) -> 0 | AG7: =IF(OR($A7="",$A7>=Parameters!$B$14),1,IF(AND(AF7>0,CityData!F6<=AF7),1,0)) -> 1 | AH7: =IF($A7="",0,IFERROR(VLOOKUP((YEAR($A7)+IF(MONTH($A7)>=10,1,0))&"|Seattle|"&MONTH($A7),Rates!$A$2:$I$181,6,FALSE()),0)) -> 0 | AI7: =IF(AH7=0,0,VLOOKUP(AH7,MIE_Components!$A$2:$F$6,2,FALSE())) -> 0 | AJ7: =IF(AH7=0,0,VLOOKUP(AH7,MIE_Components!$A$2:$F$6,3,FALSE())) -> 0 | AK7: =IF(AH7=0,0,VLOOKUP(AH7,MIE_Components!$A$2:$F$6,4,FALSE())) -> 0 | AL7: =IF(OR($A7="",AH7=0),0,MAX(5,AH7*IF(OR($A7=Parameters!$B$13,$A7=Parameters!$B$14),0.75,1)-(IF(AND($A7=DATE(2026,11,29),NOV29BF="Yes"),AI7,0)+IF(OR($A7=DATE(2026,11,29),$A7=DATE(2026,11,30),$A7=DATE(2026,12,1),$A7=DATE(2026,12,2)),AJ7,0)+IF(OR($A7=DATE(2026,11,28),$A7=DATE(2026,12,1)),AK7,0)))) -> 0 | AM7: =IF(AND($A7<>"",$A7<Parameters!$B$14),CityData!F7*(1+TAXRATE),0) -> 0 | AN7: =IF($A7="",0,IFERROR(VLOOKUP((YEAR($A7)+IF(MONTH($A7)>=10,1,0))&"|Seattle|"&MONTH($A7),Rates!$A$2:$I$181,5,FALSE()),0)) -> 0 | AO7: =IF(OR($A7="",$A7>=Parameters!$B$14),1,IF(AND(AN7>0,CityData!F7<=AN7),1,0)) -> 1
A8: =IF(AND(Parameters!$B$14>=Parameters!$B$13,ROW()-2<=Parameters!$B$14-Parameters!$B$13),Parameters!$B$13+ROW()-2,"") | B8: =IF($A8="",0,IFERROR(VLOOKUP((YEAR($A8)+IF(MONTH($A8)>=10,1,0))&"|Boston|"&MONTH($A8),Rates!$A$2:$I$181,6,FALSE()),0)) -> 0 | C8: =IF(B8=0,0,VLOOKUP(B8,MIE_Components!$A$2:$F$6,2,FALSE())) -> 0 | D8: =IF(B8=0,0,VLOOKUP(B8,MIE_Components!$A$2:$F$6,3,FALSE())) -> 0 | E8: =IF(B8=0,0,VLOOKUP(B8,MIE_Components!$A$2:$F$6,4,FALSE())) -> 0 | F8: =IF(OR($A8="",B8=0),0,MAX(5,B8*IF(OR($A8=Parameters!$B$13,$A8=Parameters!$B$14),0.75,1)-(IF(AND($A8=DATE(2026,11,29),NOV29BF="Yes"),C8,0)+IF(OR($A8=DATE(2026,11,29),$A8=DATE(2026,11,30),$A8=DATE(2026,12,1),$A8=DATE(2026,12,2)),D8,0)+IF(OR($A8=DATE(2026,11,28),$A8=DATE(2026,12,1)),E8,0)))) -> 0 | G8: =IF(AND($A8<>"",$A8<Parameters!$B$14),CityData!F3*(1+TAXRATE),0) -> 0 | H8: =IF($A8="",0,IFERROR(VLOOKUP((YEAR($A8)+IF(MONTH($A8)>=10,1,0))&"|Boston|"&MONTH($A8),Rates!$A$2:$I$181,5,FALSE()),0)) -> 0 | I8: =IF(OR($A8="",$A8>=Parameters!$B$14),1,IF(AND(H8>0,CityData!F3<=H8),1,0)) -> 1 | J8: =IF($A8="",0,IFERROR(VLOOKUP((YEAR($A8)+IF(MONTH($A8)>=10,1,0))&"|Chicago|"&MONTH($A8),Rates!$A$2:$I$181,6,FALSE()),0)) -> 0 | K8: =IF(J8=0,0,VLOOKUP(J8,MIE_Components!$A$2:$F$6,2,FALSE())) -> 0 | L8: =IF(J8=0,0,VLOOKUP(J8,MIE_Components!$A$2:$F$6,3,FALSE())) -> 0 | M8: =IF(J8=0,0,VLOOKUP(J8,MIE_Components!$A$2:$F$6,4,FALSE())) -> 0 | N8: =IF(OR($A8="",J8=0),0,MAX(5,J8*IF(OR($A8=Parameters!$B$13,$A8=Parameters!$B$14),0.75,1)-(IF(AND($A8=DATE(2026,11,29),NOV29BF="Yes"),K8,0)+IF(OR($A8=DATE(2026,11,29),$A8=DATE(2026,11,30),$A8=DATE(2026,12,1),$A8=DATE(2026,12,2)),L8,0)+IF(OR($A8=DATE(2026,11,28),$A8=DATE(2026,12,1)),M8,0)))) -> 0 | O8: =IF(AND($A8<>"",$A8<Parameters!$B$14),CityData!F4*(1+TAXRATE),0) -> 0 | P8: =IF($A8="",0,IFERROR(VLOOKUP((YEAR($A8)+IF(MONTH($A8)>=10,1,0))&"|Chicago|"&MONTH($A8),Rates!$A$2:$I$181,5,FALSE()),0)) -> 0 | Q8: =IF(OR($A8="",$A8>=Parameters!$B$14),1,IF(AND(P8>0,CityData!F4<=P8),1,0)) -> 1 | R8: =IF($A8="",0,IFERROR(VLOOKUP((YEAR($A8)+IF(MONTH($A8)>=10,1,0))&"|Denver|"&MONTH($A8),Rates!$A$2:$I$181,6,FALSE()),0)) -> 0 | S8: =IF(R8=0,0,VLOOKUP(R8,MIE_Components!$A$2:$F$6,2,FALSE())) -> 0 | T8: =IF(R8=0,0,VLOOKUP(R8,MIE_Components!$A$2:$F$6,3,FALSE())) -> 0 | U8: =IF(R8=0,0,VLOOKUP(R8,MIE_Components!$A$2:$F$6,4,FALSE())) -> 0 | V8: =IF(OR($A8="",R8=0),0,MAX(5,R8*IF(OR($A8=Parameters!$B$13,$A8=Parameters!$B$14),0.75,1)-(IF(AND($A8=DATE(2026,11,29),NOV29BF="Yes"),S8,0)+IF(OR($A8=DATE(2026,11,29),$A8=DATE(2026,11,30),$A8=DATE(2026,12,1),$A8=DATE(2026,12,2)),T8,0)+IF(OR($A8=DATE(2026,11,28),$A8=DATE(2026,12,1)),U8,0)))) -> 0 | W8: =IF(AND($A8<>"",$A8<Parameters!$B$14),CityData!F5*(1+TAXRATE),0) -> 0 | X8: =IF($A8="",0,IFERROR(VLOOKUP((YEAR($A8)+IF(MONTH($A8)>=10,1,0))&"|Denver|"&MONTH($A8),Rates!$A$2:$I$181,5,FALSE()),0)) -> 0 | Y8: =IF(OR($A8="",$A8>=Parameters!$B$14),1,IF(AND(X8>0,CityData!F5<=X8),1,0)) -> 1 | Z8: =IF($A8="",0,IFERROR(VLOOKUP((YEAR($A8)+IF(MONTH($A8)>=10,1,0))&"|Phoenix|"&MONTH($A8),Rates!$A$2:$I$181,6,FALSE()),0)) -> 0 | AA8: =IF(Z8=0,0,VLOOKUP(Z8,MIE_Components!$A$2:$F$6,2,FALSE())) -> 0 | AB8: =IF(Z8=0,0,VLOOKUP(Z8,MIE_Components!$A$2:$F$6,3,FALSE())) -> 0 | AC8: =IF(Z8=0,0,VLOOKUP(Z8,MIE_Components!$A$2:$F$6,4,FALSE())) -> 0 | AD8: =IF(OR($A8="",Z8=0),0,MAX(5,Z8*IF(OR($A8=Parameters!$B$13,$A8=Parameters!$B$14),0.75,1)-(IF(AND($A8=DATE(2026,11,29),NOV29BF="Yes"),AA8,0)+IF(OR($A8=DATE(2026,11,29),$A8=DATE(2026,11,30),$A8=DATE(2026,12,1),$A8=DATE(2026,12,2)),AB8,0)+IF(OR($A8=DATE(2026,11,28),$A8=DATE(2026,12,1)),AC8,0)))) -> 0 | AE8: =IF(AND($A8<>"",$A8<Parameters!$B$14),CityData!F6*(1+TAXRATE),0) -> 0 | AF8: =IF($A8="",0,IFERROR(VLOOKUP((YEAR($A8)+IF(MONTH($A8)>=10,1,0))&"|Phoenix|"&MONTH($A8),Rates!$A$2:$I$181,5,FALSE()),0)) -> 0 | AG8: =IF(OR($A8="",$A8>=Parameters!$B$14),1,IF(AND(AF8>0,CityData!F6<=AF8),1,0)) -> 1 | AH8: =IF($A8="",0,IFERROR(VLOOKUP((YEAR($A8)+IF(MONTH($A8)>=10,1,0))&"|Seattle|"&MONTH($A8),Rates!$A$2:$I$181,6,FALSE()),0)) -> 0 | AI8: =IF(AH8=0,0,VLOOKUP(AH8,MIE_Components!$A$2:$F$6,2,FALSE())) -> 0 | AJ8: =IF(AH8=0,0,VLOOKUP(AH8,MIE_Components!$A$2:$F$6,3,FALSE())) -> 0 | AK8: =IF(AH8=0,0,VLOOKUP(AH8,MIE_Components!$A$2:$F$6,4,FALSE())) -> 0 | AL8: =IF(OR($A8="",AH8=0),0,MAX(5,AH8*IF(OR($A8=Parameters!$B$13,$A8=Parameters!$B$14),0.75,1)-(IF(AND($A8=DATE(2026,11,29),NOV29BF="Yes"),AI8,0)+IF(OR($A8=DATE(2026,11,29),$A8=DATE(2026,11,30),$A8=DATE(2026,12,1),$A8=DATE(2026,12,2)),AJ8,0)+IF(OR($A8=DATE(2026,11,28),$A8=DATE(2026,12,1)),AK8,0)))) -> 0 | AM8: =IF(AND($A8<>"",$A8<Parameters!$B$14),CityData!F7*(1+TAXRATE),0) -> 0 | AN8: =IF($A8="",0,IFERROR(VLOOKUP((YEAR($A8)+IF(MONTH($A8)>=10,1,0))&"|Seattle|"&MONTH($A8),Rates!$A$2:$I$181,5,FALSE()),0)) -> 0 | AO8: =IF(OR($A8="",$A8>=Parameters!$B$14),1,IF(AND(AN8>0,CityData!F7<=AN8),1,0)) -> 1
A9: =IF(AND(Parameters!$B$14>=Parameters!$B$13,ROW()-2<=Parameters!$B$14-Parameters!$B$13),Parameters!$B$13+ROW()-2,"") | B9: =IF($A9="",0,IFERROR(VLOOKUP((YEAR($A9)+IF(MONTH($A9)>=10,1,0))&"|Boston|"&MONTH($A9),Rates!$A$2:$I$181,6,FALSE()),0)) -> 0 | C9: =IF(B9=0,0,VLOOKUP(B9,MIE_Components!$A$2:$F$6,2,FALSE())) -> 0 | D9: =IF(B9=0,0,VLOOKUP(B9,MIE_Components!$A$2:$F$6,3,FALSE())) -> 0 | E9: =IF(B9=0,0,VLOOKUP(B9,MIE_Components!$A$2:$F$6,4,FALSE())) -> 0 | F9: =IF(OR($A9="",B9=0),0,MAX(5,B9*IF(OR($A9=Parameters!$B$13,$A9=Parameters!$B$14),0.75,1)-(IF(AND($A9=DATE(2026,11,29),NOV29BF="Yes"),C9,0)+IF(OR($A9=DATE(2026,11,29),$A9=DATE(2026,11,30),$A9=DATE(2026,12,1),$A9=DATE(2026,12,2)),D9,0)+IF(OR($A9=DATE(2026,11,28),$A9=DATE(2026,12,1)),E9,0)))) -> 0 | G9: =IF(AND($A9<>"",$A9<Parameters!$B$14),CityData!F3*(1+TAXRATE),0) -> 0 | H9: =IF($A9="",0,IFERROR(VLOOKUP((YEAR($A9)+IF(MONTH($A9)>=10,1,0))&"|Boston|"&MONTH($A9),Rates!$A$2:$I$181,5,FALSE()),0)) -> 0 | I9: =IF(OR($A9="",$A9>=Parameters!$B$14),1,IF(AND(H9>0,CityData!F3<=H9),1,0)) -> 1 | J9: =IF($A9="",0,IFERROR(VLOOKUP((YEAR($A9)+IF(MONTH($A9)>=10,1,0))&"|Chicago|"&MONTH($A9),Rates!$A$2:$I$181,6,FALSE()),0)) -> 0 | K9: =IF(J9=0,0,VLOOKUP(J9,MIE_Components!$A$2:$F$6,2,FALSE())) -> 0 | L9: =IF(J9=0,0,VLOOKUP(J9,MIE_Components!$A$2:$F$6,3,FALSE())) -> 0 | M9: =IF(J9=0,0,VLOOKUP(J9,MIE_Components!$A$2:$F$6,4,FALSE())) -> 0 | N9: =IF(OR($A9="",J9=0),0,MAX(5,J9*IF(OR($A9=Parameters!$B$13,$A9=Parameters!$B$14),0.75,1)-(IF(AND($A9=DATE(2026,11,29),NOV29BF="Yes"),K9,0)+IF(OR($A9=DATE(2026,11,29),$A9=DATE(2026,11,30),$A9=DATE(2026,12,1),$A9=DATE(2026,12,2)),L9,0)+IF(OR($A9=DATE(2026,11,28),$A9=DATE(2026,12,1)),M9,0)))) -> 0 | O9: =IF(AND($A9<>"",$A9<Parameters!$B$14),CityData!F4*(1+TAXRATE),0) -> 0 | P9: =IF($A9="",0,IFERROR(VLOOKUP((YEAR($A9)+IF(MONTH($A9)>=10,1,0))&"|Chicago|"&MONTH($A9),Rates!$A$2:$I$181,5,FALSE()),0)) -> 0 | Q9: =IF(OR($A9="",$A9>=Parameters!$B$14),1,IF(AND(P9>0,CityData!F4<=P9),1,0)) -> 1 | R9: =IF($A9="",0,IFERROR(VLOOKUP((YEAR($A9)+IF(MONTH($A9)>=10,1,0))&"|Denver|"&MONTH($A9),Rates!$A$2:$I$181,6,FALSE()),0)) -> 0 | S9: =IF(R9=0,0,VLOOKUP(R9,MIE_Components!$A$2:$F$6,2,FALSE())) -> 0 | T9: =IF(R9=0,0,VLOOKUP(R9,MIE_Components!$A$2:$F$6,3,FALSE())) -> 0 | U9: =IF(R9=0,0,VLOOKUP(R9,MIE_Components!$A$2:$F$6,4,FALSE())) -> 0 | V9: =IF(OR($A9="",R9=0),0,MAX(5,R9*IF(OR($A9=Parameters!$B$13,$A9=Parameters!$B$14),0.75,1)-(IF(AND($A9=DATE(2026,11,29),NOV29BF="Yes"),S9,0)+IF(OR($A9=DATE(2026,11,29),$A9=DATE(2026,11,30),$A9=DATE(2026,12,1),$A9=DATE(2026,12,2)),T9,0)+IF(OR($A9=DATE(2026,11,28),$A9=DATE(2026,12,1)),U9,0)))) -> 0 | W9: =IF(AND($A9<>"",$A9<Parameters!$B$14),CityData!F5*(1+TAXRATE),0) -> 0 | X9: =IF($A9="",0,IFERROR(VLOOKUP((YEAR($A9)+IF(MONTH($A9)>=10,1,0))&"|Denver|"&MONTH($A9),Rates!$A$2:$I$181,5,FALSE()),0)) -> 0 | Y9: =IF(OR($A9="",$A9>=Parameters!$B$14),1,IF(AND(X9>0,CityData!F5<=X9),1,0)) -> 1 | Z9: =IF($A9="",0,IFERROR(VLOOKUP((YEAR($A9)+IF(MONTH($A9)>=10,1,0))&"|Phoenix|"&MONTH($A9),Rates!$A$2:$I$181,6,FALSE()),0)) -> 0 | AA9: =IF(Z9=0,0,VLOOKUP(Z9,MIE_Components!$A$2:$F$6,2,FALSE())) -> 0 | AB9: =IF(Z9=0,0,VLOOKUP(Z9,MIE_Components!$A$2:$F$6,3,FALSE())) -> 0 | AC9: =IF(Z9=0,0,VLOOKUP(Z9,MIE_Components!$A$2:$F$6,4,FALSE())) -> 0 | AD9: =IF(OR($A9="",Z9=0),0,MAX(5,Z9*IF(OR($A9=Parameters!$B$13,$A9=Parameters!$B$14),0.75,1)-(IF(AND($A9=DATE(2026,11,29),NOV29BF="Yes"),AA9,0)+IF(OR($A9=DATE(2026,11,29),$A9=DATE(2026,11,30),$A9=DATE(2026,12,1),$A9=DATE(2026,12,2)),AB9,0)+IF(OR($A9=DATE(2026,11,28),$A9=DATE(2026,12,1)),AC9,0)))) -> 0 | AE9: =IF(AND($A9<>"",$A9<Parameters!$B$14),CityData!F6*(1+TAXRATE),0) -> 0 | AF9: =IF($A9="",0,IFERROR(VLOOKUP((YEAR($A9)+IF(MONTH($A9)>=10,1,0))&"|Phoenix|"&MONTH($A9),Rates!$A$2:$I$181,5,FALSE()),0)) -> 0 | AG9: =IF(OR($A9="",$A9>=Parameters!$B$14),1,IF(AND(AF9>0,CityData!F6<=AF9),1,0)) -> 1 | AH9: =IF($A9="",0,IFERROR(VLOOKUP((YEAR($A9)+IF(MONTH($A9)>=10,1,0))&"|Seattle|"&MONTH($A9),Rates!$A$2:$I$181,6,FALSE()),0)) -> 0 | AI9: =IF(AH9=0,0,VLOOKUP(AH9,MIE_Components!$A$2:$F$6,2,FALSE())) -> 0 | AJ9: =IF(AH9=0,0,VLOOKUP(AH9,MIE_Components!$A$2:$F$6,3,FALSE())) -> 0 | AK9: =IF(AH9=0,0,VLOOKUP(AH9,MIE_Components!$A$2:$F$6,4,FALSE())) -> 0 | AL9: =IF(OR($A9="",AH9=0),0,MAX(5,AH9*IF(OR($A9=Parameters!$B$13,$A9=Parameters!$B$14),0.75,1)-(IF(AND($A9=DATE(2026,11,29),NOV29BF="Yes"),AI9,0)+IF(OR($A9=DATE(2026,11,29),$A9=DATE(2026,11,30),$A9=DATE(2026,12,1),$A9=DATE(2026,12,2)),AJ9,0)+IF(OR($A9=DATE(2026,11,28),$A9=DATE(2026,12,1)),AK9,0)))) -> 0 | AM9: =IF(AND($A9<>"",$A9<Parameters!$B$14),CityData!F7*(1+TAXRATE),0) -> 0 | AN9: =IF($A9="",0,IFERROR(VLOOKUP((YEAR($A9)+IF(MONTH($A9)>=10,1,0))&"|Seattle|"&MONTH($A9),Rates!$A$2:$I$181,5,FALSE()),0)) -> 0 | AO9: =IF(OR($A9="",$A9>=Parameters!$B$14),1,IF(AND(AN9>0,CityData!F7<=AN9),1,0)) -> 1
A10: =IF(AND(Parameters!$B$14>=Parameters!$B$13,ROW()-2<=Parameters!$B$14-Parameters!$B$13),Parameters!$B$13+ROW()-2,"") | B10: =IF($A10="",0,IFERROR(VLOOKUP((YEAR($A10)+IF(MONTH($A10)>=10,1,0))&"|Boston|"&MONTH($A10),Rates!$A$2:$I$181,6,FALSE()),0)) -> 0 | C10: =IF(B10=0,0,VLOOKUP(B10,MIE_Components!$A$2:$F$6,2,FALSE())) -> 0 | D10: =IF(B10=0,0,VLOOKUP(B10,MIE_Components!$A$2:$F$6,3,FALSE())) -> 0 | E10: =IF(B10=0,0,VLOOKUP(B10,MIE_Components!$A$2:$F$6,4,FALSE())) -> 0 | F10: =IF(OR($A10="",B10=0),0,MAX(5,B10*IF(OR($A10=Parameters!$B$13,$A10=Parameters!$B$14),0.75,1)-(IF(AND($A10=DATE(2026,11,29),NOV29BF="Yes"),C10,0)+IF(OR($A10=DATE(2026,11,29),$A10=DATE(2026,11,30),$A10=DATE(2026,12,1),$A10=DATE(2026,12,2)),D10,0)+IF(OR($A10=DATE(2026,11,28),$A10=DATE(2026,12,1)),E10,0)))) -> 0 | G10: =IF(AND($A10<>"",$A10<Parameters!$B$14),CityData!F3*(1+TAXRATE),0) -> 0 | H10: =IF($A10="",0,IFERROR(VLOOKUP((YEAR($A10)+IF(MONTH($A10)>=10,1,0))&"|Boston|"&MONTH($A10),Rates!$A$2:$I$181,5,FALSE()),0)) -> 0 | I10: =IF(OR($A10="",$A10>=Parameters!$B$14),1,IF(AND(H10>0,CityData!F3<=H10),1,0)) -> 1 | J10: =IF($A10="",0,IFERROR(VLOOKUP((YEAR($A10)+IF(MONTH($A10)>=10,1,0))&"|Chicago|"&MONTH($A10),Rates!$A$2:$I$181,6,FALSE()),0)) -> 0 | K10: =IF(J10=0,0,VLOOKUP(J10,MIE_Components!$A$2:$F$6,2,FALSE())) -> 0 | L10: =IF(J10=0,0,VLOOKUP(J10,MIE_Components!$A$2:$F$6,3,FALSE())) -> 0 | M10: =IF(J10=0,0,VLOOKUP(J10,MIE_Components!$A$2:$F$6,4,FALSE())) -> 0 | N10: =IF(OR($A10="",J10=0),0,MAX(5,J10*IF(OR($A10=Parameters!$B$13,$A10=Parameters!$B$14),0.75,1)-(IF(AND($A10=DATE(2026,11,29),NOV29BF="Yes"),K10,0)+IF(OR($A10=DATE(2026,11,29),$A10=DATE(2026,11,30),$A10=DATE(2026,12,1),$A10=DATE(2026,12,2)),L10,0)+IF(OR($A10=DATE(2026,11,28),$A10=DATE(2026,12,1)),M10,0)))) -> 0 | O10: =IF(AND($A10<>"",$A10<Parameters!$B$14),CityData!F4*(1+TAXRATE),0) -> 0 | P10: =IF($A10="",0,IFERROR(VLOOKUP((YEAR($A10)+IF(MONTH($A10)>=10,1,0))&"|Chicago|"&MONTH($A10),Rates!$A$2:$I$181,5,FALSE()),0)) -> 0 | Q10: =IF(OR($A10="",$A10>=Parameters!$B$14),1,IF(AND(P10>0,CityData!F4<=P10),1,0)) -> 1 | R10: =IF($A10="",0,IFERROR(VLOOKUP((YEAR($A10)+IF(MONTH($A10)>=10,1,0))&"|Denver|"&MONTH($A10),Rates!$A$2:$I$181,6,FALSE()),0)) -> 0 | S10: =IF(R10=0,0,VLOOKUP(R10,MIE_Components!$A$2:$F$6,2,FALSE())) -> 0 | T10: =IF(R10=0,0,VLOOKUP(R10,MIE_Components!$A$2:$F$6,3,FALSE())) -> 0 | U10: =IF(R10=0,0,VLOOKUP(R10,MIE_Components!$A$2:$F$6,4,FALSE())) -> 0 | V10: =IF(OR($A10="",R10=0),0,MAX(5,R10*IF(OR($A10=Parameters!$B$13,$A10=Parameters!$B$14),0.75,1)-(IF(AND($A10=DATE(2026,11,29),NOV29BF="Yes"),S10,0)+IF(OR($A10=DATE(2026,11,29),$A10=DATE(2026,11,30),$A10=DATE(2026,12,1),$A10=DATE(2026,12,2)),T10,0)+IF(OR($A10=DATE(2026,11,28),$A10=DATE(2026,12,1)),U10,0)))) -> 0 | W10: =IF(AND($A10<>"",$A10<Parameters!$B$14),CityData!F5*(1+TAXRATE),0) -> 0 | X10: =IF($A10="",0,IFERROR(VLOOKUP((YEAR($A10)+IF(MONTH($A10)>=10,1,0))&"|Denver|"&MONTH($A10),Rates!$A$2:$I$181,5,FALSE()),0)) -> 0 | Y10: =IF(OR($A10="",$A10>=Parameters!$B$14),1,IF(AND(X10>0,CityData!F5<=X10),1,0)) -> 1 | Z10: =IF($A10="",0,IFERROR(VLOOKUP((YEAR($A10)+IF(MONTH($A10)>=10,1,0))&"|Phoenix|"&MONTH($A10),Rates!$A$2:$I$181,6,FALSE()),0)) -> 0 | AA10: =IF(Z10=0,0,VLOOKUP(Z10,MIE_Components!$A$2:$F$6,2,FALSE())) -> 0 | AB10: =IF(Z10=0,0,VLOOKUP(Z10,MIE_Components!$A$2:$F$6,3,FALSE())) -> 0 | AC10: =IF(Z10=0,0,VLOOKUP(Z10,MIE_Components!$A$2:$F$6,4,FALSE())) -> 0 | AD10: =IF(OR($A10="",Z10=0),0,MAX(5,Z10*IF(OR($A10=Parameters!$B$13,$A10=Parameters!$B$14),0.75,1)-(IF(AND($A10=DATE(2026,11,29),NOV29BF="Yes"),AA10,0)+IF(OR($A10=DATE(2026,11,29),$A10=DATE(2026,11,30),$A10=DATE(2026,12,1),$A10=DATE(2026,12,2)),AB10,0)+IF(OR($A10=DATE(2026,11,28),$A10=DATE(2026,12,1)),AC10,0)))) -> 0 | AE10: =IF(AND($A10<>"",$A10<Parameters!$B$14),CityData!F6*(1+TAXRATE),0) -> 0 | AF10: =IF($A10="",0,IFERROR(VLOOKUP((YEAR($A10)+IF(MONTH($A10)>=10,1,0))&"|Phoenix|"&MONTH($A10),Rates!$A$2:$I$181,5,FALSE()),0)) -> 0 | AG10: =IF(OR($A10="",$A10>=Parameters!$B$14),1,IF(AND(AF10>0,CityData!F6<=AF10),1,0)) -> 1 | AH10: =IF($A10="",0,IFERROR(VLOOKUP((YEAR($A10)+IF(MONTH($A10)>=10,1,0))&"|Seattle|"&MONTH($A10),Rates!$A$2:$I$181,6,FALSE()),0)) -> 0 | AI10: =IF(AH10=0,0,VLOOKUP(AH10,MIE_Components!$A$2:$F$6,2,FALSE())) -> 0 | AJ10: =IF(AH10=0,0,VLOOKUP(AH10,MIE_Components!$A$2:$F$6,3,FALSE())) -> 0 | AK10: =IF(AH10=0,0,VLOOKUP(AH10,MIE_Components!$A$2:$F$6,4,FALSE())) -> 0 | AL10: =IF(OR($A10="",AH10=0),0,MAX(5,AH10*IF(OR($A10=Parameters!$B$13,$A10=Parameters!$B$14),0.75,1)-(IF(AND($A10=DATE(2026,11,29),NOV29BF="Yes"),AI10,0)+IF(OR($A10=DATE(2026,11,29),$A10=DATE(2026,11,30),$A10=DATE(2026,12,1),$A10=DATE(2026,12,2)),AJ10,0)+IF(OR($A10=DATE(2026,11,28),$A10=DATE(2026,12,1)),AK10,0)))) -> 0 | AM10: =IF(AND($A10<>"",$A10<Parameters!$B$14),CityData!F7*(1+TAXRATE),0) -> 0 | AN10: =IF($A10="",0,IFERROR(VLOOKUP((YEAR($A10)+IF(MONTH($A10)>=10,1,0))&"|Seattle|"&MONTH($A10),Rates!$A$2:$I$181,5,FALSE()),0)) -> 0 | AO10: =IF(OR($A10="",$A10>=Parameters!$B$14),1,IF(AND(AN10>0,CityData!F7<=AN10),1,0)) -> 1
A11: =IF(AND(Parameters!$B$14>=Parameters!$B$13,ROW()-2<=Parameters!$B$14-Parameters!$B$13),Parameters!$B$13+ROW()-2,"") | B11: =IF($A11="",0,IFERROR(VLOOKUP((YEAR($A11)+IF(MONTH($A11)>=10,1,0))&"|Boston|"&MONTH($A11),Rates!$A$2:$I$181,6,FALSE()),0)) -> 0 | C11: =IF(B11=0,0,VLOOKUP(B11,MIE_Components!$A$2:$F$6,2,FALSE())) -> 0 | D11: =IF(B11=0,0,VLOOKUP(B11,MIE_Components!$A$2:$F$6,3,FALSE())) -> 0 | E11: =IF(B11=0,0,VLOOKUP(B11,MIE_Components!$A$2:$F$6,4,FALSE())) -> 0 | F11: =IF(OR($A11="",B11=0),0,MAX(5,B11*IF(OR($A11=Parameters!$B$13,$A11=Parameters!$B$14),0.75,1)-(IF(AND($A11=DATE(2026,11,29),NOV29BF="Yes"),C11,0)+IF(OR($A11=DATE(2026,11,29),$A11=DATE(2026,11,30),$A11=DATE(2026,12,1),$A11=DATE(2026,12,2)),D11,0)+IF(OR($A11=DATE(2026,11,28),$A11=DATE(2026,12,1)),E11,0)))) -> 0 | G11: =IF(AND($A11<>"",$A11<Parameters!$B$14),CityData!F3*(1+TAXRATE),0) -> 0 | H11: =IF($A11="",0,IFERROR(VLOOKUP((YEAR($A11)+IF(MONTH($A11)>=10,1,0))&"|Boston|"&MONTH($A11),Rates!$A$2:$I$181,5,FALSE()),0)) -> 0 | I11: =IF(OR($A11="",$A11>=Parameters!$B$14),1,IF(AND(H11>0,CityData!F3<=H11),1,0)) -> 1 | J11: =IF($A11="",0,IFERROR(VLOOKUP((YEAR($A11)+IF(MONTH($A11)>=10,1,0))&"|Chicago|"&MONTH($A11),Rates!$A$2:$I$181,6,FALSE()),0)) -> 0 | K11: =IF(J11=0,0,VLOOKUP(J11,MIE_Components!$A$2:$F$6,2,FALSE())) -> 0 | L11: =IF(J11=0,0,VLOOKUP(J11,MIE_Components!$A$2:$F$6,3,FALSE())) -> 0 | M11: =IF(J11=0,0,VLOOKUP(J11,MIE_Components!$A$2:$F$6,4,FALSE())) -> 0 | N11: =IF(OR($A11="",J11=0),0,MAX(5,J11*IF(OR($A11=Parameters!$B$13,$A11=Parameters!$B$14),0.75,1)-(IF(AND($A11=DATE(2026,11,29),NOV29BF="Yes"),K11,0)+IF(OR($A11=DATE(2026,11,29),$A11=DATE(2026,11,30),$A11=DATE(2026,12,1),$A11=DATE(2026,12,2)),L11,0)+IF(OR($A11=DATE(2026,11,28),$A11=DATE(2026,12,1)),M11,0)))) -> 0 | O11: =IF(AND($A11<>"",$A11<Parameters!$B$14),CityData!F4*(1+TAXRATE),0) -> 0 | P11: =IF($A11="",0,IFERROR(VLOOKUP((YEAR($A11)+IF(MONTH($A11)>=10,1,0))&"|Chicago|"&MONTH($A11),Rates!$A$2:$I$181,5,FALSE()),0)) -> 0 | Q11: =IF(OR($A11="",$A11>=Parameters!$B$14),1,IF(AND(P11>0,CityData!F4<=P11),1,0)) -> 1 | R11: =IF($A11="",0,IFERROR(VLOOKUP((YEAR($A11)+IF(MONTH($A11)>=10,1,0))&"|Denver|"&MONTH($A11),Rates!$A$2:$I$181,6,FALSE()),0)) -> 0 | S11: =IF(R11=0,0,VLOOKUP(R11,MIE_Components!$A$2:$F$6,2,FALSE())) -> 0 | T11: =IF(R11=0,0,VLOOKUP(R11,MIE_Components!$A$2:$F$6,3,FALSE())) -> 0 | U11: =IF(R11=0,0,VLOOKUP(R11,MIE_Components!$A$2:$F$6,4,FALSE())) -> 0 | V11: =IF(OR($A11="",R11=0),0,MAX(5,R11*IF(OR($A11=Parameters!$B$13,$A11=Parameters!$B$14),0.75,1)-(IF(AND($A11=DATE(2026,11,29),NOV29BF="Yes"),S11,0)+IF(OR($A11=DATE(2026,11,29),$A11=DATE(2026,11,30),$A11=DATE(2026,12,1),$A11=DATE(2026,12,2)),T11,0)+IF(OR($A11=DATE(2026,11,28),$A11=DATE(2026,12,1)),U11,0)))) -> 0 | W11: =IF(AND($A11<>"",$A11<Parameters!$B$14),CityData!F5*(1+TAXRATE),0) -> 0 | X11: =IF($A11="",0,IFERROR(VLOOKUP((YEAR($A11)+IF(MONTH($A11)>=10,1,0))&"|Denver|"&MONTH($A11),Rates!$A$2:$I$181,5,FALSE()),0)) -> 0 | Y11: =IF(OR($A11="",$A11>=Parameters!$B$14),1,IF(AND(X11>0,CityData!F5<=X11),1,0)) -> 1 | Z11: =IF($A11="",0,IFERROR(VLOOKUP((YEAR($A11)+IF(MONTH($A11)>=10,1,0))&"|Phoenix|"&MONTH($A11),Rates!$A$2:$I$181,6,FALSE()),0)) -> 0 | AA11: =IF(Z11=0,0,VLOOKUP(Z11,MIE_Components!$A$2:$F$6,2,FALSE())) -> 0 | AB11: =IF(Z11=0,0,VLOOKUP(Z11,MIE_Components!$A$2:$F$6,3,FALSE())) -> 0 | AC11: =IF(Z11=0,0,VLOOKUP(Z11,MIE_Components!$A$2:$F$6,4,FALSE())) -> 0 | AD11: =IF(OR($A11="",Z11=0),0,MAX(5,Z11*IF(OR($A11=Parameters!$B$13,$A11=Parameters!$B$14),0.75,1)-(IF(AND($A11=DATE(2026,11,29),NOV29BF="Yes"),AA11,0)+IF(OR($A11=DATE(2026,11,29),$A11=DATE(2026,11,30),$A11=DATE(2026,12,1),$A11=DATE(2026,12,2)),AB11,0)+IF(OR($A11=DATE(2026,11,28),$A11=DATE(2026,12,1)),AC11,0)))) -> 0 | AE11: =IF(AND($A11<>"",$A11<Parameters!$B$14),CityData!F6*(1+TAXRATE),0) -> 0 | AF11: =IF($A11="",0,IFERROR(VLOOKUP((YEAR($A11)+IF(MONTH($A11)>=10,1,0))&"|Phoenix|"&MONTH($A11),Rates!$A$2:$I$181,5,FALSE()),0)) -> 0 | AG11: =IF(OR($A11="",$A11>=Parameters!$B$14),1,IF(AND(AF11>0,CityData!F6<=AF11),1,0)) -> 1 | AH11: =IF($A11="",0,IFERROR(VLOOKUP((YEAR($A11)+IF(MONTH($A11)>=10,1,0))&"|Seattle|"&MONTH($A11),Rates!$A$2:$I$181,6,FALSE()),0)) -> 0 | AI11: =IF(AH11=0,0,VLOOKUP(AH11,MIE_Components!$A$2:$F$6,2,FALSE())) -> 0 | AJ11: =IF(AH11=0,0,VLOOKUP(AH11,MIE_Components!$A$2:$F$6,3,FALSE())) -> 0 | AK11: =IF(AH11=0,0,VLOOKUP(AH11,MIE_Components!$A$2:$F$6,4,FALSE())) -> 0 | AL11: =IF(OR($A11="",AH11=0),0,MAX(5,AH11*IF(OR($A11=Parameters!$B$13,$A11=Parameters!$B$14),0.75,1)-(IF(AND($A11=DATE(2026,11,29),NOV29BF="Yes"),AI11,0)+IF(OR($A11=DATE(2026,11,29),$A11=DATE(2026,11,30),$A11=DATE(2026,12,1),$A11=DATE(2026,12,2)),AJ11,0)+IF(OR($A11=DATE(2026,11,28),$A11=DATE(2026,12,1)),AK11,0)))) -> 0 | AM11: =IF(AND($A11<>"",$A11<Parameters!$B$14),CityData!F7*(1+TAXRATE),0) -> 0 | AN11: =IF($A11="",0,IFERROR(VLOOKUP((YEAR($A11)+IF(MONTH($A11)>=10,1,0))&"|Seattle|"&MONTH($A11),Rates!$A$2:$I$181,5,FALSE()),0)) -> 0 | AO11: =IF(OR($A11="",$A11>=Parameters!$B$14),1,IF(AND(AN11>0,CityData!F7<=AN11),1,0)) -> 1
A12: =IF(AND(Parameters!$B$14>=Parameters!$B$13,ROW()-2<=Parameters!$B$14-Parameters!$B$13),Parameters!$B$13+ROW()-2,"") | B12: =IF($A12="",0,IFERROR(VLOOKUP((YEAR($A12)+IF(MONTH($A12)>=10,1,0))&"|Boston|"&MONTH($A12),Rates!$A$2:$I$181,6,FALSE()),0)) -> 0 | C12: =IF(B12=0,0,VLOOKUP(B12,MIE_Components!$A$2:$F$6,2,FALSE())) -> 0 | D12: =IF(B12=0,0,VLOOKUP(B12,MIE_Components!$A$2:$F$6,3,FALSE())) -> 0 | E12: =IF(B12=0,0,VLOOKUP(B12,MIE_Components!$A$2:$F$6,4,FALSE())) -> 0 | F12: =IF(OR($A12="",B12=0),0,MAX(5,B12*IF(OR($A12=Parameters!$B$13,$A12=Parameters!$B$14),0.75,1)-(IF(AND($A12=DATE(2026,11,29),NOV29BF="Yes"),C12,0)+IF(OR($A12=DATE(2026,11,29),$A12=DATE(2026,11,30),$A12=DATE(2026,12,1),$A12=DATE(2026,12,2)),D12,0)+IF(OR($A12=DATE(2026,11,28),$A12=DATE(2026,12,1)),E12,0)))) -> 0 | G12: =IF(AND($A12<>"",$A12<Parameters!$B$14),CityData!F3*(1+TAXRATE),0) -> 0 | H12: =IF($A12="",0,IFERROR(VLOOKUP((YEAR($A12)+IF(MONTH($A12)>=10,1,0))&"|Boston|"&MONTH($A12),Rates!$A$2:$I$181,5,FALSE()),0)) -> 0 | I12: =IF(OR($A12="",$A12>=Parameters!$B$14),1,IF(AND(H12>0,CityData!F3<=H12),1,0)) -> 1 | J12: =IF($A12="",0,IFERROR(VLOOKUP((YEAR($A12)+IF(MONTH($A12)>=10,1,0))&"|Chicago|"&MONTH($A12),Rates!$A$2:$I$181,6,FALSE()),0)) -> 0 | K12: =IF(J12=0,0,VLOOKUP(J12,MIE_Components!$A$2:$F$6,2,FALSE())) -> 0 | L12: =IF(J12=0,0,VLOOKUP(J12,MIE_Components!$A$2:$F$6,3,FALSE())) -> 0 | M12: =IF(J12=0,0,VLOOKUP(J12,MIE_Components!$A$2:$F$6,4,FALSE())) -> 0 | N12: =IF(OR($A12="",J12=0),0,MAX(5,J12*IF(OR($A12=Parameters!$B$13,$A12=Parameters!$B$14),0.75,1)-(IF(AND($A12=DATE(2026,11,29),NOV29BF="Yes"),K12,0)+IF(OR($A12=DATE(2026,11,29),$A12=DATE(2026,11,30),$A12=DATE(2026,12,1),$A12=DATE(2026,12,2)),L12,0)+IF(OR($A12=DATE(2026,11,28),$A12=DATE(2026,12,1)),M12,0)))) -> 0 | O12: =IF(AND($A12<>"",$A12<Parameters!$B$14),CityData!F4*(1+TAXRATE),0) -> 0 | P12: =IF($A12="",0,IFERROR(VLOOKUP((YEAR($A12)+IF(MONTH($A12)>=10,1,0))&"|Chicago|"&MONTH($A12),Rates!$A$2:$I$181,5,FALSE()),0)) -> 0 | Q12: =IF(OR($A12="",$A12>=Parameters!$B$14),1,IF(AND(P12>0,CityData!F4<=P12),1,0)) -> 1 | R12: =IF($A12="",0,IFERROR(VLOOKUP((YEAR($A12)+IF(MONTH($A12)>=10,1,0))&"|Denver|"&MONTH($A12),Rates!$A$2:$I$181,6,FALSE()),0)) -> 0 | S12: =IF(R12=0,0,VLOOKUP(R12,MIE_Components!$A$2:$F$6,2,FALSE())) -> 0 | T12: =IF(R12=0,0,VLOOKUP(R12,MIE_Components!$A$2:$F$6,3,FALSE())) -> 0 | U12: =IF(R12=0,0,VLOOKUP(R12,MIE_Components!$A$2:$F$6,4,FALSE())) -> 0 | V12: =IF(OR($A12="",R12=0),0,MAX(5,R12*IF(OR($A12=Parameters!$B$13,$A12=Parameters!$B$14),0.75,1)-(IF(AND($A12=DATE(2026,11,29),NOV29BF="Yes"),S12,0)+IF(OR($A12=DATE(2026,11,29),$A12=DATE(2026,11,30),$A12=DATE(2026,12,1),$A12=DATE(2026,12,2)),T12,0)+IF(OR($A12=DATE(2026,11,28),$A12=DATE(2026,12,1)),U12,0)))) -> 0 | W12: =IF(AND($A12<>"",$A12<Parameters!$B$14),CityData!F5*(1+TAXRATE),0) -> 0 | X12: =IF($A12="",0,IFERROR(VLOOKUP((YEAR($A12)+IF(MONTH($A12)>=10,1,0))&"|Denver|"&MONTH($A12),Rates!$A$2:$I$181,5,FALSE()),0)) -> 0 | Y12: =IF(OR($A12="",$A12>=Parameters!$B$14),1,IF(AND(X12>0,CityData!F5<=X12),1,0)) -> 1 | Z12: =IF($A12="",0,IFERROR(VLOOKUP((YEAR($A12)+IF(MONTH($A12)>=10,1,0))&"|Phoenix|"&MONTH($A12),Rates!$A$2:$I$181,6,FALSE()),0)) -> 0 | AA12: =IF(Z12=0,0,VLOOKUP(Z12,MIE_Components!$A$2:$F$6,2,FALSE())) -> 0 | AB12: =IF(Z12=0,0,VLOOKUP(Z12,MIE_Components!$A$2:$F$6,3,FALSE())) -> 0 | AC12: =IF(Z12=0,0,VLOOKUP(Z12,MIE_Components!$A$2:$F$6,4,FALSE())) -> 0 | AD12: =IF(OR($A12="",Z12=0),0,MAX(5,Z12*IF(OR($A12=Parameters!$B$13,$A12=Parameters!$B$14),0.75,1)-(IF(AND($A12=DATE(2026,11,29),NOV29BF="Yes"),AA12,0)+IF(OR($A12=DATE(2026,11,29),$A12=DATE(2026,11,30),$A12=DATE(2026,12,1),$A12=DATE(2026,12,2)),AB12,0)+IF(OR($A12=DATE(2026,11,28),$A12=DATE(2026,12,1)),AC12,0)))) -> 0 | AE12: =IF(AND($A12<>"",$A12<Parameters!$B$14),CityData!F6*(1+TAXRATE),0) -> 0 | AF12: =IF($A12="",0,IFERROR(VLOOKUP((YEAR($A12)+IF(MONTH($A12)>=10,1,0))&"|Phoenix|"&MONTH($A12),Rates!$A$2:$I$181,5,FALSE()),0)) -> 0 | AG12: =IF(OR($A12="",$A12>=Parameters!$B$14),1,IF(AND(AF12>0,CityData!F6<=AF12),1,0)) -> 1 | AH12: =IF($A12="",0,IFERROR(VLOOKUP((YEAR($A12)+IF(MONTH($A12)>=10,1,0))&"|Seattle|"&MONTH($A12),Rates!$A$2:$I$181,6,FALSE()),0)) -> 0 | AI12: =IF(AH12=0,0,VLOOKUP(AH12,MIE_Components!$A$2:$F$6,2,FALSE())) -> 0 | AJ12: =IF(AH12=0,0,VLOOKUP(AH12,MIE_Components!$A$2:$F$6,3,FALSE())) -> 0 | AK12: =IF(AH12=0,0,VLOOKUP(AH12,MIE_Components!$A$2:$F$6,4,FALSE())) -> 0 | AL12: =IF(OR($A12="",AH12=0),0,MAX(5,AH12*IF(OR($A12=Parameters!$B$13,$A12=Parameters!$B$14),0.75,1)-(IF(AND($A12=DATE(2026,11,29),NOV29BF="Yes"),AI12,0)+IF(OR($A12=DATE(2026,11,29),$A12=DATE(2026,11,30),$A12=DATE(2026,12,1),$A12=DATE(2026,12,2)),AJ12,0)+IF(OR($A12=DATE(2026,11,28),$A12=DATE(2026,12,1)),AK12,0)))) -> 0 | AM12: =IF(AND($A12<>"",$A12<Parameters!$B$14),CityData!F7*(1+TAXRATE),0) -> 0 | AN12: =IF($A12="",0,IFERROR(VLOOKUP((YEAR($A12)+IF(MONTH($A12)>=10,1,0))&"|Seattle|"&MONTH($A12),Rates!$A$2:$I$181,5,FALSE()),0)) -> 0 | AO12: =IF(OR($A12="",$A12>=Parameters!$B$14),1,IF(AND(AN12>0,CityData!F7<=AN12),1,0)) -> 1
A13: =IF(AND(Parameters!$B$14>=Parameters!$B$13,ROW()-2<=Parameters!$B$14-Parameters!$B$13),Parameters!$B$13+ROW()-2,"") | B13: =IF($A13="",0,IFERROR(VLOOKUP((YEAR($A13)+IF(MONTH($A13)>=10,1,0))&"|Boston|"&MONTH($A13),Rates!$A$2:$I$181,6,FALSE()),0)) -> 0 | C13: =IF(B13=0,0,VLOOKUP(B13,MIE_Components!$A$2:$F$6,2,FALSE())) -> 0 | D13: =IF(B13=0,0,VLOOKUP(B13,MIE_Components!$A$2:$F$6,3,FALSE())) -> 0 | E13: =IF(B13=0,0,VLOOKUP(B13,MIE_Components!$A$2:$F$6,4,FALSE())) -> 0 | F13: =IF(OR($A13="",B13=0),0,MAX(5,B13*IF(OR($A13=Parameters!$B$13,$A13=Parameters!$B$14),0.75,1)-(IF(AND($A13=DATE(2026,11,29),NOV29BF="Yes"),C13,0)+IF(OR($A13=DATE(2026,11,29),$A13=DATE(2026,11,30),$A13=DATE(2026,12,1),$A13=DATE(2026,12,2)),D13,0)+IF(OR($A13=DATE(2026,11,28),$A13=DATE(2026,12,1)),E13,0)))) -> 0 | G13: =IF(AND($A13<>"",$A13<Parameters!$B$14),CityData!F3*(1+TAXRATE),0) -> 0 | H13: =IF($A13="",0,IFERROR(VLOOKUP((YEAR($A13)+IF(MONTH($A13)>=10,1,0))&"|Boston|"&MONTH($A13),Rates!$A$2:$I$181,5,FALSE()),0)) -> 0 | I13: =IF(OR($A13="",$A13>=Parameters!$B$14),1,IF(AND(H13>0,CityData!F3<=H13),1,0)) -> 1 | J13: =IF($A13="",0,IFERROR(VLOOKUP((YEAR($A13)+IF(MONTH($A13)>=10,1,0))&"|Chicago|"&MONTH($A13),Rates!$A$2:$I$181,6,FALSE()),0)) -> 0 | K13: =IF(J13=0,0,VLOOKUP(J13,MIE_Components!$A$2:$F$6,2,FALSE())) -> 0 | L13: =IF(J13=0,0,VLOOKUP(J13,MIE_Components!$A$2:$F$6,3,FALSE())) -> 0 | M13: =IF(J13=0,0,VLOOKUP(J13,MIE_Components!$A$2:$F$6,4,FALSE())) -> 0 | N13: =IF(OR($A13="",J13=0),0,MAX(5,J13*IF(OR($A13=Parameters!$B$13,$A13=Parameters!$B$14),0.75,1)-(IF(AND($A13=DATE(2026,11,29),NOV29BF="Yes"),K13,0)+IF(OR($A13=DATE(2026,11,29),$A13=DATE(2026,11,30),$A13=DATE(2026,12,1),$A13=DATE(2026,12,2)),L13,0)+IF(OR($A13=DATE(2026,11,28),$A13=DATE(2026,12,1)),M13,0)))) -> 0 | O13: =IF(AND($A13<>"",$A13<Parameters!$B$14),CityData!F4*(1+TAXRATE),0) -> 0 | P13: =IF($A13="",0,IFERROR(VLOOKUP((YEAR($A13)+IF(MONTH($A13)>=10,1,0))&"|Chicago|"&MONTH($A13),Rates!$A$2:$I$181,5,FALSE()),0)) -> 0 | Q13: =IF(OR($A13="",$A13>=Parameters!$B$14),1,IF(AND(P13>0,CityData!F4<=P13),1,0)) -> 1 | R13: =IF($A13="",0,IFERROR(VLOOKUP((YEAR($A13)+IF(MONTH($A13)>=10,1,0))&"|Denver|"&MONTH($A13),Rates!$A$2:$I$181,6,FALSE()),0)) -> 0 | S13: =IF(R13=0,0,VLOOKUP(R13,MIE_Components!$A$2:$F$6,2,FALSE())) -> 0 | T13: =IF(R13=0,0,VLOOKUP(R13,MIE_Components!$A$2:$F$6,3,FALSE())) -> 0 | U13: =IF(R13=0,0,VLOOKUP(R13,MIE_Components!$A$2:$F$6,4,FALSE())) -> 0 | V13: =IF(OR($A13="",R13=0),0,MAX(5,R13*IF(OR($A13=Parameters!$B$13,$A13=Parameters!$B$14),0.75,1)-(IF(AND($A13=DATE(2026,11,29),NOV29BF="Yes"),S13,0)+IF(OR($A13=DATE(2026,11,29),$A13=DATE(2026,11,30),$A13=DATE(2026,12,1),$A13=DATE(2026,12,2)),T13,0)+IF(OR($A13=DATE(2026,11,28),$A13=DATE(2026,12,1)),U13,0)))) -> 0 | W13: =IF(AND($A13<>"",$A13<Parameters!$B$14),CityData!F5*(1+TAXRATE),0) -> 0 | X13: =IF($A13="",0,IFERROR(VLOOKUP((YEAR($A13)+IF(MONTH($A13)>=10,1,0))&"|Denver|"&MONTH($A13),Rates!$A$2:$I$181,5,FALSE()),0)) -> 0 | Y13: =IF(OR($A13="",$A13>=Parameters!$B$14),1,IF(AND(X13>0,CityData!F5<=X13),1,0)) -> 1 | Z13: =IF($A13="",0,IFERROR(VLOOKUP((YEAR($A13)+IF(MONTH($A13)>=10,1,0))&"|Phoenix|"&MONTH($A13),Rates!$A$2:$I$181,6,FALSE()),0)) -> 0 | AA13: =IF(Z13=0,0,VLOOKUP(Z13,MIE_Components!$A$2:$F$6,2,FALSE())) -> 0 | AB13: =IF(Z13=0,0,VLOOKUP(Z13,MIE_Components!$A$2:$F$6,3,FALSE())) -> 0 | AC13: =IF(Z13=0,0,VLOOKUP(Z13,MIE_Components!$A$2:$F$6,4,FALSE())) -> 0 | AD13: =IF(OR($A13="",Z13=0),0,MAX(5,Z13*IF(OR($A13=Parameters!$B$13,$A13=Parameters!$B$14),0.75,1)-(IF(AND($A13=DATE(2026,11,29),NOV29BF="Yes"),AA13,0)+IF(OR($A13=DATE(2026,11,29),$A13=DATE(2026,11,30),$A13=DATE(2026,12,1),$A13=DATE(2026,12,2)),AB13,0)+IF(OR($A13=DATE(2026,11,28),$A13=DATE(2026,12,1)),AC13,0)))) -> 0 | AE13: =IF(AND($A13<>"",$A13<Parameters!$B$14),CityData!F6*(1+TAXRATE),0) -> 0 | AF13: =IF($A13="",0,IFERROR(VLOOKUP((YEAR($A13)+IF(MONTH($A13)>=10,1,0))&"|Phoenix|"&MONTH($A13),Rates!$A$2:$I$181,5,FALSE()),0)) -> 0 | AG13: =IF(OR($A13="",$A13>=Parameters!$B$14),1,IF(AND(AF13>0,CityData!F6<=AF13),1,0)) -> 1 | AH13: =IF($A13="",0,IFERROR(VLOOKUP((YEAR($A13)+IF(MONTH($A13)>=10,1,0))&"|Seattle|"&MONTH($A13),Rates!$A$2:$I$181,6,FALSE()),0)) -> 0 | AI13: =IF(AH13=0,0,VLOOKUP(AH13,MIE_Components!$A$2:$F$6,2,FALSE())) -> 0 | AJ13: =IF(AH13=0,0,VLOOKUP(AH13,MIE_Components!$A$2:$F$6,3,FALSE())) -> 0 | AK13: =IF(AH13=0,0,VLOOKUP(AH13,MIE_Components!$A$2:$F$6,4,FALSE())) -> 0 | AL13: =IF(OR($A13="",AH13=0),0,MAX(5,AH13*IF(OR($A13=Parameters!$B$13,$A13=Parameters!$B$14),0.75,1)-(IF(AND($A13=DATE(2026,11,29),NOV29BF="Yes"),AI13,0)+IF(OR($A13=DATE(2026,11,29),$A13=DATE(2026,11,30),$A13=DATE(2026,12,1),$A13=DATE(2026,12,2)),AJ13,0)+IF(OR($A13=DATE(2026,11,28),$A13=DATE(2026,12,1)),AK13,0)))) -> 0 | AM13: =IF(AND($A13<>"",$A13<Parameters!$B$14),CityData!F7*(1+TAXRATE),0) -> 0 | AN13: =IF($A13="",0,IFERROR(VLOOKUP((YEAR($A13)+IF(MONTH($A13)>=10,1,0))&"|Seattle|"&MONTH($A13),Rates!$A$2:$I$181,5,FALSE()),0)) -> 0 | AO13: =IF(OR($A13="",$A13>=Parameters!$B$14),1,IF(AND(AN13>0,CityData!F7<=AN13),1,0)) -> 1
A14: =IF(AND(Parameters!$B$14>=Parameters!$B$13,ROW()-2<=Parameters!$B$14-Parameters!$B$13),Parameters!$B$13+ROW()-2,"") | B14: =IF($A14="",0,IFERROR(VLOOKUP((YEAR($A14)+IF(MONTH($A14)>=10,1,0))&"|Boston|"&MONTH($A14),Rates!$A$2:$I$181,6,FALSE()),0)) -> 0 | C14: =IF(B14=0,0,VLOOKUP(B14,MIE_Components!$A$2:$F$6,2,FALSE())) -> 0 | D14: =IF(B14=0,0,VLOOKUP(B14,MIE_Components!$A$2:$F$6,3,FALSE())) -> 0 | E14: =IF(B14=0,0,VLOOKUP(B14,MIE_Components!$A$2:$F$6,4,FALSE())) -> 0 | F14: =IF(OR($A14="",B14=0),0,MAX(5,B14*IF(OR($A14=Parameters!$B$13,$A14=Parameters!$B$14),0.75,1)-(IF(AND($A14=DATE(2026,11,29),NOV29BF="Yes"),C14,0)+IF(OR($A14=DATE(2026,11,29),$A14=DATE(2026,11,30),$A14=DATE(2026,12,1),$A14=DATE(2026,12,2)),D14,0)+IF(OR($A14=DATE(2026,11,28),$A14=DATE(2026,12,1)),E14,0)))) -> 0 | G14: =IF(AND($A14<>"",$A14<Parameters!$B$14),CityData!F3*(1+TAXRATE),0) -> 0 | H14: =IF($A14="",0,IFERROR(VLOOKUP((YEAR($A14)+IF(MONTH($A14)>=10,1,0))&"|Boston|"&MONTH($A14),Rates!$A$2:$I$181,5,FALSE()),0)) -> 0 | I14: =IF(OR($A14="",$A14>=Parameters!$B$14),1,IF(AND(H14>0,CityData!F3<=H14),1,0)) -> 1 | J14: =IF($A14="",0,IFERROR(VLOOKUP((YEAR($A14)+IF(MONTH($A14)>=10,1,0))&"|Chicago|"&MONTH($A14),Rates!$A$2:$I$181,6,FALSE()),0)) -> 0 | K14: =IF(J14=0,0,VLOOKUP(J14,MIE_Components!$A$2:$F$6,2,FALSE())) -> 0 | L14: =IF(J14=0,0,VLOOKUP(J14,MIE_Components!$A$2:$F$6,3,FALSE())) -> 0 | M14: =IF(J14=0,0,VLOOKUP(J14,MIE_Components!$A$2:$F$6,4,FALSE())) -> 0 | N14: =IF(OR($A14="",J14=0),0,MAX(5,J14*IF(OR($A14=Parameters!$B$13,$A14=Parameters!$B$14),0.75,1)-(IF(AND($A14=DATE(2026,11,29),NOV29BF="Yes"),K14,0)+IF(OR($A14=DATE(2026,11,29),$A14=DATE(2026,11,30),$A14=DATE(2026,12,1),$A14=DATE(2026,12,2)),L14,0)+IF(OR($A14=DATE(2026,11,28),$A14=DATE(2026,12,1)),M14,0)))) -> 0 | O14: =IF(AND($A14<>"",$A14<Parameters!$B$14),CityData!F4*(1+TAXRATE),0) -> 0 | P14: =IF($A14="",0,IFERROR(VLOOKUP((YEAR($A14)+IF(MONTH($A14)>=10,1,0))&"|Chicago|"&MONTH($A14),Rates!$A$2:$I$181,5,FALSE()),0)) -> 0 | Q14: =IF(OR($A14="",$A14>=Parameters!$B$14),1,IF(AND(P14>0,CityData!F4<=P14),1,0)) -> 1 | R14: =IF($A14="",0,IFERROR(VLOOKUP((YEAR($A14)+IF(MONTH($A14)>=10,1,0))&"|Denver|"&MONTH($A14),Rates!$A$2:$I$181,6,FALSE()),0)) -> 0 | S14: =IF(R14=0,0,VLOOKUP(R14,MIE_Components!$A$2:$F$6,2,FALSE())) -> 0 | T14: =IF(R14=0,0,VLOOKUP(R14,MIE_Components!$A$2:$F$6,3,FALSE())) -> 0 | U14: =IF(R14=0,0,VLOOKUP(R14,MIE_Components!$A$2:$F$6,4,FALSE())) -> 0 | V14: =IF(OR($A14="",R14=0),0,MAX(5,R14*IF(OR($A14=Parameters!$B$13,$A14=Parameters!$B$14),0.75,1)-(IF(AND($A14=DATE(2026,11,29),NOV29BF="Yes"),S14,0)+IF(OR($A14=DATE(2026,11,29),$A14=DATE(2026,11,30),$A14=DATE(2026,12,1),$A14=DATE(2026,12,2)),T14,0)+IF(OR($A14=DATE(2026,11,28),$A14=DATE(2026,12,1)),U14,0)))) -> 0 | W14: =IF(AND($A14<>"",$A14<Parameters!$B$14),CityData!F5*(1+TAXRATE),0) -> 0 | X14: =IF($A14="",0,IFERROR(VLOOKUP((YEAR($A14)+IF(MONTH($A14)>=10,1,0))&"|Denver|"&MONTH($A14),Rates!$A$2:$I$181,5,FALSE()),0)) -> 0 | Y14: =IF(OR($A14="",$A14>=Parameters!$B$14),1,IF(AND(X14>0,CityData!F5<=X14),1,0)) -> 1 | Z14: =IF($A14="",0,IFERROR(VLOOKUP((YEAR($A14)+IF(MONTH($A14)>=10,1,0))&"|Phoenix|"&MONTH($A14),Rates!$A$2:$I$181,6,FALSE()),0)) -> 0 | AA14: =IF(Z14=0,0,VLOOKUP(Z14,MIE_Components!$A$2:$F$6,2,FALSE())) -> 0 | AB14: =IF(Z14=0,0,VLOOKUP(Z14,MIE_Components!$A$2:$F$6,3,FALSE())) -> 0 | AC14: =IF(Z14=0,0,VLOOKUP(Z14,MIE_Components!$A$2:$F$6,4,FALSE())) -> 0 | AD14: =IF(OR($A14="",Z14=0),0,MAX(5,Z14*IF(OR($A14=Parameters!$B$13,$A14=Parameters!$B$14),0.75,1)-(IF(AND($A14=DATE(2026,11,29),NOV29BF="Yes"),AA14,0)+IF(OR($A14=DATE(2026,11,29),$A14=DATE(2026,11,30),$A14=DATE(2026,12,1),$A14=DATE(2026,12,2)),AB14,0)+IF(OR($A14=DATE(2026,11,28),$A14=DATE(2026,12,1)),AC14,0)))) -> 0 | AE14: =IF(AND($A14<>"",$A14<Parameters!$B$14),CityData!F6*(1+TAXRATE),0) -> 0 | AF14: =IF($A14="",0,IFERROR(VLOOKUP((YEAR($A14)+IF(MONTH($A14)>=10,1,0))&"|Phoenix|"&MONTH($A14),Rates!$A$2:$I$181,5,FALSE()),0)) -> 0 | AG14: =IF(OR($A14="",$A14>=Parameters!$B$14),1,IF(AND(AF14>0,CityData!F6<=AF14),1,0)) -> 1 | AH14: =IF($A14="",0,IFERROR(VLOOKUP((YEAR($A14)+IF(MONTH($A14)>=10,1,0))&"|Seattle|"&MONTH($A14),Rates!$A$2:$I$181,6,FALSE()),0)) -> 0 | AI14: =IF(AH14=0,0,VLOOKUP(AH14,MIE_Components!$A$2:$F$6,2,FALSE())) -> 0 | AJ14: =IF(AH14=0,0,VLOOKUP(AH14,MIE_Components!$A$2:$F$6,3,FALSE())) -> 0 | AK14: =IF(AH14=0,0,VLOOKUP(AH14,MIE_Components!$A$2:$F$6,4,FALSE())) -> 0 | AL14: =IF(OR($A14="",AH14=0),0,MAX(5,AH14*IF(OR($A14=Parameters!$B$13,$A14=Parameters!$B$14),0.75,1)-(IF(AND($A14=DATE(2026,11,29),NOV29BF="Yes"),AI14,0)+IF(OR($A14=DATE(2026,11,29),$A14=DATE(2026,11,30),$A14=DATE(2026,12,1),$A14=DATE(2026,12,2)),AJ14,0)+IF(OR($A14=DATE(2026,11,28),$A14=DATE(2026,12,1)),AK14,0)))) -> 0 | AM14: =IF(AND($A14<>"",$A14<Parameters!$B$14),CityData!F7*(1+TAXRATE),0) -> 0 | AN14: =IF($A14="",0,IFERROR(VLOOKUP((YEAR($A14)+IF(MONTH($A14)>=10,1,0))&"|Seattle|"&MONTH($A14),Rates!$A$2:$I$181,5,FALSE()),0)) -> 0 | AO14: =IF(OR($A14="",$A14>=Parameters!$B$14),1,IF(AND(AN14>0,CityData!F7<=AN14),1,0)) -> 1
A15: =IF(AND(Parameters!$B$14>=Parameters!$B$13,ROW()-2<=Parameters!$B$14-Parameters!$B$13),Parameters!$B$13+ROW()-2,"") | B15: =IF($A15="",0,IFERROR(VLOOKUP((YEAR($A15)+IF(MONTH($A15)>=10,1,0))&"|Boston|"&MONTH($A15),Rates!$A$2:$I$181,6,FALSE()),0)) -> 0 | C15: =IF(B15=0,0,VLOOKUP(B15,MIE_Components!$A$2:$F$6,2,FALSE())) -> 0 | D15: =IF(B15=0,0,VLOOKUP(B15,MIE_Components!$A$2:$F$6,3,FALSE())) -> 0 | E15: =IF(B15=0,0,VLOOKUP(B15,MIE_Components!$A$2:$F$6,4,FALSE())) -> 0 | F15: =IF(OR($A15="",B15=0),0,MAX(5,B15*IF(OR($A15=Parameters!$B$13,$A15=Parameters!$B$14),0.75,1)-(IF(AND($A15=DATE(2026,11,29),NOV29BF="Yes"),C15,0)+IF(OR($A15=DATE(2026,11,29),$A15=DATE(2026,11,30),$A15=DATE(2026,12,1),$A15=DATE(2026,12,2)),D15,0)+IF(OR($A15=DATE(2026,11,28),$A15=DATE(2026,12,1)),E15,0)))) -> 0 | G15: =IF(AND($A15<>"",$A15<Parameters!$B$14),CityData!F3*(1+TAXRATE),0) -> 0 | H15: =IF($A15="",0,IFERROR(VLOOKUP((YEAR($A15)+IF(MONTH($A15)>=10,1,0))&"|Boston|"&MONTH($A15),Rates!$A$2:$I$181,5,FALSE()),0)) -> 0 | I15: =IF(OR($A15="",$A15>=Parameters!$B$14),1,IF(AND(H15>0,CityData!F3<=H15),1,0)) -> 1 | J15: =IF($A15="",0,IFERROR(VLOOKUP((YEAR($A15)+IF(MONTH($A15)>=10,1,0))&"|Chicago|"&MONTH($A15),Rates!$A$2:$I$181,6,FALSE()),0)) -> 0 | K15: =IF(J15=0,0,VLOOKUP(J15,MIE_Components!$A$2:$F$6,2,FALSE())) -> 0 | L15: =IF(J15=0,0,VLOOKUP(J15,MIE_Components!$A$2:$F$6,3,FALSE())) -> 0 | M15: =IF(J15=0,0,VLOOKUP(J15,MIE_Components!$A$2:$F$6,4,FALSE())) -> 0 | N15: =IF(OR($A15="",J15=0),0,MAX(5,J15*IF(OR($A15=Parameters!$B$13,$A15=Parameters!$B$14),0.75,1)-(IF(AND($A15=DATE(2026,11,29),NOV29BF="Yes"),K15,0)+IF(OR($A15=DATE(2026,11,29),$A15=DATE(2026,11,30),$A15=DATE(2026,12,1),$A15=DATE(2026,12,2)),L15,0)+IF(OR($A15=DATE(2026,11,28),$A15=DATE(2026,12,1)),M15,0)))) -> 0 | O15: =IF(AND($A15<>"",$A15<Parameters!$B$14),CityData!F4*(1+TAXRATE),0) -> 0 | P15: =IF($A15="",0,IFERROR(VLOOKUP((YEAR($A15)+IF(MONTH($A15)>=10,1,0))&"|Chicago|"&MONTH($A15),Rates!$A$2:$I$181,5,FALSE()),0)) -> 0 | Q15: =IF(OR($A15="",$A15>=Parameters!$B$14),1,IF(AND(P15>0,CityData!F4<=P15),1,0)) -> 1 | R15: =IF($A15="",0,IFERROR(VLOOKUP((YEAR($A15)+IF(MONTH($A15)>=10,1,0))&"|Denver|"&MONTH($A15),Rates!$A$2:$I$181,6,FALSE()),0)) -> 0 | S15: =IF(R15=0,0,VLOOKUP(R15,MIE_Components!$A$2:$F$6,2,FALSE())) -> 0 | T15: =IF(R15=0,0,VLOOKUP(R15,MIE_Components!$A$2:$F$6,3,FALSE())) -> 0 | U15: =IF(R15=0,0,VLOOKUP(R15,MIE_Components!$A$2:$F$6,4,FALSE())) -> 0 | V15: =IF(OR($A15="",R15=0),0,MAX(5,R15*IF(OR($A15=Parameters!$B$13,$A15=Parameters!$B$14),0.75,1)-(IF(AND($A15=DATE(2026,11,29),NOV29BF="Yes"),S15,0)+IF(OR($A15=DATE(2026,11,29),$A15=DATE(2026,11,30),$A15=DATE(2026,12,1),$A15=DATE(2026,12,2)),T15,0)+IF(OR($A15=DATE(2026,11,28),$A15=DATE(2026,12,1)),U15,0)))) -> 0 | W15: =IF(AND($A15<>"",$A15<Parameters!$B$14),CityData!F5*(1+TAXRATE),0) -> 0 | X15: =IF($A15="",0,IFERROR(VLOOKUP((YEAR($A15)+IF(MONTH($A15)>=10,1,0))&"|Denver|"&MONTH($A15),Rates!$A$2:$I$181,5,FALSE()),0)) -> 0 | Y15: =IF(OR($A15="",$A15>=Parameters!$B$14),1,IF(AND(X15>0,CityData!F5<=X15),1,0)) -> 1 | Z15: =IF($A15="",0,IFERROR(VLOOKUP((YEAR($A15)+IF(MONTH($A15)>=10,1,0))&"|Phoenix|"&MONTH($A15),Rates!$A$2:$I$181,6,FALSE()),0)) -> 0 | AA15: =IF(Z15=0,0,VLOOKUP(Z15,MIE_Components!$A$2:$F$6,2,FALSE())) -> 0 | AB15: =IF(Z15=0,0,VLOOKUP(Z15,MIE_Components!$A$2:$F$6,3,FALSE())) -> 0 | AC15: =IF(Z15=0,0,VLOOKUP(Z15,MIE_Components!$A$2:$F$6,4,FALSE())) -> 0 | AD15: =IF(OR($A15="",Z15=0),0,MAX(5,Z15*IF(OR($A15=Parameters!$B$13,$A15=Parameters!$B$14),0.75,1)-(IF(AND($A15=DATE(2026,11,29),NOV29BF="Yes"),AA15,0)+IF(OR($A15=DATE(2026,11,29),$A15=DATE(2026,11,30),$A15=DATE(2026,12,1),$A15=DATE(2026,12,2)),AB15,0)+IF(OR($A15=DATE(2026,11,28),$A15=DATE(2026,12,1)),AC15,0)))) -> 0 | AE15: =IF(AND($A15<>"",$A15<Parameters!$B$14),CityData!F6*(1+TAXRATE),0) -> 0 | AF15: =IF($A15="",0,IFERROR(VLOOKUP((YEAR($A15)+IF(MONTH($A15)>=10,1,0))&"|Phoenix|"&MONTH($A15),Rates!$A$2:$I$181,5,FALSE()),0)) -> 0 | AG15: =IF(OR($A15="",$A15>=Parameters!$B$14),1,IF(AND(AF15>0,CityData!F6<=AF15),1,0)) -> 1 | AH15: =IF($A15="",0,IFERROR(VLOOKUP((YEAR($A15)+IF(MONTH($A15)>=10,1,0))&"|Seattle|"&MONTH($A15),Rates!$A$2:$I$181,6,FALSE()),0)) -> 0 | AI15: =IF(AH15=0,0,VLOOKUP(AH15,MIE_Components!$A$2:$F$6,2,FALSE())) -> 0 | AJ15: =IF(AH15=0,0,VLOOKUP(AH15,MIE_Components!$A$2:$F$6,3,FALSE())) -> 0 | AK15: =IF(AH15=0,0,VLOOKUP(AH15,MIE_Components!$A$2:$F$6,4,FALSE())) -> 0 | AL15: =IF(OR($A15="",AH15=0),0,MAX(5,AH15*IF(OR($A15=Parameters!$B$13,$A15=Parameters!$B$14),0.75,1)-(IF(AND($A15=DATE(2026,11,29),NOV29BF="Yes"),AI15,0)+IF(OR($A15=DATE(2026,11,29),$A15=DATE(2026,11,30),$A15=DATE(2026,12,1),$A15=DATE(2026,12,2)),AJ15,0)+IF(OR($A15=DATE(2026,11,28),$A15=DATE(2026,12,1)),AK15,0)))) -> 0 | AM15: =IF(AND($A15<>"",$A15<Parameters!$B$14),CityData!F7*(1+TAXRATE),0) -> 0 | AN15: =IF($A15="",0,IFERROR(VLOOKUP((YEAR($A15)+IF(MONTH($A15)>=10,1,0))&"|Seattle|"&MONTH($A15),Rates!$A$2:$I$181,5,FALSE()),0)) -> 0 | AO15: =IF(OR($A15="",$A15>=Parameters!$B$14),1,IF(AND(AN15>0,CityData!F7<=AN15),1,0)) -> 1
A16: =IF(AND(Parameters!$B$14>=Parameters!$B$13,ROW()-2<=Parameters!$B$14-Parameters!$B$13),Parameters!$B$13+ROW()-2,"") | B16: =IF($A16="",0,IFERROR(VLOOKUP((YEAR($A16)+IF(MONTH($A16)>=10,1,0))&"|Boston|"&MONTH($A16),Rates!$A$2:$I$181,6,FALSE()),0)) -> 0 | C16: =IF(B16=0,0,VLOOKUP(B16,MIE_Components!$A$2:$F$6,2,FALSE())) -> 0 | D16: =IF(B16=0,0,VLOOKUP(B16,MIE_Components!$A$2:$F$6,3,FALSE())) -> 0 | E16: =IF(B16=0,0,VLOOKUP(B16,MIE_Components!$A$2:$F$6,4,FALSE())) -> 0 | F16: =IF(OR($A16="",B16=0),0,MAX(5,B16*IF(OR($A16=Parameters!$B$13,$A16=Parameters!$B$14),0.75,1)-(IF(AND($A16=DATE(2026,11,29),NOV29BF="Yes"),C16,0)+IF(OR($A16=DATE(2026,11,29),$A16=DATE(2026,11,30),$A16=DATE(2026,12,1),$A16=DATE(2026,12,2)),D16,0)+IF(OR($A16=DATE(2026,11,28),$A16=DATE(2026,12,1)),E16,0)))) -> 0 | G16: =IF(AND($A16<>"",$A16<Parameters!$B$14),CityData!F3*(1+TAXRATE),0) -> 0 | H16: =IF($A16="",0,IFERROR(VLOOKUP((YEAR($A16)+IF(MONTH($A16)>=10,1,0))&"|Boston|"&MONTH($A16),Rates!$A$2:$I$181,5,FALSE()),0)) -> 0 | I16: =IF(OR($A16="",$A16>=Parameters!$B$14),1,IF(AND(H16>0,CityData!F3<=H16),1,0)) -> 1 | J16: =IF($A16="",0,IFERROR(VLOOKUP((YEAR($A16)+IF(MONTH($A16)>=10,1,0))&"|Chicago|"&MONTH($A16),Rates!$A$2:$I$181,6,FALSE()),0)) -> 0 | K16: =IF(J16=0,0,VLOOKUP(J16,MIE_Components!$A$2:$F$6,2,FALSE())) -> 0 | L16: =IF(J16=0,0,VLOOKUP(J16,MIE_Components!$A$2:$F$6,3,FALSE())) -> 0 | M16: =IF(J16=0,0,VLOOKUP(J16,MIE_Components!$A$2:$F$6,4,FALSE())) -> 0 | N16: =IF(OR($A16="",J16=0),0,MAX(5,J16*IF(OR($A16=Parameters!$B$13,$A16=Parameters!$B$14),0.75,1)-(IF(AND($A16=DATE(2026,11,29),NOV29BF="Yes"),K16,0)+IF(OR($A16=DATE(2026,11,29),$A16=DATE(2026,11,30),$A16=DATE(2026,12,1),$A16=DATE(2026,12,2)),L16,0)+IF(OR($A16=DATE(2026,11,28),$A16=DATE(2026,12,1)),M16,0)))) -> 0 | O16: =IF(AND($A16<>"",$A16<Parameters!$B$14),CityData!F4*(1+TAXRATE),0) -> 0 | P16: =IF($A16="",0,IFERROR(VLOOKUP((YEAR($A16)+IF(MONTH($A16)>=10,1,0))&"|Chicago|"&MONTH($A16),Rates!$A$2:$I$181,5,FALSE()),0)) -> 0 | Q16: =IF(OR($A16="",$A16>=Parameters!$B$14),1,IF(AND(P16>0,CityData!F4<=P16),1,0)) -> 1 | R16: =IF($A16="",0,IFERROR(VLOOKUP((YEAR($A16)+IF(MONTH($A16)>=10,1,0))&"|Denver|"&MONTH($A16),Rates!$A$2:$I$181,6,FALSE()),0)) -> 0 | S16: =IF(R16=0,0,VLOOKUP(R16,MIE_Components!$A$2:$F$6,2,FALSE())) -> 0 | T16: =IF(R16=0,0,VLOOKUP(R16,MIE_Components!$A$2:$F$6,3,FALSE())) -> 0 | U16: =IF(R16=0,0,VLOOKUP(R16,MIE_Components!$A$2:$F$6,4,FALSE())) -> 0 | V16: =IF(OR($A16="",R16=0),0,MAX(5,R16*IF(OR($A16=Parameters!$B$13,$A16=Parameters!$B$14),0.75,1)-(IF(AND($A16=DATE(2026,11,29),NOV29BF="Yes"),S16,0)+IF(OR($A16=DATE(2026,11,29),$A16=DATE(2026,11,30),$A16=DATE(2026,12,1),$A16=DATE(2026,12,2)),T16,0)+IF(OR($A16=DATE(2026,11,28),$A16=DATE(2026,12,1)),U16,0)))) -> 0 | W16: =IF(AND($A16<>"",$A16<Parameters!$B$14),CityData!F5*(1+TAXRATE),0) -> 0 | X16: =IF($A16="",0,IFERROR(VLOOKUP((YEAR($A16)+IF(MONTH($A16)>=10,1,0))&"|Denver|"&MONTH($A16),Rates!$A$2:$I$181,5,FALSE()),0)) -> 0 | Y16: =IF(OR($A16="",$A16>=Parameters!$B$14),1,IF(AND(X16>0,CityData!F5<=X16),1,0)) -> 1 | Z16: =IF($A16="",0,IFERROR(VLOOKUP((YEAR($A16)+IF(MONTH($A16)>=10,1,0))&"|Phoenix|"&MONTH($A16),Rates!$A$2:$I$181,6,FALSE()),0)) -> 0 | AA16: =IF(Z16=0,0,VLOOKUP(Z16,MIE_Components!$A$2:$F$6,2,FALSE())) -> 0 | AB16: =IF(Z16=0,0,VLOOKUP(Z16,MIE_Components!$A$2:$F$6,3,FALSE())) -> 0 | AC16: =IF(Z16=0,0,VLOOKUP(Z16,MIE_Components!$A$2:$F$6,4,FALSE())) -> 0 | AD16: =IF(OR($A16="",Z16=0),0,MAX(5,Z16*IF(OR($A16=Parameters!$B$13,$A16=Parameters!$B$14),0.75,1)-(IF(AND($A16=DATE(2026,11,29),NOV29BF="Yes"),AA16,0)+IF(OR($A16=DATE(2026,11,29),$A16=DATE(2026,11,30),$A16=DATE(2026,12,1),$A16=DATE(2026,12,2)),AB16,0)+IF(OR($A16=DATE(2026,11,28),$A16=DATE(2026,12,1)),AC16,0)))) -> 0 | AE16: =IF(AND($A16<>"",$A16<Parameters!$B$14),CityData!F6*(1+TAXRATE),0) -> 0 | AF16: =IF($A16="",0,IFERROR(VLOOKUP((YEAR($A16)+IF(MONTH($A16)>=10,1,0))&"|Phoenix|"&MONTH($A16),Rates!$A$2:$I$181,5,FALSE()),0)) -> 0 | AG16: =IF(OR($A16="",$A16>=Parameters!$B$14),1,IF(AND(AF16>0,CityData!F6<=AF16),1,0)) -> 1 | AH16: =IF($A16="",0,IFERROR(VLOOKUP((YEAR($A16)+IF(MONTH($A16)>=10,1,0))&"|Seattle|"&MONTH($A16),Rates!$A$2:$I$181,6,FALSE()),0)) -> 0 | AI16: =IF(AH16=0,0,VLOOKUP(AH16,MIE_Components!$A$2:$F$6,2,FALSE())) -> 0 | AJ16: =IF(AH16=0,0,VLOOKUP(AH16,MIE_Components!$A$2:$F$6,3,FALSE())) -> 0 | AK16: =IF(AH16=0,0,VLOOKUP(AH16,MIE_Components!$A$2:$F$6,4,FALSE())) -> 0 | AL16: =IF(OR($A16="",AH16=0),0,MAX(5,AH16*IF(OR($A16=Parameters!$B$13,$A16=Parameters!$B$14),0.75,1)-(IF(AND($A16=DATE(2026,11,29),NOV29BF="Yes"),AI16,0)+IF(OR($A16=DATE(2026,11,29),$A16=DATE(2026,11,30),$A16=DATE(2026,12,1),$A16=DATE(2026,12,2)),AJ16,0)+IF(OR($A16=DATE(2026,11,28),$A16=DATE(2026,12,1)),AK16,0)))) -> 0 | AM16: =IF(AND($A16<>"",$A16<Parameters!$B$14),CityData!F7*(1+TAXRATE),0) -> 0 | AN16: =IF($A16="",0,IFERROR(VLOOKUP((YEAR($A16)+IF(MONTH($A16)>=10,1,0))&"|Seattle|"&MONTH($A16),Rates!$A$2:$I$181,5,FALSE()),0)) -> 0 | AO16: =IF(OR($A16="",$A16>=Parameters!$B$14),1,IF(AND(AN16>0,CityData!F7<=AN16),1,0)) -> 1
A17: =IF(AND(Parameters!$B$14>=Parameters!$B$13,ROW()-2<=Parameters!$B$14-Parameters!$B$13),Parameters!$B$13+ROW()-2,"") | B17: =IF($A17="",0,IFERROR(VLOOKUP((YEAR($A17)+IF(MONTH($A17)>=10,1,0))&"|Boston|"&MONTH($A17),Rates!$A$2:$I$181,6,FALSE()),0)) -> 0 | C17: =IF(B17=0,0,VLOOKUP(B17,MIE_Components!$A$2:$F$6,2,FALSE())) -> 0 | D17: =IF(B17=0,0,VLOOKUP(B17,MIE_Components!$A$2:$F$6,3,FALSE())) -> 0 | E17: =IF(B17=0,0,VLOOKUP(B17,MIE_Components!$A$2:$F$6,4,FALSE())) -> 0 | F17: =IF(OR($A17="",B17=0),0,MAX(5,B17*IF(OR($A17=Parameters!$B$13,$A17=Parameters!$B$14),0.75,1)-(IF(AND($A17=DATE(2026,11,29),NOV29BF="Yes"),C17,0)+IF(OR($A17=DATE(2026,11,29),$A17=DATE(2026,11,30),$A17=DATE(2026,12,1),$A17=DATE(2026,12,2)),D17,0)+IF(OR($A17=DATE(2026,11,28),$A17=DATE(2026,12,1)),E17,0)))) -> 0 | G17: =IF(AND($A17<>"",$A17<Parameters!$B$14),CityData!F3*(1+TAXRATE),0) -> 0 | H17: =IF($A17="",0,IFERROR(VLOOKUP((YEAR($A17)+IF(MONTH($A17)>=10,1,0))&"|Boston|"&MONTH($A17),Rates!$A$2:$I$181,5,FALSE()),0)) -> 0 | I17: =IF(OR($A17="",$A17>=Parameters!$B$14),1,IF(AND(H17>0,CityData!F3<=H17),1,0)) -> 1 | J17: =IF($A17="",0,IFERROR(VLOOKUP((YEAR($A17)+IF(MONTH($A17)>=10,1,0))&"|Chicago|"&MONTH($A17),Rates!$A$2:$I$181,6,FALSE()),0)) -> 0 | K17: =IF(J17=0,0,VLOOKUP(J17,MIE_Components!$A$2:$F$6,2,FALSE())) -> 0 | L17: =IF(J17=0,0,VLOOKUP(J17,MIE_Components!$A$2:$F$6,3,FALSE())) -> 0 | M17: =IF(J17=0,0,VLOOKUP(J17,MIE_Components!$A$2:$F$6,4,FALSE())) -> 0 | N17: =IF(OR($A17="",J17=0),0,MAX(5,J17*IF(OR($A17=Parameters!$B$13,$A17=Parameters!$B$14),0.75,1)-(IF(AND($A17=DATE(2026,11,29),NOV29BF="Yes"),K17,0)+IF(OR($A17=DATE(2026,11,29),$A17=DATE(2026,11,30),$A17=DATE(2026,12,1),$A17=DATE(2026,12,2)),L17,0)+IF(OR($A17=DATE(2026,11,28),$A17=DATE(2026,12,1)),M17,0)))) -> 0 | O17: =IF(AND($A17<>"",$A17<Parameters!$B$14),CityData!F4*(1+TAXRATE),0) -> 0 | P17: =IF($A17="",0,IFERROR(VLOOKUP((YEAR($A17)+IF(MONTH($A17)>=10,1,0))&"|Chicago|"&MONTH($A17),Rates!$A$2:$I$181,5,FALSE()),0)) -> 0 | Q17: =IF(OR($A17="",$A17>=Parameters!$B$14),1,IF(AND(P17>0,CityData!F4<=P17),1,0)) -> 1 | R17: =IF($A17="",0,IFERROR(VLOOKUP((YEAR($A17)+IF(MONTH($A17)>=10,1,0))&"|Denver|"&MONTH($A17),Rates!$A$2:$I$181,6,FALSE()),0)) -> 0 | S17: =IF(R17=0,0,VLOOKUP(R17,MIE_Components!$A$2:$F$6,2,FALSE())) -> 0 | T17: =IF(R17=0,0,VLOOKUP(R17,MIE_Components!$A$2:$F$6,3,FALSE())) -> 0 | U17: =IF(R17=0,0,VLOOKUP(R17,MIE_Components!$A$2:$F$6,4,FALSE())) -> 0 | V17: =IF(OR($A17="",R17=0),0,MAX(5,R17*IF(OR($A17=Parameters!$B$13,$A17=Parameters!$B$14),0.75,1)-(IF(AND($A17=DATE(2026,11,29),NOV29BF="Yes"),S17,0)+IF(OR($A17=DATE(2026,11,29),$A17=DATE(2026,11,30),$A17=DATE(2026,12,1),$A17=DATE(2026,12,2)),T17,0)+IF(OR($A17=DATE(2026,11,28),$A17=DATE(2026,12,1)),U17,0)))) -> 0 | W17: =IF(AND($A17<>"",$A17<Parameters!$B$14),CityData!F5*(1+TAXRATE),0) -> 0 | X17: =IF($A17="",0,IFERROR(VLOOKUP((YEAR($A17)+IF(MONTH($A17)>=10,1,0))&"|Denver|"&MONTH($A17),Rates!$A$2:$I$181,5,FALSE()),0)) -> 0 | Y17: =IF(OR($A17="",$A17>=Parameters!$B$14),1,IF(AND(X17>0,CityData!F5<=X17),1,0)) -> 1 | Z17: =IF($A17="",0,IFERROR(VLOOKUP((YEAR($A17)+IF(MONTH($A17)>=10,1,0))&"|Phoenix|"&MONTH($A17),Rates!$A$2:$I$181,6,FALSE()),0)) -> 0 | AA17: =IF(Z17=0,0,VLOOKUP(Z17,MIE_Components!$A$2:$F$6,2,FALSE())) -> 0 | AB17: =IF(Z17=0,0,VLOOKUP(Z17,MIE_Components!$A$2:$F$6,3,FALSE())) -> 0 | AC17: =IF(Z17=0,0,VLOOKUP(Z17,MIE_Components!$A$2:$F$6,4,FALSE())) -> 0 | AD17: =IF(OR($A17="",Z17=0),0,MAX(5,Z17*IF(OR($A17=Parameters!$B$13,$A17=Parameters!$B$14),0.75,1)-(IF(AND($A17=DATE(2026,11,29),NOV29BF="Yes"),AA17,0)+IF(OR($A17=DATE(2026,11,29),$A17=DATE(2026,11,30),$A17=DATE(2026,12,1),$A17=DATE(2026,12,2)),AB17,0)+IF(OR($A17=DATE(2026,11,28),$A17=DATE(2026,12,1)),AC17,0)))) -> 0 | AE17: =IF(AND($A17<>"",$A17<Parameters!$B$14),CityData!F6*(1+TAXRATE),0) -> 0 | AF17: =IF($A17="",0,IFERROR(VLOOKUP((YEAR($A17)+IF(MONTH($A17)>=10,1,0))&"|Phoenix|"&MONTH($A17),Rates!$A$2:$I$181,5,FALSE()),0)) -> 0 | AG17: =IF(OR($A17="",$A17>=Parameters!$B$14),1,IF(AND(AF17>0,CityData!F6<=AF17),1,0)) -> 1 | AH17: =IF($A17="",0,IFERROR(VLOOKUP((YEAR($A17)+IF(MONTH($A17)>=10,1,0))&"|Seattle|"&MONTH($A17),Rates!$A$2:$I$181,6,FALSE()),0)) -> 0 | AI17: =IF(AH17=0,0,VLOOKUP(AH17,MIE_Components!$A$2:$F$6,2,FALSE())) -> 0 | AJ17: =IF(AH17=0,0,VLOOKUP(AH17,MIE_Components!$A$2:$F$6,3,FALSE())) -> 0 | AK17: =IF(AH17=0,0,VLOOKUP(AH17,MIE_Components!$A$2:$F$6,4,FALSE())) -> 0 | AL17: =IF(OR($A17="",AH17=0),0,MAX(5,AH17*IF(OR($A17=Parameters!$B$13,$A17=Parameters!$B$14),0.75,1)-(IF(AND($A17=DATE(2026,11,29),NOV29BF="Yes"),AI17,0)+IF(OR($A17=DATE(2026,11,29),$A17=DATE(2026,11,30),$A17=DATE(2026,12,1),$A17=DATE(2026,12,2)),AJ17,0)+IF(OR($A17=DATE(2026,11,28),$A17=DATE(2026,12,1)),AK17,0)))) -> 0 | AM17: =IF(AND($A17<>"",$A17<Parameters!$B$14),CityData!F7*(1+TAXRATE),0) -> 0 | AN17: =IF($A17="",0,IFERROR(VLOOKUP((YEAR($A17)+IF(MONTH($A17)>=10,1,0))&"|Seattle|"&MONTH($A17),Rates!$A$2:$I$181,5,FALSE()),0)) -> 0 | AO17: =IF(OR($A17="",$A17>=Parameters!$B$14),1,IF(AND(AN17>0,CityData!F7<=AN17),1,0)) -> 1
A18: =IF(AND(Parameters!$B$14>=Parameters!$B$13,ROW()-2<=Parameters!$B$14-Parameters!$B$13),Parameters!$B$13+ROW()-2,"") | B18: =IF($A18="",0,IFERROR(VLOOKUP((YEAR($A18)+IF(MONTH($A18)>=10,1,0))&"|Boston|"&MONTH($A18),Rates!$A$2:$I$181,6,FALSE()),0)) -> 0 | C18: =IF(B18=0,0,VLOOKUP(B18,MIE_Components!$A$2:$F$6,2,FALSE())) -> 0 | D18: =IF(B18=0,0,VLOOKUP(B18,MIE_Components!$A$2:$F$6,3,FALSE())) -> 0 | E18: =IF(B18=0,0,VLOOKUP(B18,MIE_Components!$A$2:$F$6,4,FALSE())) -> 0 | F18: =IF(OR($A18="",B18=0),0,MAX(5,B18*IF(OR($A18=Parameters!$B$13,$A18=Parameters!$B$14),0.75,1)-(IF(AND($A18=DATE(2026,11,29),NOV29BF="Yes"),C18,0)+IF(OR($A18=DATE(2026,11,29),$A18=DATE(2026,11,30),$A18=DATE(2026,12,1),$A18=DATE(2026,12,2)),D18,0)+IF(OR($A18=DATE(2026,11,28),$A18=DATE(2026,12,1)),E18,0)))) -> 0 | G18: =IF(AND($A18<>"",$A18<Parameters!$B$14),CityData!F3*(1+TAXRATE),0) -> 0 | H18: =IF($A18="",0,IFERROR(VLOOKUP((YEAR($A18)+IF(MONTH($A18)>=10,1,0))&"|Boston|"&MONTH($A18),Rates!$A$2:$I$181,5,FALSE()),0)) -> 0 | I18: =IF(OR($A18="",$A18>=Parameters!$B$14),1,IF(AND(H18>0,CityData!F3<=H18),1,0)) -> 1 | J18: =IF($A18="",0,IFERROR(VLOOKUP((YEAR($A18)+IF(MONTH($A18)>=10,1,0))&"|Chicago|"&MONTH($A18),Rates!$A$2:$I$181,6,FALSE()),0)) -> 0 | K18: =IF(J18=0,0,VLOOKUP(J18,MIE_Components!$A$2:$F$6,2,FALSE())) -> 0 | L18: =IF(J18=0,0,VLOOKUP(J18,MIE_Components!$A$2:$F$6,3,FALSE())) -> 0 | M18: =IF(J18=0,0,VLOOKUP(J18,MIE_Components!$A$2:$F$6,4,FALSE())) -> 0 | N18: =IF(OR($A18="",J18=0),0,MAX(5,J18*IF(OR($A18=Parameters!$B$13,$A18=Parameters!$B$14),0.75,1)-(IF(AND($A18=DATE(2026,11,29),NOV29BF="Yes"),K18,0)+IF(OR($A18=DATE(2026,11,29),$A18=DATE(2026,11,30),$A18=DATE(2026,12,1),$A18=DATE(2026,12,2)),L18,0)+IF(OR($A18=DATE(2026,11,28),$A18=DATE(2026,12,1)),M18,0)))) -> 0 | O18: =IF(AND($A18<>"",$A18<Parameters!$B$14),CityData!F4*(1+TAXRATE),0) -> 0 | P18: =IF($A18="",0,IFERROR(VLOOKUP((YEAR($A18)+IF(MONTH($A18)>=10,1,0))&"|Chicago|"&MONTH($A18),Rates!$A$2:$I$181,5,FALSE()),0)) -> 0 | Q18: =IF(OR($A18="",$A18>=Parameters!$B$14),1,IF(AND(P18>0,CityData!F4<=P18),1,0)) -> 1 | R18: =IF($A18="",0,IFERROR(VLOOKUP((YEAR($A18)+IF(MONTH($A18)>=10,1,0))&"|Denver|"&MONTH($A18),Rates!$A$2:$I$181,6,FALSE()),0)) -> 0 | S18: =IF(R18=0,0,VLOOKUP(R18,MIE_Components!$A$2:$F$6,2,FALSE())) -> 0 | T18: =IF(R18=0,0,VLOOKUP(R18,MIE_Components!$A$2:$F$6,3,FALSE())) -> 0 | U18: =IF(R18=0,0,VLOOKUP(R18,MIE_Components!$A$2:$F$6,4,FALSE())) -> 0 | V18: =IF(OR($A18="",R18=0),0,MAX(5,R18*IF(OR($A18=Parameters!$B$13,$A18=Parameters!$B$14),0.75,1)-(IF(AND($A18=DATE(2026,11,29),NOV29BF="Yes"),S18,0)+IF(OR($A18=DATE(2026,11,29),$A18=DATE(2026,11,30),$A18=DATE(2026,12,1),$A18=DATE(2026,12,2)),T18,0)+IF(OR($A18=DATE(2026,11,28),$A18=DATE(2026,12,1)),U18,0)))) -> 0 | W18: =IF(AND($A18<>"",$A18<Parameters!$B$14),CityData!F5*(1+TAXRATE),0) -> 0 | X18: =IF($A18="",0,IFERROR(VLOOKUP((YEAR($A18)+IF(MONTH($A18)>=10,1,0))&"|Denver|"&MONTH($A18),Rates!$A$2:$I$181,5,FALSE()),0)) -> 0 | Y18: =IF(OR($A18="",$A18>=Parameters!$B$14),1,IF(AND(X18>0,CityData!F5<=X18),1,0)) -> 1 | Z18: =IF($A18="",0,IFERROR(VLOOKUP((YEAR($A18)+IF(MONTH($A18)>=10,1,0))&"|Phoenix|"&MONTH($A18),Rates!$A$2:$I$181,6,FALSE()),0)) -> 0 | AA18: =IF(Z18=0,0,VLOOKUP(Z18,MIE_Components!$A$2:$F$6,2,FALSE())) -> 0 | AB18: =IF(Z18=0,0,VLOOKUP(Z18,MIE_Components!$A$2:$F$6,3,FALSE())) -> 0 | AC18: =IF(Z18=0,0,VLOOKUP(Z18,MIE_Components!$A$2:$F$6,4,FALSE())) -> 0 | AD18: =IF(OR($A18="",Z18=0),0,MAX(5,Z18*IF(OR($A18=Parameters!$B$13,$A18=Parameters!$B$14),0.75,1)-(IF(AND($A18=DATE(2026,11,29),NOV29BF="Yes"),AA18,0)+IF(OR($A18=DATE(2026,11,29),$A18=DATE(2026,11,30),$A18=DATE(2026,12,1),$A18=DATE(2026,12,2)),AB18,0)+IF(OR($A18=DATE(2026,11,28),$A18=DATE(2026,12,1)),AC18,0)))) -> 0 | AE18: =IF(AND($A18<>"",$A18<Parameters!$B$14),CityData!F6*(1+TAXRATE),0) -> 0 | AF18: =IF($A18="",0,IFERROR(VLOOKUP((YEAR($A18)+IF(MONTH($A18)>=10,1,0))&"|Phoenix|"&MONTH($A18),Rates!$A$2:$I$181,5,FALSE()),0)) -> 0 | AG18: =IF(OR($A18="",$A18>=Parameters!$B$14),1,IF(AND(AF18>0,CityData!F6<=AF18),1,0)) -> 1 | AH18: =IF($A18="",0,IFERROR(VLOOKUP((YEAR($A18)+IF(MONTH($A18)>=10,1,0))&"|Seattle|"&MONTH($A18),Rates!$A$2:$I$181,6,FALSE()),0)) -> 0 | AI18: =IF(AH18=0,0,VLOOKUP(AH18,MIE_Components!$A$2:$F$6,2,FALSE())) -> 0 | AJ18: =IF(AH18=0,0,VLOOKUP(AH18,MIE_Components!$A$2:$F$6,3,FALSE())) -> 0 | AK18: =IF(AH18=0,0,VLOOKUP(AH18,MIE_Components!$A$2:$F$6,4,FALSE())) -> 0 | AL18: =IF(OR($A18="",AH18=0),0,MAX(5,AH18*IF(OR($A18=Parameters!$B$13,$A18=Parameters!$B$14),0.75,1)-(IF(AND($A18=DATE(2026,11,29),NOV29BF="Yes"),AI18,0)+IF(OR($A18=DATE(2026,11,29),$A18=DATE(2026,11,30),$A18=DATE(2026,12,1),$A18=DATE(2026,12,2)),AJ18,0)+IF(OR($A18=DATE(2026,11,28),$A18=DATE(2026,12,1)),AK18,0)))) -> 0 | AM18: =IF(AND($A18<>"",$A18<Parameters!$B$14),CityData!F7*(1+TAXRATE),0) -> 0 | AN18: =IF($A18="",0,IFERROR(VLOOKUP((YEAR($A18)+IF(MONTH($A18)>=10,1,0))&"|Seattle|"&MONTH($A18),Rates!$A$2:$I$181,5,FALSE()),0)) -> 0 | AO18: =IF(OR($A18="",$A18>=Parameters!$B$14),1,IF(AND(AN18>0,CityData!F7<=AN18),1,0)) -> 1
A19: =IF(AND(Parameters!$B$14>=Parameters!$B$13,ROW()-2<=Parameters!$B$14-Parameters!$B$13),Parameters!$B$13+ROW()-2,"") | B19: =IF($A19="",0,IFERROR(VLOOKUP((YEAR($A19)+IF(MONTH($A19)>=10,1,0))&"|Boston|"&MONTH($A19),Rates!$A$2:$I$181,6,FALSE()),0)) -> 0 | C19: =IF(B19=0,0,VLOOKUP(B19,MIE_Components!$A$2:$F$6,2,FALSE())) -> 0 | D19: =IF(B19=0,0,VLOOKUP(B19,MIE_Components!$A$2:$F$6,3,FALSE())) -> 0 | E19: =IF(B19=0,0,VLOOKUP(B19,MIE_Components!$A$2:$F$6,4,FALSE())) -> 0 | F19: =IF(OR($A19="",B19=0),0,MAX(5,B19*IF(OR($A19=Parameters!$B$13,$A19=Parameters!$B$14),0.75,1)-(IF(AND($A19=DATE(2026,11,29),NOV29BF="Yes"),C19,0)+IF(OR($A19=DATE(2026,11,29),$A19=DATE(2026,11,30),$A19=DATE(2026,12,1),$A19=DATE(2026,12,2)),D19,0)+IF(OR($A19=DATE(2026,11,28),$A19=DATE(2026,12,1)),E19,0)))) -> 0 | G19: =IF(AND($A19<>"",$A19<Parameters!$B$14),CityData!F3*(1+TAXRATE),0) -> 0 | H19: =IF($A19="",0,IFERROR(VLOOKUP((YEAR($A19)+IF(MONTH($A19)>=10,1,0))&"|Boston|"&MONTH($A19),Rates!$A$2:$I$181,5,FALSE()),0)) -> 0 | I19: =IF(OR($A19="",$A19>=Parameters!$B$14),1,IF(AND(H19>0,CityData!F3<=H19),1,0)) -> 1 | J19: =IF($A19="",0,IFERROR(VLOOKUP((YEAR($A19)+IF(MONTH($A19)>=10,1,0))&"|Chicago|"&MONTH($A19),Rates!$A$2:$I$181,6,FALSE()),0)) -> 0 | K19: =IF(J19=0,0,VLOOKUP(J19,MIE_Components!$A$2:$F$6,2,FALSE())) -> 0 | L19: =IF(J19=0,0,VLOOKUP(J19,MIE_Components!$A$2:$F$6,3,FALSE())) -> 0 | M19: =IF(J19=0,0,VLOOKUP(J19,MIE_Components!$A$2:$F$6,4,FALSE())) -> 0 | N19: =IF(OR($A19="",J19=0),0,MAX(5,J19*IF(OR($A19=Parameters!$B$13,$A19=Parameters!$B$14),0.75,1)-(IF(AND($A19=DATE(2026,11,29),NOV29BF="Yes"),K19,0)+IF(OR($A19=DATE(2026,11,29),$A19=DATE(2026,11,30),$A19=DATE(2026,12,1),$A19=DATE(2026,12,2)),L19,0)+IF(OR($A19=DATE(2026,11,28),$A19=DATE(2026,12,1)),M19,0)))) -> 0 | O19: =IF(AND($A19<>"",$A19<Parameters!$B$14),CityData!F4*(1+TAXRATE),0) -> 0 | P19: =IF($A19="",0,IFERROR(VLOOKUP((YEAR($A19)+IF(MONTH($A19)>=10,1,0))&"|Chicago|"&MONTH($A19),Rates!$A$2:$I$181,5,FALSE()),0)) -> 0 | Q19: =IF(OR($A19="",$A19>=Parameters!$B$14),1,IF(AND(P19>0,CityData!F4<=P19),1,0)) -> 1 | R19: =IF($A19="",0,IFERROR(VLOOKUP((YEAR($A19)+IF(MONTH($A19)>=10,1,0))&"|Denver|"&MONTH($A19),Rates!$A$2:$I$181,6,FALSE()),0)) -> 0 | S19: =IF(R19=0,0,VLOOKUP(R19,MIE_Components!$A$2:$F$6,2,FALSE())) -> 0 | T19: =IF(R19=0,0,VLOOKUP(R19,MIE_Components!$A$2:$F$6,3,FALSE())) -> 0 | U19: =IF(R19=0,0,VLOOKUP(R19,MIE_Components!$A$2:$F$6,4,FALSE())) -> 0 | V19: =IF(OR($A19="",R19=0),0,MAX(5,R19*IF(OR($A19=Parameters!$B$13,$A19=Parameters!$B$14),0.75,1)-(IF(AND($A19=DATE(2026,11,29),NOV29BF="Yes"),S19,0)+IF(OR($A19=DATE(2026,11,29),$A19=DATE(2026,11,30),$A19=DATE(2026,12,1),$A19=DATE(2026,12,2)),T19,0)+IF(OR($A19=DATE(2026,11,28),$A19=DATE(2026,12,1)),U19,0)))) -> 0 | W19: =IF(AND($A19<>"",$A19<Parameters!$B$14),CityData!F5*(1+TAXRATE),0) -> 0 | X19: =IF($A19="",0,IFERROR(VLOOKUP((YEAR($A19)+IF(MONTH($A19)>=10,1,0))&"|Denver|"&MONTH($A19),Rates!$A$2:$I$181,5,FALSE()),0)) -> 0 | Y19: =IF(OR($A19="",$A19>=Parameters!$B$14),1,IF(AND(X19>0,CityData!F5<=X19),1,0)) -> 1 | Z19: =IF($A19="",0,IFERROR(VLOOKUP((YEAR($A19)+IF(MONTH($A19)>=10,1,0))&"|Phoenix|"&MONTH($A19),Rates!$A$2:$I$181,6,FALSE()),0)) -> 0 | AA19: =IF(Z19=0,0,VLOOKUP(Z19,MIE_Components!$A$2:$F$6,2,FALSE())) -> 0 | AB19: =IF(Z19=0,0,VLOOKUP(Z19,MIE_Components!$A$2:$F$6,3,FALSE())) -> 0 | AC19: =IF(Z19=0,0,VLOOKUP(Z19,MIE_Components!$A$2:$F$6,4,FALSE())) -> 0 | AD19: =IF(OR($A19="",Z19=0),0,MAX(5,Z19*IF(OR($A19=Parameters!$B$13,$A19=Parameters!$B$14),0.75,1)-(IF(AND($A19=DATE(2026,11,29),NOV29BF="Yes"),AA19,0)+IF(OR($A19=DATE(2026,11,29),$A19=DATE(2026,11,30),$A19=DATE(2026,12,1),$A19=DATE(2026,12,2)),AB19,0)+IF(OR($A19=DATE(2026,11,28),$A19=DATE(2026,12,1)),AC19,0)))) -> 0 | AE19: =IF(AND($A19<>"",$A19<Parameters!$B$14),CityData!F6*(1+TAXRATE),0) -> 0 | AF19: =IF($A19="",0,IFERROR(VLOOKUP((YEAR($A19)+IF(MONTH($A19)>=10,1,0))&"|Phoenix|"&MONTH($A19),Rates!$A$2:$I$181,5,FALSE()),0)) -> 0 | AG19: =IF(OR($A19="",$A19>=Parameters!$B$14),1,IF(AND(AF19>0,CityData!F6<=AF19),1,0)) -> 1 | AH19: =IF($A19="",0,IFERROR(VLOOKUP((YEAR($A19)+IF(MONTH($A19)>=10,1,0))&"|Seattle|"&MONTH($A19),Rates!$A$2:$I$181,6,FALSE()),0)) -> 0 | AI19: =IF(AH19=0,0,VLOOKUP(AH19,MIE_Components!$A$2:$F$6,2,FALSE())) -> 0 | AJ19: =IF(AH19=0,0,VLOOKUP(AH19,MIE_Components!$A$2:$F$6,3,FALSE())) -> 0 | AK19: =IF(AH19=0,0,VLOOKUP(AH19,MIE_Components!$A$2:$F$6,4,FALSE())) -> 0 | AL19: =IF(OR($A19="",AH19=0),0,MAX(5,AH19*IF(OR($A19=Parameters!$B$13,$A19=Parameters!$B$14),0.75,1)-(IF(AND($A19=DATE(2026,11,29),NOV29BF="Yes"),AI19,0)+IF(OR($A19=DATE(2026,11,29),$A19=DATE(2026,11,30),$A19=DATE(2026,12,1),$A19=DATE(2026,12,2)),AJ19,0)+IF(OR($A19=DATE(2026,11,28),$A19=DATE(2026,12,1)),AK19,0)))) -> 0 | AM19: =IF(AND($A19<>"",$A19<Parameters!$B$14),CityData!F7*(1+TAXRATE),0) -> 0 | AN19: =IF($A19="",0,IFERROR(VLOOKUP((YEAR($A19)+IF(MONTH($A19)>=10,1,0))&"|Seattle|"&MONTH($A19),Rates!$A$2:$I$181,5,FALSE()),0)) -> 0 | AO19: =IF(OR($A19="",$A19>=Parameters!$B$14),1,IF(AND(AN19>0,CityData!F7<=AN19),1,0)) -> 1
A20: =IF(AND(Parameters!$B$14>=Parameters!$B$13,ROW()-2<=Parameters!$B$14-Parameters!$B$13),Parameters!$B$13+ROW()-2,"") | B20: =IF($A20="",0,IFERROR(VLOOKUP((YEAR($A20)+IF(MONTH($A20)>=10,1,0))&"|Boston|"&MONTH($A20),Rates!$A$2:$I$181,6,FALSE()),0)) -> 0 | C20: =IF(B20=0,0,VLOOKUP(B20,MIE_Components!$A$2:$F$6,2,FALSE())) -> 0 | D20: =IF(B20=0,0,VLOOKUP(B20,MIE_Components!$A$2:$F$6,3,FALSE())) -> 0 | E20: =IF(B20=0,0,VLOOKUP(B20,MIE_Components!$A$2:$F$6,4,FALSE())) -> 0 | F20: =IF(OR($A20="",B20=0),0,MAX(5,B20*IF(OR($A20=Parameters!$B$13,$A20=Parameters!$B$14),0.75,1)-(IF(AND($A20=DATE(2026,11,29),NOV29BF="Yes"),C20,0)+IF(OR($A20=DATE(2026,11,29),$A20=DATE(2026,11,30),$A20=DATE(2026,12,1),$A20=DATE(2026,12,2)),D20,0)+IF(OR($A20=DATE(2026,11,28),$A20=DATE(2026,12,1)),E20,0)))) -> 0 | G20: =IF(AND($A20<>"",$A20<Parameters!$B$14),CityData!F3*(1+TAXRATE),0) -> 0 | H20: =IF($A20="",0,IFERROR(VLOOKUP((YEAR($A20)+IF(MONTH($A20)>=10,1,0))&"|Boston|"&MONTH($A20),Rates!$A$2:$I$181,5,FALSE()),0)) -> 0 | I20: =IF(OR($A20="",$A20>=Parameters!$B$14),1,IF(AND(H20>0,CityData!F3<=H20),1,0)) -> 1 | J20: =IF($A20="",0,IFERROR(VLOOKUP((YEAR($A20)+IF(MONTH($A20)>=10,1,0))&"|Chicago|"&MONTH($A20),Rates!$A$2:$I$181,6,FALSE()),0)) -> 0 | K20: =IF(J20=0,0,VLOOKUP(J20,MIE_Components!$A$2:$F$6,2,FALSE())) -> 0 | L20: =IF(J20=0,0,VLOOKUP(J20,MIE_Components!$A$2:$F$6,3,FALSE())) -> 0 | M20: =IF(J20=0,0,VLOOKUP(J20,MIE_Components!$A$2:$F$6,4,FALSE())) -> 0 | N20: =IF(OR($A20="",J20=0),0,MAX(5,J20*IF(OR($A20=Parameters!$B$13,$A20=Parameters!$B$14),0.75,1)-(IF(AND($A20=DATE(2026,11,29),NOV29BF="Yes"),K20,0)+IF(OR($A20=DATE(2026,11,29),$A20=DATE(2026,11,30),$A20=DATE(2026,12,1),$A20=DATE(2026,12,2)),L20,0)+IF(OR($A20=DATE(2026,11,28),$A20=DATE(2026,12,1)),M20,0)))) -> 0 | O20: =IF(AND($A20<>"",$A20<Parameters!$B$14),CityData!F4*(1+TAXRATE),0) -> 0 | P20: =IF($A20="",0,IFERROR(VLOOKUP((YEAR($A20)+IF(MONTH($A20)>=10,1,0))&"|Chicago|"&MONTH($A20),Rates!$A$2:$I$181,5,FALSE()),0)) -> 0 | Q20: =IF(OR($A20="",$A20>=Parameters!$B$14),1,IF(AND(P20>0,CityData!F4<=P20),1,0)) -> 1 | R20: =IF($A20="",0,IFERROR(VLOOKUP((YEAR($A20)+IF(MONTH($A20)>=10,1,0))&"|Denver|"&MONTH($A20),Rates!$A$2:$I$181,6,FALSE()),0)) -> 0 | S20: =IF(R20=0,0,VLOOKUP(R20,MIE_Components!$A$2:$F$6,2,FALSE())) -> 0 | T20: =IF(R20=0,0,VLOOKUP(R20,MIE_Components!$A$2:$F$6,3,FALSE())) -> 0 | U20: =IF(R20=0,0,VLOOKUP(R20,MIE_Components!$A$2:$F$6,4,FALSE())) -> 0 | V20: =IF(OR($A20="",R20=0),0,MAX(5,R20*IF(OR($A20=Parameters!$B$13,$A20=Parameters!$B$14),0.75,1)-(IF(AND($A20=DATE(2026,11,29),NOV29BF="Yes"),S20,0)+IF(OR($A20=DATE(2026,11,29),$A20=DATE(2026,11,30),$A20=DATE(2026,12,1),$A20=DATE(2026,12,2)),T20,0)+IF(OR($A20=DATE(2026,11,28),$A20=DATE(2026,12,1)),U20,0)))) -> 0 | W20: =IF(AND($A20<>"",$A20<Parameters!$B$14),CityData!F5*(1+TAXRATE),0) -> 0 | X20: =IF($A20="",0,IFERROR(VLOOKUP((YEAR($A20)+IF(MONTH($A20)>=10,1,0))&"|Denver|"&MONTH($A20),Rates!$A$2:$I$181,5,FALSE()),0)) -> 0 | Y20: =IF(OR($A20="",$A20>=Parameters!$B$14),1,IF(AND(X20>0,CityData!F5<=X20),1,0)) -> 1 | Z20: =IF($A20="",0,IFERROR(VLOOKUP((YEAR($A20)+IF(MONTH($A20)>=10,1,0))&"|Phoenix|"&MONTH($A20),Rates!$A$2:$I$181,6,FALSE()),0)) -> 0 | AA20: =IF(Z20=0,0,VLOOKUP(Z20,MIE_Components!$A$2:$F$6,2,FALSE())) -> 0 | AB20: =IF(Z20=0,0,VLOOKUP(Z20,MIE_Components!$A$2:$F$6,3,FALSE())) -> 0 | AC20: =IF(Z20=0,0,VLOOKUP(Z20,MIE_Components!$A$2:$F$6,4,FALSE())) -> 0 | AD20: =IF(OR($A20="",Z20=0),0,MAX(5,Z20*IF(OR($A20=Parameters!$B$13,$A20=Parameters!$B$14),0.75,1)-(IF(AND($A20=DATE(2026,11,29),NOV29BF="Yes"),AA20,0)+IF(OR($A20=DATE(2026,11,29),$A20=DATE(2026,11,30),$A20=DATE(2026,12,1),$A20=DATE(2026,12,2)),AB20,0)+IF(OR($A20=DATE(2026,11,28),$A20=DATE(2026,12,1)),AC20,0)))) -> 0 | AE20: =IF(AND($A20<>"",$A20<Parameters!$B$14),CityData!F6*(1+TAXRATE),0) -> 0 | AF20: =IF($A20="",0,IFERROR(VLOOKUP((YEAR($A20)+IF(MONTH($A20)>=10,1,0))&"|Phoenix|"&MONTH($A20),Rates!$A$2:$I$181,5,FALSE()),0)) -> 0 | AG20: =IF(OR($A20="",$A20>=Parameters!$B$14),1,IF(AND(AF20>0,CityData!F6<=AF20),1,0)) -> 1 | AH20: =IF($A20="",0,IFERROR(VLOOKUP((YEAR($A20)+IF(MONTH($A20)>=10,1,0))&"|Seattle|"&MONTH($A20),Rates!$A$2:$I$181,6,FALSE()),0)) -> 0 | AI20: =IF(AH20=0,0,VLOOKUP(AH20,MIE_Components!$A$2:$F$6,2,FALSE())) -> 0 | AJ20: =IF(AH20=0,0,VLOOKUP(AH20,MIE_Components!$A$2:$F$6,3,FALSE())) -> 0 | AK20: =IF(AH20=0,0,VLOOKUP(AH20,MIE_Components!$A$2:$F$6,4,FALSE())) -> 0 | AL20: =IF(OR($A20="",AH20=0),0,MAX(5,AH20*IF(OR($A20=Parameters!$B$13,$A20=Parameters!$B$14),0.75,1)-(IF(AND($A20=DATE(2026,11,29),NOV29BF="Yes"),AI20,0)+IF(OR($A20=DATE(2026,11,29),$A20=DATE(2026,11,30),$A20=DATE(2026,12,1),$A20=DATE(2026,12,2)),AJ20,0)+IF(OR($A20=DATE(2026,11,28),$A20=DATE(2026,12,1)),AK20,0)))) -> 0 | AM20: =IF(AND($A20<>"",$A20<Parameters!$B$14),CityData!F7*(1+TAXRATE),0) -> 0 | AN20: =IF($A20="",0,IFERROR(VLOOKUP((YEAR($A20)+IF(MONTH($A20)>=10,1,0))&"|Seattle|"&MONTH($A20),Rates!$A$2:$I$181,5,FALSE()),0)) -> 0 | AO20: =IF(OR($A20="",$A20>=Parameters!$B$14),1,IF(AND(AN20>0,CityData!F7<=AN20),1,0)) -> 1
A21: =IF(AND(Parameters!$B$14>=Parameters!$B$13,ROW()-2<=Parameters!$B$14-Parameters!$B$13),Parameters!$B$13+ROW()-2,"") | B21: =IF($A21="",0,IFERROR(VLOOKUP((YEAR($A21)+IF(MONTH($A21)>=10,1,0))&"|Boston|"&MONTH($A21),Rates!$A$2:$I$181,6,FALSE()),0)) -> 0 | C21: =IF(B21=0,0,VLOOKUP(B21,MIE_Components!$A$2:$F$6,2,FALSE())) -> 0 | D21: =IF(B21=0,0,VLOOKUP(B21,MIE_Components!$A$2:$F$6,3,FALSE())) -> 0 | E21: =IF(B21=0,0,VLOOKUP(B21,MIE_Components!$A$2:$F$6,4,FALSE())) -> 0 | F21: =IF(OR($A21="",B21=0),0,MAX(5,B21*IF(OR($A21=Parameters!$B$13,$A21=Parameters!$B$14),0.75,1)-(IF(AND($A21=DATE(2026,11,29),NOV29BF="Yes"),C21,0)+IF(OR($A21=DATE(2026,11,29),$A21=DATE(2026,11,30),$A21=DATE(2026,12,1),$A21=DATE(2026,12,2)),D21,0)+IF(OR($A21=DATE(2026,11,28),$A21=DATE(2026,12,1)),E21,0)))) -> 0 | G21: =IF(AND($A21<>"",$A21<Parameters!$B$14),CityData!F3*(1+TAXRATE),0) -> 0 | H21: =IF($A21="",0,IFERROR(VLOOKUP((YEAR($A21)+IF(MONTH($A21)>=10,1,0))&"|Boston|"&MONTH($A21),Rates!$A$2:$I$181,5,FALSE()),0)) -> 0 | I21: =IF(OR($A21="",$A21>=Parameters!$B$14),1,IF(AND(H21>0,CityData!F3<=H21),1,0)) -> 1 | J21: =IF($A21="",0,IFERROR(VLOOKUP((YEAR($A21)+IF(MONTH($A21)>=10,1,0))&"|Chicago|"&MONTH($A21),Rates!$A$2:$I$181,6,FALSE()),0)) -> 0 | K21: =IF(J21=0,0,VLOOKUP(J21,MIE_Components!$A$2:$F$6,2,FALSE())) -> 0 | L21: =IF(J21=0,0,VLOOKUP(J21,MIE_Components!$A$2:$F$6,3,FALSE())) -> 0 | M21: =IF(J21=0,0,VLOOKUP(J21,MIE_Components!$A$2:$F$6,4,FALSE())) -> 0 | N21: =IF(OR($A21="",J21=0),0,MAX(5,J21*IF(OR($A21=Parameters!$B$13,$A21=Parameters!$B$14),0.75,1)-(IF(AND($A21=DATE(2026,11,29),NOV29BF="Yes"),K21,0)+IF(OR($A21=DATE(2026,11,29),$A21=DATE(2026,11,30),$A21=DATE(2026,12,1),$A21=DATE(2026,12,2)),L21,0)+IF(OR($A21=DATE(2026,11,28),$A21=DATE(2026,12,1)),M21,0)))) -> 0 | O21: =IF(AND($A21<>"",$A21<Parameters!$B$14),CityData!F4*(1+TAXRATE),0) -> 0 | P21: =IF($A21="",0,IFERROR(VLOOKUP((YEAR($A21)+IF(MONTH($A21)>=10,1,0))&"|Chicago|"&MONTH($A21),Rates!$A$2:$I$181,5,FALSE()),0)) -> 0 | Q21: =IF(OR($A21="",$A21>=Parameters!$B$14),1,IF(AND(P21>0,CityData!F4<=P21),1,0)) -> 1 | R21: =IF($A21="",0,IFERROR(VLOOKUP((YEAR($A21)+IF(MONTH($A21)>=10,1,0))&"|Denver|"&MONTH($A21),Rates!$A$2:$I$181,6,FALSE()),0)) -> 0 | S21: =IF(R21=0,0,VLOOKUP(R21,MIE_Components!$A$2:$F$6,2,FALSE())) -> 0 | T21: =IF(R21=0,0,VLOOKUP(R21,MIE_Components!$A$2:$F$6,3,FALSE())) -> 0 | U21: =IF(R21=0,0,VLOOKUP(R21,MIE_Components!$A$2:$F$6,4,FALSE())) -> 0 | V21: =IF(OR($A21="",R21=0),0,MAX(5,R21*IF(OR($A21=Parameters!$B$13,$A21=Parameters!$B$14),0.75,1)-(IF(AND($A21=DATE(2026,11,29),NOV29BF="Yes"),S21,0)+IF(OR($A21=DATE(2026,11,29),$A21=DATE(2026,11,30),$A21=DATE(2026,12,1),$A21=DATE(2026,12,2)),T21,0)+IF(OR($A21=DATE(2026,11,28),$A21=DATE(2026,12,1)),U21,0)))) -> 0 | W21: =IF(AND($A21<>"",$A21<Parameters!$B$14),CityData!F5*(1+TAXRATE),0) -> 0 | X21: =IF($A21="",0,IFERROR(VLOOKUP((YEAR($A21)+IF(MONTH($A21)>=10,1,0))&"|Denver|"&MONTH($A21),Rates!$A$2:$I$181,5,FALSE()),0)) -> 0 | Y21: =IF(OR($A21="",$A21>=Parameters!$B$14),1,IF(AND(X21>0,CityData!F5<=X21),1,0)) -> 1 | Z21: =IF($A21="",0,IFERROR(VLOOKUP((YEAR($A21)+IF(MONTH($A21)>=10,1,0))&"|Phoenix|"&MONTH($A21),Rates!$A$2:$I$181,6,FALSE()),0)) -> 0 | AA21: =IF(Z21=0,0,VLOOKUP(Z21,MIE_Components!$A$2:$F$6,2,FALSE())) -> 0 | AB21: =IF(Z21=0,0,VLOOKUP(Z21,MIE_Components!$A$2:$F$6,3,FALSE())) -> 0 | AC21: =IF(Z21=0,0,VLOOKUP(Z21,MIE_Components!$A$2:$F$6,4,FALSE())) -> 0 | AD21: =IF(OR($A21="",Z21=0),0,MAX(5,Z21*IF(OR($A21=Parameters!$B$13,$A21=Parameters!$B$14),0.75,1)-(IF(AND($A21=DATE(2026,11,29),NOV29BF="Yes"),AA21,0)+IF(OR($A21=DATE(2026,11,29),$A21=DATE(2026,11,30),$A21=DATE(2026,12,1),$A21=DATE(2026,12,2)),AB21,0)+IF(OR($A21=DATE(2026,11,28),$A21=DATE(2026,12,1)),AC21,0)))) -> 0 | AE21: =IF(AND($A21<>"",$A21<Parameters!$B$14),CityData!F6*(1+TAXRATE),0) -> 0 | AF21: =IF($A21="",0,IFERROR(VLOOKUP((YEAR($A21)+IF(MONTH($A21)>=10,1,0))&"|Phoenix|"&MONTH($A21),Rates!$A$2:$I$181,5,FALSE()),0)) -> 0 | AG21: =IF(OR($A21="",$A21>=Parameters!$B$14),1,IF(AND(AF21>0,CityData!F6<=AF21),1,0)) -> 1 | AH21: =IF($A21="",0,IFERROR(VLOOKUP((YEAR($A21)+IF(MONTH($A21)>=10,1,0))&"|Seattle|"&MONTH($A21),Rates!$A$2:$I$181,6,FALSE()),0)) -> 0 | AI21: =IF(AH21=0,0,VLOOKUP(AH21,MIE_Components!$A$2:$F$6,2,FALSE())) -> 0 | AJ21: =IF(AH21=0,0,VLOOKUP(AH21,MIE_Components!$A$2:$F$6,3,FALSE())) -> 0 | AK21: =IF(AH21=0,0,VLOOKUP(AH21,MIE_Components!$A$2:$F$6,4,FALSE())) -> 0 | AL21: =IF(OR($A21="",AH21=0),0,MAX(5,AH21*IF(OR($A21=Parameters!$B$13,$A21=Parameters!$B$14),0.75,1)-(IF(AND($A21=DATE(2026,11,29),NOV29BF="Yes"),AI21,0)+IF(OR($A21=DATE(2026,11,29),$A21=DATE(2026,11,30),$A21=DATE(2026,12,1),$A21=DATE(2026,12,2)),AJ21,0)+IF(OR($A21=DATE(2026,11,28),$A21=DATE(2026,12,1)),AK21,0)))) -> 0 | AM21: =IF(AND($A21<>"",$A21<Parameters!$B$14),CityData!F7*(1+TAXRATE),0) -> 0 | AN21: =IF($A21="",0,IFERROR(VLOOKUP((YEAR($A21)+IF(MONTH($A21)>=10,1,0))&"|Seattle|"&MONTH($A21),Rates!$A$2:$I$181,5,FALSE()),0)) -> 0 | AO21: =IF(OR($A21="",$A21>=Parameters!$B$14),1,IF(AND(AN21>0,CityData!F7<=AN21),1,0)) -> 1
A22: =IF(AND(Parameters!$B$14>=Parameters!$B$13,ROW()-2<=Parameters!$B$14-Parameters!$B$13),Parameters!$B$13+ROW()-2,"") | B22: =IF($A22="",0,IFERROR(VLOOKUP((YEAR($A22)+IF(MONTH($A22)>=10,1,0))&"|Boston|"&MONTH($A22),Rates!$A$2:$I$181,6,FALSE()),0)) -> 0 | C22: =IF(B22=0,0,VLOOKUP(B22,MIE_Components!$A$2:$F$6,2,FALSE())) -> 0 | D22: =IF(B22=0,0,VLOOKUP(B22,MIE_Components!$A$2:$F$6,3,FALSE())) -> 0 | E22: =IF(B22=0,0,VLOOKUP(B22,MIE_Components!$A$2:$F$6,4,FALSE())) -> 0 | F22: =IF(OR($A22="",B22=0),0,MAX(5,B22*IF(OR($A22=Parameters!$B$13,$A22=Parameters!$B$14),0.75,1)-(IF(AND($A22=DATE(2026,11,29),NOV29BF="Yes"),C22,0)+IF(OR($A22=DATE(2026,11,29),$A22=DATE(2026,11,30),$A22=DATE(2026,12,1),$A22=DATE(2026,12,2)),D22,0)+IF(OR($A22=DATE(2026,11,28),$A22=DATE(2026,12,1)),E22,0)))) -> 0 | G22: =IF(AND($A22<>"",$A22<Parameters!$B$14),CityData!F3*(1+TAXRATE),0) -> 0 | H22: =IF($A22="",0,IFERROR(VLOOKUP((YEAR($A22)+IF(MONTH($A22)>=10,1,0))&"|Boston|"&MONTH($A22),Rates!$A$2:$I$181,5,FALSE()),0)) -> 0 | I22: =IF(OR($A22="",$A22>=Parameters!$B$14),1,IF(AND(H22>0,CityData!F3<=H22),1,0)) -> 1 | J22: =IF($A22="",0,IFERROR(VLOOKUP((YEAR($A22)+IF(MONTH($A22)>=10,1,0))&"|Chicago|"&MONTH($A22),Rates!$A$2:$I$181,6,FALSE()),0)) -> 0 | K22: =IF(J22=0,0,VLOOKUP(J22,MIE_Components!$A$2:$F$6,2,FALSE())) -> 0 | L22: =IF(J22=0,0,VLOOKUP(J22,MIE_Components!$A$2:$F$6,3,FALSE())) -> 0 | M22: =IF(J22=0,0,VLOOKUP(J22,MIE_Components!$A$2:$F$6,4,FALSE())) -> 0 | N22: =IF(OR($A22="",J22=0),0,MAX(5,J22*IF(OR($A22=Parameters!$B$13,$A22=Parameters!$B$14),0.75,1)-(IF(AND($A22=DATE(2026,11,29),NOV29BF="Yes"),K22,0)+IF(OR($A22=DATE(2026,11,29),$A22=DATE(2026,11,30),$A22=DATE(2026,12,1),$A22=DATE(2026,12,2)),L22,0)+IF(OR($A22=DATE(2026,11,28),$A22=DATE(2026,12,1)),M22,0)))) -> 0 | O22: =IF(AND($A22<>"",$A22<Parameters!$B$14),CityData!F4*(1+TAXRATE),0) -> 0 | P22: =IF($A22="",0,IFERROR(VLOOKUP((YEAR($A22)+IF(MONTH($A22)>=10,1,0))&"|Chicago|"&MONTH($A22),Rates!$A$2:$I$181,5,FALSE()),0)) -> 0 | Q22: =IF(OR($A22="",$A22>=Parameters!$B$14),1,IF(AND(P22>0,CityData!F4<=P22),1,0)) -> 1 | R22: =IF($A22="",0,IFERROR(VLOOKUP((YEAR($A22)+IF(MONTH($A22)>=10,1,0))&"|Denver|"&MONTH($A22),Rates!$A$2:$I$181,6,FALSE()),0)) -> 0 | S22: =IF(R22=0,0,VLOOKUP(R22,MIE_Components!$A$2:$F$6,2,FALSE())) -> 0 | T22: =IF(R22=0,0,VLOOKUP(R22,MIE_Components!$A$2:$F$6,3,FALSE())) -> 0 | U22: =IF(R22=0,0,VLOOKUP(R22,MIE_Components!$A$2:$F$6,4,FALSE())) -> 0 | V22: =IF(OR($A22="",R22=0),0,MAX(5,R22*IF(OR($A22=Parameters!$B$13,$A22=Parameters!$B$14),0.75,1)-(IF(AND($A22=DATE(2026,11,29),NOV29BF="Yes"),S22,0)+IF(OR($A22=DATE(2026,11,29),$A22=DATE(2026,11,30),$A22=DATE(2026,12,1),$A22=DATE(2026,12,2)),T22,0)+IF(OR($A22=DATE(2026,11,28),$A22=DATE(2026,12,1)),U22,0)))) -> 0 | W22: =IF(AND($A22<>"",$A22<Parameters!$B$14),CityData!F5*(1+TAXRATE),0) -> 0 | X22: =IF($A22="",0,IFERROR(VLOOKUP((YEAR($A22)+IF(MONTH($A22)>=10,1,0))&"|Denver|"&MONTH($A22),Rates!$A$2:$I$181,5,FALSE()),0)) -> 0 | Y22: =IF(OR($A22="",$A22>=Parameters!$B$14),1,IF(AND(X22>0,CityData!F5<=X22),1,0)) -> 1 | Z22: =IF($A22="",0,IFERROR(VLOOKUP((YEAR($A22)+IF(MONTH($A22)>=10,1,0))&"|Phoenix|"&MONTH($A22),Rates!$A$2:$I$181,6,FALSE()),0)) -> 0 | AA22: =IF(Z22=0,0,VLOOKUP(Z22,MIE_Components!$A$2:$F$6,2,FALSE())) -> 0 | AB22: =IF(Z22=0,0,VLOOKUP(Z22,MIE_Components!$A$2:$F$6,3,FALSE())) -> 0 | AC22: =IF(Z22=0,0,VLOOKUP(Z22,MIE_Components!$A$2:$F$6,4,FALSE())) -> 0 | AD22: =IF(OR($A22="",Z22=0),0,MAX(5,Z22*IF(OR($A22=Parameters!$B$13,$A22=Parameters!$B$14),0.75,1)-(IF(AND($A22=DATE(2026,11,29),NOV29BF="Yes"),AA22,0)+IF(OR($A22=DATE(2026,11,29),$A22=DATE(2026,11,30),$A22=DATE(2026,12,1),$A22=DATE(2026,12,2)),AB22,0)+IF(OR($A22=DATE(2026,11,28),$A22=DATE(2026,12,1)),AC22,0)))) -> 0 | AE22: =IF(AND($A22<>"",$A22<Parameters!$B$14),CityData!F6*(1+TAXRATE),0) -> 0 | AF22: =IF($A22="",0,IFERROR(VLOOKUP((YEAR($A22)+IF(MONTH($A22)>=10,1,0))&"|Phoenix|"&MONTH($A22),Rates!$A$2:$I$181,5,FALSE()),0)) -> 0 | AG22: =IF(OR($A22="",$A22>=Parameters!$B$14),1,IF(AND(AF22>0,CityData!F6<=AF22),1,0)) -> 1 | AH22: =IF($A22="",0,IFERROR(VLOOKUP((YEAR($A22)+IF(MONTH($A22)>=10,1,0))&"|Seattle|"&MONTH($A22),Rates!$A$2:$I$181,6,FALSE()),0)) -> 0 | AI22: =IF(AH22=0,0,VLOOKUP(AH22,MIE_Components!$A$2:$F$6,2,FALSE())) -> 0 | AJ22: =IF(AH22=0,0,VLOOKUP(AH22,MIE_Components!$A$2:$F$6,3,FALSE())) -> 0 | AK22: =IF(AH22=0,0,VLOOKUP(AH22,MIE_Components!$A$2:$F$6,4,FALSE())) -> 0 | AL22: =IF(OR($A22="",AH22=0),0,MAX(5,AH22*IF(OR($A22=Parameters!$B$13,$A22=Parameters!$B$14),0.75,1)-(IF(AND($A22=DATE(2026,11,29),NOV29BF="Yes"),AI22,0)+IF(OR($A22=DATE(2026,11,29),$A22=DATE(2026,11,30),$A22=DATE(2026,12,1),$A22=DATE(2026,12,2)),AJ22,0)+IF(OR($A22=DATE(2026,11,28),$A22=DATE(2026,12,1)),AK22,0)))) -> 0 | AM22: =IF(AND($A22<>"",$A22<Parameters!$B$14),CityData!F7*(1+TAXRATE),0) -> 0 | AN22: =IF($A22="",0,IFERROR(VLOOKUP((YEAR($A22)+IF(MONTH($A22)>=10,1,0))&"|Seattle|"&MONTH($A22),Rates!$A$2:$I$181,5,FALSE()),0)) -> 0 | AO22: =IF(OR($A22="",$A22>=Parameters!$B$14),1,IF(AND(AN22>0,CityData!F7<=AN22),1,0)) -> 1
A23: =IF(AND(Parameters!$B$14>=Parameters!$B$13,ROW()-2<=Parameters!$B$14-Parameters!$B$13),Parameters!$B$13+ROW()-2,"") | B23: =IF($A23="",0,IFERROR(VLOOKUP((YEAR($A23)+IF(MONTH($A23)>=10,1,0))&"|Boston|"&MONTH($A23),Rates!$A$2:$I$181,6,FALSE()),0)) -> 0 | C23: =IF(B23=0,0,VLOOKUP(B23,MIE_Components!$A$2:$F$6,2,FALSE())) -> 0 | D23: =IF(B23=0,0,VLOOKUP(B23,MIE_Components!$A$2:$F$6,3,FALSE())) -> 0 | E23: =IF(B23=0,0,VLOOKUP(B23,MIE_Components!$A$2:$F$6,4,FALSE())) -> 0 | F23: =IF(OR($A23="",B23=0),0,MAX(5,B23*IF(OR($A23=Parameters!$B$13,$A23=Parameters!$B$14),0.75,1)-(IF(AND($A23=DATE(2026,11,29),NOV29BF="Yes"),C23,0)+IF(OR($A23=DATE(2026,11,29),$A23=DATE(2026,11,30),$A23=DATE(2026,12,1),$A23=DATE(2026,12,2)),D23,0)+IF(OR($A23=DATE(2026,11,28),$A23=DATE(2026,12,1)),E23,0)))) -> 0 | G23: =IF(AND($A23<>"",$A23<Parameters!$B$14),CityData!F3*(1+TAXRATE),0) -> 0 | H23: =IF($A23="",0,IFERROR(VLOOKUP((YEAR($A23)+IF(MONTH($A23)>=10,1,0))&"|Boston|"&MONTH($A23),Rates!$A$2:$I$181,5,FALSE()),0)) -> 0 | I23: =IF(OR($A23="",$A23>=Parameters!$B$14),1,IF(AND(H23>0,CityData!F3<=H23),1,0)) -> 1 | J23: =IF($A23="",0,IFERROR(VLOOKUP((YEAR($A23)+IF(MONTH($A23)>=10,1,0))&"|Chicago|"&MONTH($A23),Rates!$A$2:$I$181,6,FALSE()),0)) -> 0 | K23: =IF(J23=0,0,VLOOKUP(J23,MIE_Components!$A$2:$F$6,2,FALSE())) -> 0 | L23: =IF(J23=0,0,VLOOKUP(J23,MIE_Components!$A$2:$F$6,3,FALSE())) -> 0 | M23: =IF(J23=0,0,VLOOKUP(J23,MIE_Components!$A$2:$F$6,4,FALSE())) -> 0 | N23: =IF(OR($A23="",J23=0),0,MAX(5,J23*IF(OR($A23=Parameters!$B$13,$A23=Parameters!$B$14),0.75,1)-(IF(AND($A23=DATE(2026,11,29),NOV29BF="Yes"),K23,0)+IF(OR($A23=DATE(2026,11,29),$A23=DATE(2026,11,30),$A23=DATE(2026,12,1),$A23=DATE(2026,12,2)),L23,0)+IF(OR($A23=DATE(2026,11,28),$A23=DATE(2026,12,1)),M23,0)))) -> 0 | O23: =IF(AND($A23<>"",$A23<Parameters!$B$14),CityData!F4*(1+TAXRATE),0) -> 0 | P23: =IF($A23="",0,IFERROR(VLOOKUP((YEAR($A23)+IF(MONTH($A23)>=10,1,0))&"|Chicago|"&MONTH($A23),Rates!$A$2:$I$181,5,FALSE()),0)) -> 0 | Q23: =IF(OR($A23="",$A23>=Parameters!$B$14),1,IF(AND(P23>0,CityData!F4<=P23),1,0)) -> 1 | R23: =IF($A23="",0,IFERROR(VLOOKUP((YEAR($A23)+IF(MONTH($A23)>=10,1,0))&"|Denver|"&MONTH($A23),Rates!$A$2:$I$181,6,FALSE()),0)) -> 0 | S23: =IF(R23=0,0,VLOOKUP(R23,MIE_Components!$A$2:$F$6,2,FALSE())) -> 0 | T23: =IF(R23=0,0,VLOOKUP(R23,MIE_Components!$A$2:$F$6,3,FALSE())) -> 0 | U23: =IF(R23=0,0,VLOOKUP(R23,MIE_Components!$A$2:$F$6,4,FALSE())) -> 0 | V23: =IF(OR($A23="",R23=0),0,MAX(5,R23*IF(OR($A23=Parameters!$B$13,$A23=Parameters!$B$14),0.75,1)-(IF(AND($A23=DATE(2026,11,29),NOV29BF="Yes"),S23,0)+IF(OR($A23=DATE(2026,11,29),$A23=DATE(2026,11,30),$A23=DATE(2026,12,1),$A23=DATE(2026,12,2)),T23,0)+IF(OR($A23=DATE(2026,11,28),$A23=DATE(2026,12,1)),U23,0)))) -> 0 | W23: =IF(AND($A23<>"",$A23<Parameters!$B$14),CityData!F5*(1+TAXRATE),0) -> 0 | X23: =IF($A23="",0,IFERROR(VLOOKUP((YEAR($A23)+IF(MONTH($A23)>=10,1,0))&"|Denver|"&MONTH($A23),Rates!$A$2:$I$181,5,FALSE()),0)) -> 0 | Y23: =IF(OR($A23="",$A23>=Parameters!$B$14),1,IF(AND(X23>0,CityData!F5<=X23),1,0)) -> 1 | Z23: =IF($A23="",0,IFERROR(VLOOKUP((YEAR($A23)+IF(MONTH($A23)>=10,1,0))&"|Phoenix|"&MONTH($A23),Rates!$A$2:$I$181,6,FALSE()),0)) -> 0 | AA23: =IF(Z23=0,0,VLOOKUP(Z23,MIE_Components!$A$2:$F$6,2,FALSE())) -> 0 | AB23: =IF(Z23=0,0,VLOOKUP(Z23,MIE_Components!$A$2:$F$6,3,FALSE())) -> 0 | AC23: =IF(Z23=0,0,VLOOKUP(Z23,MIE_Components!$A$2:$F$6,4,FALSE())) -> 0 | AD23: =IF(OR($A23="",Z23=0),0,MAX(5,Z23*IF(OR($A23=Parameters!$B$13,$A23=Parameters!$B$14),0.75,1)-(IF(AND($A23=DATE(2026,11,29),NOV29BF="Yes"),AA23,0)+IF(OR($A23=DATE(2026,11,29),$A23=DATE(2026,11,30),$A23=DATE(2026,12,1),$A23=DATE(2026,12,2)),AB23,0)+IF(OR($A23=DATE(2026,11,28),$A23=DATE(2026,12,1)),AC23,0)))) -> 0 | AE23: =IF(AND($A23<>"",$A23<Parameters!$B$14),CityData!F6*(1+TAXRATE),0) -> 0 | AF23: =IF($A23="",0,IFERROR(VLOOKUP((YEAR($A23)+IF(MONTH($A23)>=10,1,0))&"|Phoenix|"&MONTH($A23),Rates!$A$2:$I$181,5,FALSE()),0)) -> 0 | AG23: =IF(OR($A23="",$A23>=Parameters!$B$14),1,IF(AND(AF23>0,CityData!F6<=AF23),1,0)) -> 1 | AH23: =IF($A23="",0,IFERROR(VLOOKUP((YEAR($A23)+IF(MONTH($A23)>=10,1,0))&"|Seattle|"&MONTH($A23),Rates!$A$2:$I$181,6,FALSE()),0)) -> 0 | AI23: =IF(AH23=0,0,VLOOKUP(AH23,MIE_Components!$A$2:$F$6,2,FALSE())) -> 0 | AJ23: =IF(AH23=0,0,VLOOKUP(AH23,MIE_Components!$A$2:$F$6,3,FALSE())) -> 0 | AK23: =IF(AH23=0,0,VLOOKUP(AH23,MIE_Components!$A$2:$F$6,4,FALSE())) -> 0 | AL23: =IF(OR($A23="",AH23=0),0,MAX(5,AH23*IF(OR($A23=Parameters!$B$13,$A23=Parameters!$B$14),0.75,1)-(IF(AND($A23=DATE(2026,11,29),NOV29BF="Yes"),AI23,0)+IF(OR($A23=DATE(2026,11,29),$A23=DATE(2026,11,30),$A23=DATE(2026,12,1),$A23=DATE(2026,12,2)),AJ23,0)+IF(OR($A23=DATE(2026,11,28),$A23=DATE(2026,12,1)),AK23,0)))) -> 0 | AM23: =IF(AND($A23<>"",$A23<Parameters!$B$14),CityData!F7*(1+TAXRATE),0) -> 0 | AN23: =IF($A23="",0,IFERROR(VLOOKUP((YEAR($A23)+IF(MONTH($A23)>=10,1,0))&"|Seattle|"&MONTH($A23),Rates!$A$2:$I$181,5,FALSE()),0)) -> 0 | AO23: =IF(OR($A23="",$A23>=Parameters!$B$14),1,IF(AND(AN23>0,CityData!F7<=AN23),1,0)) -> 1
A24: =IF(AND(Parameters!$B$14>=Parameters!$B$13,ROW()-2<=Parameters!$B$14-Parameters!$B$13),Parameters!$B$13+ROW()-2,"") | B24: =IF($A24="",0,IFERROR(VLOOKUP((YEAR($A24)+IF(MONTH($A24)>=10,1,0))&"|Boston|"&MONTH($A24),Rates!$A$2:$I$181,6,FALSE()),0)) -> 0 | C24: =IF(B24=0,0,VLOOKUP(B24,MIE_Components!$A$2:$F$6,2,FALSE())) -> 0 | D24: =IF(B24=0,0,VLOOKUP(B24,MIE_Components!$A$2:$F$6,3,FALSE())) -> 0 | E24: =IF(B24=0,0,VLOOKUP(B24,MIE_Components!$A$2:$F$6,4,FALSE())) -> 0 | F24: =IF(OR($A24="",B24=0),0,MAX(5,B24*IF(OR($A24=Parameters!$B$13,$A24=Parameters!$B$14),0.75,1)-(IF(AND($A24=DATE(2026,11,29),NOV29BF="Yes"),C24,0)+IF(OR($A24=DATE(2026,11,29),$A24=DATE(2026,11,30),$A24=DATE(2026,12,1),$A24=DATE(2026,12,2)),D24,0)+IF(OR($A24=DATE(2026,11,28),$A24=DATE(2026,12,1)),E24,0)))) -> 0 | G24: =IF(AND($A24<>"",$A24<Parameters!$B$14),CityData!F3*(1+TAXRATE),0) -> 0 | H24: =IF($A24="",0,IFERROR(VLOOKUP((YEAR($A24)+IF(MONTH($A24)>=10,1,0))&"|Boston|"&MONTH($A24),Rates!$A$2:$I$181,5,FALSE()),0)) -> 0 | I24: =IF(OR($A24="",$A24>=Parameters!$B$14),1,IF(AND(H24>0,CityData!F3<=H24),1,0)) -> 1 | J24: =IF($A24="",0,IFERROR(VLOOKUP((YEAR($A24)+IF(MONTH($A24)>=10,1,0))&"|Chicago|"&MONTH($A24),Rates!$A$2:$I$181,6,FALSE()),0)) -> 0 | K24: =IF(J24=0,0,VLOOKUP(J24,MIE_Components!$A$2:$F$6,2,FALSE())) -> 0 | L24: =IF(J24=0,0,VLOOKUP(J24,MIE_Components!$A$2:$F$6,3,FALSE())) -> 0 | M24: =IF(J24=0,0,VLOOKUP(J24,MIE_Components!$A$2:$F$6,4,FALSE())) -> 0 | N24: =IF(OR($A24="",J24=0),0,MAX(5,J24*IF(OR($A24=Parameters!$B$13,$A24=Parameters!$B$14),0.75,1)-(IF(AND($A24=DATE(2026,11,29),NOV29BF="Yes"),K24,0)+IF(OR($A24=DATE(2026,11,29),$A24=DATE(2026,11,30),$A24=DATE(2026,12,1),$A24=DATE(2026,12,2)),L24,0)+IF(OR($A24=DATE(2026,11,28),$A24=DATE(2026,12,1)),M24,0)))) -> 0 | O24: =IF(AND($A24<>"",$A24<Parameters!$B$14),CityData!F4*(1+TAXRATE),0) -> 0 | P24: =IF($A24="",0,IFERROR(VLOOKUP((YEAR($A24)+IF(MONTH($A24)>=10,1,0))&"|Chicago|"&MONTH($A24),Rates!$A$2:$I$181,5,FALSE()),0)) -> 0 | Q24: =IF(OR($A24="",$A24>=Parameters!$B$14),1,IF(AND(P24>0,CityData!F4<=P24),1,0)) -> 1 | R24: =IF($A24="",0,IFERROR(VLOOKUP((YEAR($A24)+IF(MONTH($A24)>=10,1,0))&"|Denver|"&MONTH($A24),Rates!$A$2:$I$181,6,FALSE()),0)) -> 0 | S24: =IF(R24=0,0,VLOOKUP(R24,MIE_Components!$A$2:$F$6,2,FALSE())) -> 0 | T24: =IF(R24=0,0,VLOOKUP(R24,MIE_Components!$A$2:$F$6,3,FALSE())) -> 0 | U24: =IF(R24=0,0,VLOOKUP(R24,MIE_Components!$A$2:$F$6,4,FALSE())) -> 0 | V24: =IF(OR($A24="",R24=0),0,MAX(5,R24*IF(OR($A24=Parameters!$B$13,$A24=Parameters!$B$14),0.75,1)-(IF(AND($A24=DATE(2026,11,29),NOV29BF="Yes"),S24,0)+IF(OR($A24=DATE(2026,11,29),$A24=DATE(2026,11,30),$A24=DATE(2026,12,1),$A24=DATE(2026,12,2)),T24,0)+IF(OR($A24=DATE(2026,11,28),$A24=DATE(2026,12,1)),U24,0)))) -> 0 | W24: =IF(AND($A24<>"",$A24<Parameters!$B$14),CityData!F5*(1+TAXRATE),0) -> 0 | X24: =IF($A24="",0,IFERROR(VLOOKUP((YEAR($A24)+IF(MONTH($A24)>=10,1,0))&"|Denver|"&MONTH($A24),Rates!$A$2:$I$181,5,FALSE()),0)) -> 0 | Y24: =IF(OR($A24="",$A24>=Parameters!$B$14),1,IF(AND(X24>0,CityData!F5<=X24),1,0)) -> 1 | Z24: =IF($A24="",0,IFERROR(VLOOKUP((YEAR($A24)+IF(MONTH($A24)>=10,1,0))&"|Phoenix|"&MONTH($A24),Rates!$A$2:$I$181,6,FALSE()),0)) -> 0 | AA24: =IF(Z24=0,0,VLOOKUP(Z24,MIE_Components!$A$2:$F$6,2,FALSE())) -> 0 | AB24: =IF(Z24=0,0,VLOOKUP(Z24,MIE_Components!$A$2:$F$6,3,FALSE())) -> 0 | AC24: =IF(Z24=0,0,VLOOKUP(Z24,MIE_Components!$A$2:$F$6,4,FALSE())) -> 0 | AD24: =IF(OR($A24="",Z24=0),0,MAX(5,Z24*IF(OR($A24=Parameters!$B$13,$A24=Parameters!$B$14),0.75,1)-(IF(AND($A24=DATE(2026,11,29),NOV29BF="Yes"),AA24,0)+IF(OR($A24=DATE(2026,11,29),$A24=DATE(2026,11,30),$A24=DATE(2026,12,1),$A24=DATE(2026,12,2)),AB24,0)+IF(OR($A24=DATE(2026,11,28),$A24=DATE(2026,12,1)),AC24,0)))) -> 0 | AE24: =IF(AND($A24<>"",$A24<Parameters!$B$14),CityData!F6*(1+TAXRATE),0) -> 0 | AF24: =IF($A24="",0,IFERROR(VLOOKUP((YEAR($A24)+IF(MONTH($A24)>=10,1,0))&"|Phoenix|"&MONTH($A24),Rates!$A$2:$I$181,5,FALSE()),0)) -> 0 | AG24: =IF(OR($A24="",$A24>=Parameters!$B$14),1,IF(AND(AF24>0,CityData!F6<=AF24),1,0)) -> 1 | AH24: =IF($A24="",0,IFERROR(VLOOKUP((YEAR($A24)+IF(MONTH($A24)>=10,1,0))&"|Seattle|"&MONTH($A24),Rates!$A$2:$I$181,6,FALSE()),0)) -> 0 | AI24: =IF(AH24=0,0,VLOOKUP(AH24,MIE_Components!$A$2:$F$6,2,FALSE())) -> 0 | AJ24: =IF(AH24=0,0,VLOOKUP(AH24,MIE_Components!$A$2:$F$6,3,FALSE())) -> 0 | AK24: =IF(AH24=0,0,VLOOKUP(AH24,MIE_Components!$A$2:$F$6,4,FALSE())) -> 0 | AL24: =IF(OR($A24="",AH24=0),0,MAX(5,AH24*IF(OR($A24=Parameters!$B$13,$A24=Parameters!$B$14),0.75,1)-(IF(AND($A24=DATE(2026,11,29),NOV29BF="Yes"),AI24,0)+IF(OR($A24=DATE(2026,11,29),$A24=DATE(2026,11,30),$A24=DATE(2026,12,1),$A24=DATE(2026,12,2)),AJ24,0)+IF(OR($A24=DATE(2026,11,28),$A24=DATE(2026,12,1)),AK24,0)))) -> 0 | AM24: =IF(AND($A24<>"",$A24<Parameters!$B$14),CityData!F7*(1+TAXRATE),0) -> 0 | AN24: =IF($A24="",0,IFERROR(VLOOKUP((YEAR($A24)+IF(MONTH($A24)>=10,1,0))&"|Seattle|"&MONTH($A24),Rates!$A$2:$I$181,5,FALSE()),0)) -> 0 | AO24: =IF(OR($A24="",$A24>=Parameters!$B$14),1,IF(AND(AN24>0,CityData!F7<=AN24),1,0)) -> 1
