Workbook

Sheet Daily
A1: 逐日差旅明细 | DAILY
A2: 金额均为每人每日美元；住宿上限是报销天花板，预算按实际报价（不超过上限）计入。税率12%为本练习内部预算假设。
A4: 地点 | B4: 县/区域 | C4: 日期 | D4: 财政年度 | E4: 住宿夜? | F4: 住宿上限 | G4: 未税报价 | H4: 可报销住宿预算 | I4: 住宿税率 | J4: 住宿税预算 | K4: 全额M&IE | L4: 首/末日比例 | M4: 比例后M&IE | N4: 早餐扣减 | O4: 午餐扣减 | P4: 晚餐扣减 | Q4: 扣减合计 | R4: 最低杂费 | S4: 最终M&IE | T4: 说明 | U4: 费率原表行号 | V4: 住宿合规性
A5: Chicago, IL | B5: Cook | C5: 2025-09-28 | D5: FY2025 | E5: 是 | F5: 223 | G5: 218 | H5: =MIN(F5,G5) -> 218 | I5: 0.12 | J5: =H5*I5 -> 26.16 | K5: 92 | L5: 0.75 | M5: =K5*L5 -> 69 | N5: 0 | O5: 0 | P5: 38 | Q5: =SUM(N5:P5) -> 38 | R5: 5 | S5: =MAX(R5,M5-Q5) -> 31 | T5: 出发；政府提供欢迎晚餐 | U5: 258 | V5: =IF(E5="否","不适用",IF(G5<=F5,"报价≤上限","需实际费用授权")) -> 报价≤上限
A6: Chicago, IL | B6: Cook | C6: 2025-09-29 | D6: FY2025 | E6: 是 | F6: 223 | G6: 218 | H6: =MIN(F6,G6) -> 218 | I6: 0.12 | J6: =H6*I6 -> 26.16 | K6: 92 | L6: 1 | M6: =K6*L6 -> 92 | N6: 0 | O6: 26 | P6: 0 | Q6: =SUM(N6:P6) -> 26 | R6: 5 | S6: =MAX(R6,M6-Q6) -> 66 | T6: 培训；注册费含午餐；酒店免费早餐 | U6: 258 | V6: =IF(E6="否","不适用",IF(G6<=F6,"报价≤上限","需实际费用授权")) -> 报价≤上限
A7: Chicago, IL | B7: Cook | C7: 2025-09-30 | D7: FY2025 | E7: 是 | F7: 223 | G7: 218 | H7: =MIN(F7,G7) -> 218 | I7: 0.12 | J7: =H7*I7 -> 26.16 | K7: 92 | L7: 1 | M7: =K7*L7 -> 92 | N7: 0 | O7: 26 | P7: 0 | Q7: =SUM(N7:P7) -> 26 | R7: 5 | S7: =MAX(R7,M7-Q7) -> 66 | T7: 培训；注册费含午餐；酒店免费早餐 | U7: 258 | V7: =IF(E7="否","不适用",IF(G7<=F7,"报价≤上限","需实际费用授权")) -> 报价≤上限
A8: Chicago, IL | B8: Cook | C8: 2025-10-01 | D8: FY2026 | E8: 是 | F8: 223 | G8: 218 | H8: =MIN(F8,G8) -> 218 | I8: 0.12 | J8: =H8*I8 -> 26.16 | K8: 92 | L8: 1 | M8: =K8*L8 -> 92 | N8: 0 | O8: 26 | P8: 38 | Q8: =SUM(N8:P8) -> 64 | R8: 5 | S8: =MAX(R8,M8-Q8) -> 28 | T8: 培训；注册费含午餐；政府提供晚餐；酒店免费早餐 | U8: 254 | V8: =IF(E8="否","不适用",IF(G8<=F8,"报价≤上限","需实际费用授权")) -> 报价≤上限
A9: Chicago, IL | B9: Cook | C9: 2025-10-02 | D9: FY2026 | E9: 否 | F9: 0 | G9: 0 | H9: =MIN(F9,G9) -> 0 | I9: 0 | J9: =H9*I9 -> 0 | K9: 92 | L9: 0.75 | M9: =K9*L9 -> 69 | N9: 0 | O9: 26 | P9: 0 | Q9: =SUM(N9:P9) -> 26 | R9: 5 | S9: =MAX(R9,M9-Q9) -> 43 | T9: 返回；政府提供离场午餐；酒店免费早餐 | U9: 254 | V9: =IF(E9="否","不适用",IF(G9<=F9,"报价≤上限","需实际费用授权")) -> 不适用
A10: Denver, CO | B10: Denver | C10: 2025-09-28 | D10: FY2025 | E10: 是 | F10: 215 | G10: 209 | H10: =MIN(F10,G10) -> 209 | I10: 0.12 | J10: =H10*I10 -> 25.08 | K10: 92 | L10: 0.75 | M10: =K10*L10 -> 69 | N10: 0 | O10: 0 | P10: 38 | Q10: =SUM(N10:P10) -> 38 | R10: 5 | S10: =MAX(R10,M10-Q10) -> 31 | T10: 出发；政府提供欢迎晚餐 | U10: 109 | V10: =IF(E10="否","不适用",IF(G10<=F10,"报价≤上限","需实际费用授权")) -> 报价≤上限
A11: Denver, CO | B11: Denver | C11: 2025-09-29 | D11: FY2025 | E11: 是 | F11: 215 | G11: 209 | H11: =MIN(F11,G11) -> 209 | I11: 0.12 | J11: =H11*I11 -> 25.08 | K11: 92 | L11: 1 | M11: =K11*L11 -> 92 | N11: 0 | O11: 26 | P11: 0 | Q11: =SUM(N11:P11) -> 26 | R11: 5 | S11: =MAX(R11,M11-Q11) -> 66 | T11: 培训；注册费含午餐；酒店免费早餐 | U11: 109 | V11: =IF(E11="否","不适用",IF(G11<=F11,"报价≤上限","需实际费用授权")) -> 报价≤上限
A12: Denver, CO | B12: Denver | C12: 2025-09-30 | D12: FY2025 | E12: 是 | F12: 215 | G12: 209 | H12: =MIN(F12,G12) -> 209 | I12: 0.12 | J12: =H12*I12 -> 25.08 | K12: 92 | L12: 1 | M12: =K12*L12 -> 92 | N12: 0 | O12: 26 | P12: 0 | Q12: =SUM(N12:P12) -> 26 | R12: 5 | S12: =MAX(R12,M12-Q12) -> 66 | T12: 培训；注册费含午餐；酒店免费早餐 | U12: 109 | V12: =IF(E12="否","不适用",IF(G12<=F12,"报价≤上限","需实际费用授权")) -> 报价≤上限
A13: Denver, CO | B13: Denver | C13: 2025-10-01 | D13: FY2026 | E13: 是 | F13: 215 | G13: 209 | H13: =MIN(F13,G13) -> 209 | I13: 0.12 | J13: =H13*I13 -> 25.08 | K13: 92 | L13: 1 | M13: =K13*L13 -> 92 | N13: 0 | O13: 26 | P13: 38 | Q13: =SUM(N13:P13) -> 64 | R13: 5 | S13: =MAX(R13,M13-Q13) -> 28 | T13: 培训；注册费含午餐；政府提供晚餐；酒店免费早餐 | U13: 107 | V13: =IF(E13="否","不适用",IF(G13<=F13,"报价≤上限","需实际费用授权")) -> 报价≤上限
A14: Denver, CO | B14: Denver | C14: 2025-10-02 | D14: FY2026 | E14: 否 | F14: 0 | G14: 0 | H14: =MIN(F14,G14) -> 0 | I14: 0 | J14: =H14*I14 -> 0 | K14: 92 | L14: 0.75 | M14: =K14*L14 -> 69 | N14: 0 | O14: 26 | P14: 0 | Q14: =SUM(N14:P14) -> 26 | R14: 5 | S14: =MAX(R14,M14-Q14) -> 43 | T14: 返回；政府提供离场午餐；酒店免费早餐 | U14: 107 | V14: =IF(E14="否","不适用",IF(G14<=F14,"报价≤上限","需实际费用授权")) -> 不适用
A15: Phoenix, AZ | B15: Maricopa | C15: 2025-09-28 | D15: FY2025 | E15: 是 | F15: 160 | G15: 155 | H15: =MIN(F15,G15) -> 155 | I15: 0.12 | J15: =H15*I15 -> 18.6 | K15: 86 | L15: 0.75 | M15: =K15*L15 -> 64.5 | N15: 0 | O15: 0 | P15: 36 | Q15: =SUM(N15:P15) -> 36 | R15: 5 | S15: =MAX(R15,M15-Q15) -> 28.5 | T15: 出发；政府提供欢迎晚餐 | U15: 22 | V15: =IF(E15="否","不适用",IF(G15<=F15,"报价≤上限","需实际费用授权")) -> 报价≤上限
A16: Phoenix, AZ | B16: Maricopa | C16: 2025-09-29 | D16: FY2025 | E16: 是 | F16: 160 | G16: 155 | H16: =MIN(F16,G16) -> 155 | I16: 0.12 | J16: =H16*I16 -> 18.6 | K16: 86 | L16: 1 | M16: =K16*L16 -> 86 | N16: 0 | O16: 23 | P16: 0 | Q16: =SUM(N16:P16) -> 23 | R16: 5 | S16: =MAX(R16,M16-Q16) -> 63 | T16: 培训；注册费含午餐；酒店免费早餐 | U16: 22 | V16: =IF(E16="否","不适用",IF(G16<=F16,"报价≤上限","需实际费用授权")) -> 报价≤上限
... A19: Phoenix, AZ | B19: Maricopa | C19: 2025-10-02 | D19: FY2026 | E19: 否 | F19: 0 | G19: 0 | H19: =MIN(F19,G19) -> 0 | I19: 0 | J19: =H19*I19 -> 0 | K19: 86 | L19: 0.75 | M19: =K19*L19 -> 64.5 | N19: 0 | O19: 23 | P19: 0 | Q19: =SUM(N19:P19) -> 23 | R19: 5 | S19: =MAX(R19,M19-Q19) -> 41.5 | T19: 返回；政府提供离场午餐；酒店免费早餐 | U19: 18 | V19: =IF(E19="否","不适用",IF(G19<=F19,"报价≤上限","需实际费用授权")) -> 不适用

Sheet Options
A1: 六方案总预算 | OPTIONS
A2: 目标顺序：先最大化合规人数，再在同人数下选最低总额；本表保留原53,000美元总上限排名，年度资金可行性见FundingBridge。
A4: 原总额排名 | B4: 地点 | C4: 人数 | D4: 住宿/人 | E4: 住宿税/人 | F4: M&IE/人 | G4: 机票/人 | H4: 当地交通/人 | I4: 注册/人 | J4: 固定场地费 | K4: 基础成本 | L4: 5%储备 | M4: 批准总额 | N4: 预算余量(53,000-总额) | O4: 总额状态 | P4: 住宿合规性 | Q4: 压力基础成本 | R4: 压力5%储备 | S4: 压力总额 | T4: 压力余量 | U4: 压力状态 | V4: 总额口径决策标记
A5: =rank.eq(M5,$M$5:$M$10,1) -> #NAME? | B5: Chicago, IL | C5: 18 | D5: =SUMIF(Daily!$A$5:$A$19,B5,Daily!$H$5:$H$19) -> 872 | E5: =SUMIF(Daily!$A$5:$A$19,B5,Daily!$J$5:$J$19) -> 104.64 | F5: =SUMIF(Daily!$A$5:$A$19,B5,Daily!$S$5:$S$19) -> 234 | G5: 410 | H5: 80 | I5: 180 | J5: 9500 | K5: =C5*SUM(D5:I5)+J5 -> 43351.52 | L5: =K5*5% -> 2167.576 | M5: =K5+L5 -> 45519.096 | N5: =53000-M5 -> 7480.904 | O5: =IF(N5>=0,"总额内","超总额") -> 总额内 | P5: =IF(COUNTIFS(Daily!$A$5:$A$19,B5,Daily!$V$5:$V$19,"需实际费用授权")=0,"全部报价≤上限","需实际费用授权") -> 全部报价≤上限 | Q5: =K5+C5*G5*20% -> 44827.52 | R5: =Q5*5% -> 2241.376 | S5: =Q5+R5 -> 47068.896 | T5: =53000-S5 -> 5931.104 | U5: =IF(T5>=0,"压力总额内","压力超总额") -> 压力总额内 | V5: =IF(AND(C5=24,N5>=0),"原总额口径候选",IF(AND(C5=18,N5>=0),"人数次选","不可行")) -> 人数次选
A6: =rank.eq(M6,$M$5:$M$10,1) -> #NAME? | B6: Chicago, IL | C6: 24 | D6: =SUMIF(Daily!$A$5:$A$19,B6,Daily!$H$5:$H$19) -> 872 | E6: =SUMIF(Daily!$A$5:$A$19,B6,Daily!$J$5:$J$19) -> 104.64 | F6: =SUMIF(Daily!$A$5:$A$19,B6,Daily!$S$5:$S$19) -> 234 | G6: 410 | H6: 80 | I6: 180 | J6: 9500 | K6: =C6*SUM(D6:I6)+J6 -> 54635.36 | L6: =K6*5% -> 2731.768 | M6: =K6+L6 -> 57367.128 | N6: =53000-M6 -> -4367.128 | O6: =IF(N6>=0,"总额内","超总额") -> 超总额 | P6: =IF(COUNTIFS(Daily!$A$5:$A$19,B6,Daily!$V$5:$V$19,"需实际费用授权")=0,"全部报价≤上限","需实际费用授权") -> 全部报价≤上限 | Q6: =K6+C6*G6*20% -> 56603.36 | R6: =Q6*5% -> 2830.168 | S6: =Q6+R6 -> 59433.528 | T6: =53000-S6 -> -6433.528 | U6: =IF(T6>=0,"压力总额内","压力超总额") -> 压力超总额 | V6: =IF(AND(C6=24,N6>=0),"原总额口径候选",IF(AND(C6=18,N6>=0),"人数次选","不可行")) -> 不可行
A7: =rank.eq(M7,$M$5:$M$10,1) -> #NAME? | B7: Denver, CO | C7: 18 | D7: =SUMIF(Daily!$A$5:$A$19,B7,Daily!$H$5:$H$19) -> 836 | E7: =SUMIF(Daily!$A$5:$A$19,B7,Daily!$J$5:$J$19) -> 100.32 | F7: =SUMIF(Daily!$A$5:$A$19,B7,Daily!$S$5:$S$19) -> 234 | G7: 340 | H7: 70 | I7: 180 | J7: 10500 | K7: =C7*SUM(D7:I7)+J7 -> 42185.76 | L7: =K7*5% -> 2109.288 | M7: =K7+L7 -> 44295.048 | N7: =53000-M7 -> 8704.952 | O7: =IF(N7>=0,"总额内","超总额") -> 总额内 | P7: =IF(COUNTIFS(Daily!$A$5:$A$19,B7,Daily!$V$5:$V$19,"需实际费用授权")=0,"全部报价≤上限","需实际费用授权") -> 全部报价≤上限 | Q7: =K7+C7*G7*20% -> 43409.76 | R7: =Q7*5% -> 2170.488 | S7: =Q7+R7 -> 45580.248 | T7: =53000-S7 -> 7419.752 | U7: =IF(T7>=0,"压力总额内","压力超总额") -> 压力总额内 | V7: =IF(AND(C7=24,N7>=0),"原总额口径候选",IF(AND(C7=18,N7>=0),"人数次选","不可行")) -> 人数次选
A8: =rank.eq(M8,$M$5:$M$10,1) -> #NAME? | B8: Denver, CO | C8: 24 | D8: =SUMIF(Daily!$A$5:$A$19,B8,Daily!$H$5:$H$19) -> 836 | E8: =SUMIF(Daily!$A$5:$A$19,B8,Daily!$J$5:$J$19) -> 100.32 | F8: =SUMIF(Daily!$A$5:$A$19,B8,Daily!$S$5:$S$19) -> 234 | G8: 340 | H8: 70 | I8: 180 | J8: 10500 | K8: =C8*SUM(D8:I8)+J8 -> 52747.68 | L8: =K8*5% -> 2637.384 | M8: =K8+L8 -> 55385.064 | N8: =53000-M8 -> -2385.064 | O8: =IF(N8>=0,"总额内","超总额") -> 超总额 | P8: =IF(COUNTIFS(Daily!$A$5:$A$19,B8,Daily!$V$5:$V$19,"需实际费用授权")=0,"全部报价≤上限","需实际费用授权") -> 全部报价≤上限 | Q8: =K8+C8*G8*20% -> 54379.68 | R8: =Q8*5% -> 2718.984 | S8: =Q8+R8 -> 57098.664 | T8: =53000-S8 -> -4098.664 | U8: =IF(T8>=0,"压力总额内","压力超总额") -> 压力超总额 | V8: =IF(AND(C8=24,N8>=0),"原总额口径候选",IF(AND(C8=18,N8>=0),"人数次选","不可行")) -> 不可行
A9: =rank.eq(M9,$M$5:$M$10,1) -> #NAME? | B9: Phoenix, AZ | C9: 18 | D9: =SUMIF(Daily!$A$5:$A$19,B9,Daily!$H$5:$H$19) -> 620 | E9: =SUMIF(Daily!$A$5:$A$19,B9,Daily!$J$5:$J$19) -> 74.4 | F9: =SUMIF(Daily!$A$5:$A$19,B9,Daily!$S$5:$S$19) -> 223 | G9: 510 | H9: 90 | I9: 180 | J9: 8000 | K9: =C9*SUM(D9:I9)+J9 -> 38553.2 | L9: =K9*5% -> 1927.66 | M9: =K9+L9 -> 40480.86 | N9: =53000-M9 -> 12519.14 | O9: =IF(N9>=0,"总额内","超总额") -> 总额内 | P9: =IF(COUNTIFS(Daily!$A$5:$A$19,B9,Daily!$V$5:$V$19,"需实际费用授权")=0,"全部报价≤上限","需实际费用授权") -> 全部报价≤上限 | Q9: =K9+C9*G9*20% -> 40389.2 | R9: =Q9*5% -> 2019.46 | S9: =Q9+R9 -> 42408.66 | T9: =53000-S9 -> 10591.34 | U9: =IF(T9>=0,"压力总额内","压力超总额") -> 压力总额内 | V9: =IF(AND(C9=24,N9>=0),"原总额口径候选",IF(AND(C9=18,N9>=0),"人数次选","不可行")) -> 人数次选
A10: =rank.eq(M10,$M$5:$M$10,1) -> #NAME? | B10: Phoenix, AZ | C10: 24 | D10: =SUMIF(Daily!$A$5:$A$19,B10,Daily!$H$5:$H$19) -> 620 | E10: =SUMIF(Daily!$A$5:$A$19,B10,Daily!$J$5:$J$19) -> 74.4 | F10: =SUMIF(Daily!$A$5:$A$19,B10,Daily!$S$5:$S$19) -> 223 | G10: 510 | H10: 90 | I10: 180 | J10: 8000 | K10: =C10*SUM(D10:I10)+J10 -> 48737.6 | L10: =K10*5% -> 2436.88 | M10: =K10+L10 -> 51174.48 | N10: =53000-M10 -> 1825.52 | O10: =IF(N10>=0,"总额内","超总额") -> 总额内 | P10: =IF(COUNTIFS(Daily!$A$5:$A$19,B10,Daily!$V$5:$V$19,"需实际费用授权")=0,"全部报价≤上限","需实际费用授权") -> 全部报价≤上限 | Q10: =K10+C10*G10*20% -> 51185.6 | R10: =Q10*5% -> 2559.28 | S10: =Q10+R10 -> 53744.88 | T10: =53000-S10 -> -744.88 | U10: =IF(T10>=0,"压力总额内","压力超总额") -> 压力超总额 | V10: =IF(AND(C10=24,N10>=0),"原总额口径候选",IF(AND(C10=18,N10>=0),"人数次选","不可行")) -> 原总额口径候选

Sheet FundingBridge
A1: 分年度资金桥接 | FUNDING BRIDGE
A2: 内部管理归集（非拨款法结论）：两年基础各加5%储备；原额度FY2025 $41,000、FY2026 $12,000；调整仅移动额度，不改变成本或$53,000总上限。
A4: 地点 | B4: 人数 | C4: 情景 | D4: FY2025基础 | E4: FY2025储备 | F4: FY2025含储备 | G4: FY2025原额度余量 | H4: FY2026基础 | I4: FY2026储备 | J4: FY2026含储备 | K4: FY2026原额度余量 | L4: 两年合计 | M4: 总上限余量 | N4: 最小必要调整 FY26→FY25 | O4: 调整≤1,500且两年/总额可行? | P4: 调整后FY2025额度 | Q4: 调整后FY2026额度 | R4: 调整后FY2025余量 | S4: 调整后FY2026余量 | T4: 决策结论
A5: Chicago, IL | B5: 18 | C5: 基准 | D5: =18*(410*100%+80/2+180*2/3+SUMIFS(Daily!$H$5:$H$19,Daily!$A$5:$A$19,A5,Daily!$D$5:$D$19,"FY2025")+SUMIFS(Daily!$J$5:$J$19,Daily!$A$5:$A$19,A5,Daily!$D$5:$D$19,"FY2025")+SUMIFS(Daily!$S$5:$S$19,Daily!$A$5:$A$19,A5,Daily!$D$5:$D$19,"FY2025"))+9500 -> 35878.64 | E5: =D5*5% -> 1793.932 | F5: =D5+E5 -> 37672.572 | G5: =41000-F5 -> 3327.428 | H5: =18*(80/2+180/3+SUMIFS(Daily!$H$5:$H$19,Daily!$A$5:$A$19,A5,Daily!$D$5:$D$19,"FY2026")+SUMIFS(Daily!$J$5:$J$19,Daily!$A$5:$A$19,A5,Daily!$D$5:$D$19,"FY2026")+SUMIFS(Daily!$S$5:$S$19,Daily!$A$5:$A$19,A5,Daily!$D$5:$D$19,"FY2026")) -> 7472.88 | I5: =H5*5% -> 373.644 | J5: =H5+I5 -> 7846.524 | K5: =12000-J5 -> 4153.476 | L5: =F5+J5 -> 45519.096 | M5: =53000-L5 -> 7480.904 | N5: =MAX(0,F5-41000) -> 0 | O5: =IF(AND(N5<=1500,M5>=0,J5<=12000-N5),"是","否") -> 是 | P5: =41000+N5 -> 41000 | Q5: =12000-N5 -> 12000 | R5: =P5-F5 -> 3327.428 | S5: =Q5-J5 -> 4153.476 | T5: =IF(O5="是",IF(N5=0,"无需调整可行","调整获批后可行"),IF(M5<0,"总额超限，无解",IF(N5>1500,"FY2025缺口超调整上限，无解","FY2026移出额度后不足，无解"))) -> 无需调整可行
A6: Chicago, IL | B6: 18 | C6: 机票+20% | D6: =18*(410*120%+80/2+180*2/3+SUMIFS(Daily!$H$5:$H$19,Daily!$A$5:$A$19,A6,Daily!$D$5:$D$19,"FY2025")+SUMIFS(Daily!$J$5:$J$19,Daily!$A$5:$A$19,A6,Daily!$D$5:$D$19,"FY2025")+SUMIFS(Daily!$S$5:$S$19,Daily!$A$5:$A$19,A6,Daily!$D$5:$D$19,"FY2025"))+9500 -> 37354.64 | E6: =D6*5% -> 1867.732 | F6: =D6+E6 -> 39222.372 | G6: =41000-F6 -> 1777.628 | H6: =18*(80/2+180/3+SUMIFS(Daily!$H$5:$H$19,Daily!$A$5:$A$19,A6,Daily!$D$5:$D$19,"FY2026")+SUMIFS(Daily!$J$5:$J$19,Daily!$A$5:$A$19,A6,Daily!$D$5:$D$19,"FY2026")+SUMIFS(Daily!$S$5:$S$19,Daily!$A$5:$A$19,A6,Daily!$D$5:$D$19,"FY2026")) -> 7472.88 | I6: =H6*5% -> 373.644 | J6: =H6+I6 -> 7846.524 | K6: =12000-J6 -> 4153.476 | L6: =F6+J6 -> 47068.896 | M6: =53000-L6 -> 5931.104 | N6: =MAX(0,F6-41000) -> 0 | O6: =IF(AND(N6<=1500,M6>=0,J6<=12000-N6),"是","否") -> 是 | P6: =41000+N6 -> 41000 | Q6: =12000-N6 -> 12000 | R6: =P6-F6 -> 1777.628 | S6: =Q6-J6 -> 4153.476 | T6: =IF(O6="是",IF(N6=0,"无需调整可行","调整获批后可行"),IF(M6<0,"总额超限，无解",IF(N6>1500,"FY2025缺口超调整上限，无解","FY2026移出额度后不足，无解"))) -> 无需调整可行
A7: Chicago, IL | B7: 24 | C7: 基准 | D7: =24*(410*100%+80/2+180*2/3+SUMIFS(Daily!$H$5:$H$19,Daily!$A$5:$A$19,A7,Daily!$D$5:$D$19,"FY2025")+SUMIFS(Daily!$J$5:$J$19,Daily!$A$5:$A$19,A7,Daily!$D$5:$D$19,"FY2025")+SUMIFS(Daily!$S$5:$S$19,Daily!$A$5:$A$19,A7,Daily!$D$5:$D$19,"FY2025"))+9500 -> 44671.52 | E7: =D7*5% -> 2233.576 | F7: =D7+E7 -> 46905.096 | G7: =41000-F7 -> -5905.096 | H7: =24*(80/2+180/3+SUMIFS(Daily!$H$5:$H$19,Daily!$A$5:$A$19,A7,Daily!$D$5:$D$19,"FY2026")+SUMIFS(Daily!$J$5:$J$19,Daily!$A$5:$A$19,A7,Daily!$D$5:$D$19,"FY2026")+SUMIFS(Daily!$S$5:$S$19,Daily!$A$5:$A$19,A7,Daily!$D$5:$D$19,"FY2026")) -> 9963.84 | I7: =H7*5% -> 498.192 | J7: =H7+I7 -> 10462.032 | K7: =12000-J7 -> 1537.968 | L7: =F7+J7 -> 57367.128 | M7: =53000-L7 -> -4367.128 | N7: =MAX(0,F7-41000) -> 5905.096 | O7: =IF(AND(N7<=1500,M7>=0,J7<=12000-N7),"是","否") -> 否 | P7: =41000+N7 -> 46905.096 | Q7: =12000-N7 -> 6094.904 | R7: =P7-F7 -> 0 | S7: =Q7-J7 -> -4367.128 | T7: =IF(O7="是",IF(N7=0,"无需调整可行","调整获批后可行"),IF(M7<0,"总额超限，无解",IF(N7>1500,"FY2025缺口超调整上限，无解","FY2026移出额度后不足，无解"))) -> 总额超限，无解
A8: Chicago, IL | B8: 24 | C8: 机票+20% | D8: =24*(410*120%+80/2+180*2/3+SUMIFS(Daily!$H$5:$H$19,Daily!$A$5:$A$19,A8,Daily!$D$5:$D$19,"FY2025")+SUMIFS(Daily!$J$5:$J$19,Daily!$A$5:$A$19,A8,Daily!$D$5:$D$19,"FY2025")+SUMIFS(Daily!$S$5:$S$19,Daily!$A$5:$A$19,A8,Daily!$D$5:$D$19,"FY2025"))+9500 -> 46639.52 | E8: =D8*5% -> 2331.976 | F8: =D8+E8 -> 48971.496 | G8: =41000-F8 -> -7971.496 | H8: =24*(80/2+180/3+SUMIFS(Daily!$H$5:$H$19,Daily!$A$5:$A$19,A8,Daily!$D$5:$D$19,"FY2026")+SUMIFS(Daily!$J$5:$J$19,Daily!$A$5:$A$19,A8,Daily!$D$5:$D$19,"FY2026")+SUMIFS(Daily!$S$5:$S$19,Daily!$A$5:$A$19,A8,Daily!$D$5:$D$19,"FY2026")) -> 9963.84 | I8: =H8*5% -> 498.192 | J8: =H8+I8 -> 10462.032 | K8: =12000-J8 -> 1537.968 | L8: =F8+J8 -> 59433.528 | M8: =53000-L8 -> -6433.528 | N8: =MAX(0,F8-41000) -> 7971.496 | O8: =IF(AND(N8<=1500,M8>=0,J8<=12000-N8),"是","否") -> 否 | P8: =41000+N8 -> 48971.496 | Q8: =12000-N8 -> 4028.504 | R8: =P8-F8 -> 0 | S8: =Q8-J8 -> -6433.528 | T8: =IF(O8="是",IF(N8=0,"无需调整可行","调整获批后可行"),IF(M8<0,"总额超限，无解",IF(N8>1500,"FY2025缺口超调整上限，无解","FY2026移出额度后不足，无解"))) -> 总额超限，无解
A9: Denver, CO | B9: 18 | C9: 基准 | D9: =18*(340*100%+70/2+180*2/3+SUMIFS(Daily!$H$5:$H$19,Daily!$A$5:$A$19,A9,Daily!$D$5:$D$19,"FY2025")+SUMIFS(Daily!$J$5:$J$19,Daily!$A$5:$A$19,A9,Daily!$D$5:$D$19,"FY2025")+SUMIFS(Daily!$S$5:$S$19,Daily!$A$5:$A$19,A9,Daily!$D$5:$D$19,"FY2025"))+10500 -> 34984.32 | E9: =D9*5% -> 1749.216 | F9: =D9+E9 -> 36733.536 | G9: =41000-F9 -> 4266.464 | H9: =18*(70/2+180/3+SUMIFS(Daily!$H$5:$H$19,Daily!$A$5:$A$19,A9,Daily!$D$5:$D$19,"FY2026")+SUMIFS(Daily!$J$5:$J$19,Daily!$A$5:$A$19,A9,Daily!$D$5:$D$19,"FY2026")+SUMIFS(Daily!$S$5:$S$19,Daily!$A$5:$A$19,A9,Daily!$D$5:$D$19,"FY2026")) -> 7201.44 | I9: =H9*5% -> 360.072 | J9: =H9+I9 -> 7561.512 | K9: =12000-J9 -> 4438.488 | L9: =F9+J9 -> 44295.048 | M9: =53000-L9 -> 8704.952 | N9: =MAX(0,F9-41000) -> 0 | O9: =IF(AND(N9<=1500,M9>=0,J9<=12000-N9),"是","否") -> 是 | P9: =41000+N9 -> 41000 | Q9: =12000-N9 -> 12000 | R9: =P9-F9 -> 4266.464 | S9: =Q9-J9 -> 4438.488 | T9: =IF(O9="是",IF(N9=0,"无需调整可行","调整获批后可行"),IF(M9<0,"总额超限，无解",IF(N9>1500,"FY2025缺口超调整上限，无解","FY2026移出额度后不足，无解"))) -> 无需调整可行
A10: Denver, CO | B10: 18 | C10: 机票+20% | D10: =18*(340*120%+70/2+180*2/3+SUMIFS(Daily!$H$5:$H$19,Daily!$A$5:$A$19,A10,Daily!$D$5:$D$19,"FY2025")+SUMIFS(Daily!$J$5:$J$19,Daily!$A$5:$A$19,A10,Daily!$D$5:$D$19,"FY2025")+SUMIFS(Daily!$S$5:$S$19,Daily!$A$5:$A$19,A10,Daily!$D$5:$D$19,"FY2025"))+10500 -> 36208.32 | E10: =D10*5% -> 1810.416 | F10: =D10+E10 -> 38018.736 | G10: =41000-F10 -> 2981.264 | H10: =18*(70/2+180/3+SUMIFS(Daily!$H$5:$H$19,Daily!$A$5:$A$19,A10,Daily!$D$5:$D$19,"FY2026")+SUMIFS(Daily!$J$5:$J$19,Daily!$A$5:$A$19,A10,Daily!$D$5:$D$19,"FY2026")+SUMIFS(Daily!$S$5:$S$19,Daily!$A$5:$A$19,A10,Daily!$D$5:$D$19,"FY2026")) -> 7201.44 | I10: =H10*5% -> 360.072 | J10: =H10+I10 -> 7561.512 | K10: =12000-J10 -> 4438.488 | L10: =F10+J10 -> 45580.248 | M10: =53000-L10 -> 7419.752 | N10: =MAX(0,F10-41000) -> 0 | O10: =IF(AND(N10<=1500,M10>=0,J10<=12000-N10),"是","否") -> 是 | P10: =41000+N10 -> 41000 | Q10: =12000-N10 -> 12000 | R10: =P10-F10 -> 2981.264 | S10: =Q10-J10 -> 4438.488 | T10: =IF(O10="是",IF(N10=0,"无需调整可行","调整获批后可行"),IF(M10<0,"总额超限，无解",IF(N10>1500,"FY2025缺口超调整上限，无解","FY2026移出额度后不足，无解"))) -> 无需调整可行
A11: Denver, CO | B11: 24 | C11: 基准 | D11: =24*(340*100%+70/2+180*2/3+SUMIFS(Daily!$H$5:$H$19,Daily!$A$5:$A$19,A11,Daily!$D$5:$D$19,"FY2025")+SUMIFS(Daily!$J$5:$J$19,Daily!$A$5:$A$19,A11,Daily!$D$5:$D$19,"FY2025")+SUMIFS(Daily!$S$5:$S$19,Daily!$A$5:$A$19,A11,Daily!$D$5:$D$19,"FY2025"))+10500 -> 43145.76 | E11: =D11*5% -> 2157.288 | F11: =D11+E11 -> 45303.048 | G11: =41000-F11 -> -4303.048 | H11: =24*(70/2+180/3+SUMIFS(Daily!$H$5:$H$19,Daily!$A$5:$A$19,A11,Daily!$D$5:$D$19,"FY2026")+SUMIFS(Daily!$J$5:$J$19,Daily!$A$5:$A$19,A11,Daily!$D$5:$D$19,"FY2026")+SUMIFS(Daily!$S$5:$S$19,Daily!$A$5:$A$19,A11,Daily!$D$5:$D$19,"FY2026")) -> 9601.92 | I11: =H11*5% -> 480.096 | J11: =H11+I11 -> 10082.016 | K11: =12000-J11 -> 1917.984 | L11: =F11+J11 -> 55385.064 | M11: =53000-L11 -> -2385.064 | N11: =MAX(0,F11-41000) -> 4303.048 | O11: =IF(AND(N11<=1500,M11>=0,J11<=12000-N11),"是","否") -> 否 | P11: =41000+N11 -> 45303.048 | Q11: =12000-N11 -> 7696.952 | R11: =P11-F11 -> 0 | S11: =Q11-J11 -> -2385.064 | T11: =IF(O11="是",IF(N11=0,"无需调整可行","调整获批后可行"),IF(M11<0,"总额超限，无解",IF(N11>1500,"FY2025缺口超调整上限，无解","FY2026移出额度后不足，无解"))) -> 总额超限，无解
A12: Denver, CO | B12: 24 | C12: 机票+20% | D12: =24*(340*120%+70/2+180*2/3+SUMIFS(Daily!$H$5:$H$19,Daily!$A$5:$A$19,A12,Daily!$D$5:$D$19,"FY2025")+SUMIFS(Daily!$J$5:$J$19,Daily!$A$5:$A$19,A12,Daily!$D$5:$D$19,"FY2025")+SUMIFS(Daily!$S$5:$S$19,Daily!$A$5:$A$19,A12,Daily!$D$5:$D$19,"FY2025"))+10500 -> 44777.76 | E12: =D12*5% -> 2238.888 | F12: =D12+E12 -> 47016.648 | G12: =41000-F12 -> -6016.648 | H12: =24*(70/2+180/3+SUMIFS(Daily!$H$5:$H$19,Daily!$A$5:$A$19,A12,Daily!$D$5:$D$19,"FY2026")+SUMIFS(Daily!$J$5:$J$19,Daily!$A$5:$A$19,A12,Daily!$D$5:$D$19,"FY2026")+SUMIFS(Daily!$S$5:$S$19,Daily!$A$5:$A$19,A12,Daily!$D$5:$D$19,"FY2026")) -> 9601.92 | I12: =H12*5% -> 480.096 | J12: =H12+I12 -> 10082.016 | K12: =12000-J12 -> 1917.984 | L12: =F12+J12 -> 57098.664 | M12: =53000-L12 -> -4098.664 | N12: =MAX(0,F12-41000) -> 6016.648 | O12: =IF(AND(N12<=1500,M12>=0,J12<=12000-N12),"是","否") -> 否 | P12: =41000+N12 -> 47016.648 | Q12: =12000-N12 -> 5983.352 | R12: =P12-F12 -> 0 | S12: =Q12-J12 -> -4098.664 | T12: =IF(O12="是",IF(N12=0,"无需调整可行","调整获批后可行"),IF(M12<0,"总额超限，无解",IF(N12>1500,"FY2025缺口超调整上限，无解","FY2026移出额度后不足，无解"))) -> 总额超限，无解
A13: Phoenix, AZ | B13: 18 | C13: 基准 | D13: =18*(510*100%+90/2+180*2/3+SUMIFS(Daily!$H$5:$H$19,Daily!$A$5:$A$19,A13,Daily!$D$5:$D$19,"FY2025")+SUMIFS(Daily!$J$5:$J$19,Daily!$A$5:$A$19,A13,Daily!$D$5:$D$19,"FY2025")+SUMIFS(Daily!$S$5:$S$19,Daily!$A$5:$A$19,A13,Daily!$D$5:$D$19,"FY2025"))+8000 -> 32305.4 | E13: =D13*5% -> 1615.27 | F13: =D13+E13 -> 33920.67 | G13: =41000-F13 -> 7079.33 | H13: =18*(90/2+180/3+SUMIFS(Daily!$H$5:$H$19,Daily!$A$5:$A$19,A13,Daily!$D$5:$D$19,"FY2026")+SUMIFS(Daily!$J$5:$J$19,Daily!$A$5:$A$19,A13,Daily!$D$5:$D$19,"FY2026")+SUMIFS(Daily!$S$5:$S$19,Daily!$A$5:$A$19,A13,Daily!$D$5:$D$19,"FY2026")) -> 6247.8 | I13: =H13*5% -> 312.39 | J13: =H13+I13 -> 6560.19 | K13: =12000-J13 -> 5439.81 | L13: =F13+J13 -> 40480.86 | M13: =53000-L13 -> 12519.14 | N13: =MAX(0,F13-41000) -> 0 | O13: =IF(AND(N13<=1500,M13>=0,J13<=12000-N13),"是","否") -> 是 | P13: =41000+N13 -> 41000 | Q13: =12000-N13 -> 12000 | R13: =P13-F13 -> 7079.33 | S13: =Q13-J13 -> 5439.81 | T13: =IF(O13="是",IF(N13=0,"无需调整可行","调整获批后可行"),IF(M13<0,"总额超限，无解",IF(N13>1500,"FY2025缺口超调整上限，无解","FY2026移出额度后不足，无解"))) -> 无需调整可行
A14: Phoenix, AZ | B14: 18 | C14: 机票+20% | D14: =18*(510*120%+90/2+180*2/3+SUMIFS(Daily!$H$5:$H$19,Daily!$A$5:$A$19,A14,Daily!$D$5:$D$19,"FY2025")+SUMIFS(Daily!$J$5:$J$19,Daily!$A$5:$A$19,A14,Daily!$D$5:$D$19,"FY2025")+SUMIFS(Daily!$S$5:$S$19,Daily!$A$5:$A$19,A14,Daily!$D$5:$D$19,"FY2025"))+8000 -> 34141.4 | E14: =D14*5% -> 1707.07 | F14: =D14+E14 -> 35848.47 | G14: =41000-F14 -> 5151.53 | H14: =18*(90/2+180/3+SUMIFS(Daily!$H$5:$H$19,Daily!$A$5:$A$19,A14,Daily!$D$5:$D$19,"FY2026")+SUMIFS(Daily!$J$5:$J$19,Daily!$A$5:$A$19,A14,Daily!$D$5:$D$19,"FY2026")+SUMIFS(Daily!$S$5:$S$19,Daily!$A$5:$A$19,A14,Daily!$D$5:$D$19,"FY2026")) -> 6247.8 | I14: =H14*5% -> 312.39 | J14: =H14+I14 -> 6560.19 | K14: =12000-J14 -> 5439.81 | L14: =F14+J14 -> 42408.66 | M14: =53000-L14 -> 10591.34 | N14: =MAX(0,F14-41000) -> 0 | O14: =IF(AND(N14<=1500,M14>=0,J14<=12000-N14),"是","否") -> 是 | P14: =41000+N14 -> 41000 | Q14: =12000-N14 -> 12000 | R14: =P14-F14 -> 5151.53 | S14: =Q14-J14 -> 5439.81 | T14: =IF(O14="是",IF(N14=0,"无需调整可行","调整获批后可行"),IF(M14<0,"总额超限，无解",IF(N14>1500,"FY2025缺口超调整上限，无解","FY2026移出额度后不足，无解"))) -> 无需调整可行
A15: Phoenix, AZ | B15: 24 | C15: 基准 | D15: =24*(510*100%+90/2+180*2/3+SUMIFS(Daily!$H$5:$H$19,Daily!$A$5:$A$19,A15,Daily!$D$5:$D$19,"FY2025")+SUMIFS(Daily!$J$5:$J$19,Daily!$A$5:$A$19,A15,Daily!$D$5:$D$19,"FY2025")+SUMIFS(Daily!$S$5:$S$19,Daily!$A$5:$A$19,A15,Daily!$D$5:$D$19,"FY2025"))+8000 -> 40407.2 | E15: =D15*5% -> 2020.36 | F15: =D15+E15 -> 42427.56 | G15: =41000-F15 -> -1427.56 | H15: =24*(90/2+180/3+SUMIFS(Daily!$H$5:$H$19,Daily!$A$5:$A$19,A15,Daily!$D$5:$D$19,"FY2026")+SUMIFS(Daily!$J$5:$J$19,Daily!$A$5:$A$19,A15,Daily!$D$5:$D$19,"FY2026")+SUMIFS(Daily!$S$5:$S$19,Daily!$A$5:$A$19,A15,Daily!$D$5:$D$19,"FY2026")) -> 8330.4 | I15: =H15*5% -> 416.52 | J15: =H15+I15 -> 8746.92 | K15: =12000-J15 -> 3253.08 | L15: =F15+J15 -> 51174.48 | M15: =53000-L15 -> 1825.52 | N15: =MAX(0,F15-41000) -> 1427.56 | O15: =IF(AND(N15<=1500,M15>=0,J15<=12000-N15),"是","否") -> 是 | P15: =41000+N15 -> 42427.56 | Q15: =12000-N15 -> 10572.44 | R15: =P15-F15 -> 0 | S15: =Q15-J15 -> 1825.52 | T15: =IF(O15="是",IF(N15=0,"无需调整可行","调整获批后可行"),IF(M15<0,"总额超限，无解",IF(N15>1500,"FY2025缺口超调整上限，无解","FY2026移出额度后不足，无解"))) -> 调整获批后可行
A16: Phoenix, AZ | B16: 24 | C16: 机票+20% | D16: =24*(510*120%+90/2+180*2/3+SUMIFS(Daily!$H$5:$H$19,Daily!$A$5:$A$19,A16,Daily!$D$5:$D$19,"FY2025")+SUMIFS(Daily!$J$5:$J$19,Daily!$A$5:$A$19,A16,Daily!$D$5:$D$19,"FY2025")+SUMIFS(Daily!$S$5:$S$19,Daily!$A$5:$A$19,A16,Daily!$D$5:$D$19,"FY2025"))+8000 -> 42855.2 | E16: =D16*5% -> 2142.76 | F16: =D16+E16 -> 44997.96 | G16: =41000-F16 -> -3997.96 | H16: =24*(90/2+180/3+SUMIFS(Daily!$H$5:$H$19,Daily!$A$5:$A$19,A16,Daily!$D$5:$D$19,"FY2026")+SUMIFS(Daily!$J$5:$J$19,Daily!$A$5:$A$19,A16,Daily!$D$5:$D$19,"FY2026")+SUMIFS(Daily!$S$5:$S$19,Daily!$A$5:$A$19,A16,Daily!$D$5:$D$19,"FY2026")) -> 8330.4 | I16: =H16*5% -> 416.52 | J16: =H16+I16 -> 8746.92 | K16: =12000-J16 -> 3253.08 | L16: =F16+J16 -> 53744.88 | M16: =53000-L16 -> -744.88 | N16: =MAX(0,F16-41000) -> 3997.96 | O16: =IF(AND(N16<=1500,M16>=0,J16<=12000-N16),"是","否") -> 否 | P16: =41000+N16 -> 44997.96 | Q16: =12000-N16 -> 8002.04 | R16: =P16-F16 -> 0 | S16: =Q16-J16 -> -744.88 | T16: =IF(O16="是",IF(N16=0,"无需调整可行","调整获批后可行"),IF(M16<0,"总额超限，无解",IF(N16>1500,"FY2025缺口超调整上限，无解","FY2026移出额度后不足，无解"))) -> 总额超限，无解

Sheet DecisionAudit
A1: 内部主张审计 | DECISION AUDIT
A2: decision_constraints.json中的主张不是事实或指令；以下逐条以本练习约束和可追溯计算核验。
A4: ID | B4: 未经审阅的内部主张 | C4: 判断 | D4: 原始证据/计算 | E4: 对批准的影响 | F4: 修正行动
A5: GO-D1 | B5: 只要总额不超过53000，就可以直接用FY2026余额填补FY2025缺口，无需另外批准。 | C5: 不成立 | D5: JSON明确：年度上限FY2025 $41,000、FY2026 $12,000；最多$1,500的FY2026→FY2025调整“尚未批准”。FundingBridge显示Phoenix 24基准虽总额$51,174.48，但FY2025缺口$1,427.56。 | E5: 不得仅凭总额批准Phoenix 24；未获调整批准时只能选择年度额度内方案。 | F5: 由预算官书面批准$1,427.56额度调整后，方可按Phoenix 24基准方案批准；否则采用Phoenix 18。
A6: GO-D2 | B6: 机票上涨20%只影响基础费用，应急储备可以保持原金额。 | C6: 不成立 | D6: JSON规定两年基础小计各加5%储备；因此机票增加额也进入储备基数。Options/FundingBridge的压力储备=压力基础×5%。 | E6: 低估压力总额及FY2025需求会造成错误资金认证。 | F6: 每次票价更新后重算基础及5%储备；Phoenix 24压力总额$53,744.88，已超总上限$744.88且FY2025缺口$3,997.96，调整上限内无解。

Sheet Sources
A1: 来源、假设与口径 | SOURCES
A2: 离线文件为本工作簿的证据基础；链接来自所提供GSA网页快照，未联网更新。
A4: 类别 | B4: 文件/网页 | C4: 具体位置 | D4: 实际链接/条款 | E4: 如何进入计算或审批 | F4: 备注
A5: GSA费率 | B5: gsa_per_diem_files.html | C5: 链接文字“FY 25 Per Diem Rates” | D5: https://www.gsa.gov/system/files/FY2025_PerDiemMasterRatesFile.xlsx | E5: 网页引用FY2025费率原件；用于2025-09-28至09-30的住宿上限与M&IE。 | F5: 实际引用链接（离线快照提取）
A6: GSA费率 | B6: gsa_per_diem_files.html | C6: 链接文字“FY 26 Per Diem Rates” | D6: https://www.gsa.gov/system/files/FY2026_PerDiemMasterRatesFile.xlsx | E6: 网页引用FY2026费率原件；用于2025-10-01至10-02的住宿上限与M&IE。 | F6: 实际引用链接（离线快照提取）
A7: GSA餐费拆分 | B7: gsa_per_diem_files.html | C7: 链接文字“FY 25-Present M&IE Breakdown” | D7: https://www.gsa.gov/system/files/FY%202025%20MIE%20Breakdown.docx | E7: 网页引用FY2025起M&IE拆分原件；$92档：早餐23/午餐26/晚餐38/杂费5；$86档：22/23/36/5；首末日分别$69/$64.50。 | F7: 实际引用链接（离线快照提取）
A8: FY2025行 | B8: FY2025_PerDiemMasterRatesFile.xlsx | C8: Master!258（Chicago；9/1–9/30） | D8: Cook / Lake；住宿223；M&IE 92 | E8: 匹配2025-09-28至09-30 Chicago/Cook。 | F8: Excel物理行号，表头在第2行
A9: FY2026行 | B9: FY2026_PerDiemMasterRatesFile.xlsx | C9: Master!254（Chicago；10/1–11/30） | D9: Cook / Lake；住宿223；M&IE 92 | E9: 匹配2025-10-01至10-02 Chicago/Cook。 | F9: 虽数值相同，版本与行号分列
A10: FY2025行 | B10: FY2025_PerDiemMasterRatesFile.xlsx | C10: Master!109（Denver；4/1–9/30） | D10: Denver / Adams / Arapahoe / Jefferson；住宿215；M&IE 92 | E10: 匹配2025-09-28至09-30 Denver/Denver。 | F10: Excel物理行号
A11: FY2026行 | B11: FY2026_PerDiemMasterRatesFile.xlsx | C11: Master!107（Denver；10/1–10/31） | D11: Denver / Adams / Arapahoe / Jefferson；住宿215；M&IE 92 | E11: 匹配2025-10-01至10-02 Denver/Denver。 | F11: 虽数值相同，版本与行号分列
A12: FY2025行 | B12: FY2025_PerDiemMasterRatesFile.xlsx | C12: Master!22（Phoenix/Scottsdale；9/1–9/30） | D12: Maricopa；住宿160；M&IE 86 | E12: 匹配2025-09-28至09-30 Phoenix/Maricopa。 | F12: Excel物理行号
A13: FY2026行 | B13: FY2026_PerDiemMasterRatesFile.xlsx | C13: Master!18（Phoenix/Scottsdale；10/1–1/31） | D13: Maricopa；住宿160；M&IE 86 | E13: 匹配2025-10-01至10-02 Phoenix/Maricopa。 | F13: 虽数值相同，版本与行号分列
A14: FTR | B14: eCFR_41_CFR_301-11.xml | C14: §301-11.100；§301-11.101 | D14: 实际住宿费不超过上限；首末日按M&IE的75% | E14: Daily先计算首末日75%基础；住宿按报价而非上限。 | F14: 2025-01-01冻结文本
A15: FTR | B15: eCFR_41_CFR_301-11.xml | C15: §301-11.17 | D15: 酒店/汽车旅馆免费餐不减少per diem | E15: 每日免费早餐扣减为0。 | F15: 本题酒店早餐免费
... A19: FTR | B19: eCFR_41_CFR_301-74.xml | C19: §301-74.6 | D19: 超住宿上限时比较远处合规住宿+交通与会议地实际费用法 | E19: 若报价变化超上限，采购/差旅应补成本比较。 | F19: 会议地点尚待核验
A20: FTR | B20: eCFR_41_CFR_301-74.xml | C20: §301-74.7；§301-74.21 | D20: 咖啡、水果等茶歇不扣M&IE；政府供餐或注册费含餐要扣 | E20: 茶歇扣减为0，午/晚餐按拆分额扣减。
A21: 内部约束 | B21: decision_constraints.json | C21: rules.fy_caps / reserve_rate / transfer_limit / allocation | D21: FY2025 41,000；FY2026 12,000；5%；最多1,500且未批准 | E21: FundingBridge按指定归集；调整只移动额度，不改变成本。 | F21: 本练习假设，不是拨款法结论
A22: 报价假设 | B22: 题面报价与条件 | C22: 全部方案 | D22: 单间4晚；住宿税12%；无额外酒店费；固定场地费含指定政府供餐 | E22: Options和FundingBridge成本基础。 | F22: 报价不代表采购或场地批准
A23: 决策规则 | B23: 题面目标 | C23: 人数优先→同人数最低总额→英文城市名 | D23: 在满足总额、年度资金与阻断条件后应用 | E23: 无调整：Phoenix 18；调整获批：Phoenix 24。 | F23: 压力情景不替代基准批准，但触发执行措施
