Workbook

Sheet ControlPanel
A1: Credit Review Control Panel
A2: Blue cells are editable model inputs. Static Word/CSV snapshots reflect only default inputs and unchanged source amounts.
A4: Input | B4: Value | C4: Rule / status
A5: Start period | B5: 20240630 | C5: Existing YYYYMMDD quarter; must precede end
A6: End period | B6: 20250630 | C6: Existing YYYYMMDD quarter; must follow start
A7: Review slots | B7: 8 | C7: Integer 3–12
A9: Model valid | B9: =AND(COUNTIF(RawFinancials!$W$5:$W$750,$B$5)>0,COUNTIF(RawFinancials!$W$5:$W$750,$B$6)>0,$B$5<$B$6,ISNUMBER($B$7),$B$7=INT($B$7),$B$7>=3,$B$7<=12,COUNTIFS(BankQuarter!$D$5:$D$750,$B$6,BankQuarter!$R$5:$R$750,TRUE())>=$B$7,COUNTIFS(BankQuarter!$D$5:$D$750,$B$6,BankQuarter!$E$5:$E$750,"VT",BankQuarter!$R$5:$R$750,TRUE())>0,COUNTIFS(BankQuarter!$D$5:$D$750,$B$6,BankQuarter!$E$5:$E$750,"NH",BankQuarter!$R$5:$R$750,TRUE())>0,COUNTIFS(BankQuarter!$D$5:$D$750,$B$6,BankQuarter!$E$5:$E$750,"ME",BankQuarter!$R$5:$R$750,TRUE())>0) -> TRUE | C9: FALSE clears all priority outputs
A10: Raw amounts unchanged | B10: =COUNTIF(BankQuarter!$T$5:$T$750,TRUE())=0 -> TRUE | C10: Exact comparison for ASSET, P9ASSET, NAASSET; blank differs from 0
A11: Static snapshot current | B11: =AND($B$5=20240630,$B$6=20250630,$B$7=8,$B$10) -> TRUE | C11: TRUE only for default inputs and unchanged raw amounts
A13: Interpretation
A14: If MODEL VALID is FALSE, correct the period/order/slot inputs or ensure the end period has enough valid banks and at least one valid bank in each state. Priority names and count are automatically cleared. Parameter or raw-amount changes do not update the static memo or follow-up CSV; re-export them. Amount corrections are an internal verified-copy scenario and do not assert the public source was wrong.

Sheet RawFinancials
A1: Raw Financials — Editable Local Copy
A2: 746 source records in original order. Only ASSET, P9ASSET and NAASSET are unlocked; blanks remain distinct from numeric zero.
A4: source_row | B4: ASSET | C4: CERT | D4: DEP | E4: ELNATRY | F4: EQ | G4: EQV | H4: ID | I4: LNATRESR | J4: LNCI | K4: LNCON | L4: LNLSGR | M4: LNLSNET | N4: LNRE | O4: NAASSET | P4: NAMEFULL | Q4: NCLNLSR | R4: NIMY | S4: NTLNLS | T4: P3ASSET | U4: P9ASSET | V4: RBCRWAJ | W4: REPDTE | X4: ROA | Y4: ROE | Z4: STALP
A5: 2 | B5: 3688993 | C5: 11971 | D5: 3055632 | E5: 0.08 | F5: 461681 | G5: 12.515095582995142 | H5: 11971_20220331 | I5: 0.8726555144377637 | J5: 201303 | K5: 7873 | L5: 2657406 | M5: 2634216 | N5: 2317079 | O5: 9213 | P5: BAR HARBOR BANK & TRUST | Q5: 0.3784141376966862 | R5: 3.006742138500755 | S5: -95 | T5: 4642 | U5: 843 | V5: 13.678961 | W5: 20220331 | X5: 1.1162343 | Y5: 8.77 | Z5: ME
A6: 3 | B6: 964163 | C6: 12874 | D6: 854194 | E6: 0 | F6: 97916 | G6: 10.155544238889068 | H6: 12874_20220331 | I6: 1.0653480801084996 | J6: 138143 | K6: 5249 | L6: 732906 | M6: 725098 | N6: 577596 | O6: 1069 | P6: KATAHDIN TRUST COMPANY | Q6: 0.14585772254559248 | R6: 3.4019504411499137 | S6: -5 | T6: 374 | U6: 0 | V6: 15.601603 | W6: 20220331 | X6: 0.83149732 | Y6: 7.95 | Z6: ME
A7: 4 | B7: 1784835 | C7: 13063 | D7: 1619076 | E7: 0 | F7: 148181 | G7: 8.302224015105038 | H7: 13063_20220331 | I7: 1.2180099706634604 | J7: 55361 | K7: 837 | L7: 1223389 | M7: 1208488 | N7: 1160807 | O7: 408 | P7: KENNEBUNK SAVINGS BANK | Q7: 0.13111120011705188 | R7: 3.2711147741028457 | S7: -5 | T7: 3 | U7: 1196 | V7: 0 | W7: 20220331 | X7: 0.48237313 | Y7: 5.56 | Z7: ME
A8: 5 | B8: 869402 | C8: 14134 | D8: 737795 | E8: 0.1 | F8: 101808 | G8: 11.710117989146562 | H8: 14134_20220331 | I8: 1.4014366486247207 | J8: 27870 | K8: 26813 | L8: 596388 | M8: 588030 | N8: 516229 | O8: 8014 | P8: PASSUMPSIC SAVINGS BANK | Q8: 1.3437560782577784 | R8: 2.742437977347796 | S8: 19 | T8: 4990 | U8: 0 | V8: 17.570983 | W8: 20220331 | X8: -0.38729339 | Y8: -3.23 | Z8: VT
A9: 6 | B9: 222692 | C9: 14136 | D9: 199279 | E9: 0.08 | F9: 18834 | G9: 8.457421011980673 | H9: 14136_20220331 | I9: 1.1501745063903168 | J9: 12518 | K9: 11422 | L9: 121199 | M9: 119805 | N9: 96809 | O9: 174 | P9: WELLS RIVER SAVINGS BANK | Q9: 0.6707976138416983 | R9: 3.4223699758291275 | S9: 7 | T9: 803 | U9: 639 | V9: 17.27622 | W9: 20220331 | X9: 0.19954922 | Y9: 2.14 | Z9: VT
A10: 7 | B10: 1414510 | C10: 14140 | D10: 1199427 | E10: 0 | F10: 123854 | G10: 8.75596496313211 | H10: 14140_20220331 | I10: 1.1077738349896176 | J10: 82518 | K10: 1318 | L10: 957867 | M10: 947256 | N10: 866005 | O10: 5589 | P10: NORTHFIELD SAVINGS BANK | Q10: 0.58348392835331 | R10: 2.9698131336094122 | S10: 9 | T10: 785 | U10: 0 | V10: 0 | W10: 20220331 | X10: 0.66212632 | Y10: 7.07 | Z10: VT
A11: 8 | B11: 1232701 | C11: 14158 | D11: 1137254 | E11: 0 | F11: 85105 | G11: 6.9039450767055435 | H11: 14158_20220331 | I11: 1.0031734264943204 | J11: 44549 | K11: 2157 | L11: 830963 | M11: 822627 | N11: 698008 | O11: 4405 | P11: UNION BANK | Q11: 0.5576662258127016 | R11: 3.185373520467468 | S11: 0 | T11: 1620 | U11: 229 | V11: 14.788126 | W11: 20220331 | X11: 0.88329132 | Y11: 11.64 | Z11: VT
A12: 9 | B12: 384095 | C12: 14168 | D12: 345364 | E12: 0 | F12: 34244 | G12: 8.915502675119438 | H12: 14168_20220331 | I12: 1.5327875284455024 | J12: 9537 | K12: 8111 | L12: 191155 | M12: 188225 | N12: 161619 | O12: 1188 | P12: PEOPLES TRUST COMPANY OF ST. ALBANS | Q12: 0.6214851821819989 | R12: 2.4184590804383865 | S12: 34 | T12: 187 | U12: 0 | V12: 19.824643 | W12: 20220331 | X12: 0.13578832 | Y12: 1.45 | Z12: VT
A13: 10 | B13: 1221074 | C13: 14240 | D13: 1020645 | E13: 0 | F13: 102113 | G13: 8.36255624147267 | H13: 14240_20220331 | I13: 1.1483381231280392 | J13: 29648 | K13: 17990 | L13: 824670 | M13: 815200 | N13: 705835 | O13: 2204 | P13: NORTHWAY BANK | Q13: 0.26725841851892274 | R13: 2.8194207261510216 | S13: -4 | T13: 1936 | U13: 0 | V13: 15.106992 | W13: 20220331 | X13: 0.069811881 | Y13: 0.79 | Z13: NH
A14: 11 | B14: 836644 | C14: 17115 | D14: 738943 | E14: -0.08 | F14: 83239 | G14: 9.949154000984887 | H14: 17115_20220331 | I14: 1.1671320266694696 | J14: 43003 | K14: 3606 | L14: 656481 | M14: 648819 | N14: 608827 | O14: 164 | P14: PARTNERS BANK OF NEW ENGLAND | Q14: 0.02498168263818755 | R14: 3.5126361724170407 | S14: 240 | T14: 62 | U14: 0 | V14: 15.606469 | W14: 20220331 | X14: 1.1149693 | Y14: 11.05 | Z14: ME
A15: 12 | B15: 1291920 | C15: 17180 | D15: 1121172 | E15: 0.06 | F15: 126979 | G15: 9.828704563750078 | H15: 17180_20220331 | I15: 0.9861620605817762 | J15: 44797 | K15: 141431 | L15: 1143017 | M15: 1131745 | N15: 937482 | O15: 5753 | P15: MEREDITH VILLAGE SAVINGS BANK | Q15: 0.5033170985208444 | R15: 3.569993155239652 | S15: 36 | T15: 1540 | U15: 0 | V15: 16.056943 | W15: 20220331 | X15: 0.80278929 | Y15: 8.11 | Z15: NH
A16: 13 | B16: 352255 | C16: 17443 | D16: 302135 | E16: 0.06 | F16: 42822 | G16: 12.15653432882429 | H16: 17443_20220331 | I16: 0.858419069393285 | J16: 0 | K16: 1909 | L16: 188952 | M16: 187330 | N16: 186037 | O16: 842 | P16: PISCATAQUA SAVINGS BANK | Q16: 0.44561581777382614 | R16: 2.012217920234347 | S16: 0 | T16: 2524 | U16: 0 | V16: 0 | W16: 20220331 | X16: 0.61925341 | Y16: 4.79 | Z16: NH
... A750: 747 | B750: 87770 | C750: 6280 | D750: 77256 | E750: 0.09 | F750: 9949 | G750: 11.335308191865103 | H750: 6280_20250630 | I750: 1.2995896032831737 | J750: 3899 | K750: 1311 | L750: 73100 | M750: 72150 | N750: 64947 | O750: 1455 | P750: THE FIRST NATIONAL BANK OF ORWELL | Q750: 1.990424076607387 | R750: 4.539434075857917 | S750: 0 | T750: 592 | U750: 0 | V750: 0 | W750: 20250630 | X750: 1.3665403 | Y750: 12.13 | Z750: VT

Sheet _RawBaseline
A1: source_row | B1: ASSET | C1: CERT | D1: DEP | E1: ELNATRY | F1: EQ | G1: EQV | H1: ID | I1: LNATRESR | J1: LNCI | K1: LNCON | L1: LNLSGR | M1: LNLSNET | N1: LNRE | O1: NAASSET | P1: NAMEFULL | Q1: NCLNLSR | R1: NIMY | S1: NTLNLS | T1: P3ASSET | U1: P9ASSET | V1: RBCRWAJ | W1: REPDTE | X1: ROA | Y1: ROE | Z1: STALP
A2: 2 | B2: 3688993 | C2: 11971 | D2: 3055632 | E2: 0.08 | F2: 461681 | G2: 12.515095582995142 | H2: 11971_20220331 | I2: 0.8726555144377637 | J2: 201303 | K2: 7873 | L2: 2657406 | M2: 2634216 | N2: 2317079 | O2: 9213 | P2: BAR HARBOR BANK & TRUST | Q2: 0.3784141376966862 | R2: 3.006742138500755 | S2: -95 | T2: 4642 | U2: 843 | V2: 13.678961 | W2: 20220331 | X2: 1.1162343 | Y2: 8.77 | Z2: ME
A3: 3 | B3: 964163 | C3: 12874 | D3: 854194 | E3: 0 | F3: 97916 | G3: 10.155544238889068 | H3: 12874_20220331 | I3: 1.0653480801084996 | J3: 138143 | K3: 5249 | L3: 732906 | M3: 725098 | N3: 577596 | O3: 1069 | P3: KATAHDIN TRUST COMPANY | Q3: 0.14585772254559248 | R3: 3.4019504411499137 | S3: -5 | T3: 374 | U3: 0 | V3: 15.601603 | W3: 20220331 | X3: 0.83149732 | Y3: 7.95 | Z3: ME
A4: 4 | B4: 1784835 | C4: 13063 | D4: 1619076 | E4: 0 | F4: 148181 | G4: 8.302224015105038 | H4: 13063_20220331 | I4: 1.2180099706634604 | J4: 55361 | K4: 837 | L4: 1223389 | M4: 1208488 | N4: 1160807 | O4: 408 | P4: KENNEBUNK SAVINGS BANK | Q4: 0.13111120011705188 | R4: 3.2711147741028457 | S4: -5 | T4: 3 | U4: 1196 | V4: 0 | W4: 20220331 | X4: 0.48237313 | Y4: 5.56 | Z4: ME
A5: 5 | B5: 869402 | C5: 14134 | D5: 737795 | E5: 0.1 | F5: 101808 | G5: 11.710117989146562 | H5: 14134_20220331 | I5: 1.4014366486247207 | J5: 27870 | K5: 26813 | L5: 596388 | M5: 588030 | N5: 516229 | O5: 8014 | P5: PASSUMPSIC SAVINGS BANK | Q5: 1.3437560782577784 | R5: 2.742437977347796 | S5: 19 | T5: 4990 | U5: 0 | V5: 17.570983 | W5: 20220331 | X5: -0.38729339 | Y5: -3.23 | Z5: VT
A6: 6 | B6: 222692 | C6: 14136 | D6: 199279 | E6: 0.08 | F6: 18834 | G6: 8.457421011980673 | H6: 14136_20220331 | I6: 1.1501745063903168 | J6: 12518 | K6: 11422 | L6: 121199 | M6: 119805 | N6: 96809 | O6: 174 | P6: WELLS RIVER SAVINGS BANK | Q6: 0.6707976138416983 | R6: 3.4223699758291275 | S6: 7 | T6: 803 | U6: 639 | V6: 17.27622 | W6: 20220331 | X6: 0.19954922 | Y6: 2.14 | Z6: VT
A7: 7 | B7: 1414510 | C7: 14140 | D7: 1199427 | E7: 0 | F7: 123854 | G7: 8.75596496313211 | H7: 14140_20220331 | I7: 1.1077738349896176 | J7: 82518 | K7: 1318 | L7: 957867 | M7: 947256 | N7: 866005 | O7: 5589 | P7: NORTHFIELD SAVINGS BANK | Q7: 0.58348392835331 | R7: 2.9698131336094122 | S7: 9 | T7: 785 | U7: 0 | V7: 0 | W7: 20220331 | X7: 0.66212632 | Y7: 7.07 | Z7: VT
A8: 8 | B8: 1232701 | C8: 14158 | D8: 1137254 | E8: 0 | F8: 85105 | G8: 6.9039450767055435 | H8: 14158_20220331 | I8: 1.0031734264943204 | J8: 44549 | K8: 2157 | L8: 830963 | M8: 822627 | N8: 698008 | O8: 4405 | P8: UNION BANK | Q8: 0.5576662258127016 | R8: 3.185373520467468 | S8: 0 | T8: 1620 | U8: 229 | V8: 14.788126 | W8: 20220331 | X8: 0.88329132 | Y8: 11.64 | Z8: VT
A9: 9 | B9: 384095 | C9: 14168 | D9: 345364 | E9: 0 | F9: 34244 | G9: 8.915502675119438 | H9: 14168_20220331 | I9: 1.5327875284455024 | J9: 9537 | K9: 8111 | L9: 191155 | M9: 188225 | N9: 161619 | O9: 1188 | P9: PEOPLES TRUST COMPANY OF ST. ALBANS | Q9: 0.6214851821819989 | R9: 2.4184590804383865 | S9: 34 | T9: 187 | U9: 0 | V9: 19.824643 | W9: 20220331 | X9: 0.13578832 | Y9: 1.45 | Z9: VT
A10: 10 | B10: 1221074 | C10: 14240 | D10: 1020645 | E10: 0 | F10: 102113 | G10: 8.36255624147267 | H10: 14240_20220331 | I10: 1.1483381231280392 | J10: 29648 | K10: 17990 | L10: 824670 | M10: 815200 | N10: 705835 | O10: 2204 | P10: NORTHWAY BANK | Q10: 0.26725841851892274 | R10: 2.8194207261510216 | S10: -4 | T10: 1936 | U10: 0 | V10: 15.106992 | W10: 20220331 | X10: 0.069811881 | Y10: 0.79 | Z10: NH
A11: 11 | B11: 836644 | C11: 17115 | D11: 738943 | E11: -0.08 | F11: 83239 | G11: 9.949154000984887 | H11: 17115_20220331 | I11: 1.1671320266694696 | J11: 43003 | K11: 3606 | L11: 656481 | M11: 648819 | N11: 608827 | O11: 164 | P11: PARTNERS BANK OF NEW ENGLAND | Q11: 0.02498168263818755 | R11: 3.5126361724170407 | S11: 240 | T11: 62 | U11: 0 | V11: 15.606469 | W11: 20220331 | X11: 1.1149693 | Y11: 11.05 | Z11: ME
A12: 12 | B12: 1291920 | C12: 17180 | D12: 1121172 | E12: 0.06 | F12: 126979 | G12: 9.828704563750078 | H12: 17180_20220331 | I12: 0.9861620605817762 | J12: 44797 | K12: 141431 | L12: 1143017 | M12: 1131745 | N12: 937482 | O12: 5753 | P12: MEREDITH VILLAGE SAVINGS BANK | Q12: 0.5033170985208444 | R12: 3.569993155239652 | S12: 36 | T12: 1540 | U12: 0 | V12: 16.056943 | W12: 20220331 | X12: 0.80278929 | Y12: 8.11 | Z12: NH
A13: 13 | B13: 352255 | C13: 17443 | D13: 302135 | E13: 0.06 | F13: 42822 | G13: 12.15653432882429 | H13: 17443_20220331 | I13: 0.858419069393285 | J13: 0 | K13: 1909 | L13: 188952 | M13: 187330 | N13: 186037 | O13: 842 | P13: PISCATAQUA SAVINGS BANK | Q13: 0.44561581777382614 | R13: 2.012217920234347 | S13: 0 | T13: 2524 | U13: 0 | V13: 0 | W13: 20220331 | X13: 0.61925341 | Y13: 4.79 | Z13: NH
... A747: 747 | B747: 87770 | C747: 6280 | D747: 77256 | E747: 0.09 | F747: 9949 | G747: 11.335308191865103 | H747: 6280_20250630 | I747: 1.2995896032831737 | J747: 3899 | K747: 1311 | L747: 73100 | M747: 72150 | N747: 64947 | O747: 1455 | P747: THE FIRST NATIONAL BANK OF ORWELL | Q747: 1.990424076607387 | R747: 4.539434075857917 | S747: 0 | T747: 592 | U747: 0 | V747: 0 | W747: 20250630 | X747: 1.3665403 | Y747: 12.13 | Z747: VT

Sheet InstitutionSnapshot
A1: Institution Snapshot
A2: Later snapshot joined by CERT only; ACTIVE is shown for context and is not used to remove or backfill historical financial records.
A4: CERT | B4: NAME | C4: ACTIVE | D4: REPDTE | E4: DATEUPDT | F4: STALP | G4: Matched financial CERT?
A5: 10 | B5: Northeast Bank of Sanford | C5: 0 | E5: 10/04/1990 | F5: ME | G5: =COUNTIF(BankQuarter!$B$5:$B$750,A5)>0 -> FALSE
A6: 10022 | B6: BankEast National Bank | C6: 0 | E6: 10/04/1990 | F6: NH | G6: =COUNTIF(BankQuarter!$B$5:$B$750,A6)>0 -> FALSE
A7: 10029 | B7: The Island Pond National Bank | C7: 0 | E7: 10/05/1995 | F7: VT | G7: =COUNTIF(BankQuarter!$B$5:$B$750,A7)>0 -> FALSE
A8: 11369 | B8: Aroostook Trust Company | C8: 0 | D8: 09/30/1986 | E8: 10/05/1995 | F8: ME | G8: =COUNTIF(BankQuarter!$B$5:$B$750,A8)>0 -> FALSE
A9: 11372 | B9: Casco Bank & Trust Company | C9: 0 | E9: 10/04/1990 | F9: ME | G9: =COUNTIF(BankQuarter!$B$5:$B$750,A9)>0 -> FALSE
A10: 11485 | B10: North Country Bank | C10: 0 | D10: 03/31/1986 | E10: 10/04/1990 | F10: NH | G10: =COUNTIF(BankQuarter!$B$5:$B$750,A10)>0 -> FALSE
A11: 11486 | B11: Nashua Trust Company | C11: 0 | D11: 06/30/1991 | E11: 08/24/1994 | F11: NH | G11: =COUNTIF(BankQuarter!$B$5:$B$750,A11)>0 -> FALSE
A12: 11970 | B12: Keybank National Association | C12: 0 | D12: 03/31/1997 | E12: 07/21/1997 | F12: ME | G12: =COUNTIF(BankQuarter!$B$5:$B$750,A12)>0 -> FALSE
A13: 11971 | B13: Bar Harbor Bank & Trust | C13: 1 | D13: 06/30/2026 | E13: 09/16/2025 | F13: ME | G13: =COUNTIF(BankQuarter!$B$5:$B$750,A13)>0 -> TRUE
A14: 12003 | B14: Eastport Savings Bank | C14: 0 | E14: 09/14/1995 | F14: ME | G14: =COUNTIF(BankQuarter!$B$5:$B$750,A14)>0 -> FALSE
A15: 12254 | B15: North Conway Bank | C15: 0 | D15: 06/30/1995 | E15: 08/03/1995 | F15: NH | G15: =COUNTIF(BankQuarter!$B$5:$B$750,A15)>0 -> FALSE
A16: 12725 | B16: Livermore Falls Trust Company | C16: 0 | D16: 12/31/1998 | E16: 02/26/1999 | F16: ME | G16: =COUNTIF(BankQuarter!$B$5:$B$750,A16)>0 -> FALSE
A17: 12873 | B17: Pepperell Bank & Trust | C17: 0 | D17: 06/30/2007 | E17: 09/12/2007 | F17: ME | G17: =COUNTIF(BankQuarter!$B$5:$B$750,A17)>0 -> FALSE
A18: 12874 | B18: Katahdin Trust Company | C18: 1 | D18: 06/30/2026 | E18: 11/18/2024 | F18: ME | G18: =COUNTIF(BankQuarter!$B$5:$B$750,A18)>0 -> TRUE
A19: 12878 | B19: 1st Consumers Savings Bank | C19: 0 | E19: 09/11/1995 | F19: ME | G19: =COUNTIF(BankQuarter!$B$5:$B$750,A19)>0 -> FALSE
A20: 13063 | B20: Kennebunk Savings Bank | C20: 1 | D20: 06/30/2026 | E20: 11/18/2024 | F20: ME | G20: =COUNTIF(BankQuarter!$B$5:$B$750,A20)>0 -> TRUE
A21: 13064 | B21: Heritage Savings Bank | C21: 0 | E21: 09/14/1995 | F21: ME | G21: =COUNTIF(BankQuarter!$B$5:$B$750,A21)>0 -> FALSE
A22: 13174 | B22: Federal Trust Company | C22: 0 | D22: 06/30/1984 | E22: 10/04/1990 | F22: ME | G22: =COUNTIF(BankQuarter!$B$5:$B$750,A22)>0 -> FALSE
A23: 13175 | B23: Key Bank of Eastern Maine | C23: 0 | D23: 09/30/1988 | E23: 10/04/1990 | F23: ME | G23: =COUNTIF(BankQuarter!$B$5:$B$750,A23)>0 -> FALSE
A24: 13176 | B24: Northeast Bank of Lincoln | C24: 0 | E24: 05/05/1999 | F24: ME | G24: =COUNTIF(BankQuarter!$B$5:$B$750,A24)>0 -> FALSE
A25: 13288 | B25: South Paris Savings Bank | C25: 0 | E25: 09/20/1995 | F25: ME | G25: =COUNTIF(BankQuarter!$B$5:$B$750,A25)>0 -> FALSE
A26: 13422 | B26: Montpelier National Bank | C26: 0 | E26: 09/12/1997 | F26: VT | G26: =COUNTIF(BankQuarter!$B$5:$B$750,A26)>0 -> FALSE
A27: 13848 | B27: The Enosburg Falls National Bank | C27: 0 | E27: 08/20/1992 | F27: VT | G27: =COUNTIF(BankQuarter!$B$5:$B$750,A27)>0 -> FALSE
A28: 14127 | B28: KeyBank National Association | C28: 0 | D28: 03/31/1997 | E28: 07/21/1997 | F28: VT | G28: =COUNTIF(BankQuarter!$B$5:$B$750,A28)>0 -> FALSE
A29: 14132 | B29: Marble Bank | C29: 0 | D29: 12/31/1995 | E29: 03/15/1996 | F29: VT | G29: =COUNTIF(BankQuarter!$B$5:$B$750,A29)>0 -> FALSE
A30: 14133 | B30: Rutland Savings Bank | C30: 0 | E30: 09/11/1995 | F30: VT | G30: =COUNTIF(BankQuarter!$B$5:$B$750,A30)>0 -> FALSE
A31: 14134 | B31: Passumpsic Savings Bank | C31: 1 | D31: 06/30/2026 | E31: 11/18/2024 | F31: VT | G31: =COUNTIF(BankQuarter!$B$5:$B$750,A31)>0 -> TRUE
A32: 14136 | B32: Wells River Savings Bank | C32: 1 | D32: 06/30/2026 | E32: 11/18/2024 | F32: VT | G32: =COUNTIF(BankQuarter!$B$5:$B$750,A32)>0 -> TRUE
A33: 14140 | B33: Northfield Savings Bank | C33: 1 | D33: 06/30/2026 | E33: 11/18/2024 | F33: VT | G33: =COUNTIF(BankQuarter!$B$5:$B$750,A33)>0 -> TRUE
A34: 14142 | B34: Barre Trust Company | C34: 0 | E34: 06/09/1995 | F34: VT | G34: =COUNTIF(BankQuarter!$B$5:$B$750,A34)>0 -> FALSE
A35: 14143 | B35: Granite Savings Bank and Trust Company | C35: 0 | D35: 03/31/2000 | E35: 08/07/2000 | F35: VT | G35: =COUNTIF(BankQuarter!$B$5:$B$750,A35)>0 -> FALSE
A36: 14146 | B36: Bellows Falls Trust Company | C36: 0 | D36: 03/31/1993 | E36: 05/26/1993 | F36: VT | G36: =COUNTIF(BankQuarter!$B$5:$B$750,A36)>0 -> FALSE
A37: 14147 | B37: First Vermont Bank , National Association | C37: 0 | D37: 12/31/2001 | E37: 01/28/2002 | F37: VT | G37: =COUNTIF(BankQuarter!$B$5:$B$750,A37)>0 -> FALSE
A38: 14149 | B38: Chittenden Trust Company | C38: 0 | D38: 12/31/2008 | E38: 02/19/2009 | F38: VT | G38: =COUNTIF(BankQuarter!$B$5:$B$750,A38)>0 -> FALSE
A39: 14152 | B39: Hardwick Trust Company | C39: 0 | E39: 05/05/1999 | F39: VT | G39: =COUNTIF(BankQuarter!$B$5:$B$750,A39)>0 -> FALSE
A40: 14153 | B40: Lamoille County Bank | C40: 0 | E40: 10/05/1995 | F40: VT | G40: =COUNTIF(BankQuarter!$B$5:$B$750,A40)>0 -> FALSE
A41: 14154 | B41: Sterling Trust Company | C41: 0 | D41: 03/31/1985 | E41: 08/20/1992 | F41: VT | G41: =COUNTIF(BankQuarter!$B$5:$B$750,A41)>0 -> FALSE
A42: 14155 | B42: LyndonBank | C42: 0 | D42: 12/31/2007 | E42: 03/11/2008 | F42: VT | G42: =COUNTIF(BankQuarter!$B$5:$B$750,A42)>0 -> FALSE
A43: 14158 | B43: Union Bank | C43: 1 | D43: 06/30/2026 | E43: 11/18/2024 | F43: VT | G43: =COUNTIF(BankQuarter!$B$5:$B$750,A43)>0 -> TRUE
A44: 14160 | B44: Northfield Trust Company | C44: 0 | E44: 05/05/1999 | F44: VT | G44: =COUNTIF(BankQuarter!$B$5:$B$750,A44)>0 -> FALSE
A45: 14163 | B45: Green Mountain Bank | C45: 0 | D45: 06/30/1997 | E45: 10/18/1997 | F45: VT | G45: =COUNTIF(BankQuarter!$B$5:$B$750,A45)>0 -> FALSE
A46: 14167 | B46: Franklin Lamoille Bank, National Association | C46: 0 | D46: 12/31/2001 | E46: 01/28/2002 | F46: VT | G46: =COUNTIF(BankQuarter!$B$5:$B$750,A46)>0 -> FALSE
A47: 14168 | B47: Peoples Trust Company of St. Albans | C47: 1 | D47: 06/30/2026 | E47: 11/18/2024 | F47: VT | G47: =COUNTIF(BankQuarter!$B$5:$B$750,A47)>0 -> TRUE
A48: 14169 | B48: Citizens Savings Bank and Trust Company | C48: 0 | D48: 03/31/2003 | E48: 06/20/2003 | F48: VT | G48: =COUNTIF(BankQuarter!$B$5:$B$750,A48)>0 -> FALSE
A49: 14170 | B49: Bank of Waterbury | C49: 0 | E49: 05/05/1999 | F49: VT | G49: =COUNTIF(BankQuarter!$B$5:$B$750,A49)>0 -> FALSE
A50: 14171 | B50: First Twin-State Bank | C50: 0 | D50: 06/30/1991 | E50: 08/20/1992 | F50: VT | G50: =COUNTIF(BankQuarter!$B$5:$B$750,A50)>0 -> FALSE
A51: 14240 | B51: Northway Bank | C51: 0 | D51: 12/31/2024 | E51: 01/14/2025 | F51: NH | G51: =COUNTIF(BankQuarter!$B$5:$B$750,A51)>0 -> TRUE
A52: 14889 | B52: The Liberty National Bank in Ellsworth | C52: 0 | E52: 10/04/1990 | F52: ME | G52: =COUNTIF(BankQuarter!$B$5:$B$750,A52)>0 -> FALSE
A53: 15217 | B53: Houlton Savings Bank | C53: 0 | E53: 09/20/1995 | F53: ME | G53: =COUNTIF(BankQuarter!$B$5:$B$750,A53)>0 -> FALSE
A54: 15453 | B54: Houlton Trust Company | C54: 0 | E54: 10/04/1990 | F54: ME | G54: =COUNTIF(BankQuarter!$B$5:$B$750,A54)>0 -> FALSE
A55: 15646 | B55: Peoples National Bank of Groveton | C55: 0 | E55: 10/04/1990 | F55: NH | G55: =COUNTIF(BankQuarter!$B$5:$B$750,A55)>0 -> FALSE
A56: 15952 | B56: BankEast | C56: 0 | D56: 06/30/1991 | E56: 10/24/1991 | F56: NH | G56: =COUNTIF(BankQuarter!$B$5:$B$750,A56)>0 -> FALSE
A57: 16532 | B57: White Mountain Bank and Trust Company | C57: 0 | E57: 10/04/1990 | F57: NH | G57: =COUNTIF(BankQuarter!$B$5:$B$750,A57)>0 -> FALSE
A58: 16927 | B58: Durham Trust Company | C58: 0 | D58: 09/30/1991 | E58: 11/20/1991 | F58: NH | G58: =COUNTIF(BankQuarter!$B$5:$B$750,A58)>0 -> FALSE
A59: 16998 | B59: Brunswick Savings Institution | C59: 0 | E59: 10/17/1995 | F59: ME | G59: =COUNTIF(BankQuarter!$B$5:$B$750,A59)>0 -> FALSE
A60: 17017 | B60: Washburn Trust Company | C60: 0 | E60: 10/04/1990 | F60: ME | G60: =COUNTIF(BankQuarter!$B$5:$B$750,A60)>0 -> FALSE
A61: 17115 | B61: Partners Bank of New England | C61: 1 | D61: 06/30/2026 | E61: 11/18/2024 | F61: ME | G61: =COUNTIF(BankQuarter!$B$5:$B$750,A61)>0 -> TRUE
A62: 17176 | B62: Southeast Bank for Savings | C62: 0 | D62: 12/31/1994 | E62: 04/06/1995 | F62: NH | G62: =COUNTIF(BankQuarter!$B$5:$B$750,A62)>0 -> FALSE
A63: 17178 | B63: Amoskeag Bank | C63: 0 | D63: 06/30/1991 | E63: 10/24/1991 | F63: NH | G63: =COUNTIF(BankQuarter!$B$5:$B$750,A63)>0 -> FALSE
A64: 17179 | B64: Meredith Bank & Trust | C64: 0 | D64: 06/30/1988 | E64: 10/04/1990 | F64: NH | G64: =COUNTIF(BankQuarter!$B$5:$B$750,A64)>0 -> FALSE
A65: 17180 | B65: Meredith Village Savings Bank | C65: 1 | D65: 06/30/2026 | E65: 11/18/2024 | F65: NH | G65: =COUNTIF(BankQuarter!$B$5:$B$750,A65)>0 -> TRUE
A66: 17189 | B66: Iona Savings Bank | C66: 0 | D66: 06/30/1991 | E66: 10/23/1991 | F66: NH | G66: =COUNTIF(BankQuarter!$B$5:$B$750,A66)>0 -> FALSE
A67: 17196 | B67: BankEast Savings Bank | C67: 0 | E67: 09/19/1995 | F67: NH | G67: =COUNTIF(BankQuarter!$B$5:$B$750,A67)>0 -> FALSE
A68: 17218 | B68: Portsmouth Savings Bank | C68: 0 | D68: 06/30/1997 | E68: 09/15/1997 | F68: NH | G68: =COUNTIF(BankQuarter!$B$5:$B$750,A68)>0 -> FALSE
A69: 17235 | B69: City Savings Bank of Laconia, New Hampshire | C69: 0 | E69: 10/12/1995 | F69: NH | G69: =COUNTIF(BankQuarter!$B$5:$B$750,A69)>0 -> FALSE
A70: 17236 | B70: New Hampshire Savings Bank | C70: 0 | D70: 09/30/1990 | E70: 01/14/1991 | F70: NH | G70: =COUNTIF(BankQuarter!$B$5:$B$750,A70)>0 -> FALSE
A71: 17237 | B71: Numerica Savings Bank, FSB | C71: 0 | D71: 09/30/1991 | E71: 10/24/1991 | F71: NH | G71: =COUNTIF(BankQuarter!$B$5:$B$750,A71)>0 -> FALSE
A72: 17238 | B72: Manchester Savings Bank | C72: 0 | E72: 06/08/1995 | F72: NH | G72: =COUNTIF(BankQuarter!$B$5:$B$750,A72)>0 -> FALSE
A73: 17251 | B73: City Savings Bank of Berlin | C73: 0 | E73: 10/04/1990 | F73: NH | G73: =COUNTIF(BankQuarter!$B$5:$B$750,A73)>0 -> FALSE
A74: 17443 | B74: Piscataqua Savings Bank | C74: 1 | D74: 06/30/2026 | E74: 11/18/2024 | F74: NH | G74: =COUNTIF(BankQuarter!$B$5:$B$750,A74)>0 -> TRUE
A75: 17476 | B75: Mechanics' Savings Bank | C75: 0 | D75: 12/31/2019 | E75: 01/07/2020 | F75: ME | G75: =COUNTIF(BankQuarter!$B$5:$B$750,A75)>0 -> FALSE
A76: 17658 | B76: Norway Savings Bank | C76: 1 | D76: 06/30/2026 | E76: 11/18/2024 | F76: ME | G76: =COUNTIF(BankQuarter!$B$5:$B$750,A76)>0 -> TRUE
A77: 17720 | B77: People's Savings Bank | C77: 0 | D77: 12/31/1984 | E77: 09/11/1995 | F77: ME | G77: =COUNTIF(BankQuarter!$B$5:$B$750,A77)>0 -> FALSE
A78: 17721 | B78: Maine Savings Bank | C78: 0 | D78: 12/31/1990 | E78: 02/20/1991 | F78: ME | G78: =COUNTIF(BankQuarter!$B$5:$B$750,A78)>0 -> FALSE
A79: 17729 | B79: Northeast Bank of Westbrook | C79: 0 | E79: 10/05/1995 | F79: ME | G79: =COUNTIF(BankQuarter!$B$5:$B$750,A79)>0 -> FALSE
A80: 17741 | B80: Maine Community Bank | C80: 1 | D80: 06/30/2026 | E80: 07/31/2025 | F80: ME | G80: =COUNTIF(BankQuarter!$B$5:$B$750,A80)>0 -> TRUE
A81: 17742 | B81: York County Savings Bank | C81: 0 | E81: 09/13/1995 | F81: ME | G81: =COUNTIF(BankQuarter!$B$5:$B$750,A81)>0 -> FALSE
A82: 17743 | B82: Saco & Biddeford Savings Institution | C82: 1 | D82: 06/30/2026 | E82: 11/18/2024 | F82: ME | G82: =COUNTIF(BankQuarter!$B$5:$B$750,A82)>0 -> TRUE
A83: 17748 | B83: Gorham Savings Bank | C83: 0 | D83: 12/31/2024 | E83: 01/08/2025 | F83: ME | G83: =COUNTIF(BankQuarter!$B$5:$B$750,A83)>0 -> TRUE
A84: 17749 | B84: Bath Savings Institution | C84: 1 | D84: 06/30/2026 | E84: 11/18/2024 | F84: ME | G84: =COUNTIF(BankQuarter!$B$5:$B$750,A84)>0 -> TRUE
A85: 17751 | B85: Androscoggin Savings Bank | C85: 1 | D85: 06/30/2026 | E85: 06/16/2026 | F85: ME | G85: =COUNTIF(BankQuarter!$B$5:$B$750,A85)>0 -> TRUE
A86: 17752 | B86: Waterville Savings Bank | C86: 0 | E86: 09/14/1995 | F86: ME | G86: =COUNTIF(BankQuarter!$B$5:$B$750,A86)>0 -> FALSE
A87: 17763 | B87: The Exeter Banking Company | C87: 0 | D87: 12/31/1990 | E87: 02/11/1991 | F87: NH | G87: =COUNTIF(BankQuarter!$B$5:$B$750,A87)>0 -> FALSE
A88: 17804 | B88: People's Savings Bank | C88: 0 | E88: 09/25/1995 | F88: ME | G88: =COUNTIF(BankQuarter!$B$5:$B$750,A88)>0 -> FALSE
A89: 17855 | B89: New London Trust F.S.B. | C89: 0 | D89: 09/30/1999 | E89: 11/12/1999 | F89: NH | G89: =COUNTIF(BankQuarter!$B$5:$B$750,A89)>0 -> FALSE
A90: 17879 | B90: Bank Meridian, National Association | C90: 0 | D90: 06/30/1991 | E90: 10/24/1991 | F90: NH | G90: =COUNTIF(BankQuarter!$B$5:$B$750,A90)>0 -> FALSE
A91: 17897 | B91: Kennebec Savings Bank | C91: 1 | D91: 06/30/2026 | E91: 11/18/2024 | F91: ME | G91: =COUNTIF(BankQuarter!$B$5:$B$750,A91)>0 -> TRUE
A92: 17939 | B92: The Suncook Bank | C92: 0 | D92: 06/30/1991 | E92: 12/09/1991 | F92: NH | G92: =COUNTIF(BankQuarter!$B$5:$B$750,A92)>0 -> FALSE
A93: 17951 | B93: Franklin Savings Bank | C93: 1 | D93: 06/30/2026 | E93: 11/18/2024 | F93: NH | G93: =COUNTIF(BankQuarter!$B$5:$B$750,A93)>0 -> TRUE
A94: 17958 | B94: The Whitefield Savings Bank & Trust Company | C94: 0 | D94: 03/31/1985 | E94: 10/06/1995 | F94: NH | G94: =COUNTIF(BankQuarter!$B$5:$B$750,A94)>0 -> FALSE
A95: 17960 | B95: Merrimack County Savings Bank | C95: 1 | D95: 06/30/2026 | E95: 11/18/2024 | F95: NH | G95: =COUNTIF(BankQuarter!$B$5:$B$750,A95)>0 -> TRUE
A96: 17991 | B96: CFX Bank | C96: 0 | D96: 03/31/1998 | E96: 04/22/1998 | F96: NH | G96: =COUNTIF(BankQuarter!$B$5:$B$750,A96)>0 -> FALSE
A97: 17992 | B97: Granite Bank | C97: 0 | D97: 03/31/2004 | E97: 06/24/2004 | F97: NH | G97: =COUNTIF(BankQuarter!$B$5:$B$750,A97)>0 -> FALSE
A98: 18010 | B98: The Bristol Savings Bank | C98: 0 | E98: 09/14/1995 | F98: NH | G98: =COUNTIF(BankQuarter!$B$5:$B$750,A98)>0 -> FALSE
A99: 18011 | B99: Monadnock Savings Bank | C99: 0 | E99: 09/14/1995 | F99: NH | G99: =COUNTIF(BankQuarter!$B$5:$B$750,A99)>0 -> FALSE
A100: 18012 | B100: Bank of New Hampshire | C100: 1 | D100: 06/30/2026 | E100: 11/18/2024 | F100: NH | G100: =COUNTIF(BankQuarter!$B$5:$B$750,A100)>0 -> TRUE
A101: 18013 | B101: Mascoma Bank | C101: 1 | D101: 06/30/2026 | E101: 11/18/2024 | F101: NH | G101: =COUNTIF(BankQuarter!$B$5:$B$750,A101)>0 -> TRUE
...

Sheet BankQuarter
A1: Bank-Quarter Calculation Table
A2: Formula-driven from RawFinancials. Proxy = 100 × (P9ASSET + NAASSET) / ASSET; invalid rows remain excluded, never coerced to zero.
A4: source_row | B4: CERT | C4: Bank name | D4: REPDTE | E4: State | F4: ASSET ($000) | G4: P9ASSET ($000) | H4: NAASSET ($000) | I4: Proxy numerator ($000) | J4: DEP ($000) | K4: EQ ($000) | L4: LNLSGR ($000) | M4: LNRE ($000) | N4: ROA raw % | O4: RBCRWAJ raw % | P4: RE loans / gross loans % | Q4: Equity / assets % | R4: Proxy valid? | S4: Proxy % | T4: Amount revised? | U4: End proxy for start row % | V4: End state for start row | W4: Has valid start? | X4: Has valid end? | Y4: Start state for end row | Z4: State rank at end | AA4: Remaining rank at end | AB4: Endpoint row? | AC4: Key
A5: =RawFinancials!A5 -> 2 | B5: =RawFinancials!C5 -> 11971 | C5: =RawFinancials!P5 -> BAR HARBOR BANK & TRUST | D5: =RawFinancials!W5 -> 20220331 | E5: =RawFinancials!Z5 -> ME | F5: =RawFinancials!B5 -> 3688993 | G5: =RawFinancials!U5 -> 843 | H5: =RawFinancials!O5 -> 9213 | I5: =IF(AND(ISNUMBER(G5),ISNUMBER(H5)),G5+H5,"") -> 10056 | J5: =RawFinancials!D5 -> 3055632 | K5: =RawFinancials!F5 -> 461681 | L5: =RawFinancials!L5 -> 2657406 | M5: =RawFinancials!N5 -> 2317079 | N5: =RawFinancials!X5 -> 1.1162343 | O5: =RawFinancials!V5 -> 13.678961 | P5: =IF(AND(ISNUMBER(L5),L5<>0,ISNUMBER(M5)),100*M5/L5,"") -> 87.193263 | Q5: =IF(AND(ISNUMBER(F5),F5<>0,ISNUMBER(K5)),100*K5/F5,"") -> 12.515096 | R5: =AND(ISNUMBER(F5),F5>0,ISNUMBER(G5),G5>=0,ISNUMBER(H5),H5>=0) -> TRUE | S5: =IF(R5,100*I5/F5,"") -> 0.27259472 | T5: =NOT(AND(OR(AND(ISBLANK(RawFinancials!B5),ISBLANK(_RawBaseline!B2)),AND(ISNUMBER(RawFinancials!B5),ISNUMBER(_RawBaseline!B2),RawFinancials!B5=_RawBaseline!B2)),OR(AND(ISBLANK(RawFinancials!U5),ISBLANK(_RawBaseline!U2)),AND(ISNUMBER(RawFinancials!U5),ISNUMBER(_RawBaseline!U2),RawFinancials!U5=_RawBaseline!U2)),OR(AND(ISBLANK(RawFinancials!O5),ISBLANK(_RawBaseline!O2)),AND(ISNUMBER(RawFinancials!O5),ISNUMBER(_RawBaseline!O2),RawFinancials!O5=_RawBaseline!O2)))) -> FALSE | U5: =IF(AND(D5=WF_START_PERIOD,R5,COUNTIFS($B$5:$B$750,B5,$D$5:$D$750,WF_END_PERIOD,$R$5:$R$750,TRUE())>0),SUMIFS($S$5:$S$750,$B$5:$B$750,B5,$D$5:$D$750,WF_END_PERIOD,$R$5:$R$750,TRUE()),0) -> 0 | V5: =IF(AND(D5=WF_START_PERIOD,COUNTIFS($B$5:$B$750,B5,$D$5:$D$750,WF_END_PERIOD)>0),INDEX($E$5:$E$750,MATCH(B5&"|"&WF_END_PERIOD,$AC$5:$AC$750,0)),"") | W5: =COUNTIFS($B$5:$B$750,B5,$D$5:$D$750,WF_START_PERIOD,$R$5:$R$750,TRUE())>0 -> TRUE | X5: =COUNTIFS($B$5:$B$750,B5,$D$5:$D$750,WF_END_PERIOD,$R$5:$R$750,TRUE())>0 -> TRUE | Y5: =IF(AND(D5=WF_END_PERIOD,COUNTIFS($B$5:$B$750,B5,$D$5:$D$750,WF_START_PERIOD)>0),INDEX($E$5:$E$750,MATCH(B5&"|"&WF_START_PERIOD,$AC$5:$AC$750,0)),"") | Z5: =IF(AND(D5=WF_END_PERIOD,R5),1+COUNTIFS($D$5:$D$750,WF_END_PERIOD,$E$5:$E$750,E5,$R$5:$R$750,TRUE(),$S$5:$S$750,">"&S5)+COUNTIFS($D$5:$D$750,WF_END_PERIOD,$E$5:$E$750,E5,$R$5:$R$750,TRUE(),$S$5:$S$750,S5,$B$5:$B$750,"<"&B5),"") | AA5: =IF(AND(D5=WF_END_PERIOD,R5,Z5<>1),1+COUNTIFS($D$5:$D$750,WF_END_PERIOD,$R$5:$R$750,TRUE(),$Z$5:$Z$750,"<>1",$S$5:$S$750,">"&S5)+COUNTIFS($D$5:$D$750,WF_END_PERIOD,$R$5:$R$750,TRUE(),$Z$5:$Z$750,"<>1",$S$5:$S$750,S5,$B$5:$B$750,"<"&B5),"") | AB5: =OR(D5=WF_START_PERIOD,D5=WF_END_PERIOD) -> FALSE | AC5: =B5&"|"&D5 -> 11971|20220331
A6: =RawFinancials!A6 -> 3 | B6: =RawFinancials!C6 -> 12874 | C6: =RawFinancials!P6 -> KATAHDIN TRUST COMPANY | D6: =RawFinancials!W6 -> 20220331 | E6: =RawFinancials!Z6 -> ME | F6: =RawFinancials!B6 -> 964163 | G6: =RawFinancials!U6 -> 0 | H6: =RawFinancials!O6 -> 1069 | I6: =IF(AND(ISNUMBER(G6),ISNUMBER(H6)),G6+H6,"") -> 1069 | J6: =RawFinancials!D6 -> 854194 | K6: =RawFinancials!F6 -> 97916 | L6: =RawFinancials!L6 -> 732906 | M6: =RawFinancials!N6 -> 577596 | N6: =RawFinancials!X6 -> 0.83149732 | O6: =RawFinancials!V6 -> 15.601603 | P6: =IF(AND(ISNUMBER(L6),L6<>0,ISNUMBER(M6)),100*M6/L6,"") -> 78.809015 | Q6: =IF(AND(ISNUMBER(F6),F6<>0,ISNUMBER(K6)),100*K6/F6,"") -> 10.155544 | R6: =AND(ISNUMBER(F6),F6>0,ISNUMBER(G6),G6>=0,ISNUMBER(H6),H6>=0) -> TRUE | S6: =IF(R6,100*I6/F6,"") -> 0.11087337 | T6: =NOT(AND(OR(AND(ISBLANK(RawFinancials!B6),ISBLANK(_RawBaseline!B3)),AND(ISNUMBER(RawFinancials!B6),ISNUMBER(_RawBaseline!B3),RawFinancials!B6=_RawBaseline!B3)),OR(AND(ISBLANK(RawFinancials!U6),ISBLANK(_RawBaseline!U3)),AND(ISNUMBER(RawFinancials!U6),ISNUMBER(_RawBaseline!U3),RawFinancials!U6=_RawBaseline!U3)),OR(AND(ISBLANK(RawFinancials!O6),ISBLANK(_RawBaseline!O3)),AND(ISNUMBER(RawFinancials!O6),ISNUMBER(_RawBaseline!O3),RawFinancials!O6=_RawBaseline!O3)))) -> FALSE | U6: =IF(AND(D6=WF_START_PERIOD,R6,COUNTIFS($B$5:$B$750,B6,$D$5:$D$750,WF_END_PERIOD,$R$5:$R$750,TRUE())>0),SUMIFS($S$5:$S$750,$B$5:$B$750,B6,$D$5:$D$750,WF_END_PERIOD,$R$5:$R$750,TRUE()),0) -> 0 | V6: =IF(AND(D6=WF_START_PERIOD,COUNTIFS($B$5:$B$750,B6,$D$5:$D$750,WF_END_PERIOD)>0),INDEX($E$5:$E$750,MATCH(B6&"|"&WF_END_PERIOD,$AC$5:$AC$750,0)),"") | W6: =COUNTIFS($B$5:$B$750,B6,$D$5:$D$750,WF_START_PERIOD,$R$5:$R$750,TRUE())>0 -> TRUE | X6: =COUNTIFS($B$5:$B$750,B6,$D$5:$D$750,WF_END_PERIOD,$R$5:$R$750,TRUE())>0 -> TRUE | Y6: =IF(AND(D6=WF_END_PERIOD,COUNTIFS($B$5:$B$750,B6,$D$5:$D$750,WF_START_PERIOD)>0),INDEX($E$5:$E$750,MATCH(B6&"|"&WF_START_PERIOD,$AC$5:$AC$750,0)),"") | Z6: =IF(AND(D6=WF_END_PERIOD,R6),1+COUNTIFS($D$5:$D$750,WF_END_PERIOD,$E$5:$E$750,E6,$R$5:$R$750,TRUE(),$S$5:$S$750,">"&S6)+COUNTIFS($D$5:$D$750,WF_END_PERIOD,$E$5:$E$750,E6,$R$5:$R$750,TRUE(),$S$5:$S$750,S6,$B$5:$B$750,"<"&B6),"") | AA6: =IF(AND(D6=WF_END_PERIOD,R6,Z6<>1),1+COUNTIFS($D$5:$D$750,WF_END_PERIOD,$R$5:$R$750,TRUE(),$Z$5:$Z$750,"<>1",$S$5:$S$750,">"&S6)+COUNTIFS($D$5:$D$750,WF_END_PERIOD,$R$5:$R$750,TRUE(),$Z$5:$Z$750,"<>1",$S$5:$S$750,S6,$B$5:$B$750,"<"&B6),"") | AB6: =OR(D6=WF_START_PERIOD,D6=WF_END_PERIOD) -> FALSE | AC6: =B6&"|"&D6 -> 12874|20220331
A7: =RawFinancials!A7 -> 4 | B7: =RawFinancials!C7 -> 13063 | C7: =RawFinancials!P7 -> KENNEBUNK SAVINGS BANK | D7: =RawFinancials!W7 -> 20220331 | E7: =RawFinancials!Z7 -> ME | F7: =RawFinancials!B7 -> 1784835 | G7: =RawFinancials!U7 -> 1196 | H7: =RawFinancials!O7 -> 408 | I7: =IF(AND(ISNUMBER(G7),ISNUMBER(H7)),G7+H7,"") -> 1604 | J7: =RawFinancials!D7 -> 1619076 | K7: =RawFinancials!F7 -> 148181 | L7: =RawFinancials!L7 -> 1223389 | M7: =RawFinancials!N7 -> 1160807 | N7: =RawFinancials!X7 -> 0.48237313 | O7: =RawFinancials!V7 -> 0 | P7: =IF(AND(ISNUMBER(L7),L7<>0,ISNUMBER(M7)),100*M7/L7,"") -> 94.884538 | Q7: =IF(AND(ISNUMBER(F7),F7<>0,ISNUMBER(K7)),100*K7/F7,"") -> 8.302224 | R7: =AND(ISNUMBER(F7),F7>0,ISNUMBER(G7),G7>=0,ISNUMBER(H7),H7>=0) -> TRUE | S7: =IF(R7,100*I7/F7,"") -> 0.089868251 | T7: =NOT(AND(OR(AND(ISBLANK(RawFinancials!B7),ISBLANK(_RawBaseline!B4)),AND(ISNUMBER(RawFinancials!B7),ISNUMBER(_RawBaseline!B4),RawFinancials!B7=_RawBaseline!B4)),OR(AND(ISBLANK(RawFinancials!U7),ISBLANK(_RawBaseline!U4)),AND(ISNUMBER(RawFinancials!U7),ISNUMBER(_RawBaseline!U4),RawFinancials!U7=_RawBaseline!U4)),OR(AND(ISBLANK(RawFinancials!O7),ISBLANK(_RawBaseline!O4)),AND(ISNUMBER(RawFinancials!O7),ISNUMBER(_RawBaseline!O4),RawFinancials!O7=_RawBaseline!O4)))) -> FALSE | U7: =IF(AND(D7=WF_START_PERIOD,R7,COUNTIFS($B$5:$B$750,B7,$D$5:$D$750,WF_END_PERIOD,$R$5:$R$750,TRUE())>0),SUMIFS($S$5:$S$750,$B$5:$B$750,B7,$D$5:$D$750,WF_END_PERIOD,$R$5:$R$750,TRUE()),0) -> 0 | V7: =IF(AND(D7=WF_START_PERIOD,COUNTIFS($B$5:$B$750,B7,$D$5:$D$750,WF_END_PERIOD)>0),INDEX($E$5:$E$750,MATCH(B7&"|"&WF_END_PERIOD,$AC$5:$AC$750,0)),"") | W7: =COUNTIFS($B$5:$B$750,B7,$D$5:$D$750,WF_START_PERIOD,$R$5:$R$750,TRUE())>0 -> TRUE | X7: =COUNTIFS($B$5:$B$750,B7,$D$5:$D$750,WF_END_PERIOD,$R$5:$R$750,TRUE())>0 -> TRUE | Y7: =IF(AND(D7=WF_END_PERIOD,COUNTIFS($B$5:$B$750,B7,$D$5:$D$750,WF_START_PERIOD)>0),INDEX($E$5:$E$750,MATCH(B7&"|"&WF_START_PERIOD,$AC$5:$AC$750,0)),"") | Z7: =IF(AND(D7=WF_END_PERIOD,R7),1+COUNTIFS($D$5:$D$750,WF_END_PERIOD,$E$5:$E$750,E7,$R$5:$R$750,TRUE(),$S$5:$S$750,">"&S7)+COUNTIFS($D$5:$D$750,WF_END_PERIOD,$E$5:$E$750,E7,$R$5:$R$750,TRUE(),$S$5:$S$750,S7,$B$5:$B$750,"<"&B7),"") | AA7: =IF(AND(D7=WF_END_PERIOD,R7,Z7<>1),1+COUNTIFS($D$5:$D$750,WF_END_PERIOD,$R$5:$R$750,TRUE(),$Z$5:$Z$750,"<>1",$S$5:$S$750,">"&S7)+COUNTIFS($D$5:$D$750,WF_END_PERIOD,$R$5:$R$750,TRUE(),$Z$5:$Z$750,"<>1",$S$5:$S$750,S7,$B$5:$B$750,"<"&B7),"") | AB7: =OR(D7=WF_START_PERIOD,D7=WF_END_PERIOD) -> FALSE | AC7: =B7&"|"&D7 -> 13063|20220331
A8: =RawFinancials!A8 -> 5 | B8: =RawFinancials!C8 -> 14134 | C8: =RawFinancials!P8 -> PASSUMPSIC SAVINGS BANK | D8: =RawFinancials!W8 -> 20220331 | E8: =RawFinancials!Z8 -> VT | F8: =RawFinancials!B8 -> 869402 | G8: =RawFinancials!U8 -> 0 | H8: =RawFinancials!O8 -> 8014 | I8: =IF(AND(ISNUMBER(G8),ISNUMBER(H8)),G8+H8,"") -> 8014 | J8: =RawFinancials!D8 -> 737795 | K8: =RawFinancials!F8 -> 101808 | L8: =RawFinancials!L8 -> 596388 | M8: =RawFinancials!N8 -> 516229 | N8: =RawFinancials!X8 -> -0.38729339 | O8: =RawFinancials!V8 -> 17.570983 | P8: =IF(AND(ISNUMBER(L8),L8<>0,ISNUMBER(M8)),100*M8/L8,"") -> 86.559253 | Q8: =IF(AND(ISNUMBER(F8),F8<>0,ISNUMBER(K8)),100*K8/F8,"") -> 11.710118 | R8: =AND(ISNUMBER(F8),F8>0,ISNUMBER(G8),G8>=0,ISNUMBER(H8),H8>=0) -> TRUE | S8: =IF(R8,100*I8/F8,"") -> 0.92178302 | T8: =NOT(AND(OR(AND(ISBLANK(RawFinancials!B8),ISBLANK(_RawBaseline!B5)),AND(ISNUMBER(RawFinancials!B8),ISNUMBER(_RawBaseline!B5),RawFinancials!B8=_RawBaseline!B5)),OR(AND(ISBLANK(RawFinancials!U8),ISBLANK(_RawBaseline!U5)),AND(ISNUMBER(RawFinancials!U8),ISNUMBER(_RawBaseline!U5),RawFinancials!U8=_RawBaseline!U5)),OR(AND(ISBLANK(RawFinancials!O8),ISBLANK(_RawBaseline!O5)),AND(ISNUMBER(RawFinancials!O8),ISNUMBER(_RawBaseline!O5),RawFinancials!O8=_RawBaseline!O5)))) -> FALSE | U8: =IF(AND(D8=WF_START_PERIOD,R8,COUNTIFS($B$5:$B$750,B8,$D$5:$D$750,WF_END_PERIOD,$R$5:$R$750,TRUE())>0),SUMIFS($S$5:$S$750,$B$5:$B$750,B8,$D$5:$D$750,WF_END_PERIOD,$R$5:$R$750,TRUE()),0) -> 0 | V8: =IF(AND(D8=WF_START_PERIOD,COUNTIFS($B$5:$B$750,B8,$D$5:$D$750,WF_END_PERIOD)>0),INDEX($E$5:$E$750,MATCH(B8&"|"&WF_END_PERIOD,$AC$5:$AC$750,0)),"") | W8: =COUNTIFS($B$5:$B$750,B8,$D$5:$D$750,WF_START_PERIOD,$R$5:$R$750,TRUE())>0 -> TRUE | X8: =COUNTIFS($B$5:$B$750,B8,$D$5:$D$750,WF_END_PERIOD,$R$5:$R$750,TRUE())>0 -> TRUE | Y8: =IF(AND(D8=WF_END_PERIOD,COUNTIFS($B$5:$B$750,B8,$D$5:$D$750,WF_START_PERIOD)>0),INDEX($E$5:$E$750,MATCH(B8&"|"&WF_START_PERIOD,$AC$5:$AC$750,0)),"") | Z8: =IF(AND(D8=WF_END_PERIOD,R8),1+COUNTIFS($D$5:$D$750,WF_END_PERIOD,$E$5:$E$750,E8,$R$5:$R$750,TRUE(),$S$5:$S$750,">"&S8)+COUNTIFS($D$5:$D$750,WF_END_PERIOD,$E$5:$E$750,E8,$R$5:$R$750,TRUE(),$S$5:$S$750,S8,$B$5:$B$750,"<"&B8),"") | AA8: =IF(AND(D8=WF_END_PERIOD,R8,Z8<>1),1+COUNTIFS($D$5:$D$750,WF_END_PERIOD,$R$5:$R$750,TRUE(),$Z$5:$Z$750,"<>1",$S$5:$S$750,">"&S8)+COUNTIFS($D$5:$D$750,WF_END_PERIOD,$R$5:$R$750,TRUE(),$Z$5:$Z$750,"<>1",$S$5:$S$750,S8,$B$5:$B$750,"<"&B8),"") | AB8: =OR(D8=WF_START_PERIOD,D8=WF_END_PERIOD) -> FALSE | AC8: =B8&"|"&D8 -> 14134|20220331
A9: =RawFinancials!A9 -> 6 | B9: =RawFinancials!C9 -> 14136 | C9: =RawFinancials!P9 -> WELLS RIVER SAVINGS BANK | D9: =RawFinancials!W9 -> 20220331 | E9: =RawFinancials!Z9 -> VT | F9: =RawFinancials!B9 -> 222692 | G9: =RawFinancials!U9 -> 639 | H9: =RawFinancials!O9 -> 174 | I9: =IF(AND(ISNUMBER(G9),ISNUMBER(H9)),G9+H9,"") -> 813 | J9: =RawFinancials!D9 -> 199279 | K9: =RawFinancials!F9 -> 18834 | L9: =RawFinancials!L9 -> 121199 | M9: =RawFinancials!N9 -> 96809 | N9: =RawFinancials!X9 -> 0.19954922 | O9: =RawFinancials!V9 -> 17.27622 | P9: =IF(AND(ISNUMBER(L9),L9<>0,ISNUMBER(M9)),100*M9/L9,"") -> 79.876072 | Q9: =IF(AND(ISNUMBER(F9),F9<>0,ISNUMBER(K9)),100*K9/F9,"") -> 8.457421 | R9: =AND(ISNUMBER(F9),F9>0,ISNUMBER(G9),G9>=0,ISNUMBER(H9),H9>=0) -> TRUE | S9: =IF(R9,100*I9/F9,"") -> 0.36507822 | T9: =NOT(AND(OR(AND(ISBLANK(RawFinancials!B9),ISBLANK(_RawBaseline!B6)),AND(ISNUMBER(RawFinancials!B9),ISNUMBER(_RawBaseline!B6),RawFinancials!B9=_RawBaseline!B6)),OR(AND(ISBLANK(RawFinancials!U9),ISBLANK(_RawBaseline!U6)),AND(ISNUMBER(RawFinancials!U9),ISNUMBER(_RawBaseline!U6),RawFinancials!U9=_RawBaseline!U6)),OR(AND(ISBLANK(RawFinancials!O9),ISBLANK(_RawBaseline!O6)),AND(ISNUMBER(RawFinancials!O9),ISNUMBER(_RawBaseline!O6),RawFinancials!O9=_RawBaseline!O6)))) -> FALSE | U9: =IF(AND(D9=WF_START_PERIOD,R9,COUNTIFS($B$5:$B$750,B9,$D$5:$D$750,WF_END_PERIOD,$R$5:$R$750,TRUE())>0),SUMIFS($S$5:$S$750,$B$5:$B$750,B9,$D$5:$D$750,WF_END_PERIOD,$R$5:$R$750,TRUE()),0) -> 0 | V9: =IF(AND(D9=WF_START_PERIOD,COUNTIFS($B$5:$B$750,B9,$D$5:$D$750,WF_END_PERIOD)>0),INDEX($E$5:$E$750,MATCH(B9&"|"&WF_END_PERIOD,$AC$5:$AC$750,0)),"") | W9: =COUNTIFS($B$5:$B$750,B9,$D$5:$D$750,WF_START_PERIOD,$R$5:$R$750,TRUE())>0 -> TRUE | X9: =COUNTIFS($B$5:$B$750,B9,$D$5:$D$750,WF_END_PERIOD,$R$5:$R$750,TRUE())>0 -> TRUE | Y9: =IF(AND(D9=WF_END_PERIOD,COUNTIFS($B$5:$B$750,B9,$D$5:$D$750,WF_START_PERIOD)>0),INDEX($E$5:$E$750,MATCH(B9&"|"&WF_START_PERIOD,$AC$5:$AC$750,0)),"") | Z9: =IF(AND(D9=WF_END_PERIOD,R9),1+COUNTIFS($D$5:$D$750,WF_END_PERIOD,$E$5:$E$750,E9,$R$5:$R$750,TRUE(),$S$5:$S$750,">"&S9)+COUNTIFS($D$5:$D$750,WF_END_PERIOD,$E$5:$E$750,E9,$R$5:$R$750,TRUE(),$S$5:$S$750,S9,$B$5:$B$750,"<"&B9),"") | AA9: =IF(AND(D9=WF_END_PERIOD,R9,Z9<>1),1+COUNTIFS($D$5:$D$750,WF_END_PERIOD,$R$5:$R$750,TRUE(),$Z$5:$Z$750,"<>1",$S$5:$S$750,">"&S9)+COUNTIFS($D$5:$D$750,WF_END_PERIOD,$R$5:$R$750,TRUE(),$Z$5:$Z$750,"<>1",$S$5:$S$750,S9,$B$5:$B$750,"<"&B9),"") | AB9: =OR(D9=WF_START_PERIOD,D9=WF_END_PERIOD) -> FALSE | AC9: =B9&"|"&D9 -> 14136|20220331
A10: =RawFinancials!A10 -> 7 | B10: =RawFinancials!C10 -> 14140 | C10: =RawFinancials!P10 -> NORTHFIELD SAVINGS BANK | D10: =RawFinancials!W10 -> 20220331 | E10: =RawFinancials!Z10 -> VT | F10: =RawFinancials!B10 -> 1414510 | G10: =RawFinancials!U10 -> 0 | H10: =RawFinancials!O10 -> 5589 | I10: =IF(AND(ISNUMBER(G10),ISNUMBER(H10)),G10+H10,"") -> 5589 | J10: =RawFinancials!D10 -> 1199427 | K10: =RawFinancials!F10 -> 123854 | L10: =RawFinancials!L10 -> 957867 | M10: =RawFinancials!N10 -> 866005 | N10: =RawFinancials!X10 -> 0.66212632 | O10: =RawFinancials!V10 -> 0 | P10: =IF(AND(ISNUMBER(L10),L10<>0,ISNUMBER(M10)),100*M10/L10,"") -> 90.409733 | Q10: =IF(AND(ISNUMBER(F10),F10<>0,ISNUMBER(K10)),100*K10/F10,"") -> 8.755965 | R10: =AND(ISNUMBER(F10),F10>0,ISNUMBER(G10),G10>=0,ISNUMBER(H10),H10>=0) -> TRUE | S10: =IF(R10,100*I10/F10,"") -> 0.39511916 | T10: =NOT(AND(OR(AND(ISBLANK(RawFinancials!B10),ISBLANK(_RawBaseline!B7)),AND(ISNUMBER(RawFinancials!B10),ISNUMBER(_RawBaseline!B7),RawFinancials!B10=_RawBaseline!B7)),OR(AND(ISBLANK(RawFinancials!U10),ISBLANK(_RawBaseline!U7)),AND(ISNUMBER(RawFinancials!U10),ISNUMBER(_RawBaseline!U7),RawFinancials!U10=_RawBaseline!U7)),OR(AND(ISBLANK(RawFinancials!O10),ISBLANK(_RawBaseline!O7)),AND(ISNUMBER(RawFinancials!O10),ISNUMBER(_RawBaseline!O7),RawFinancials!O10=_RawBaseline!O7)))) -> FALSE | U10: =IF(AND(D10=WF_START_PERIOD,R10,COUNTIFS($B$5:$B$750,B10,$D$5:$D$750,WF_END_PERIOD,$R$5:$R$750,TRUE())>0),SUMIFS($S$5:$S$750,$B$5:$B$750,B10,$D$5:$D$750,WF_END_PERIOD,$R$5:$R$750,TRUE()),0) -> 0 | V10: =IF(AND(D10=WF_START_PERIOD,COUNTIFS($B$5:$B$750,B10,$D$5:$D$750,WF_END_PERIOD)>0),INDEX($E$5:$E$750,MATCH(B10&"|"&WF_END_PERIOD,$AC$5:$AC$750,0)),"") | W10: =COUNTIFS($B$5:$B$750,B10,$D$5:$D$750,WF_START_PERIOD,$R$5:$R$750,TRUE())>0 -> TRUE | X10: =COUNTIFS($B$5:$B$750,B10,$D$5:$D$750,WF_END_PERIOD,$R$5:$R$750,TRUE())>0 -> TRUE | Y10: =IF(AND(D10=WF_END_PERIOD,COUNTIFS($B$5:$B$750,B10,$D$5:$D$750,WF_START_PERIOD)>0),INDEX($E$5:$E$750,MATCH(B10&"|"&WF_START_PERIOD,$AC$5:$AC$750,0)),"") | Z10: =IF(AND(D10=WF_END_PERIOD,R10),1+COUNTIFS($D$5:$D$750,WF_END_PERIOD,$E$5:$E$750,E10,$R$5:$R$750,TRUE(),$S$5:$S$750,">"&S10)+COUNTIFS($D$5:$D$750,WF_END_PERIOD,$E$5:$E$750,E10,$R$5:$R$750,TRUE(),$S$5:$S$750,S10,$B$5:$B$750,"<"&B10),"") | AA10: =IF(AND(D10=WF_END_PERIOD,R10,Z10<>1),1+COUNTIFS($D$5:$D$750,WF_END_PERIOD,$R$5:$R$750,TRUE(),$Z$5:$Z$750,"<>1",$S$5:$S$750,">"&S10)+COUNTIFS($D$5:$D$750,WF_END_PERIOD,$R$5:$R$750,TRUE(),$Z$5:$Z$750,"<>1",$S$5:$S$750,S10,$B$5:$B$750,"<"&B10),"") | AB10: =OR(D10=WF_START_PERIOD,D10=WF_END_PERIOD) -> FALSE | AC10: =B10&"|"&D10 -> 14140|20220331
A11: =RawFinancials!A11 -> 8 | B11: =RawFinancials!C11 -> 14158 | C11: =RawFinancials!P11 -> UNION BANK | D11: =RawFinancials!W11 -> 20220331 | E11: =RawFinancials!Z11 -> VT | F11: =RawFinancials!B11 -> 1232701 | G11: =RawFinancials!U11 -> 229 | H11: =RawFinancials!O11 -> 4405 | I11: =IF(AND(ISNUMBER(G11),ISNUMBER(H11)),G11+H11,"") -> 4634 | J11: =RawFinancials!D11 -> 1137254 | K11: =RawFinancials!F11 -> 85105 | L11: =RawFinancials!L11 -> 830963 | M11: =RawFinancials!N11 -> 698008 | N11: =RawFinancials!X11 -> 0.88329132 | O11: =RawFinancials!V11 -> 14.788126 | P11: =IF(AND(ISNUMBER(L11),L11<>0,ISNUMBER(M11)),100*M11/L11,"") -> 83.999889 | Q11: =IF(AND(ISNUMBER(F11),F11<>0,ISNUMBER(K11)),100*K11/F11,"") -> 6.9039451 | R11: =AND(ISNUMBER(F11),F11>0,ISNUMBER(G11),G11>=0,ISNUMBER(H11),H11>=0) -> TRUE | S11: =IF(R11,100*I11/F11,"") -> 0.37592247 | T11: =NOT(AND(OR(AND(ISBLANK(RawFinancials!B11),ISBLANK(_RawBaseline!B8)),AND(ISNUMBER(RawFinancials!B11),ISNUMBER(_RawBaseline!B8),RawFinancials!B11=_RawBaseline!B8)),OR(AND(ISBLANK(RawFinancials!U11),ISBLANK(_RawBaseline!U8)),AND(ISNUMBER(RawFinancials!U11),ISNUMBER(_RawBaseline!U8),RawFinancials!U11=_RawBaseline!U8)),OR(AND(ISBLANK(RawFinancials!O11),ISBLANK(_RawBaseline!O8)),AND(ISNUMBER(RawFinancials!O11),ISNUMBER(_RawBaseline!O8),RawFinancials!O11=_RawBaseline!O8)))) -> FALSE | U11: =IF(AND(D11=WF_START_PERIOD,R11,COUNTIFS($B$5:$B$750,B11,$D$5:$D$750,WF_END_PERIOD,$R$5:$R$750,TRUE())>0),SUMIFS($S$5:$S$750,$B$5:$B$750,B11,$D$5:$D$750,WF_END_PERIOD,$R$5:$R$750,TRUE()),0) -> 0 | V11: =IF(AND(D11=WF_START_PERIOD,COUNTIFS($B$5:$B$750,B11,$D$5:$D$750,WF_END_PERIOD)>0),INDEX($E$5:$E$750,MATCH(B11&"|"&WF_END_PERIOD,$AC$5:$AC$750,0)),"") | W11: =COUNTIFS($B$5:$B$750,B11,$D$5:$D$750,WF_START_PERIOD,$R$5:$R$750,TRUE())>0 -> TRUE | X11: =COUNTIFS($B$5:$B$750,B11,$D$5:$D$750,WF_END_PERIOD,$R$5:$R$750,TRUE())>0 -> TRUE | Y11: =IF(AND(D11=WF_END_PERIOD,COUNTIFS($B$5:$B$750,B11,$D$5:$D$750,WF_START_PERIOD)>0),INDEX($E$5:$E$750,MATCH(B11&"|"&WF_START_PERIOD,$AC$5:$AC$750,0)),"") | Z11: =IF(AND(D11=WF_END_PERIOD,R11),1+COUNTIFS($D$5:$D$750,WF_END_PERIOD,$E$5:$E$750,E11,$R$5:$R$750,TRUE(),$S$5:$S$750,">"&S11)+COUNTIFS($D$5:$D$750,WF_END_PERIOD,$E$5:$E$750,E11,$R$5:$R$750,TRUE(),$S$5:$S$750,S11,$B$5:$B$750,"<"&B11),"") | AA11: =IF(AND(D11=WF_END_PERIOD,R11,Z11<>1),1+COUNTIFS($D$5:$D$750,WF_END_PERIOD,$R$5:$R$750,TRUE(),$Z$5:$Z$750,"<>1",$S$5:$S$750,">"&S11)+COUNTIFS($D$5:$D$750,WF_END_PERIOD,$R$5:$R$750,TRUE(),$Z$5:$Z$750,"<>1",$S$5:$S$750,S11,$B$5:$B$750,"<"&B11),"") | AB11: =OR(D11=WF_START_PERIOD,D11=WF_END_PERIOD) -> FALSE | AC11: =B11&"|"&D11 -> 14158|20220331
A12: =RawFinancials!A12 -> 9 | B12: =RawFinancials!C12 -> 14168 | C12: =RawFinancials!P12 -> PEOPLES TRUST COMPANY OF ST. ALBANS | D12: =RawFinancials!W12 -> 20220331 | E12: =RawFinancials!Z12 -> VT | F12: =RawFinancials!B12 -> 384095 | G12: =RawFinancials!U12 -> 0 | H12: =RawFinancials!O12 -> 1188 | I12: =IF(AND(ISNUMBER(G12),ISNUMBER(H12)),G12+H12,"") -> 1188 | J12: =RawFinancials!D12 -> 345364 | K12: =RawFinancials!F12 -> 34244 | L12: =RawFinancials!L12 -> 191155 | M12: =RawFinancials!N12 -> 161619 | N12: =RawFinancials!X12 -> 0.13578832 | O12: =RawFinancials!V12 -> 19.824643 | P12: =IF(AND(ISNUMBER(L12),L12<>0,ISNUMBER(M12)),100*M12/L12,"") -> 84.548665 | Q12: =IF(AND(ISNUMBER(F12),F12<>0,ISNUMBER(K12)),100*K12/F12,"") -> 8.9155027 | R12: =AND(ISNUMBER(F12),F12>0,ISNUMBER(G12),G12>=0,ISNUMBER(H12),H12>=0) -> TRUE | S12: =IF(R12,100*I12/F12,"") -> 0.30929848 | T12: =NOT(AND(OR(AND(ISBLANK(RawFinancials!B12),ISBLANK(_RawBaseline!B9)),AND(ISNUMBER(RawFinancials!B12),ISNUMBER(_RawBaseline!B9),RawFinancials!B12=_RawBaseline!B9)),OR(AND(ISBLANK(RawFinancials!U12),ISBLANK(_RawBaseline!U9)),AND(ISNUMBER(RawFinancials!U12),ISNUMBER(_RawBaseline!U9),RawFinancials!U12=_RawBaseline!U9)),OR(AND(ISBLANK(RawFinancials!O12),ISBLANK(_RawBaseline!O9)),AND(ISNUMBER(RawFinancials!O12),ISNUMBER(_RawBaseline!O9),RawFinancials!O12=_RawBaseline!O9)))) -> FALSE | U12: =IF(AND(D12=WF_START_PERIOD,R12,COUNTIFS($B$5:$B$750,B12,$D$5:$D$750,WF_END_PERIOD,$R$5:$R$750,TRUE())>0),SUMIFS($S$5:$S$750,$B$5:$B$750,B12,$D$5:$D$750,WF_END_PERIOD,$R$5:$R$750,TRUE()),0) -> 0 | V12: =IF(AND(D12=WF_START_PERIOD,COUNTIFS($B$5:$B$750,B12,$D$5:$D$750,WF_END_PERIOD)>0),INDEX($E$5:$E$750,MATCH(B12&"|"&WF_END_PERIOD,$AC$5:$AC$750,0)),"") | W12: =COUNTIFS($B$5:$B$750,B12,$D$5:$D$750,WF_START_PERIOD,$R$5:$R$750,TRUE())>0 -> TRUE | X12: =COUNTIFS($B$5:$B$750,B12,$D$5:$D$750,WF_END_PERIOD,$R$5:$R$750,TRUE())>0 -> TRUE | Y12: =IF(AND(D12=WF_END_PERIOD,COUNTIFS($B$5:$B$750,B12,$D$5:$D$750,WF_START_PERIOD)>0),INDEX($E$5:$E$750,MATCH(B12&"|"&WF_START_PERIOD,$AC$5:$AC$750,0)),"") | Z12: =IF(AND(D12=WF_END_PERIOD,R12),1+COUNTIFS($D$5:$D$750,WF_END_PERIOD,$E$5:$E$750,E12,$R$5:$R$750,TRUE(),$S$5:$S$750,">"&S12)+COUNTIFS($D$5:$D$750,WF_END_PERIOD,$E$5:$E$750,E12,$R$5:$R$750,TRUE(),$S$5:$S$750,S12,$B$5:$B$750,"<"&B12),"") | AA12: =IF(AND(D12=WF_END_PERIOD,R12,Z12<>1),1+COUNTIFS($D$5:$D$750,WF_END_PERIOD,$R$5:$R$750,TRUE(),$Z$5:$Z$750,"<>1",$S$5:$S$750,">"&S12)+COUNTIFS($D$5:$D$750,WF_END_PERIOD,$R$5:$R$750,TRUE(),$Z$5:$Z$750,"<>1",$S$5:$S$750,S12,$B$5:$B$750,"<"&B12),"") | AB12: =OR(D12=WF_START_PERIOD,D12=WF_END_PERIOD) -> FALSE | AC12: =B12&"|"&D12 -> 14168|20220331
A13: =RawFinancials!A13 -> 10 | B13: =RawFinancials!C13 -> 14240 | C13: =RawFinancials!P13 -> NORTHWAY BANK | D13: =RawFinancials!W13 -> 20220331 | E13: =RawFinancials!Z13 -> NH | F13: =RawFinancials!B13 -> 1221074 | G13: =RawFinancials!U13 -> 0 | H13: =RawFinancials!O13 -> 2204 | I13: =IF(AND(ISNUMBER(G13),ISNUMBER(H13)),G13+H13,"") -> 2204 | J13: =RawFinancials!D13 -> 1020645 | K13: =RawFinancials!F13 -> 102113 | L13: =RawFinancials!L13 -> 824670 | M13: =RawFinancials!N13 -> 705835 | N13: =RawFinancials!X13 -> 0.069811881 | O13: =RawFinancials!V13 -> 15.106992 | P13: =IF(AND(ISNUMBER(L13),L13<>0,ISNUMBER(M13)),100*M13/L13,"") -> 85.589994 | Q13: =IF(AND(ISNUMBER(F13),F13<>0,ISNUMBER(K13)),100*K13/F13,"") -> 8.3625562 | R13: =AND(ISNUMBER(F13),F13>0,ISNUMBER(G13),G13>=0,ISNUMBER(H13),H13>=0) -> TRUE | S13: =IF(R13,100*I13/F13,"") -> 0.18049684 | T13: =NOT(AND(OR(AND(ISBLANK(RawFinancials!B13),ISBLANK(_RawBaseline!B10)),AND(ISNUMBER(RawFinancials!B13),ISNUMBER(_RawBaseline!B10),RawFinancials!B13=_RawBaseline!B10)),OR(AND(ISBLANK(RawFinancials!U13),ISBLANK(_RawBaseline!U10)),AND(ISNUMBER(RawFinancials!U13),ISNUMBER(_RawBaseline!U10),RawFinancials!U13=_RawBaseline!U10)),OR(AND(ISBLANK(RawFinancials!O13),ISBLANK(_RawBaseline!O10)),AND(ISNUMBER(RawFinancials!O13),ISNUMBER(_RawBaseline!O10),RawFinancials!O13=_RawBaseline!O10)))) -> FALSE | U13: =IF(AND(D13=WF_START_PERIOD,R13,COUNTIFS($B$5:$B$750,B13,$D$5:$D$750,WF_END_PERIOD,$R$5:$R$750,TRUE())>0),SUMIFS($S$5:$S$750,$B$5:$B$750,B13,$D$5:$D$750,WF_END_PERIOD,$R$5:$R$750,TRUE()),0) -> 0 | V13: =IF(AND(D13=WF_START_PERIOD,COUNTIFS($B$5:$B$750,B13,$D$5:$D$750,WF_END_PERIOD)>0),INDEX($E$5:$E$750,MATCH(B13&"|"&WF_END_PERIOD,$AC$5:$AC$750,0)),"") | W13: =COUNTIFS($B$5:$B$750,B13,$D$5:$D$750,WF_START_PERIOD,$R$5:$R$750,TRUE())>0 -> TRUE | X13: =COUNTIFS($B$5:$B$750,B13,$D$5:$D$750,WF_END_PERIOD,$R$5:$R$750,TRUE())>0 -> FALSE | Y13: =IF(AND(D13=WF_END_PERIOD,COUNTIFS($B$5:$B$750,B13,$D$5:$D$750,WF_START_PERIOD)>0),INDEX($E$5:$E$750,MATCH(B13&"|"&WF_START_PERIOD,$AC$5:$AC$750,0)),"") | Z13: =IF(AND(D13=WF_END_PERIOD,R13),1+COUNTIFS($D$5:$D$750,WF_END_PERIOD,$E$5:$E$750,E13,$R$5:$R$750,TRUE(),$S$5:$S$750,">"&S13)+COUNTIFS($D$5:$D$750,WF_END_PERIOD,$E$5:$E$750,E13,$R$5:$R$750,TRUE(),$S$5:$S$750,S13,$B$5:$B$750,"<"&B13),"") | AA13: =IF(AND(D13=WF_END_PERIOD,R13,Z13<>1),1+COUNTIFS($D$5:$D$750,WF_END_PERIOD,$R$5:$R$750,TRUE(),$Z$5:$Z$750,"<>1",$S$5:$S$750,">"&S13)+COUNTIFS($D$5:$D$750,WF_END_PERIOD,$R$5:$R$750,TRUE(),$Z$5:$Z$750,"<>1",$S$5:$S$750,S13,$B$5:$B$750,"<"&B13),"") | AB13: =OR(D13=WF_START_PERIOD,D13=WF_END_PERIOD) -> FALSE | AC13: =B13&"|"&D13 -> 14240|20220331
A14: =RawFinancials!A14 -> 11 | B14: =RawFinancials!C14 -> 17115 | C14: =RawFinancials!P14 -> PARTNERS BANK OF NEW ENGLAND | D14: =RawFinancials!W14 -> 20220331 | E14: =RawFinancials!Z14 -> ME | F14: =RawFinancials!B14 -> 836644 | G14: =RawFinancials!U14 -> 0 | H14: =RawFinancials!O14 -> 164 | I14: =IF(AND(ISNUMBER(G14),ISNUMBER(H14)),G14+H14,"") -> 164 | J14: =RawFinancials!D14 -> 738943 | K14: =RawFinancials!F14 -> 83239 | L14: =RawFinancials!L14 -> 656481 | M14: =RawFinancials!N14 -> 608827 | N14: =RawFinancials!X14 -> 1.1149693 | O14: =RawFinancials!V14 -> 15.606469 | P14: =IF(AND(ISNUMBER(L14),L14<>0,ISNUMBER(M14)),100*M14/L14,"") -> 92.740993 | Q14: =IF(AND(ISNUMBER(F14),F14<>0,ISNUMBER(K14)),100*K14/F14,"") -> 9.949154 | R14: =AND(ISNUMBER(F14),F14>0,ISNUMBER(G14),G14>=0,ISNUMBER(H14),H14>=0) -> TRUE | S14: =IF(R14,100*I14/F14,"") -> 0.019602125 | T14: =NOT(AND(OR(AND(ISBLANK(RawFinancials!B14),ISBLANK(_RawBaseline!B11)),AND(ISNUMBER(RawFinancials!B14),ISNUMBER(_RawBaseline!B11),RawFinancials!B14=_RawBaseline!B11)),OR(AND(ISBLANK(RawFinancials!U14),ISBLANK(_RawBaseline!U11)),AND(ISNUMBER(RawFinancials!U14),ISNUMBER(_RawBaseline!U11),RawFinancials!U14=_RawBaseline!U11)),OR(AND(ISBLANK(RawFinancials!O14),ISBLANK(_RawBaseline!O11)),AND(ISNUMBER(RawFinancials!O14),ISNUMBER(_RawBaseline!O11),RawFinancials!O14=_RawBaseline!O11)))) -> FALSE | U14: =IF(AND(D14=WF_START_PERIOD,R14,COUNTIFS($B$5:$B$750,B14,$D$5:$D$750,WF_END_PERIOD,$R$5:$R$750,TRUE())>0),SUMIFS($S$5:$S$750,$B$5:$B$750,B14,$D$5:$D$750,WF_END_PERIOD,$R$5:$R$750,TRUE()),0) -> 0 | V14: =IF(AND(D14=WF_START_PERIOD,COUNTIFS($B$5:$B$750,B14,$D$5:$D$750,WF_END_PERIOD)>0),INDEX($E$5:$E$750,MATCH(B14&"|"&WF_END_PERIOD,$AC$5:$AC$750,0)),"") | W14: =COUNTIFS($B$5:$B$750,B14,$D$5:$D$750,WF_START_PERIOD,$R$5:$R$750,TRUE())>0 -> TRUE | X14: =COUNTIFS($B$5:$B$750,B14,$D$5:$D$750,WF_END_PERIOD,$R$5:$R$750,TRUE())>0 -> TRUE | Y14: =IF(AND(D14=WF_END_PERIOD,COUNTIFS($B$5:$B$750,B14,$D$5:$D$750,WF_START_PERIOD)>0),INDEX($E$5:$E$750,MATCH(B14&"|"&WF_START_PERIOD,$AC$5:$AC$750,0)),"") | Z14: =IF(AND(D14=WF_END_PERIOD,R14),1+COUNTIFS($D$5:$D$750,WF_END_PERIOD,$E$5:$E$750,E14,$R$5:$R$750,TRUE(),$S$5:$S$750,">"&S14)+COUNTIFS($D$5:$D$750,WF_END_PERIOD,$E$5:$E$750,E14,$R$5:$R$750,TRUE(),$S$5:$S$750,S14,$B$5:$B$750,"<"&B14),"") | AA14: =IF(AND(D14=WF_END_PERIOD,R14,Z14<>1),1+COUNTIFS($D$5:$D$750,WF_END_PERIOD,$R$5:$R$750,TRUE(),$Z$5:$Z$750,"<>1",$S$5:$S$750,">"&S14)+COUNTIFS($D$5:$D$750,WF_END_PERIOD,$R$5:$R$750,TRUE(),$Z$5:$Z$750,"<>1",$S$5:$S$750,S14,$B$5:$B$750,"<"&B14),"") | AB14: =OR(D14=WF_START_PERIOD,D14=WF_END_PERIOD) -> FALSE | AC14: =B14&"|"&D14 -> 17115|20220331
A15: =RawFinancials!A15 -> 12 | B15: =RawFinancials!C15 -> 17180 | C15: =RawFinancials!P15 -> MEREDITH VILLAGE SAVINGS BANK | D15: =RawFinancials!W15 -> 20220331 | E15: =RawFinancials!Z15 -> NH | F15: =RawFinancials!B15 -> 1291920 | G15: =RawFinancials!U15 -> 0 | H15: =RawFinancials!O15 -> 5753 | I15: =IF(AND(ISNUMBER(G15),ISNUMBER(H15)),G15+H15,"") -> 5753 | J15: =RawFinancials!D15 -> 1121172 | K15: =RawFinancials!F15 -> 126979 | L15: =RawFinancials!L15 -> 1143017 | M15: =RawFinancials!N15 -> 937482 | N15: =RawFinancials!X15 -> 0.80278929 | O15: =RawFinancials!V15 -> 16.056943 | P15: =IF(AND(ISNUMBER(L15),L15<>0,ISNUMBER(M15)),100*M15/L15,"") -> 82.018203 | Q15: =IF(AND(ISNUMBER(F15),F15<>0,ISNUMBER(K15)),100*K15/F15,"") -> 9.8287046 | R15: =AND(ISNUMBER(F15),F15>0,ISNUMBER(G15),G15>=0,ISNUMBER(H15),H15>=0) -> TRUE | S15: =IF(R15,100*I15/F15,"") -> 0.44530621 | T15: =NOT(AND(OR(AND(ISBLANK(RawFinancials!B15),ISBLANK(_RawBaseline!B12)),AND(ISNUMBER(RawFinancials!B15),ISNUMBER(_RawBaseline!B12),RawFinancials!B15=_RawBaseline!B12)),OR(AND(ISBLANK(RawFinancials!U15),ISBLANK(_RawBaseline!U12)),AND(ISNUMBER(RawFinancials!U15),ISNUMBER(_RawBaseline!U12),RawFinancials!U15=_RawBaseline!U12)),OR(AND(ISBLANK(RawFinancials!O15),ISBLANK(_RawBaseline!O12)),AND(ISNUMBER(RawFinancials!O15),ISNUMBER(_RawBaseline!O12),RawFinancials!O15=_RawBaseline!O12)))) -> FALSE | U15: =IF(AND(D15=WF_START_PERIOD,R15,COUNTIFS($B$5:$B$750,B15,$D$5:$D$750,WF_END_PERIOD,$R$5:$R$750,TRUE())>0),SUMIFS($S$5:$S$750,$B$5:$B$750,B15,$D$5:$D$750,WF_END_PERIOD,$R$5:$R$750,TRUE()),0) -> 0 | V15: =IF(AND(D15=WF_START_PERIOD,COUNTIFS($B$5:$B$750,B15,$D$5:$D$750,WF_END_PERIOD)>0),INDEX($E$5:$E$750,MATCH(B15&"|"&WF_END_PERIOD,$AC$5:$AC$750,0)),"") | W15: =COUNTIFS($B$5:$B$750,B15,$D$5:$D$750,WF_START_PERIOD,$R$5:$R$750,TRUE())>0 -> TRUE | X15: =COUNTIFS($B$5:$B$750,B15,$D$5:$D$750,WF_END_PERIOD,$R$5:$R$750,TRUE())>0 -> TRUE | Y15: =IF(AND(D15=WF_END_PERIOD,COUNTIFS($B$5:$B$750,B15,$D$5:$D$750,WF_START_PERIOD)>0),INDEX($E$5:$E$750,MATCH(B15&"|"&WF_START_PERIOD,$AC$5:$AC$750,0)),"") | Z15: =IF(AND(D15=WF_END_PERIOD,R15),1+COUNTIFS($D$5:$D$750,WF_END_PERIOD,$E$5:$E$750,E15,$R$5:$R$750,TRUE(),$S$5:$S$750,">"&S15)+COUNTIFS($D$5:$D$750,WF_END_PERIOD,$E$5:$E$750,E15,$R$5:$R$750,TRUE(),$S$5:$S$750,S15,$B$5:$B$750,"<"&B15),"") | AA15: =IF(AND(D15=WF_END_PERIOD,R15,Z15<>1),1+COUNTIFS($D$5:$D$750,WF_END_PERIOD,$R$5:$R$750,TRUE(),$Z$5:$Z$750,"<>1",$S$5:$S$750,">"&S15)+COUNTIFS($D$5:$D$750,WF_END_PERIOD,$R$5:$R$750,TRUE(),$Z$5:$Z$750,"<>1",$S$5:$S$750,S15,$B$5:$B$750,"<"&B15),"") | AB15: =OR(D15=WF_START_PERIOD,D15=WF_END_PERIOD) -> FALSE | AC15: =B15&"|"&D15 -> 17180|20220331
A16: =RawFinancials!A16 -> 13 | B16: =RawFinancials!C16 -> 17443 | C16: =RawFinancials!P16 -> PISCATAQUA SAVINGS BANK | D16: =RawFinancials!W16 -> 20220331 | E16: =RawFinancials!Z16 -> NH | F16: =RawFinancials!B16 -> 352255 | G16: =RawFinancials!U16 -> 0 | H16: =RawFinancials!O16 -> 842 | I16: =IF(AND(ISNUMBER(G16),ISNUMBER(H16)),G16+H16,"") -> 842 | J16: =RawFinancials!D16 -> 302135 | K16: =RawFinancials!F16 -> 42822 | L16: =RawFinancials!L16 -> 188952 | M16: =RawFinancials!N16 -> 186037 | N16: =RawFinancials!X16 -> 0.61925341 | O16: =RawFinancials!V16 -> 0 | P16: =IF(AND(ISNUMBER(L16),L16<>0,ISNUMBER(M16)),100*M16/L16,"") -> 98.45728 | Q16: =IF(AND(ISNUMBER(F16),F16<>0,ISNUMBER(K16)),100*K16/F16,"") -> 12.156534 | R16: =AND(ISNUMBER(F16),F16>0,ISNUMBER(G16),G16>=0,ISNUMBER(H16),H16>=0) -> TRUE | S16: =IF(R16,100*I16/F16,"") -> 0.23903138 | T16: =NOT(AND(OR(AND(ISBLANK(RawFinancials!B16),ISBLANK(_RawBaseline!B13)),AND(ISNUMBER(RawFinancials!B16),ISNUMBER(_RawBaseline!B13),RawFinancials!B16=_RawBaseline!B13)),OR(AND(ISBLANK(RawFinancials!U16),ISBLANK(_RawBaseline!U13)),AND(ISNUMBER(RawFinancials!U16),ISNUMBER(_RawBaseline!U13),RawFinancials!U16=_RawBaseline!U13)),OR(AND(ISBLANK(RawFinancials!O16),ISBLANK(_RawBaseline!O13)),AND(ISNUMBER(RawFinancials!O16),ISNUMBER(_RawBaseline!O13),RawFinancials!O16=_RawBaseline!O13)))) -> FALSE | U16: =IF(AND(D16=WF_START_PERIOD,R16,COUNTIFS($B$5:$B$750,B16,$D$5:$D$750,WF_END_PERIOD,$R$5:$R$750,TRUE())>0),SUMIFS($S$5:$S$750,$B$5:$B$750,B16,$D$5:$D$750,WF_END_PERIOD,$R$5:$R$750,TRUE()),0) -> 0 | V16: =IF(AND(D16=WF_START_PERIOD,COUNTIFS($B$5:$B$750,B16,$D$5:$D$750,WF_END_PERIOD)>0),INDEX($E$5:$E$750,MATCH(B16&"|"&WF_END_PERIOD,$AC$5:$AC$750,0)),"") | W16: =COUNTIFS($B$5:$B$750,B16,$D$5:$D$750,WF_START_PERIOD,$R$5:$R$750,TRUE())>0 -> TRUE | X16: =COUNTIFS($B$5:$B$750,B16,$D$5:$D$750,WF_END_PERIOD,$R$5:$R$750,TRUE())>0 -> TRUE | Y16: =IF(AND(D16=WF_END_PERIOD,COUNTIFS($B$5:$B$750,B16,$D$5:$D$750,WF_START_PERIOD)>0),INDEX($E$5:$E$750,MATCH(B16&"|"&WF_START_PERIOD,$AC$5:$AC$750,0)),"") | Z16: =IF(AND(D16=WF_END_PERIOD,R16),1+COUNTIFS($D$5:$D$750,WF_END_PERIOD,$E$5:$E$750,E16,$R$5:$R$750,TRUE(),$S$5:$S$750,">"&S16)+COUNTIFS($D$5:$D$750,WF_END_PERIOD,$E$5:$E$750,E16,$R$5:$R$750,TRUE(),$S$5:$S$750,S16,$B$5:$B$750,"<"&B16),"") | AA16: =IF(AND(D16=WF_END_PERIOD,R16,Z16<>1),1+COUNTIFS($D$5:$D$750,WF_END_PERIOD,$R$5:$R$750,TRUE(),$Z$5:$Z$750,"<>1",$S$5:$S$750,">"&S16)+COUNTIFS($D$5:$D$750,WF_END_PERIOD,$R$5:$R$750,TRUE(),$Z$5:$Z$750,"<>1",$S$5:$S$750,S16,$B$5:$B$750,"<"&B16),"") | AB16: =OR(D16=WF_START_PERIOD,D16=WF_END_PERIOD) -> FALSE | AC16: =B16&"|"&D16 -> 17443|20220331
... A750: =RawFinancials!A750 -> 747 | B750: =RawFinancials!C750 -> 6280 | C750: =RawFinancials!P750 -> THE FIRST NATIONAL BANK OF ORWELL | D750: =RawFinancials!W750 -> 20250630 | E750: =RawFinancials!Z750 -> VT | F750: =RawFinancials!B750 -> 87770 | G750: =RawFinancials!U750 -> 0 | H750: =RawFinancials!O750 -> 1455 | I750: =IF(AND(ISNUMBER(G750),ISNUMBER(H750)),G750+H750,"") -> 1455 | J750: =RawFinancials!D750 -> 77256 | K750: =RawFinancials!F750 -> 9949 | L750: =RawFinancials!L750 -> 73100 | M750: =RawFinancials!N750 -> 64947 | N750: =RawFinancials!X750 -> 1.3665403 | O750: =RawFinancials!V750 -> 0 | P750: =IF(AND(ISNUMBER(L750),L750<>0,ISNUMBER(M750)),100*M750/L750,"") -> 88.846785 | Q750: =IF(AND(ISNUMBER(F750),F750<>0,ISNUMBER(K750)),100*K750/F750,"") -> 11.335308 | R750: =AND(ISNUMBER(F750),F750>0,ISNUMBER(G750),G750>=0,ISNUMBER(H750),H750>=0) -> TRUE | S750: =IF(R750,100*I750/F750,"") -> 1.6577418 | T750: =NOT(AND(OR(AND(ISBLANK(RawFinancials!B750),ISBLANK(_RawBaseline!B747)),AND(ISNUMBER(RawFinancials!B750),ISNUMBER(_RawBaseline!B747),RawFinancials!B750=_RawBaseline!B747)),OR(AND(ISBLANK(RawFinancials!U750),ISBLANK(_RawBaseline!U747)),AND(ISNUMBER(RawFinancials!U750),ISNUMBER(_RawBaseline!U747),RawFinancials!U750=_RawBaseline!U747)),OR(AND(ISBLANK(RawFinancials!O750),ISBLANK(_RawBaseline!O747)),AND(ISNUMBER(RawFinancials!O750),ISNUMBER(_RawBaseline!O747),RawFinancials!O750=_RawBaseline!O747)))) -> FALSE | U750: =IF(AND(D750=WF_START_PERIOD,R750,COUNTIFS($B$5:$B$750,B750,$D$5:$D$750,WF_END_PERIOD,$R$5:$R$750,TRUE())>0),SUMIFS($S$5:$S$750,$B$5:$B$750,B750,$D$5:$D$750,WF_END_PERIOD,$R$5:$R$750,TRUE()),0) -> 0 | V750: =IF(AND(D750=WF_START_PERIOD,COUNTIFS($B$5:$B$750,B750,$D$5:$D$750,WF_END_PERIOD)>0),INDEX($E$5:$E$750,MATCH(B750&"|"&WF_END_PERIOD,$AC$5:$AC$750,0)),"") | W750: =COUNTIFS($B$5:$B$750,B750,$D$5:$D$750,WF_START_PERIOD,$R$5:$R$750,TRUE())>0 -> TRUE | X750: =COUNTIFS($B$5:$B$750,B750,$D$5:$D$750,WF_END_PERIOD,$R$5:$R$750,TRUE())>0 -> TRUE | Y750: =IF(AND(D750=WF_END_PERIOD,COUNTIFS($B$5:$B$750,B750,$D$5:$D$750,WF_START_PERIOD)>0),INDEX($E$5:$E$750,MATCH(B750&"|"&WF_START_PERIOD,$AC$5:$AC$750,0)),"") -> VT | Z750: =IF(AND(D750=WF_END_PERIOD,R750),1+COUNTIFS($D$5:$D$750,WF_END_PERIOD,$E$5:$E$750,E750,$R$5:$R$750,TRUE(),$S$5:$S$750,">"&S750)+COUNTIFS($D$5:$D$750,WF_END_PERIOD,$E$5:$E$750,E750,$R$5:$R$750,TRUE(),$S$5:$S$750,S750,$B$5:$B$750,"<"&B750),"") -> 1 | AA750: =IF(AND(D750=WF_END_PERIOD,R750,Z750<>1),1+COUNTIFS($D$5:$D$750,WF_END_PERIOD,$R$5:$R$750,TRUE(),$Z$5:$Z$750,"<>1",$S$5:$S$750,">"&S750)+COUNTIFS($D$5:$D$750,WF_END_PERIOD,$R$5:$R$750,TRUE(),$Z$5:$Z$750,"<>1",$S$5:$S$750,S750,$B$5:$B$750,"<"&B750),"") | AB750: =OR(D750=WF_START_PERIOD,D750=WF_END_PERIOD) -> TRUE | AC750: =B750&"|"&D750 -> 6280|20250630

Sheet DataAudit
A1: Data Audit
A2: Source shape, key integrity, quarter coverage, institution linkage, and formula-driven invalid-row reporting.
A4: Audit item | B4: Result | C4: Interpretation
A5: Financial source rows | B5: 746 | C5: Required complete local copy
A6: Financial columns | B6: 25 | C6: Original columns; source_row added at left
A7: Distinct CERT | B7: 54 | C7: Across all quarters
A8: Distinct quarters | B8: 14 | C8: 2022-03-31 through 2025-06-30
A9: Duplicate CERT + REPDTE | B9: 0 | C9: Expected 0
A10: Institution rows | B10: 355 | C10: Later snapshot
A11: Duplicate institution CERT | B11: 0 | C11: Expected 0 for one-to-one join
A12: Financial rows matched to institution CERT | B12: 746 | C12: 746 of 746
A13: Unmatched financial CERT | B13: 0 | C13: Expected 0
A14: Unused institution snapshot CERT | B14: 301 | C14: Historical/later universe; not joined into quarter population
A17: Quarter coverage and invalid proxy inputs
A18: REPDTE | B18: Rows | C18: Banks | D18: VT | E18: NH | F18: ME | G18: Missing vs 54-bank union | H18: ASSET blank/zero | I18: P9ASSET blank | J18: NAASSET blank | K18: Invalid proxy rows
A19: 20220331 | B19: =COUNTIF(BankQuarter!$D$5:$D$750,A19) -> 51 | C19: =COUNTIF(BankQuarter!$D$5:$D$750,A19) -> 51 | D19: =COUNTIFS(BankQuarter!$D$5:$D$750,$A19,BankQuarter!$E$5:$E$750,"VT") -> 11 | E19: =COUNTIFS(BankQuarter!$D$5:$D$750,$A19,BankQuarter!$E$5:$E$750,"NH") -> 17 | F19: =COUNTIFS(BankQuarter!$D$5:$D$750,$A19,BankQuarter!$E$5:$E$750,"ME") -> 23 | G19: =54-C19 -> 3 | H19: =COUNTIFS(BankQuarter!$D$5:$D$750,$A19,BankQuarter!$F$5:$F$750,"<=0")+COUNTIFS(BankQuarter!$D$5:$D$750,$A19,BankQuarter!$F$5:$F$750,"") -> 0 | I19: =COUNTIFS(BankQuarter!$D$5:$D$750,$A19,BankQuarter!$G$5:$G$750,"") -> 0 | J19: =COUNTIFS(BankQuarter!$D$5:$D$750,$A19,BankQuarter!$H$5:$H$750,"") -> 0 | K19: =COUNTIFS(BankQuarter!$D$5:$D$750,$A19,BankQuarter!$R$5:$R$750,FALSE()) -> 0
A20: 20220630 | B20: =COUNTIF(BankQuarter!$D$5:$D$750,A20) -> 52 | C20: =COUNTIF(BankQuarter!$D$5:$D$750,A20) -> 52 | D20: =COUNTIFS(BankQuarter!$D$5:$D$750,$A20,BankQuarter!$E$5:$E$750,"VT") -> 11 | E20: =COUNTIFS(BankQuarter!$D$5:$D$750,$A20,BankQuarter!$E$5:$E$750,"NH") -> 18 | F20: =COUNTIFS(BankQuarter!$D$5:$D$750,$A20,BankQuarter!$E$5:$E$750,"ME") -> 23 | G20: =54-C20 -> 2 | H20: =COUNTIFS(BankQuarter!$D$5:$D$750,$A20,BankQuarter!$F$5:$F$750,"<=0")+COUNTIFS(BankQuarter!$D$5:$D$750,$A20,BankQuarter!$F$5:$F$750,"") -> 0 | I20: =COUNTIFS(BankQuarter!$D$5:$D$750,$A20,BankQuarter!$G$5:$G$750,"") -> 0 | J20: =COUNTIFS(BankQuarter!$D$5:$D$750,$A20,BankQuarter!$H$5:$H$750,"") -> 0 | K20: =COUNTIFS(BankQuarter!$D$5:$D$750,$A20,BankQuarter!$R$5:$R$750,FALSE()) -> 0
A21: 20220930 | B21: =COUNTIF(BankQuarter!$D$5:$D$750,A21) -> 53 | C21: =COUNTIF(BankQuarter!$D$5:$D$750,A21) -> 53 | D21: =COUNTIFS(BankQuarter!$D$5:$D$750,$A21,BankQuarter!$E$5:$E$750,"VT") -> 12 | E21: =COUNTIFS(BankQuarter!$D$5:$D$750,$A21,BankQuarter!$E$5:$E$750,"NH") -> 18 | F21: =COUNTIFS(BankQuarter!$D$5:$D$750,$A21,BankQuarter!$E$5:$E$750,"ME") -> 23 | G21: =54-C21 -> 1 | H21: =COUNTIFS(BankQuarter!$D$5:$D$750,$A21,BankQuarter!$F$5:$F$750,"<=0")+COUNTIFS(BankQuarter!$D$5:$D$750,$A21,BankQuarter!$F$5:$F$750,"") -> 0 | I21: =COUNTIFS(BankQuarter!$D$5:$D$750,$A21,BankQuarter!$G$5:$G$750,"") -> 0 | J21: =COUNTIFS(BankQuarter!$D$5:$D$750,$A21,BankQuarter!$H$5:$H$750,"") -> 0 | K21: =COUNTIFS(BankQuarter!$D$5:$D$750,$A21,BankQuarter!$R$5:$R$750,FALSE()) -> 0
A22: 20221231 | B22: =COUNTIF(BankQuarter!$D$5:$D$750,A22) -> 54 | C22: =COUNTIF(BankQuarter!$D$5:$D$750,A22) -> 54 | D22: =COUNTIFS(BankQuarter!$D$5:$D$750,$A22,BankQuarter!$E$5:$E$750,"VT") -> 12 | E22: =COUNTIFS(BankQuarter!$D$5:$D$750,$A22,BankQuarter!$E$5:$E$750,"NH") -> 19 | F22: =COUNTIFS(BankQuarter!$D$5:$D$750,$A22,BankQuarter!$E$5:$E$750,"ME") -> 23 | G22: =54-C22 -> 0 | H22: =COUNTIFS(BankQuarter!$D$5:$D$750,$A22,BankQuarter!$F$5:$F$750,"<=0")+COUNTIFS(BankQuarter!$D$5:$D$750,$A22,BankQuarter!$F$5:$F$750,"") -> 0 | I22: =COUNTIFS(BankQuarter!$D$5:$D$750,$A22,BankQuarter!$G$5:$G$750,"") -> 0 | J22: =COUNTIFS(BankQuarter!$D$5:$D$750,$A22,BankQuarter!$H$5:$H$750,"") -> 0 | K22: =COUNTIFS(BankQuarter!$D$5:$D$750,$A22,BankQuarter!$R$5:$R$750,FALSE()) -> 0
A23: 20230331 | B23: =COUNTIF(BankQuarter!$D$5:$D$750,A23) -> 54 | C23: =COUNTIF(BankQuarter!$D$5:$D$750,A23) -> 54 | D23: =COUNTIFS(BankQuarter!$D$5:$D$750,$A23,BankQuarter!$E$5:$E$750,"VT") -> 12 | E23: =COUNTIFS(BankQuarter!$D$5:$D$750,$A23,BankQuarter!$E$5:$E$750,"NH") -> 19 | F23: =COUNTIFS(BankQuarter!$D$5:$D$750,$A23,BankQuarter!$E$5:$E$750,"ME") -> 23 | G23: =54-C23 -> 0 | H23: =COUNTIFS(BankQuarter!$D$5:$D$750,$A23,BankQuarter!$F$5:$F$750,"<=0")+COUNTIFS(BankQuarter!$D$5:$D$750,$A23,BankQuarter!$F$5:$F$750,"") -> 0 | I23: =COUNTIFS(BankQuarter!$D$5:$D$750,$A23,BankQuarter!$G$5:$G$750,"") -> 0 | J23: =COUNTIFS(BankQuarter!$D$5:$D$750,$A23,BankQuarter!$H$5:$H$750,"") -> 0 | K23: =COUNTIFS(BankQuarter!$D$5:$D$750,$A23,BankQuarter!$R$5:$R$750,FALSE()) -> 0
A24: 20230630 | B24: =COUNTIF(BankQuarter!$D$5:$D$750,A24) -> 54 | C24: =COUNTIF(BankQuarter!$D$5:$D$750,A24) -> 54 | D24: =COUNTIFS(BankQuarter!$D$5:$D$750,$A24,BankQuarter!$E$5:$E$750,"VT") -> 12 | E24: =COUNTIFS(BankQuarter!$D$5:$D$750,$A24,BankQuarter!$E$5:$E$750,"NH") -> 19 | F24: =COUNTIFS(BankQuarter!$D$5:$D$750,$A24,BankQuarter!$E$5:$E$750,"ME") -> 23 | G24: =54-C24 -> 0 | H24: =COUNTIFS(BankQuarter!$D$5:$D$750,$A24,BankQuarter!$F$5:$F$750,"<=0")+COUNTIFS(BankQuarter!$D$5:$D$750,$A24,BankQuarter!$F$5:$F$750,"") -> 0 | I24: =COUNTIFS(BankQuarter!$D$5:$D$750,$A24,BankQuarter!$G$5:$G$750,"") -> 0 | J24: =COUNTIFS(BankQuarter!$D$5:$D$750,$A24,BankQuarter!$H$5:$H$750,"") -> 0 | K24: =COUNTIFS(BankQuarter!$D$5:$D$750,$A24,BankQuarter!$R$5:$R$750,FALSE()) -> 0
A25: 20230930 | B25: =COUNTIF(BankQuarter!$D$5:$D$750,A25) -> 54 | C25: =COUNTIF(BankQuarter!$D$5:$D$750,A25) -> 54 | D25: =COUNTIFS(BankQuarter!$D$5:$D$750,$A25,BankQuarter!$E$5:$E$750,"VT") -> 12 | E25: =COUNTIFS(BankQuarter!$D$5:$D$750,$A25,BankQuarter!$E$5:$E$750,"NH") -> 19 | F25: =COUNTIFS(BankQuarter!$D$5:$D$750,$A25,BankQuarter!$E$5:$E$750,"ME") -> 23 | G25: =54-C25 -> 0 | H25: =COUNTIFS(BankQuarter!$D$5:$D$750,$A25,BankQuarter!$F$5:$F$750,"<=0")+COUNTIFS(BankQuarter!$D$5:$D$750,$A25,BankQuarter!$F$5:$F$750,"") -> 0 | I25: =COUNTIFS(BankQuarter!$D$5:$D$750,$A25,BankQuarter!$G$5:$G$750,"") -> 0 | J25: =COUNTIFS(BankQuarter!$D$5:$D$750,$A25,BankQuarter!$H$5:$H$750,"") -> 0 | K25: =COUNTIFS(BankQuarter!$D$5:$D$750,$A25,BankQuarter!$R$5:$R$750,FALSE()) -> 0
A26: 20231231 | B26: =COUNTIF(BankQuarter!$D$5:$D$750,A26) -> 54 | C26: =COUNTIF(BankQuarter!$D$5:$D$750,A26) -> 54 | D26: =COUNTIFS(BankQuarter!$D$5:$D$750,$A26,BankQuarter!$E$5:$E$750,"VT") -> 12 | E26: =COUNTIFS(BankQuarter!$D$5:$D$750,$A26,BankQuarter!$E$5:$E$750,"NH") -> 19 | F26: =COUNTIFS(BankQuarter!$D$5:$D$750,$A26,BankQuarter!$E$5:$E$750,"ME") -> 23 | G26: =54-C26 -> 0 | H26: =COUNTIFS(BankQuarter!$D$5:$D$750,$A26,BankQuarter!$F$5:$F$750,"<=0")+COUNTIFS(BankQuarter!$D$5:$D$750,$A26,BankQuarter!$F$5:$F$750,"") -> 0 | I26: =COUNTIFS(BankQuarter!$D$5:$D$750,$A26,BankQuarter!$G$5:$G$750,"") -> 0 | J26: =COUNTIFS(BankQuarter!$D$5:$D$750,$A26,BankQuarter!$H$5:$H$750,"") -> 0 | K26: =COUNTIFS(BankQuarter!$D$5:$D$750,$A26,BankQuarter!$R$5:$R$750,FALSE()) -> 0
A27: 20240331 | B27: =COUNTIF(BankQuarter!$D$5:$D$750,A27) -> 54 | C27: =COUNTIF(BankQuarter!$D$5:$D$750,A27) -> 54 | D27: =COUNTIFS(BankQuarter!$D$5:$D$750,$A27,BankQuarter!$E$5:$E$750,"VT") -> 12 | E27: =COUNTIFS(BankQuarter!$D$5:$D$750,$A27,BankQuarter!$E$5:$E$750,"NH") -> 19 | F27: =COUNTIFS(BankQuarter!$D$5:$D$750,$A27,BankQuarter!$E$5:$E$750,"ME") -> 23 | G27: =54-C27 -> 0 | H27: =COUNTIFS(BankQuarter!$D$5:$D$750,$A27,BankQuarter!$F$5:$F$750,"<=0")+COUNTIFS(BankQuarter!$D$5:$D$750,$A27,BankQuarter!$F$5:$F$750,"") -> 0 | I27: =COUNTIFS(BankQuarter!$D$5:$D$750,$A27,BankQuarter!$G$5:$G$750,"") -> 0 | J27: =COUNTIFS(BankQuarter!$D$5:$D$750,$A27,BankQuarter!$H$5:$H$750,"") -> 0 | K27: =COUNTIFS(BankQuarter!$D$5:$D$750,$A27,BankQuarter!$R$5:$R$750,FALSE()) -> 0
A28: 20240630 | B28: =COUNTIF(BankQuarter!$D$5:$D$750,A28) -> 54 | C28: =COUNTIF(BankQuarter!$D$5:$D$750,A28) -> 54 | D28: =COUNTIFS(BankQuarter!$D$5:$D$750,$A28,BankQuarter!$E$5:$E$750,"VT") -> 12 | E28: =COUNTIFS(BankQuarter!$D$5:$D$750,$A28,BankQuarter!$E$5:$E$750,"NH") -> 19 | F28: =COUNTIFS(BankQuarter!$D$5:$D$750,$A28,BankQuarter!$E$5:$E$750,"ME") -> 23 | G28: =54-C28 -> 0 | H28: =COUNTIFS(BankQuarter!$D$5:$D$750,$A28,BankQuarter!$F$5:$F$750,"<=0")+COUNTIFS(BankQuarter!$D$5:$D$750,$A28,BankQuarter!$F$5:$F$750,"") -> 0 | I28: =COUNTIFS(BankQuarter!$D$5:$D$750,$A28,BankQuarter!$G$5:$G$750,"") -> 0 | J28: =COUNTIFS(BankQuarter!$D$5:$D$750,$A28,BankQuarter!$H$5:$H$750,"") -> 0 | K28: =COUNTIFS(BankQuarter!$D$5:$D$750,$A28,BankQuarter!$R$5:$R$750,FALSE()) -> 0
A29: 20240930 | B29: =COUNTIF(BankQuarter!$D$5:$D$750,A29) -> 54 | C29: =COUNTIF(BankQuarter!$D$5:$D$750,A29) -> 54 | D29: =COUNTIFS(BankQuarter!$D$5:$D$750,$A29,BankQuarter!$E$5:$E$750,"VT") -> 12 | E29: =COUNTIFS(BankQuarter!$D$5:$D$750,$A29,BankQuarter!$E$5:$E$750,"NH") -> 19 | F29: =COUNTIFS(BankQuarter!$D$5:$D$750,$A29,BankQuarter!$E$5:$E$750,"ME") -> 23 | G29: =54-C29 -> 0 | H29: =COUNTIFS(BankQuarter!$D$5:$D$750,$A29,BankQuarter!$F$5:$F$750,"<=0")+COUNTIFS(BankQuarter!$D$5:$D$750,$A29,BankQuarter!$F$5:$F$750,"") -> 0 | I29: =COUNTIFS(BankQuarter!$D$5:$D$750,$A29,BankQuarter!$G$5:$G$750,"") -> 0 | J29: =COUNTIFS(BankQuarter!$D$5:$D$750,$A29,BankQuarter!$H$5:$H$750,"") -> 0 | K29: =COUNTIFS(BankQuarter!$D$5:$D$750,$A29,BankQuarter!$R$5:$R$750,FALSE()) -> 0
A30: 20241231 | B30: =COUNTIF(BankQuarter!$D$5:$D$750,A30) -> 54 | C30: =COUNTIF(BankQuarter!$D$5:$D$750,A30) -> 54 | D30: =COUNTIFS(BankQuarter!$D$5:$D$750,$A30,BankQuarter!$E$5:$E$750,"VT") -> 12 | E30: =COUNTIFS(BankQuarter!$D$5:$D$750,$A30,BankQuarter!$E$5:$E$750,"NH") -> 19 | F30: =COUNTIFS(BankQuarter!$D$5:$D$750,$A30,BankQuarter!$E$5:$E$750,"ME") -> 23 | G30: =54-C30 -> 0 | H30: =COUNTIFS(BankQuarter!$D$5:$D$750,$A30,BankQuarter!$F$5:$F$750,"<=0")+COUNTIFS(BankQuarter!$D$5:$D$750,$A30,BankQuarter!$F$5:$F$750,"") -> 0 | I30: =COUNTIFS(BankQuarter!$D$5:$D$750,$A30,BankQuarter!$G$5:$G$750,"") -> 0 | J30: =COUNTIFS(BankQuarter!$D$5:$D$750,$A30,BankQuarter!$H$5:$H$750,"") -> 0 | K30: =COUNTIFS(BankQuarter!$D$5:$D$750,$A30,BankQuarter!$R$5:$R$750,FALSE()) -> 0
... A32: 20250630 | B32: =COUNTIF(BankQuarter!$D$5:$D$750,A32) -> 52 | C32: =COUNTIF(BankQuarter!$D$5:$D$750,A32) -> 52 | D32: =COUNTIFS(BankQuarter!$D$5:$D$750,$A32,BankQuarter!$E$5:$E$750,"VT") -> 12 | E32: =COUNTIFS(BankQuarter!$D$5:$D$750,$A32,BankQuarter!$E$5:$E$750,"NH") -> 18 | F32: =COUNTIFS(BankQuarter!$D$5:$D$750,$A32,BankQuarter!$E$5:$E$750,"ME") -> 22 | G32: =54-C32 -> 2 | H32: =COUNTIFS(BankQuarter!$D$5:$D$750,$A32,BankQuarter!$F$5:$F$750,"<=0")+COUNTIFS(BankQuarter!$D$5:$D$750,$A32,BankQuarter!$F$5:$F$750,"") -> 0 | I32: =COUNTIFS(BankQuarter!$D$5:$D$750,$A32,BankQuarter!$G$5:$G$750,"") -> 0 | J32: =COUNTIFS(BankQuarter!$D$5:$D$750,$A32,BankQuarter!$H$5:$H$750,"") -> 0 | K32: =COUNTIFS(BankQuarter!$D$5:$D$750,$A32,BankQuarter!$R$5:$R$750,FALSE()) -> 0
A35: Current input checks
A36: Start exists | B36: =COUNTIF(BankQuarter!$D$5:$D$750,WF_START_PERIOD)>0 -> TRUE
A37: End exists | B37: =COUNTIF(BankQuarter!$D$5:$D$750,WF_END_PERIOD)>0 -> TRUE
A38: Start before end | B38: =WF_START_PERIOD<WF_END_PERIOD -> TRUE
A39: Slots valid | B39: =AND(ISNUMBER(WF_REVIEW_SLOTS),WF_REVIEW_SLOTS=INT(WF_REVIEW_SLOTS),WF_REVIEW_SLOTS>=3,WF_REVIEW_SLOTS<=12) -> TRUE
A40: Valid end banks | B40: =COUNTIFS(BankQuarter!$D$5:$D$750,WF_END_PERIOD,BankQuarter!$R$5:$R$750,TRUE()) -> 52
A41: Invalid end rows | B41: =COUNTIFS(BankQuarter!$D$5:$D$750,WF_END_PERIOD,BankQuarter!$R$5:$R$750,FALSE()) -> 0
A42: Valid VT / NH / ME | B42: =COUNTIFS(BankQuarter!$D$5:$D$750,WF_END_PERIOD,BankQuarter!$E$5:$E$750,"VT",BankQuarter!$R$5:$R$750,TRUE())&" / "&COUNTIFS(BankQuarter!$D$5:$D$750,WF_END_PERIOD,BankQuarter!$E$5:$E$750,"NH",BankQuarter!$R$5:$R$750,TRUE())&" / "&COUNTIFS(BankQuarter!$D$5:$D$750,WF_END_PERIOD,BankQuarter!$E$5:$E$750,"ME",BankQuarter!$R$5:$R$750,TRUE()) -> 12 / 18 / 22
A43: Model valid | B43: =WF_MODEL_VALID -> TRUE
A44: Raw unchanged | B44: =WF_RAW_UNCHANGED -> TRUE

Sheet PeerQuarter
A1: Quarterly Peer Aggregates
A2: Rates use sum of valid numerators divided by sum of valid ASSET; bank percentages are never averaged.
A4: REPDTE | B4: Group | C4: Valid banks | D4: ASSET sum ($000) | E4: P9 + NA sum ($000) | F4: Proxy % | G4: Invalid rows
A5: 20220331 | B5: ALL | C5: =COUNTIFS(BankQuarter!$D$5:$D$750,A5,BankQuarter!$R$5:$R$750,TRUE()) -> 51 | D5: =SUMIFS(BankQuarter!$F$5:$F$750,BankQuarter!$D$5:$D$750,A5,BankQuarter!$R$5:$R$750,TRUE()) -> 59852474 | E5: =SUMIFS(BankQuarter!$I$5:$I$750,BankQuarter!$D$5:$D$750,A5,BankQuarter!$R$5:$R$750,TRUE()) -> 136841 | F5: =IFERROR(100*E5/D5,"") -> 0.22863048 | G5: =COUNTIFS(BankQuarter!$D$5:$D$750,A5,BankQuarter!$R$5:$R$750,FALSE()) -> 0
A6: 20220331 | B6: ME | C6: =COUNTIFS(BankQuarter!$D$5:$D$750,A6,BankQuarter!$R$5:$R$750,TRUE(),BankQuarter!$E$5:$E$750,B6) -> 23 | D6: =SUMIFS(BankQuarter!$F$5:$F$750,BankQuarter!$D$5:$D$750,A6,BankQuarter!$R$5:$R$750,TRUE(),BankQuarter!$E$5:$E$750,B6) -> 37324757 | E6: =SUMIFS(BankQuarter!$I$5:$I$750,BankQuarter!$D$5:$D$750,A6,BankQuarter!$R$5:$R$750,TRUE(),BankQuarter!$E$5:$E$750,B6) -> 79744 | F6: =IFERROR(100*E6/D6,"") -> 0.21364908 | G6: =COUNTIFS(BankQuarter!$D$5:$D$750,A6,BankQuarter!$R$5:$R$750,FALSE(),BankQuarter!$E$5:$E$750,B6) -> 0
A7: 20220331 | B7: NH | C7: =COUNTIFS(BankQuarter!$D$5:$D$750,A7,BankQuarter!$R$5:$R$750,TRUE(),BankQuarter!$E$5:$E$750,B7) -> 17 | D7: =SUMIFS(BankQuarter!$F$5:$F$750,BankQuarter!$D$5:$D$750,A7,BankQuarter!$R$5:$R$750,TRUE(),BankQuarter!$E$5:$E$750,B7) -> 15167858 | E7: =SUMIFS(BankQuarter!$I$5:$I$750,BankQuarter!$D$5:$D$750,A7,BankQuarter!$R$5:$R$750,TRUE(),BankQuarter!$E$5:$E$750,B7) -> 23673 | F7: =IFERROR(100*E7/D7,"") -> 0.15607345 | G7: =COUNTIFS(BankQuarter!$D$5:$D$750,A7,BankQuarter!$R$5:$R$750,FALSE(),BankQuarter!$E$5:$E$750,B7) -> 0
A8: 20220331 | B8: VT | C8: =COUNTIFS(BankQuarter!$D$5:$D$750,A8,BankQuarter!$R$5:$R$750,TRUE(),BankQuarter!$E$5:$E$750,B8) -> 11 | D8: =SUMIFS(BankQuarter!$F$5:$F$750,BankQuarter!$D$5:$D$750,A8,BankQuarter!$R$5:$R$750,TRUE(),BankQuarter!$E$5:$E$750,B8) -> 7359859 | E8: =SUMIFS(BankQuarter!$I$5:$I$750,BankQuarter!$D$5:$D$750,A8,BankQuarter!$R$5:$R$750,TRUE(),BankQuarter!$E$5:$E$750,B8) -> 33424 | F8: =IFERROR(100*E8/D8,"") -> 0.45413914 | G8: =COUNTIFS(BankQuarter!$D$5:$D$750,A8,BankQuarter!$R$5:$R$750,FALSE(),BankQuarter!$E$5:$E$750,B8) -> 0
A9: 20220630 | B9: ALL | C9: =COUNTIFS(BankQuarter!$D$5:$D$750,A9,BankQuarter!$R$5:$R$750,TRUE()) -> 52 | D9: =SUMIFS(BankQuarter!$F$5:$F$750,BankQuarter!$D$5:$D$750,A9,BankQuarter!$R$5:$R$750,TRUE()) -> 60747875 | E9: =SUMIFS(BankQuarter!$I$5:$I$750,BankQuarter!$D$5:$D$750,A9,BankQuarter!$R$5:$R$750,TRUE()) -> 116533 | F9: =IFERROR(100*E9/D9,"") -> 0.19183058 | G9: =COUNTIFS(BankQuarter!$D$5:$D$750,A9,BankQuarter!$R$5:$R$750,FALSE()) -> 0
A10: 20220630 | B10: ME | C10: =COUNTIFS(BankQuarter!$D$5:$D$750,A10,BankQuarter!$R$5:$R$750,TRUE(),BankQuarter!$E$5:$E$750,B10) -> 23 | D10: =SUMIFS(BankQuarter!$F$5:$F$750,BankQuarter!$D$5:$D$750,A10,BankQuarter!$R$5:$R$750,TRUE(),BankQuarter!$E$5:$E$750,B10) -> 38015500 | E10: =SUMIFS(BankQuarter!$I$5:$I$750,BankQuarter!$D$5:$D$750,A10,BankQuarter!$R$5:$R$750,TRUE(),BankQuarter!$E$5:$E$750,B10) -> 66628 | F10: =IFERROR(100*E10/D10,"") -> 0.17526535 | G10: =COUNTIFS(BankQuarter!$D$5:$D$750,A10,BankQuarter!$R$5:$R$750,FALSE(),BankQuarter!$E$5:$E$750,B10) -> 0
A11: 20220630 | B11: NH | C11: =COUNTIFS(BankQuarter!$D$5:$D$750,A11,BankQuarter!$R$5:$R$750,TRUE(),BankQuarter!$E$5:$E$750,B11) -> 18 | D11: =SUMIFS(BankQuarter!$F$5:$F$750,BankQuarter!$D$5:$D$750,A11,BankQuarter!$R$5:$R$750,TRUE(),BankQuarter!$E$5:$E$750,B11) -> 15488639 | E11: =SUMIFS(BankQuarter!$I$5:$I$750,BankQuarter!$D$5:$D$750,A11,BankQuarter!$R$5:$R$750,TRUE(),BankQuarter!$E$5:$E$750,B11) -> 22048 | F11: =IFERROR(100*E11/D11,"") -> 0.1423495 | G11: =COUNTIFS(BankQuarter!$D$5:$D$750,A11,BankQuarter!$R$5:$R$750,FALSE(),BankQuarter!$E$5:$E$750,B11) -> 0
A12: 20220630 | B12: VT | C12: =COUNTIFS(BankQuarter!$D$5:$D$750,A12,BankQuarter!$R$5:$R$750,TRUE(),BankQuarter!$E$5:$E$750,B12) -> 11 | D12: =SUMIFS(BankQuarter!$F$5:$F$750,BankQuarter!$D$5:$D$750,A12,BankQuarter!$R$5:$R$750,TRUE(),BankQuarter!$E$5:$E$750,B12) -> 7243736 | E12: =SUMIFS(BankQuarter!$I$5:$I$750,BankQuarter!$D$5:$D$750,A12,BankQuarter!$R$5:$R$750,TRUE(),BankQuarter!$E$5:$E$750,B12) -> 27857 | F12: =IFERROR(100*E12/D12,"") -> 0.38456675 | G12: =COUNTIFS(BankQuarter!$D$5:$D$750,A12,BankQuarter!$R$5:$R$750,FALSE(),BankQuarter!$E$5:$E$750,B12) -> 0
A13: 20220930 | B13: ALL | C13: =COUNTIFS(BankQuarter!$D$5:$D$750,A13,BankQuarter!$R$5:$R$750,TRUE()) -> 53 | D13: =SUMIFS(BankQuarter!$F$5:$F$750,BankQuarter!$D$5:$D$750,A13,BankQuarter!$R$5:$R$750,TRUE()) -> 62354271 | E13: =SUMIFS(BankQuarter!$I$5:$I$750,BankQuarter!$D$5:$D$750,A13,BankQuarter!$R$5:$R$750,TRUE()) -> 109246 | F13: =IFERROR(100*E13/D13,"") -> 0.17520211 | G13: =COUNTIFS(BankQuarter!$D$5:$D$750,A13,BankQuarter!$R$5:$R$750,FALSE()) -> 0
A14: 20220930 | B14: ME | C14: =COUNTIFS(BankQuarter!$D$5:$D$750,A14,BankQuarter!$R$5:$R$750,TRUE(),BankQuarter!$E$5:$E$750,B14) -> 23 | D14: =SUMIFS(BankQuarter!$F$5:$F$750,BankQuarter!$D$5:$D$750,A14,BankQuarter!$R$5:$R$750,TRUE(),BankQuarter!$E$5:$E$750,B14) -> 38997566 | E14: =SUMIFS(BankQuarter!$I$5:$I$750,BankQuarter!$D$5:$D$750,A14,BankQuarter!$R$5:$R$750,TRUE(),BankQuarter!$E$5:$E$750,B14) -> 58678 | F14: =IFERROR(100*E14/D14,"") -> 0.1504658 | G14: =COUNTIFS(BankQuarter!$D$5:$D$750,A14,BankQuarter!$R$5:$R$750,FALSE(),BankQuarter!$E$5:$E$750,B14) -> 0
A15: 20220930 | B15: NH | C15: =COUNTIFS(BankQuarter!$D$5:$D$750,A15,BankQuarter!$R$5:$R$750,TRUE(),BankQuarter!$E$5:$E$750,B15) -> 18 | D15: =SUMIFS(BankQuarter!$F$5:$F$750,BankQuarter!$D$5:$D$750,A15,BankQuarter!$R$5:$R$750,TRUE(),BankQuarter!$E$5:$E$750,B15) -> 15915289 | E15: =SUMIFS(BankQuarter!$I$5:$I$750,BankQuarter!$D$5:$D$750,A15,BankQuarter!$R$5:$R$750,TRUE(),BankQuarter!$E$5:$E$750,B15) -> 21146 | F15: =IFERROR(100*E15/D15,"") -> 0.13286595 | G15: =COUNTIFS(BankQuarter!$D$5:$D$750,A15,BankQuarter!$R$5:$R$750,FALSE(),BankQuarter!$E$5:$E$750,B15) -> 0
A16: 20220930 | B16: VT | C16: =COUNTIFS(BankQuarter!$D$5:$D$750,A16,BankQuarter!$R$5:$R$750,TRUE(),BankQuarter!$E$5:$E$750,B16) -> 12 | D16: =SUMIFS(BankQuarter!$F$5:$F$750,BankQuarter!$D$5:$D$750,A16,BankQuarter!$R$5:$R$750,TRUE(),BankQuarter!$E$5:$E$750,B16) -> 7441416 | E16: =SUMIFS(BankQuarter!$I$5:$I$750,BankQuarter!$D$5:$D$750,A16,BankQuarter!$R$5:$R$750,TRUE(),BankQuarter!$E$5:$E$750,B16) -> 29422 | F16: =IFERROR(100*E16/D16,"") -> 0.39538174 | G16: =COUNTIFS(BankQuarter!$D$5:$D$750,A16,BankQuarter!$R$5:$R$750,FALSE(),BankQuarter!$E$5:$E$750,B16) -> 0
A17: 20221231 | B17: ALL | C17: =COUNTIFS(BankQuarter!$D$5:$D$750,A17,BankQuarter!$R$5:$R$750,TRUE()) -> 54 | D17: =SUMIFS(BankQuarter!$F$5:$F$750,BankQuarter!$D$5:$D$750,A17,BankQuarter!$R$5:$R$750,TRUE()) -> 64502953 | E17: =SUMIFS(BankQuarter!$I$5:$I$750,BankQuarter!$D$5:$D$750,A17,BankQuarter!$R$5:$R$750,TRUE()) -> 123030 | F17: =IFERROR(100*E17/D17,"") -> 0.19073545 | G17: =COUNTIFS(BankQuarter!$D$5:$D$750,A17,BankQuarter!$R$5:$R$750,FALSE()) -> 0
A18: 20221231 | B18: ME | C18: =COUNTIFS(BankQuarter!$D$5:$D$750,A18,BankQuarter!$R$5:$R$750,TRUE(),BankQuarter!$E$5:$E$750,B18) -> 23 | D18: =SUMIFS(BankQuarter!$F$5:$F$750,BankQuarter!$D$5:$D$750,A18,BankQuarter!$R$5:$R$750,TRUE(),BankQuarter!$E$5:$E$750,B18) -> 40711151 | E18: =SUMIFS(BankQuarter!$I$5:$I$750,BankQuarter!$D$5:$D$750,A18,BankQuarter!$R$5:$R$750,TRUE(),BankQuarter!$E$5:$E$750,B18) -> 69279 | F18: =IFERROR(100*E18/D18,"") -> 0.17017205 | G18: =COUNTIFS(BankQuarter!$D$5:$D$750,A18,BankQuarter!$R$5:$R$750,FALSE(),BankQuarter!$E$5:$E$750,B18) -> 0
A19: 20221231 | B19: NH | C19: =COUNTIFS(BankQuarter!$D$5:$D$750,A19,BankQuarter!$R$5:$R$750,TRUE(),BankQuarter!$E$5:$E$750,B19) -> 19 | D19: =SUMIFS(BankQuarter!$F$5:$F$750,BankQuarter!$D$5:$D$750,A19,BankQuarter!$R$5:$R$750,TRUE(),BankQuarter!$E$5:$E$750,B19) -> 16241743 | E19: =SUMIFS(BankQuarter!$I$5:$I$750,BankQuarter!$D$5:$D$750,A19,BankQuarter!$R$5:$R$750,TRUE(),BankQuarter!$E$5:$E$750,B19) -> 20482 | F19: =IFERROR(100*E19/D19,"") -> 0.12610715 | G19: =COUNTIFS(BankQuarter!$D$5:$D$750,A19,BankQuarter!$R$5:$R$750,FALSE(),BankQuarter!$E$5:$E$750,B19) -> 0
A20: 20221231 | B20: VT | C20: =COUNTIFS(BankQuarter!$D$5:$D$750,A20,BankQuarter!$R$5:$R$750,TRUE(),BankQuarter!$E$5:$E$750,B20) -> 12 | D20: =SUMIFS(BankQuarter!$F$5:$F$750,BankQuarter!$D$5:$D$750,A20,BankQuarter!$R$5:$R$750,TRUE(),BankQuarter!$E$5:$E$750,B20) -> 7550059 | E20: =SUMIFS(BankQuarter!$I$5:$I$750,BankQuarter!$D$5:$D$750,A20,BankQuarter!$R$5:$R$750,TRUE(),BankQuarter!$E$5:$E$750,B20) -> 33269 | F20: =IFERROR(100*E20/D20,"") -> 0.44064556 | G20: =COUNTIFS(BankQuarter!$D$5:$D$750,A20,BankQuarter!$R$5:$R$750,FALSE(),BankQuarter!$E$5:$E$750,B20) -> 0
A21: 20230331 | B21: ALL | C21: =COUNTIFS(BankQuarter!$D$5:$D$750,A21,BankQuarter!$R$5:$R$750,TRUE()) -> 54 | D21: =SUMIFS(BankQuarter!$F$5:$F$750,BankQuarter!$D$5:$D$750,A21,BankQuarter!$R$5:$R$750,TRUE()) -> 65286835 | E21: =SUMIFS(BankQuarter!$I$5:$I$750,BankQuarter!$D$5:$D$750,A21,BankQuarter!$R$5:$R$750,TRUE()) -> 126451 | F21: =IFERROR(100*E21/D21,"") -> 0.1936853 | G21: =COUNTIFS(BankQuarter!$D$5:$D$750,A21,BankQuarter!$R$5:$R$750,FALSE()) -> 0
A22: 20230331 | B22: ME | C22: =COUNTIFS(BankQuarter!$D$5:$D$750,A22,BankQuarter!$R$5:$R$750,TRUE(),BankQuarter!$E$5:$E$750,B22) -> 23 | D22: =SUMIFS(BankQuarter!$F$5:$F$750,BankQuarter!$D$5:$D$750,A22,BankQuarter!$R$5:$R$750,TRUE(),BankQuarter!$E$5:$E$750,B22) -> 41248817 | E22: =SUMIFS(BankQuarter!$I$5:$I$750,BankQuarter!$D$5:$D$750,A22,BankQuarter!$R$5:$R$750,TRUE(),BankQuarter!$E$5:$E$750,B22) -> 72471 | F22: =IFERROR(100*E22/D22,"") -> 0.17569231 | G22: =COUNTIFS(BankQuarter!$D$5:$D$750,A22,BankQuarter!$R$5:$R$750,FALSE(),BankQuarter!$E$5:$E$750,B22) -> 0
A23: 20230331 | B23: NH | C23: =COUNTIFS(BankQuarter!$D$5:$D$750,A23,BankQuarter!$R$5:$R$750,TRUE(),BankQuarter!$E$5:$E$750,B23) -> 19 | D23: =SUMIFS(BankQuarter!$F$5:$F$750,BankQuarter!$D$5:$D$750,A23,BankQuarter!$R$5:$R$750,TRUE(),BankQuarter!$E$5:$E$750,B23) -> 16492351 | E23: =SUMIFS(BankQuarter!$I$5:$I$750,BankQuarter!$D$5:$D$750,A23,BankQuarter!$R$5:$R$750,TRUE(),BankQuarter!$E$5:$E$750,B23) -> 21816 | F23: =IFERROR(100*E23/D23,"") -> 0.1322795 | G23: =COUNTIFS(BankQuarter!$D$5:$D$750,A23,BankQuarter!$R$5:$R$750,FALSE(),BankQuarter!$E$5:$E$750,B23) -> 0
A24: 20230331 | B24: VT | C24: =COUNTIFS(BankQuarter!$D$5:$D$750,A24,BankQuarter!$R$5:$R$750,TRUE(),BankQuarter!$E$5:$E$750,B24) -> 12 | D24: =SUMIFS(BankQuarter!$F$5:$F$750,BankQuarter!$D$5:$D$750,A24,BankQuarter!$R$5:$R$750,TRUE(),BankQuarter!$E$5:$E$750,B24) -> 7545667 | E24: =SUMIFS(BankQuarter!$I$5:$I$750,BankQuarter!$D$5:$D$750,A24,BankQuarter!$R$5:$R$750,TRUE(),BankQuarter!$E$5:$E$750,B24) -> 32164 | F24: =IFERROR(100*E24/D24,"") -> 0.42625788 | G24: =COUNTIFS(BankQuarter!$D$5:$D$750,A24,BankQuarter!$R$5:$R$750,FALSE(),BankQuarter!$E$5:$E$750,B24) -> 0
A25: 20230630 | B25: ALL | C25: =COUNTIFS(BankQuarter!$D$5:$D$750,A25,BankQuarter!$R$5:$R$750,TRUE()) -> 54 | D25: =SUMIFS(BankQuarter!$F$5:$F$750,BankQuarter!$D$5:$D$750,A25,BankQuarter!$R$5:$R$750,TRUE()) -> 66103367 | E25: =SUMIFS(BankQuarter!$I$5:$I$750,BankQuarter!$D$5:$D$750,A25,BankQuarter!$R$5:$R$750,TRUE()) -> 138756 | F25: =IFERROR(100*E25/D25,"") -> 0.20990761 | G25: =COUNTIFS(BankQuarter!$D$5:$D$750,A25,BankQuarter!$R$5:$R$750,FALSE()) -> 0
A26: 20230630 | B26: ME | C26: =COUNTIFS(BankQuarter!$D$5:$D$750,A26,BankQuarter!$R$5:$R$750,TRUE(),BankQuarter!$E$5:$E$750,B26) -> 23 | D26: =SUMIFS(BankQuarter!$F$5:$F$750,BankQuarter!$D$5:$D$750,A26,BankQuarter!$R$5:$R$750,TRUE(),BankQuarter!$E$5:$E$750,B26) -> 41636903 | E26: =SUMIFS(BankQuarter!$I$5:$I$750,BankQuarter!$D$5:$D$750,A26,BankQuarter!$R$5:$R$750,TRUE(),BankQuarter!$E$5:$E$750,B26) -> 74941 | F26: =IFERROR(100*E26/D26,"") -> 0.17998697 | G26: =COUNTIFS(BankQuarter!$D$5:$D$750,A26,BankQuarter!$R$5:$R$750,FALSE(),BankQuarter!$E$5:$E$750,B26) -> 0
A27: 20230630 | B27: NH | C27: =COUNTIFS(BankQuarter!$D$5:$D$750,A27,BankQuarter!$R$5:$R$750,TRUE(),BankQuarter!$E$5:$E$750,B27) -> 19 | D27: =SUMIFS(BankQuarter!$F$5:$F$750,BankQuarter!$D$5:$D$750,A27,BankQuarter!$R$5:$R$750,TRUE(),BankQuarter!$E$5:$E$750,B27) -> 16868331 | E27: =SUMIFS(BankQuarter!$I$5:$I$750,BankQuarter!$D$5:$D$750,A27,BankQuarter!$R$5:$R$750,TRUE(),BankQuarter!$E$5:$E$750,B27) -> 30872 | F27: =IFERROR(100*E27/D27,"") -> 0.18301751 | G27: =COUNTIFS(BankQuarter!$D$5:$D$750,A27,BankQuarter!$R$5:$R$750,FALSE(),BankQuarter!$E$5:$E$750,B27) -> 0
A28: 20230630 | B28: VT | C28: =COUNTIFS(BankQuarter!$D$5:$D$750,A28,BankQuarter!$R$5:$R$750,TRUE(),BankQuarter!$E$5:$E$750,B28) -> 12 | D28: =SUMIFS(BankQuarter!$F$5:$F$750,BankQuarter!$D$5:$D$750,A28,BankQuarter!$R$5:$R$750,TRUE(),BankQuarter!$E$5:$E$750,B28) -> 7598133 | E28: =SUMIFS(BankQuarter!$I$5:$I$750,BankQuarter!$D$5:$D$750,A28,BankQuarter!$R$5:$R$750,TRUE(),BankQuarter!$E$5:$E$750,B28) -> 32943 | F28: =IFERROR(100*E28/D28,"") -> 0.43356704 | G28: =COUNTIFS(BankQuarter!$D$5:$D$750,A28,BankQuarter!$R$5:$R$750,FALSE(),BankQuarter!$E$5:$E$750,B28) -> 0
A29: 20230930 | B29: ALL | C29: =COUNTIFS(BankQuarter!$D$5:$D$750,A29,BankQuarter!$R$5:$R$750,TRUE()) -> 54 | D29: =SUMIFS(BankQuarter!$F$5:$F$750,BankQuarter!$D$5:$D$750,A29,BankQuarter!$R$5:$R$750,TRUE()) -> 66427421 | E29: =SUMIFS(BankQuarter!$I$5:$I$750,BankQuarter!$D$5:$D$750,A29,BankQuarter!$R$5:$R$750,TRUE()) -> 143883 | F29: =IFERROR(100*E29/D29,"") -> 0.21660182 | G29: =COUNTIFS(BankQuarter!$D$5:$D$750,A29,BankQuarter!$R$5:$R$750,FALSE()) -> 0
A30: 20230930 | B30: ME | C30: =COUNTIFS(BankQuarter!$D$5:$D$750,A30,BankQuarter!$R$5:$R$750,TRUE(),BankQuarter!$E$5:$E$750,B30) -> 23 | D30: =SUMIFS(BankQuarter!$F$5:$F$750,BankQuarter!$D$5:$D$750,A30,BankQuarter!$R$5:$R$750,TRUE(),BankQuarter!$E$5:$E$750,B30) -> 41707922 | E30: =SUMIFS(BankQuarter!$I$5:$I$750,BankQuarter!$D$5:$D$750,A30,BankQuarter!$R$5:$R$750,TRUE(),BankQuarter!$E$5:$E$750,B30) -> 76406 | F30: =IFERROR(100*E30/D30,"") -> 0.18319302 | G30: =COUNTIFS(BankQuarter!$D$5:$D$750,A30,BankQuarter!$R$5:$R$750,FALSE(),BankQuarter!$E$5:$E$750,B30) -> 0
A31: 20230930 | B31: NH | C31: =COUNTIFS(BankQuarter!$D$5:$D$750,A31,BankQuarter!$R$5:$R$750,TRUE(),BankQuarter!$E$5:$E$750,B31) -> 19 | D31: =SUMIFS(BankQuarter!$F$5:$F$750,BankQuarter!$D$5:$D$750,A31,BankQuarter!$R$5:$R$750,TRUE(),BankQuarter!$E$5:$E$750,B31) -> 16937411 | E31: =SUMIFS(BankQuarter!$I$5:$I$750,BankQuarter!$D$5:$D$750,A31,BankQuarter!$R$5:$R$750,TRUE(),BankQuarter!$E$5:$E$750,B31) -> 33535 | F31: =IFERROR(100*E31/D31,"") -> 0.19799366 | G31: =COUNTIFS(BankQuarter!$D$5:$D$750,A31,BankQuarter!$R$5:$R$750,FALSE(),BankQuarter!$E$5:$E$750,B31) -> 0
A32: 20230930 | B32: VT | C32: =COUNTIFS(BankQuarter!$D$5:$D$750,A32,BankQuarter!$R$5:$R$750,TRUE(),BankQuarter!$E$5:$E$750,B32) -> 12 | D32: =SUMIFS(BankQuarter!$F$5:$F$750,BankQuarter!$D$5:$D$750,A32,BankQuarter!$R$5:$R$750,TRUE(),BankQuarter!$E$5:$E$750,B32) -> 7782088 | E32: =SUMIFS(BankQuarter!$I$5:$I$750,BankQuarter!$D$5:$D$750,A32,BankQuarter!$R$5:$R$750,TRUE(),BankQuarter!$E$5:$E$750,B32) -> 33942 | F32: =IFERROR(100*E32/D32,"") -> 0.43615544 | G32: =COUNTIFS(BankQuarter!$D$5:$D$750,A32,BankQuarter!$R$5:$R$750,FALSE(),BankQuarter!$E$5:$E$750,B32) -> 0
A33: 20231231 | B33: ALL | C33: =COUNTIFS(BankQuarter!$D$5:$D$750,A33,BankQuarter!$R$5:$R$750,TRUE()) -> 54 | D33: =SUMIFS(BankQuarter!$F$5:$F$750,BankQuarter!$D$5:$D$750,A33,BankQuarter!$R$5:$R$750,TRUE()) -> 67228962 | E33: =SUMIFS(BankQuarter!$I$5:$I$750,BankQuarter!$D$5:$D$750,A33,BankQuarter!$R$5:$R$750,TRUE()) -> 158668 | F33: =IFERROR(100*E33/D33,"") -> 0.23601138 | G33: =COUNTIFS(BankQuarter!$D$5:$D$750,A33,BankQuarter!$R$5:$R$750,FALSE()) -> 0
A34: 20231231 | B34: ME | C34: =COUNTIFS(BankQuarter!$D$5:$D$750,A34,BankQuarter!$R$5:$R$750,TRUE(),BankQuarter!$E$5:$E$750,B34) -> 23 | D34: =SUMIFS(BankQuarter!$F$5:$F$750,BankQuarter!$D$5:$D$750,A34,BankQuarter!$R$5:$R$750,TRUE(),BankQuarter!$E$5:$E$750,B34) -> 42110091 | E34: =SUMIFS(BankQuarter!$I$5:$I$750,BankQuarter!$D$5:$D$750,A34,BankQuarter!$R$5:$R$750,TRUE(),BankQuarter!$E$5:$E$750,B34) -> 96144 | F34: =IFERROR(100*E34/D34,"") -> 0.22831582 | G34: =COUNTIFS(BankQuarter!$D$5:$D$750,A34,BankQuarter!$R$5:$R$750,FALSE(),BankQuarter!$E$5:$E$750,B34) -> 0
A35: 20231231 | B35: NH | C35: =COUNTIFS(BankQuarter!$D$5:$D$750,A35,BankQuarter!$R$5:$R$750,TRUE(),BankQuarter!$E$5:$E$750,B35) -> 19 | D35: =SUMIFS(BankQuarter!$F$5:$F$750,BankQuarter!$D$5:$D$750,A35,BankQuarter!$R$5:$R$750,TRUE(),BankQuarter!$E$5:$E$750,B35) -> 17110799 | E35: =SUMIFS(BankQuarter!$I$5:$I$750,BankQuarter!$D$5:$D$750,A35,BankQuarter!$R$5:$R$750,TRUE(),BankQuarter!$E$5:$E$750,B35) -> 30295 | F35: =IFERROR(100*E35/D35,"") -> 0.17705193 | G35: =COUNTIFS(BankQuarter!$D$5:$D$750,A35,BankQuarter!$R$5:$R$750,FALSE(),BankQuarter!$E$5:$E$750,B35) -> 0
A36: 20231231 | B36: VT | C36: =COUNTIFS(BankQuarter!$D$5:$D$750,A36,BankQuarter!$R$5:$R$750,TRUE(),BankQuarter!$E$5:$E$750,B36) -> 12 | D36: =SUMIFS(BankQuarter!$F$5:$F$750,BankQuarter!$D$5:$D$750,A36,BankQuarter!$R$5:$R$750,TRUE(),BankQuarter!$E$5:$E$750,B36) -> 8008072 | E36: =SUMIFS(BankQuarter!$I$5:$I$750,BankQuarter!$D$5:$D$750,A36,BankQuarter!$R$5:$R$750,TRUE(),BankQuarter!$E$5:$E$750,B36) -> 32229 | F36: =IFERROR(100*E36/D36,"") -> 0.40245642 | G36: =COUNTIFS(BankQuarter!$D$5:$D$750,A36,BankQuarter!$R$5:$R$750,FALSE(),BankQuarter!$E$5:$E$750,B36) -> 0
A37: 20240331 | B37: ALL | C37: =COUNTIFS(BankQuarter!$D$5:$D$750,A37,BankQuarter!$R$5:$R$750,TRUE()) -> 54 | D37: =SUMIFS(BankQuarter!$F$5:$F$750,BankQuarter!$D$5:$D$750,A37,BankQuarter!$R$5:$R$750,TRUE()) -> 67408258 | E37: =SUMIFS(BankQuarter!$I$5:$I$750,BankQuarter!$D$5:$D$750,A37,BankQuarter!$R$5:$R$750,TRUE()) -> 199761 | F37: =IFERROR(100*E37/D37,"") -> 0.296345 | G37: =COUNTIFS(BankQuarter!$D$5:$D$750,A37,BankQuarter!$R$5:$R$750,FALSE()) -> 0
A38: 20240331 | B38: ME | C38: =COUNTIFS(BankQuarter!$D$5:$D$750,A38,BankQuarter!$R$5:$R$750,TRUE(),BankQuarter!$E$5:$E$750,B38) -> 23 | D38: =SUMIFS(BankQuarter!$F$5:$F$750,BankQuarter!$D$5:$D$750,A38,BankQuarter!$R$5:$R$750,TRUE(),BankQuarter!$E$5:$E$750,B38) -> 42291921 | E38: =SUMIFS(BankQuarter!$I$5:$I$750,BankQuarter!$D$5:$D$750,A38,BankQuarter!$R$5:$R$750,TRUE(),BankQuarter!$E$5:$E$750,B38) -> 103921 | F38: =IFERROR(100*E38/D38,"") -> 0.24572305 | G38: =COUNTIFS(BankQuarter!$D$5:$D$750,A38,BankQuarter!$R$5:$R$750,FALSE(),BankQuarter!$E$5:$E$750,B38) -> 0
A39: 20240331 | B39: NH | C39: =COUNTIFS(BankQuarter!$D$5:$D$750,A39,BankQuarter!$R$5:$R$750,TRUE(),BankQuarter!$E$5:$E$750,B39) -> 19 | D39: =SUMIFS(BankQuarter!$F$5:$F$750,BankQuarter!$D$5:$D$750,A39,BankQuarter!$R$5:$R$750,TRUE(),BankQuarter!$E$5:$E$750,B39) -> 17104248 | E39: =SUMIFS(BankQuarter!$I$5:$I$750,BankQuarter!$D$5:$D$750,A39,BankQuarter!$R$5:$R$750,TRUE(),BankQuarter!$E$5:$E$750,B39) -> 62757 | F39: =IFERROR(100*E39/D39,"") -> 0.36690885 | G39: =COUNTIFS(BankQuarter!$D$5:$D$750,A39,BankQuarter!$R$5:$R$750,FALSE(),BankQuarter!$E$5:$E$750,B39) -> 0
A40: 20240331 | B40: VT | C40: =COUNTIFS(BankQuarter!$D$5:$D$750,A40,BankQuarter!$R$5:$R$750,TRUE(),BankQuarter!$E$5:$E$750,B40) -> 12 | D40: =SUMIFS(BankQuarter!$F$5:$F$750,BankQuarter!$D$5:$D$750,A40,BankQuarter!$R$5:$R$750,TRUE(),BankQuarter!$E$5:$E$750,B40) -> 8012089 | E40: =SUMIFS(BankQuarter!$I$5:$I$750,BankQuarter!$D$5:$D$750,A40,BankQuarter!$R$5:$R$750,TRUE(),BankQuarter!$E$5:$E$750,B40) -> 33083 | F40: =IFERROR(100*E40/D40,"") -> 0.41291354 | G40: =COUNTIFS(BankQuarter!$D$5:$D$750,A40,BankQuarter!$R$5:$R$750,FALSE(),BankQuarter!$E$5:$E$750,B40) -> 0
A41: 20240630 | B41: ALL | C41: =COUNTIFS(BankQuarter!$D$5:$D$750,A41,BankQuarter!$R$5:$R$750,TRUE()) -> 54 | D41: =SUMIFS(BankQuarter!$F$5:$F$750,BankQuarter!$D$5:$D$750,A41,BankQuarter!$R$5:$R$750,TRUE()) -> 68174434 | E41: =SUMIFS(BankQuarter!$I$5:$I$750,BankQuarter!$D$5:$D$750,A41,BankQuarter!$R$5:$R$750,TRUE()) -> 203546 | F41: =IFERROR(100*E41/D41,"") -> 0.29856647 | G41: =COUNTIFS(BankQuarter!$D$5:$D$750,A41,BankQuarter!$R$5:$R$750,FALSE()) -> 0
A42: 20240630 | B42: ME | C42: =COUNTIFS(BankQuarter!$D$5:$D$750,A42,BankQuarter!$R$5:$R$750,TRUE(),BankQuarter!$E$5:$E$750,B42) -> 23 | D42: =SUMIFS(BankQuarter!$F$5:$F$750,BankQuarter!$D$5:$D$750,A42,BankQuarter!$R$5:$R$750,TRUE(),BankQuarter!$E$5:$E$750,B42) -> 42836512 | E42: =SUMIFS(BankQuarter!$I$5:$I$750,BankQuarter!$D$5:$D$750,A42,BankQuarter!$R$5:$R$750,TRUE(),BankQuarter!$E$5:$E$750,B42) -> 113174 | F42: =IFERROR(100*E42/D42,"") -> 0.26419985 | G42: =COUNTIFS(BankQuarter!$D$5:$D$750,A42,BankQuarter!$R$5:$R$750,FALSE(),BankQuarter!$E$5:$E$750,B42) -> 0
A43: 20240630 | B43: NH | C43: =COUNTIFS(BankQuarter!$D$5:$D$750,A43,BankQuarter!$R$5:$R$750,TRUE(),BankQuarter!$E$5:$E$750,B43) -> 19 | D43: =SUMIFS(BankQuarter!$F$5:$F$750,BankQuarter!$D$5:$D$750,A43,BankQuarter!$R$5:$R$750,TRUE(),BankQuarter!$E$5:$E$750,B43) -> 17279833 | E43: =SUMIFS(BankQuarter!$I$5:$I$750,BankQuarter!$D$5:$D$750,A43,BankQuarter!$R$5:$R$750,TRUE(),BankQuarter!$E$5:$E$750,B43) -> 63087 | F43: =IFERROR(100*E43/D43,"") -> 0.36509033 | G43: =COUNTIFS(BankQuarter!$D$5:$D$750,A43,BankQuarter!$R$5:$R$750,FALSE(),BankQuarter!$E$5:$E$750,B43) -> 0
A44: 20240630 | B44: VT | C44: =COUNTIFS(BankQuarter!$D$5:$D$750,A44,BankQuarter!$R$5:$R$750,TRUE(),BankQuarter!$E$5:$E$750,B44) -> 12 | D44: =SUMIFS(BankQuarter!$F$5:$F$750,BankQuarter!$D$5:$D$750,A44,BankQuarter!$R$5:$R$750,TRUE(),BankQuarter!$E$5:$E$750,B44) -> 8058089 | E44: =SUMIFS(BankQuarter!$I$5:$I$750,BankQuarter!$D$5:$D$750,A44,BankQuarter!$R$5:$R$750,TRUE(),BankQuarter!$E$5:$E$750,B44) -> 27285 | F44: =IFERROR(100*E44/D44,"") -> 0.33860386 | G44: =COUNTIFS(BankQuarter!$D$5:$D$750,A44,BankQuarter!$R$5:$R$750,FALSE(),BankQuarter!$E$5:$E$750,B44) -> 0
A45: 20240930 | B45: ALL | C45: =COUNTIFS(BankQuarter!$D$5:$D$750,A45,BankQuarter!$R$5:$R$750,TRUE()) -> 54 | D45: =SUMIFS(BankQuarter!$F$5:$F$750,BankQuarter!$D$5:$D$750,A45,BankQuarter!$R$5:$R$750,TRUE()) -> 69727725 | E45: =SUMIFS(BankQuarter!$I$5:$I$750,BankQuarter!$D$5:$D$750,A45,BankQuarter!$R$5:$R$750,TRUE()) -> 202918 | F45: =IFERROR(100*E45/D45,"") -> 0.2910148 | G45: =COUNTIFS(BankQuarter!$D$5:$D$750,A45,BankQuarter!$R$5:$R$750,FALSE()) -> 0
A46: 20240930 | B46: ME | C46: =COUNTIFS(BankQuarter!$D$5:$D$750,A46,BankQuarter!$R$5:$R$750,TRUE(),BankQuarter!$E$5:$E$750,B46) -> 23 | D46: =SUMIFS(BankQuarter!$F$5:$F$750,BankQuarter!$D$5:$D$750,A46,BankQuarter!$R$5:$R$750,TRUE(),BankQuarter!$E$5:$E$750,B46) -> 43857564 | E46: =SUMIFS(BankQuarter!$I$5:$I$750,BankQuarter!$D$5:$D$750,A46,BankQuarter!$R$5:$R$750,TRUE(),BankQuarter!$E$5:$E$750,B46) -> 111386 | F46: =IFERROR(100*E46/D46,"") -> 0.25397215 | G46: =COUNTIFS(BankQuarter!$D$5:$D$750,A46,BankQuarter!$R$5:$R$750,FALSE(),BankQuarter!$E$5:$E$750,B46) -> 0
A47: 20240930 | B47: NH | C47: =COUNTIFS(BankQuarter!$D$5:$D$750,A47,BankQuarter!$R$5:$R$750,TRUE(),BankQuarter!$E$5:$E$750,B47) -> 19 | D47: =SUMIFS(BankQuarter!$F$5:$F$750,BankQuarter!$D$5:$D$750,A47,BankQuarter!$R$5:$R$750,TRUE(),BankQuarter!$E$5:$E$750,B47) -> 17448405 | E47: =SUMIFS(BankQuarter!$I$5:$I$750,BankQuarter!$D$5:$D$750,A47,BankQuarter!$R$5:$R$750,TRUE(),BankQuarter!$E$5:$E$750,B47) -> 66699 | F47: =IFERROR(100*E47/D47,"") -> 0.38226417 | G47: =COUNTIFS(BankQuarter!$D$5:$D$750,A47,BankQuarter!$R$5:$R$750,FALSE(),BankQuarter!$E$5:$E$750,B47) -> 0
A48: 20240930 | B48: VT | C48: =COUNTIFS(BankQuarter!$D$5:$D$750,A48,BankQuarter!$R$5:$R$750,TRUE(),BankQuarter!$E$5:$E$750,B48) -> 12 | D48: =SUMIFS(BankQuarter!$F$5:$F$750,BankQuarter!$D$5:$D$750,A48,BankQuarter!$R$5:$R$750,TRUE(),BankQuarter!$E$5:$E$750,B48) -> 8421756 | E48: =SUMIFS(BankQuarter!$I$5:$I$750,BankQuarter!$D$5:$D$750,A48,BankQuarter!$R$5:$R$750,TRUE(),BankQuarter!$E$5:$E$750,B48) -> 24833 | F48: =IFERROR(100*E48/D48,"") -> 0.29486725 | G48: =COUNTIFS(BankQuarter!$D$5:$D$750,A48,BankQuarter!$R$5:$R$750,FALSE(),BankQuarter!$E$5:$E$750,B48) -> 0
A49: 20241231 | B49: ALL | C49: =COUNTIFS(BankQuarter!$D$5:$D$750,A49,BankQuarter!$R$5:$R$750,TRUE()) -> 54 | D49: =SUMIFS(BankQuarter!$F$5:$F$750,BankQuarter!$D$5:$D$750,A49,BankQuarter!$R$5:$R$750,TRUE()) -> 70110166 | E49: =SUMIFS(BankQuarter!$I$5:$I$750,BankQuarter!$D$5:$D$750,A49,BankQuarter!$R$5:$R$750,TRUE()) -> 197476 | F49: =IFERROR(100*E49/D49,"") -> 0.28166529 | G49: =COUNTIFS(BankQuarter!$D$5:$D$750,A49,BankQuarter!$R$5:$R$750,FALSE()) -> 0
A50: 20241231 | B50: ME | C50: =COUNTIFS(BankQuarter!$D$5:$D$750,A50,BankQuarter!$R$5:$R$750,TRUE(),BankQuarter!$E$5:$E$750,B50) -> 23 | D50: =SUMIFS(BankQuarter!$F$5:$F$750,BankQuarter!$D$5:$D$750,A50,BankQuarter!$R$5:$R$750,TRUE(),BankQuarter!$E$5:$E$750,B50) -> 44159558 | E50: =SUMIFS(BankQuarter!$I$5:$I$750,BankQuarter!$D$5:$D$750,A50,BankQuarter!$R$5:$R$750,TRUE(),BankQuarter!$E$5:$E$750,B50) -> 105164 | F50: =IFERROR(100*E50/D50,"") -> 0.2381455 | G50: =COUNTIFS(BankQuarter!$D$5:$D$750,A50,BankQuarter!$R$5:$R$750,FALSE(),BankQuarter!$E$5:$E$750,B50) -> 0
A51: 20241231 | B51: NH | C51: =COUNTIFS(BankQuarter!$D$5:$D$750,A51,BankQuarter!$R$5:$R$750,TRUE(),BankQuarter!$E$5:$E$750,B51) -> 19 | D51: =SUMIFS(BankQuarter!$F$5:$F$750,BankQuarter!$D$5:$D$750,A51,BankQuarter!$R$5:$R$750,TRUE(),BankQuarter!$E$5:$E$750,B51) -> 17386962 | E51: =SUMIFS(BankQuarter!$I$5:$I$750,BankQuarter!$D$5:$D$750,A51,BankQuarter!$R$5:$R$750,TRUE(),BankQuarter!$E$5:$E$750,B51) -> 64887 | F51: =IFERROR(100*E51/D51,"") -> 0.37319343 | G51: =COUNTIFS(BankQuarter!$D$5:$D$750,A51,BankQuarter!$R$5:$R$750,FALSE(),BankQuarter!$E$5:$E$750,B51) -> 0
A52: 20241231 | B52: VT | C52: =COUNTIFS(BankQuarter!$D$5:$D$750,A52,BankQuarter!$R$5:$R$750,TRUE(),BankQuarter!$E$5:$E$750,B52) -> 12 | D52: =SUMIFS(BankQuarter!$F$5:$F$750,BankQuarter!$D$5:$D$750,A52,BankQuarter!$R$5:$R$750,TRUE(),BankQuarter!$E$5:$E$750,B52) -> 8563646 | E52: =SUMIFS(BankQuarter!$I$5:$I$750,BankQuarter!$D$5:$D$750,A52,BankQuarter!$R$5:$R$750,TRUE(),BankQuarter!$E$5:$E$750,B52) -> 27425 | F52: =IFERROR(100*E52/D52,"") -> 0.32024911 | G52: =COUNTIFS(BankQuarter!$D$5:$D$750,A52,BankQuarter!$R$5:$R$750,FALSE(),BankQuarter!$E$5:$E$750,B52) -> 0
A53: 20250331 | B53: ALL | C53: =COUNTIFS(BankQuarter!$D$5:$D$750,A53,BankQuarter!$R$5:$R$750,TRUE()) -> 52 | D53: =SUMIFS(BankQuarter!$F$5:$F$750,BankQuarter!$D$5:$D$750,A53,BankQuarter!$R$5:$R$750,TRUE()) -> 70509303 | E53: =SUMIFS(BankQuarter!$I$5:$I$750,BankQuarter!$D$5:$D$750,A53,BankQuarter!$R$5:$R$750,TRUE()) -> 206872 | F53: =IFERROR(100*E53/D53,"") -> 0.29339675 | G53: =COUNTIFS(BankQuarter!$D$5:$D$750,A53,BankQuarter!$R$5:$R$750,FALSE()) -> 0
A54: 20250331 | B54: ME | C54: =COUNTIFS(BankQuarter!$D$5:$D$750,A54,BankQuarter!$R$5:$R$750,TRUE(),BankQuarter!$E$5:$E$750,B54) -> 22 | D54: =SUMIFS(BankQuarter!$F$5:$F$750,BankQuarter!$D$5:$D$750,A54,BankQuarter!$R$5:$R$750,TRUE(),BankQuarter!$E$5:$E$750,B54) -> 45509746 | E54: =SUMIFS(BankQuarter!$I$5:$I$750,BankQuarter!$D$5:$D$750,A54,BankQuarter!$R$5:$R$750,TRUE(),BankQuarter!$E$5:$E$750,B54) -> 118037 | F54: =IFERROR(100*E54/D54,"") -> 0.25936642 | G54: =COUNTIFS(BankQuarter!$D$5:$D$750,A54,BankQuarter!$R$5:$R$750,FALSE(),BankQuarter!$E$5:$E$750,B54) -> 0
A55: 20250331 | B55: NH | C55: =COUNTIFS(BankQuarter!$D$5:$D$750,A55,BankQuarter!$R$5:$R$750,TRUE(),BankQuarter!$E$5:$E$750,B55) -> 18 | D55: =SUMIFS(BankQuarter!$F$5:$F$750,BankQuarter!$D$5:$D$750,A55,BankQuarter!$R$5:$R$750,TRUE(),BankQuarter!$E$5:$E$750,B55) -> 16458416 | E55: =SUMIFS(BankQuarter!$I$5:$I$750,BankQuarter!$D$5:$D$750,A55,BankQuarter!$R$5:$R$750,TRUE(),BankQuarter!$E$5:$E$750,B55) -> 47401 | F55: =IFERROR(100*E55/D55,"") -> 0.28800463 | G55: =COUNTIFS(BankQuarter!$D$5:$D$750,A55,BankQuarter!$R$5:$R$750,FALSE(),BankQuarter!$E$5:$E$750,B55) -> 0
A56: 20250331 | B56: VT | C56: =COUNTIFS(BankQuarter!$D$5:$D$750,A56,BankQuarter!$R$5:$R$750,TRUE(),BankQuarter!$E$5:$E$750,B56) -> 12 | D56: =SUMIFS(BankQuarter!$F$5:$F$750,BankQuarter!$D$5:$D$750,A56,BankQuarter!$R$5:$R$750,TRUE(),BankQuarter!$E$5:$E$750,B56) -> 8541141 | E56: =SUMIFS(BankQuarter!$I$5:$I$750,BankQuarter!$D$5:$D$750,A56,BankQuarter!$R$5:$R$750,TRUE(),BankQuarter!$E$5:$E$750,B56) -> 41434 | F56: =IFERROR(100*E56/D56,"") -> 0.48511083 | G56: =COUNTIFS(BankQuarter!$D$5:$D$750,A56,BankQuarter!$R$5:$R$750,FALSE(),BankQuarter!$E$5:$E$750,B56) -> 0
A57: 20250630 | B57: ALL | C57: =COUNTIFS(BankQuarter!$D$5:$D$750,A57,BankQuarter!$R$5:$R$750,TRUE()) -> 52 | D57: =SUMIFS(BankQuarter!$F$5:$F$750,BankQuarter!$D$5:$D$750,A57,BankQuarter!$R$5:$R$750,TRUE()) -> 71266944 | E57: =SUMIFS(BankQuarter!$I$5:$I$750,BankQuarter!$D$5:$D$750,A57,BankQuarter!$R$5:$R$750,TRUE()) -> 262400 | F57: =IFERROR(100*E57/D57,"") -> 0.36819314 | G57: =COUNTIFS(BankQuarter!$D$5:$D$750,A57,BankQuarter!$R$5:$R$750,FALSE()) -> 0
A58: 20250630 | B58: ME | C58: =COUNTIFS(BankQuarter!$D$5:$D$750,A58,BankQuarter!$R$5:$R$750,TRUE(),BankQuarter!$E$5:$E$750,B58) -> 22 | D58: =SUMIFS(BankQuarter!$F$5:$F$750,BankQuarter!$D$5:$D$750,A58,BankQuarter!$R$5:$R$750,TRUE(),BankQuarter!$E$5:$E$750,B58) -> 46035765 | E58: =SUMIFS(BankQuarter!$I$5:$I$750,BankQuarter!$D$5:$D$750,A58,BankQuarter!$R$5:$R$750,TRUE(),BankQuarter!$E$5:$E$750,B58) -> 169125 | F58: =IFERROR(100*E58/D58,"") -> 0.36737741 | G58: =COUNTIFS(BankQuarter!$D$5:$D$750,A58,BankQuarter!$R$5:$R$750,FALSE(),BankQuarter!$E$5:$E$750,B58) -> 0
A59: 20250630 | B59: NH | C59: =COUNTIFS(BankQuarter!$D$5:$D$750,A59,BankQuarter!$R$5:$R$750,TRUE(),BankQuarter!$E$5:$E$750,B59) -> 18 | D59: =SUMIFS(BankQuarter!$F$5:$F$750,BankQuarter!$D$5:$D$750,A59,BankQuarter!$R$5:$R$750,TRUE(),BankQuarter!$E$5:$E$750,B59) -> 16713625 | E59: =SUMIFS(BankQuarter!$I$5:$I$750,BankQuarter!$D$5:$D$750,A59,BankQuarter!$R$5:$R$750,TRUE(),BankQuarter!$E$5:$E$750,B59) -> 51136 | F59: =IFERROR(100*E59/D59,"") -> 0.30595397 | G59: =COUNTIFS(BankQuarter!$D$5:$D$750,A59,BankQuarter!$R$5:$R$750,FALSE(),BankQuarter!$E$5:$E$750,B59) -> 0
A60: 20250630 | B60: VT | C60: =COUNTIFS(BankQuarter!$D$5:$D$750,A60,BankQuarter!$R$5:$R$750,TRUE(),BankQuarter!$E$5:$E$750,B60) -> 12 | D60: =SUMIFS(BankQuarter!$F$5:$F$750,BankQuarter!$D$5:$D$750,A60,BankQuarter!$R$5:$R$750,TRUE(),BankQuarter!$E$5:$E$750,B60) -> 8517554 | E60: =SUMIFS(BankQuarter!$I$5:$I$750,BankQuarter!$D$5:$D$750,A60,BankQuarter!$R$5:$R$750,TRUE(),BankQuarter!$E$5:$E$750,B60) -> 42139 | F60: =IFERROR(100*E60/D60,"") -> 0.49473123 | G60: =COUNTIFS(BankQuarter!$D$5:$D$750,A60,BankQuarter!$R$5:$R$750,FALSE(),BankQuarter!$E$5:$E$750,B60) -> 0

Sheet EndpointBridge
A1: Endpoint Bridge
A2: Observation scope versus common-bank, start-asset-fixed weights. State for common banks is fixed to the selected end period.
A4: Group | B4: Observed start % | C4: Observed end % | D4: Observed change pp | E4: Fixed start % | F4: Fixed end % | G4: Fixed change pp | H4: Residual: scope & weight pp | I4: Common N | J4: Entering N | K4: Exiting N | L4: Entering assets ($000) | M4: Exiting assets ($000)
A5: ALL | B5: =IFERROR(100*SUMIFS(BankQuarter!$I$5:$I$750,BankQuarter!$D$5:$D$750,WF_START_PERIOD,BankQuarter!$R$5:$R$750,TRUE())/SUMIFS(BankQuarter!$F$5:$F$750,BankQuarter!$D$5:$D$750,WF_START_PERIOD,BankQuarter!$R$5:$R$750,TRUE()),"") -> 0.29856647 | C5: =IFERROR(100*SUMIFS(BankQuarter!$I$5:$I$750,BankQuarter!$D$5:$D$750,WF_END_PERIOD,BankQuarter!$R$5:$R$750,TRUE())/SUMIFS(BankQuarter!$F$5:$F$750,BankQuarter!$D$5:$D$750,WF_END_PERIOD,BankQuarter!$R$5:$R$750,TRUE()),"") -> 0.36819314 | D5: =C5-B5 -> 0.069626673 | E5: =IFERROR(100*SUMPRODUCT((BankQuarter!$D$5:$D$750=WF_START_PERIOD)*(BankQuarter!$R$5:$R$750=TRUE())*(BankQuarter!$X$5:$X$750=TRUE())*BankQuarter!$I$5:$I$750)/SUMPRODUCT((BankQuarter!$D$5:$D$750=WF_START_PERIOD)*(BankQuarter!$R$5:$R$750=TRUE())*(BankQuarter!$X$5:$X$750=TRUE())*BankQuarter!$F$5:$F$750),"") -> 0.2943426 | F5: =IFERROR(SUMPRODUCT((BankQuarter!$D$5:$D$750=WF_START_PERIOD)*(BankQuarter!$R$5:$R$750=TRUE())*(BankQuarter!$X$5:$X$750=TRUE())*BankQuarter!$F$5:$F$750*BankQuarter!$U$5:$U$750)/SUMPRODUCT((BankQuarter!$D$5:$D$750=WF_START_PERIOD)*(BankQuarter!$R$5:$R$750=TRUE())*(BankQuarter!$X$5:$X$750=TRUE())*BankQuarter!$F$5:$F$750),"") -> 0.35737369 | G5: =F5-E5 -> 0.063031091 | H5: =D5-G5 -> 0.0065955818 | I5: =SUMPRODUCT((BankQuarter!$D$5:$D$750=WF_START_PERIOD)*(BankQuarter!$R$5:$R$750=TRUE())*(BankQuarter!$X$5:$X$750=TRUE())) -> 52 | J5: =SUMPRODUCT((BankQuarter!$D$5:$D$750=WF_END_PERIOD)*(BankQuarter!$R$5:$R$750=TRUE())*(BankQuarter!$W$5:$W$750=FALSE())) -> 0 | K5: =SUMPRODUCT((BankQuarter!$D$5:$D$750=WF_START_PERIOD)*(BankQuarter!$R$5:$R$750=TRUE())*(BankQuarter!$X$5:$X$750=FALSE())) -> 2 | L5: =SUMPRODUCT((BankQuarter!$D$5:$D$750=WF_END_PERIOD)*(BankQuarter!$R$5:$R$750=TRUE())*(BankQuarter!$W$5:$W$750=FALSE())*BankQuarter!$F$5:$F$750) -> 0 | M5: =SUMPRODUCT((BankQuarter!$D$5:$D$750=WF_START_PERIOD)*(BankQuarter!$R$5:$R$750=TRUE())*(BankQuarter!$X$5:$X$750=FALSE())*BankQuarter!$F$5:$F$750) -> 2924280
A6: ME | B6: =IFERROR(100*SUMIFS(BankQuarter!$I$5:$I$750,BankQuarter!$D$5:$D$750,WF_START_PERIOD,BankQuarter!$R$5:$R$750,TRUE(),BankQuarter!$E$5:$E$750,$A6)/SUMIFS(BankQuarter!$F$5:$F$750,BankQuarter!$D$5:$D$750,WF_START_PERIOD,BankQuarter!$R$5:$R$750,TRUE(),BankQuarter!$E$5:$E$750,$A6),"") -> 0.26419985 | C6: =IFERROR(100*SUMIFS(BankQuarter!$I$5:$I$750,BankQuarter!$D$5:$D$750,WF_END_PERIOD,BankQuarter!$R$5:$R$750,TRUE(),BankQuarter!$E$5:$E$750,$A6)/SUMIFS(BankQuarter!$F$5:$F$750,BankQuarter!$D$5:$D$750,WF_END_PERIOD,BankQuarter!$R$5:$R$750,TRUE(),BankQuarter!$E$5:$E$750,$A6),"") -> 0.36737741 | D6: =C6-B6 -> 0.10317756 | E6: =IFERROR(100*SUMPRODUCT((BankQuarter!$D$5:$D$750=WF_START_PERIOD)*(BankQuarter!$R$5:$R$750=TRUE())*(BankQuarter!$X$5:$X$750=TRUE())*(BankQuarter!$V$5:$V$750=$A6)*BankQuarter!$I$5:$I$750)/SUMPRODUCT((BankQuarter!$D$5:$D$750=WF_START_PERIOD)*(BankQuarter!$R$5:$R$750=TRUE())*(BankQuarter!$X$5:$X$750=TRUE())*(BankQuarter!$V$5:$V$750=$A6)*BankQuarter!$F$5:$F$750),"") -> 0.25554764 | F6: =IFERROR(SUMPRODUCT((BankQuarter!$D$5:$D$750=WF_START_PERIOD)*(BankQuarter!$R$5:$R$750=TRUE())*(BankQuarter!$X$5:$X$750=TRUE())*(BankQuarter!$V$5:$V$750=$A6)*BankQuarter!$F$5:$F$750*BankQuarter!$U$5:$U$750)/SUMPRODUCT((BankQuarter!$D$5:$D$750=WF_START_PERIOD)*(BankQuarter!$R$5:$R$750=TRUE())*(BankQuarter!$X$5:$X$750=TRUE())*(BankQuarter!$V$5:$V$750=$A6)*BankQuarter!$F$5:$F$750),"") -> 0.35303711 | G6: =F6-E6 -> 0.097489475 | H6: =D6-G6 -> 0.0056880831 | I6: =SUMPRODUCT((BankQuarter!$D$5:$D$750=WF_START_PERIOD)*(BankQuarter!$R$5:$R$750=TRUE())*(BankQuarter!$X$5:$X$750=TRUE())*(BankQuarter!$V$5:$V$750=$A6)) -> 22 | J6: =SUMPRODUCT((BankQuarter!$D$5:$D$750=WF_END_PERIOD)*(BankQuarter!$R$5:$R$750=TRUE())*(BankQuarter!$E$5:$E$750=$A6)*((BankQuarter!$W$5:$W$750=FALSE())+(BankQuarter!$Y$5:$Y$750<>$A6)>0)) -> 0 | K6: =SUMPRODUCT((BankQuarter!$D$5:$D$750=WF_START_PERIOD)*(BankQuarter!$R$5:$R$750=TRUE())*(BankQuarter!$E$5:$E$750=$A6)*((BankQuarter!$X$5:$X$750=FALSE())+(BankQuarter!$V$5:$V$750<>$A6)>0)) -> 1 | L6: =SUMPRODUCT((BankQuarter!$D$5:$D$750=WF_END_PERIOD)*(BankQuarter!$R$5:$R$750=TRUE())*(BankQuarter!$E$5:$E$750=$A6)*((BankQuarter!$W$5:$W$750=FALSE())+(BankQuarter!$Y$5:$Y$750<>$A6)>0)*BankQuarter!$F$5:$F$750) -> 0 | M6: =SUMPRODUCT((BankQuarter!$D$5:$D$750=WF_START_PERIOD)*(BankQuarter!$R$5:$R$750=TRUE())*(BankQuarter!$E$5:$E$750=$A6)*((BankQuarter!$X$5:$X$750=FALSE())+(BankQuarter!$V$5:$V$750<>$A6)>0)*BankQuarter!$F$5:$F$750) -> 1653584
A7: NH | B7: =IFERROR(100*SUMIFS(BankQuarter!$I$5:$I$750,BankQuarter!$D$5:$D$750,WF_START_PERIOD,BankQuarter!$R$5:$R$750,TRUE(),BankQuarter!$E$5:$E$750,$A7)/SUMIFS(BankQuarter!$F$5:$F$750,BankQuarter!$D$5:$D$750,WF_START_PERIOD,BankQuarter!$R$5:$R$750,TRUE(),BankQuarter!$E$5:$E$750,$A7),"") -> 0.36509033 | C7: =IFERROR(100*SUMIFS(BankQuarter!$I$5:$I$750,BankQuarter!$D$5:$D$750,WF_END_PERIOD,BankQuarter!$R$5:$R$750,TRUE(),BankQuarter!$E$5:$E$750,$A7)/SUMIFS(BankQuarter!$F$5:$F$750,BankQuarter!$D$5:$D$750,WF_END_PERIOD,BankQuarter!$R$5:$R$750,TRUE(),BankQuarter!$E$5:$E$750,$A7),"") -> 0.30595397 | D7: =C7-B7 -> -0.059136359 | E7: =IFERROR(100*SUMPRODUCT((BankQuarter!$D$5:$D$750=WF_START_PERIOD)*(BankQuarter!$R$5:$R$750=TRUE())*(BankQuarter!$X$5:$X$750=TRUE())*(BankQuarter!$V$5:$V$750=$A7)*BankQuarter!$I$5:$I$750)/SUMPRODUCT((BankQuarter!$D$5:$D$750=WF_START_PERIOD)*(BankQuarter!$R$5:$R$750=TRUE())*(BankQuarter!$X$5:$X$750=TRUE())*(BankQuarter!$V$5:$V$750=$A7)*BankQuarter!$F$5:$F$750),"") -> 0.37186264 | F7: =IFERROR(SUMPRODUCT((BankQuarter!$D$5:$D$750=WF_START_PERIOD)*(BankQuarter!$R$5:$R$750=TRUE())*(BankQuarter!$X$5:$X$750=TRUE())*(BankQuarter!$V$5:$V$750=$A7)*BankQuarter!$F$5:$F$750*BankQuarter!$U$5:$U$750)/SUMPRODUCT((BankQuarter!$D$5:$D$750=WF_START_PERIOD)*(BankQuarter!$R$5:$R$750=TRUE())*(BankQuarter!$X$5:$X$750=TRUE())*(BankQuarter!$V$5:$V$750=$A7)*BankQuarter!$F$5:$F$750),"") -> 0.29904611 | G7: =F7-E7 -> -0.072816535 | H7: =D7-G7 -> 0.013680176 | I7: =SUMPRODUCT((BankQuarter!$D$5:$D$750=WF_START_PERIOD)*(BankQuarter!$R$5:$R$750=TRUE())*(BankQuarter!$X$5:$X$750=TRUE())*(BankQuarter!$V$5:$V$750=$A7)) -> 18 | J7: =SUMPRODUCT((BankQuarter!$D$5:$D$750=WF_END_PERIOD)*(BankQuarter!$R$5:$R$750=TRUE())*(BankQuarter!$E$5:$E$750=$A7)*((BankQuarter!$W$5:$W$750=FALSE())+(BankQuarter!$Y$5:$Y$750<>$A7)>0)) -> 0 | K7: =SUMPRODUCT((BankQuarter!$D$5:$D$750=WF_START_PERIOD)*(BankQuarter!$R$5:$R$750=TRUE())*(BankQuarter!$E$5:$E$750=$A7)*((BankQuarter!$X$5:$X$750=FALSE())+(BankQuarter!$V$5:$V$750<>$A7)>0)) -> 1 | L7: =SUMPRODUCT((BankQuarter!$D$5:$D$750=WF_END_PERIOD)*(BankQuarter!$R$5:$R$750=TRUE())*(BankQuarter!$E$5:$E$750=$A7)*((BankQuarter!$W$5:$W$750=FALSE())+(BankQuarter!$Y$5:$Y$750<>$A7)>0)*BankQuarter!$F$5:$F$750) -> 0 | M7: =SUMPRODUCT((BankQuarter!$D$5:$D$750=WF_START_PERIOD)*(BankQuarter!$R$5:$R$750=TRUE())*(BankQuarter!$E$5:$E$750=$A7)*((BankQuarter!$X$5:$X$750=FALSE())+(BankQuarter!$V$5:$V$750<>$A7)>0)*BankQuarter!$F$5:$F$750) -> 1270696
A8: VT | B8: =IFERROR(100*SUMIFS(BankQuarter!$I$5:$I$750,BankQuarter!$D$5:$D$750,WF_START_PERIOD,BankQuarter!$R$5:$R$750,TRUE(),BankQuarter!$E$5:$E$750,$A8)/SUMIFS(BankQuarter!$F$5:$F$750,BankQuarter!$D$5:$D$750,WF_START_PERIOD,BankQuarter!$R$5:$R$750,TRUE(),BankQuarter!$E$5:$E$750,$A8),"") -> 0.33860386 | C8: =IFERROR(100*SUMIFS(BankQuarter!$I$5:$I$750,BankQuarter!$D$5:$D$750,WF_END_PERIOD,BankQuarter!$R$5:$R$750,TRUE(),BankQuarter!$E$5:$E$750,$A8)/SUMIFS(BankQuarter!$F$5:$F$750,BankQuarter!$D$5:$D$750,WF_END_PERIOD,BankQuarter!$R$5:$R$750,TRUE(),BankQuarter!$E$5:$E$750,$A8),"") -> 0.49473123 | D8: =C8-B8 -> 0.15612738 | E8: =IFERROR(100*SUMPRODUCT((BankQuarter!$D$5:$D$750=WF_START_PERIOD)*(BankQuarter!$R$5:$R$750=TRUE())*(BankQuarter!$X$5:$X$750=TRUE())*(BankQuarter!$V$5:$V$750=$A8)*BankQuarter!$I$5:$I$750)/SUMPRODUCT((BankQuarter!$D$5:$D$750=WF_START_PERIOD)*(BankQuarter!$R$5:$R$750=TRUE())*(BankQuarter!$X$5:$X$750=TRUE())*(BankQuarter!$V$5:$V$750=$A8)*BankQuarter!$F$5:$F$750),"") -> 0.33860386 | F8: =IFERROR(SUMPRODUCT((BankQuarter!$D$5:$D$750=WF_START_PERIOD)*(BankQuarter!$R$5:$R$750=TRUE())*(BankQuarter!$X$5:$X$750=TRUE())*(BankQuarter!$V$5:$V$750=$A8)*BankQuarter!$F$5:$F$750*BankQuarter!$U$5:$U$750)/SUMPRODUCT((BankQuarter!$D$5:$D$750=WF_START_PERIOD)*(BankQuarter!$R$5:$R$750=TRUE())*(BankQuarter!$X$5:$X$750=TRUE())*(BankQuarter!$V$5:$V$750=$A8)*BankQuarter!$F$5:$F$750),"") -> 0.49541724 | G8: =F8-E8 -> 0.15681339 | H8: =D8-G8 -> -0.00068601043 | I8: =SUMPRODUCT((BankQuarter!$D$5:$D$750=WF_START_PERIOD)*(BankQuarter!$R$5:$R$750=TRUE())*(BankQuarter!$X$5:$X$750=TRUE())*(BankQuarter!$V$5:$V$750=$A8)) -> 12 | J8: =SUMPRODUCT((BankQuarter!$D$5:$D$750=WF_END_PERIOD)*(BankQuarter!$R$5:$R$750=TRUE())*(BankQuarter!$E$5:$E$750=$A8)*((BankQuarter!$W$5:$W$750=FALSE())+(BankQuarter!$Y$5:$Y$750<>$A8)>0)) -> 0 | K8: =SUMPRODUCT((BankQuarter!$D$5:$D$750=WF_START_PERIOD)*(BankQuarter!$R$5:$R$750=TRUE())*(BankQuarter!$E$5:$E$750=$A8)*((BankQuarter!$X$5:$X$750=FALSE())+(BankQuarter!$V$5:$V$750<>$A8)>0)) -> 0 | L8: =SUMPRODUCT((BankQuarter!$D$5:$D$750=WF_END_PERIOD)*(BankQuarter!$R$5:$R$750=TRUE())*(BankQuarter!$E$5:$E$750=$A8)*((BankQuarter!$W$5:$W$750=FALSE())+(BankQuarter!$Y$5:$Y$750<>$A8)>0)*BankQuarter!$F$5:$F$750) -> 0 | M8: =SUMPRODUCT((BankQuarter!$D$5:$D$750=WF_START_PERIOD)*(BankQuarter!$R$5:$R$750=TRUE())*(BankQuarter!$E$5:$E$750=$A8)*((BankQuarter!$X$5:$X$750=FALSE())+(BankQuarter!$V$5:$V$750<>$A8)>0)*BankQuarter!$F$5:$F$750) -> 0
A11: Definitions
A12: Observed: each endpoint’s valid-bank population and current endpoint assets. Fixed: banks valid at both endpoints, assigned to the selected end-period state, with start-period ASSET held fixed at both dates. Entering/exiting: endpoint valid-set differences within each group; blanks/zero ASSET are not zero-asset members. Residual = observed change − fixed change and is labelled only as scope and weight change impact, without unsupported causal decomposition.
A17: Endpoint membership detail
A18: CERT | B18: Bank name | C18: Start state | D18: End state | E18: Start valid? | F18: End valid? | G18: Movement | H18: Start assets ($000) | I18: End assets ($000) | J18: Start source row | K18: End source row | L18: Start proxy % | M18: End proxy %
A19: 4255 | B19: =IF(COUNTIFS(BankQuarter!$B$5:$B$750,A19,BankQuarter!$D$5:$D$750,WF_END_PERIOD)>0,INDEX(BankQuarter!$C$5:$C$750,MATCH(A19&"|"&WF_END_PERIOD,BankQuarter!$AC$5:$AC$750,0)),IF(COUNTIFS(BankQuarter!$B$5:$B$750,A19,BankQuarter!$D$5:$D$750,WF_START_PERIOD)>0,INDEX(BankQuarter!$C$5:$C$750,MATCH(A19&"|"&WF_START_PERIOD,BankQuarter!$AC$5:$AC$750,0)),"")) -> THE CAMDEN NATIONAL BANK | C19: =IF(COUNTIFS(BankQuarter!$B$5:$B$750,A19,BankQuarter!$D$5:$D$750,WF_START_PERIOD)=0,"",INDEX(BankQuarter!$E$5:$E$750,MATCH(A19&"|"&WF_START_PERIOD,BankQuarter!$AC$5:$AC$750,0))) -> ME | D19: =IF(COUNTIFS(BankQuarter!$B$5:$B$750,A19,BankQuarter!$D$5:$D$750,WF_END_PERIOD)=0,"",INDEX(BankQuarter!$E$5:$E$750,MATCH(A19&"|"&WF_END_PERIOD,BankQuarter!$AC$5:$AC$750,0))) -> ME | E19: =COUNTIFS(BankQuarter!$B$5:$B$750,A19,BankQuarter!$D$5:$D$750,WF_START_PERIOD,BankQuarter!$R$5:$R$750,TRUE())>0 -> TRUE | F19: =COUNTIFS(BankQuarter!$B$5:$B$750,A19,BankQuarter!$D$5:$D$750,WF_END_PERIOD,BankQuarter!$R$5:$R$750,TRUE())>0 -> TRUE | G19: =IF(AND(E19,F19),IF(C19=D19,"Common","State move "&C19&"→"&D19),IF(AND(E19,NOT(F19)),"Exiting ALL",IF(AND(NOT(E19),F19),"Entering ALL","Neither valid"))) -> Common | H19: =IF(COUNTIFS(BankQuarter!$B$5:$B$750,A19,BankQuarter!$D$5:$D$750,WF_START_PERIOD)=0,"",INDEX(BankQuarter!$F$5:$F$750,MATCH(A19&"|"&WF_START_PERIOD,BankQuarter!$AC$5:$AC$750,0))) -> 5709625 | I19: =IF(COUNTIFS(BankQuarter!$B$5:$B$750,A19,BankQuarter!$D$5:$D$750,WF_END_PERIOD)=0,"",INDEX(BankQuarter!$F$5:$F$750,MATCH(A19&"|"&WF_END_PERIOD,BankQuarter!$AC$5:$AC$750,0))) -> 6902692 | J19: =IF(COUNTIFS(BankQuarter!$B$5:$B$750,A19,BankQuarter!$D$5:$D$750,WF_START_PERIOD)=0,"",INDEX(BankQuarter!$A$5:$A$750,MATCH(A19&"|"&WF_START_PERIOD,BankQuarter!$AC$5:$AC$750,0))) -> 527 | K19: =IF(COUNTIFS(BankQuarter!$B$5:$B$750,A19,BankQuarter!$D$5:$D$750,WF_END_PERIOD)=0,"",INDEX(BankQuarter!$A$5:$A$750,MATCH(A19&"|"&WF_END_PERIOD,BankQuarter!$AC$5:$AC$750,0))) -> 739 | L19: =IF(COUNTIFS(BankQuarter!$B$5:$B$750,A19,BankQuarter!$D$5:$D$750,WF_START_PERIOD)=0,"",INDEX(BankQuarter!$S$5:$S$750,MATCH(A19&"|"&WF_START_PERIOD,BankQuarter!$AC$5:$AC$750,0))) -> 0.13652385 | M19: =IF(COUNTIFS(BankQuarter!$B$5:$B$750,A19,BankQuarter!$D$5:$D$750,WF_END_PERIOD)=0,"",INDEX(BankQuarter!$S$5:$S$750,MATCH(A19&"|"&WF_END_PERIOD,BankQuarter!$AC$5:$AC$750,0))) -> 0.26333204
A20: 4256 | B20: =IF(COUNTIFS(BankQuarter!$B$5:$B$750,A20,BankQuarter!$D$5:$D$750,WF_END_PERIOD)>0,INDEX(BankQuarter!$C$5:$C$750,MATCH(A20&"|"&WF_END_PERIOD,BankQuarter!$AC$5:$AC$750,0)),IF(COUNTIFS(BankQuarter!$B$5:$B$750,A20,BankQuarter!$D$5:$D$750,WF_START_PERIOD)>0,INDEX(BankQuarter!$C$5:$C$750,MATCH(A20&"|"&WF_START_PERIOD,BankQuarter!$AC$5:$AC$750,0)),"")) -> FIRST NATIONAL BANK | C20: =IF(COUNTIFS(BankQuarter!$B$5:$B$750,A20,BankQuarter!$D$5:$D$750,WF_START_PERIOD)=0,"",INDEX(BankQuarter!$E$5:$E$750,MATCH(A20&"|"&WF_START_PERIOD,BankQuarter!$AC$5:$AC$750,0))) -> ME | D20: =IF(COUNTIFS(BankQuarter!$B$5:$B$750,A20,BankQuarter!$D$5:$D$750,WF_END_PERIOD)=0,"",INDEX(BankQuarter!$E$5:$E$750,MATCH(A20&"|"&WF_END_PERIOD,BankQuarter!$AC$5:$AC$750,0))) -> ME | E20: =COUNTIFS(BankQuarter!$B$5:$B$750,A20,BankQuarter!$D$5:$D$750,WF_START_PERIOD,BankQuarter!$R$5:$R$750,TRUE())>0 -> TRUE | F20: =COUNTIFS(BankQuarter!$B$5:$B$750,A20,BankQuarter!$D$5:$D$750,WF_END_PERIOD,BankQuarter!$R$5:$R$750,TRUE())>0 -> TRUE | G20: =IF(AND(E20,F20),IF(C20=D20,"Common","State move "&C20&"→"&D20),IF(AND(E20,NOT(F20)),"Exiting ALL",IF(AND(NOT(E20),F20),"Entering ALL","Neither valid"))) -> Common | H20: =IF(COUNTIFS(BankQuarter!$B$5:$B$750,A20,BankQuarter!$D$5:$D$750,WF_START_PERIOD)=0,"",INDEX(BankQuarter!$F$5:$F$750,MATCH(A20&"|"&WF_START_PERIOD,BankQuarter!$AC$5:$AC$750,0))) -> 3049270 | I20: =IF(COUNTIFS(BankQuarter!$B$5:$B$750,A20,BankQuarter!$D$5:$D$750,WF_END_PERIOD)=0,"",INDEX(BankQuarter!$F$5:$F$750,MATCH(A20&"|"&WF_END_PERIOD,BankQuarter!$AC$5:$AC$750,0))) -> 3164056 | J20: =IF(COUNTIFS(BankQuarter!$B$5:$B$750,A20,BankQuarter!$D$5:$D$750,WF_START_PERIOD)=0,"",INDEX(BankQuarter!$A$5:$A$750,MATCH(A20&"|"&WF_START_PERIOD,BankQuarter!$AC$5:$AC$750,0))) -> 528 | K20: =IF(COUNTIFS(BankQuarter!$B$5:$B$750,A20,BankQuarter!$D$5:$D$750,WF_END_PERIOD)=0,"",INDEX(BankQuarter!$A$5:$A$750,MATCH(A20&"|"&WF_END_PERIOD,BankQuarter!$AC$5:$AC$750,0))) -> 740 | L20: =IF(COUNTIFS(BankQuarter!$B$5:$B$750,A20,BankQuarter!$D$5:$D$750,WF_START_PERIOD)=0,"",INDEX(BankQuarter!$S$5:$S$750,MATCH(A20&"|"&WF_START_PERIOD,BankQuarter!$AC$5:$AC$750,0))) -> 0.086938841 | M20: =IF(COUNTIFS(BankQuarter!$B$5:$B$750,A20,BankQuarter!$D$5:$D$750,WF_END_PERIOD)=0,"",INDEX(BankQuarter!$S$5:$S$750,MATCH(A20&"|"&WF_END_PERIOD,BankQuarter!$AC$5:$AC$750,0))) -> 0.2053061
A21: 6271 | B21: =IF(COUNTIFS(BankQuarter!$B$5:$B$750,A21,BankQuarter!$D$5:$D$750,WF_END_PERIOD)>0,INDEX(BankQuarter!$C$5:$C$750,MATCH(A21&"|"&WF_END_PERIOD,BankQuarter!$AC$5:$AC$750,0)),IF(COUNTIFS(BankQuarter!$B$5:$B$750,A21,BankQuarter!$D$5:$D$750,WF_START_PERIOD)>0,INDEX(BankQuarter!$C$5:$C$750,MATCH(A21&"|"&WF_START_PERIOD,BankQuarter!$AC$5:$AC$750,0)),"")) -> COMMUNITY NATIONAL BANK | C21: =IF(COUNTIFS(BankQuarter!$B$5:$B$750,A21,BankQuarter!$D$5:$D$750,WF_START_PERIOD)=0,"",INDEX(BankQuarter!$E$5:$E$750,MATCH(A21&"|"&WF_START_PERIOD,BankQuarter!$AC$5:$AC$750,0))) -> VT | D21: =IF(COUNTIFS(BankQuarter!$B$5:$B$750,A21,BankQuarter!$D$5:$D$750,WF_END_PERIOD)=0,"",INDEX(BankQuarter!$E$5:$E$750,MATCH(A21&"|"&WF_END_PERIOD,BankQuarter!$AC$5:$AC$750,0))) -> VT | E21: =COUNTIFS(BankQuarter!$B$5:$B$750,A21,BankQuarter!$D$5:$D$750,WF_START_PERIOD,BankQuarter!$R$5:$R$750,TRUE())>0 -> TRUE | F21: =COUNTIFS(BankQuarter!$B$5:$B$750,A21,BankQuarter!$D$5:$D$750,WF_END_PERIOD,BankQuarter!$R$5:$R$750,TRUE())>0 -> TRUE | G21: =IF(AND(E21,F21),IF(C21=D21,"Common","State move "&C21&"→"&D21),IF(AND(E21,NOT(F21)),"Exiting ALL",IF(AND(NOT(E21),F21),"Entering ALL","Neither valid"))) -> Common | H21: =IF(COUNTIFS(BankQuarter!$B$5:$B$750,A21,BankQuarter!$D$5:$D$750,WF_START_PERIOD)=0,"",INDEX(BankQuarter!$F$5:$F$750,MATCH(A21&"|"&WF_START_PERIOD,BankQuarter!$AC$5:$AC$750,0))) -> 1099892 | I21: =IF(COUNTIFS(BankQuarter!$B$5:$B$750,A21,BankQuarter!$D$5:$D$750,WF_END_PERIOD)=0,"",INDEX(BankQuarter!$F$5:$F$750,MATCH(A21&"|"&WF_END_PERIOD,BankQuarter!$AC$5:$AC$750,0))) -> 1166044 | J21: =IF(COUNTIFS(BankQuarter!$B$5:$B$750,A21,BankQuarter!$D$5:$D$750,WF_START_PERIOD)=0,"",INDEX(BankQuarter!$A$5:$A$750,MATCH(A21&"|"&WF_START_PERIOD,BankQuarter!$AC$5:$AC$750,0))) -> 533 | K21: =IF(COUNTIFS(BankQuarter!$B$5:$B$750,A21,BankQuarter!$D$5:$D$750,WF_END_PERIOD)=0,"",INDEX(BankQuarter!$A$5:$A$750,MATCH(A21&"|"&WF_END_PERIOD,BankQuarter!$AC$5:$AC$750,0))) -> 745 | L21: =IF(COUNTIFS(BankQuarter!$B$5:$B$750,A21,BankQuarter!$D$5:$D$750,WF_START_PERIOD)=0,"",INDEX(BankQuarter!$S$5:$S$750,MATCH(A21&"|"&WF_START_PERIOD,BankQuarter!$AC$5:$AC$750,0))) -> 0.58969426 | M21: =IF(COUNTIFS(BankQuarter!$B$5:$B$750,A21,BankQuarter!$D$5:$D$750,WF_END_PERIOD)=0,"",INDEX(BankQuarter!$S$5:$S$750,MATCH(A21&"|"&WF_END_PERIOD,BankQuarter!$AC$5:$AC$750,0))) -> 0.79165109
A22: 6275 | B22: =IF(COUNTIFS(BankQuarter!$B$5:$B$750,A22,BankQuarter!$D$5:$D$750,WF_END_PERIOD)>0,INDEX(BankQuarter!$C$5:$C$750,MATCH(A22&"|"&WF_END_PERIOD,BankQuarter!$AC$5:$AC$750,0)),IF(COUNTIFS(BankQuarter!$B$5:$B$750,A22,BankQuarter!$D$5:$D$750,WF_START_PERIOD)>0,INDEX(BankQuarter!$C$5:$C$750,MATCH(A22&"|"&WF_START_PERIOD,BankQuarter!$AC$5:$AC$750,0)),"")) -> THE NATIONAL BANK OF MIDDLEBURY | C22: =IF(COUNTIFS(BankQuarter!$B$5:$B$750,A22,BankQuarter!$D$5:$D$750,WF_START_PERIOD)=0,"",INDEX(BankQuarter!$E$5:$E$750,MATCH(A22&"|"&WF_START_PERIOD,BankQuarter!$AC$5:$AC$750,0))) -> VT | D22: =IF(COUNTIFS(BankQuarter!$B$5:$B$750,A22,BankQuarter!$D$5:$D$750,WF_END_PERIOD)=0,"",INDEX(BankQuarter!$E$5:$E$750,MATCH(A22&"|"&WF_END_PERIOD,BankQuarter!$AC$5:$AC$750,0))) -> VT | E22: =COUNTIFS(BankQuarter!$B$5:$B$750,A22,BankQuarter!$D$5:$D$750,WF_START_PERIOD,BankQuarter!$R$5:$R$750,TRUE())>0 -> TRUE | F22: =COUNTIFS(BankQuarter!$B$5:$B$750,A22,BankQuarter!$D$5:$D$750,WF_END_PERIOD,BankQuarter!$R$5:$R$750,TRUE())>0 -> TRUE | G22: =IF(AND(E22,F22),IF(C22=D22,"Common","State move "&C22&"→"&D22),IF(AND(E22,NOT(F22)),"Exiting ALL",IF(AND(NOT(E22),F22),"Entering ALL","Neither valid"))) -> Common | H22: =IF(COUNTIFS(BankQuarter!$B$5:$B$750,A22,BankQuarter!$D$5:$D$750,WF_START_PERIOD)=0,"",INDEX(BankQuarter!$F$5:$F$750,MATCH(A22&"|"&WF_START_PERIOD,BankQuarter!$AC$5:$AC$750,0))) -> 555322 | I22: =IF(COUNTIFS(BankQuarter!$B$5:$B$750,A22,BankQuarter!$D$5:$D$750,WF_END_PERIOD)=0,"",INDEX(BankQuarter!$F$5:$F$750,MATCH(A22&"|"&WF_END_PERIOD,BankQuarter!$AC$5:$AC$750,0))) -> 552605 | J22: =IF(COUNTIFS(BankQuarter!$B$5:$B$750,A22,BankQuarter!$D$5:$D$750,WF_START_PERIOD)=0,"",INDEX(BankQuarter!$A$5:$A$750,MATCH(A22&"|"&WF_START_PERIOD,BankQuarter!$AC$5:$AC$750,0))) -> 534 | K22: =IF(COUNTIFS(BankQuarter!$B$5:$B$750,A22,BankQuarter!$D$5:$D$750,WF_END_PERIOD)=0,"",INDEX(BankQuarter!$A$5:$A$750,MATCH(A22&"|"&WF_END_PERIOD,BankQuarter!$AC$5:$AC$750,0))) -> 746 | L22: =IF(COUNTIFS(BankQuarter!$B$5:$B$750,A22,BankQuarter!$D$5:$D$750,WF_START_PERIOD)=0,"",INDEX(BankQuarter!$S$5:$S$750,MATCH(A22&"|"&WF_START_PERIOD,BankQuarter!$AC$5:$AC$750,0))) -> 0.2038457 | M22: =IF(COUNTIFS(BankQuarter!$B$5:$B$750,A22,BankQuarter!$D$5:$D$750,WF_END_PERIOD)=0,"",INDEX(BankQuarter!$S$5:$S$750,MATCH(A22&"|"&WF_END_PERIOD,BankQuarter!$AC$5:$AC$750,0))) -> 0.11798663
A23: 6280 | B23: =IF(COUNTIFS(BankQuarter!$B$5:$B$750,A23,BankQuarter!$D$5:$D$750,WF_END_PERIOD)>0,INDEX(BankQuarter!$C$5:$C$750,MATCH(A23&"|"&WF_END_PERIOD,BankQuarter!$AC$5:$AC$750,0)),IF(COUNTIFS(BankQuarter!$B$5:$B$750,A23,BankQuarter!$D$5:$D$750,WF_START_PERIOD)>0,INDEX(BankQuarter!$C$5:$C$750,MATCH(A23&"|"&WF_START_PERIOD,BankQuarter!$AC$5:$AC$750,0)),"")) -> THE FIRST NATIONAL BANK OF ORWELL | C23: =IF(COUNTIFS(BankQuarter!$B$5:$B$750,A23,BankQuarter!$D$5:$D$750,WF_START_PERIOD)=0,"",INDEX(BankQuarter!$E$5:$E$750,MATCH(A23&"|"&WF_START_PERIOD,BankQuarter!$AC$5:$AC$750,0))) -> VT | D23: =IF(COUNTIFS(BankQuarter!$B$5:$B$750,A23,BankQuarter!$D$5:$D$750,WF_END_PERIOD)=0,"",INDEX(BankQuarter!$E$5:$E$750,MATCH(A23&"|"&WF_END_PERIOD,BankQuarter!$AC$5:$AC$750,0))) -> VT | E23: =COUNTIFS(BankQuarter!$B$5:$B$750,A23,BankQuarter!$D$5:$D$750,WF_START_PERIOD,BankQuarter!$R$5:$R$750,TRUE())>0 -> TRUE | F23: =COUNTIFS(BankQuarter!$B$5:$B$750,A23,BankQuarter!$D$5:$D$750,WF_END_PERIOD,BankQuarter!$R$5:$R$750,TRUE())>0 -> TRUE | G23: =IF(AND(E23,F23),IF(C23=D23,"Common","State move "&C23&"→"&D23),IF(AND(E23,NOT(F23)),"Exiting ALL",IF(AND(NOT(E23),F23),"Entering ALL","Neither valid"))) -> Common | H23: =IF(COUNTIFS(BankQuarter!$B$5:$B$750,A23,BankQuarter!$D$5:$D$750,WF_START_PERIOD)=0,"",INDEX(BankQuarter!$F$5:$F$750,MATCH(A23&"|"&WF_START_PERIOD,BankQuarter!$AC$5:$AC$750,0))) -> 81265 | I23: =IF(COUNTIFS(BankQuarter!$B$5:$B$750,A23,BankQuarter!$D$5:$D$750,WF_END_PERIOD)=0,"",INDEX(BankQuarter!$F$5:$F$750,MATCH(A23&"|"&WF_END_PERIOD,BankQuarter!$AC$5:$AC$750,0))) -> 87770 | J23: =IF(COUNTIFS(BankQuarter!$B$5:$B$750,A23,BankQuarter!$D$5:$D$750,WF_START_PERIOD)=0,"",INDEX(BankQuarter!$A$5:$A$750,MATCH(A23&"|"&WF_START_PERIOD,BankQuarter!$AC$5:$AC$750,0))) -> 535 | K23: =IF(COUNTIFS(BankQuarter!$B$5:$B$750,A23,BankQuarter!$D$5:$D$750,WF_END_PERIOD)=0,"",INDEX(BankQuarter!$A$5:$A$750,MATCH(A23&"|"&WF_END_PERIOD,BankQuarter!$AC$5:$AC$750,0))) -> 747 | L23: =IF(COUNTIFS(BankQuarter!$B$5:$B$750,A23,BankQuarter!$D$5:$D$750,WF_START_PERIOD)=0,"",INDEX(BankQuarter!$S$5:$S$750,MATCH(A23&"|"&WF_START_PERIOD,BankQuarter!$AC$5:$AC$750,0))) -> 1.4840337 | M23: =IF(COUNTIFS(BankQuarter!$B$5:$B$750,A23,BankQuarter!$D$5:$D$750,WF_END_PERIOD)=0,"",INDEX(BankQuarter!$S$5:$S$750,MATCH(A23&"|"&WF_END_PERIOD,BankQuarter!$AC$5:$AC$750,0))) -> 1.6577418
A24: 11971 | B24: =IF(COUNTIFS(BankQuarter!$B$5:$B$750,A24,BankQuarter!$D$5:$D$750,WF_END_PERIOD)>0,INDEX(BankQuarter!$C$5:$C$750,MATCH(A24&"|"&WF_END_PERIOD,BankQuarter!$AC$5:$AC$750,0)),IF(COUNTIFS(BankQuarter!$B$5:$B$750,A24,BankQuarter!$D$5:$D$750,WF_START_PERIOD)>0,INDEX(BankQuarter!$C$5:$C$750,MATCH(A24&"|"&WF_START_PERIOD,BankQuarter!$AC$5:$AC$750,0)),"")) -> BAR HARBOR BANK & TRUST | C24: =IF(COUNTIFS(BankQuarter!$B$5:$B$750,A24,BankQuarter!$D$5:$D$750,WF_START_PERIOD)=0,"",INDEX(BankQuarter!$E$5:$E$750,MATCH(A24&"|"&WF_START_PERIOD,BankQuarter!$AC$5:$AC$750,0))) -> ME | D24: =IF(COUNTIFS(BankQuarter!$B$5:$B$750,A24,BankQuarter!$D$5:$D$750,WF_END_PERIOD)=0,"",INDEX(BankQuarter!$E$5:$E$750,MATCH(A24&"|"&WF_END_PERIOD,BankQuarter!$AC$5:$AC$750,0))) -> ME | E24: =COUNTIFS(BankQuarter!$B$5:$B$750,A24,BankQuarter!$D$5:$D$750,WF_START_PERIOD,BankQuarter!$R$5:$R$750,TRUE())>0 -> TRUE | F24: =COUNTIFS(BankQuarter!$B$5:$B$750,A24,BankQuarter!$D$5:$D$750,WF_END_PERIOD,BankQuarter!$R$5:$R$750,TRUE())>0 -> TRUE | G24: =IF(AND(E24,F24),IF(C24=D24,"Common","State move "&C24&"→"&D24),IF(AND(E24,NOT(F24)),"Exiting ALL",IF(AND(NOT(E24),F24),"Entering ALL","Neither valid"))) -> Common | H24: =IF(COUNTIFS(BankQuarter!$B$5:$B$750,A24,BankQuarter!$D$5:$D$750,WF_START_PERIOD)=0,"",INDEX(BankQuarter!$F$5:$F$750,MATCH(A24&"|"&WF_START_PERIOD,BankQuarter!$AC$5:$AC$750,0))) -> 4030143 | I24: =IF(COUNTIFS(BankQuarter!$B$5:$B$750,A24,BankQuarter!$D$5:$D$750,WF_END_PERIOD)=0,"",INDEX(BankQuarter!$F$5:$F$750,MATCH(A24&"|"&WF_END_PERIOD,BankQuarter!$AC$5:$AC$750,0))) -> 4106441 | J24: =IF(COUNTIFS(BankQuarter!$B$5:$B$750,A24,BankQuarter!$D$5:$D$750,WF_START_PERIOD)=0,"",INDEX(BankQuarter!$A$5:$A$750,MATCH(A24&"|"&WF_START_PERIOD,BankQuarter!$AC$5:$AC$750,0))) -> 482 | K24: =IF(COUNTIFS(BankQuarter!$B$5:$B$750,A24,BankQuarter!$D$5:$D$750,WF_END_PERIOD)=0,"",INDEX(BankQuarter!$A$5:$A$750,MATCH(A24&"|"&WF_END_PERIOD,BankQuarter!$AC$5:$AC$750,0))) -> 696 | L24: =IF(COUNTIFS(BankQuarter!$B$5:$B$750,A24,BankQuarter!$D$5:$D$750,WF_START_PERIOD)=0,"",INDEX(BankQuarter!$S$5:$S$750,MATCH(A24&"|"&WF_START_PERIOD,BankQuarter!$AC$5:$AC$750,0))) -> 0.15657013 | M24: =IF(COUNTIFS(BankQuarter!$B$5:$B$750,A24,BankQuarter!$D$5:$D$750,WF_END_PERIOD)=0,"",INDEX(BankQuarter!$S$5:$S$750,MATCH(A24&"|"&WF_END_PERIOD,BankQuarter!$AC$5:$AC$750,0))) -> 0.24744055
A25: 12874 | B25: =IF(COUNTIFS(BankQuarter!$B$5:$B$750,A25,BankQuarter!$D$5:$D$750,WF_END_PERIOD)>0,INDEX(BankQuarter!$C$5:$C$750,MATCH(A25&"|"&WF_END_PERIOD,BankQuarter!$AC$5:$AC$750,0)),IF(COUNTIFS(BankQuarter!$B$5:$B$750,A25,BankQuarter!$D$5:$D$750,WF_START_PERIOD)>0,INDEX(BankQuarter!$C$5:$C$750,MATCH(A25&"|"&WF_START_PERIOD,BankQuarter!$AC$5:$AC$750,0)),"")) -> KATAHDIN TRUST COMPANY | C25: =IF(COUNTIFS(BankQuarter!$B$5:$B$750,A25,BankQuarter!$D$5:$D$750,WF_START_PERIOD)=0,"",INDEX(BankQuarter!$E$5:$E$750,MATCH(A25&"|"&WF_START_PERIOD,BankQuarter!$AC$5:$AC$750,0))) -> ME | D25: =IF(COUNTIFS(BankQuarter!$B$5:$B$750,A25,BankQuarter!$D$5:$D$750,WF_END_PERIOD)=0,"",INDEX(BankQuarter!$E$5:$E$750,MATCH(A25&"|"&WF_END_PERIOD,BankQuarter!$AC$5:$AC$750,0))) -> ME | E25: =COUNTIFS(BankQuarter!$B$5:$B$750,A25,BankQuarter!$D$5:$D$750,WF_START_PERIOD,BankQuarter!$R$5:$R$750,TRUE())>0 -> TRUE | F25: =COUNTIFS(BankQuarter!$B$5:$B$750,A25,BankQuarter!$D$5:$D$750,WF_END_PERIOD,BankQuarter!$R$5:$R$750,TRUE())>0 -> TRUE | G25: =IF(AND(E25,F25),IF(C25=D25,"Common","State move "&C25&"→"&D25),IF(AND(E25,NOT(F25)),"Exiting ALL",IF(AND(NOT(E25),F25),"Entering ALL","Neither valid"))) -> Common | H25: =IF(COUNTIFS(BankQuarter!$B$5:$B$750,A25,BankQuarter!$D$5:$D$750,WF_START_PERIOD)=0,"",INDEX(BankQuarter!$F$5:$F$750,MATCH(A25&"|"&WF_START_PERIOD,BankQuarter!$AC$5:$AC$750,0))) -> 1036850 | I25: =IF(COUNTIFS(BankQuarter!$B$5:$B$750,A25,BankQuarter!$D$5:$D$750,WF_END_PERIOD)=0,"",INDEX(BankQuarter!$F$5:$F$750,MATCH(A25&"|"&WF_END_PERIOD,BankQuarter!$AC$5:$AC$750,0))) -> 1085692 | J25: =IF(COUNTIFS(BankQuarter!$B$5:$B$750,A25,BankQuarter!$D$5:$D$750,WF_START_PERIOD)=0,"",INDEX(BankQuarter!$A$5:$A$750,MATCH(A25&"|"&WF_START_PERIOD,BankQuarter!$AC$5:$AC$750,0))) -> 483 | K25: =IF(COUNTIFS(BankQuarter!$B$5:$B$750,A25,BankQuarter!$D$5:$D$750,WF_END_PERIOD)=0,"",INDEX(BankQuarter!$A$5:$A$750,MATCH(A25&"|"&WF_END_PERIOD,BankQuarter!$AC$5:$AC$750,0))) -> 697 | L25: =IF(COUNTIFS(BankQuarter!$B$5:$B$750,A25,BankQuarter!$D$5:$D$750,WF_START_PERIOD)=0,"",INDEX(BankQuarter!$S$5:$S$750,MATCH(A25&"|"&WF_START_PERIOD,BankQuarter!$AC$5:$AC$750,0))) -> 0.14621208 | M25: =IF(COUNTIFS(BankQuarter!$B$5:$B$750,A25,BankQuarter!$D$5:$D$750,WF_END_PERIOD)=0,"",INDEX(BankQuarter!$S$5:$S$750,MATCH(A25&"|"&WF_END_PERIOD,BankQuarter!$AC$5:$AC$750,0))) -> 0.12821316
A26: 13063 | B26: =IF(COUNTIFS(BankQuarter!$B$5:$B$750,A26,BankQuarter!$D$5:$D$750,WF_END_PERIOD)>0,INDEX(BankQuarter!$C$5:$C$750,MATCH(A26&"|"&WF_END_PERIOD,BankQuarter!$AC$5:$AC$750,0)),IF(COUNTIFS(BankQuarter!$B$5:$B$750,A26,BankQuarter!$D$5:$D$750,WF_START_PERIOD)>0,INDEX(BankQuarter!$C$5:$C$750,MATCH(A26&"|"&WF_START_PERIOD,BankQuarter!$AC$5:$AC$750,0)),"")) -> KENNEBUNK SAVINGS BANK | C26: =IF(COUNTIFS(BankQuarter!$B$5:$B$750,A26,BankQuarter!$D$5:$D$750,WF_START_PERIOD)=0,"",INDEX(BankQuarter!$E$5:$E$750,MATCH(A26&"|"&WF_START_PERIOD,BankQuarter!$AC$5:$AC$750,0))) -> ME | D26: =IF(COUNTIFS(BankQuarter!$B$5:$B$750,A26,BankQuarter!$D$5:$D$750,WF_END_PERIOD)=0,"",INDEX(BankQuarter!$E$5:$E$750,MATCH(A26&"|"&WF_END_PERIOD,BankQuarter!$AC$5:$AC$750,0))) -> ME | E26: =COUNTIFS(BankQuarter!$B$5:$B$750,A26,BankQuarter!$D$5:$D$750,WF_START_PERIOD,BankQuarter!$R$5:$R$750,TRUE())>0 -> TRUE | F26: =COUNTIFS(BankQuarter!$B$5:$B$750,A26,BankQuarter!$D$5:$D$750,WF_END_PERIOD,BankQuarter!$R$5:$R$750,TRUE())>0 -> TRUE | G26: =IF(AND(E26,F26),IF(C26=D26,"Common","State move "&C26&"→"&D26),IF(AND(E26,NOT(F26)),"Exiting ALL",IF(AND(NOT(E26),F26),"Entering ALL","Neither valid"))) -> Common | H26: =IF(COUNTIFS(BankQuarter!$B$5:$B$750,A26,BankQuarter!$D$5:$D$750,WF_START_PERIOD)=0,"",INDEX(BankQuarter!$F$5:$F$750,MATCH(A26&"|"&WF_START_PERIOD,BankQuarter!$AC$5:$AC$750,0))) -> 1848882 | I26: =IF(COUNTIFS(BankQuarter!$B$5:$B$750,A26,BankQuarter!$D$5:$D$750,WF_END_PERIOD)=0,"",INDEX(BankQuarter!$F$5:$F$750,MATCH(A26&"|"&WF_END_PERIOD,BankQuarter!$AC$5:$AC$750,0))) -> 1933479 | J26: =IF(COUNTIFS(BankQuarter!$B$5:$B$750,A26,BankQuarter!$D$5:$D$750,WF_START_PERIOD)=0,"",INDEX(BankQuarter!$A$5:$A$750,MATCH(A26&"|"&WF_START_PERIOD,BankQuarter!$AC$5:$AC$750,0))) -> 484 | K26: =IF(COUNTIFS(BankQuarter!$B$5:$B$750,A26,BankQuarter!$D$5:$D$750,WF_END_PERIOD)=0,"",INDEX(BankQuarter!$A$5:$A$750,MATCH(A26&"|"&WF_END_PERIOD,BankQuarter!$AC$5:$AC$750,0))) -> 698 | L26: =IF(COUNTIFS(BankQuarter!$B$5:$B$750,A26,BankQuarter!$D$5:$D$750,WF_START_PERIOD)=0,"",INDEX(BankQuarter!$S$5:$S$750,MATCH(A26&"|"&WF_START_PERIOD,BankQuarter!$AC$5:$AC$750,0))) -> 0.037914805 | M26: =IF(COUNTIFS(BankQuarter!$B$5:$B$750,A26,BankQuarter!$D$5:$D$750,WF_END_PERIOD)=0,"",INDEX(BankQuarter!$S$5:$S$750,MATCH(A26&"|"&WF_END_PERIOD,BankQuarter!$AC$5:$AC$750,0))) -> 0.12650771
A27: 14134 | B27: =IF(COUNTIFS(BankQuarter!$B$5:$B$750,A27,BankQuarter!$D$5:$D$750,WF_END_PERIOD)>0,INDEX(BankQuarter!$C$5:$C$750,MATCH(A27&"|"&WF_END_PERIOD,BankQuarter!$AC$5:$AC$750,0)),IF(COUNTIFS(BankQuarter!$B$5:$B$750,A27,BankQuarter!$D$5:$D$750,WF_START_PERIOD)>0,INDEX(BankQuarter!$C$5:$C$750,MATCH(A27&"|"&WF_START_PERIOD,BankQuarter!$AC$5:$AC$750,0)),"")) -> PASSUMPSIC SAVINGS BANK | C27: =IF(COUNTIFS(BankQuarter!$B$5:$B$750,A27,BankQuarter!$D$5:$D$750,WF_START_PERIOD)=0,"",INDEX(BankQuarter!$E$5:$E$750,MATCH(A27&"|"&WF_START_PERIOD,BankQuarter!$AC$5:$AC$750,0))) -> VT | D27: =IF(COUNTIFS(BankQuarter!$B$5:$B$750,A27,BankQuarter!$D$5:$D$750,WF_END_PERIOD)=0,"",INDEX(BankQuarter!$E$5:$E$750,MATCH(A27&"|"&WF_END_PERIOD,BankQuarter!$AC$5:$AC$750,0))) -> VT | E27: =COUNTIFS(BankQuarter!$B$5:$B$750,A27,BankQuarter!$D$5:$D$750,WF_START_PERIOD,BankQuarter!$R$5:$R$750,TRUE())>0 -> TRUE | F27: =COUNTIFS(BankQuarter!$B$5:$B$750,A27,BankQuarter!$D$5:$D$750,WF_END_PERIOD,BankQuarter!$R$5:$R$750,TRUE())>0 -> TRUE | G27: =IF(AND(E27,F27),IF(C27=D27,"Common","State move "&C27&"→"&D27),IF(AND(E27,NOT(F27)),"Exiting ALL",IF(AND(NOT(E27),F27),"Entering ALL","Neither valid"))) -> Common | H27: =IF(COUNTIFS(BankQuarter!$B$5:$B$750,A27,BankQuarter!$D$5:$D$750,WF_START_PERIOD)=0,"",INDEX(BankQuarter!$F$5:$F$750,MATCH(A27&"|"&WF_START_PERIOD,BankQuarter!$AC$5:$AC$750,0))) -> 842999 | I27: =IF(COUNTIFS(BankQuarter!$B$5:$B$750,A27,BankQuarter!$D$5:$D$750,WF_END_PERIOD)=0,"",INDEX(BankQuarter!$F$5:$F$750,MATCH(A27&"|"&WF_END_PERIOD,BankQuarter!$AC$5:$AC$750,0))) -> 882477 | J27: =IF(COUNTIFS(BankQuarter!$B$5:$B$750,A27,BankQuarter!$D$5:$D$750,WF_START_PERIOD)=0,"",INDEX(BankQuarter!$A$5:$A$750,MATCH(A27&"|"&WF_START_PERIOD,BankQuarter!$AC$5:$AC$750,0))) -> 485 | K27: =IF(COUNTIFS(BankQuarter!$B$5:$B$750,A27,BankQuarter!$D$5:$D$750,WF_END_PERIOD)=0,"",INDEX(BankQuarter!$A$5:$A$750,MATCH(A27&"|"&WF_END_PERIOD,BankQuarter!$AC$5:$AC$750,0))) -> 699 | L27: =IF(COUNTIFS(BankQuarter!$B$5:$B$750,A27,BankQuarter!$D$5:$D$750,WF_START_PERIOD)=0,"",INDEX(BankQuarter!$S$5:$S$750,MATCH(A27&"|"&WF_START_PERIOD,BankQuarter!$AC$5:$AC$750,0))) -> 1.1729551 | M27: =IF(COUNTIFS(BankQuarter!$B$5:$B$750,A27,BankQuarter!$D$5:$D$750,WF_END_PERIOD)=0,"",INDEX(BankQuarter!$S$5:$S$750,MATCH(A27&"|"&WF_END_PERIOD,BankQuarter!$AC$5:$AC$750,0))) -> 0.30743011
A28: 14136 | B28: =IF(COUNTIFS(BankQuarter!$B$5:$B$750,A28,BankQuarter!$D$5:$D$750,WF_END_PERIOD)>0,INDEX(BankQuarter!$C$5:$C$750,MATCH(A28&"|"&WF_END_PERIOD,BankQuarter!$AC$5:$AC$750,0)),IF(COUNTIFS(BankQuarter!$B$5:$B$750,A28,BankQuarter!$D$5:$D$750,WF_START_PERIOD)>0,INDEX(BankQuarter!$C$5:$C$750,MATCH(A28&"|"&WF_START_PERIOD,BankQuarter!$AC$5:$AC$750,0)),"")) -> WELLS RIVER SAVINGS BANK | C28: =IF(COUNTIFS(BankQuarter!$B$5:$B$750,A28,BankQuarter!$D$5:$D$750,WF_START_PERIOD)=0,"",INDEX(BankQuarter!$E$5:$E$750,MATCH(A28&"|"&WF_START_PERIOD,BankQuarter!$AC$5:$AC$750,0))) -> VT | D28: =IF(COUNTIFS(BankQuarter!$B$5:$B$750,A28,BankQuarter!$D$5:$D$750,WF_END_PERIOD)=0,"",INDEX(BankQuarter!$E$5:$E$750,MATCH(A28&"|"&WF_END_PERIOD,BankQuarter!$AC$5:$AC$750,0))) -> VT | E28: =COUNTIFS(BankQuarter!$B$5:$B$750,A28,BankQuarter!$D$5:$D$750,WF_START_PERIOD,BankQuarter!$R$5:$R$750,TRUE())>0 -> TRUE | F28: =COUNTIFS(BankQuarter!$B$5:$B$750,A28,BankQuarter!$D$5:$D$750,WF_END_PERIOD,BankQuarter!$R$5:$R$750,TRUE())>0 -> TRUE | G28: =IF(AND(E28,F28),IF(C28=D28,"Common","State move "&C28&"→"&D28),IF(AND(E28,NOT(F28)),"Exiting ALL",IF(AND(NOT(E28),F28),"Entering ALL","Neither valid"))) -> Common | H28: =IF(COUNTIFS(BankQuarter!$B$5:$B$750,A28,BankQuarter!$D$5:$D$750,WF_START_PERIOD)=0,"",INDEX(BankQuarter!$F$5:$F$750,MATCH(A28&"|"&WF_START_PERIOD,BankQuarter!$AC$5:$AC$750,0))) -> 234689 | I28: =IF(COUNTIFS(BankQuarter!$B$5:$B$750,A28,BankQuarter!$D$5:$D$750,WF_END_PERIOD)=0,"",INDEX(BankQuarter!$F$5:$F$750,MATCH(A28&"|"&WF_END_PERIOD,BankQuarter!$AC$5:$AC$750,0))) -> 247991 | J28: =IF(COUNTIFS(BankQuarter!$B$5:$B$750,A28,BankQuarter!$D$5:$D$750,WF_START_PERIOD)=0,"",INDEX(BankQuarter!$A$5:$A$750,MATCH(A28&"|"&WF_START_PERIOD,BankQuarter!$AC$5:$AC$750,0))) -> 486 | K28: =IF(COUNTIFS(BankQuarter!$B$5:$B$750,A28,BankQuarter!$D$5:$D$750,WF_END_PERIOD)=0,"",INDEX(BankQuarter!$A$5:$A$750,MATCH(A28&"|"&WF_END_PERIOD,BankQuarter!$AC$5:$AC$750,0))) -> 700 | L28: =IF(COUNTIFS(BankQuarter!$B$5:$B$750,A28,BankQuarter!$D$5:$D$750,WF_START_PERIOD)=0,"",INDEX(BankQuarter!$S$5:$S$750,MATCH(A28&"|"&WF_START_PERIOD,BankQuarter!$AC$5:$AC$750,0))) -> 0.32127624 | M28: =IF(COUNTIFS(BankQuarter!$B$5:$B$750,A28,BankQuarter!$D$5:$D$750,WF_END_PERIOD)=0,"",INDEX(BankQuarter!$S$5:$S$750,MATCH(A28&"|"&WF_END_PERIOD,BankQuarter!$AC$5:$AC$750,0))) -> 0.43428995
A29: 14140 | B29: =IF(COUNTIFS(BankQuarter!$B$5:$B$750,A29,BankQuarter!$D$5:$D$750,WF_END_PERIOD)>0,INDEX(BankQuarter!$C$5:$C$750,MATCH(A29&"|"&WF_END_PERIOD,BankQuarter!$AC$5:$AC$750,0)),IF(COUNTIFS(BankQuarter!$B$5:$B$750,A29,BankQuarter!$D$5:$D$750,WF_START_PERIOD)>0,INDEX(BankQuarter!$C$5:$C$750,MATCH(A29&"|"&WF_START_PERIOD,BankQuarter!$AC$5:$AC$750,0)),"")) -> NORTHFIELD SAVINGS BANK | C29: =IF(COUNTIFS(BankQuarter!$B$5:$B$750,A29,BankQuarter!$D$5:$D$750,WF_START_PERIOD)=0,"",INDEX(BankQuarter!$E$5:$E$750,MATCH(A29&"|"&WF_START_PERIOD,BankQuarter!$AC$5:$AC$750,0))) -> VT | D29: =IF(COUNTIFS(BankQuarter!$B$5:$B$750,A29,BankQuarter!$D$5:$D$750,WF_END_PERIOD)=0,"",INDEX(BankQuarter!$E$5:$E$750,MATCH(A29&"|"&WF_END_PERIOD,BankQuarter!$AC$5:$AC$750,0))) -> VT | E29: =COUNTIFS(BankQuarter!$B$5:$B$750,A29,BankQuarter!$D$5:$D$750,WF_START_PERIOD,BankQuarter!$R$5:$R$750,TRUE())>0 -> TRUE | F29: =COUNTIFS(BankQuarter!$B$5:$B$750,A29,BankQuarter!$D$5:$D$750,WF_END_PERIOD,BankQuarter!$R$5:$R$750,TRUE())>0 -> TRUE | G29: =IF(AND(E29,F29),IF(C29=D29,"Common","State move "&C29&"→"&D29),IF(AND(E29,NOT(F29)),"Exiting ALL",IF(AND(NOT(E29),F29),"Entering ALL","Neither valid"))) -> Common | H29: =IF(COUNTIFS(BankQuarter!$B$5:$B$750,A29,BankQuarter!$D$5:$D$750,WF_START_PERIOD)=0,"",INDEX(BankQuarter!$F$5:$F$750,MATCH(A29&"|"&WF_START_PERIOD,BankQuarter!$AC$5:$AC$750,0))) -> 1498757 | I29: =IF(COUNTIFS(BankQuarter!$B$5:$B$750,A29,BankQuarter!$D$5:$D$750,WF_END_PERIOD)=0,"",INDEX(BankQuarter!$F$5:$F$750,MATCH(A29&"|"&WF_END_PERIOD,BankQuarter!$AC$5:$AC$750,0))) -> 1560737 | J29: =IF(COUNTIFS(BankQuarter!$B$5:$B$750,A29,BankQuarter!$D$5:$D$750,WF_START_PERIOD)=0,"",INDEX(BankQuarter!$A$5:$A$750,MATCH(A29&"|"&WF_START_PERIOD,BankQuarter!$AC$5:$AC$750,0))) -> 487 | K29: =IF(COUNTIFS(BankQuarter!$B$5:$B$750,A29,BankQuarter!$D$5:$D$750,WF_END_PERIOD)=0,"",INDEX(BankQuarter!$A$5:$A$750,MATCH(A29&"|"&WF_END_PERIOD,BankQuarter!$AC$5:$AC$750,0))) -> 701 | L29: =IF(COUNTIFS(BankQuarter!$B$5:$B$750,A29,BankQuarter!$D$5:$D$750,WF_START_PERIOD)=0,"",INDEX(BankQuarter!$S$5:$S$750,MATCH(A29&"|"&WF_START_PERIOD,BankQuarter!$AC$5:$AC$750,0))) -> 0.13651312 | M29: =IF(COUNTIFS(BankQuarter!$B$5:$B$750,A29,BankQuarter!$D$5:$D$750,WF_END_PERIOD)=0,"",INDEX(BankQuarter!$S$5:$S$750,MATCH(A29&"|"&WF_END_PERIOD,BankQuarter!$AC$5:$AC$750,0))) -> 0.47644158
A30: 14158 | B30: =IF(COUNTIFS(BankQuarter!$B$5:$B$750,A30,BankQuarter!$D$5:$D$750,WF_END_PERIOD)>0,INDEX(BankQuarter!$C$5:$C$750,MATCH(A30&"|"&WF_END_PERIOD,BankQuarter!$AC$5:$AC$750,0)),IF(COUNTIFS(BankQuarter!$B$5:$B$750,A30,BankQuarter!$D$5:$D$750,WF_START_PERIOD)>0,INDEX(BankQuarter!$C$5:$C$750,MATCH(A30&"|"&WF_START_PERIOD,BankQuarter!$AC$5:$AC$750,0)),"")) -> UNION BANK | C30: =IF(COUNTIFS(BankQuarter!$B$5:$B$750,A30,BankQuarter!$D$5:$D$750,WF_START_PERIOD)=0,"",INDEX(BankQuarter!$E$5:$E$750,MATCH(A30&"|"&WF_START_PERIOD,BankQuarter!$AC$5:$AC$750,0))) -> VT | D30: =IF(COUNTIFS(BankQuarter!$B$5:$B$750,A30,BankQuarter!$D$5:$D$750,WF_END_PERIOD)=0,"",INDEX(BankQuarter!$E$5:$E$750,MATCH(A30&"|"&WF_END_PERIOD,BankQuarter!$AC$5:$AC$750,0))) -> VT | E30: =COUNTIFS(BankQuarter!$B$5:$B$750,A30,BankQuarter!$D$5:$D$750,WF_START_PERIOD,BankQuarter!$R$5:$R$750,TRUE())>0 -> TRUE | F30: =COUNTIFS(BankQuarter!$B$5:$B$750,A30,BankQuarter!$D$5:$D$750,WF_END_PERIOD,BankQuarter!$R$5:$R$750,TRUE())>0 -> TRUE | G30: =IF(AND(E30,F30),IF(C30=D30,"Common","State move "&C30&"→"&D30),IF(AND(E30,NOT(F30)),"Exiting ALL",IF(AND(NOT(E30),F30),"Entering ALL","Neither valid"))) -> Common | H30: =IF(COUNTIFS(BankQuarter!$B$5:$B$750,A30,BankQuarter!$D$5:$D$750,WF_START_PERIOD)=0,"",INDEX(BankQuarter!$F$5:$F$750,MATCH(A30&"|"&WF_START_PERIOD,BankQuarter!$AC$5:$AC$750,0))) -> 1397831 | I30: =IF(COUNTIFS(BankQuarter!$B$5:$B$750,A30,BankQuarter!$D$5:$D$750,WF_END_PERIOD)=0,"",INDEX(BankQuarter!$F$5:$F$750,MATCH(A30&"|"&WF_END_PERIOD,BankQuarter!$AC$5:$AC$750,0))) -> 1479452 | J30: =IF(COUNTIFS(BankQuarter!$B$5:$B$750,A30,BankQuarter!$D$5:$D$750,WF_START_PERIOD)=0,"",INDEX(BankQuarter!$A$5:$A$750,MATCH(A30&"|"&WF_START_PERIOD,BankQuarter!$AC$5:$AC$750,0))) -> 488 | K30: =IF(COUNTIFS(BankQuarter!$B$5:$B$750,A30,BankQuarter!$D$5:$D$750,WF_END_PERIOD)=0,"",INDEX(BankQuarter!$A$5:$A$750,MATCH(A30&"|"&WF_END_PERIOD,BankQuarter!$AC$5:$AC$750,0))) -> 702 | L30: =IF(COUNTIFS(BankQuarter!$B$5:$B$750,A30,BankQuarter!$D$5:$D$750,WF_START_PERIOD)=0,"",INDEX(BankQuarter!$S$5:$S$750,MATCH(A30&"|"&WF_START_PERIOD,BankQuarter!$AC$5:$AC$750,0))) -> 0.13792798 | M30: =IF(COUNTIFS(BankQuarter!$B$5:$B$750,A30,BankQuarter!$D$5:$D$750,WF_END_PERIOD)=0,"",INDEX(BankQuarter!$S$5:$S$750,MATCH(A30&"|"&WF_END_PERIOD,BankQuarter!$AC$5:$AC$750,0))) -> 1.0315306
... A72: 59298 | B72: =IF(COUNTIFS(BankQuarter!$B$5:$B$750,A72,BankQuarter!$D$5:$D$750,WF_END_PERIOD)>0,INDEX(BankQuarter!$C$5:$C$750,MATCH(A72&"|"&WF_END_PERIOD,BankQuarter!$AC$5:$AC$750,0)),IF(COUNTIFS(BankQuarter!$B$5:$B$750,A72,BankQuarter!$D$5:$D$750,WF_START_PERIOD)>0,INDEX(BankQuarter!$C$5:$C$750,MATCH(A72&"|"&WF_START_PERIOD,BankQuarter!$AC$5:$AC$750,0)),"")) -> BANK OF BURLINGTON | C72: =IF(COUNTIFS(BankQuarter!$B$5:$B$750,A72,BankQuarter!$D$5:$D$750,WF_START_PERIOD)=0,"",INDEX(BankQuarter!$E$5:$E$750,MATCH(A72&"|"&WF_START_PERIOD,BankQuarter!$AC$5:$AC$750,0))) -> VT | D72: =IF(COUNTIFS(BankQuarter!$B$5:$B$750,A72,BankQuarter!$D$5:$D$750,WF_END_PERIOD)=0,"",INDEX(BankQuarter!$E$5:$E$750,MATCH(A72&"|"&WF_END_PERIOD,BankQuarter!$AC$5:$AC$750,0))) -> VT | E72: =COUNTIFS(BankQuarter!$B$5:$B$750,A72,BankQuarter!$D$5:$D$750,WF_START_PERIOD,BankQuarter!$R$5:$R$750,TRUE())>0 -> TRUE | F72: =COUNTIFS(BankQuarter!$B$5:$B$750,A72,BankQuarter!$D$5:$D$750,WF_END_PERIOD,BankQuarter!$R$5:$R$750,TRUE())>0 -> TRUE | G72: =IF(AND(E72,F72),IF(C72=D72,"Common","State move "&C72&"→"&D72),IF(AND(E72,NOT(F72)),"Exiting ALL",IF(AND(NOT(E72),F72),"Entering ALL","Neither valid"))) -> Common | H72: =IF(COUNTIFS(BankQuarter!$B$5:$B$750,A72,BankQuarter!$D$5:$D$750,WF_START_PERIOD)=0,"",INDEX(BankQuarter!$F$5:$F$750,MATCH(A72&"|"&WF_START_PERIOD,BankQuarter!$AC$5:$AC$750,0))) -> 218470 | I72: =IF(COUNTIFS(BankQuarter!$B$5:$B$750,A72,BankQuarter!$D$5:$D$750,WF_END_PERIOD)=0,"",INDEX(BankQuarter!$F$5:$F$750,MATCH(A72&"|"&WF_END_PERIOD,BankQuarter!$AC$5:$AC$750,0))) -> 269483 | J72: =IF(COUNTIFS(BankQuarter!$B$5:$B$750,A72,BankQuarter!$D$5:$D$750,WF_START_PERIOD)=0,"",INDEX(BankQuarter!$A$5:$A$750,MATCH(A72&"|"&WF_START_PERIOD,BankQuarter!$AC$5:$AC$750,0))) -> 532 | K72: =IF(COUNTIFS(BankQuarter!$B$5:$B$750,A72,BankQuarter!$D$5:$D$750,WF_END_PERIOD)=0,"",INDEX(BankQuarter!$A$5:$A$750,MATCH(A72&"|"&WF_END_PERIOD,BankQuarter!$AC$5:$AC$750,0))) -> 744 | L72: =IF(COUNTIFS(BankQuarter!$B$5:$B$750,A72,BankQuarter!$D$5:$D$750,WF_START_PERIOD)=0,"",INDEX(BankQuarter!$S$5:$S$750,MATCH(A72&"|"&WF_START_PERIOD,BankQuarter!$AC$5:$AC$750,0))) -> 0 | M72: =IF(COUNTIFS(BankQuarter!$B$5:$B$750,A72,BankQuarter!$D$5:$D$750,WF_END_PERIOD)=0,"",INDEX(BankQuarter!$S$5:$S$750,MATCH(A72&"|"&WF_END_PERIOD,BankQuarter!$AC$5:$AC$750,0))) -> 0

Sheet Priority
A1: Review Priority Allocation
A2: First one per state in VT, NH, ME order; then highest remaining proxy. Ties use ascending numeric CERT. Invalid model clears the list.
A4: Order | B4: CERT | C4: State | D4: Bank name | E4: End source row | F4: Start source row | G4: End ASSET ($000) | H4: End P9ASSET ($000) | I4: End NAASSET ($000) | J4: End proxy % | K4: Start proxy % | L4: Change pp | M4: RE loans / gross loans % | N4: Equity / assets % | O4: End ROA raw % | P4: End RBCRWAJ raw % | Q4: Start ASSET ($000) | R4: Start P9ASSET ($000) | S4: Start NAASSET ($000) | T4: Start ROA raw % | U4: Why review | V4: Specific evidence request
A5: 1 | B5: =IF(AND(WF_MODEL_VALID,A5<=WF_REVIEW_SLOTS),SUMIFS(BankQuarter!$B$5:$B$750,BankQuarter!$D$5:$D$750,WF_END_PERIOD,BankQuarter!$E$5:$E$750,"VT",BankQuarter!$R$5:$R$750,TRUE(),BankQuarter!$Z$5:$Z$750,1),"") -> 6280 | C5: =IF($B5="","",INDEX(BankQuarter!$E$5:$E$750,MATCH($B5&"|"&WF_END_PERIOD,BankQuarter!$AC$5:$AC$750,0))) -> VT | D5: =IF($B5="","",INDEX(BankQuarter!$C$5:$C$750,MATCH($B5&"|"&WF_END_PERIOD,BankQuarter!$AC$5:$AC$750,0))) -> THE FIRST NATIONAL BANK OF ORWELL | E5: =IF($B5="","",INDEX(BankQuarter!$A$5:$A$750,MATCH($B5&"|"&WF_END_PERIOD,BankQuarter!$AC$5:$AC$750,0))) -> 747 | F5: =IF($B5="","",IF(COUNTIFS(BankQuarter!$B$5:$B$750,$B5,BankQuarter!$D$5:$D$750,WF_START_PERIOD)=0,"",INDEX(BankQuarter!$A$5:$A$750,MATCH($B5&"|"&WF_START_PERIOD,BankQuarter!$AC$5:$AC$750,0)))) -> 535 | G5: =IF($B5="","",INDEX(BankQuarter!$F$5:$F$750,MATCH($B5&"|"&WF_END_PERIOD,BankQuarter!$AC$5:$AC$750,0))) -> 87770 | H5: =IF($B5="","",INDEX(BankQuarter!$G$5:$G$750,MATCH($B5&"|"&WF_END_PERIOD,BankQuarter!$AC$5:$AC$750,0))) -> 0 | I5: =IF($B5="","",INDEX(BankQuarter!$H$5:$H$750,MATCH($B5&"|"&WF_END_PERIOD,BankQuarter!$AC$5:$AC$750,0))) -> 1455 | J5: =IF($B5="","",INDEX(BankQuarter!$S$5:$S$750,MATCH($B5&"|"&WF_END_PERIOD,BankQuarter!$AC$5:$AC$750,0))) -> 1.6577418 | K5: =IF($B5="","",IF(COUNTIFS(BankQuarter!$B$5:$B$750,$B5,BankQuarter!$D$5:$D$750,WF_START_PERIOD,BankQuarter!$R$5:$R$750,TRUE())=0,"",INDEX(BankQuarter!$S$5:$S$750,MATCH($B5&"|"&WF_START_PERIOD,BankQuarter!$AC$5:$AC$750,0)))) -> 1.4840337 | L5: =IF(OR(J5="",K5=""),"",J5-K5) -> 0.17370811 | M5: =IF($B5="","",INDEX(BankQuarter!$P$5:$P$750,MATCH($B5&"|"&WF_END_PERIOD,BankQuarter!$AC$5:$AC$750,0))) -> 88.846785 | N5: =IF($B5="","",INDEX(BankQuarter!$Q$5:$Q$750,MATCH($B5&"|"&WF_END_PERIOD,BankQuarter!$AC$5:$AC$750,0))) -> 11.335308 | O5: =IF($B5="","",INDEX(BankQuarter!$N$5:$N$750,MATCH($B5&"|"&WF_END_PERIOD,BankQuarter!$AC$5:$AC$750,0))) -> 1.3665403 | P5: =IF($B5="","",INDEX(BankQuarter!$O$5:$O$750,MATCH($B5&"|"&WF_END_PERIOD,BankQuarter!$AC$5:$AC$750,0))) -> 0 | Q5: =IF($B5="","",IF(COUNTIFS(BankQuarter!$B$5:$B$750,$B5,BankQuarter!$D$5:$D$750,WF_START_PERIOD)=0,"",INDEX(BankQuarter!$F$5:$F$750,MATCH($B5&"|"&WF_START_PERIOD,BankQuarter!$AC$5:$AC$750,0)))) -> 81265 | R5: =IF($B5="","",IF(COUNTIFS(BankQuarter!$B$5:$B$750,$B5,BankQuarter!$D$5:$D$750,WF_START_PERIOD)=0,"",INDEX(BankQuarter!$G$5:$G$750,MATCH($B5&"|"&WF_START_PERIOD,BankQuarter!$AC$5:$AC$750,0)))) -> 0 | S5: =IF($B5="","",IF(COUNTIFS(BankQuarter!$B$5:$B$750,$B5,BankQuarter!$D$5:$D$750,WF_START_PERIOD)=0,"",INDEX(BankQuarter!$H$5:$H$750,MATCH($B5&"|"&WF_START_PERIOD,BankQuarter!$AC$5:$AC$750,0)))) -> 1206 | T5: =IF($B5="","",IF(COUNTIFS(BankQuarter!$B$5:$B$750,$B5,BankQuarter!$D$5:$D$750,WF_START_PERIOD)=0,"",INDEX(BankQuarter!$N$5:$N$750,MATCH($B5&"|"&WF_START_PERIOD,BankQuarter!$AC$5:$AC$750,0)))) -> 1.4362929 | U5: =IF(B5="","","End proxy "&TEXT(J5,"0.0000")&"%; "&IF(K5="","no valid start comparison","change "&TEXT(L5,"0.0000")&" pp")&". Screening signal only; verify loan-level causes.") -> End proxy 1.6577%; change 0.1737 pp. Screening signal only; verify loan-level causes. | V5: =IF(B5="","","Obtain past-due/nonaccrual loan tape, aging, payment history, accrual-status support, classifications/watch list and grade migration"&IF(M5>=75,"; CRE/RE concentration report, largest exposures, appraisals and stress results","")&IF(O5<0.5,"; earnings bridge, charge-offs, provisions and ACL support","")&IF(P5=0,"; RBCRWAJ is reported as 0—verify applicability/reporting basis and obtain capital schedules","; capital schedules and risk-weight support")) -> Obtain past-due/nonaccrual loan tape, aging, payment history, accrual-status support, classifications/watch list and grade migration; CRE/RE concentration report, largest exposures, appraisals and stress results; RBCRWAJ is reported as 0—verify applicability/reporting basis and obtain capital schedules
A6: 2 | B6: =IF(AND(WF_MODEL_VALID,A6<=WF_REVIEW_SLOTS),SUMIFS(BankQuarter!$B$5:$B$750,BankQuarter!$D$5:$D$750,WF_END_PERIOD,BankQuarter!$E$5:$E$750,"NH",BankQuarter!$R$5:$R$750,TRUE(),BankQuarter!$Z$5:$Z$750,1),"") -> 59289 | C6: =IF($B6="","",INDEX(BankQuarter!$E$5:$E$750,MATCH($B6&"|"&WF_END_PERIOD,BankQuarter!$AC$5:$AC$750,0))) -> NH | D6: =IF($B6="","",INDEX(BankQuarter!$C$5:$C$750,MATCH($B6&"|"&WF_END_PERIOD,BankQuarter!$AC$5:$AC$750,0))) -> WALDEN MUTUAL BANK | E6: =IF($B6="","",INDEX(BankQuarter!$A$5:$A$750,MATCH($B6&"|"&WF_END_PERIOD,BankQuarter!$AC$5:$AC$750,0))) -> 743 | F6: =IF($B6="","",IF(COUNTIFS(BankQuarter!$B$5:$B$750,$B6,BankQuarter!$D$5:$D$750,WF_START_PERIOD)=0,"",INDEX(BankQuarter!$A$5:$A$750,MATCH($B6&"|"&WF_START_PERIOD,BankQuarter!$AC$5:$AC$750,0)))) -> 531 | G6: =IF($B6="","",INDEX(BankQuarter!$F$5:$F$750,MATCH($B6&"|"&WF_END_PERIOD,BankQuarter!$AC$5:$AC$750,0))) -> 145991 | H6: =IF($B6="","",INDEX(BankQuarter!$G$5:$G$750,MATCH($B6&"|"&WF_END_PERIOD,BankQuarter!$AC$5:$AC$750,0))) -> 0 | I6: =IF($B6="","",INDEX(BankQuarter!$H$5:$H$750,MATCH($B6&"|"&WF_END_PERIOD,BankQuarter!$AC$5:$AC$750,0))) -> 2835 | J6: =IF($B6="","",INDEX(BankQuarter!$S$5:$S$750,MATCH($B6&"|"&WF_END_PERIOD,BankQuarter!$AC$5:$AC$750,0))) -> 1.9419005 | K6: =IF($B6="","",IF(COUNTIFS(BankQuarter!$B$5:$B$750,$B6,BankQuarter!$D$5:$D$750,WF_START_PERIOD,BankQuarter!$R$5:$R$750,TRUE())=0,"",INDEX(BankQuarter!$S$5:$S$750,MATCH($B6&"|"&WF_START_PERIOD,BankQuarter!$AC$5:$AC$750,0)))) -> 0.30778236 | L6: =IF(OR(J6="",K6=""),"",J6-K6) -> 1.6341182 | M6: =IF($B6="","",INDEX(BankQuarter!$P$5:$P$750,MATCH($B6&"|"&WF_END_PERIOD,BankQuarter!$AC$5:$AC$750,0))) -> 36.175662 | N6: =IF($B6="","",INDEX(BankQuarter!$Q$5:$Q$750,MATCH($B6&"|"&WF_END_PERIOD,BankQuarter!$AC$5:$AC$750,0))) -> 10.752718 | O6: =IF($B6="","",INDEX(BankQuarter!$N$5:$N$750,MATCH($B6&"|"&WF_END_PERIOD,BankQuarter!$AC$5:$AC$750,0))) -> -0.2399886 | P6: =IF($B6="","",INDEX(BankQuarter!$O$5:$O$750,MATCH($B6&"|"&WF_END_PERIOD,BankQuarter!$AC$5:$AC$750,0))) -> 0 | Q6: =IF($B6="","",IF(COUNTIFS(BankQuarter!$B$5:$B$750,$B6,BankQuarter!$D$5:$D$750,WF_START_PERIOD)=0,"",INDEX(BankQuarter!$F$5:$F$750,MATCH($B6&"|"&WF_START_PERIOD,BankQuarter!$AC$5:$AC$750,0)))) -> 105919 | R6: =IF($B6="","",IF(COUNTIFS(BankQuarter!$B$5:$B$750,$B6,BankQuarter!$D$5:$D$750,WF_START_PERIOD)=0,"",INDEX(BankQuarter!$G$5:$G$750,MATCH($B6&"|"&WF_START_PERIOD,BankQuarter!$AC$5:$AC$750,0)))) -> 0 | S6: =IF($B6="","",IF(COUNTIFS(BankQuarter!$B$5:$B$750,$B6,BankQuarter!$D$5:$D$750,WF_START_PERIOD)=0,"",INDEX(BankQuarter!$H$5:$H$750,MATCH($B6&"|"&WF_START_PERIOD,BankQuarter!$AC$5:$AC$750,0)))) -> 326 | T6: =IF($B6="","",IF(COUNTIFS(BankQuarter!$B$5:$B$750,$B6,BankQuarter!$D$5:$D$750,WF_START_PERIOD)=0,"",INDEX(BankQuarter!$N$5:$N$750,MATCH($B6&"|"&WF_START_PERIOD,BankQuarter!$AC$5:$AC$750,0)))) -> -1.1303906 | U6: =IF(B6="","","End proxy "&TEXT(J6,"0.0000")&"%; "&IF(K6="","no valid start comparison","change "&TEXT(L6,"0.0000")&" pp")&". Screening signal only; verify loan-level causes.") -> End proxy 1.9419%; change 1.6341 pp. Screening signal only; verify loan-level causes. | V6: =IF(B6="","","Obtain past-due/nonaccrual loan tape, aging, payment history, accrual-status support, classifications/watch list and grade migration"&IF(M6>=75,"; CRE/RE concentration report, largest exposures, appraisals and stress results","")&IF(O6<0.5,"; earnings bridge, charge-offs, provisions and ACL support","")&IF(P6=0,"; RBCRWAJ is reported as 0—verify applicability/reporting basis and obtain capital schedules","; capital schedules and risk-weight support")) -> Obtain past-due/nonaccrual loan tape, aging, payment history, accrual-status support, classifications/watch list and grade migration; earnings bridge, charge-offs, provisions and ACL support; RBCRWAJ is reported as 0—verify applicability/reporting basis and obtain capital schedules
A7: 3 | B7: =IF(AND(WF_MODEL_VALID,A7<=WF_REVIEW_SLOTS),SUMIFS(BankQuarter!$B$5:$B$750,BankQuarter!$D$5:$D$750,WF_END_PERIOD,BankQuarter!$E$5:$E$750,"ME",BankQuarter!$R$5:$R$750,TRUE(),BankQuarter!$Z$5:$Z$750,1),"") -> 29636 | C7: =IF($B7="","",INDEX(BankQuarter!$E$5:$E$750,MATCH($B7&"|"&WF_END_PERIOD,BankQuarter!$AC$5:$AC$750,0))) -> ME | D7: =IF($B7="","",INDEX(BankQuarter!$C$5:$C$750,MATCH($B7&"|"&WF_END_PERIOD,BankQuarter!$AC$5:$AC$750,0))) -> FIRST FEDERAL SAVINGS AND LOAN ASSOCIATION OF BATH | E7: =IF($B7="","",INDEX(BankQuarter!$A$5:$A$750,MATCH($B7&"|"&WF_END_PERIOD,BankQuarter!$AC$5:$AC$750,0))) -> 732 | F7: =IF($B7="","",IF(COUNTIFS(BankQuarter!$B$5:$B$750,$B7,BankQuarter!$D$5:$D$750,WF_START_PERIOD)=0,"",INDEX(BankQuarter!$A$5:$A$750,MATCH($B7&"|"&WF_START_PERIOD,BankQuarter!$AC$5:$AC$750,0)))) -> 520 | G7: =IF($B7="","",INDEX(BankQuarter!$F$5:$F$750,MATCH($B7&"|"&WF_END_PERIOD,BankQuarter!$AC$5:$AC$750,0))) -> 185573 | H7: =IF($B7="","",INDEX(BankQuarter!$G$5:$G$750,MATCH($B7&"|"&WF_END_PERIOD,BankQuarter!$AC$5:$AC$750,0))) -> 0 | I7: =IF($B7="","",INDEX(BankQuarter!$H$5:$H$750,MATCH($B7&"|"&WF_END_PERIOD,BankQuarter!$AC$5:$AC$750,0))) -> 3102 | J7: =IF($B7="","",INDEX(BankQuarter!$S$5:$S$750,MATCH($B7&"|"&WF_END_PERIOD,BankQuarter!$AC$5:$AC$750,0))) -> 1.6715794 | K7: =IF($B7="","",IF(COUNTIFS(BankQuarter!$B$5:$B$750,$B7,BankQuarter!$D$5:$D$750,WF_START_PERIOD,BankQuarter!$R$5:$R$750,TRUE())=0,"",INDEX(BankQuarter!$S$5:$S$750,MATCH($B7&"|"&WF_START_PERIOD,BankQuarter!$AC$5:$AC$750,0)))) -> 1.5150759 | L7: =IF(OR(J7="",K7=""),"",J7-K7) -> 0.15650351 | M7: =IF($B7="","",INDEX(BankQuarter!$P$5:$P$750,MATCH($B7&"|"&WF_END_PERIOD,BankQuarter!$AC$5:$AC$750,0))) -> 97.763348 | N7: =IF($B7="","",INDEX(BankQuarter!$Q$5:$Q$750,MATCH($B7&"|"&WF_END_PERIOD,BankQuarter!$AC$5:$AC$750,0))) -> 14.897641 | O7: =IF($B7="","",INDEX(BankQuarter!$N$5:$N$750,MATCH($B7&"|"&WF_END_PERIOD,BankQuarter!$AC$5:$AC$750,0))) -> 0.23461911 | P7: =IF($B7="","",INDEX(BankQuarter!$O$5:$O$750,MATCH($B7&"|"&WF_END_PERIOD,BankQuarter!$AC$5:$AC$750,0))) -> 27.167214 | Q7: =IF($B7="","",IF(COUNTIFS(BankQuarter!$B$5:$B$750,$B7,BankQuarter!$D$5:$D$750,WF_START_PERIOD)=0,"",INDEX(BankQuarter!$F$5:$F$750,MATCH($B7&"|"&WF_START_PERIOD,BankQuarter!$AC$5:$AC$750,0)))) -> 180255 | R7: =IF($B7="","",IF(COUNTIFS(BankQuarter!$B$5:$B$750,$B7,BankQuarter!$D$5:$D$750,WF_START_PERIOD)=0,"",INDEX(BankQuarter!$G$5:$G$750,MATCH($B7&"|"&WF_START_PERIOD,BankQuarter!$AC$5:$AC$750,0)))) -> 0 | S7: =IF($B7="","",IF(COUNTIFS(BankQuarter!$B$5:$B$750,$B7,BankQuarter!$D$5:$D$750,WF_START_PERIOD)=0,"",INDEX(BankQuarter!$H$5:$H$750,MATCH($B7&"|"&WF_START_PERIOD,BankQuarter!$AC$5:$AC$750,0)))) -> 2731 | T7: =IF($B7="","",IF(COUNTIFS(BankQuarter!$B$5:$B$750,$B7,BankQuarter!$D$5:$D$750,WF_START_PERIOD)=0,"",INDEX(BankQuarter!$N$5:$N$750,MATCH($B7&"|"&WF_START_PERIOD,BankQuarter!$AC$5:$AC$750,0)))) -> 0.24776601 | U7: =IF(B7="","","End proxy "&TEXT(J7,"0.0000")&"%; "&IF(K7="","no valid start comparison","change "&TEXT(L7,"0.0000")&" pp")&". Screening signal only; verify loan-level causes.") -> End proxy 1.6716%; change 0.1565 pp. Screening signal only; verify loan-level causes. | V7: =IF(B7="","","Obtain past-due/nonaccrual loan tape, aging, payment history, accrual-status support, classifications/watch list and grade migration"&IF(M7>=75,"; CRE/RE concentration report, largest exposures, appraisals and stress results","")&IF(O7<0.5,"; earnings bridge, charge-offs, provisions and ACL support","")&IF(P7=0,"; RBCRWAJ is reported as 0—verify applicability/reporting basis and obtain capital schedules","; capital schedules and risk-weight support")) -> Obtain past-due/nonaccrual loan tape, aging, payment history, accrual-status support, classifications/watch list and grade migration; CRE/RE concentration report, largest exposures, appraisals and stress results; earnings bridge, charge-offs, provisions and ACL support; capital schedules and risk-weight support
A8: 4 | B8: =IF(AND(WF_MODEL_VALID,A8<=WF_REVIEW_SLOTS),SUMIFS(BankQuarter!$B$5:$B$750,BankQuarter!$D$5:$D$750,WF_END_PERIOD,BankQuarter!$R$5:$R$750,TRUE(),BankQuarter!$AA$5:$AA$750,1),"") -> 59086 | C8: =IF($B8="","",INDEX(BankQuarter!$E$5:$E$750,MATCH($B8&"|"&WF_END_PERIOD,BankQuarter!$AC$5:$AC$750,0))) -> NH | D8: =IF($B8="","",INDEX(BankQuarter!$C$5:$C$750,MATCH($B8&"|"&WF_END_PERIOD,BankQuarter!$AC$5:$AC$750,0))) -> PRIMARY BANK | E8: =IF($B8="","",INDEX(BankQuarter!$A$5:$A$750,MATCH($B8&"|"&WF_END_PERIOD,BankQuarter!$AC$5:$AC$750,0))) -> 741 | F8: =IF($B8="","",IF(COUNTIFS(BankQuarter!$B$5:$B$750,$B8,BankQuarter!$D$5:$D$750,WF_START_PERIOD)=0,"",INDEX(BankQuarter!$A$5:$A$750,MATCH($B8&"|"&WF_START_PERIOD,BankQuarter!$AC$5:$AC$750,0)))) -> 529 | G8: =IF($B8="","",INDEX(BankQuarter!$F$5:$F$750,MATCH($B8&"|"&WF_END_PERIOD,BankQuarter!$AC$5:$AC$750,0))) -> 724753 | H8: =IF($B8="","",INDEX(BankQuarter!$G$5:$G$750,MATCH($B8&"|"&WF_END_PERIOD,BankQuarter!$AC$5:$AC$750,0))) -> 7830 | I8: =IF($B8="","",INDEX(BankQuarter!$H$5:$H$750,MATCH($B8&"|"&WF_END_PERIOD,BankQuarter!$AC$5:$AC$750,0))) -> 5998 | J8: =IF($B8="","",INDEX(BankQuarter!$S$5:$S$750,MATCH($B8&"|"&WF_END_PERIOD,BankQuarter!$AC$5:$AC$750,0))) -> 1.9079604 | K8: =IF($B8="","",IF(COUNTIFS(BankQuarter!$B$5:$B$750,$B8,BankQuarter!$D$5:$D$750,WF_START_PERIOD,BankQuarter!$R$5:$R$750,TRUE())=0,"",INDEX(BankQuarter!$S$5:$S$750,MATCH($B8&"|"&WF_START_PERIOD,BankQuarter!$AC$5:$AC$750,0)))) -> 0.57239486 | L8: =IF(OR(J8="",K8=""),"",J8-K8) -> 1.3355655 | M8: =IF($B8="","",INDEX(BankQuarter!$P$5:$P$750,MATCH($B8&"|"&WF_END_PERIOD,BankQuarter!$AC$5:$AC$750,0))) -> 80.008981 | N8: =IF($B8="","",INDEX(BankQuarter!$Q$5:$Q$750,MATCH($B8&"|"&WF_END_PERIOD,BankQuarter!$AC$5:$AC$750,0))) -> 14.600147 | O8: =IF($B8="","",INDEX(BankQuarter!$N$5:$N$750,MATCH($B8&"|"&WF_END_PERIOD,BankQuarter!$AC$5:$AC$750,0))) -> 1.556918 | P8: =IF($B8="","",INDEX(BankQuarter!$O$5:$O$750,MATCH($B8&"|"&WF_END_PERIOD,BankQuarter!$AC$5:$AC$750,0))) -> 16.78059 | Q8: =IF($B8="","",IF(COUNTIFS(BankQuarter!$B$5:$B$750,$B8,BankQuarter!$D$5:$D$750,WF_START_PERIOD)=0,"",INDEX(BankQuarter!$F$5:$F$750,MATCH($B8&"|"&WF_START_PERIOD,BankQuarter!$AC$5:$AC$750,0)))) -> 706680 | R8: =IF($B8="","",IF(COUNTIFS(BankQuarter!$B$5:$B$750,$B8,BankQuarter!$D$5:$D$750,WF_START_PERIOD)=0,"",INDEX(BankQuarter!$G$5:$G$750,MATCH($B8&"|"&WF_START_PERIOD,BankQuarter!$AC$5:$AC$750,0)))) -> 0 | S8: =IF($B8="","",IF(COUNTIFS(BankQuarter!$B$5:$B$750,$B8,BankQuarter!$D$5:$D$750,WF_START_PERIOD)=0,"",INDEX(BankQuarter!$H$5:$H$750,MATCH($B8&"|"&WF_START_PERIOD,BankQuarter!$AC$5:$AC$750,0)))) -> 4045 | T8: =IF($B8="","",IF(COUNTIFS(BankQuarter!$B$5:$B$750,$B8,BankQuarter!$D$5:$D$750,WF_START_PERIOD)=0,"",INDEX(BankQuarter!$N$5:$N$750,MATCH($B8&"|"&WF_START_PERIOD,BankQuarter!$AC$5:$AC$750,0)))) -> 1.4156706 | U8: =IF(B8="","","End proxy "&TEXT(J8,"0.0000")&"%; "&IF(K8="","no valid start comparison","change "&TEXT(L8,"0.0000")&" pp")&". Screening signal only; verify loan-level causes.") -> End proxy 1.9080%; change 1.3356 pp. Screening signal only; verify loan-level causes. | V8: =IF(B8="","","Obtain past-due/nonaccrual loan tape, aging, payment history, accrual-status support, classifications/watch list and grade migration"&IF(M8>=75,"; CRE/RE concentration report, largest exposures, appraisals and stress results","")&IF(O8<0.5,"; earnings bridge, charge-offs, provisions and ACL support","")&IF(P8=0,"; RBCRWAJ is reported as 0—verify applicability/reporting basis and obtain capital schedules","; capital schedules and risk-weight support")) -> Obtain past-due/nonaccrual loan tape, aging, payment history, accrual-status support, classifications/watch list and grade migration; CRE/RE concentration report, largest exposures, appraisals and stress results; capital schedules and risk-weight support
A9: 5 | B9: =IF(AND(WF_MODEL_VALID,A9<=WF_REVIEW_SLOTS),SUMIFS(BankQuarter!$B$5:$B$750,BankQuarter!$D$5:$D$750,WF_END_PERIOD,BankQuarter!$R$5:$R$750,TRUE(),BankQuarter!$AA$5:$AA$750,2),"") -> 30878 | C9: =IF($B9="","",INDEX(BankQuarter!$E$5:$E$750,MATCH($B9&"|"&WF_END_PERIOD,BankQuarter!$AC$5:$AC$750,0))) -> ME | D9: =IF($B9="","",INDEX(BankQuarter!$C$5:$C$750,MATCH($B9&"|"&WF_END_PERIOD,BankQuarter!$AC$5:$AC$750,0))) -> BAR HARBOR SAVINGS AND LOAN ASSOCIATION | E9: =IF($B9="","",INDEX(BankQuarter!$A$5:$A$750,MATCH($B9&"|"&WF_END_PERIOD,BankQuarter!$AC$5:$AC$750,0))) -> 736 | F9: =IF($B9="","",IF(COUNTIFS(BankQuarter!$B$5:$B$750,$B9,BankQuarter!$D$5:$D$750,WF_START_PERIOD)=0,"",INDEX(BankQuarter!$A$5:$A$750,MATCH($B9&"|"&WF_START_PERIOD,BankQuarter!$AC$5:$AC$750,0)))) -> 524 | G9: =IF($B9="","",INDEX(BankQuarter!$F$5:$F$750,MATCH($B9&"|"&WF_END_PERIOD,BankQuarter!$AC$5:$AC$750,0))) -> 98909 | H9: =IF($B9="","",INDEX(BankQuarter!$G$5:$G$750,MATCH($B9&"|"&WF_END_PERIOD,BankQuarter!$AC$5:$AC$750,0))) -> 0 | I9: =IF($B9="","",INDEX(BankQuarter!$H$5:$H$750,MATCH($B9&"|"&WF_END_PERIOD,BankQuarter!$AC$5:$AC$750,0))) -> 1353 | J9: =IF($B9="","",INDEX(BankQuarter!$S$5:$S$750,MATCH($B9&"|"&WF_END_PERIOD,BankQuarter!$AC$5:$AC$750,0))) -> 1.3679241 | K9: =IF($B9="","",IF(COUNTIFS(BankQuarter!$B$5:$B$750,$B9,BankQuarter!$D$5:$D$750,WF_START_PERIOD,BankQuarter!$R$5:$R$750,TRUE())=0,"",INDEX(BankQuarter!$S$5:$S$750,MATCH($B9&"|"&WF_START_PERIOD,BankQuarter!$AC$5:$AC$750,0)))) -> 1.7771084 | L9: =IF(OR(J9="",K9=""),"",J9-K9) -> -0.40918438 | M9: =IF($B9="","",INDEX(BankQuarter!$P$5:$P$750,MATCH($B9&"|"&WF_END_PERIOD,BankQuarter!$AC$5:$AC$750,0))) -> 99.795434 | N9: =IF($B9="","",INDEX(BankQuarter!$Q$5:$Q$750,MATCH($B9&"|"&WF_END_PERIOD,BankQuarter!$AC$5:$AC$750,0))) -> 12.022162 | O9: =IF($B9="","",INDEX(BankQuarter!$N$5:$N$750,MATCH($B9&"|"&WF_END_PERIOD,BankQuarter!$AC$5:$AC$750,0))) -> 0.0020154179 | P9: =IF($B9="","",INDEX(BankQuarter!$O$5:$O$750,MATCH($B9&"|"&WF_END_PERIOD,BankQuarter!$AC$5:$AC$750,0))) -> 0 | Q9: =IF($B9="","",IF(COUNTIFS(BankQuarter!$B$5:$B$750,$B9,BankQuarter!$D$5:$D$750,WF_START_PERIOD)=0,"",INDEX(BankQuarter!$F$5:$F$750,MATCH($B9&"|"&WF_START_PERIOD,BankQuarter!$AC$5:$AC$750,0)))) -> 102920 | R9: =IF($B9="","",IF(COUNTIFS(BankQuarter!$B$5:$B$750,$B9,BankQuarter!$D$5:$D$750,WF_START_PERIOD)=0,"",INDEX(BankQuarter!$G$5:$G$750,MATCH($B9&"|"&WF_START_PERIOD,BankQuarter!$AC$5:$AC$750,0)))) -> 0 | S9: =IF($B9="","",IF(COUNTIFS(BankQuarter!$B$5:$B$750,$B9,BankQuarter!$D$5:$D$750,WF_START_PERIOD)=0,"",INDEX(BankQuarter!$H$5:$H$750,MATCH($B9&"|"&WF_START_PERIOD,BankQuarter!$AC$5:$AC$750,0)))) -> 1829 | T9: =IF($B9="","",IF(COUNTIFS(BankQuarter!$B$5:$B$750,$B9,BankQuarter!$D$5:$D$750,WF_START_PERIOD)=0,"",INDEX(BankQuarter!$N$5:$N$750,MATCH($B9&"|"&WF_START_PERIOD,BankQuarter!$AC$5:$AC$750,0)))) -> -0.22771497 | U9: =IF(B9="","","End proxy "&TEXT(J9,"0.0000")&"%; "&IF(K9="","no valid start comparison","change "&TEXT(L9,"0.0000")&" pp")&". Screening signal only; verify loan-level causes.") -> End proxy 1.3679%; change -0.4092 pp. Screening signal only; verify loan-level causes. | V9: =IF(B9="","","Obtain past-due/nonaccrual loan tape, aging, payment history, accrual-status support, classifications/watch list and grade migration"&IF(M9>=75,"; CRE/RE concentration report, largest exposures, appraisals and stress results","")&IF(O9<0.5,"; earnings bridge, charge-offs, provisions and ACL support","")&IF(P9=0,"; RBCRWAJ is reported as 0—verify applicability/reporting basis and obtain capital schedules","; capital schedules and risk-weight support")) -> Obtain past-due/nonaccrual loan tape, aging, payment history, accrual-status support, classifications/watch list and grade migration; CRE/RE concentration report, largest exposures, appraisals and stress results; earnings bridge, charge-offs, provisions and ACL support; RBCRWAJ is reported as 0—verify applicability/reporting basis and obtain capital schedules
A10: 6 | B10: =IF(AND(WF_MODEL_VALID,A10<=WF_REVIEW_SLOTS),SUMIFS(BankQuarter!$B$5:$B$750,BankQuarter!$D$5:$D$750,WF_END_PERIOD,BankQuarter!$R$5:$R$750,TRUE(),BankQuarter!$AA$5:$AA$750,3),"") -> 19836 | C10: =IF($B10="","",INDEX(BankQuarter!$E$5:$E$750,MATCH($B10&"|"&WF_END_PERIOD,BankQuarter!$AC$5:$AC$750,0))) -> ME | D10: =IF($B10="","",INDEX(BankQuarter!$C$5:$C$750,MATCH($B10&"|"&WF_END_PERIOD,BankQuarter!$AC$5:$AC$750,0))) -> FRANKLIN SAVINGS BANK | E10: =IF($B10="","",INDEX(BankQuarter!$A$5:$A$750,MATCH($B10&"|"&WF_END_PERIOD,BankQuarter!$AC$5:$AC$750,0))) -> 725 | F10: =IF($B10="","",IF(COUNTIFS(BankQuarter!$B$5:$B$750,$B10,BankQuarter!$D$5:$D$750,WF_START_PERIOD)=0,"",INDEX(BankQuarter!$A$5:$A$750,MATCH($B10&"|"&WF_START_PERIOD,BankQuarter!$AC$5:$AC$750,0)))) -> 513 | G10: =IF($B10="","",INDEX(BankQuarter!$F$5:$F$750,MATCH($B10&"|"&WF_END_PERIOD,BankQuarter!$AC$5:$AC$750,0))) -> 755186 | H10: =IF($B10="","",INDEX(BankQuarter!$G$5:$G$750,MATCH($B10&"|"&WF_END_PERIOD,BankQuarter!$AC$5:$AC$750,0))) -> 141 | I10: =IF($B10="","",INDEX(BankQuarter!$H$5:$H$750,MATCH($B10&"|"&WF_END_PERIOD,BankQuarter!$AC$5:$AC$750,0))) -> 8281 | J10: =IF($B10="","",INDEX(BankQuarter!$S$5:$S$750,MATCH($B10&"|"&WF_END_PERIOD,BankQuarter!$AC$5:$AC$750,0))) -> 1.1152219 | K10: =IF($B10="","",IF(COUNTIFS(BankQuarter!$B$5:$B$750,$B10,BankQuarter!$D$5:$D$750,WF_START_PERIOD,BankQuarter!$R$5:$R$750,TRUE())=0,"",INDEX(BankQuarter!$S$5:$S$750,MATCH($B10&"|"&WF_START_PERIOD,BankQuarter!$AC$5:$AC$750,0)))) -> 0.81498664 | L10: =IF(OR(J10="",K10=""),"",J10-K10) -> 0.3002353 | M10: =IF($B10="","",INDEX(BankQuarter!$P$5:$P$750,MATCH($B10&"|"&WF_END_PERIOD,BankQuarter!$AC$5:$AC$750,0))) -> 91.345024 | N10: =IF($B10="","",INDEX(BankQuarter!$Q$5:$Q$750,MATCH($B10&"|"&WF_END_PERIOD,BankQuarter!$AC$5:$AC$750,0))) -> 17.275876 | O10: =IF($B10="","",INDEX(BankQuarter!$N$5:$N$750,MATCH($B10&"|"&WF_END_PERIOD,BankQuarter!$AC$5:$AC$750,0))) -> 0.83954125 | P10: =IF($B10="","",INDEX(BankQuarter!$O$5:$O$750,MATCH($B10&"|"&WF_END_PERIOD,BankQuarter!$AC$5:$AC$750,0))) -> 23.054852 | Q10: =IF($B10="","",IF(COUNTIFS(BankQuarter!$B$5:$B$750,$B10,BankQuarter!$D$5:$D$750,WF_START_PERIOD)=0,"",INDEX(BankQuarter!$F$5:$F$750,MATCH($B10&"|"&WF_START_PERIOD,BankQuarter!$AC$5:$AC$750,0)))) -> 693631 | R10: =IF($B10="","",IF(COUNTIFS(BankQuarter!$B$5:$B$750,$B10,BankQuarter!$D$5:$D$750,WF_START_PERIOD)=0,"",INDEX(BankQuarter!$G$5:$G$750,MATCH($B10&"|"&WF_START_PERIOD,BankQuarter!$AC$5:$AC$750,0)))) -> 539 | S10: =IF($B10="","",IF(COUNTIFS(BankQuarter!$B$5:$B$750,$B10,BankQuarter!$D$5:$D$750,WF_START_PERIOD)=0,"",INDEX(BankQuarter!$H$5:$H$750,MATCH($B10&"|"&WF_START_PERIOD,BankQuarter!$AC$5:$AC$750,0)))) -> 5114 | T10: =IF($B10="","",IF(COUNTIFS(BankQuarter!$B$5:$B$750,$B10,BankQuarter!$D$5:$D$750,WF_START_PERIOD)=0,"",INDEX(BankQuarter!$N$5:$N$750,MATCH($B10&"|"&WF_START_PERIOD,BankQuarter!$AC$5:$AC$750,0)))) -> 0.6592637 | U10: =IF(B10="","","End proxy "&TEXT(J10,"0.0000")&"%; "&IF(K10="","no valid start comparison","change "&TEXT(L10,"0.0000")&" pp")&". Screening signal only; verify loan-level causes.") -> End proxy 1.1152%; change 0.3002 pp. Screening signal only; verify loan-level causes. | V10: =IF(B10="","","Obtain past-due/nonaccrual loan tape, aging, payment history, accrual-status support, classifications/watch list and grade migration"&IF(M10>=75,"; CRE/RE concentration report, largest exposures, appraisals and stress results","")&IF(O10<0.5,"; earnings bridge, charge-offs, provisions and ACL support","")&IF(P10=0,"; RBCRWAJ is reported as 0—verify applicability/reporting basis and obtain capital schedules","; capital schedules and risk-weight support")) -> Obtain past-due/nonaccrual loan tape, aging, payment history, accrual-status support, classifications/watch list and grade migration; CRE/RE concentration report, largest exposures, appraisals and stress results; capital schedules and risk-weight support
A11: 7 | B11: =IF(AND(WF_MODEL_VALID,A11<=WF_REVIEW_SLOTS),SUMIFS(BankQuarter!$B$5:$B$750,BankQuarter!$D$5:$D$750,WF_END_PERIOD,BankQuarter!$R$5:$R$750,TRUE(),BankQuarter!$AA$5:$AA$750,4),"") -> 14158 | C11: =IF($B11="","",INDEX(BankQuarter!$E$5:$E$750,MATCH($B11&"|"&WF_END_PERIOD,BankQuarter!$AC$5:$AC$750,0))) -> VT | D11: =IF($B11="","",INDEX(BankQuarter!$C$5:$C$750,MATCH($B11&"|"&WF_END_PERIOD,BankQuarter!$AC$5:$AC$750,0))) -> UNION BANK | E11: =IF($B11="","",INDEX(BankQuarter!$A$5:$A$750,MATCH($B11&"|"&WF_END_PERIOD,BankQuarter!$AC$5:$AC$750,0))) -> 702 | F11: =IF($B11="","",IF(COUNTIFS(BankQuarter!$B$5:$B$750,$B11,BankQuarter!$D$5:$D$750,WF_START_PERIOD)=0,"",INDEX(BankQuarter!$A$5:$A$750,MATCH($B11&"|"&WF_START_PERIOD,BankQuarter!$AC$5:$AC$750,0)))) -> 488 | G11: =IF($B11="","",INDEX(BankQuarter!$F$5:$F$750,MATCH($B11&"|"&WF_END_PERIOD,BankQuarter!$AC$5:$AC$750,0))) -> 1479452 | H11: =IF($B11="","",INDEX(BankQuarter!$G$5:$G$750,MATCH($B11&"|"&WF_END_PERIOD,BankQuarter!$AC$5:$AC$750,0))) -> 72 | I11: =IF($B11="","",INDEX(BankQuarter!$H$5:$H$750,MATCH($B11&"|"&WF_END_PERIOD,BankQuarter!$AC$5:$AC$750,0))) -> 15189 | J11: =IF($B11="","",INDEX(BankQuarter!$S$5:$S$750,MATCH($B11&"|"&WF_END_PERIOD,BankQuarter!$AC$5:$AC$750,0))) -> 1.0315306 | K11: =IF($B11="","",IF(COUNTIFS(BankQuarter!$B$5:$B$750,$B11,BankQuarter!$D$5:$D$750,WF_START_PERIOD,BankQuarter!$R$5:$R$750,TRUE())=0,"",INDEX(BankQuarter!$S$5:$S$750,MATCH($B11&"|"&WF_START_PERIOD,BankQuarter!$AC$5:$AC$750,0)))) -> 0.13792798 | L11: =IF(OR(J11="",K11=""),"",J11-K11) -> 0.89360262 | M11: =IF($B11="","",INDEX(BankQuarter!$P$5:$P$750,MATCH($B11&"|"&WF_END_PERIOD,BankQuarter!$AC$5:$AC$750,0))) -> 92.585155 | N11: =IF($B11="","",INDEX(BankQuarter!$Q$5:$Q$750,MATCH($B11&"|"&WF_END_PERIOD,BankQuarter!$AC$5:$AC$750,0))) -> 5.8481789 | O11: =IF($B11="","",INDEX(BankQuarter!$N$5:$N$750,MATCH($B11&"|"&WF_END_PERIOD,BankQuarter!$AC$5:$AC$750,0))) -> 0.70486927 | P11: =IF($B11="","",INDEX(BankQuarter!$O$5:$O$750,MATCH($B11&"|"&WF_END_PERIOD,BankQuarter!$AC$5:$AC$750,0))) -> 12.623433 | Q11: =IF($B11="","",IF(COUNTIFS(BankQuarter!$B$5:$B$750,$B11,BankQuarter!$D$5:$D$750,WF_START_PERIOD)=0,"",INDEX(BankQuarter!$F$5:$F$750,MATCH($B11&"|"&WF_START_PERIOD,BankQuarter!$AC$5:$AC$750,0)))) -> 1397831 | R11: =IF($B11="","",IF(COUNTIFS(BankQuarter!$B$5:$B$750,$B11,BankQuarter!$D$5:$D$750,WF_START_PERIOD)=0,"",INDEX(BankQuarter!$G$5:$G$750,MATCH($B11&"|"&WF_START_PERIOD,BankQuarter!$AC$5:$AC$750,0)))) -> 157 | S11: =IF($B11="","",IF(COUNTIFS(BankQuarter!$B$5:$B$750,$B11,BankQuarter!$D$5:$D$750,WF_START_PERIOD)=0,"",INDEX(BankQuarter!$H$5:$H$750,MATCH($B11&"|"&WF_START_PERIOD,BankQuarter!$AC$5:$AC$750,0)))) -> 1771 | T11: =IF($B11="","",IF(COUNTIFS(BankQuarter!$B$5:$B$750,$B11,BankQuarter!$D$5:$D$750,WF_START_PERIOD)=0,"",INDEX(BankQuarter!$N$5:$N$750,MATCH($B11&"|"&WF_START_PERIOD,BankQuarter!$AC$5:$AC$750,0)))) -> 0.68793074 | U11: =IF(B11="","","End proxy "&TEXT(J11,"0.0000")&"%; "&IF(K11="","no valid start comparison","change "&TEXT(L11,"0.0000")&" pp")&". Screening signal only; verify loan-level causes.") -> End proxy 1.0315%; change 0.8936 pp. Screening signal only; verify loan-level causes. | V11: =IF(B11="","","Obtain past-due/nonaccrual loan tape, aging, payment history, accrual-status support, classifications/watch list and grade migration"&IF(M11>=75,"; CRE/RE concentration report, largest exposures, appraisals and stress results","")&IF(O11<0.5,"; earnings bridge, charge-offs, provisions and ACL support","")&IF(P11=0,"; RBCRWAJ is reported as 0—verify applicability/reporting basis and obtain capital schedules","; capital schedules and risk-weight support")) -> Obtain past-due/nonaccrual loan tape, aging, payment history, accrual-status support, classifications/watch list and grade migration; CRE/RE concentration report, largest exposures, appraisals and stress results; capital schedules and risk-weight support
A12: 8 | B12: =IF(AND(WF_MODEL_VALID,A12<=WF_REVIEW_SLOTS),SUMIFS(BankQuarter!$B$5:$B$750,BankQuarter!$D$5:$D$750,WF_END_PERIOD,BankQuarter!$R$5:$R$750,TRUE(),BankQuarter!$AA$5:$AA$750,5),"") -> 19690 | C12: =IF($B12="","",INDEX(BankQuarter!$E$5:$E$750,MATCH($B12&"|"&WF_END_PERIOD,BankQuarter!$AC$5:$AC$750,0))) -> ME | D12: =IF($B12="","",INDEX(BankQuarter!$C$5:$C$750,MATCH($B12&"|"&WF_END_PERIOD,BankQuarter!$AC$5:$AC$750,0))) -> NORTHEAST BANK | E12: =IF($B12="","",INDEX(BankQuarter!$A$5:$A$750,MATCH($B12&"|"&WF_END_PERIOD,BankQuarter!$AC$5:$AC$750,0))) -> 724 | F12: =IF($B12="","",IF(COUNTIFS(BankQuarter!$B$5:$B$750,$B12,BankQuarter!$D$5:$D$750,WF_START_PERIOD)=0,"",INDEX(BankQuarter!$A$5:$A$750,MATCH($B12&"|"&WF_START_PERIOD,BankQuarter!$AC$5:$AC$750,0)))) -> 512 | G12: =IF($B12="","",INDEX(BankQuarter!$F$5:$F$750,MATCH($B12&"|"&WF_END_PERIOD,BankQuarter!$AC$5:$AC$750,0))) -> 4279069 | H12: =IF($B12="","",INDEX(BankQuarter!$G$5:$G$750,MATCH($B12&"|"&WF_END_PERIOD,BankQuarter!$AC$5:$AC$750,0))) -> 0 | I12: =IF($B12="","",INDEX(BankQuarter!$H$5:$H$750,MATCH($B12&"|"&WF_END_PERIOD,BankQuarter!$AC$5:$AC$750,0))) -> 35011 | J12: =IF($B12="","",INDEX(BankQuarter!$S$5:$S$750,MATCH($B12&"|"&WF_END_PERIOD,BankQuarter!$AC$5:$AC$750,0))) -> 0.81819199 | K12: =IF($B12="","",IF(COUNTIFS(BankQuarter!$B$5:$B$750,$B12,BankQuarter!$D$5:$D$750,WF_START_PERIOD,BankQuarter!$R$5:$R$750,TRUE())=0,"",INDEX(BankQuarter!$S$5:$S$750,MATCH($B12&"|"&WF_START_PERIOD,BankQuarter!$AC$5:$AC$750,0)))) -> 0.90224037 | L12: =IF(OR(J12="",K12=""),"",J12-K12) -> -0.084048377 | M12: =IF($B12="","",INDEX(BankQuarter!$P$5:$P$750,MATCH($B12&"|"&WF_END_PERIOD,BankQuarter!$AC$5:$AC$750,0))) -> 75.272634 | N12: =IF($B12="","",INDEX(BankQuarter!$Q$5:$Q$750,MATCH($B12&"|"&WF_END_PERIOD,BankQuarter!$AC$5:$AC$750,0))) -> 11.551251 | O12: =IF($B12="","",INDEX(BankQuarter!$N$5:$N$750,MATCH($B12&"|"&WF_END_PERIOD,BankQuarter!$AC$5:$AC$750,0))) -> 2.0918421 | P12: =IF($B12="","",INDEX(BankQuarter!$O$5:$O$750,MATCH($B12&"|"&WF_END_PERIOD,BankQuarter!$AC$5:$AC$750,0))) -> 14.696581 | Q12: =IF($B12="","",IF(COUNTIFS(BankQuarter!$B$5:$B$750,$B12,BankQuarter!$D$5:$D$750,WF_START_PERIOD)=0,"",INDEX(BankQuarter!$F$5:$F$750,MATCH($B12&"|"&WF_START_PERIOD,BankQuarter!$AC$5:$AC$750,0)))) -> 3132203 | R12: =IF($B12="","",IF(COUNTIFS(BankQuarter!$B$5:$B$750,$B12,BankQuarter!$D$5:$D$750,WF_START_PERIOD)=0,"",INDEX(BankQuarter!$G$5:$G$750,MATCH($B12&"|"&WF_START_PERIOD,BankQuarter!$AC$5:$AC$750,0)))) -> 0 | S12: =IF($B12="","",IF(COUNTIFS(BankQuarter!$B$5:$B$750,$B12,BankQuarter!$D$5:$D$750,WF_START_PERIOD)=0,"",INDEX(BankQuarter!$H$5:$H$750,MATCH($B12&"|"&WF_START_PERIOD,BankQuarter!$AC$5:$AC$750,0)))) -> 28260 | T12: =IF($B12="","",IF(COUNTIFS(BankQuarter!$B$5:$B$750,$B12,BankQuarter!$D$5:$D$750,WF_START_PERIOD)=0,"",INDEX(BankQuarter!$N$5:$N$750,MATCH($B12&"|"&WF_START_PERIOD,BankQuarter!$AC$5:$AC$750,0)))) -> 1.9118907 | U12: =IF(B12="","","End proxy "&TEXT(J12,"0.0000")&"%; "&IF(K12="","no valid start comparison","change "&TEXT(L12,"0.0000")&" pp")&". Screening signal only; verify loan-level causes.") -> End proxy 0.8182%; change -0.0840 pp. Screening signal only; verify loan-level causes. | V12: =IF(B12="","","Obtain past-due/nonaccrual loan tape, aging, payment history, accrual-status support, classifications/watch list and grade migration"&IF(M12>=75,"; CRE/RE concentration report, largest exposures, appraisals and stress results","")&IF(O12<0.5,"; earnings bridge, charge-offs, provisions and ACL support","")&IF(P12=0,"; RBCRWAJ is reported as 0—verify applicability/reporting basis and obtain capital schedules","; capital schedules and risk-weight support")) -> Obtain past-due/nonaccrual loan tape, aging, payment history, accrual-status support, classifications/watch list and grade migration; CRE/RE concentration report, largest exposures, appraisals and stress results; capital schedules and risk-weight support
A13: 9 | B13: =IF(AND(WF_MODEL_VALID,A13<=WF_REVIEW_SLOTS),SUMIFS(BankQuarter!$B$5:$B$750,BankQuarter!$D$5:$D$750,WF_END_PERIOD,BankQuarter!$R$5:$R$750,TRUE(),BankQuarter!$AA$5:$AA$750,6),"") | C13: =IF($B13="","",INDEX(BankQuarter!$E$5:$E$750,MATCH($B13&"|"&WF_END_PERIOD,BankQuarter!$AC$5:$AC$750,0))) | D13: =IF($B13="","",INDEX(BankQuarter!$C$5:$C$750,MATCH($B13&"|"&WF_END_PERIOD,BankQuarter!$AC$5:$AC$750,0))) | E13: =IF($B13="","",INDEX(BankQuarter!$A$5:$A$750,MATCH($B13&"|"&WF_END_PERIOD,BankQuarter!$AC$5:$AC$750,0))) | F13: =IF($B13="","",IF(COUNTIFS(BankQuarter!$B$5:$B$750,$B13,BankQuarter!$D$5:$D$750,WF_START_PERIOD)=0,"",INDEX(BankQuarter!$A$5:$A$750,MATCH($B13&"|"&WF_START_PERIOD,BankQuarter!$AC$5:$AC$750,0)))) | G13: =IF($B13="","",INDEX(BankQuarter!$F$5:$F$750,MATCH($B13&"|"&WF_END_PERIOD,BankQuarter!$AC$5:$AC$750,0))) | H13: =IF($B13="","",INDEX(BankQuarter!$G$5:$G$750,MATCH($B13&"|"&WF_END_PERIOD,BankQuarter!$AC$5:$AC$750,0))) | I13: =IF($B13="","",INDEX(BankQuarter!$H$5:$H$750,MATCH($B13&"|"&WF_END_PERIOD,BankQuarter!$AC$5:$AC$750,0))) | J13: =IF($B13="","",INDEX(BankQuarter!$S$5:$S$750,MATCH($B13&"|"&WF_END_PERIOD,BankQuarter!$AC$5:$AC$750,0))) | K13: =IF($B13="","",IF(COUNTIFS(BankQuarter!$B$5:$B$750,$B13,BankQuarter!$D$5:$D$750,WF_START_PERIOD,BankQuarter!$R$5:$R$750,TRUE())=0,"",INDEX(BankQuarter!$S$5:$S$750,MATCH($B13&"|"&WF_START_PERIOD,BankQuarter!$AC$5:$AC$750,0)))) | L13: =IF(OR(J13="",K13=""),"",J13-K13) | M13: =IF($B13="","",INDEX(BankQuarter!$P$5:$P$750,MATCH($B13&"|"&WF_END_PERIOD,BankQuarter!$AC$5:$AC$750,0))) | N13: =IF($B13="","",INDEX(BankQuarter!$Q$5:$Q$750,MATCH($B13&"|"&WF_END_PERIOD,BankQuarter!$AC$5:$AC$750,0))) | O13: =IF($B13="","",INDEX(BankQuarter!$N$5:$N$750,MATCH($B13&"|"&WF_END_PERIOD,BankQuarter!$AC$5:$AC$750,0))) | P13: =IF($B13="","",INDEX(BankQuarter!$O$5:$O$750,MATCH($B13&"|"&WF_END_PERIOD,BankQuarter!$AC$5:$AC$750,0))) | Q13: =IF($B13="","",IF(COUNTIFS(BankQuarter!$B$5:$B$750,$B13,BankQuarter!$D$5:$D$750,WF_START_PERIOD)=0,"",INDEX(BankQuarter!$F$5:$F$750,MATCH($B13&"|"&WF_START_PERIOD,BankQuarter!$AC$5:$AC$750,0)))) | R13: =IF($B13="","",IF(COUNTIFS(BankQuarter!$B$5:$B$750,$B13,BankQuarter!$D$5:$D$750,WF_START_PERIOD)=0,"",INDEX(BankQuarter!$G$5:$G$750,MATCH($B13&"|"&WF_START_PERIOD,BankQuarter!$AC$5:$AC$750,0)))) | S13: =IF($B13="","",IF(COUNTIFS(BankQuarter!$B$5:$B$750,$B13,BankQuarter!$D$5:$D$750,WF_START_PERIOD)=0,"",INDEX(BankQuarter!$H$5:$H$750,MATCH($B13&"|"&WF_START_PERIOD,BankQuarter!$AC$5:$AC$750,0)))) | T13: =IF($B13="","",IF(COUNTIFS(BankQuarter!$B$5:$B$750,$B13,BankQuarter!$D$5:$D$750,WF_START_PERIOD)=0,"",INDEX(BankQuarter!$N$5:$N$750,MATCH($B13&"|"&WF_START_PERIOD,BankQuarter!$AC$5:$AC$750,0)))) | U13: =IF(B13="","","End proxy "&TEXT(J13,"0.0000")&"%; "&IF(K13="","no valid start comparison","change "&TEXT(L13,"0.0000")&" pp")&". Screening signal only; verify loan-level causes.") | V13: =IF(B13="","","Obtain past-due/nonaccrual loan tape, aging, payment history, accrual-status support, classifications/watch list and grade migration"&IF(M13>=75,"; CRE/RE concentration report, largest exposures, appraisals and stress results","")&IF(O13<0.5,"; earnings bridge, charge-offs, provisions and ACL support","")&IF(P13=0,"; RBCRWAJ is reported as 0—verify applicability/reporting basis and obtain capital schedules","; capital schedules and risk-weight support"))
A14: 10 | B14: =IF(AND(WF_MODEL_VALID,A14<=WF_REVIEW_SLOTS),SUMIFS(BankQuarter!$B$5:$B$750,BankQuarter!$D$5:$D$750,WF_END_PERIOD,BankQuarter!$R$5:$R$750,TRUE(),BankQuarter!$AA$5:$AA$750,7),"") | C14: =IF($B14="","",INDEX(BankQuarter!$E$5:$E$750,MATCH($B14&"|"&WF_END_PERIOD,BankQuarter!$AC$5:$AC$750,0))) | D14: =IF($B14="","",INDEX(BankQuarter!$C$5:$C$750,MATCH($B14&"|"&WF_END_PERIOD,BankQuarter!$AC$5:$AC$750,0))) | E14: =IF($B14="","",INDEX(BankQuarter!$A$5:$A$750,MATCH($B14&"|"&WF_END_PERIOD,BankQuarter!$AC$5:$AC$750,0))) | F14: =IF($B14="","",IF(COUNTIFS(BankQuarter!$B$5:$B$750,$B14,BankQuarter!$D$5:$D$750,WF_START_PERIOD)=0,"",INDEX(BankQuarter!$A$5:$A$750,MATCH($B14&"|"&WF_START_PERIOD,BankQuarter!$AC$5:$AC$750,0)))) | G14: =IF($B14="","",INDEX(BankQuarter!$F$5:$F$750,MATCH($B14&"|"&WF_END_PERIOD,BankQuarter!$AC$5:$AC$750,0))) | H14: =IF($B14="","",INDEX(BankQuarter!$G$5:$G$750,MATCH($B14&"|"&WF_END_PERIOD,BankQuarter!$AC$5:$AC$750,0))) | I14: =IF($B14="","",INDEX(BankQuarter!$H$5:$H$750,MATCH($B14&"|"&WF_END_PERIOD,BankQuarter!$AC$5:$AC$750,0))) | J14: =IF($B14="","",INDEX(BankQuarter!$S$5:$S$750,MATCH($B14&"|"&WF_END_PERIOD,BankQuarter!$AC$5:$AC$750,0))) | K14: =IF($B14="","",IF(COUNTIFS(BankQuarter!$B$5:$B$750,$B14,BankQuarter!$D$5:$D$750,WF_START_PERIOD,BankQuarter!$R$5:$R$750,TRUE())=0,"",INDEX(BankQuarter!$S$5:$S$750,MATCH($B14&"|"&WF_START_PERIOD,BankQuarter!$AC$5:$AC$750,0)))) | L14: =IF(OR(J14="",K14=""),"",J14-K14) | M14: =IF($B14="","",INDEX(BankQuarter!$P$5:$P$750,MATCH($B14&"|"&WF_END_PERIOD,BankQuarter!$AC$5:$AC$750,0))) | N14: =IF($B14="","",INDEX(BankQuarter!$Q$5:$Q$750,MATCH($B14&"|"&WF_END_PERIOD,BankQuarter!$AC$5:$AC$750,0))) | O14: =IF($B14="","",INDEX(BankQuarter!$N$5:$N$750,MATCH($B14&"|"&WF_END_PERIOD,BankQuarter!$AC$5:$AC$750,0))) | P14: =IF($B14="","",INDEX(BankQuarter!$O$5:$O$750,MATCH($B14&"|"&WF_END_PERIOD,BankQuarter!$AC$5:$AC$750,0))) | Q14: =IF($B14="","",IF(COUNTIFS(BankQuarter!$B$5:$B$750,$B14,BankQuarter!$D$5:$D$750,WF_START_PERIOD)=0,"",INDEX(BankQuarter!$F$5:$F$750,MATCH($B14&"|"&WF_START_PERIOD,BankQuarter!$AC$5:$AC$750,0)))) | R14: =IF($B14="","",IF(COUNTIFS(BankQuarter!$B$5:$B$750,$B14,BankQuarter!$D$5:$D$750,WF_START_PERIOD)=0,"",INDEX(BankQuarter!$G$5:$G$750,MATCH($B14&"|"&WF_START_PERIOD,BankQuarter!$AC$5:$AC$750,0)))) | S14: =IF($B14="","",IF(COUNTIFS(BankQuarter!$B$5:$B$750,$B14,BankQuarter!$D$5:$D$750,WF_START_PERIOD)=0,"",INDEX(BankQuarter!$H$5:$H$750,MATCH($B14&"|"&WF_START_PERIOD,BankQuarter!$AC$5:$AC$750,0)))) | T14: =IF($B14="","",IF(COUNTIFS(BankQuarter!$B$5:$B$750,$B14,BankQuarter!$D$5:$D$750,WF_START_PERIOD)=0,"",INDEX(BankQuarter!$N$5:$N$750,MATCH($B14&"|"&WF_START_PERIOD,BankQuarter!$AC$5:$AC$750,0)))) | U14: =IF(B14="","","End proxy "&TEXT(J14,"0.0000")&"%; "&IF(K14="","no valid start comparison","change "&TEXT(L14,"0.0000")&" pp")&". Screening signal only; verify loan-level causes.") | V14: =IF(B14="","","Obtain past-due/nonaccrual loan tape, aging, payment history, accrual-status support, classifications/watch list and grade migration"&IF(M14>=75,"; CRE/RE concentration report, largest exposures, appraisals and stress results","")&IF(O14<0.5,"; earnings bridge, charge-offs, provisions and ACL support","")&IF(P14=0,"; RBCRWAJ is reported as 0—verify applicability/reporting basis and obtain capital schedules","; capital schedules and risk-weight support"))
A15: 11 | B15: =IF(AND(WF_MODEL_VALID,A15<=WF_REVIEW_SLOTS),SUMIFS(BankQuarter!$B$5:$B$750,BankQuarter!$D$5:$D$750,WF_END_PERIOD,BankQuarter!$R$5:$R$750,TRUE(),BankQuarter!$AA$5:$AA$750,8),"") | C15: =IF($B15="","",INDEX(BankQuarter!$E$5:$E$750,MATCH($B15&"|"&WF_END_PERIOD,BankQuarter!$AC$5:$AC$750,0))) | D15: =IF($B15="","",INDEX(BankQuarter!$C$5:$C$750,MATCH($B15&"|"&WF_END_PERIOD,BankQuarter!$AC$5:$AC$750,0))) | E15: =IF($B15="","",INDEX(BankQuarter!$A$5:$A$750,MATCH($B15&"|"&WF_END_PERIOD,BankQuarter!$AC$5:$AC$750,0))) | F15: =IF($B15="","",IF(COUNTIFS(BankQuarter!$B$5:$B$750,$B15,BankQuarter!$D$5:$D$750,WF_START_PERIOD)=0,"",INDEX(BankQuarter!$A$5:$A$750,MATCH($B15&"|"&WF_START_PERIOD,BankQuarter!$AC$5:$AC$750,0)))) | G15: =IF($B15="","",INDEX(BankQuarter!$F$5:$F$750,MATCH($B15&"|"&WF_END_PERIOD,BankQuarter!$AC$5:$AC$750,0))) | H15: =IF($B15="","",INDEX(BankQuarter!$G$5:$G$750,MATCH($B15&"|"&WF_END_PERIOD,BankQuarter!$AC$5:$AC$750,0))) | I15: =IF($B15="","",INDEX(BankQuarter!$H$5:$H$750,MATCH($B15&"|"&WF_END_PERIOD,BankQuarter!$AC$5:$AC$750,0))) | J15: =IF($B15="","",INDEX(BankQuarter!$S$5:$S$750,MATCH($B15&"|"&WF_END_PERIOD,BankQuarter!$AC$5:$AC$750,0))) | K15: =IF($B15="","",IF(COUNTIFS(BankQuarter!$B$5:$B$750,$B15,BankQuarter!$D$5:$D$750,WF_START_PERIOD,BankQuarter!$R$5:$R$750,TRUE())=0,"",INDEX(BankQuarter!$S$5:$S$750,MATCH($B15&"|"&WF_START_PERIOD,BankQuarter!$AC$5:$AC$750,0)))) | L15: =IF(OR(J15="",K15=""),"",J15-K15) | M15: =IF($B15="","",INDEX(BankQuarter!$P$5:$P$750,MATCH($B15&"|"&WF_END_PERIOD,BankQuarter!$AC$5:$AC$750,0))) | N15: =IF($B15="","",INDEX(BankQuarter!$Q$5:$Q$750,MATCH($B15&"|"&WF_END_PERIOD,BankQuarter!$AC$5:$AC$750,0))) | O15: =IF($B15="","",INDEX(BankQuarter!$N$5:$N$750,MATCH($B15&"|"&WF_END_PERIOD,BankQuarter!$AC$5:$AC$750,0))) | P15: =IF($B15="","",INDEX(BankQuarter!$O$5:$O$750,MATCH($B15&"|"&WF_END_PERIOD,BankQuarter!$AC$5:$AC$750,0))) | Q15: =IF($B15="","",IF(COUNTIFS(BankQuarter!$B$5:$B$750,$B15,BankQuarter!$D$5:$D$750,WF_START_PERIOD)=0,"",INDEX(BankQuarter!$F$5:$F$750,MATCH($B15&"|"&WF_START_PERIOD,BankQuarter!$AC$5:$AC$750,0)))) | R15: =IF($B15="","",IF(COUNTIFS(BankQuarter!$B$5:$B$750,$B15,BankQuarter!$D$5:$D$750,WF_START_PERIOD)=0,"",INDEX(BankQuarter!$G$5:$G$750,MATCH($B15&"|"&WF_START_PERIOD,BankQuarter!$AC$5:$AC$750,0)))) | S15: =IF($B15="","",IF(COUNTIFS(BankQuarter!$B$5:$B$750,$B15,BankQuarter!$D$5:$D$750,WF_START_PERIOD)=0,"",INDEX(BankQuarter!$H$5:$H$750,MATCH($B15&"|"&WF_START_PERIOD,BankQuarter!$AC$5:$AC$750,0)))) | T15: =IF($B15="","",IF(COUNTIFS(BankQuarter!$B$5:$B$750,$B15,BankQuarter!$D$5:$D$750,WF_START_PERIOD)=0,"",INDEX(BankQuarter!$N$5:$N$750,MATCH($B15&"|"&WF_START_PERIOD,BankQuarter!$AC$5:$AC$750,0)))) | U15: =IF(B15="","","End proxy "&TEXT(J15,"0.0000")&"%; "&IF(K15="","no valid start comparison","change "&TEXT(L15,"0.0000")&" pp")&". Screening signal only; verify loan-level causes.") | V15: =IF(B15="","","Obtain past-due/nonaccrual loan tape, aging, payment history, accrual-status support, classifications/watch list and grade migration"&IF(M15>=75,"; CRE/RE concentration report, largest exposures, appraisals and stress results","")&IF(O15<0.5,"; earnings bridge, charge-offs, provisions and ACL support","")&IF(P15=0,"; RBCRWAJ is reported as 0—verify applicability/reporting basis and obtain capital schedules","; capital schedules and risk-weight support"))
A16: 12 | B16: =IF(AND(WF_MODEL_VALID,A16<=WF_REVIEW_SLOTS),SUMIFS(BankQuarter!$B$5:$B$750,BankQuarter!$D$5:$D$750,WF_END_PERIOD,BankQuarter!$R$5:$R$750,TRUE(),BankQuarter!$AA$5:$AA$750,9),"") | C16: =IF($B16="","",INDEX(BankQuarter!$E$5:$E$750,MATCH($B16&"|"&WF_END_PERIOD,BankQuarter!$AC$5:$AC$750,0))) | D16: =IF($B16="","",INDEX(BankQuarter!$C$5:$C$750,MATCH($B16&"|"&WF_END_PERIOD,BankQuarter!$AC$5:$AC$750,0))) | E16: =IF($B16="","",INDEX(BankQuarter!$A$5:$A$750,MATCH($B16&"|"&WF_END_PERIOD,BankQuarter!$AC$5:$AC$750,0))) | F16: =IF($B16="","",IF(COUNTIFS(BankQuarter!$B$5:$B$750,$B16,BankQuarter!$D$5:$D$750,WF_START_PERIOD)=0,"",INDEX(BankQuarter!$A$5:$A$750,MATCH($B16&"|"&WF_START_PERIOD,BankQuarter!$AC$5:$AC$750,0)))) | G16: =IF($B16="","",INDEX(BankQuarter!$F$5:$F$750,MATCH($B16&"|"&WF_END_PERIOD,BankQuarter!$AC$5:$AC$750,0))) | H16: =IF($B16="","",INDEX(BankQuarter!$G$5:$G$750,MATCH($B16&"|"&WF_END_PERIOD,BankQuarter!$AC$5:$AC$750,0))) | I16: =IF($B16="","",INDEX(BankQuarter!$H$5:$H$750,MATCH($B16&"|"&WF_END_PERIOD,BankQuarter!$AC$5:$AC$750,0))) | J16: =IF($B16="","",INDEX(BankQuarter!$S$5:$S$750,MATCH($B16&"|"&WF_END_PERIOD,BankQuarter!$AC$5:$AC$750,0))) | K16: =IF($B16="","",IF(COUNTIFS(BankQuarter!$B$5:$B$750,$B16,BankQuarter!$D$5:$D$750,WF_START_PERIOD,BankQuarter!$R$5:$R$750,TRUE())=0,"",INDEX(BankQuarter!$S$5:$S$750,MATCH($B16&"|"&WF_START_PERIOD,BankQuarter!$AC$5:$AC$750,0)))) | L16: =IF(OR(J16="",K16=""),"",J16-K16) | M16: =IF($B16="","",INDEX(BankQuarter!$P$5:$P$750,MATCH($B16&"|"&WF_END_PERIOD,BankQuarter!$AC$5:$AC$750,0))) | N16: =IF($B16="","",INDEX(BankQuarter!$Q$5:$Q$750,MATCH($B16&"|"&WF_END_PERIOD,BankQuarter!$AC$5:$AC$750,0))) | O16: =IF($B16="","",INDEX(BankQuarter!$N$5:$N$750,MATCH($B16&"|"&WF_END_PERIOD,BankQuarter!$AC$5:$AC$750,0))) | P16: =IF($B16="","",INDEX(BankQuarter!$O$5:$O$750,MATCH($B16&"|"&WF_END_PERIOD,BankQuarter!$AC$5:$AC$750,0))) | Q16: =IF($B16="","",IF(COUNTIFS(BankQuarter!$B$5:$B$750,$B16,BankQuarter!$D$5:$D$750,WF_START_PERIOD)=0,"",INDEX(BankQuarter!$F$5:$F$750,MATCH($B16&"|"&WF_START_PERIOD,BankQuarter!$AC$5:$AC$750,0)))) | R16: =IF($B16="","",IF(COUNTIFS(BankQuarter!$B$5:$B$750,$B16,BankQuarter!$D$5:$D$750,WF_START_PERIOD)=0,"",INDEX(BankQuarter!$G$5:$G$750,MATCH($B16&"|"&WF_START_PERIOD,BankQuarter!$AC$5:$AC$750,0)))) | S16: =IF($B16="","",IF(COUNTIFS(BankQuarter!$B$5:$B$750,$B16,BankQuarter!$D$5:$D$750,WF_START_PERIOD)=0,"",INDEX(BankQuarter!$H$5:$H$750,MATCH($B16&"|"&WF_START_PERIOD,BankQuarter!$AC$5:$AC$750,0)))) | T16: =IF($B16="","",IF(COUNTIFS(BankQuarter!$B$5:$B$750,$B16,BankQuarter!$D$5:$D$750,WF_START_PERIOD)=0,"",INDEX(BankQuarter!$N$5:$N$750,MATCH($B16&"|"&WF_START_PERIOD,BankQuarter!$AC$5:$AC$750,0)))) | U16: =IF(B16="","","End proxy "&TEXT(J16,"0.0000")&"%; "&IF(K16="","no valid start comparison","change "&TEXT(L16,"0.0000")&" pp")&". Screening signal only; verify loan-level causes.") | V16: =IF(B16="","","Obtain past-due/nonaccrual loan tape, aging, payment history, accrual-status support, classifications/watch list and grade migration"&IF(M16>=75,"; CRE/RE concentration report, largest exposures, appraisals and stress results","")&IF(O16<0.5,"; earnings bridge, charge-offs, provisions and ACL support","")&IF(P16=0,"; RBCRWAJ is reported as 0—verify applicability/reporting basis and obtain capital schedules","; capital schedules and risk-weight support"))
A19: Priority count | B19: =IF(WF_MODEL_VALID,COUNT(B5:B16),0) -> 8

Sheet Sources
A1: Sources, Definitions and Method Notes
A2: Frozen local source materials only; no live updates. Definitions are from files linked by the supplied FDIC API documentation snapshot.
A4: Topic / field | B4: FDIC definition or analytical treatment | C4: Local source | D4: Document locator | E4: Unit / caution | F4: Use in model
A5: CERT | B5: A unique NUMBER assigned by the FDIC used to identify institutions and for the issuance of insurance certificates. | C5: financial_definitions.yaml | D5: fdic_api_documentation.html → risview_properties.yaml | F5: Primary join/key component
A6: REPDTE | B6: The last day of the financial reporting period selected. | C6: financial_definitions.yaml | D6: fdic_api_documentation.html → risview_properties.yaml | F6: Quarter-key component
A7: ASSET | B7: The sum of all assets owned by the institution including cash, loans, securities, bank premises and other assets. This total does not include off-balance-sheet accounts. | C7: financial_definitions.yaml | D7: fdic_api_documentation.html → risview_properties.yaml | E7: Amount treated as $000 per exercise | F7: Proxy denominator and fixed weight
A8: DEP | B8: The sum of all deposits including demand deposits, money market deposits, other savings deposits, time deposits and deposits in foreign offices. | C8: financial_definitions.yaml | D8: fdic_api_documentation.html → risview_properties.yaml | E8: Amount treated as $000 per exercise | F8: Context / display
A9: EQ | B9: Total equity capital (includes preferred and common stock, surplus and undivided profits). | C9: financial_definitions.yaml | D9: fdic_api_documentation.html → risview_properties.yaml | E9: Amount treated as $000 per exercise | F9: Equity/assets numerator
A10: LNLSGR | B10: LOANS AND LEASES-TOTAL | C10: financial_definitions.yaml | D10: fdic_api_documentation.html → risview_properties.yaml | E10: Amount treated as $000 per exercise | F10: RE concentration denominator
A11: LNRE | B11: RE LOANS | C11: financial_definitions.yaml | D11: fdic_api_documentation.html → risview_properties.yaml | E11: Amount treated as $000 per exercise | F11: RE concentration numerator
A12: P9ASSET | B12: 90+ DAYS P/D-TOTAL ASSETS | C12: financial_definitions.yaml | D12: fdic_api_documentation.html → risview_properties.yaml | E12: Amount treated as $000 per exercise | F12: Proxy numerator component
A13: NAASSET | B13: NONACCRUAL-TOTAL ASSETS | C13: financial_definitions.yaml | D13: fdic_api_documentation.html → risview_properties.yaml | E13: Amount treated as $000 per exercise | F13: Proxy numerator component
A14: ROA | B14: Net income after taxes and extraordinary items (annualized) as a percent of average total assets. | C14: financial_definitions.yaml | D14: fdic_api_documentation.html → risview_properties.yaml | E14: Original percent; ROA already annualized | F14: Shown without re-annualizing
A15: RBCRWAJ | B15: TOTAL RBC RATIO-PCA | C15: financial_definitions.yaml | D15: fdic_api_documentation.html → risview_properties.yaml | E15: Original percent; zero retained and flagged for applicability/reporting verification | F15: Shown as reported
A16: STALP | B16: FIPS STATE ALPHA CODE | C16: financial_definitions.yaml | D16: fdic_api_documentation.html → risview_properties.yaml | F16: Context / display
A17: NAMEFULL | B17: INSTITUTION FULL NAME | C17: financial_definitions.yaml | D17: fdic_api_documentation.html → risview_properties.yaml | F17: Context / display
A18: Institution CERT | B18: A unique NUMBER assigned by the FDIC used to identify institutions and for the issuance of insurance certificates. | C18: institution_definitions.yaml | D18: fdic_api_documentation.html → institution_properties.yaml | F18: Joined by CERT only
A19: Institution NAME | B19: The legal title or name of the institution. | C19: institution_definitions.yaml | D19: fdic_api_documentation.html → institution_properties.yaml | F19: Joined by CERT only
A20: Institution ACTIVE | B20: A number indicating the status of an institution. 1='Institutions that are currently open and insured by the FDIC'; 0='Institution closed or not insured by FDIC' | C20: institution_definitions.yaml | D20: fdic_api_documentation.html → institution_properties.yaml | E20: Later snapshot; ACTIVE is not historical status and does not filter financial rows | F20: Joined by CERT only
A21: Institution REPDTE | B21: The last day of the financial reporting period selected. | C21: institution_definitions.yaml | D21: fdic_api_documentation.html → institution_properties.yaml | F21: Joined by CERT only
A22: Institution DATEUPDT | B22: The date of the last data update. | C22: institution_definitions.yaml | D22: fdic_api_documentation.html → institution_properties.yaml | F22: Joined by CERT only
A23: Institution STALP | B23: The state abbreviation of the location of the institution's main office. | C23: institution_definitions.yaml | D23: fdic_api_documentation.html → institution_properties.yaml | F23: Joined by CERT only
A24: Loan review system | B24: Review should cover grading, changes, ACL information, independence, scope, depth and follow-up. | C24: FDIC_RMS_Manual_3.2_Loans.pdf | D24: Manual pp. 3.2-4 to 3.2-5 | E24: No universal threshold supplied | F24: Supports requests for classifications, grade migration, documentation and follow-up
A25: Past due and nonaccrual | B25: High overdue volume can signal liberal standards or weak servicing, but comparisons may mislead because renewal/extension policies vary; consider makeup and reasons. | C25: FDIC_RMS_Manual_3.2_Loans.pdf | D25: Manual pp. 3.2-49 to 3.2-50 | E25: Proxy is not a rating or loan NPL ratio | F25: Supports loan-level aging, payment, accrual and servicing evidence
A26: Real estate lending | B26: Risk depends on loan amount relative to collateral, interest rate and especially repayment ability; policies should fit institution size and scope. | C26: FDIC_RMS_Manual_3.2_Loans.pdf | D26: Manual pp. 3.2-17 to 3.2-18 | E26: Share indicates concentration, not quality | F26: Supports borrower cash flow, valuation, appraisal and concentration review
A27: Collateral/documentation | B27: Loan review considers credit quality, collateral documentation, lien perfection, approvals, covenants, policy compliance and grade timeliness. | C27: FDIC_RMS_Manual_3.2_Loans.pdf | D27: Manual p. 3.2-5 | E27: Evidence must be institution-specific | F27: Supports specific document requests
A28: Concentrations | B28: Lending policies should set portfolio mix/diversification goals and monitor concentrations with corrective action where needed. | C28: FDIC_RMS_Manual_3.2_Loans.pdf | D28: Manual p. 3.2-3 and concentration section p. 3.2-57 | E28: No threshold imported | F28: Supports concentration reports and stress analysis
