Workbook

Sheet Options
A1: 集中培训会务方案比较｜FY2027
A2: 修改黄色参数后，Options/Daily自动回算；Word/PPT/CSV为2026-10-23快照，参数变化后必须重新核对并导出。待询价项目未计入，任何“预算内”仅指已知费用。
A4: 可调整参数 | D4: 参数约束 | V4: 城市 | W4: 票价 | X4: 酒店报价 | Y4: MIE | Z4: 当地RT | AA4: 11/28上限 | AB4: 11/29上限 | AC4: 11/30上限 | AD4: 12/1上限
A5: 批准预算上限 | B5: 53000 | D5: $0–$100,000（含储备） | V5: Chicago | W5: 271 | X5: 126 | Y5: 92 | Z5: 10 | AA5: 232 | AB5: 232 | AC5: 232 | AD5: 148
A6: 票价调整系数 | B6: 1 | D6: 0.5–2；压力情景在调整后再×1.20 | V6: Denver | W6: 466 | X6: 75 | Y6: 92 | Z6: 20 | AA6: 170 | AB6: 170 | AC6: 170 | AD6: 170
A7: 应急储备比例 | B7: 0.05 | D7: 0–20%；基础费用小计 | V7: Phoenix | W7: 581 | X7: 93 | Y7: 86 | Z7: 4 | AA7: 165 | AB7: 165 | AC7: 165 | AD7: 165
A8: 11月29日政府提供早餐 | B8: 否 | D8: 是/否；“是”不新增采购费用但扣早餐M&IE | V8: Boston | W8: 330 | X8: 202 | Y8: 92 | Z8: 5 | AA8: 213 | AB8: 213 | AC8: 213 | AD8: 213
A9: 抵达日期 | B9: 46354 | D9: 不得晚于2026-11-29；预算按实际住宿夜数回算 | V9: Seattle | W9: 977 | X9: 170 | Y9: 92 | Z9: 6 | AA9: 188 | AB9: 188 | AC9: 188 | AD9: 188
A10: 返程日期 | B10: 46358 | D10: 不得早于2026-12-02；预算按实际住宿夜数回算
A13: 城市 | B13: 人数 | C13: 调整后机票 | D13: 住宿含12%税 | E13: M&IE净额 | F13: 注册费 | G13: 机构供餐 | H13: 总部↔DCA | I13: 当地交通 | J13: 场地/茶歇 | K13: 基础已知小计 | L13: 应急储备 | M13: 已知含储备 | N13: 场地等可用余额 | O13: 已知费用判定 | P13: 证据完整性 | Q13: 压力含储备 | R13: 压力判定 | S13: 排序 | T13: 临时结论
A14: Chicago | B14: 18 | C14: =$B14*$B$6*$W$5 | D14: =$B14*1.12*MAX(0,$B$10-$B$9)*$X$5 | E14: =$B14*(234.0-IF($B$8="是",23,0)+MAX(0,$B$10-$B$9-4)*92) | F14: =$B14*180 | G14: =$B14*102 | H14: =$B14*12 | I14: =$B14*$Z$5 | J14: 0 | K14: =SUM(C14:J14) | L14: =K14*$B$7 | M14: =K14+L14 | N14: =MAX(0,$B$5-M14) | O14: =IF(M14<=$B$5,"已知费用内","超预算") | P14: 待询价—阻断 | Q14: =(K14+C14*20%)*(1+$B$7) | R14: =IF(Q14<=$B$5,"压力已知费用内","压力超预算") | S14: =IF(O14="超预算",999999,(24-B14)*1000000+M14+COUNTIF($A$14:A14,A14)/1000) | T14: =IF(AND(B14=MAXIFS($B$14:$B$23,$O$14:$O$23,"已知费用内"),S14=MINIFS($S$14:$S$23,$B$14:$B$23,B14,$O$14:$O$23,"已知费用内")),"临时推荐*",IF(O14="已知费用内","备选*","排除"))
A15: Chicago | B15: 24 | C15: =$B15*$B$6*$W$5 | D15: =$B15*1.12*MAX(0,$B$10-$B$9)*$X$5 | E15: =$B15*(234.0-IF($B$8="是",23,0)+MAX(0,$B$10-$B$9-4)*92) | F15: =$B15*180 | G15: =$B15*102 | H15: =$B15*12 | I15: =$B15*$Z$5 | J15: 0 | K15: =SUM(C15:J15) | L15: =K15*$B$7 | M15: =K15+L15 | N15: =MAX(0,$B$5-M15) | O15: =IF(M15<=$B$5,"已知费用内","超预算") | P15: 待询价—阻断 | Q15: =(K15+C15*20%)*(1+$B$7) | R15: =IF(Q15<=$B$5,"压力已知费用内","压力超预算") | S15: =IF(O15="超预算",999999,(24-B15)*1000000+M15+COUNTIF($A$14:A15,A15)/1000) | T15: =IF(AND(B15=MAXIFS($B$14:$B$23,$O$14:$O$23,"已知费用内"),S15=MINIFS($S$14:$S$23,$B$14:$B$23,B15,$O$14:$O$23,"已知费用内")),"临时推荐*",IF(O15="已知费用内","备选*","排除"))
A16: Denver | B16: 18 | C16: =$B16*$B$6*$W$6 | D16: =$B16*1.12*MAX(0,$B$10-$B$9)*$X$6 | E16: =$B16*(234.0-IF($B$8="是",23,0)+MAX(0,$B$10-$B$9-4)*92) | F16: =$B16*180 | G16: =$B16*102 | H16: =$B16*12 | I16: =$B16*$Z$6 | J16: 0 | K16: =SUM(C16:J16) | L16: =K16*$B$7 | M16: =K16+L16 | N16: =MAX(0,$B$5-M16) | O16: =IF(M16<=$B$5,"已知费用内","超预算") | P16: 待询价—阻断 | Q16: =(K16+C16*20%)*(1+$B$7) | R16: =IF(Q16<=$B$5,"压力已知费用内","压力超预算") | S16: =IF(O16="超预算",999999,(24-B16)*1000000+M16+COUNTIF($A$14:A16,A16)/1000) | T16: =IF(AND(B16=MAXIFS($B$14:$B$23,$O$14:$O$23,"已知费用内"),S16=MINIFS($S$14:$S$23,$B$14:$B$23,B16,$O$14:$O$23,"已知费用内")),"临时推荐*",IF(O16="已知费用内","备选*","排除"))
A17: Denver | B17: 24 | C17: =$B17*$B$6*$W$6 | D17: =$B17*1.12*MAX(0,$B$10-$B$9)*$X$6 | E17: =$B17*(234.0-IF($B$8="是",23,0)+MAX(0,$B$10-$B$9-4)*92) | F17: =$B17*180 | G17: =$B17*102 | H17: =$B17*12 | I17: =$B17*$Z$6 | J17: 0 | K17: =SUM(C17:J17) | L17: =K17*$B$7 | M17: =K17+L17 | N17: =MAX(0,$B$5-M17) | O17: =IF(M17<=$B$5,"已知费用内","超预算") | P17: 待询价—阻断 | Q17: =(K17+C17*20%)*(1+$B$7) | R17: =IF(Q17<=$B$5,"压力已知费用内","压力超预算") | S17: =IF(O17="超预算",999999,(24-B17)*1000000+M17+COUNTIF($A$14:A17,A17)/1000) | T17: =IF(AND(B17=MAXIFS($B$14:$B$23,$O$14:$O$23,"已知费用内"),S17=MINIFS($S$14:$S$23,$B$14:$B$23,B17,$O$14:$O$23,"已知费用内")),"临时推荐*",IF(O17="已知费用内","备选*","排除"))
A18: Phoenix | B18: 18 | C18: =$B18*$B$6*$W$7 | D18: =$B18*1.12*MAX(0,$B$10-$B$9)*$X$7 | E18: =$B18*(223.0-IF($B$8="是",22,0)+MAX(0,$B$10-$B$9-4)*86) | F18: =$B18*180 | G18: =$B18*95 | H18: =$B18*12 | I18: =$B18*$Z$7 | J18: 0 | K18: =SUM(C18:J18) | L18: =K18*$B$7 | M18: =K18+L18 | N18: =MAX(0,$B$5-M18) | O18: =IF(M18<=$B$5,"已知费用内","超预算") | P18: 待询价—阻断 | Q18: =(K18+C18*20%)*(1+$B$7) | R18: =IF(Q18<=$B$5,"压力已知费用内","压力超预算") | S18: =IF(O18="超预算",999999,(24-B18)*1000000+M18+COUNTIF($A$14:A18,A18)/1000) | T18: =IF(AND(B18=MAXIFS($B$14:$B$23,$O$14:$O$23,"已知费用内"),S18=MINIFS($S$14:$S$23,$B$14:$B$23,B18,$O$14:$O$23,"已知费用内")),"临时推荐*",IF(O18="已知费用内","备选*","排除"))
A19: Phoenix | B19: 24 | C19: =$B19*$B$6*$W$7 | D19: =$B19*1.12*MAX(0,$B$10-$B$9)*$X$7 | E19: =$B19*(223.0-IF($B$8="是",22,0)+MAX(0,$B$10-$B$9-4)*86) | F19: =$B19*180 | G19: =$B19*95 | H19: =$B19*12 | I19: =$B19*$Z$7 | J19: 0 | K19: =SUM(C19:J19) | L19: =K19*$B$7 | M19: =K19+L19 | N19: =MAX(0,$B$5-M19) | O19: =IF(M19<=$B$5,"已知费用内","超预算") | P19: 待询价—阻断 | Q19: =(K19+C19*20%)*(1+$B$7) | R19: =IF(Q19<=$B$5,"压力已知费用内","压力超预算") | S19: =IF(O19="超预算",999999,(24-B19)*1000000+M19+COUNTIF($A$14:A19,A19)/1000) | T19: =IF(AND(B19=MAXIFS($B$14:$B$23,$O$14:$O$23,"已知费用内"),S19=MINIFS($S$14:$S$23,$B$14:$B$23,B19,$O$14:$O$23,"已知费用内")),"临时推荐*",IF(O19="已知费用内","备选*","排除"))
A20: Boston | B20: 18 | C20: =$B20*$B$6*$W$8 | D20: =$B20*1.12*MAX(0,$B$10-$B$9)*$X$8 | E20: =$B20*(234.0-IF($B$8="是",23,0)+MAX(0,$B$10-$B$9-4)*92) | F20: =$B20*180 | G20: =$B20*102 | H20: =$B20*12 | I20: =$B20*$Z$8 | J20: 0 | K20: =SUM(C20:J20) | L20: =K20*$B$7 | M20: =K20+L20 | N20: =MAX(0,$B$5-M20) | O20: =IF(M20<=$B$5,"已知费用内","超预算") | P20: 待询价—阻断 | Q20: =(K20+C20*20%)*(1+$B$7) | R20: =IF(Q20<=$B$5,"压力已知费用内","压力超预算") | S20: =IF(O20="超预算",999999,(24-B20)*1000000+M20+COUNTIF($A$14:A20,A20)/1000) | T20: =IF(AND(B20=MAXIFS($B$14:$B$23,$O$14:$O$23,"已知费用内"),S20=MINIFS($S$14:$S$23,$B$14:$B$23,B20,$O$14:$O$23,"已知费用内")),"临时推荐*",IF(O20="已知费用内","备选*","排除"))
A21: Boston | B21: 24 | C21: =$B21*$B$6*$W$8 | D21: =$B21*1.12*MAX(0,$B$10-$B$9)*$X$8 | E21: =$B21*(234.0-IF($B$8="是",23,0)+MAX(0,$B$10-$B$9-4)*92) | F21: =$B21*180 | G21: =$B21*102 | H21: =$B21*12 | I21: =$B21*$Z$8 | J21: 0 | K21: =SUM(C21:J21) | L21: =K21*$B$7 | M21: =K21+L21 | N21: =MAX(0,$B$5-M21) | O21: =IF(M21<=$B$5,"已知费用内","超预算") | P21: 待询价—阻断 | Q21: =(K21+C21*20%)*(1+$B$7) | R21: =IF(Q21<=$B$5,"压力已知费用内","压力超预算") | S21: =IF(O21="超预算",999999,(24-B21)*1000000+M21+COUNTIF($A$14:A21,A21)/1000) | T21: =IF(AND(B21=MAXIFS($B$14:$B$23,$O$14:$O$23,"已知费用内"),S21=MINIFS($S$14:$S$23,$B$14:$B$23,B21,$O$14:$O$23,"已知费用内")),"临时推荐*",IF(O21="已知费用内","备选*","排除"))
A22: Seattle | B22: 18 | C22: =$B22*$B$6*$W$9 | D22: =$B22*1.12*MAX(0,$B$10-$B$9)*$X$9 | E22: =$B22*(234.0-IF($B$8="是",23,0)+MAX(0,$B$10-$B$9-4)*92) | F22: =$B22*180 | G22: =$B22*102 | H22: =$B22*12 | I22: =$B22*$Z$9 | J22: 0 | K22: =SUM(C22:J22) | L22: =K22*$B$7 | M22: =K22+L22 | N22: =MAX(0,$B$5-M22) | O22: =IF(M22<=$B$5,"已知费用内","超预算") | P22: 待询价—阻断 | Q22: =(K22+C22*20%)*(1+$B$7) | R22: =IF(Q22<=$B$5,"压力已知费用内","压力超预算") | S22: =IF(O22="超预算",999999,(24-B22)*1000000+M22+COUNTIF($A$14:A22,A22)/1000) | T22: =IF(AND(B22=MAXIFS($B$14:$B$23,$O$14:$O$23,"已知费用内"),S22=MINIFS($S$14:$S$23,$B$14:$B$23,B22,$O$14:$O$23,"已知费用内")),"临时推荐*",IF(O22="已知费用内","备选*","排除"))
A23: Seattle | B23: 24 | C23: =$B23*$B$6*$W$9 | D23: =$B23*1.12*MAX(0,$B$10-$B$9)*$X$9 | E23: =$B23*(234.0-IF($B$8="是",23,0)+MAX(0,$B$10-$B$9-4)*92) | F23: =$B23*180 | G23: =$B23*102 | H23: =$B23*12 | I23: =$B23*$Z$9 | J23: 0 | K23: =SUM(C23:J23) | L23: =K23*$B$7 | M23: =K23+L23 | N23: =MAX(0,$B$5-M23) | O23: =IF(M23<=$B$5,"已知费用内","超预算") | P23: 待询价—阻断 | Q23: =(K23+C23*20%)*(1+$B$7) | R23: =IF(Q23<=$B$5,"压力已知费用内","压力超预算") | S23: =IF(O23="超预算",999999,(24-B23)*1000000+M23+COUNTIF($A$14:A23,A23)/1000) | T23: =IF(AND(B23=MAXIFS($B$14:$B$23,$O$14:$O$23,"已知费用内"),S23=MINIFS($S$14:$S$23,$B$14:$B$23,B23,$O$14:$O$23,"已知费用内")),"临时推荐*",IF(O23="已知费用内","备选*","排除"))
A25: * 临时推荐只按已知费用执行题面排序；场地、茶歇、机构供餐正式报价、团体房量/早餐、资质、采购与资金均未完成，最终批准被阻断。场地等报价必须不超过“可用余额”（并考虑储备）后方可维持预算内。

Sheet Daily
A1: 逐日预算明细
A2: 修改黄色参数后，Options/Daily自动回算；Word/PPT/CSV为2026-10-23快照，参数变化后必须重新核对并导出。待询价项目未计入，任何“预算内”仅指已知费用。
A4: 城市 | B4: 人数 | C4: 日期 | D4: 日程/餐食 | E4: 机票 | F4: 住宿 | G4: 住宿税12% | H4: M&IE净额 | I4: 注册 | J4: 机构供餐 | K4: 总部↔DCA | L4: 当地交通 | M4: 场地/茶歇 | N4: 当日已知小计
A5: =IF(AND(C5>=Options!$B$9,C5<=Options!$B$10),"Chicago","") | B5: =IF(A5="","",18) | C5: 46296 | D5: =IF(A5="","",IF(C5=DATE(2026,11,29),"培训；注册午餐；早餐参数",IF(C5=DATE(2026,11,30),"培训；注册午餐",IF(C5=DATE(2026,12,1),"培训；注册午餐；机构晚餐",IF(C5=Options!$B$9,"抵达；"&IF(C5=DATE(2026,11,28),"机构晚餐","无统一供餐"),IF(C5=Options!$B$10,"返程；"&IF(C5=DATE(2026,12,2),"机构午餐","无统一供餐"),"差旅状态；无统一日程")))))) | E5: =IF(C5=Options!$B$9,Options!$C$14,0) | F5: =IF(AND(A5<>"",C5<Options!$B$10),B5*Options!$X$5,0) | G5: =F5*12% | H5: =IF(A5="",0,B5*(92*IF(OR(C5=Options!$B$9,C5=Options!$B$10),75%,100%)-IF(C5=DATE(2026,11,29),26+IF(Options!$B$8="是",23,0),0)-IF(C5=DATE(2026,11,30),26,0)-IF(C5=DATE(2026,12,1),64,0)-IF(C5=DATE(2026,11,28),38,0)-IF(C5=DATE(2026,12,2),26,0))) | I5: =IF(AND(C5>=DATE(2026,11,29),C5<=DATE(2026,12,1)),B5*60,0) | J5: =IF(A5="",0,B5*(IF(C5=DATE(2026,11,28),38,0)+IF(C5=DATE(2026,12,1),38,0)+IF(C5=DATE(2026,12,2),26,0))) | K5: =IF(C5=Options!$B$9,B5*12,0) | L5: =IF(C5=Options!$B$9,B5*Options!$Z$5,0) | M5: 0 | N5: =SUM(E5:M5)
A6: =IF(AND(C6>=Options!$B$9,C6<=Options!$B$10),"Chicago","") | B6: =IF(A6="","",18) | C6: 46297 | D6: =IF(A6="","",IF(C6=DATE(2026,11,29),"培训；注册午餐；早餐参数",IF(C6=DATE(2026,11,30),"培训；注册午餐",IF(C6=DATE(2026,12,1),"培训；注册午餐；机构晚餐",IF(C6=Options!$B$9,"抵达；"&IF(C6=DATE(2026,11,28),"机构晚餐","无统一供餐"),IF(C6=Options!$B$10,"返程；"&IF(C6=DATE(2026,12,2),"机构午餐","无统一供餐"),"差旅状态；无统一日程")))))) | E6: =IF(C6=Options!$B$9,Options!$C$14,0) | F6: =IF(AND(A6<>"",C6<Options!$B$10),B6*Options!$X$5,0) | G6: =F6*12% | H6: =IF(A6="",0,B6*(92*IF(OR(C6=Options!$B$9,C6=Options!$B$10),75%,100%)-IF(C6=DATE(2026,11,29),26+IF(Options!$B$8="是",23,0),0)-IF(C6=DATE(2026,11,30),26,0)-IF(C6=DATE(2026,12,1),64,0)-IF(C6=DATE(2026,11,28),38,0)-IF(C6=DATE(2026,12,2),26,0))) | I6: =IF(AND(C6>=DATE(2026,11,29),C6<=DATE(2026,12,1)),B6*60,0) | J6: =IF(A6="",0,B6*(IF(C6=DATE(2026,11,28),38,0)+IF(C6=DATE(2026,12,1),38,0)+IF(C6=DATE(2026,12,2),26,0))) | K6: =IF(C6=Options!$B$9,B6*12,0) | L6: =IF(C6=Options!$B$9,B6*Options!$Z$5,0) | M6: 0 | N6: =SUM(E6:M6)
A7: =IF(AND(C7>=Options!$B$9,C7<=Options!$B$10),"Chicago","") | B7: =IF(A7="","",18) | C7: 46298 | D7: =IF(A7="","",IF(C7=DATE(2026,11,29),"培训；注册午餐；早餐参数",IF(C7=DATE(2026,11,30),"培训；注册午餐",IF(C7=DATE(2026,12,1),"培训；注册午餐；机构晚餐",IF(C7=Options!$B$9,"抵达；"&IF(C7=DATE(2026,11,28),"机构晚餐","无统一供餐"),IF(C7=Options!$B$10,"返程；"&IF(C7=DATE(2026,12,2),"机构午餐","无统一供餐"),"差旅状态；无统一日程")))))) | E7: =IF(C7=Options!$B$9,Options!$C$14,0) | F7: =IF(AND(A7<>"",C7<Options!$B$10),B7*Options!$X$5,0) | G7: =F7*12% | H7: =IF(A7="",0,B7*(92*IF(OR(C7=Options!$B$9,C7=Options!$B$10),75%,100%)-IF(C7=DATE(2026,11,29),26+IF(Options!$B$8="是",23,0),0)-IF(C7=DATE(2026,11,30),26,0)-IF(C7=DATE(2026,12,1),64,0)-IF(C7=DATE(2026,11,28),38,0)-IF(C7=DATE(2026,12,2),26,0))) | I7: =IF(AND(C7>=DATE(2026,11,29),C7<=DATE(2026,12,1)),B7*60,0) | J7: =IF(A7="",0,B7*(IF(C7=DATE(2026,11,28),38,0)+IF(C7=DATE(2026,12,1),38,0)+IF(C7=DATE(2026,12,2),26,0))) | K7: =IF(C7=Options!$B$9,B7*12,0) | L7: =IF(C7=Options!$B$9,B7*Options!$Z$5,0) | M7: 0 | N7: =SUM(E7:M7)
A8: =IF(AND(C8>=Options!$B$9,C8<=Options!$B$10),"Chicago","") | B8: =IF(A8="","",18) | C8: 46299 | D8: =IF(A8="","",IF(C8=DATE(2026,11,29),"培训；注册午餐；早餐参数",IF(C8=DATE(2026,11,30),"培训；注册午餐",IF(C8=DATE(2026,12,1),"培训；注册午餐；机构晚餐",IF(C8=Options!$B$9,"抵达；"&IF(C8=DATE(2026,11,28),"机构晚餐","无统一供餐"),IF(C8=Options!$B$10,"返程；"&IF(C8=DATE(2026,12,2),"机构午餐","无统一供餐"),"差旅状态；无统一日程")))))) | E8: =IF(C8=Options!$B$9,Options!$C$14,0) | F8: =IF(AND(A8<>"",C8<Options!$B$10),B8*Options!$X$5,0) | G8: =F8*12% | H8: =IF(A8="",0,B8*(92*IF(OR(C8=Options!$B$9,C8=Options!$B$10),75%,100%)-IF(C8=DATE(2026,11,29),26+IF(Options!$B$8="是",23,0),0)-IF(C8=DATE(2026,11,30),26,0)-IF(C8=DATE(2026,12,1),64,0)-IF(C8=DATE(2026,11,28),38,0)-IF(C8=DATE(2026,12,2),26,0))) | I8: =IF(AND(C8>=DATE(2026,11,29),C8<=DATE(2026,12,1)),B8*60,0) | J8: =IF(A8="",0,B8*(IF(C8=DATE(2026,11,28),38,0)+IF(C8=DATE(2026,12,1),38,0)+IF(C8=DATE(2026,12,2),26,0))) | K8: =IF(C8=Options!$B$9,B8*12,0) | L8: =IF(C8=Options!$B$9,B8*Options!$Z$5,0) | M8: 0 | N8: =SUM(E8:M8)
A9: =IF(AND(C9>=Options!$B$9,C9<=Options!$B$10),"Chicago","") | B9: =IF(A9="","",18) | C9: 46300 | D9: =IF(A9="","",IF(C9=DATE(2026,11,29),"培训；注册午餐；早餐参数",IF(C9=DATE(2026,11,30),"培训；注册午餐",IF(C9=DATE(2026,12,1),"培训；注册午餐；机构晚餐",IF(C9=Options!$B$9,"抵达；"&IF(C9=DATE(2026,11,28),"机构晚餐","无统一供餐"),IF(C9=Options!$B$10,"返程；"&IF(C9=DATE(2026,12,2),"机构午餐","无统一供餐"),"差旅状态；无统一日程")))))) | E9: =IF(C9=Options!$B$9,Options!$C$14,0) | F9: =IF(AND(A9<>"",C9<Options!$B$10),B9*Options!$X$5,0) | G9: =F9*12% | H9: =IF(A9="",0,B9*(92*IF(OR(C9=Options!$B$9,C9=Options!$B$10),75%,100%)-IF(C9=DATE(2026,11,29),26+IF(Options!$B$8="是",23,0),0)-IF(C9=DATE(2026,11,30),26,0)-IF(C9=DATE(2026,12,1),64,0)-IF(C9=DATE(2026,11,28),38,0)-IF(C9=DATE(2026,12,2),26,0))) | I9: =IF(AND(C9>=DATE(2026,11,29),C9<=DATE(2026,12,1)),B9*60,0) | J9: =IF(A9="",0,B9*(IF(C9=DATE(2026,11,28),38,0)+IF(C9=DATE(2026,12,1),38,0)+IF(C9=DATE(2026,12,2),26,0))) | K9: =IF(C9=Options!$B$9,B9*12,0) | L9: =IF(C9=Options!$B$9,B9*Options!$Z$5,0) | M9: 0 | N9: =SUM(E9:M9)
A10: =IF(AND(C10>=Options!$B$9,C10<=Options!$B$10),"Chicago","") | B10: =IF(A10="","",18) | C10: 46301 | D10: =IF(A10="","",IF(C10=DATE(2026,11,29),"培训；注册午餐；早餐参数",IF(C10=DATE(2026,11,30),"培训；注册午餐",IF(C10=DATE(2026,12,1),"培训；注册午餐；机构晚餐",IF(C10=Options!$B$9,"抵达；"&IF(C10=DATE(2026,11,28),"机构晚餐","无统一供餐"),IF(C10=Options!$B$10,"返程；"&IF(C10=DATE(2026,12,2),"机构午餐","无统一供餐"),"差旅状态；无统一日程")))))) | E10: =IF(C10=Options!$B$9,Options!$C$14,0) | F10: =IF(AND(A10<>"",C10<Options!$B$10),B10*Options!$X$5,0) | G10: =F10*12% | H10: =IF(A10="",0,B10*(92*IF(OR(C10=Options!$B$9,C10=Options!$B$10),75%,100%)-IF(C10=DATE(2026,11,29),26+IF(Options!$B$8="是",23,0),0)-IF(C10=DATE(2026,11,30),26,0)-IF(C10=DATE(2026,12,1),64,0)-IF(C10=DATE(2026,11,28),38,0)-IF(C10=DATE(2026,12,2),26,0))) | I10: =IF(AND(C10>=DATE(2026,11,29),C10<=DATE(2026,12,1)),B10*60,0) | J10: =IF(A10="",0,B10*(IF(C10=DATE(2026,11,28),38,0)+IF(C10=DATE(2026,12,1),38,0)+IF(C10=DATE(2026,12,2),26,0))) | K10: =IF(C10=Options!$B$9,B10*12,0) | L10: =IF(C10=Options!$B$9,B10*Options!$Z$5,0) | M10: 0 | N10: =SUM(E10:M10)
A11: =IF(AND(C11>=Options!$B$9,C11<=Options!$B$10),"Chicago","") | B11: =IF(A11="","",18) | C11: 46302 | D11: =IF(A11="","",IF(C11=DATE(2026,11,29),"培训；注册午餐；早餐参数",IF(C11=DATE(2026,11,30),"培训；注册午餐",IF(C11=DATE(2026,12,1),"培训；注册午餐；机构晚餐",IF(C11=Options!$B$9,"抵达；"&IF(C11=DATE(2026,11,28),"机构晚餐","无统一供餐"),IF(C11=Options!$B$10,"返程；"&IF(C11=DATE(2026,12,2),"机构午餐","无统一供餐"),"差旅状态；无统一日程")))))) | E11: =IF(C11=Options!$B$9,Options!$C$14,0) | F11: =IF(AND(A11<>"",C11<Options!$B$10),B11*Options!$X$5,0) | G11: =F11*12% | H11: =IF(A11="",0,B11*(92*IF(OR(C11=Options!$B$9,C11=Options!$B$10),75%,100%)-IF(C11=DATE(2026,11,29),26+IF(Options!$B$8="是",23,0),0)-IF(C11=DATE(2026,11,30),26,0)-IF(C11=DATE(2026,12,1),64,0)-IF(C11=DATE(2026,11,28),38,0)-IF(C11=DATE(2026,12,2),26,0))) | I11: =IF(AND(C11>=DATE(2026,11,29),C11<=DATE(2026,12,1)),B11*60,0) | J11: =IF(A11="",0,B11*(IF(C11=DATE(2026,11,28),38,0)+IF(C11=DATE(2026,12,1),38,0)+IF(C11=DATE(2026,12,2),26,0))) | K11: =IF(C11=Options!$B$9,B11*12,0) | L11: =IF(C11=Options!$B$9,B11*Options!$Z$5,0) | M11: 0 | N11: =SUM(E11:M11)
A12: =IF(AND(C12>=Options!$B$9,C12<=Options!$B$10),"Chicago","") | B12: =IF(A12="","",18) | C12: 46303 | D12: =IF(A12="","",IF(C12=DATE(2026,11,29),"培训；注册午餐；早餐参数",IF(C12=DATE(2026,11,30),"培训；注册午餐",IF(C12=DATE(2026,12,1),"培训；注册午餐；机构晚餐",IF(C12=Options!$B$9,"抵达；"&IF(C12=DATE(2026,11,28),"机构晚餐","无统一供餐"),IF(C12=Options!$B$10,"返程；"&IF(C12=DATE(2026,12,2),"机构午餐","无统一供餐"),"差旅状态；无统一日程")))))) | E12: =IF(C12=Options!$B$9,Options!$C$14,0) | F12: =IF(AND(A12<>"",C12<Options!$B$10),B12*Options!$X$5,0) | G12: =F12*12% | H12: =IF(A12="",0,B12*(92*IF(OR(C12=Options!$B$9,C12=Options!$B$10),75%,100%)-IF(C12=DATE(2026,11,29),26+IF(Options!$B$8="是",23,0),0)-IF(C12=DATE(2026,11,30),26,0)-IF(C12=DATE(2026,12,1),64,0)-IF(C12=DATE(2026,11,28),38,0)-IF(C12=DATE(2026,12,2),26,0))) | I12: =IF(AND(C12>=DATE(2026,11,29),C12<=DATE(2026,12,1)),B12*60,0) | J12: =IF(A12="",0,B12*(IF(C12=DATE(2026,11,28),38,0)+IF(C12=DATE(2026,12,1),38,0)+IF(C12=DATE(2026,12,2),26,0))) | K12: =IF(C12=Options!$B$9,B12*12,0) | L12: =IF(C12=Options!$B$9,B12*Options!$Z$5,0) | M12: 0 | N12: =SUM(E12:M12)
A13: =IF(AND(C13>=Options!$B$9,C13<=Options!$B$10),"Chicago","") | B13: =IF(A13="","",18) | C13: 46304 | D13: =IF(A13="","",IF(C13=DATE(2026,11,29),"培训；注册午餐；早餐参数",IF(C13=DATE(2026,11,30),"培训；注册午餐",IF(C13=DATE(2026,12,1),"培训；注册午餐；机构晚餐",IF(C13=Options!$B$9,"抵达；"&IF(C13=DATE(2026,11,28),"机构晚餐","无统一供餐"),IF(C13=Options!$B$10,"返程；"&IF(C13=DATE(2026,12,2),"机构午餐","无统一供餐"),"差旅状态；无统一日程")))))) | E13: =IF(C13=Options!$B$9,Options!$C$14,0) | F13: =IF(AND(A13<>"",C13<Options!$B$10),B13*Options!$X$5,0) | G13: =F13*12% | H13: =IF(A13="",0,B13*(92*IF(OR(C13=Options!$B$9,C13=Options!$B$10),75%,100%)-IF(C13=DATE(2026,11,29),26+IF(Options!$B$8="是",23,0),0)-IF(C13=DATE(2026,11,30),26,0)-IF(C13=DATE(2026,12,1),64,0)-IF(C13=DATE(2026,11,28),38,0)-IF(C13=DATE(2026,12,2),26,0))) | I13: =IF(AND(C13>=DATE(2026,11,29),C13<=DATE(2026,12,1)),B13*60,0) | J13: =IF(A13="",0,B13*(IF(C13=DATE(2026,11,28),38,0)+IF(C13=DATE(2026,12,1),38,0)+IF(C13=DATE(2026,12,2),26,0))) | K13: =IF(C13=Options!$B$9,B13*12,0) | L13: =IF(C13=Options!$B$9,B13*Options!$Z$5,0) | M13: 0 | N13: =SUM(E13:M13)
A14: =IF(AND(C14>=Options!$B$9,C14<=Options!$B$10),"Chicago","") | B14: =IF(A14="","",18) | C14: 46305 | D14: =IF(A14="","",IF(C14=DATE(2026,11,29),"培训；注册午餐；早餐参数",IF(C14=DATE(2026,11,30),"培训；注册午餐",IF(C14=DATE(2026,12,1),"培训；注册午餐；机构晚餐",IF(C14=Options!$B$9,"抵达；"&IF(C14=DATE(2026,11,28),"机构晚餐","无统一供餐"),IF(C14=Options!$B$10,"返程；"&IF(C14=DATE(2026,12,2),"机构午餐","无统一供餐"),"差旅状态；无统一日程")))))) | E14: =IF(C14=Options!$B$9,Options!$C$14,0) | F14: =IF(AND(A14<>"",C14<Options!$B$10),B14*Options!$X$5,0) | G14: =F14*12% | H14: =IF(A14="",0,B14*(92*IF(OR(C14=Options!$B$9,C14=Options!$B$10),75%,100%)-IF(C14=DATE(2026,11,29),26+IF(Options!$B$8="是",23,0),0)-IF(C14=DATE(2026,11,30),26,0)-IF(C14=DATE(2026,12,1),64,0)-IF(C14=DATE(2026,11,28),38,0)-IF(C14=DATE(2026,12,2),26,0))) | I14: =IF(AND(C14>=DATE(2026,11,29),C14<=DATE(2026,12,1)),B14*60,0) | J14: =IF(A14="",0,B14*(IF(C14=DATE(2026,11,28),38,0)+IF(C14=DATE(2026,12,1),38,0)+IF(C14=DATE(2026,12,2),26,0))) | K14: =IF(C14=Options!$B$9,B14*12,0) | L14: =IF(C14=Options!$B$9,B14*Options!$Z$5,0) | M14: 0 | N14: =SUM(E14:M14)
A15: =IF(AND(C15>=Options!$B$9,C15<=Options!$B$10),"Chicago","") | B15: =IF(A15="","",18) | C15: 46306 | D15: =IF(A15="","",IF(C15=DATE(2026,11,29),"培训；注册午餐；早餐参数",IF(C15=DATE(2026,11,30),"培训；注册午餐",IF(C15=DATE(2026,12,1),"培训；注册午餐；机构晚餐",IF(C15=Options!$B$9,"抵达；"&IF(C15=DATE(2026,11,28),"机构晚餐","无统一供餐"),IF(C15=Options!$B$10,"返程；"&IF(C15=DATE(2026,12,2),"机构午餐","无统一供餐"),"差旅状态；无统一日程")))))) | E15: =IF(C15=Options!$B$9,Options!$C$14,0) | F15: =IF(AND(A15<>"",C15<Options!$B$10),B15*Options!$X$5,0) | G15: =F15*12% | H15: =IF(A15="",0,B15*(92*IF(OR(C15=Options!$B$9,C15=Options!$B$10),75%,100%)-IF(C15=DATE(2026,11,29),26+IF(Options!$B$8="是",23,0),0)-IF(C15=DATE(2026,11,30),26,0)-IF(C15=DATE(2026,12,1),64,0)-IF(C15=DATE(2026,11,28),38,0)-IF(C15=DATE(2026,12,2),26,0))) | I15: =IF(AND(C15>=DATE(2026,11,29),C15<=DATE(2026,12,1)),B15*60,0) | J15: =IF(A15="",0,B15*(IF(C15=DATE(2026,11,28),38,0)+IF(C15=DATE(2026,12,1),38,0)+IF(C15=DATE(2026,12,2),26,0))) | K15: =IF(C15=Options!$B$9,B15*12,0) | L15: =IF(C15=Options!$B$9,B15*Options!$Z$5,0) | M15: 0 | N15: =SUM(E15:M15)
A16: =IF(AND(C16>=Options!$B$9,C16<=Options!$B$10),"Chicago","") | B16: =IF(A16="","",18) | C16: 46307 | D16: =IF(A16="","",IF(C16=DATE(2026,11,29),"培训；注册午餐；早餐参数",IF(C16=DATE(2026,11,30),"培训；注册午餐",IF(C16=DATE(2026,12,1),"培训；注册午餐；机构晚餐",IF(C16=Options!$B$9,"抵达；"&IF(C16=DATE(2026,11,28),"机构晚餐","无统一供餐"),IF(C16=Options!$B$10,"返程；"&IF(C16=DATE(2026,12,2),"机构午餐","无统一供餐"),"差旅状态；无统一日程")))))) | E16: =IF(C16=Options!$B$9,Options!$C$14,0) | F16: =IF(AND(A16<>"",C16<Options!$B$10),B16*Options!$X$5,0) | G16: =F16*12% | H16: =IF(A16="",0,B16*(92*IF(OR(C16=Options!$B$9,C16=Options!$B$10),75%,100%)-IF(C16=DATE(2026,11,29),26+IF(Options!$B$8="是",23,0),0)-IF(C16=DATE(2026,11,30),26,0)-IF(C16=DATE(2026,12,1),64,0)-IF(C16=DATE(2026,11,28),38,0)-IF(C16=DATE(2026,12,2),26,0))) | I16: =IF(AND(C16>=DATE(2026,11,29),C16<=DATE(2026,12,1)),B16*60,0) | J16: =IF(A16="",0,B16*(IF(C16=DATE(2026,11,28),38,0)+IF(C16=DATE(2026,12,1),38,0)+IF(C16=DATE(2026,12,2),26,0))) | K16: =IF(C16=Options!$B$9,B16*12,0) | L16: =IF(C16=Options!$B$9,B16*Options!$Z$5,0) | M16: 0 | N16: =SUM(E16:M16)
... A369: =IF(AND(C369>=Options!$B$9,C369<=Options!$B$10),"Chicago","") | B369: =IF(A369="","",18) | C369: 46660 | D369: =IF(A369="","",IF(C369=DATE(2026,11,29),"培训；注册午餐；早餐参数",IF(C369=DATE(2026,11,30),"培训；注册午餐",IF(C369=DATE(2026,12,1),"培训；注册午餐；机构晚餐",IF(C369=Options!$B$9,"抵达；"&IF(C369=DATE(2026,11,28),"机构晚餐","无统一供餐"),IF(C369=Options!$B$10,"返程；"&IF(C369=DATE(2026,12,2),"机构午餐","无统一供餐"),"差旅状态；无统一日程")))))) | E369: =IF(C369=Options!$B$9,Options!$C$14,0) | F369: =IF(AND(A369<>"",C369<Options!$B$10),B369*Options!$X$5,0) | G369: =F369*12% | H369: =IF(A369="",0,B369*(92*IF(OR(C369=Options!$B$9,C369=Options!$B$10),75%,100%)-IF(C369=DATE(2026,11,29),26+IF(Options!$B$8="是",23,0),0)-IF(C369=DATE(2026,11,30),26,0)-IF(C369=DATE(2026,12,1),64,0)-IF(C369=DATE(2026,11,28),38,0)-IF(C369=DATE(2026,12,2),26,0))) | I369: =IF(AND(C369>=DATE(2026,11,29),C369<=DATE(2026,12,1)),B369*60,0) | J369: =IF(A369="",0,B369*(IF(C369=DATE(2026,11,28),38,0)+IF(C369=DATE(2026,12,1),38,0)+IF(C369=DATE(2026,12,2),26,0))) | K369: =IF(C369=Options!$B$9,B369*12,0) | L369: =IF(C369=Options!$B$9,B369*Options!$Z$5,0) | M369: 0 | N369: =SUM(E369:M369)
A370: =IF(AND(C370>=Options!$B$9,C370<=Options!$B$10),"Chicago","") | B370: =IF(A370="","",24) | C370: 46296 | D370: =IF(A370="","",IF(C370=DATE(2026,11,29),"培训；注册午餐；早餐参数",IF(C370=DATE(2026,11,30),"培训；注册午餐",IF(C370=DATE(2026,12,1),"培训；注册午餐；机构晚餐",IF(C370=Options!$B$9,"抵达；"&IF(C370=DATE(2026,11,28),"机构晚餐","无统一供餐"),IF(C370=Options!$B$10,"返程；"&IF(C370=DATE(2026,12,2),"机构午餐","无统一供餐"),"差旅状态；无统一日程")))))) | E370: =IF(C370=Options!$B$9,Options!$C$15,0) | F370: =IF(AND(A370<>"",C370<Options!$B$10),B370*Options!$X$5,0) | G370: =F370*12% | H370: =IF(A370="",0,B370*(92*IF(OR(C370=Options!$B$9,C370=Options!$B$10),75%,100%)-IF(C370=DATE(2026,11,29),26+IF(Options!$B$8="是",23,0),0)-IF(C370=DATE(2026,11,30),26,0)-IF(C370=DATE(2026,12,1),64,0)-IF(C370=DATE(2026,11,28),38,0)-IF(C370=DATE(2026,12,2),26,0))) | I370: =IF(AND(C370>=DATE(2026,11,29),C370<=DATE(2026,12,1)),B370*60,0) | J370: =IF(A370="",0,B370*(IF(C370=DATE(2026,11,28),38,0)+IF(C370=DATE(2026,12,1),38,0)+IF(C370=DATE(2026,12,2),26,0))) | K370: =IF(C370=Options!$B$9,B370*12,0) | L370: =IF(C370=Options!$B$9,B370*Options!$Z$5,0) | M370: 0 | N370: =SUM(E370:M370)
A371: =IF(AND(C371>=Options!$B$9,C371<=Options!$B$10),"Chicago","") | B371: =IF(A371="","",24) | C371: 46297 | D371: =IF(A371="","",IF(C371=DATE(2026,11,29),"培训；注册午餐；早餐参数",IF(C371=DATE(2026,11,30),"培训；注册午餐",IF(C371=DATE(2026,12,1),"培训；注册午餐；机构晚餐",IF(C371=Options!$B$9,"抵达；"&IF(C371=DATE(2026,11,28),"机构晚餐","无统一供餐"),IF(C371=Options!$B$10,"返程；"&IF(C371=DATE(2026,12,2),"机构午餐","无统一供餐"),"差旅状态；无统一日程")))))) | E371: =IF(C371=Options!$B$9,Options!$C$15,0) | F371: =IF(AND(A371<>"",C371<Options!$B$10),B371*Options!$X$5,0) | G371: =F371*12% | H371: =IF(A371="",0,B371*(92*IF(OR(C371=Options!$B$9,C371=Options!$B$10),75%,100%)-IF(C371=DATE(2026,11,29),26+IF(Options!$B$8="是",23,0),0)-IF(C371=DATE(2026,11,30),26,0)-IF(C371=DATE(2026,12,1),64,0)-IF(C371=DATE(2026,11,28),38,0)-IF(C371=DATE(2026,12,2),26,0))) | I371: =IF(AND(C371>=DATE(2026,11,29),C371<=DATE(2026,12,1)),B371*60,0) | J371: =IF(A371="",0,B371*(IF(C371=DATE(2026,11,28),38,0)+IF(C371=DATE(2026,12,1),38,0)+IF(C371=DATE(2026,12,2),26,0))) | K371: =IF(C371=Options!$B$9,B371*12,0) | L371: =IF(C371=Options!$B$9,B371*Options!$Z$5,0) | M371: 0 | N371: =SUM(E371:M371)
A372: =IF(AND(C372>=Options!$B$9,C372<=Options!$B$10),"Chicago","") | B372: =IF(A372="","",24) | C372: 46298 | D372: =IF(A372="","",IF(C372=DATE(2026,11,29),"培训；注册午餐；早餐参数",IF(C372=DATE(2026,11,30),"培训；注册午餐",IF(C372=DATE(2026,12,1),"培训；注册午餐；机构晚餐",IF(C372=Options!$B$9,"抵达；"&IF(C372=DATE(2026,11,28),"机构晚餐","无统一供餐"),IF(C372=Options!$B$10,"返程；"&IF(C372=DATE(2026,12,2),"机构午餐","无统一供餐"),"差旅状态；无统一日程")))))) | E372: =IF(C372=Options!$B$9,Options!$C$15,0) | F372: =IF(AND(A372<>"",C372<Options!$B$10),B372*Options!$X$5,0) | G372: =F372*12% | H372: =IF(A372="",0,B372*(92*IF(OR(C372=Options!$B$9,C372=Options!$B$10),75%,100%)-IF(C372=DATE(2026,11,29),26+IF(Options!$B$8="是",23,0),0)-IF(C372=DATE(2026,11,30),26,0)-IF(C372=DATE(2026,12,1),64,0)-IF(C372=DATE(2026,11,28),38,0)-IF(C372=DATE(2026,12,2),26,0))) | I372: =IF(AND(C372>=DATE(2026,11,29),C372<=DATE(2026,12,1)),B372*60,0) | J372: =IF(A372="",0,B372*(IF(C372=DATE(2026,11,28),38,0)+IF(C372=DATE(2026,12,1),38,0)+IF(C372=DATE(2026,12,2),26,0))) | K372: =IF(C372=Options!$B$9,B372*12,0) | L372: =IF(C372=Options!$B$9,B372*Options!$Z$5,0) | M372: 0 | N372: =SUM(E372:M372)
A373: =IF(AND(C373>=Options!$B$9,C373<=Options!$B$10),"Chicago","") | B373: =IF(A373="","",24) | C373: 46299 | D373: =IF(A373="","",IF(C373=DATE(2026,11,29),"培训；注册午餐；早餐参数",IF(C373=DATE(2026,11,30),"培训；注册午餐",IF(C373=DATE(2026,12,1),"培训；注册午餐；机构晚餐",IF(C373=Options!$B$9,"抵达；"&IF(C373=DATE(2026,11,28),"机构晚餐","无统一供餐"),IF(C373=Options!$B$10,"返程；"&IF(C373=DATE(2026,12,2),"机构午餐","无统一供餐"),"差旅状态；无统一日程")))))) | E373: =IF(C373=Options!$B$9,Options!$C$15,0) | F373: =IF(AND(A373<>"",C373<Options!$B$10),B373*Options!$X$5,0) | G373: =F373*12% | H373: =IF(A373="",0,B373*(92*IF(OR(C373=Options!$B$9,C373=Options!$B$10),75%,100%)-IF(C373=DATE(2026,11,29),26+IF(Options!$B$8="是",23,0),0)-IF(C373=DATE(2026,11,30),26,0)-IF(C373=DATE(2026,12,1),64,0)-IF(C373=DATE(2026,11,28),38,0)-IF(C373=DATE(2026,12,2),26,0))) | I373: =IF(AND(C373>=DATE(2026,11,29),C373<=DATE(2026,12,1)),B373*60,0) | J373: =IF(A373="",0,B373*(IF(C373=DATE(2026,11,28),38,0)+IF(C373=DATE(2026,12,1),38,0)+IF(C373=DATE(2026,12,2),26,0))) | K373: =IF(C373=Options!$B$9,B373*12,0) | L373: =IF(C373=Options!$B$9,B373*Options!$Z$5,0) | M373: 0 | N373: =SUM(E373:M373)
A374: =IF(AND(C374>=Options!$B$9,C374<=Options!$B$10),"Chicago","") | B374: =IF(A374="","",24) | C374: 46300 | D374: =IF(A374="","",IF(C374=DATE(2026,11,29),"培训；注册午餐；早餐参数",IF(C374=DATE(2026,11,30),"培训；注册午餐",IF(C374=DATE(2026,12,1),"培训；注册午餐；机构晚餐",IF(C374=Options!$B$9,"抵达；"&IF(C374=DATE(2026,11,28),"机构晚餐","无统一供餐"),IF(C374=Options!$B$10,"返程；"&IF(C374=DATE(2026,12,2),"机构午餐","无统一供餐"),"差旅状态；无统一日程")))))) | E374: =IF(C374=Options!$B$9,Options!$C$15,0) | F374: =IF(AND(A374<>"",C374<Options!$B$10),B374*Options!$X$5,0) | G374: =F374*12% | H374: =IF(A374="",0,B374*(92*IF(OR(C374=Options!$B$9,C374=Options!$B$10),75%,100%)-IF(C374=DATE(2026,11,29),26+IF(Options!$B$8="是",23,0),0)-IF(C374=DATE(2026,11,30),26,0)-IF(C374=DATE(2026,12,1),64,0)-IF(C374=DATE(2026,11,28),38,0)-IF(C374=DATE(2026,12,2),26,0))) | I374: =IF(AND(C374>=DATE(2026,11,29),C374<=DATE(2026,12,1)),B374*60,0) | J374: =IF(A374="",0,B374*(IF(C374=DATE(2026,11,28),38,0)+IF(C374=DATE(2026,12,1),38,0)+IF(C374=DATE(2026,12,2),26,0))) | K374: =IF(C374=Options!$B$9,B374*12,0) | L374: =IF(C374=Options!$B$9,B374*Options!$Z$5,0) | M374: 0 | N374: =SUM(E374:M374)
A375: =IF(AND(C375>=Options!$B$9,C375<=Options!$B$10),"Chicago","") | B375: =IF(A375="","",24) | C375: 46301 | D375: =IF(A375="","",IF(C375=DATE(2026,11,29),"培训；注册午餐；早餐参数",IF(C375=DATE(2026,11,30),"培训；注册午餐",IF(C375=DATE(2026,12,1),"培训；注册午餐；机构晚餐",IF(C375=Options!$B$9,"抵达；"&IF(C375=DATE(2026,11,28),"机构晚餐","无统一供餐"),IF(C375=Options!$B$10,"返程；"&IF(C375=DATE(2026,12,2),"机构午餐","无统一供餐"),"差旅状态；无统一日程")))))) | E375: =IF(C375=Options!$B$9,Options!$C$15,0) | F375: =IF(AND(A375<>"",C375<Options!$B$10),B375*Options!$X$5,0) | G375: =F375*12% | H375: =IF(A375="",0,B375*(92*IF(OR(C375=Options!$B$9,C375=Options!$B$10),75%,100%)-IF(C375=DATE(2026,11,29),26+IF(Options!$B$8="是",23,0),0)-IF(C375=DATE(2026,11,30),26,0)-IF(C375=DATE(2026,12,1),64,0)-IF(C375=DATE(2026,11,28),38,0)-IF(C375=DATE(2026,12,2),26,0))) | I375: =IF(AND(C375>=DATE(2026,11,29),C375<=DATE(2026,12,1)),B375*60,0) | J375: =IF(A375="",0,B375*(IF(C375=DATE(2026,11,28),38,0)+IF(C375=DATE(2026,12,1),38,0)+IF(C375=DATE(2026,12,2),26,0))) | K375: =IF(C375=Options!$B$9,B375*12,0) | L375: =IF(C375=Options!$B$9,B375*Options!$Z$5,0) | M375: 0 | N375: =SUM(E375:M375)
A376: =IF(AND(C376>=Options!$B$9,C376<=Options!$B$10),"Chicago","") | B376: =IF(A376="","",24) | C376: 46302 | D376: =IF(A376="","",IF(C376=DATE(2026,11,29),"培训；注册午餐；早餐参数",IF(C376=DATE(2026,11,30),"培训；注册午餐",IF(C376=DATE(2026,12,1),"培训；注册午餐；机构晚餐",IF(C376=Options!$B$9,"抵达；"&IF(C376=DATE(2026,11,28),"机构晚餐","无统一供餐"),IF(C376=Options!$B$10,"返程；"&IF(C376=DATE(2026,12,2),"机构午餐","无统一供餐"),"差旅状态；无统一日程")))))) | E376: =IF(C376=Options!$B$9,Options!$C$15,0) | F376: =IF(AND(A376<>"",C376<Options!$B$10),B376*Options!$X$5,0) | G376: =F376*12% | H376: =IF(A376="",0,B376*(92*IF(OR(C376=Options!$B$9,C376=Options!$B$10),75%,100%)-IF(C376=DATE(2026,11,29),26+IF(Options!$B$8="是",23,0),0)-IF(C376=DATE(2026,11,30),26,0)-IF(C376=DATE(2026,12,1),64,0)-IF(C376=DATE(2026,11,28),38,0)-IF(C376=DATE(2026,12,2),26,0))) | I376: =IF(AND(C376>=DATE(2026,11,29),C376<=DATE(2026,12,1)),B376*60,0) | J376: =IF(A376="",0,B376*(IF(C376=DATE(2026,11,28),38,0)+IF(C376=DATE(2026,12,1),38,0)+IF(C376=DATE(2026,12,2),26,0))) | K376: =IF(C376=Options!$B$9,B376*12,0) | L376: =IF(C376=Options!$B$9,B376*Options!$Z$5,0) | M376: 0 | N376: =SUM(E376:M376)
A377: =IF(AND(C377>=Options!$B$9,C377<=Options!$B$10),"Chicago","") | B377: =IF(A377="","",24) | C377: 46303 | D377: =IF(A377="","",IF(C377=DATE(2026,11,29),"培训；注册午餐；早餐参数",IF(C377=DATE(2026,11,30),"培训；注册午餐",IF(C377=DATE(2026,12,1),"培训；注册午餐；机构晚餐",IF(C377=Options!$B$9,"抵达；"&IF(C377=DATE(2026,11,28),"机构晚餐","无统一供餐"),IF(C377=Options!$B$10,"返程；"&IF(C377=DATE(2026,12,2),"机构午餐","无统一供餐"),"差旅状态；无统一日程")))))) | E377: =IF(C377=Options!$B$9,Options!$C$15,0) | F377: =IF(AND(A377<>"",C377<Options!$B$10),B377*Options!$X$5,0) | G377: =F377*12% | H377: =IF(A377="",0,B377*(92*IF(OR(C377=Options!$B$9,C377=Options!$B$10),75%,100%)-IF(C377=DATE(2026,11,29),26+IF(Options!$B$8="是",23,0),0)-IF(C377=DATE(2026,11,30),26,0)-IF(C377=DATE(2026,12,1),64,0)-IF(C377=DATE(2026,11,28),38,0)-IF(C377=DATE(2026,12,2),26,0))) | I377: =IF(AND(C377>=DATE(2026,11,29),C377<=DATE(2026,12,1)),B377*60,0) | J377: =IF(A377="",0,B377*(IF(C377=DATE(2026,11,28),38,0)+IF(C377=DATE(2026,12,1),38,0)+IF(C377=DATE(2026,12,2),26,0))) | K377: =IF(C377=Options!$B$9,B377*12,0) | L377: =IF(C377=Options!$B$9,B377*Options!$Z$5,0) | M377: 0 | N377: =SUM(E377:M377)
A378: =IF(AND(C378>=Options!$B$9,C378<=Options!$B$10),"Chicago","") | B378: =IF(A378="","",24) | C378: 46304 | D378: =IF(A378="","",IF(C378=DATE(2026,11,29),"培训；注册午餐；早餐参数",IF(C378=DATE(2026,11,30),"培训；注册午餐",IF(C378=DATE(2026,12,1),"培训；注册午餐；机构晚餐",IF(C378=Options!$B$9,"抵达；"&IF(C378=DATE(2026,11,28),"机构晚餐","无统一供餐"),IF(C378=Options!$B$10,"返程；"&IF(C378=DATE(2026,12,2),"机构午餐","无统一供餐"),"差旅状态；无统一日程")))))) | E378: =IF(C378=Options!$B$9,Options!$C$15,0) | F378: =IF(AND(A378<>"",C378<Options!$B$10),B378*Options!$X$5,0) | G378: =F378*12% | H378: =IF(A378="",0,B378*(92*IF(OR(C378=Options!$B$9,C378=Options!$B$10),75%,100%)-IF(C378=DATE(2026,11,29),26+IF(Options!$B$8="是",23,0),0)-IF(C378=DATE(2026,11,30),26,0)-IF(C378=DATE(2026,12,1),64,0)-IF(C378=DATE(2026,11,28),38,0)-IF(C378=DATE(2026,12,2),26,0))) | I378: =IF(AND(C378>=DATE(2026,11,29),C378<=DATE(2026,12,1)),B378*60,0) | J378: =IF(A378="",0,B378*(IF(C378=DATE(2026,11,28),38,0)+IF(C378=DATE(2026,12,1),38,0)+IF(C378=DATE(2026,12,2),26,0))) | K378: =IF(C378=Options!$B$9,B378*12,0) | L378: =IF(C378=Options!$B$9,B378*Options!$Z$5,0) | M378: 0 | N378: =SUM(E378:M378)
A379: =IF(AND(C379>=Options!$B$9,C379<=Options!$B$10),"Chicago","") | B379: =IF(A379="","",24) | C379: 46305 | D379: =IF(A379="","",IF(C379=DATE(2026,11,29),"培训；注册午餐；早餐参数",IF(C379=DATE(2026,11,30),"培训；注册午餐",IF(C379=DATE(2026,12,1),"培训；注册午餐；机构晚餐",IF(C379=Options!$B$9,"抵达；"&IF(C379=DATE(2026,11,28),"机构晚餐","无统一供餐"),IF(C379=Options!$B$10,"返程；"&IF(C379=DATE(2026,12,2),"机构午餐","无统一供餐"),"差旅状态；无统一日程")))))) | E379: =IF(C379=Options!$B$9,Options!$C$15,0) | F379: =IF(AND(A379<>"",C379<Options!$B$10),B379*Options!$X$5,0) | G379: =F379*12% | H379: =IF(A379="",0,B379*(92*IF(OR(C379=Options!$B$9,C379=Options!$B$10),75%,100%)-IF(C379=DATE(2026,11,29),26+IF(Options!$B$8="是",23,0),0)-IF(C379=DATE(2026,11,30),26,0)-IF(C379=DATE(2026,12,1),64,0)-IF(C379=DATE(2026,11,28),38,0)-IF(C379=DATE(2026,12,2),26,0))) | I379: =IF(AND(C379>=DATE(2026,11,29),C379<=DATE(2026,12,1)),B379*60,0) | J379: =IF(A379="",0,B379*(IF(C379=DATE(2026,11,28),38,0)+IF(C379=DATE(2026,12,1),38,0)+IF(C379=DATE(2026,12,2),26,0))) | K379: =IF(C379=Options!$B$9,B379*12,0) | L379: =IF(C379=Options!$B$9,B379*Options!$Z$5,0) | M379: 0 | N379: =SUM(E379:M379)
A380: =IF(AND(C380>=Options!$B$9,C380<=Options!$B$10),"Chicago","") | B380: =IF(A380="","",24) | C380: 46306 | D380: =IF(A380="","",IF(C380=DATE(2026,11,29),"培训；注册午餐；早餐参数",IF(C380=DATE(2026,11,30),"培训；注册午餐",IF(C380=DATE(2026,12,1),"培训；注册午餐；机构晚餐",IF(C380=Options!$B$9,"抵达；"&IF(C380=DATE(2026,11,28),"机构晚餐","无统一供餐"),IF(C380=Options!$B$10,"返程；"&IF(C380=DATE(2026,12,2),"机构午餐","无统一供餐"),"差旅状态；无统一日程")))))) | E380: =IF(C380=Options!$B$9,Options!$C$15,0) | F380: =IF(AND(A380<>"",C380<Options!$B$10),B380*Options!$X$5,0) | G380: =F380*12% | H380: =IF(A380="",0,B380*(92*IF(OR(C380=Options!$B$9,C380=Options!$B$10),75%,100%)-IF(C380=DATE(2026,11,29),26+IF(Options!$B$8="是",23,0),0)-IF(C380=DATE(2026,11,30),26,0)-IF(C380=DATE(2026,12,1),64,0)-IF(C380=DATE(2026,11,28),38,0)-IF(C380=DATE(2026,12,2),26,0))) | I380: =IF(AND(C380>=DATE(2026,11,29),C380<=DATE(2026,12,1)),B380*60,0) | J380: =IF(A380="",0,B380*(IF(C380=DATE(2026,11,28),38,0)+IF(C380=DATE(2026,12,1),38,0)+IF(C380=DATE(2026,12,2),26,0))) | K380: =IF(C380=Options!$B$9,B380*12,0) | L380: =IF(C380=Options!$B$9,B380*Options!$Z$5,0) | M380: 0 | N380: =SUM(E380:M380)
A381: =IF(AND(C381>=Options!$B$9,C381<=Options!$B$10),"Chicago","") | B381: =IF(A381="","",24) | C381: 46307 | D381: =IF(A381="","",IF(C381=DATE(2026,11,29),"培训；注册午餐；早餐参数",IF(C381=DATE(2026,11,30),"培训；注册午餐",IF(C381=DATE(2026,12,1),"培训；注册午餐；机构晚餐",IF(C381=Options!$B$9,"抵达；"&IF(C381=DATE(2026,11,28),"机构晚餐","无统一供餐"),IF(C381=Options!$B$10,"返程；"&IF(C381=DATE(2026,12,2),"机构午餐","无统一供餐"),"差旅状态；无统一日程")))))) | E381: =IF(C381=Options!$B$9,Options!$C$15,0) | F381: =IF(AND(A381<>"",C381<Options!$B$10),B381*Options!$X$5,0) | G381: =F381*12% | H381: =IF(A381="",0,B381*(92*IF(OR(C381=Options!$B$9,C381=Options!$B$10),75%,100%)-IF(C381=DATE(2026,11,29),26+IF(Options!$B$8="是",23,0),0)-IF(C381=DATE(2026,11,30),26,0)-IF(C381=DATE(2026,12,1),64,0)-IF(C381=DATE(2026,11,28),38,0)-IF(C381=DATE(2026,12,2),26,0))) | I381: =IF(AND(C381>=DATE(2026,11,29),C381<=DATE(2026,12,1)),B381*60,0) | J381: =IF(A381="",0,B381*(IF(C381=DATE(2026,11,28),38,0)+IF(C381=DATE(2026,12,1),38,0)+IF(C381=DATE(2026,12,2),26,0))) | K381: =IF(C381=Options!$B$9,B381*12,0) | L381: =IF(C381=Options!$B$9,B381*Options!$Z$5,0) | M381: 0 | N381: =SUM(E381:M381)
... A734: =IF(AND(C734>=Options!$B$9,C734<=Options!$B$10),"Chicago","") | B734: =IF(A734="","",24) | C734: 46660 | D734: =IF(A734="","",IF(C734=DATE(2026,11,29),"培训；注册午餐；早餐参数",IF(C734=DATE(2026,11,30),"培训；注册午餐",IF(C734=DATE(2026,12,1),"培训；注册午餐；机构晚餐",IF(C734=Options!$B$9,"抵达；"&IF(C734=DATE(2026,11,28),"机构晚餐","无统一供餐"),IF(C734=Options!$B$10,"返程；"&IF(C734=DATE(2026,12,2),"机构午餐","无统一供餐"),"差旅状态；无统一日程")))))) | E734: =IF(C734=Options!$B$9,Options!$C$15,0) | F734: =IF(AND(A734<>"",C734<Options!$B$10),B734*Options!$X$5,0) | G734: =F734*12% | H734: =IF(A734="",0,B734*(92*IF(OR(C734=Options!$B$9,C734=Options!$B$10),75%,100%)-IF(C734=DATE(2026,11,29),26+IF(Options!$B$8="是",23,0),0)-IF(C734=DATE(2026,11,30),26,0)-IF(C734=DATE(2026,12,1),64,0)-IF(C734=DATE(2026,11,28),38,0)-IF(C734=DATE(2026,12,2),26,0))) | I734: =IF(AND(C734>=DATE(2026,11,29),C734<=DATE(2026,12,1)),B734*60,0) | J734: =IF(A734="",0,B734*(IF(C734=DATE(2026,11,28),38,0)+IF(C734=DATE(2026,12,1),38,0)+IF(C734=DATE(2026,12,2),26,0))) | K734: =IF(C734=Options!$B$9,B734*12,0) | L734: =IF(C734=Options!$B$9,B734*Options!$Z$5,0) | M734: 0 | N734: =SUM(E734:M734)
A735: =IF(AND(C735>=Options!$B$9,C735<=Options!$B$10),"Denver","") | B735: =IF(A735="","",18) | C735: 46296 | D735: =IF(A735="","",IF(C735=DATE(2026,11,29),"培训；注册午餐；早餐参数",IF(C735=DATE(2026,11,30),"培训；注册午餐",IF(C735=DATE(2026,12,1),"培训；注册午餐；机构晚餐",IF(C735=Options!$B$9,"抵达；"&IF(C735=DATE(2026,11,28),"机构晚餐","无统一供餐"),IF(C735=Options!$B$10,"返程；"&IF(C735=DATE(2026,12,2),"机构午餐","无统一供餐"),"差旅状态；无统一日程")))))) | E735: =IF(C735=Options!$B$9,Options!$C$16,0) | F735: =IF(AND(A735<>"",C735<Options!$B$10),B735*Options!$X$6,0) | G735: =F735*12% | H735: =IF(A735="",0,B735*(92*IF(OR(C735=Options!$B$9,C735=Options!$B$10),75%,100%)-IF(C735=DATE(2026,11,29),26+IF(Options!$B$8="是",23,0),0)-IF(C735=DATE(2026,11,30),26,0)-IF(C735=DATE(2026,12,1),64,0)-IF(C735=DATE(2026,11,28),38,0)-IF(C735=DATE(2026,12,2),26,0))) | I735: =IF(AND(C735>=DATE(2026,11,29),C735<=DATE(2026,12,1)),B735*60,0) | J735: =IF(A735="",0,B735*(IF(C735=DATE(2026,11,28),38,0)+IF(C735=DATE(2026,12,1),38,0)+IF(C735=DATE(2026,12,2),26,0))) | K735: =IF(C735=Options!$B$9,B735*12,0) | L735: =IF(C735=Options!$B$9,B735*Options!$Z$6,0) | M735: 0 | N735: =SUM(E735:M735)
A736: =IF(AND(C736>=Options!$B$9,C736<=Options!$B$10),"Denver","") | B736: =IF(A736="","",18) | C736: 46297 | D736: =IF(A736="","",IF(C736=DATE(2026,11,29),"培训；注册午餐；早餐参数",IF(C736=DATE(2026,11,30),"培训；注册午餐",IF(C736=DATE(2026,12,1),"培训；注册午餐；机构晚餐",IF(C736=Options!$B$9,"抵达；"&IF(C736=DATE(2026,11,28),"机构晚餐","无统一供餐"),IF(C736=Options!$B$10,"返程；"&IF(C736=DATE(2026,12,2),"机构午餐","无统一供餐"),"差旅状态；无统一日程")))))) | E736: =IF(C736=Options!$B$9,Options!$C$16,0) | F736: =IF(AND(A736<>"",C736<Options!$B$10),B736*Options!$X$6,0) | G736: =F736*12% | H736: =IF(A736="",0,B736*(92*IF(OR(C736=Options!$B$9,C736=Options!$B$10),75%,100%)-IF(C736=DATE(2026,11,29),26+IF(Options!$B$8="是",23,0),0)-IF(C736=DATE(2026,11,30),26,0)-IF(C736=DATE(2026,12,1),64,0)-IF(C736=DATE(2026,11,28),38,0)-IF(C736=DATE(2026,12,2),26,0))) | I736: =IF(AND(C736>=DATE(2026,11,29),C736<=DATE(2026,12,1)),B736*60,0) | J736: =IF(A736="",0,B736*(IF(C736=DATE(2026,11,28),38,0)+IF(C736=DATE(2026,12,1),38,0)+IF(C736=DATE(2026,12,2),26,0))) | K736: =IF(C736=Options!$B$9,B736*12,0) | L736: =IF(C736=Options!$B$9,B736*Options!$Z$6,0) | M736: 0 | N736: =SUM(E736:M736)
A737: =IF(AND(C737>=Options!$B$9,C737<=Options!$B$10),"Denver","") | B737: =IF(A737="","",18) | C737: 46298 | D737: =IF(A737="","",IF(C737=DATE(2026,11,29),"培训；注册午餐；早餐参数",IF(C737=DATE(2026,11,30),"培训；注册午餐",IF(C737=DATE(2026,12,1),"培训；注册午餐；机构晚餐",IF(C737=Options!$B$9,"抵达；"&IF(C737=DATE(2026,11,28),"机构晚餐","无统一供餐"),IF(C737=Options!$B$10,"返程；"&IF(C737=DATE(2026,12,2),"机构午餐","无统一供餐"),"差旅状态；无统一日程")))))) | E737: =IF(C737=Options!$B$9,Options!$C$16,0) | F737: =IF(AND(A737<>"",C737<Options!$B$10),B737*Options!$X$6,0) | G737: =F737*12% | H737: =IF(A737="",0,B737*(92*IF(OR(C737=Options!$B$9,C737=Options!$B$10),75%,100%)-IF(C737=DATE(2026,11,29),26+IF(Options!$B$8="是",23,0),0)-IF(C737=DATE(2026,11,30),26,0)-IF(C737=DATE(2026,12,1),64,0)-IF(C737=DATE(2026,11,28),38,0)-IF(C737=DATE(2026,12,2),26,0))) | I737: =IF(AND(C737>=DATE(2026,11,29),C737<=DATE(2026,12,1)),B737*60,0) | J737: =IF(A737="",0,B737*(IF(C737=DATE(2026,11,28),38,0)+IF(C737=DATE(2026,12,1),38,0)+IF(C737=DATE(2026,12,2),26,0))) | K737: =IF(C737=Options!$B$9,B737*12,0) | L737: =IF(C737=Options!$B$9,B737*Options!$Z$6,0) | M737: 0 | N737: =SUM(E737:M737)
A738: =IF(AND(C738>=Options!$B$9,C738<=Options!$B$10),"Denver","") | B738: =IF(A738="","",18) | C738: 46299 | D738: =IF(A738="","",IF(C738=DATE(2026,11,29),"培训；注册午餐；早餐参数",IF(C738=DATE(2026,11,30),"培训；注册午餐",IF(C738=DATE(2026,12,1),"培训；注册午餐；机构晚餐",IF(C738=Options!$B$9,"抵达；"&IF(C738=DATE(2026,11,28),"机构晚餐","无统一供餐"),IF(C738=Options!$B$10,"返程；"&IF(C738=DATE(2026,12,2),"机构午餐","无统一供餐"),"差旅状态；无统一日程")))))) | E738: =IF(C738=Options!$B$9,Options!$C$16,0) | F738: =IF(AND(A738<>"",C738<Options!$B$10),B738*Options!$X$6,0) | G738: =F738*12% | H738: =IF(A738="",0,B738*(92*IF(OR(C738=Options!$B$9,C738=Options!$B$10),75%,100%)-IF(C738=DATE(2026,11,29),26+IF(Options!$B$8="是",23,0),0)-IF(C738=DATE(2026,11,30),26,0)-IF(C738=DATE(2026,12,1),64,0)-IF(C738=DATE(2026,11,28),38,0)-IF(C738=DATE(2026,12,2),26,0))) | I738: =IF(AND(C738>=DATE(2026,11,29),C738<=DATE(2026,12,1)),B738*60,0) | J738: =IF(A738="",0,B738*(IF(C738=DATE(2026,11,28),38,0)+IF(C738=DATE(2026,12,1),38,0)+IF(C738=DATE(2026,12,2),26,0))) | K738: =IF(C738=Options!$B$9,B738*12,0) | L738: =IF(C738=Options!$B$9,B738*Options!$Z$6,0) | M738: 0 | N738: =SUM(E738:M738)
A739: =IF(AND(C739>=Options!$B$9,C739<=Options!$B$10),"Denver","") | B739: =IF(A739="","",18) | C739: 46300 | D739: =IF(A739="","",IF(C739=DATE(2026,11,29),"培训；注册午餐；早餐参数",IF(C739=DATE(2026,11,30),"培训；注册午餐",IF(C739=DATE(2026,12,1),"培训；注册午餐；机构晚餐",IF(C739=Options!$B$9,"抵达；"&IF(C739=DATE(2026,11,28),"机构晚餐","无统一供餐"),IF(C739=Options!$B$10,"返程；"&IF(C739=DATE(2026,12,2),"机构午餐","无统一供餐"),"差旅状态；无统一日程")))))) | E739: =IF(C739=Options!$B$9,Options!$C$16,0) | F739: =IF(AND(A739<>"",C739<Options!$B$10),B739*Options!$X$6,0) | G739: =F739*12% | H739: =IF(A739="",0,B739*(92*IF(OR(C739=Options!$B$9,C739=Options!$B$10),75%,100%)-IF(C739=DATE(2026,11,29),26+IF(Options!$B$8="是",23,0),0)-IF(C739=DATE(2026,11,30),26,0)-IF(C739=DATE(2026,12,1),64,0)-IF(C739=DATE(2026,11,28),38,0)-IF(C739=DATE(2026,12,2),26,0))) | I739: =IF(AND(C739>=DATE(2026,11,29),C739<=DATE(2026,12,1)),B739*60,0) | J739: =IF(A739="",0,B739*(IF(C739=DATE(2026,11,28),38,0)+IF(C739=DATE(2026,12,1),38,0)+IF(C739=DATE(2026,12,2),26,0))) | K739: =IF(C739=Options!$B$9,B739*12,0) | L739: =IF(C739=Options!$B$9,B739*Options!$Z$6,0) | M739: 0 | N739: =SUM(E739:M739)
A740: =IF(AND(C740>=Options!$B$9,C740<=Options!$B$10),"Denver","") | B740: =IF(A740="","",18) | C740: 46301 | D740: =IF(A740="","",IF(C740=DATE(2026,11,29),"培训；注册午餐；早餐参数",IF(C740=DATE(2026,11,30),"培训；注册午餐",IF(C740=DATE(2026,12,1),"培训；注册午餐；机构晚餐",IF(C740=Options!$B$9,"抵达；"&IF(C740=DATE(2026,11,28),"机构晚餐","无统一供餐"),IF(C740=Options!$B$10,"返程；"&IF(C740=DATE(2026,12,2),"机构午餐","无统一供餐"),"差旅状态；无统一日程")))))) | E740: =IF(C740=Options!$B$9,Options!$C$16,0) | F740: =IF(AND(A740<>"",C740<Options!$B$10),B740*Options!$X$6,0) | G740: =F740*12% | H740: =IF(A740="",0,B740*(92*IF(OR(C740=Options!$B$9,C740=Options!$B$10),75%,100%)-IF(C740=DATE(2026,11,29),26+IF(Options!$B$8="是",23,0),0)-IF(C740=DATE(2026,11,30),26,0)-IF(C740=DATE(2026,12,1),64,0)-IF(C740=DATE(2026,11,28),38,0)-IF(C740=DATE(2026,12,2),26,0))) | I740: =IF(AND(C740>=DATE(2026,11,29),C740<=DATE(2026,12,1)),B740*60,0) | J740: =IF(A740="",0,B740*(IF(C740=DATE(2026,11,28),38,0)+IF(C740=DATE(2026,12,1),38,0)+IF(C740=DATE(2026,12,2),26,0))) | K740: =IF(C740=Options!$B$9,B740*12,0) | L740: =IF(C740=Options!$B$9,B740*Options!$Z$6,0) | M740: 0 | N740: =SUM(E740:M740)
A741: =IF(AND(C741>=Options!$B$9,C741<=Options!$B$10),"Denver","") | B741: =IF(A741="","",18) | C741: 46302 | D741: =IF(A741="","",IF(C741=DATE(2026,11,29),"培训；注册午餐；早餐参数",IF(C741=DATE(2026,11,30),"培训；注册午餐",IF(C741=DATE(2026,12,1),"培训；注册午餐；机构晚餐",IF(C741=Options!$B$9,"抵达；"&IF(C741=DATE(2026,11,28),"机构晚餐","无统一供餐"),IF(C741=Options!$B$10,"返程；"&IF(C741=DATE(2026,12,2),"机构午餐","无统一供餐"),"差旅状态；无统一日程")))))) | E741: =IF(C741=Options!$B$9,Options!$C$16,0) | F741: =IF(AND(A741<>"",C741<Options!$B$10),B741*Options!$X$6,0) | G741: =F741*12% | H741: =IF(A741="",0,B741*(92*IF(OR(C741=Options!$B$9,C741=Options!$B$10),75%,100%)-IF(C741=DATE(2026,11,29),26+IF(Options!$B$8="是",23,0),0)-IF(C741=DATE(2026,11,30),26,0)-IF(C741=DATE(2026,12,1),64,0)-IF(C741=DATE(2026,11,28),38,0)-IF(C741=DATE(2026,12,2),26,0))) | I741: =IF(AND(C741>=DATE(2026,11,29),C741<=DATE(2026,12,1)),B741*60,0) | J741: =IF(A741="",0,B741*(IF(C741=DATE(2026,11,28),38,0)+IF(C741=DATE(2026,12,1),38,0)+IF(C741=DATE(2026,12,2),26,0))) | K741: =IF(C741=Options!$B$9,B741*12,0) | L741: =IF(C741=Options!$B$9,B741*Options!$Z$6,0) | M741: 0 | N741: =SUM(E741:M741)
A742: =IF(AND(C742>=Options!$B$9,C742<=Options!$B$10),"Denver","") | B742: =IF(A742="","",18) | C742: 46303 | D742: =IF(A742="","",IF(C742=DATE(2026,11,29),"培训；注册午餐；早餐参数",IF(C742=DATE(2026,11,30),"培训；注册午餐",IF(C742=DATE(2026,12,1),"培训；注册午餐；机构晚餐",IF(C742=Options!$B$9,"抵达；"&IF(C742=DATE(2026,11,28),"机构晚餐","无统一供餐"),IF(C742=Options!$B$10,"返程；"&IF(C742=DATE(2026,12,2),"机构午餐","无统一供餐"),"差旅状态；无统一日程")))))) | E742: =IF(C742=Options!$B$9,Options!$C$16,0) | F742: =IF(AND(A742<>"",C742<Options!$B$10),B742*Options!$X$6,0) | G742: =F742*12% | H742: =IF(A742="",0,B742*(92*IF(OR(C742=Options!$B$9,C742=Options!$B$10),75%,100%)-IF(C742=DATE(2026,11,29),26+IF(Options!$B$8="是",23,0),0)-IF(C742=DATE(2026,11,30),26,0)-IF(C742=DATE(2026,12,1),64,0)-IF(C742=DATE(2026,11,28),38,0)-IF(C742=DATE(2026,12,2),26,0))) | I742: =IF(AND(C742>=DATE(2026,11,29),C742<=DATE(2026,12,1)),B742*60,0) | J742: =IF(A742="",0,B742*(IF(C742=DATE(2026,11,28),38,0)+IF(C742=DATE(2026,12,1),38,0)+IF(C742=DATE(2026,12,2),26,0))) | K742: =IF(C742=Options!$B$9,B742*12,0) | L742: =IF(C742=Options!$B$9,B742*Options!$Z$6,0) | M742: 0 | N742: =SUM(E742:M742)
A743: =IF(AND(C743>=Options!$B$9,C743<=Options!$B$10),"Denver","") | B743: =IF(A743="","",18) | C743: 46304 | D743: =IF(A743="","",IF(C743=DATE(2026,11,29),"培训；注册午餐；早餐参数",IF(C743=DATE(2026,11,30),"培训；注册午餐",IF(C743=DATE(2026,12,1),"培训；注册午餐；机构晚餐",IF(C743=Options!$B$9,"抵达；"&IF(C743=DATE(2026,11,28),"机构晚餐","无统一供餐"),IF(C743=Options!$B$10,"返程；"&IF(C743=DATE(2026,12,2),"机构午餐","无统一供餐"),"差旅状态；无统一日程")))))) | E743: =IF(C743=Options!$B$9,Options!$C$16,0) | F743: =IF(AND(A743<>"",C743<Options!$B$10),B743*Options!$X$6,0) | G743: =F743*12% | H743: =IF(A743="",0,B743*(92*IF(OR(C743=Options!$B$9,C743=Options!$B$10),75%,100%)-IF(C743=DATE(2026,11,29),26+IF(Options!$B$8="是",23,0),0)-IF(C743=DATE(2026,11,30),26,0)-IF(C743=DATE(2026,12,1),64,0)-IF(C743=DATE(2026,11,28),38,0)-IF(C743=DATE(2026,12,2),26,0))) | I743: =IF(AND(C743>=DATE(2026,11,29),C743<=DATE(2026,12,1)),B743*60,0) | J743: =IF(A743="",0,B743*(IF(C743=DATE(2026,11,28),38,0)+IF(C743=DATE(2026,12,1),38,0)+IF(C743=DATE(2026,12,2),26,0))) | K743: =IF(C743=Options!$B$9,B743*12,0) | L743: =IF(C743=Options!$B$9,B743*Options!$Z$6,0) | M743: 0 | N743: =SUM(E743:M743)
A744: =IF(AND(C744>=Options!$B$9,C744<=Options!$B$10),"Denver","") | B744: =IF(A744="","",18) | C744: 46305 | D744: =IF(A744="","",IF(C744=DATE(2026,11,29),"培训；注册午餐；早餐参数",IF(C744=DATE(2026,11,30),"培训；注册午餐",IF(C744=DATE(2026,12,1),"培训；注册午餐；机构晚餐",IF(C744=Options!$B$9,"抵达；"&IF(C744=DATE(2026,11,28),"机构晚餐","无统一供餐"),IF(C744=Options!$B$10,"返程；"&IF(C744=DATE(2026,12,2),"机构午餐","无统一供餐"),"差旅状态；无统一日程")))))) | E744: =IF(C744=Options!$B$9,Options!$C$16,0) | F744: =IF(AND(A744<>"",C744<Options!$B$10),B744*Options!$X$6,0) | G744: =F744*12% | H744: =IF(A744="",0,B744*(92*IF(OR(C744=Options!$B$9,C744=Options!$B$10),75%,100%)-IF(C744=DATE(2026,11,29),26+IF(Options!$B$8="是",23,0),0)-IF(C744=DATE(2026,11,30),26,0)-IF(C744=DATE(2026,12,1),64,0)-IF(C744=DATE(2026,11,28),38,0)-IF(C744=DATE(2026,12,2),26,0))) | I744: =IF(AND(C744>=DATE(2026,11,29),C744<=DATE(2026,12,1)),B744*60,0) | J744: =IF(A744="",0,B744*(IF(C744=DATE(2026,11,28),38,0)+IF(C744=DATE(2026,12,1),38,0)+IF(C744=DATE(2026,12,2),26,0))) | K744: =IF(C744=Options!$B$9,B744*12,0) | L744: =IF(C744=Options!$B$9,B744*Options!$Z$6,0) | M744: 0 | N744: =SUM(E744:M744)
A745: =IF(AND(C745>=Options!$B$9,C745<=Options!$B$10),"Denver","") | B745: =IF(A745="","",18) | C745: 46306 | D745: =IF(A745="","",IF(C745=DATE(2026,11,29),"培训；注册午餐；早餐参数",IF(C745=DATE(2026,11,30),"培训；注册午餐",IF(C745=DATE(2026,12,1),"培训；注册午餐；机构晚餐",IF(C745=Options!$B$9,"抵达；"&IF(C745=DATE(2026,11,28),"机构晚餐","无统一供餐"),IF(C745=Options!$B$10,"返程；"&IF(C745=DATE(2026,12,2),"机构午餐","无统一供餐"),"差旅状态；无统一日程")))))) | E745: =IF(C745=Options!$B$9,Options!$C$16,0) | F745: =IF(AND(A745<>"",C745<Options!$B$10),B745*Options!$X$6,0) | G745: =F745*12% | H745: =IF(A745="",0,B745*(92*IF(OR(C745=Options!$B$9,C745=Options!$B$10),75%,100%)-IF(C745=DATE(2026,11,29),26+IF(Options!$B$8="是",23,0),0)-IF(C745=DATE(2026,11,30),26,0)-IF(C745=DATE(2026,12,1),64,0)-IF(C745=DATE(2026,11,28),38,0)-IF(C745=DATE(2026,12,2),26,0))) | I745: =IF(AND(C745>=DATE(2026,11,29),C745<=DATE(2026,12,1)),B745*60,0) | J745: =IF(A745="",0,B745*(IF(C745=DATE(2026,11,28),38,0)+IF(C745=DATE(2026,12,1),38,0)+IF(C745=DATE(2026,12,2),26,0))) | K745: =IF(C745=Options!$B$9,B745*12,0) | L745: =IF(C745=Options!$B$9,B745*Options!$Z$6,0) | M745: 0 | N745: =SUM(E745:M745)
A746: =IF(AND(C746>=Options!$B$9,C746<=Options!$B$10),"Denver","") | B746: =IF(A746="","",18) | C746: 46307 | D746: =IF(A746="","",IF(C746=DATE(2026,11,29),"培训；注册午餐；早餐参数",IF(C746=DATE(2026,11,30),"培训；注册午餐",IF(C746=DATE(2026,12,1),"培训；注册午餐；机构晚餐",IF(C746=Options!$B$9,"抵达；"&IF(C746=DATE(2026,11,28),"机构晚餐","无统一供餐"),IF(C746=Options!$B$10,"返程；"&IF(C746=DATE(2026,12,2),"机构午餐","无统一供餐"),"差旅状态；无统一日程")))))) | E746: =IF(C746=Options!$B$9,Options!$C$16,0) | F746: =IF(AND(A746<>"",C746<Options!$B$10),B746*Options!$X$6,0) | G746: =F746*12% | H746: =IF(A746="",0,B746*(92*IF(OR(C746=Options!$B$9,C746=Options!$B$10),75%,100%)-IF(C746=DATE(2026,11,29),26+IF(Options!$B$8="是",23,0),0)-IF(C746=DATE(2026,11,30),26,0)-IF(C746=DATE(2026,12,1),64,0)-IF(C746=DATE(2026,11,28),38,0)-IF(C746=DATE(2026,12,2),26,0))) | I746: =IF(AND(C746>=DATE(2026,11,29),C746<=DATE(2026,12,1)),B746*60,0) | J746: =IF(A746="",0,B746*(IF(C746=DATE(2026,11,28),38,0)+IF(C746=DATE(2026,12,1),38,0)+IF(C746=DATE(2026,12,2),26,0))) | K746: =IF(C746=Options!$B$9,B746*12,0) | L746: =IF(C746=Options!$B$9,B746*Options!$Z$6,0) | M746: 0 | N746: =SUM(E746:M746)
... A1099: =IF(AND(C1099>=Options!$B$9,C1099<=Options!$B$10),"Denver","") | B1099: =IF(A1099="","",18) | C1099: 46660 | D1099: =IF(A1099="","",IF(C1099=DATE(2026,11,29),"培训；注册午餐；早餐参数",IF(C1099=DATE(2026,11,30),"培训；注册午餐",IF(C1099=DATE(2026,12,1),"培训；注册午餐；机构晚餐",IF(C1099=Options!$B$9,"抵达；"&IF(C1099=DATE(2026,11,28),"机构晚餐","无统一供餐"),IF(C1099=Options!$B$10,"返程；"&IF(C1099=DATE(2026,12,2),"机构午餐","无统一供餐"),"差旅状态；无统一日程")))))) | E1099: =IF(C1099=Options!$B$9,Options!$C$16,0) | F1099: =IF(AND(A1099<>"",C1099<Options!$B$10),B1099*Options!$X$6,0) | G1099: =F1099*12% | H1099: =IF(A1099="",0,B1099*(92*IF(OR(C1099=Options!$B$9,C1099=Options!$B$10),75%,100%)-IF(C1099=DATE(2026,11,29),26+IF(Options!$B$8="是",23,0),0)-IF(C1099=DATE(2026,11,30),26,0)-IF(C1099=DATE(2026,12,1),64,0)-IF(C1099=DATE(2026,11,28),38,0)-IF(C1099=DATE(2026,12,2),26,0))) | I1099: =IF(AND(C1099>=DATE(2026,11,29),C1099<=DATE(2026,12,1)),B1099*60,0) | J1099: =IF(A1099="",0,B1099*(IF(C1099=DATE(2026,11,28),38,0)+IF(C1099=DATE(2026,12,1),38,0)+IF(C1099=DATE(2026,12,2),26,0))) | K1099: =IF(C1099=Options!$B$9,B1099*12,0) | L1099: =IF(C1099=Options!$B$9,B1099*Options!$Z$6,0) | M1099: 0 | N1099: =SUM(E1099:M1099)
A1100: =IF(AND(C1100>=Options!$B$9,C1100<=Options!$B$10),"Denver","") | B1100: =IF(A1100="","",24) | C1100: 46296 | D1100: =IF(A1100="","",IF(C1100=DATE(2026,11,29),"培训；注册午餐；早餐参数",IF(C1100=DATE(2026,11,30),"培训；注册午餐",IF(C1100=DATE(2026,12,1),"培训；注册午餐；机构晚餐",IF(C1100=Options!$B$9,"抵达；"&IF(C1100=DATE(2026,11,28),"机构晚餐","无统一供餐"),IF(C1100=Options!$B$10,"返程；"&IF(C1100=DATE(2026,12,2),"机构午餐","无统一供餐"),"差旅状态；无统一日程")))))) | E1100: =IF(C1100=Options!$B$9,Options!$C$17,0) | F1100: =IF(AND(A1100<>"",C1100<Options!$B$10),B1100*Options!$X$6,0) | G1100: =F1100*12% | H1100: =IF(A1100="",0,B1100*(92*IF(OR(C1100=Options!$B$9,C1100=Options!$B$10),75%,100%)-IF(C1100=DATE(2026,11,29),26+IF(Options!$B$8="是",23,0),0)-IF(C1100=DATE(2026,11,30),26,0)-IF(C1100=DATE(2026,12,1),64,0)-IF(C1100=DATE(2026,11,28),38,0)-IF(C1100=DATE(2026,12,2),26,0))) | I1100: =IF(AND(C1100>=DATE(2026,11,29),C1100<=DATE(2026,12,1)),B1100*60,0) | J1100: =IF(A1100="",0,B1100*(IF(C1100=DATE(2026,11,28),38,0)+IF(C1100=DATE(2026,12,1),38,0)+IF(C1100=DATE(2026,12,2),26,0))) | K1100: =IF(C1100=Options!$B$9,B1100*12,0) | L1100: =IF(C1100=Options!$B$9,B1100*Options!$Z$6,0) | M1100: 0 | N1100: =SUM(E1100:M1100)
A1101: =IF(AND(C1101>=Options!$B$9,C1101<=Options!$B$10),"Denver","") | B1101: =IF(A1101="","",24) | C1101: 46297 | D1101: =IF(A1101="","",IF(C1101=DATE(2026,11,29),"培训；注册午餐；早餐参数",IF(C1101=DATE(2026,11,30),"培训；注册午餐",IF(C1101=DATE(2026,12,1),"培训；注册午餐；机构晚餐",IF(C1101=Options!$B$9,"抵达；"&IF(C1101=DATE(2026,11,28),"机构晚餐","无统一供餐"),IF(C1101=Options!$B$10,"返程；"&IF(C1101=DATE(2026,12,2),"机构午餐","无统一供餐"),"差旅状态；无统一日程")))))) | E1101: =IF(C1101=Options!$B$9,Options!$C$17,0) | F1101: =IF(AND(A1101<>"",C1101<Options!$B$10),B1101*Options!$X$6,0) | G1101: =F1101*12% | H1101: =IF(A1101="",0,B1101*(92*IF(OR(C1101=Options!$B$9,C1101=Options!$B$10),75%,100%)-IF(C1101=DATE(2026,11,29),26+IF(Options!$B$8="是",23,0),0)-IF(C1101=DATE(2026,11,30),26,0)-IF(C1101=DATE(2026,12,1),64,0)-IF(C1101=DATE(2026,11,28),38,0)-IF(C1101=DATE(2026,12,2),26,0))) | I1101: =IF(AND(C1101>=DATE(2026,11,29),C1101<=DATE(2026,12,1)),B1101*60,0) | J1101: =IF(A1101="",0,B1101*(IF(C1101=DATE(2026,11,28),38,0)+IF(C1101=DATE(2026,12,1),38,0)+IF(C1101=DATE(2026,12,2),26,0))) | K1101: =IF(C1101=Options!$B$9,B1101*12,0) | L1101: =IF(C1101=Options!$B$9,B1101*Options!$Z$6,0) | M1101: 0 | N1101: =SUM(E1101:M1101)
A1102: =IF(AND(C1102>=Options!$B$9,C1102<=Options!$B$10),"Denver","") | B1102: =IF(A1102="","",24) | C1102: 46298 | D1102: =IF(A1102="","",IF(C1102=DATE(2026,11,29),"培训；注册午餐；早餐参数",IF(C1102=DATE(2026,11,30),"培训；注册午餐",IF(C1102=DATE(2026,12,1),"培训；注册午餐；机构晚餐",IF(C1102=Options!$B$9,"抵达；"&IF(C1102=DATE(2026,11,28),"机构晚餐","无统一供餐"),IF(C1102=Options!$B$10,"返程；"&IF(C1102=DATE(2026,12,2),"机构午餐","无统一供餐"),"差旅状态；无统一日程")))))) | E1102: =IF(C1102=Options!$B$9,Options!$C$17,0) | F1102: =IF(AND(A1102<>"",C1102<Options!$B$10),B1102*Options!$X$6,0) | G1102: =F1102*12% | H1102: =IF(A1102="",0,B1102*(92*IF(OR(C1102=Options!$B$9,C1102=Options!$B$10),75%,100%)-IF(C1102=DATE(2026,11,29),26+IF(Options!$B$8="是",23,0),0)-IF(C1102=DATE(2026,11,30),26,0)-IF(C1102=DATE(2026,12,1),64,0)-IF(C1102=DATE(2026,11,28),38,0)-IF(C1102=DATE(2026,12,2),26,0))) | I1102: =IF(AND(C1102>=DATE(2026,11,29),C1102<=DATE(2026,12,1)),B1102*60,0) | J1102: =IF(A1102="",0,B1102*(IF(C1102=DATE(2026,11,28),38,0)+IF(C1102=DATE(2026,12,1),38,0)+IF(C1102=DATE(2026,12,2),26,0))) | K1102: =IF(C1102=Options!$B$9,B1102*12,0) | L1102: =IF(C1102=Options!$B$9,B1102*Options!$Z$6,0) | M1102: 0 | N1102: =SUM(E1102:M1102)
A1103: =IF(AND(C1103>=Options!$B$9,C1103<=Options!$B$10),"Denver","") | B1103: =IF(A1103="","",24) | C1103: 46299 | D1103: =IF(A1103="","",IF(C1103=DATE(2026,11,29),"培训；注册午餐；早餐参数",IF(C1103=DATE(2026,11,30),"培训；注册午餐",IF(C1103=DATE(2026,12,1),"培训；注册午餐；机构晚餐",IF(C1103=Options!$B$9,"抵达；"&IF(C1103=DATE(2026,11,28),"机构晚餐","无统一供餐"),IF(C1103=Options!$B$10,"返程；"&IF(C1103=DATE(2026,12,2),"机构午餐","无统一供餐"),"差旅状态；无统一日程")))))) | E1103: =IF(C1103=Options!$B$9,Options!$C$17,0) | F1103: =IF(AND(A1103<>"",C1103<Options!$B$10),B1103*Options!$X$6,0) | G1103: =F1103*12% | H1103: =IF(A1103="",0,B1103*(92*IF(OR(C1103=Options!$B$9,C1103=Options!$B$10),75%,100%)-IF(C1103=DATE(2026,11,29),26+IF(Options!$B$8="是",23,0),0)-IF(C1103=DATE(2026,11,30),26,0)-IF(C1103=DATE(2026,12,1),64,0)-IF(C1103=DATE(2026,11,28),38,0)-IF(C1103=DATE(2026,12,2),26,0))) | I1103: =IF(AND(C1103>=DATE(2026,11,29),C1103<=DATE(2026,12,1)),B1103*60,0) | J1103: =IF(A1103="",0,B1103*(IF(C1103=DATE(2026,11,28),38,0)+IF(C1103=DATE(2026,12,1),38,0)+IF(C1103=DATE(2026,12,2),26,0))) | K1103: =IF(C1103=Options!$B$9,B1103*12,0) | L1103: =IF(C1103=Options!$B$9,B1103*Options!$Z$6,0) | M1103: 0 | N1103: =SUM(E1103:M1103)
A1104: =IF(AND(C1104>=Options!$B$9,C1104<=Options!$B$10),"Denver","") | B1104: =IF(A1104="","",24) | C1104: 46300 | D1104: =IF(A1104="","",IF(C1104=DATE(2026,11,29),"培训；注册午餐；早餐参数",IF(C1104=DATE(2026,11,30),"培训；注册午餐",IF(C1104=DATE(2026,12,1),"培训；注册午餐；机构晚餐",IF(C1104=Options!$B$9,"抵达；"&IF(C1104=DATE(2026,11,28),"机构晚餐","无统一供餐"),IF(C1104=Options!$B$10,"返程；"&IF(C1104=DATE(2026,12,2),"机构午餐","无统一供餐"),"差旅状态；无统一日程")))))) | E1104: =IF(C1104=Options!$B$9,Options!$C$17,0) | F1104: =IF(AND(A1104<>"",C1104<Options!$B$10),B1104*Options!$X$6,0) | G1104: =F1104*12% | H1104: =IF(A1104="",0,B1104*(92*IF(OR(C1104=Options!$B$9,C1104=Options!$B$10),75%,100%)-IF(C1104=DATE(2026,11,29),26+IF(Options!$B$8="是",23,0),0)-IF(C1104=DATE(2026,11,30),26,0)-IF(C1104=DATE(2026,12,1),64,0)-IF(C1104=DATE(2026,11,28),38,0)-IF(C1104=DATE(2026,12,2),26,0))) | I1104: =IF(AND(C1104>=DATE(2026,11,29),C1104<=DATE(2026,12,1)),B1104*60,0) | J1104: =IF(A1104="",0,B1104*(IF(C1104=DATE(2026,11,28),38,0)+IF(C1104=DATE(2026,12,1),38,0)+IF(C1104=DATE(2026,12,2),26,0))) | K1104: =IF(C1104=Options!$B$9,B1104*12,0) | L1104: =IF(C1104=Options!$B$9,B1104*Options!$Z$6,0) | M1104: 0 | N1104: =SUM(E1104:M1104)
A1105: =IF(AND(C1105>=Options!$B$9,C1105<=Options!$B$10),"Denver","") | B1105: =IF(A1105="","",24) | C1105: 46301 | D1105: =IF(A1105="","",IF(C1105=DATE(2026,11,29),"培训；注册午餐；早餐参数",IF(C1105=DATE(2026,11,30),"培训；注册午餐",IF(C1105=DATE(2026,12,1),"培训；注册午餐；机构晚餐",IF(C1105=Options!$B$9,"抵达；"&IF(C1105=DATE(2026,11,28),"机构晚餐","无统一供餐"),IF(C1105=Options!$B$10,"返程；"&IF(C1105=DATE(2026,12,2),"机构午餐","无统一供餐"),"差旅状态；无统一日程")))))) | E1105: =IF(C1105=Options!$B$9,Options!$C$17,0) | F1105: =IF(AND(A1105<>"",C1105<Options!$B$10),B1105*Options!$X$6,0) | G1105: =F1105*12% | H1105: =IF(A1105="",0,B1105*(92*IF(OR(C1105=Options!$B$9,C1105=Options!$B$10),75%,100%)-IF(C1105=DATE(2026,11,29),26+IF(Options!$B$8="是",23,0),0)-IF(C1105=DATE(2026,11,30),26,0)-IF(C1105=DATE(2026,12,1),64,0)-IF(C1105=DATE(2026,11,28),38,0)-IF(C1105=DATE(2026,12,2),26,0))) | I1105: =IF(AND(C1105>=DATE(2026,11,29),C1105<=DATE(2026,12,1)),B1105*60,0) | J1105: =IF(A1105="",0,B1105*(IF(C1105=DATE(2026,11,28),38,0)+IF(C1105=DATE(2026,12,1),38,0)+IF(C1105=DATE(2026,12,2),26,0))) | K1105: =IF(C1105=Options!$B$9,B1105*12,0) | L1105: =IF(C1105=Options!$B$9,B1105*Options!$Z$6,0) | M1105: 0 | N1105: =SUM(E1105:M1105)
A1106: =IF(AND(C1106>=Options!$B$9,C1106<=Options!$B$10),"Denver","") | B1106: =IF(A1106="","",24) | C1106: 46302 | D1106: =IF(A1106="","",IF(C1106=DATE(2026,11,29),"培训；注册午餐；早餐参数",IF(C1106=DATE(2026,11,30),"培训；注册午餐",IF(C1106=DATE(2026,12,1),"培训；注册午餐；机构晚餐",IF(C1106=Options!$B$9,"抵达；"&IF(C1106=DATE(2026,11,28),"机构晚餐","无统一供餐"),IF(C1106=Options!$B$10,"返程；"&IF(C1106=DATE(2026,12,2),"机构午餐","无统一供餐"),"差旅状态；无统一日程")))))) | E1106: =IF(C1106=Options!$B$9,Options!$C$17,0) | F1106: =IF(AND(A1106<>"",C1106<Options!$B$10),B1106*Options!$X$6,0) | G1106: =F1106*12% | H1106: =IF(A1106="",0,B1106*(92*IF(OR(C1106=Options!$B$9,C1106=Options!$B$10),75%,100%)-IF(C1106=DATE(2026,11,29),26+IF(Options!$B$8="是",23,0),0)-IF(C1106=DATE(2026,11,30),26,0)-IF(C1106=DATE(2026,12,1),64,0)-IF(C1106=DATE(2026,11,28),38,0)-IF(C1106=DATE(2026,12,2),26,0))) | I1106: =IF(AND(C1106>=DATE(2026,11,29),C1106<=DATE(2026,12,1)),B1106*60,0) | J1106: =IF(A1106="",0,B1106*(IF(C1106=DATE(2026,11,28),38,0)+IF(C1106=DATE(2026,12,1),38,0)+IF(C1106=DATE(2026,12,2),26,0))) | K1106: =IF(C1106=Options!$B$9,B1106*12,0) | L1106: =IF(C1106=Options!$B$9,B1106*Options!$Z$6,0) | M1106: 0 | N1106: =SUM(E1106:M1106)
A1107: =IF(AND(C1107>=Options!$B$9,C1107<=Options!$B$10),"Denver","") | B1107: =IF(A1107="","",24) | C1107: 46303 | D1107: =IF(A1107="","",IF(C1107=DATE(2026,11,29),"培训；注册午餐；早餐参数",IF(C1107=DATE(2026,11,30),"培训；注册午餐",IF(C1107=DATE(2026,12,1),"培训；注册午餐；机构晚餐",IF(C1107=Options!$B$9,"抵达；"&IF(C1107=DATE(2026,11,28),"机构晚餐","无统一供餐"),IF(C1107=Options!$B$10,"返程；"&IF(C1107=DATE(2026,12,2),"机构午餐","无统一供餐"),"差旅状态；无统一日程")))))) | E1107: =IF(C1107=Options!$B$9,Options!$C$17,0) | F1107: =IF(AND(A1107<>"",C1107<Options!$B$10),B1107*Options!$X$6,0) | G1107: =F1107*12% | H1107: =IF(A1107="",0,B1107*(92*IF(OR(C1107=Options!$B$9,C1107=Options!$B$10),75%,100%)-IF(C1107=DATE(2026,11,29),26+IF(Options!$B$8="是",23,0),0)-IF(C1107=DATE(2026,11,30),26,0)-IF(C1107=DATE(2026,12,1),64,0)-IF(C1107=DATE(2026,11,28),38,0)-IF(C1107=DATE(2026,12,2),26,0))) | I1107: =IF(AND(C1107>=DATE(2026,11,29),C1107<=DATE(2026,12,1)),B1107*60,0) | J1107: =IF(A1107="",0,B1107*(IF(C1107=DATE(2026,11,28),38,0)+IF(C1107=DATE(2026,12,1),38,0)+IF(C1107=DATE(2026,12,2),26,0))) | K1107: =IF(C1107=Options!$B$9,B1107*12,0) | L1107: =IF(C1107=Options!$B$9,B1107*Options!$Z$6,0) | M1107: 0 | N1107: =SUM(E1107:M1107)
A1108: =IF(AND(C1108>=Options!$B$9,C1108<=Options!$B$10),"Denver","") | B1108: =IF(A1108="","",24) | C1108: 46304 | D1108: =IF(A1108="","",IF(C1108=DATE(2026,11,29),"培训；注册午餐；早餐参数",IF(C1108=DATE(2026,11,30),"培训；注册午餐",IF(C1108=DATE(2026,12,1),"培训；注册午餐；机构晚餐",IF(C1108=Options!$B$9,"抵达；"&IF(C1108=DATE(2026,11,28),"机构晚餐","无统一供餐"),IF(C1108=Options!$B$10,"返程；"&IF(C1108=DATE(2026,12,2),"机构午餐","无统一供餐"),"差旅状态；无统一日程")))))) | E1108: =IF(C1108=Options!$B$9,Options!$C$17,0) | F1108: =IF(AND(A1108<>"",C1108<Options!$B$10),B1108*Options!$X$6,0) | G1108: =F1108*12% | H1108: =IF(A1108="",0,B1108*(92*IF(OR(C1108=Options!$B$9,C1108=Options!$B$10),75%,100%)-IF(C1108=DATE(2026,11,29),26+IF(Options!$B$8="是",23,0),0)-IF(C1108=DATE(2026,11,30),26,0)-IF(C1108=DATE(2026,12,1),64,0)-IF(C1108=DATE(2026,11,28),38,0)-IF(C1108=DATE(2026,12,2),26,0))) | I1108: =IF(AND(C1108>=DATE(2026,11,29),C1108<=DATE(2026,12,1)),B1108*60,0) | J1108: =IF(A1108="",0,B1108*(IF(C1108=DATE(2026,11,28),38,0)+IF(C1108=DATE(2026,12,1),38,0)+IF(C1108=DATE(2026,12,2),26,0))) | K1108: =IF(C1108=Options!$B$9,B1108*12,0) | L1108: =IF(C1108=Options!$B$9,B1108*Options!$Z$6,0) | M1108: 0 | N1108: =SUM(E1108:M1108)
A1109: =IF(AND(C1109>=Options!$B$9,C1109<=Options!$B$10),"Denver","") | B1109: =IF(A1109="","",24) | C1109: 46305 | D1109: =IF(A1109="","",IF(C1109=DATE(2026,11,29),"培训；注册午餐；早餐参数",IF(C1109=DATE(2026,11,30),"培训；注册午餐",IF(C1109=DATE(2026,12,1),"培训；注册午餐；机构晚餐",IF(C1109=Options!$B$9,"抵达；"&IF(C1109=DATE(2026,11,28),"机构晚餐","无统一供餐"),IF(C1109=Options!$B$10,"返程；"&IF(C1109=DATE(2026,12,2),"机构午餐","无统一供餐"),"差旅状态；无统一日程")))))) | E1109: =IF(C1109=Options!$B$9,Options!$C$17,0) | F1109: =IF(AND(A1109<>"",C1109<Options!$B$10),B1109*Options!$X$6,0) | G1109: =F1109*12% | H1109: =IF(A1109="",0,B1109*(92*IF(OR(C1109=Options!$B$9,C1109=Options!$B$10),75%,100%)-IF(C1109=DATE(2026,11,29),26+IF(Options!$B$8="是",23,0),0)-IF(C1109=DATE(2026,11,30),26,0)-IF(C1109=DATE(2026,12,1),64,0)-IF(C1109=DATE(2026,11,28),38,0)-IF(C1109=DATE(2026,12,2),26,0))) | I1109: =IF(AND(C1109>=DATE(2026,11,29),C1109<=DATE(2026,12,1)),B1109*60,0) | J1109: =IF(A1109="",0,B1109*(IF(C1109=DATE(2026,11,28),38,0)+IF(C1109=DATE(2026,12,1),38,0)+IF(C1109=DATE(2026,12,2),26,0))) | K1109: =IF(C1109=Options!$B$9,B1109*12,0) | L1109: =IF(C1109=Options!$B$9,B1109*Options!$Z$6,0) | M1109: 0 | N1109: =SUM(E1109:M1109)
A1110: =IF(AND(C1110>=Options!$B$9,C1110<=Options!$B$10),"Denver","") | B1110: =IF(A1110="","",24) | C1110: 46306 | D1110: =IF(A1110="","",IF(C1110=DATE(2026,11,29),"培训；注册午餐；早餐参数",IF(C1110=DATE(2026,11,30),"培训；注册午餐",IF(C1110=DATE(2026,12,1),"培训；注册午餐；机构晚餐",IF(C1110=Options!$B$9,"抵达；"&IF(C1110=DATE(2026,11,28),"机构晚餐","无统一供餐"),IF(C1110=Options!$B$10,"返程；"&IF(C1110=DATE(2026,12,2),"机构午餐","无统一供餐"),"差旅状态；无统一日程")))))) | E1110: =IF(C1110=Options!$B$9,Options!$C$17,0) | F1110: =IF(AND(A1110<>"",C1110<Options!$B$10),B1110*Options!$X$6,0) | G1110: =F1110*12% | H1110: =IF(A1110="",0,B1110*(92*IF(OR(C1110=Options!$B$9,C1110=Options!$B$10),75%,100%)-IF(C1110=DATE(2026,11,29),26+IF(Options!$B$8="是",23,0),0)-IF(C1110=DATE(2026,11,30),26,0)-IF(C1110=DATE(2026,12,1),64,0)-IF(C1110=DATE(2026,11,28),38,0)-IF(C1110=DATE(2026,12,2),26,0))) | I1110: =IF(AND(C1110>=DATE(2026,11,29),C1110<=DATE(2026,12,1)),B1110*60,0) | J1110: =IF(A1110="",0,B1110*(IF(C1110=DATE(2026,11,28),38,0)+IF(C1110=DATE(2026,12,1),38,0)+IF(C1110=DATE(2026,12,2),26,0))) | K1110: =IF(C1110=Options!$B$9,B1110*12,0) | L1110: =IF(C1110=Options!$B$9,B1110*Options!$Z$6,0) | M1110: 0 | N1110: =SUM(E1110:M1110)
A1111: =IF(AND(C1111>=Options!$B$9,C1111<=Options!$B$10),"Denver","") | B1111: =IF(A1111="","",24) | C1111: 46307 | D1111: =IF(A1111="","",IF(C1111=DATE(2026,11,29),"培训；注册午餐；早餐参数",IF(C1111=DATE(2026,11,30),"培训；注册午餐",IF(C1111=DATE(2026,12,1),"培训；注册午餐；机构晚餐",IF(C1111=Options!$B$9,"抵达；"&IF(C1111=DATE(2026,11,28),"机构晚餐","无统一供餐"),IF(C1111=Options!$B$10,"返程；"&IF(C1111=DATE(2026,12,2),"机构午餐","无统一供餐"),"差旅状态；无统一日程")))))) | E1111: =IF(C1111=Options!$B$9,Options!$C$17,0) | F1111: =IF(AND(A1111<>"",C1111<Options!$B$10),B1111*Options!$X$6,0) | G1111: =F1111*12% | H1111: =IF(A1111="",0,B1111*(92*IF(OR(C1111=Options!$B$9,C1111=Options!$B$10),75%,100%)-IF(C1111=DATE(2026,11,29),26+IF(Options!$B$8="是",23,0),0)-IF(C1111=DATE(2026,11,30),26,0)-IF(C1111=DATE(2026,12,1),64,0)-IF(C1111=DATE(2026,11,28),38,0)-IF(C1111=DATE(2026,12,2),26,0))) | I1111: =IF(AND(C1111>=DATE(2026,11,29),C1111<=DATE(2026,12,1)),B1111*60,0) | J1111: =IF(A1111="",0,B1111*(IF(C1111=DATE(2026,11,28),38,0)+IF(C1111=DATE(2026,12,1),38,0)+IF(C1111=DATE(2026,12,2),26,0))) | K1111: =IF(C1111=Options!$B$9,B1111*12,0) | L1111: =IF(C1111=Options!$B$9,B1111*Options!$Z$6,0) | M1111: 0 | N1111: =SUM(E1111:M1111)
... A1464: =IF(AND(C1464>=Options!$B$9,C1464<=Options!$B$10),"Denver","") | B1464: =IF(A1464="","",24) | C1464: 46660 | D1464: =IF(A1464="","",IF(C1464=DATE(2026,11,29),"培训；注册午餐；早餐参数",IF(C1464=DATE(2026,11,30),"培训；注册午餐",IF(C1464=DATE(2026,12,1),"培训；注册午餐；机构晚餐",IF(C1464=Options!$B$9,"抵达；"&IF(C1464=DATE(2026,11,28),"机构晚餐","无统一供餐"),IF(C1464=Options!$B$10,"返程；"&IF(C1464=DATE(2026,12,2),"机构午餐","无统一供餐"),"差旅状态；无统一日程")))))) | E1464: =IF(C1464=Options!$B$9,Options!$C$17,0) | F1464: =IF(AND(A1464<>"",C1464<Options!$B$10),B1464*Options!$X$6,0) | G1464: =F1464*12% | H1464: =IF(A1464="",0,B1464*(92*IF(OR(C1464=Options!$B$9,C1464=Options!$B$10),75%,100%)-IF(C1464=DATE(2026,11,29),26+IF(Options!$B$8="是",23,0),0)-IF(C1464=DATE(2026,11,30),26,0)-IF(C1464=DATE(2026,12,1),64,0)-IF(C1464=DATE(2026,11,28),38,0)-IF(C1464=DATE(2026,12,2),26,0))) | I1464: =IF(AND(C1464>=DATE(2026,11,29),C1464<=DATE(2026,12,1)),B1464*60,0) | J1464: =IF(A1464="",0,B1464*(IF(C1464=DATE(2026,11,28),38,0)+IF(C1464=DATE(2026,12,1),38,0)+IF(C1464=DATE(2026,12,2),26,0))) | K1464: =IF(C1464=Options!$B$9,B1464*12,0) | L1464: =IF(C1464=Options!$B$9,B1464*Options!$Z$6,0) | M1464: 0 | N1464: =SUM(E1464:M1464)
A1465: =IF(AND(C1465>=Options!$B$9,C1465<=Options!$B$10),"Phoenix","") | B1465: =IF(A1465="","",18) | C1465: 46296 | D1465: =IF(A1465="","",IF(C1465=DATE(2026,11,29),"培训；注册午餐；早餐参数",IF(C1465=DATE(2026,11,30),"培训；注册午餐",IF(C1465=DATE(2026,12,1),"培训；注册午餐；机构晚餐",IF(C1465=Options!$B$9,"抵达；"&IF(C1465=DATE(2026,11,28),"机构晚餐","无统一供餐"),IF(C1465=Options!$B$10,"返程；"&IF(C1465=DATE(2026,12,2),"机构午餐","无统一供餐"),"差旅状态；无统一日程")))))) | E1465: =IF(C1465=Options!$B$9,Options!$C$18,0) | F1465: =IF(AND(A1465<>"",C1465<Options!$B$10),B1465*Options!$X$7,0) | G1465: =F1465*12% | H1465: =IF(A1465="",0,B1465*(86*IF(OR(C1465=Options!$B$9,C1465=Options!$B$10),75%,100%)-IF(C1465=DATE(2026,11,29),23+IF(Options!$B$8="是",22,0),0)-IF(C1465=DATE(2026,11,30),23,0)-IF(C1465=DATE(2026,12,1),59,0)-IF(C1465=DATE(2026,11,28),36,0)-IF(C1465=DATE(2026,12,2),23,0))) | I1465: =IF(AND(C1465>=DATE(2026,11,29),C1465<=DATE(2026,12,1)),B1465*60,0) | J1465: =IF(A1465="",0,B1465*(IF(C1465=DATE(2026,11,28),36,0)+IF(C1465=DATE(2026,12,1),36,0)+IF(C1465=DATE(2026,12,2),23,0))) | K1465: =IF(C1465=Options!$B$9,B1465*12,0) | L1465: =IF(C1465=Options!$B$9,B1465*Options!$Z$7,0) | M1465: 0 | N1465: =SUM(E1465:M1465)
A1466: =IF(AND(C1466>=Options!$B$9,C1466<=Options!$B$10),"Phoenix","") | B1466: =IF(A1466="","",18) | C1466: 46297 | D1466: =IF(A1466="","",IF(C1466=DATE(2026,11,29),"培训；注册午餐；早餐参数",IF(C1466=DATE(2026,11,30),"培训；注册午餐",IF(C1466=DATE(2026,12,1),"培训；注册午餐；机构晚餐",IF(C1466=Options!$B$9,"抵达；"&IF(C1466=DATE(2026,11,28),"机构晚餐","无统一供餐"),IF(C1466=Options!$B$10,"返程；"&IF(C1466=DATE(2026,12,2),"机构午餐","无统一供餐"),"差旅状态；无统一日程")))))) | E1466: =IF(C1466=Options!$B$9,Options!$C$18,0) | F1466: =IF(AND(A1466<>"",C1466<Options!$B$10),B1466*Options!$X$7,0) | G1466: =F1466*12% | H1466: =IF(A1466="",0,B1466*(86*IF(OR(C1466=Options!$B$9,C1466=Options!$B$10),75%,100%)-IF(C1466=DATE(2026,11,29),23+IF(Options!$B$8="是",22,0),0)-IF(C1466=DATE(2026,11,30),23,0)-IF(C1466=DATE(2026,12,1),59,0)-IF(C1466=DATE(2026,11,28),36,0)-IF(C1466=DATE(2026,12,2),23,0))) | I1466: =IF(AND(C1466>=DATE(2026,11,29),C1466<=DATE(2026,12,1)),B1466*60,0) | J1466: =IF(A1466="",0,B1466*(IF(C1466=DATE(2026,11,28),36,0)+IF(C1466=DATE(2026,12,1),36,0)+IF(C1466=DATE(2026,12,2),23,0))) | K1466: =IF(C1466=Options!$B$9,B1466*12,0) | L1466: =IF(C1466=Options!$B$9,B1466*Options!$Z$7,0) | M1466: 0 | N1466: =SUM(E1466:M1466)
A1467: =IF(AND(C1467>=Options!$B$9,C1467<=Options!$B$10),"Phoenix","") | B1467: =IF(A1467="","",18) | C1467: 46298 | D1467: =IF(A1467="","",IF(C1467=DATE(2026,11,29),"培训；注册午餐；早餐参数",IF(C1467=DATE(2026,11,30),"培训；注册午餐",IF(C1467=DATE(2026,12,1),"培训；注册午餐；机构晚餐",IF(C1467=Options!$B$9,"抵达；"&IF(C1467=DATE(2026,11,28),"机构晚餐","无统一供餐"),IF(C1467=Options!$B$10,"返程；"&IF(C1467=DATE(2026,12,2),"机构午餐","无统一供餐"),"差旅状态；无统一日程")))))) | E1467: =IF(C1467=Options!$B$9,Options!$C$18,0) | F1467: =IF(AND(A1467<>"",C1467<Options!$B$10),B1467*Options!$X$7,0) | G1467: =F1467*12% | H1467: =IF(A1467="",0,B1467*(86*IF(OR(C1467=Options!$B$9,C1467=Options!$B$10),75%,100%)-IF(C1467=DATE(2026,11,29),23+IF(Options!$B$8="是",22,0),0)-IF(C1467=DATE(2026,11,30),23,0)-IF(C1467=DATE(2026,12,1),59,0)-IF(C1467=DATE(2026,11,28),36,0)-IF(C1467=DATE(2026,12,2),23,0))) | I1467: =IF(AND(C1467>=DATE(2026,11,29),C1467<=DATE(2026,12,1)),B1467*60,0) | J1467: =IF(A1467="",0,B1467*(IF(C1467=DATE(2026,11,28),36,0)+IF(C1467=DATE(2026,12,1),36,0)+IF(C1467=DATE(2026,12,2),23,0))) | K1467: =IF(C1467=Options!$B$9,B1467*12,0) | L1467: =IF(C1467=Options!$B$9,B1467*Options!$Z$7,0) | M1467: 0 | N1467: =SUM(E1467:M1467)
A1468: =IF(AND(C1468>=Options!$B$9,C1468<=Options!$B$10),"Phoenix","") | B1468: =IF(A1468="","",18) | C1468: 46299 | D1468: =IF(A1468="","",IF(C1468=DATE(2026,11,29),"培训；注册午餐；早餐参数",IF(C1468=DATE(2026,11,30),"培训；注册午餐",IF(C1468=DATE(2026,12,1),"培训；注册午餐；机构晚餐",IF(C1468=Options!$B$9,"抵达；"&IF(C1468=DATE(2026,11,28),"机构晚餐","无统一供餐"),IF(C1468=Options!$B$10,"返程；"&IF(C1468=DATE(2026,12,2),"机构午餐","无统一供餐"),"差旅状态；无统一日程")))))) | E1468: =IF(C1468=Options!$B$9,Options!$C$18,0) | F1468: =IF(AND(A1468<>"",C1468<Options!$B$10),B1468*Options!$X$7,0) | G1468: =F1468*12% | H1468: =IF(A1468="",0,B1468*(86*IF(OR(C1468=Options!$B$9,C1468=Options!$B$10),75%,100%)-IF(C1468=DATE(2026,11,29),23+IF(Options!$B$8="是",22,0),0)-IF(C1468=DATE(2026,11,30),23,0)-IF(C1468=DATE(2026,12,1),59,0)-IF(C1468=DATE(2026,11,28),36,0)-IF(C1468=DATE(2026,12,2),23,0))) | I1468: =IF(AND(C1468>=DATE(2026,11,29),C1468<=DATE(2026,12,1)),B1468*60,0) | J1468: =IF(A1468="",0,B1468*(IF(C1468=DATE(2026,11,28),36,0)+IF(C1468=DATE(2026,12,1),36,0)+IF(C1468=DATE(2026,12,2),23,0))) | K1468: =IF(C1468=Options!$B$9,B1468*12,0) | L1468: =IF(C1468=Options!$B$9,B1468*Options!$Z$7,0) | M1468: 0 | N1468: =SUM(E1468:M1468)
A1469: =IF(AND(C1469>=Options!$B$9,C1469<=Options!$B$10),"Phoenix","") | B1469: =IF(A1469="","",18) | C1469: 46300 | D1469: =IF(A1469="","",IF(C1469=DATE(2026,11,29),"培训；注册午餐；早餐参数",IF(C1469=DATE(2026,11,30),"培训；注册午餐",IF(C1469=DATE(2026,12,1),"培训；注册午餐；机构晚餐",IF(C1469=Options!$B$9,"抵达；"&IF(C1469=DATE(2026,11,28),"机构晚餐","无统一供餐"),IF(C1469=Options!$B$10,"返程；"&IF(C1469=DATE(2026,12,2),"机构午餐","无统一供餐"),"差旅状态；无统一日程")))))) | E1469: =IF(C1469=Options!$B$9,Options!$C$18,0) | F1469: =IF(AND(A1469<>"",C1469<Options!$B$10),B1469*Options!$X$7,0) | G1469: =F1469*12% | H1469: =IF(A1469="",0,B1469*(86*IF(OR(C1469=Options!$B$9,C1469=Options!$B$10),75%,100%)-IF(C1469=DATE(2026,11,29),23+IF(Options!$B$8="是",22,0),0)-IF(C1469=DATE(2026,11,30),23,0)-IF(C1469=DATE(2026,12,1),59,0)-IF(C1469=DATE(2026,11,28),36,0)-IF(C1469=DATE(2026,12,2),23,0))) | I1469: =IF(AND(C1469>=DATE(2026,11,29),C1469<=DATE(2026,12,1)),B1469*60,0) | J1469: =IF(A1469="",0,B1469*(IF(C1469=DATE(2026,11,28),36,0)+IF(C1469=DATE(2026,12,1),36,0)+IF(C1469=DATE(2026,12,2),23,0))) | K1469: =IF(C1469=Options!$B$9,B1469*12,0) | L1469: =IF(C1469=Options!$B$9,B1469*Options!$Z$7,0) | M1469: 0 | N1469: =SUM(E1469:M1469)
A1470: =IF(AND(C1470>=Options!$B$9,C1470<=Options!$B$10),"Phoenix","") | B1470: =IF(A1470="","",18) | C1470: 46301 | D1470: =IF(A1470="","",IF(C1470=DATE(2026,11,29),"培训；注册午餐；早餐参数",IF(C1470=DATE(2026,11,30),"培训；注册午餐",IF(C1470=DATE(2026,12,1),"培训；注册午餐；机构晚餐",IF(C1470=Options!$B$9,"抵达；"&IF(C1470=DATE(2026,11,28),"机构晚餐","无统一供餐"),IF(C1470=Options!$B$10,"返程；"&IF(C1470=DATE(2026,12,2),"机构午餐","无统一供餐"),"差旅状态；无统一日程")))))) | E1470: =IF(C1470=Options!$B$9,Options!$C$18,0) | F1470: =IF(AND(A1470<>"",C1470<Options!$B$10),B1470*Options!$X$7,0) | G1470: =F1470*12% | H1470: =IF(A1470="",0,B1470*(86*IF(OR(C1470=Options!$B$9,C1470=Options!$B$10),75%,100%)-IF(C1470=DATE(2026,11,29),23+IF(Options!$B$8="是",22,0),0)-IF(C1470=DATE(2026,11,30),23,0)-IF(C1470=DATE(2026,12,1),59,0)-IF(C1470=DATE(2026,11,28),36,0)-IF(C1470=DATE(2026,12,2),23,0))) | I1470: =IF(AND(C1470>=DATE(2026,11,29),C1470<=DATE(2026,12,1)),B1470*60,0) | J1470: =IF(A1470="",0,B1470*(IF(C1470=DATE(2026,11,28),36,0)+IF(C1470=DATE(2026,12,1),36,0)+IF(C1470=DATE(2026,12,2),23,0))) | K1470: =IF(C1470=Options!$B$9,B1470*12,0) | L1470: =IF(C1470=Options!$B$9,B1470*Options!$Z$7,0) | M1470: 0 | N1470: =SUM(E1470:M1470)
A1471: =IF(AND(C1471>=Options!$B$9,C1471<=Options!$B$10),"Phoenix","") | B1471: =IF(A1471="","",18) | C1471: 46302 | D1471: =IF(A1471="","",IF(C1471=DATE(2026,11,29),"培训；注册午餐；早餐参数",IF(C1471=DATE(2026,11,30),"培训；注册午餐",IF(C1471=DATE(2026,12,1),"培训；注册午餐；机构晚餐",IF(C1471=Options!$B$9,"抵达；"&IF(C1471=DATE(2026,11,28),"机构晚餐","无统一供餐"),IF(C1471=Options!$B$10,"返程；"&IF(C1471=DATE(2026,12,2),"机构午餐","无统一供餐"),"差旅状态；无统一日程")))))) | E1471: =IF(C1471=Options!$B$9,Options!$C$18,0) | F1471: =IF(AND(A1471<>"",C1471<Options!$B$10),B1471*Options!$X$7,0) | G1471: =F1471*12% | H1471: =IF(A1471="",0,B1471*(86*IF(OR(C1471=Options!$B$9,C1471=Options!$B$10),75%,100%)-IF(C1471=DATE(2026,11,29),23+IF(Options!$B$8="是",22,0),0)-IF(C1471=DATE(2026,11,30),23,0)-IF(C1471=DATE(2026,12,1),59,0)-IF(C1471=DATE(2026,11,28),36,0)-IF(C1471=DATE(2026,12,2),23,0))) | I1471: =IF(AND(C1471>=DATE(2026,11,29),C1471<=DATE(2026,12,1)),B1471*60,0) | J1471: =IF(A1471="",0,B1471*(IF(C1471=DATE(2026,11,28),36,0)+IF(C1471=DATE(2026,12,1),36,0)+IF(C1471=DATE(2026,12,2),23,0))) | K1471: =IF(C1471=Options!$B$9,B1471*12,0) | L1471: =IF(C1471=Options!$B$9,B1471*Options!$Z$7,0) | M1471: 0 | N1471: =SUM(E1471:M1471)
A1472: =IF(AND(C1472>=Options!$B$9,C1472<=Options!$B$10),"Phoenix","") | B1472: =IF(A1472="","",18) | C1472: 46303 | D1472: =IF(A1472="","",IF(C1472=DATE(2026,11,29),"培训；注册午餐；早餐参数",IF(C1472=DATE(2026,11,30),"培训；注册午餐",IF(C1472=DATE(2026,12,1),"培训；注册午餐；机构晚餐",IF(C1472=Options!$B$9,"抵达；"&IF(C1472=DATE(2026,11,28),"机构晚餐","无统一供餐"),IF(C1472=Options!$B$10,"返程；"&IF(C1472=DATE(2026,12,2),"机构午餐","无统一供餐"),"差旅状态；无统一日程")))))) | E1472: =IF(C1472=Options!$B$9,Options!$C$18,0) | F1472: =IF(AND(A1472<>"",C1472<Options!$B$10),B1472*Options!$X$7,0) | G1472: =F1472*12% | H1472: =IF(A1472="",0,B1472*(86*IF(OR(C1472=Options!$B$9,C1472=Options!$B$10),75%,100%)-IF(C1472=DATE(2026,11,29),23+IF(Options!$B$8="是",22,0),0)-IF(C1472=DATE(2026,11,30),23,0)-IF(C1472=DATE(2026,12,1),59,0)-IF(C1472=DATE(2026,11,28),36,0)-IF(C1472=DATE(2026,12,2),23,0))) | I1472: =IF(AND(C1472>=DATE(2026,11,29),C1472<=DATE(2026,12,1)),B1472*60,0) | J1472: =IF(A1472="",0,B1472*(IF(C1472=DATE(2026,11,28),36,0)+IF(C1472=DATE(2026,12,1),36,0)+IF(C1472=DATE(2026,12,2),23,0))) | K1472: =IF(C1472=Options!$B$9,B1472*12,0) | L1472: =IF(C1472=Options!$B$9,B1472*Options!$Z$7,0) | M1472: 0 | N1472: =SUM(E1472:M1472)
A1473: =IF(AND(C1473>=Options!$B$9,C1473<=Options!$B$10),"Phoenix","") | B1473: =IF(A1473="","",18) | C1473: 46304 | D1473: =IF(A1473="","",IF(C1473=DATE(2026,11,29),"培训；注册午餐；早餐参数",IF(C1473=DATE(2026,11,30),"培训；注册午餐",IF(C1473=DATE(2026,12,1),"培训；注册午餐；机构晚餐",IF(C1473=Options!$B$9,"抵达；"&IF(C1473=DATE(2026,11,28),"机构晚餐","无统一供餐"),IF(C1473=Options!$B$10,"返程；"&IF(C1473=DATE(2026,12,2),"机构午餐","无统一供餐"),"差旅状态；无统一日程")))))) | E1473: =IF(C1473=Options!$B$9,Options!$C$18,0) | F1473: =IF(AND(A1473<>"",C1473<Options!$B$10),B1473*Options!$X$7,0) | G1473: =F1473*12% | H1473: =IF(A1473="",0,B1473*(86*IF(OR(C1473=Options!$B$9,C1473=Options!$B$10),75%,100%)-IF(C1473=DATE(2026,11,29),23+IF(Options!$B$8="是",22,0),0)-IF(C1473=DATE(2026,11,30),23,0)-IF(C1473=DATE(2026,12,1),59,0)-IF(C1473=DATE(2026,11,28),36,0)-IF(C1473=DATE(2026,12,2),23,0))) | I1473: =IF(AND(C1473>=DATE(2026,11,29),C1473<=DATE(2026,12,1)),B1473*60,0) | J1473: =IF(A1473="",0,B1473*(IF(C1473=DATE(2026,11,28),36,0)+IF(C1473=DATE(2026,12,1),36,0)+IF(C1473=DATE(2026,12,2),23,0))) | K1473: =IF(C1473=Options!$B$9,B1473*12,0) | L1473: =IF(C1473=Options!$B$9,B1473*Options!$Z$7,0) | M1473: 0 | N1473: =SUM(E1473:M1473)
A1474: =IF(AND(C1474>=Options!$B$9,C1474<=Options!$B$10),"Phoenix","") | B1474: =IF(A1474="","",18) | C1474: 46305 | D1474: =IF(A1474="","",IF(C1474=DATE(2026,11,29),"培训；注册午餐；早餐参数",IF(C1474=DATE(2026,11,30),"培训；注册午餐",IF(C1474=DATE(2026,12,1),"培训；注册午餐；机构晚餐",IF(C1474=Options!$B$9,"抵达；"&IF(C1474=DATE(2026,11,28),"机构晚餐","无统一供餐"),IF(C1474=Options!$B$10,"返程；"&IF(C1474=DATE(2026,12,2),"机构午餐","无统一供餐"),"差旅状态；无统一日程")))))) | E1474: =IF(C1474=Options!$B$9,Options!$C$18,0) | F1474: =IF(AND(A1474<>"",C1474<Options!$B$10),B1474*Options!$X$7,0) | G1474: =F1474*12% | H1474: =IF(A1474="",0,B1474*(86*IF(OR(C1474=Options!$B$9,C1474=Options!$B$10),75%,100%)-IF(C1474=DATE(2026,11,29),23+IF(Options!$B$8="是",22,0),0)-IF(C1474=DATE(2026,11,30),23,0)-IF(C1474=DATE(2026,12,1),59,0)-IF(C1474=DATE(2026,11,28),36,0)-IF(C1474=DATE(2026,12,2),23,0))) | I1474: =IF(AND(C1474>=DATE(2026,11,29),C1474<=DATE(2026,12,1)),B1474*60,0) | J1474: =IF(A1474="",0,B1474*(IF(C1474=DATE(2026,11,28),36,0)+IF(C1474=DATE(2026,12,1),36,0)+IF(C1474=DATE(2026,12,2),23,0))) | K1474: =IF(C1474=Options!$B$9,B1474*12,0) | L1474: =IF(C1474=Options!$B$9,B1474*Options!$Z$7,0) | M1474: 0 | N1474: =SUM(E1474:M1474)
A1475: =IF(AND(C1475>=Options!$B$9,C1475<=Options!$B$10),"Phoenix","") | B1475: =IF(A1475="","",18) | C1475: 46306 | D1475: =IF(A1475="","",IF(C1475=DATE(2026,11,29),"培训；注册午餐；早餐参数",IF(C1475=DATE(2026,11,30),"培训；注册午餐",IF(C1475=DATE(2026,12,1),"培训；注册午餐；机构晚餐",IF(C1475=Options!$B$9,"抵达；"&IF(C1475=DATE(2026,11,28),"机构晚餐","无统一供餐"),IF(C1475=Options!$B$10,"返程；"&IF(C1475=DATE(2026,12,2),"机构午餐","无统一供餐"),"差旅状态；无统一日程")))))) | E1475: =IF(C1475=Options!$B$9,Options!$C$18,0) | F1475: =IF(AND(A1475<>"",C1475<Options!$B$10),B1475*Options!$X$7,0) | G1475: =F1475*12% | H1475: =IF(A1475="",0,B1475*(86*IF(OR(C1475=Options!$B$9,C1475=Options!$B$10),75%,100%)-IF(C1475=DATE(2026,11,29),23+IF(Options!$B$8="是",22,0),0)-IF(C1475=DATE(2026,11,30),23,0)-IF(C1475=DATE(2026,12,1),59,0)-IF(C1475=DATE(2026,11,28),36,0)-IF(C1475=DATE(2026,12,2),23,0))) | I1475: =IF(AND(C1475>=DATE(2026,11,29),C1475<=DATE(2026,12,1)),B1475*60,0) | J1475: =IF(A1475="",0,B1475*(IF(C1475=DATE(2026,11,28),36,0)+IF(C1475=DATE(2026,12,1),36,0)+IF(C1475=DATE(2026,12,2),23,0))) | K1475: =IF(C1475=Options!$B$9,B1475*12,0) | L1475: =IF(C1475=Options!$B$9,B1475*Options!$Z$7,0) | M1475: 0 | N1475: =SUM(E1475:M1475)
A1476: =IF(AND(C1476>=Options!$B$9,C1476<=Options!$B$10),"Phoenix","") | B1476: =IF(A1476="","",18) | C1476: 46307 | D1476: =IF(A1476="","",IF(C1476=DATE(2026,11,29),"培训；注册午餐；早餐参数",IF(C1476=DATE(2026,11,30),"培训；注册午餐",IF(C1476=DATE(2026,12,1),"培训；注册午餐；机构晚餐",IF(C1476=Options!$B$9,"抵达；"&IF(C1476=DATE(2026,11,28),"机构晚餐","无统一供餐"),IF(C1476=Options!$B$10,"返程；"&IF(C1476=DATE(2026,12,2),"机构午餐","无统一供餐"),"差旅状态；无统一日程")))))) | E1476: =IF(C1476=Options!$B$9,Options!$C$18,0) | F1476: =IF(AND(A1476<>"",C1476<Options!$B$10),B1476*Options!$X$7,0) | G1476: =F1476*12% | H1476: =IF(A1476="",0,B1476*(86*IF(OR(C1476=Options!$B$9,C1476=Options!$B$10),75%,100%)-IF(C1476=DATE(2026,11,29),23+IF(Options!$B$8="是",22,0),0)-IF(C1476=DATE(2026,11,30),23,0)-IF(C1476=DATE(2026,12,1),59,0)-IF(C1476=DATE(2026,11,28),36,0)-IF(C1476=DATE(2026,12,2),23,0))) | I1476: =IF(AND(C1476>=DATE(2026,11,29),C1476<=DATE(2026,12,1)),B1476*60,0) | J1476: =IF(A1476="",0,B1476*(IF(C1476=DATE(2026,11,28),36,0)+IF(C1476=DATE(2026,12,1),36,0)+IF(C1476=DATE(2026,12,2),23,0))) | K1476: =IF(C1476=Options!$B$9,B1476*12,0) | L1476: =IF(C1476=Options!$B$9,B1476*Options!$Z$7,0) | M1476: 0 | N1476: =SUM(E1476:M1476)
... A1829: =IF(AND(C1829>=Options!$B$9,C1829<=Options!$B$10),"Phoenix","") | B1829: =IF(A1829="","",18) | C1829: 46660 | D1829: =IF(A1829="","",IF(C1829=DATE(2026,11,29),"培训；注册午餐；早餐参数",IF(C1829=DATE(2026,11,30),"培训；注册午餐",IF(C1829=DATE(2026,12,1),"培训；注册午餐；机构晚餐",IF(C1829=Options!$B$9,"抵达；"&IF(C1829=DATE(2026,11,28),"机构晚餐","无统一供餐"),IF(C1829=Options!$B$10,"返程；"&IF(C1829=DATE(2026,12,2),"机构午餐","无统一供餐"),"差旅状态；无统一日程")))))) | E1829: =IF(C1829=Options!$B$9,Options!$C$18,0) | F1829: =IF(AND(A1829<>"",C1829<Options!$B$10),B1829*Options!$X$7,0) | G1829: =F1829*12% | H1829: =IF(A1829="",0,B1829*(86*IF(OR(C1829=Options!$B$9,C1829=Options!$B$10),75%,100%)-IF(C1829=DATE(2026,11,29),23+IF(Options!$B$8="是",22,0),0)-IF(C1829=DATE(2026,11,30),23,0)-IF(C1829=DATE(2026,12,1),59,0)-IF(C1829=DATE(2026,11,28),36,0)-IF(C1829=DATE(2026,12,2),23,0))) | I1829: =IF(AND(C1829>=DATE(2026,11,29),C1829<=DATE(2026,12,1)),B1829*60,0) | J1829: =IF(A1829="",0,B1829*(IF(C1829=DATE(2026,11,28),36,0)+IF(C1829=DATE(2026,12,1),36,0)+IF(C1829=DATE(2026,12,2),23,0))) | K1829: =IF(C1829=Options!$B$9,B1829*12,0) | L1829: =IF(C1829=Options!$B$9,B1829*Options!$Z$7,0) | M1829: 0 | N1829: =SUM(E1829:M1829)
A1830: =IF(AND(C1830>=Options!$B$9,C1830<=Options!$B$10),"Phoenix","") | B1830: =IF(A1830="","",24) | C1830: 46296 | D1830: =IF(A1830="","",IF(C1830=DATE(2026,11,29),"培训；注册午餐；早餐参数",IF(C1830=DATE(2026,11,30),"培训；注册午餐",IF(C1830=DATE(2026,12,1),"培训；注册午餐；机构晚餐",IF(C1830=Options!$B$9,"抵达；"&IF(C1830=DATE(2026,11,28),"机构晚餐","无统一供餐"),IF(C1830=Options!$B$10,"返程；"&IF(C1830=DATE(2026,12,2),"机构午餐","无统一供餐"),"差旅状态；无统一日程")))))) | E1830: =IF(C1830=Options!$B$9,Options!$C$19,0) | F1830: =IF(AND(A1830<>"",C1830<Options!$B$10),B1830*Options!$X$7,0) | G1830: =F1830*12% | H1830: =IF(A1830="",0,B1830*(86*IF(OR(C1830=Options!$B$9,C1830=Options!$B$10),75%,100%)-IF(C1830=DATE(2026,11,29),23+IF(Options!$B$8="是",22,0),0)-IF(C1830=DATE(2026,11,30),23,0)-IF(C1830=DATE(2026,12,1),59,0)-IF(C1830=DATE(2026,11,28),36,0)-IF(C1830=DATE(2026,12,2),23,0))) | I1830: =IF(AND(C1830>=DATE(2026,11,29),C1830<=DATE(2026,12,1)),B1830*60,0) | J1830: =IF(A1830="",0,B1830*(IF(C1830=DATE(2026,11,28),36,0)+IF(C1830=DATE(2026,12,1),36,0)+IF(C1830=DATE(2026,12,2),23,0))) | K1830: =IF(C1830=Options!$B$9,B1830*12,0) | L1830: =IF(C1830=Options!$B$9,B1830*Options!$Z$7,0) | M1830: 0 | N1830: =SUM(E1830:M1830)
A1831: =IF(AND(C1831>=Options!$B$9,C1831<=Options!$B$10),"Phoenix","") | B1831: =IF(A1831="","",24) | C1831: 46297 | D1831: =IF(A1831="","",IF(C1831=DATE(2026,11,29),"培训；注册午餐；早餐参数",IF(C1831=DATE(2026,11,30),"培训；注册午餐",IF(C1831=DATE(2026,12,1),"培训；注册午餐；机构晚餐",IF(C1831=Options!$B$9,"抵达；"&IF(C1831=DATE(2026,11,28),"机构晚餐","无统一供餐"),IF(C1831=Options!$B$10,"返程；"&IF(C1831=DATE(2026,12,2),"机构午餐","无统一供餐"),"差旅状态；无统一日程")))))) | E1831: =IF(C1831=Options!$B$9,Options!$C$19,0) | F1831: =IF(AND(A1831<>"",C1831<Options!$B$10),B1831*Options!$X$7,0) | G1831: =F1831*12% | H1831: =IF(A1831="",0,B1831*(86*IF(OR(C1831=Options!$B$9,C1831=Options!$B$10),75%,100%)-IF(C1831=DATE(2026,11,29),23+IF(Options!$B$8="是",22,0),0)-IF(C1831=DATE(2026,11,30),23,0)-IF(C1831=DATE(2026,12,1),59,0)-IF(C1831=DATE(2026,11,28),36,0)-IF(C1831=DATE(2026,12,2),23,0))) | I1831: =IF(AND(C1831>=DATE(2026,11,29),C1831<=DATE(2026,12,1)),B1831*60,0) | J1831: =IF(A1831="",0,B1831*(IF(C1831=DATE(2026,11,28),36,0)+IF(C1831=DATE(2026,12,1),36,0)+IF(C1831=DATE(2026,12,2),23,0))) | K1831: =IF(C1831=Options!$B$9,B1831*12,0) | L1831: =IF(C1831=Options!$B$9,B1831*Options!$Z$7,0) | M1831: 0 | N1831: =SUM(E1831:M1831)
A1832: =IF(AND(C1832>=Options!$B$9,C1832<=Options!$B$10),"Phoenix","") | B1832: =IF(A1832="","",24) | C1832: 46298 | D1832: =IF(A1832="","",IF(C1832=DATE(2026,11,29),"培训；注册午餐；早餐参数",IF(C1832=DATE(2026,11,30),"培训；注册午餐",IF(C1832=DATE(2026,12,1),"培训；注册午餐；机构晚餐",IF(C1832=Options!$B$9,"抵达；"&IF(C1832=DATE(2026,11,28),"机构晚餐","无统一供餐"),IF(C1832=Options!$B$10,"返程；"&IF(C1832=DATE(2026,12,2),"机构午餐","无统一供餐"),"差旅状态；无统一日程")))))) | E1832: =IF(C1832=Options!$B$9,Options!$C$19,0) | F1832: =IF(AND(A1832<>"",C1832<Options!$B$10),B1832*Options!$X$7,0) | G1832: =F1832*12% | H1832: =IF(A1832="",0,B1832*(86*IF(OR(C1832=Options!$B$9,C1832=Options!$B$10),75%,100%)-IF(C1832=DATE(2026,11,29),23+IF(Options!$B$8="是",22,0),0)-IF(C1832=DATE(2026,11,30),23,0)-IF(C1832=DATE(2026,12,1),59,0)-IF(C1832=DATE(2026,11,28),36,0)-IF(C1832=DATE(2026,12,2),23,0))) | I1832: =IF(AND(C1832>=DATE(2026,11,29),C1832<=DATE(2026,12,1)),B1832*60,0) | J1832: =IF(A1832="",0,B1832*(IF(C1832=DATE(2026,11,28),36,0)+IF(C1832=DATE(2026,12,1),36,0)+IF(C1832=DATE(2026,12,2),23,0))) | K1832: =IF(C1832=Options!$B$9,B1832*12,0) | L1832: =IF(C1832=Options!$B$9,B1832*Options!$Z$7,0) | M1832: 0 | N1832: =SUM(E1832:M1832)
A1833: =IF(AND(C1833>=Options!$B$9,C1833<=Options!$B$10),"Phoenix","") | B1833: =IF(A1833="","",24) | C1833: 46299 | D1833: =IF(A1833="","",IF(C1833=DATE(2026,11,29),"培训；注册午餐；早餐参数",IF(C1833=DATE(2026,11,30),"培训；注册午餐",IF(C1833=DATE(2026,12,1),"培训；注册午餐；机构晚餐",IF(C1833=Options!$B$9,"抵达；"&IF(C1833=DATE(2026,11,28),"机构晚餐","无统一供餐"),IF(C1833=Options!$B$10,"返程；"&IF(C1833=DATE(2026,12,2),"机构午餐","无统一供餐"),"差旅状态；无统一日程")))))) | E1833: =IF(C1833=Options!$B$9,Options!$C$19,0) | F1833: =IF(AND(A1833<>"",C1833<Options!$B$10),B1833*Options!$X$7,0) | G1833: =F1833*12% | H1833: =IF(A1833="",0,B1833*(86*IF(OR(C1833=Options!$B$9,C1833=Options!$B$10),75%,100%)-IF(C1833=DATE(2026,11,29),23+IF(Options!$B$8="是",22,0),0)-IF(C1833=DATE(2026,11,30),23,0)-IF(C1833=DATE(2026,12,1),59,0)-IF(C1833=DATE(2026,11,28),36,0)-IF(C1833=DATE(2026,12,2),23,0))) | I1833: =IF(AND(C1833>=DATE(2026,11,29),C1833<=DATE(2026,12,1)),B1833*60,0) | J1833: =IF(A1833="",0,B1833*(IF(C1833=DATE(2026,11,28),36,0)+IF(C1833=DATE(2026,12,1),36,0)+IF(C1833=DATE(2026,12,2),23,0))) | K1833: =IF(C1833=Options!$B$9,B1833*12,0) | L1833: =IF(C1833=Options!$B$9,B1833*Options!$Z$7,0) | M1833: 0 | N1833: =SUM(E1833:M1833)
A1834: =IF(AND(C1834>=Options!$B$9,C1834<=Options!$B$10),"Phoenix","") | B1834: =IF(A1834="","",24) | C1834: 46300 | D1834: =IF(A1834="","",IF(C1834=DATE(2026,11,29),"培训；注册午餐；早餐参数",IF(C1834=DATE(2026,11,30),"培训；注册午餐",IF(C1834=DATE(2026,12,1),"培训；注册午餐；机构晚餐",IF(C1834=Options!$B$9,"抵达；"&IF(C1834=DATE(2026,11,28),"机构晚餐","无统一供餐"),IF(C1834=Options!$B$10,"返程；"&IF(C1834=DATE(2026,12,2),"机构午餐","无统一供餐"),"差旅状态；无统一日程")))))) | E1834: =IF(C1834=Options!$B$9,Options!$C$19,0) | F1834: =IF(AND(A1834<>"",C1834<Options!$B$10),B1834*Options!$X$7,0) | G1834: =F1834*12% | H1834: =IF(A1834="",0,B1834*(86*IF(OR(C1834=Options!$B$9,C1834=Options!$B$10),75%,100%)-IF(C1834=DATE(2026,11,29),23+IF(Options!$B$8="是",22,0),0)-IF(C1834=DATE(2026,11,30),23,0)-IF(C1834=DATE(2026,12,1),59,0)-IF(C1834=DATE(2026,11,28),36,0)-IF(C1834=DATE(2026,12,2),23,0))) | I1834: =IF(AND(C1834>=DATE(2026,11,29),C1834<=DATE(2026,12,1)),B1834*60,0) | J1834: =IF(A1834="",0,B1834*(IF(C1834=DATE(2026,11,28),36,0)+IF(C1834=DATE(2026,12,1),36,0)+IF(C1834=DATE(2026,12,2),23,0))) | K1834: =IF(C1834=Options!$B$9,B1834*12,0) | L1834: =IF(C1834=Options!$B$9,B1834*Options!$Z$7,0) | M1834: 0 | N1834: =SUM(E1834:M1834)
A1835: =IF(AND(C1835>=Options!$B$9,C1835<=Options!$B$10),"Phoenix","") | B1835: =IF(A1835="","",24) | C1835: 46301 | D1835: =IF(A1835="","",IF(C1835=DATE(2026,11,29),"培训；注册午餐；早餐参数",IF(C1835=DATE(2026,11,30),"培训；注册午餐",IF(C1835=DATE(2026,12,1),"培训；注册午餐；机构晚餐",IF(C1835=Options!$B$9,"抵达；"&IF(C1835=DATE(2026,11,28),"机构晚餐","无统一供餐"),IF(C1835=Options!$B$10,"返程；"&IF(C1835=DATE(2026,12,2),"机构午餐","无统一供餐"),"差旅状态；无统一日程")))))) | E1835: =IF(C1835=Options!$B$9,Options!$C$19,0) | F1835: =IF(AND(A1835<>"",C1835<Options!$B$10),B1835*Options!$X$7,0) | G1835: =F1835*12% | H1835: =IF(A1835="",0,B1835*(86*IF(OR(C1835=Options!$B$9,C1835=Options!$B$10),75%,100%)-IF(C1835=DATE(2026,11,29),23+IF(Options!$B$8="是",22,0),0)-IF(C1835=DATE(2026,11,30),23,0)-IF(C1835=DATE(2026,12,1),59,0)-IF(C1835=DATE(2026,11,28),36,0)-IF(C1835=DATE(2026,12,2),23,0))) | I1835: =IF(AND(C1835>=DATE(2026,11,29),C1835<=DATE(2026,12,1)),B1835*60,0) | J1835: =IF(A1835="",0,B1835*(IF(C1835=DATE(2026,11,28),36,0)+IF(C1835=DATE(2026,12,1),36,0)+IF(C1835=DATE(2026,12,2),23,0))) | K1835: =IF(C1835=Options!$B$9,B1835*12,0) | L1835: =IF(C1835=Options!$B$9,B1835*Options!$Z$7,0) | M1835: 0 | N1835: =SUM(E1835:M1835)
A1836: =IF(AND(C1836>=Options!$B$9,C1836<=Options!$B$10),"Phoenix","") | B1836: =IF(A1836="","",24) | C1836: 46302 | D1836: =IF(A1836="","",IF(C1836=DATE(2026,11,29),"培训；注册午餐；早餐参数",IF(C1836=DATE(2026,11,30),"培训；注册午餐",IF(C1836=DATE(2026,12,1),"培训；注册午餐；机构晚餐",IF(C1836=Options!$B$9,"抵达；"&IF(C1836=DATE(2026,11,28),"机构晚餐","无统一供餐"),IF(C1836=Options!$B$10,"返程；"&IF(C1836=DATE(2026,12,2),"机构午餐","无统一供餐"),"差旅状态；无统一日程")))))) | E1836: =IF(C1836=Options!$B$9,Options!$C$19,0) | F1836: =IF(AND(A1836<>"",C1836<Options!$B$10),B1836*Options!$X$7,0) | G1836: =F1836*12% | H1836: =IF(A1836="",0,B1836*(86*IF(OR(C1836=Options!$B$9,C1836=Options!$B$10),75%,100%)-IF(C1836=DATE(2026,11,29),23+IF(Options!$B$8="是",22,0),0)-IF(C1836=DATE(2026,11,30),23,0)-IF(C1836=DATE(2026,12,1),59,0)-IF(C1836=DATE(2026,11,28),36,0)-IF(C1836=DATE(2026,12,2),23,0))) | I1836: =IF(AND(C1836>=DATE(2026,11,29),C1836<=DATE(2026,12,1)),B1836*60,0) | J1836: =IF(A1836="",0,B1836*(IF(C1836=DATE(2026,11,28),36,0)+IF(C1836=DATE(2026,12,1),36,0)+IF(C1836=DATE(2026,12,2),23,0))) | K1836: =IF(C1836=Options!$B$9,B1836*12,0) | L1836: =IF(C1836=Options!$B$9,B1836*Options!$Z$7,0) | M1836: 0 | N1836: =SUM(E1836:M1836)
A1837: =IF(AND(C1837>=Options!$B$9,C1837<=Options!$B$10),"Phoenix","") | B1837: =IF(A1837="","",24) | C1837: 46303 | D1837: =IF(A1837="","",IF(C1837=DATE(2026,11,29),"培训；注册午餐；早餐参数",IF(C1837=DATE(2026,11,30),"培训；注册午餐",IF(C1837=DATE(2026,12,1),"培训；注册午餐；机构晚餐",IF(C1837=Options!$B$9,"抵达；"&IF(C1837=DATE(2026,11,28),"机构晚餐","无统一供餐"),IF(C1837=Options!$B$10,"返程；"&IF(C1837=DATE(2026,12,2),"机构午餐","无统一供餐"),"差旅状态；无统一日程")))))) | E1837: =IF(C1837=Options!$B$9,Options!$C$19,0) | F1837: =IF(AND(A1837<>"",C1837<Options!$B$10),B1837*Options!$X$7,0) | G1837: =F1837*12% | H1837: =IF(A1837="",0,B1837*(86*IF(OR(C1837=Options!$B$9,C1837=Options!$B$10),75%,100%)-IF(C1837=DATE(2026,11,29),23+IF(Options!$B$8="是",22,0),0)-IF(C1837=DATE(2026,11,30),23,0)-IF(C1837=DATE(2026,12,1),59,0)-IF(C1837=DATE(2026,11,28),36,0)-IF(C1837=DATE(2026,12,2),23,0))) | I1837: =IF(AND(C1837>=DATE(2026,11,29),C1837<=DATE(2026,12,1)),B1837*60,0) | J1837: =IF(A1837="",0,B1837*(IF(C1837=DATE(2026,11,28),36,0)+IF(C1837=DATE(2026,12,1),36,0)+IF(C1837=DATE(2026,12,2),23,0))) | K1837: =IF(C1837=Options!$B$9,B1837*12,0) | L1837: =IF(C1837=Options!$B$9,B1837*Options!$Z$7,0) | M1837: 0 | N1837: =SUM(E1837:M1837)
A1838: =IF(AND(C1838>=Options!$B$9,C1838<=Options!$B$10),"Phoenix","") | B1838: =IF(A1838="","",24) | C1838: 46304 | D1838: =IF(A1838="","",IF(C1838=DATE(2026,11,29),"培训；注册午餐；早餐参数",IF(C1838=DATE(2026,11,30),"培训；注册午餐",IF(C1838=DATE(2026,12,1),"培训；注册午餐；机构晚餐",IF(C1838=Options!$B$9,"抵达；"&IF(C1838=DATE(2026,11,28),"机构晚餐","无统一供餐"),IF(C1838=Options!$B$10,"返程；"&IF(C1838=DATE(2026,12,2),"机构午餐","无统一供餐"),"差旅状态；无统一日程")))))) | E1838: =IF(C1838=Options!$B$9,Options!$C$19,0) | F1838: =IF(AND(A1838<>"",C1838<Options!$B$10),B1838*Options!$X$7,0) | G1838: =F1838*12% | H1838: =IF(A1838="",0,B1838*(86*IF(OR(C1838=Options!$B$9,C1838=Options!$B$10),75%,100%)-IF(C1838=DATE(2026,11,29),23+IF(Options!$B$8="是",22,0),0)-IF(C1838=DATE(2026,11,30),23,0)-IF(C1838=DATE(2026,12,1),59,0)-IF(C1838=DATE(2026,11,28),36,0)-IF(C1838=DATE(2026,12,2),23,0))) | I1838: =IF(AND(C1838>=DATE(2026,11,29),C1838<=DATE(2026,12,1)),B1838*60,0) | J1838: =IF(A1838="",0,B1838*(IF(C1838=DATE(2026,11,28),36,0)+IF(C1838=DATE(2026,12,1),36,0)+IF(C1838=DATE(2026,12,2),23,0))) | K1838: =IF(C1838=Options!$B$9,B1838*12,0) | L1838: =IF(C1838=Options!$B$9,B1838*Options!$Z$7,0) | M1838: 0 | N1838: =SUM(E1838:M1838)
A1839: =IF(AND(C1839>=Options!$B$9,C1839<=Options!$B$10),"Phoenix","") | B1839: =IF(A1839="","",24) | C1839: 46305 | D1839: =IF(A1839="","",IF(C1839=DATE(2026,11,29),"培训；注册午餐；早餐参数",IF(C1839=DATE(2026,11,30),"培训；注册午餐",IF(C1839=DATE(2026,12,1),"培训；注册午餐；机构晚餐",IF(C1839=Options!$B$9,"抵达；"&IF(C1839=DATE(2026,11,28),"机构晚餐","无统一供餐"),IF(C1839=Options!$B$10,"返程；"&IF(C1839=DATE(2026,12,2),"机构午餐","无统一供餐"),"差旅状态；无统一日程")))))) | E1839: =IF(C1839=Options!$B$9,Options!$C$19,0) | F1839: =IF(AND(A1839<>"",C1839<Options!$B$10),B1839*Options!$X$7,0) | G1839: =F1839*12% | H1839: =IF(A1839="",0,B1839*(86*IF(OR(C1839=Options!$B$9,C1839=Options!$B$10),75%,100%)-IF(C1839=DATE(2026,11,29),23+IF(Options!$B$8="是",22,0),0)-IF(C1839=DATE(2026,11,30),23,0)-IF(C1839=DATE(2026,12,1),59,0)-IF(C1839=DATE(2026,11,28),36,0)-IF(C1839=DATE(2026,12,2),23,0))) | I1839: =IF(AND(C1839>=DATE(2026,11,29),C1839<=DATE(2026,12,1)),B1839*60,0) | J1839: =IF(A1839="",0,B1839*(IF(C1839=DATE(2026,11,28),36,0)+IF(C1839=DATE(2026,12,1),36,0)+IF(C1839=DATE(2026,12,2),23,0))) | K1839: =IF(C1839=Options!$B$9,B1839*12,0) | L1839: =IF(C1839=Options!$B$9,B1839*Options!$Z$7,0) | M1839: 0 | N1839: =SUM(E1839:M1839)
A1840: =IF(AND(C1840>=Options!$B$9,C1840<=Options!$B$10),"Phoenix","") | B1840: =IF(A1840="","",24) | C1840: 46306 | D1840: =IF(A1840="","",IF(C1840=DATE(2026,11,29),"培训；注册午餐；早餐参数",IF(C1840=DATE(2026,11,30),"培训；注册午餐",IF(C1840=DATE(2026,12,1),"培训；注册午餐；机构晚餐",IF(C1840=Options!$B$9,"抵达；"&IF(C1840=DATE(2026,11,28),"机构晚餐","无统一供餐"),IF(C1840=Options!$B$10,"返程；"&IF(C1840=DATE(2026,12,2),"机构午餐","无统一供餐"),"差旅状态；无统一日程")))))) | E1840: =IF(C1840=Options!$B$9,Options!$C$19,0) | F1840: =IF(AND(A1840<>"",C1840<Options!$B$10),B1840*Options!$X$7,0) | G1840: =F1840*12% | H1840: =IF(A1840="",0,B1840*(86*IF(OR(C1840=Options!$B$9,C1840=Options!$B$10),75%,100%)-IF(C1840=DATE(2026,11,29),23+IF(Options!$B$8="是",22,0),0)-IF(C1840=DATE(2026,11,30),23,0)-IF(C1840=DATE(2026,12,1),59,0)-IF(C1840=DATE(2026,11,28),36,0)-IF(C1840=DATE(2026,12,2),23,0))) | I1840: =IF(AND(C1840>=DATE(2026,11,29),C1840<=DATE(2026,12,1)),B1840*60,0) | J1840: =IF(A1840="",0,B1840*(IF(C1840=DATE(2026,11,28),36,0)+IF(C1840=DATE(2026,12,1),36,0)+IF(C1840=DATE(2026,12,2),23,0))) | K1840: =IF(C1840=Options!$B$9,B1840*12,0) | L1840: =IF(C1840=Options!$B$9,B1840*Options!$Z$7,0) | M1840: 0 | N1840: =SUM(E1840:M1840)
A1841: =IF(AND(C1841>=Options!$B$9,C1841<=Options!$B$10),"Phoenix","") | B1841: =IF(A1841="","",24) | C1841: 46307 | D1841: =IF(A1841="","",IF(C1841=DATE(2026,11,29),"培训；注册午餐；早餐参数",IF(C1841=DATE(2026,11,30),"培训；注册午餐",IF(C1841=DATE(2026,12,1),"培训；注册午餐；机构晚餐",IF(C1841=Options!$B$9,"抵达；"&IF(C1841=DATE(2026,11,28),"机构晚餐","无统一供餐"),IF(C1841=Options!$B$10,"返程；"&IF(C1841=DATE(2026,12,2),"机构午餐","无统一供餐"),"差旅状态；无统一日程")))))) | E1841: =IF(C1841=Options!$B$9,Options!$C$19,0) | F1841: =IF(AND(A1841<>"",C1841<Options!$B$10),B1841*Options!$X$7,0) | G1841: =F1841*12% | H1841: =IF(A1841="",0,B1841*(86*IF(OR(C1841=Options!$B$9,C1841=Options!$B$10),75%,100%)-IF(C1841=DATE(2026,11,29),23+IF(Options!$B$8="是",22,0),0)-IF(C1841=DATE(2026,11,30),23,0)-IF(C1841=DATE(2026,12,1),59,0)-IF(C1841=DATE(2026,11,28),36,0)-IF(C1841=DATE(2026,12,2),23,0))) | I1841: =IF(AND(C1841>=DATE(2026,11,29),C1841<=DATE(2026,12,1)),B1841*60,0) | J1841: =IF(A1841="",0,B1841*(IF(C1841=DATE(2026,11,28),36,0)+IF(C1841=DATE(2026,12,1),36,0)+IF(C1841=DATE(2026,12,2),23,0))) | K1841: =IF(C1841=Options!$B$9,B1841*12,0) | L1841: =IF(C1841=Options!$B$9,B1841*Options!$Z$7,0) | M1841: 0 | N1841: =SUM(E1841:M1841)
... A2194: =IF(AND(C2194>=Options!$B$9,C2194<=Options!$B$10),"Phoenix","") | B2194: =IF(A2194="","",24) | C2194: 46660 | D2194: =IF(A2194="","",IF(C2194=DATE(2026,11,29),"培训；注册午餐；早餐参数",IF(C2194=DATE(2026,11,30),"培训；注册午餐",IF(C2194=DATE(2026,12,1),"培训；注册午餐；机构晚餐",IF(C2194=Options!$B$9,"抵达；"&IF(C2194=DATE(2026,11,28),"机构晚餐","无统一供餐"),IF(C2194=Options!$B$10,"返程；"&IF(C2194=DATE(2026,12,2),"机构午餐","无统一供餐"),"差旅状态；无统一日程")))))) | E2194: =IF(C2194=Options!$B$9,Options!$C$19,0) | F2194: =IF(AND(A2194<>"",C2194<Options!$B$10),B2194*Options!$X$7,0) | G2194: =F2194*12% | H2194: =IF(A2194="",0,B2194*(86*IF(OR(C2194=Options!$B$9,C2194=Options!$B$10),75%,100%)-IF(C2194=DATE(2026,11,29),23+IF(Options!$B$8="是",22,0),0)-IF(C2194=DATE(2026,11,30),23,0)-IF(C2194=DATE(2026,12,1),59,0)-IF(C2194=DATE(2026,11,28),36,0)-IF(C2194=DATE(2026,12,2),23,0))) | I2194: =IF(AND(C2194>=DATE(2026,11,29),C2194<=DATE(2026,12,1)),B2194*60,0) | J2194: =IF(A2194="",0,B2194*(IF(C2194=DATE(2026,11,28),36,0)+IF(C2194=DATE(2026,12,1),36,0)+IF(C2194=DATE(2026,12,2),23,0))) | K2194: =IF(C2194=Options!$B$9,B2194*12,0) | L2194: =IF(C2194=Options!$B$9,B2194*Options!$Z$7,0) | M2194: 0 | N2194: =SUM(E2194:M2194)
A2195: =IF(AND(C2195>=Options!$B$9,C2195<=Options!$B$10),"Boston","") | B2195: =IF(A2195="","",18) | C2195: 46296 | D2195: =IF(A2195="","",IF(C2195=DATE(2026,11,29),"培训；注册午餐；早餐参数",IF(C2195=DATE(2026,11,30),"培训；注册午餐",IF(C2195=DATE(2026,12,1),"培训；注册午餐；机构晚餐",IF(C2195=Options!$B$9,"抵达；"&IF(C2195=DATE(2026,11,28),"机构晚餐","无统一供餐"),IF(C2195=Options!$B$10,"返程；"&IF(C2195=DATE(2026,12,2),"机构午餐","无统一供餐"),"差旅状态；无统一日程")))))) | E2195: =IF(C2195=Options!$B$9,Options!$C$20,0) | F2195: =IF(AND(A2195<>"",C2195<Options!$B$10),B2195*Options!$X$8,0) | G2195: =F2195*12% | H2195: =IF(A2195="",0,B2195*(92*IF(OR(C2195=Options!$B$9,C2195=Options!$B$10),75%,100%)-IF(C2195=DATE(2026,11,29),26+IF(Options!$B$8="是",23,0),0)-IF(C2195=DATE(2026,11,30),26,0)-IF(C2195=DATE(2026,12,1),64,0)-IF(C2195=DATE(2026,11,28),38,0)-IF(C2195=DATE(2026,12,2),26,0))) | I2195: =IF(AND(C2195>=DATE(2026,11,29),C2195<=DATE(2026,12,1)),B2195*60,0) | J2195: =IF(A2195="",0,B2195*(IF(C2195=DATE(2026,11,28),38,0)+IF(C2195=DATE(2026,12,1),38,0)+IF(C2195=DATE(2026,12,2),26,0))) | K2195: =IF(C2195=Options!$B$9,B2195*12,0) | L2195: =IF(C2195=Options!$B$9,B2195*Options!$Z$8,0) | M2195: 0 | N2195: =SUM(E2195:M2195)
A2196: =IF(AND(C2196>=Options!$B$9,C2196<=Options!$B$10),"Boston","") | B2196: =IF(A2196="","",18) | C2196: 46297 | D2196: =IF(A2196="","",IF(C2196=DATE(2026,11,29),"培训；注册午餐；早餐参数",IF(C2196=DATE(2026,11,30),"培训；注册午餐",IF(C2196=DATE(2026,12,1),"培训；注册午餐；机构晚餐",IF(C2196=Options!$B$9,"抵达；"&IF(C2196=DATE(2026,11,28),"机构晚餐","无统一供餐"),IF(C2196=Options!$B$10,"返程；"&IF(C2196=DATE(2026,12,2),"机构午餐","无统一供餐"),"差旅状态；无统一日程")))))) | E2196: =IF(C2196=Options!$B$9,Options!$C$20,0) | F2196: =IF(AND(A2196<>"",C2196<Options!$B$10),B2196*Options!$X$8,0) | G2196: =F2196*12% | H2196: =IF(A2196="",0,B2196*(92*IF(OR(C2196=Options!$B$9,C2196=Options!$B$10),75%,100%)-IF(C2196=DATE(2026,11,29),26+IF(Options!$B$8="是",23,0),0)-IF(C2196=DATE(2026,11,30),26,0)-IF(C2196=DATE(2026,12,1),64,0)-IF(C2196=DATE(2026,11,28),38,0)-IF(C2196=DATE(2026,12,2),26,0))) | I2196: =IF(AND(C2196>=DATE(2026,11,29),C2196<=DATE(2026,12,1)),B2196*60,0) | J2196: =IF(A2196="",0,B2196*(IF(C2196=DATE(2026,11,28),38,0)+IF(C2196=DATE(2026,12,1),38,0)+IF(C2196=DATE(2026,12,2),26,0))) | K2196: =IF(C2196=Options!$B$9,B2196*12,0) | L2196: =IF(C2196=Options!$B$9,B2196*Options!$Z$8,0) | M2196: 0 | N2196: =SUM(E2196:M2196)
A2197: =IF(AND(C2197>=Options!$B$9,C2197<=Options!$B$10),"Boston","") | B2197: =IF(A2197="","",18) | C2197: 46298 | D2197: =IF(A2197="","",IF(C2197=DATE(2026,11,29),"培训；注册午餐；早餐参数",IF(C2197=DATE(2026,11,30),"培训；注册午餐",IF(C2197=DATE(2026,12,1),"培训；注册午餐；机构晚餐",IF(C2197=Options!$B$9,"抵达；"&IF(C2197=DATE(2026,11,28),"机构晚餐","无统一供餐"),IF(C2197=Options!$B$10,"返程；"&IF(C2197=DATE(2026,12,2),"机构午餐","无统一供餐"),"差旅状态；无统一日程")))))) | E2197: =IF(C2197=Options!$B$9,Options!$C$20,0) | F2197: =IF(AND(A2197<>"",C2197<Options!$B$10),B2197*Options!$X$8,0) | G2197: =F2197*12% | H2197: =IF(A2197="",0,B2197*(92*IF(OR(C2197=Options!$B$9,C2197=Options!$B$10),75%,100%)-IF(C2197=DATE(2026,11,29),26+IF(Options!$B$8="是",23,0),0)-IF(C2197=DATE(2026,11,30),26,0)-IF(C2197=DATE(2026,12,1),64,0)-IF(C2197=DATE(2026,11,28),38,0)-IF(C2197=DATE(2026,12,2),26,0))) | I2197: =IF(AND(C2197>=DATE(2026,11,29),C2197<=DATE(2026,12,1)),B2197*60,0) | J2197: =IF(A2197="",0,B2197*(IF(C2197=DATE(2026,11,28),38,0)+IF(C2197=DATE(2026,12,1),38,0)+IF(C2197=DATE(2026,12,2),26,0))) | K2197: =IF(C2197=Options!$B$9,B2197*12,0) | L2197: =IF(C2197=Options!$B$9,B2197*Options!$Z$8,0) | M2197: 0 | N2197: =SUM(E2197:M2197)
A2198: =IF(AND(C2198>=Options!$B$9,C2198<=Options!$B$10),"Boston","") | B2198: =IF(A2198="","",18) | C2198: 46299 | D2198: =IF(A2198="","",IF(C2198=DATE(2026,11,29),"培训；注册午餐；早餐参数",IF(C2198=DATE(2026,11,30),"培训；注册午餐",IF(C2198=DATE(2026,12,1),"培训；注册午餐；机构晚餐",IF(C2198=Options!$B$9,"抵达；"&IF(C2198=DATE(2026,11,28),"机构晚餐","无统一供餐"),IF(C2198=Options!$B$10,"返程；"&IF(C2198=DATE(2026,12,2),"机构午餐","无统一供餐"),"差旅状态；无统一日程")))))) | E2198: =IF(C2198=Options!$B$9,Options!$C$20,0) | F2198: =IF(AND(A2198<>"",C2198<Options!$B$10),B2198*Options!$X$8,0) | G2198: =F2198*12% | H2198: =IF(A2198="",0,B2198*(92*IF(OR(C2198=Options!$B$9,C2198=Options!$B$10),75%,100%)-IF(C2198=DATE(2026,11,29),26+IF(Options!$B$8="是",23,0),0)-IF(C2198=DATE(2026,11,30),26,0)-IF(C2198=DATE(2026,12,1),64,0)-IF(C2198=DATE(2026,11,28),38,0)-IF(C2198=DATE(2026,12,2),26,0))) | I2198: =IF(AND(C2198>=DATE(2026,11,29),C2198<=DATE(2026,12,1)),B2198*60,0) | J2198: =IF(A2198="",0,B2198*(IF(C2198=DATE(2026,11,28),38,0)+IF(C2198=DATE(2026,12,1),38,0)+IF(C2198=DATE(2026,12,2),26,0))) | K2198: =IF(C2198=Options!$B$9,B2198*12,0) | L2198: =IF(C2198=Options!$B$9,B2198*Options!$Z$8,0) | M2198: 0 | N2198: =SUM(E2198:M2198)
A2199: =IF(AND(C2199>=Options!$B$9,C2199<=Options!$B$10),"Boston","") | B2199: =IF(A2199="","",18) | C2199: 46300 | D2199: =IF(A2199="","",IF(C2199=DATE(2026,11,29),"培训；注册午餐；早餐参数",IF(C2199=DATE(2026,11,30),"培训；注册午餐",IF(C2199=DATE(2026,12,1),"培训；注册午餐；机构晚餐",IF(C2199=Options!$B$9,"抵达；"&IF(C2199=DATE(2026,11,28),"机构晚餐","无统一供餐"),IF(C2199=Options!$B$10,"返程；"&IF(C2199=DATE(2026,12,2),"机构午餐","无统一供餐"),"差旅状态；无统一日程")))))) | E2199: =IF(C2199=Options!$B$9,Options!$C$20,0) | F2199: =IF(AND(A2199<>"",C2199<Options!$B$10),B2199*Options!$X$8,0) | G2199: =F2199*12% | H2199: =IF(A2199="",0,B2199*(92*IF(OR(C2199=Options!$B$9,C2199=Options!$B$10),75%,100%)-IF(C2199=DATE(2026,11,29),26+IF(Options!$B$8="是",23,0),0)-IF(C2199=DATE(2026,11,30),26,0)-IF(C2199=DATE(2026,12,1),64,0)-IF(C2199=DATE(2026,11,28),38,0)-IF(C2199=DATE(2026,12,2),26,0))) | I2199: =IF(AND(C2199>=DATE(2026,11,29),C2199<=DATE(2026,12,1)),B2199*60,0) | J2199: =IF(A2199="",0,B2199*(IF(C2199=DATE(2026,11,28),38,0)+IF(C2199=DATE(2026,12,1),38,0)+IF(C2199=DATE(2026,12,2),26,0))) | K2199: =IF(C2199=Options!$B$9,B2199*12,0) | L2199: =IF(C2199=Options!$B$9,B2199*Options!$Z$8,0) | M2199: 0 | N2199: =SUM(E2199:M2199)
A2200: =IF(AND(C2200>=Options!$B$9,C2200<=Options!$B$10),"Boston","") | B2200: =IF(A2200="","",18) | C2200: 46301 | D2200: =IF(A2200="","",IF(C2200=DATE(2026,11,29),"培训；注册午餐；早餐参数",IF(C2200=DATE(2026,11,30),"培训；注册午餐",IF(C2200=DATE(2026,12,1),"培训；注册午餐；机构晚餐",IF(C2200=Options!$B$9,"抵达；"&IF(C2200=DATE(2026,11,28),"机构晚餐","无统一供餐"),IF(C2200=Options!$B$10,"返程；"&IF(C2200=DATE(2026,12,2),"机构午餐","无统一供餐"),"差旅状态；无统一日程")))))) | E2200: =IF(C2200=Options!$B$9,Options!$C$20,0) | F2200: =IF(AND(A2200<>"",C2200<Options!$B$10),B2200*Options!$X$8,0) | G2200: =F2200*12% | H2200: =IF(A2200="",0,B2200*(92*IF(OR(C2200=Options!$B$9,C2200=Options!$B$10),75%,100%)-IF(C2200=DATE(2026,11,29),26+IF(Options!$B$8="是",23,0),0)-IF(C2200=DATE(2026,11,30),26,0)-IF(C2200=DATE(2026,12,1),64,0)-IF(C2200=DATE(2026,11,28),38,0)-IF(C2200=DATE(2026,12,2),26,0))) | I2200: =IF(AND(C2200>=DATE(2026,11,29),C2200<=DATE(2026,12,1)),B2200*60,0) | J2200: =IF(A2200="",0,B2200*(IF(C2200=DATE(2026,11,28),38,0)+IF(C2200=DATE(2026,12,1),38,0)+IF(C2200=DATE(2026,12,2),26,0))) | K2200: =IF(C2200=Options!$B$9,B2200*12,0) | L2200: =IF(C2200=Options!$B$9,B2200*Options!$Z$8,0) | M2200: 0 | N2200: =SUM(E2200:M2200)
A2201: =IF(AND(C2201>=Options!$B$9,C2201<=Options!$B$10),"Boston","") | B2201: =IF(A2201="","",18) | C2201: 46302 | D2201: =IF(A2201="","",IF(C2201=DATE(2026,11,29),"培训；注册午餐；早餐参数",IF(C2201=DATE(2026,11,30),"培训；注册午餐",IF(C2201=DATE(2026,12,1),"培训；注册午餐；机构晚餐",IF(C2201=Options!$B$9,"抵达；"&IF(C2201=DATE(2026,11,28),"机构晚餐","无统一供餐"),IF(C2201=Options!$B$10,"返程；"&IF(C2201=DATE(2026,12,2),"机构午餐","无统一供餐"),"差旅状态；无统一日程")))))) | E2201: =IF(C2201=Options!$B$9,Options!$C$20,0) | F2201: =IF(AND(A2201<>"",C2201<Options!$B$10),B2201*Options!$X$8,0) | G2201: =F2201*12% | H2201: =IF(A2201="",0,B2201*(92*IF(OR(C2201=Options!$B$9,C2201=Options!$B$10),75%,100%)-IF(C2201=DATE(2026,11,29),26+IF(Options!$B$8="是",23,0),0)-IF(C2201=DATE(2026,11,30),26,0)-IF(C2201=DATE(2026,12,1),64,0)-IF(C2201=DATE(2026,11,28),38,0)-IF(C2201=DATE(2026,12,2),26,0))) | I2201: =IF(AND(C2201>=DATE(2026,11,29),C2201<=DATE(2026,12,1)),B2201*60,0) | J2201: =IF(A2201="",0,B2201*(IF(C2201=DATE(2026,11,28),38,0)+IF(C2201=DATE(2026,12,1),38,0)+IF(C2201=DATE(2026,12,2),26,0))) | K2201: =IF(C2201=Options!$B$9,B2201*12,0) | L2201: =IF(C2201=Options!$B$9,B2201*Options!$Z$8,0) | M2201: 0 | N2201: =SUM(E2201:M2201)
A2202: =IF(AND(C2202>=Options!$B$9,C2202<=Options!$B$10),"Boston","") | B2202: =IF(A2202="","",18) | C2202: 46303 | D2202: =IF(A2202="","",IF(C2202=DATE(2026,11,29),"培训；注册午餐；早餐参数",IF(C2202=DATE(2026,11,30),"培训；注册午餐",IF(C2202=DATE(2026,12,1),"培训；注册午餐；机构晚餐",IF(C2202=Options!$B$9,"抵达；"&IF(C2202=DATE(2026,11,28),"机构晚餐","无统一供餐"),IF(C2202=Options!$B$10,"返程；"&IF(C2202=DATE(2026,12,2),"机构午餐","无统一供餐"),"差旅状态；无统一日程")))))) | E2202: =IF(C2202=Options!$B$9,Options!$C$20,0) | F2202: =IF(AND(A2202<>"",C2202<Options!$B$10),B2202*Options!$X$8,0) | G2202: =F2202*12% | H2202: =IF(A2202="",0,B2202*(92*IF(OR(C2202=Options!$B$9,C2202=Options!$B$10),75%,100%)-IF(C2202=DATE(2026,11,29),26+IF(Options!$B$8="是",23,0),0)-IF(C2202=DATE(2026,11,30),26,0)-IF(C2202=DATE(2026,12,1),64,0)-IF(C2202=DATE(2026,11,28),38,0)-IF(C2202=DATE(2026,12,2),26,0))) | I2202: =IF(AND(C2202>=DATE(2026,11,29),C2202<=DATE(2026,12,1)),B2202*60,0) | J2202: =IF(A2202="",0,B2202*(IF(C2202=DATE(2026,11,28),38,0)+IF(C2202=DATE(2026,12,1),38,0)+IF(C2202=DATE(2026,12,2),26,0))) | K2202: =IF(C2202=Options!$B$9,B2202*12,0) | L2202: =IF(C2202=Options!$B$9,B2202*Options!$Z$8,0) | M2202: 0 | N2202: =SUM(E2202:M2202)
A2203: =IF(AND(C2203>=Options!$B$9,C2203<=Options!$B$10),"Boston","") | B2203: =IF(A2203="","",18) | C2203: 46304 | D2203: =IF(A2203="","",IF(C2203=DATE(2026,11,29),"培训；注册午餐；早餐参数",IF(C2203=DATE(2026,11,30),"培训；注册午餐",IF(C2203=DATE(2026,12,1),"培训；注册午餐；机构晚餐",IF(C2203=Options!$B$9,"抵达；"&IF(C2203=DATE(2026,11,28),"机构晚餐","无统一供餐"),IF(C2203=Options!$B$10,"返程；"&IF(C2203=DATE(2026,12,2),"机构午餐","无统一供餐"),"差旅状态；无统一日程")))))) | E2203: =IF(C2203=Options!$B$9,Options!$C$20,0) | F2203: =IF(AND(A2203<>"",C2203<Options!$B$10),B2203*Options!$X$8,0) | G2203: =F2203*12% | H2203: =IF(A2203="",0,B2203*(92*IF(OR(C2203=Options!$B$9,C2203=Options!$B$10),75%,100%)-IF(C2203=DATE(2026,11,29),26+IF(Options!$B$8="是",23,0),0)-IF(C2203=DATE(2026,11,30),26,0)-IF(C2203=DATE(2026,12,1),64,0)-IF(C2203=DATE(2026,11,28),38,0)-IF(C2203=DATE(2026,12,2),26,0))) | I2203: =IF(AND(C2203>=DATE(2026,11,29),C2203<=DATE(2026,12,1)),B2203*60,0) | J2203: =IF(A2203="",0,B2203*(IF(C2203=DATE(2026,11,28),38,0)+IF(C2203=DATE(2026,12,1),38,0)+IF(C2203=DATE(2026,12,2),26,0))) | K2203: =IF(C2203=Options!$B$9,B2203*12,0) | L2203: =IF(C2203=Options!$B$9,B2203*Options!$Z$8,0) | M2203: 0 | N2203: =SUM(E2203:M2203)
A2204: =IF(AND(C2204>=Options!$B$9,C2204<=Options!$B$10),"Boston","") | B2204: =IF(A2204="","",18) | C2204: 46305 | D2204: =IF(A2204="","",IF(C2204=DATE(2026,11,29),"培训；注册午餐；早餐参数",IF(C2204=DATE(2026,11,30),"培训；注册午餐",IF(C2204=DATE(2026,12,1),"培训；注册午餐；机构晚餐",IF(C2204=Options!$B$9,"抵达；"&IF(C2204=DATE(2026,11,28),"机构晚餐","无统一供餐"),IF(C2204=Options!$B$10,"返程；"&IF(C2204=DATE(2026,12,2),"机构午餐","无统一供餐"),"差旅状态；无统一日程")))))) | E2204: =IF(C2204=Options!$B$9,Options!$C$20,0) | F2204: =IF(AND(A2204<>"",C2204<Options!$B$10),B2204*Options!$X$8,0) | G2204: =F2204*12% | H2204: =IF(A2204="",0,B2204*(92*IF(OR(C2204=Options!$B$9,C2204=Options!$B$10),75%,100%)-IF(C2204=DATE(2026,11,29),26+IF(Options!$B$8="是",23,0),0)-IF(C2204=DATE(2026,11,30),26,0)-IF(C2204=DATE(2026,12,1),64,0)-IF(C2204=DATE(2026,11,28),38,0)-IF(C2204=DATE(2026,12,2),26,0))) | I2204: =IF(AND(C2204>=DATE(2026,11,29),C2204<=DATE(2026,12,1)),B2204*60,0) | J2204: =IF(A2204="",0,B2204*(IF(C2204=DATE(2026,11,28),38,0)+IF(C2204=DATE(2026,12,1),38,0)+IF(C2204=DATE(2026,12,2),26,0))) | K2204: =IF(C2204=Options!$B$9,B2204*12,0) | L2204: =IF(C2204=Options!$B$9,B2204*Options!$Z$8,0) | M2204: 0 | N2204: =SUM(E2204:M2204)
A2205: =IF(AND(C2205>=Options!$B$9,C2205<=Options!$B$10),"Boston","") | B2205: =IF(A2205="","",18) | C2205: 46306 | D2205: =IF(A2205="","",IF(C2205=DATE(2026,11,29),"培训；注册午餐；早餐参数",IF(C2205=DATE(2026,11,30),"培训；注册午餐",IF(C2205=DATE(2026,12,1),"培训；注册午餐；机构晚餐",IF(C2205=Options!$B$9,"抵达；"&IF(C2205=DATE(2026,11,28),"机构晚餐","无统一供餐"),IF(C2205=Options!$B$10,"返程；"&IF(C2205=DATE(2026,12,2),"机构午餐","无统一供餐"),"差旅状态；无统一日程")))))) | E2205: =IF(C2205=Options!$B$9,Options!$C$20,0) | F2205: =IF(AND(A2205<>"",C2205<Options!$B$10),B2205*Options!$X$8,0) | G2205: =F2205*12% | H2205: =IF(A2205="",0,B2205*(92*IF(OR(C2205=Options!$B$9,C2205=Options!$B$10),75%,100%)-IF(C2205=DATE(2026,11,29),26+IF(Options!$B$8="是",23,0),0)-IF(C2205=DATE(2026,11,30),26,0)-IF(C2205=DATE(2026,12,1),64,0)-IF(C2205=DATE(2026,11,28),38,0)-IF(C2205=DATE(2026,12,2),26,0))) | I2205: =IF(AND(C2205>=DATE(2026,11,29),C2205<=DATE(2026,12,1)),B2205*60,0) | J2205: =IF(A2205="",0,B2205*(IF(C2205=DATE(2026,11,28),38,0)+IF(C2205=DATE(2026,12,1),38,0)+IF(C2205=DATE(2026,12,2),26,0))) | K2205: =IF(C2205=Options!$B$9,B2205*12,0) | L2205: =IF(C2205=Options!$B$9,B2205*Options!$Z$8,0) | M2205: 0 | N2205: =SUM(E2205:M2205)
A2206: =IF(AND(C2206>=Options!$B$9,C2206<=Options!$B$10),"Boston","") | B2206: =IF(A2206="","",18) | C2206: 46307 | D2206: =IF(A2206="","",IF(C2206=DATE(2026,11,29),"培训；注册午餐；早餐参数",IF(C2206=DATE(2026,11,30),"培训；注册午餐",IF(C2206=DATE(2026,12,1),"培训；注册午餐；机构晚餐",IF(C2206=Options!$B$9,"抵达；"&IF(C2206=DATE(2026,11,28),"机构晚餐","无统一供餐"),IF(C2206=Options!$B$10,"返程；"&IF(C2206=DATE(2026,12,2),"机构午餐","无统一供餐"),"差旅状态；无统一日程")))))) | E2206: =IF(C2206=Options!$B$9,Options!$C$20,0) | F2206: =IF(AND(A2206<>"",C2206<Options!$B$10),B2206*Options!$X$8,0) | G2206: =F2206*12% | H2206: =IF(A2206="",0,B2206*(92*IF(OR(C2206=Options!$B$9,C2206=Options!$B$10),75%,100%)-IF(C2206=DATE(2026,11,29),26+IF(Options!$B$8="是",23,0),0)-IF(C2206=DATE(2026,11,30),26,0)-IF(C2206=DATE(2026,12,1),64,0)-IF(C2206=DATE(2026,11,28),38,0)-IF(C2206=DATE(2026,12,2),26,0))) | I2206: =IF(AND(C2206>=DATE(2026,11,29),C2206<=DATE(2026,12,1)),B2206*60,0) | J2206: =IF(A2206="",0,B2206*(IF(C2206=DATE(2026,11,28),38,0)+IF(C2206=DATE(2026,12,1),38,0)+IF(C2206=DATE(2026,12,2),26,0))) | K2206: =IF(C2206=Options!$B$9,B2206*12,0) | L2206: =IF(C2206=Options!$B$9,B2206*Options!$Z$8,0) | M2206: 0 | N2206: =SUM(E2206:M2206)
... A2559: =IF(AND(C2559>=Options!$B$9,C2559<=Options!$B$10),"Boston","") | B2559: =IF(A2559="","",18) | C2559: 46660 | D2559: =IF(A2559="","",IF(C2559=DATE(2026,11,29),"培训；注册午餐；早餐参数",IF(C2559=DATE(2026,11,30),"培训；注册午餐",IF(C2559=DATE(2026,12,1),"培训；注册午餐；机构晚餐",IF(C2559=Options!$B$9,"抵达；"&IF(C2559=DATE(2026,11,28),"机构晚餐","无统一供餐"),IF(C2559=Options!$B$10,"返程；"&IF(C2559=DATE(2026,12,2),"机构午餐","无统一供餐"),"差旅状态；无统一日程")))))) | E2559: =IF(C2559=Options!$B$9,Options!$C$20,0) | F2559: =IF(AND(A2559<>"",C2559<Options!$B$10),B2559*Options!$X$8,0) | G2559: =F2559*12% | H2559: =IF(A2559="",0,B2559*(92*IF(OR(C2559=Options!$B$9,C2559=Options!$B$10),75%,100%)-IF(C2559=DATE(2026,11,29),26+IF(Options!$B$8="是",23,0),0)-IF(C2559=DATE(2026,11,30),26,0)-IF(C2559=DATE(2026,12,1),64,0)-IF(C2559=DATE(2026,11,28),38,0)-IF(C2559=DATE(2026,12,2),26,0))) | I2559: =IF(AND(C2559>=DATE(2026,11,29),C2559<=DATE(2026,12,1)),B2559*60,0) | J2559: =IF(A2559="",0,B2559*(IF(C2559=DATE(2026,11,28),38,0)+IF(C2559=DATE(2026,12,1),38,0)+IF(C2559=DATE(2026,12,2),26,0))) | K2559: =IF(C2559=Options!$B$9,B2559*12,0) | L2559: =IF(C2559=Options!$B$9,B2559*Options!$Z$8,0) | M2559: 0 | N2559: =SUM(E2559:M2559)
A2560: =IF(AND(C2560>=Options!$B$9,C2560<=Options!$B$10),"Boston","") | B2560: =IF(A2560="","",24) | C2560: 46296 | D2560: =IF(A2560="","",IF(C2560=DATE(2026,11,29),"培训；注册午餐；早餐参数",IF(C2560=DATE(2026,11,30),"培训；注册午餐",IF(C2560=DATE(2026,12,1),"培训；注册午餐；机构晚餐",IF(C2560=Options!$B$9,"抵达；"&IF(C2560=DATE(2026,11,28),"机构晚餐","无统一供餐"),IF(C2560=Options!$B$10,"返程；"&IF(C2560=DATE(2026,12,2),"机构午餐","无统一供餐"),"差旅状态；无统一日程")))))) | E2560: =IF(C2560=Options!$B$9,Options!$C$21,0) | F2560: =IF(AND(A2560<>"",C2560<Options!$B$10),B2560*Options!$X$8,0) | G2560: =F2560*12% | H2560: =IF(A2560="",0,B2560*(92*IF(OR(C2560=Options!$B$9,C2560=Options!$B$10),75%,100%)-IF(C2560=DATE(2026,11,29),26+IF(Options!$B$8="是",23,0),0)-IF(C2560=DATE(2026,11,30),26,0)-IF(C2560=DATE(2026,12,1),64,0)-IF(C2560=DATE(2026,11,28),38,0)-IF(C2560=DATE(2026,12,2),26,0))) | I2560: =IF(AND(C2560>=DATE(2026,11,29),C2560<=DATE(2026,12,1)),B2560*60,0) | J2560: =IF(A2560="",0,B2560*(IF(C2560=DATE(2026,11,28),38,0)+IF(C2560=DATE(2026,12,1),38,0)+IF(C2560=DATE(2026,12,2),26,0))) | K2560: =IF(C2560=Options!$B$9,B2560*12,0) | L2560: =IF(C2560=Options!$B$9,B2560*Options!$Z$8,0) | M2560: 0 | N2560: =SUM(E2560:M2560)
A2561: =IF(AND(C2561>=Options!$B$9,C2561<=Options!$B$10),"Boston","") | B2561: =IF(A2561="","",24) | C2561: 46297 | D2561: =IF(A2561="","",IF(C2561=DATE(2026,11,29),"培训；注册午餐；早餐参数",IF(C2561=DATE(2026,11,30),"培训；注册午餐",IF(C2561=DATE(2026,12,1),"培训；注册午餐；机构晚餐",IF(C2561=Options!$B$9,"抵达；"&IF(C2561=DATE(2026,11,28),"机构晚餐","无统一供餐"),IF(C2561=Options!$B$10,"返程；"&IF(C2561=DATE(2026,12,2),"机构午餐","无统一供餐"),"差旅状态；无统一日程")))))) | E2561: =IF(C2561=Options!$B$9,Options!$C$21,0) | F2561: =IF(AND(A2561<>"",C2561<Options!$B$10),B2561*Options!$X$8,0) | G2561: =F2561*12% | H2561: =IF(A2561="",0,B2561*(92*IF(OR(C2561=Options!$B$9,C2561=Options!$B$10),75%,100%)-IF(C2561=DATE(2026,11,29),26+IF(Options!$B$8="是",23,0),0)-IF(C2561=DATE(2026,11,30),26,0)-IF(C2561=DATE(2026,12,1),64,0)-IF(C2561=DATE(2026,11,28),38,0)-IF(C2561=DATE(2026,12,2),26,0))) | I2561: =IF(AND(C2561>=DATE(2026,11,29),C2561<=DATE(2026,12,1)),B2561*60,0) | J2561: =IF(A2561="",0,B2561*(IF(C2561=DATE(2026,11,28),38,0)+IF(C2561=DATE(2026,12,1),38,0)+IF(C2561=DATE(2026,12,2),26,0))) | K2561: =IF(C2561=Options!$B$9,B2561*12,0) | L2561: =IF(C2561=Options!$B$9,B2561*Options!$Z$8,0) | M2561: 0 | N2561: =SUM(E2561:M2561)
A2562: =IF(AND(C2562>=Options!$B$9,C2562<=Options!$B$10),"Boston","") | B2562: =IF(A2562="","",24) | C2562: 46298 | D2562: =IF(A2562="","",IF(C2562=DATE(2026,11,29),"培训；注册午餐；早餐参数",IF(C2562=DATE(2026,11,30),"培训；注册午餐",IF(C2562=DATE(2026,12,1),"培训；注册午餐；机构晚餐",IF(C2562=Options!$B$9,"抵达；"&IF(C2562=DATE(2026,11,28),"机构晚餐","无统一供餐"),IF(C2562=Options!$B$10,"返程；"&IF(C2562=DATE(2026,12,2),"机构午餐","无统一供餐"),"差旅状态；无统一日程")))))) | E2562: =IF(C2562=Options!$B$9,Options!$C$21,0) | F2562: =IF(AND(A2562<>"",C2562<Options!$B$10),B2562*Options!$X$8,0) | G2562: =F2562*12% | H2562: =IF(A2562="",0,B2562*(92*IF(OR(C2562=Options!$B$9,C2562=Options!$B$10),75%,100%)-IF(C2562=DATE(2026,11,29),26+IF(Options!$B$8="是",23,0),0)-IF(C2562=DATE(2026,11,30),26,0)-IF(C2562=DATE(2026,12,1),64,0)-IF(C2562=DATE(2026,11,28),38,0)-IF(C2562=DATE(2026,12,2),26,0))) | I2562: =IF(AND(C2562>=DATE(2026,11,29),C2562<=DATE(2026,12,1)),B2562*60,0) | J2562: =IF(A2562="",0,B2562*(IF(C2562=DATE(2026,11,28),38,0)+IF(C2562=DATE(2026,12,1),38,0)+IF(C2562=DATE(2026,12,2),26,0))) | K2562: =IF(C2562=Options!$B$9,B2562*12,0) | L2562: =IF(C2562=Options!$B$9,B2562*Options!$Z$8,0) | M2562: 0 | N2562: =SUM(E2562:M2562)
A2563: =IF(AND(C2563>=Options!$B$9,C2563<=Options!$B$10),"Boston","") | B2563: =IF(A2563="","",24) | C2563: 46299 | D2563: =IF(A2563="","",IF(C2563=DATE(2026,11,29),"培训；注册午餐；早餐参数",IF(C2563=DATE(2026,11,30),"培训；注册午餐",IF(C2563=DATE(2026,12,1),"培训；注册午餐；机构晚餐",IF(C2563=Options!$B$9,"抵达；"&IF(C2563=DATE(2026,11,28),"机构晚餐","无统一供餐"),IF(C2563=Options!$B$10,"返程；"&IF(C2563=DATE(2026,12,2),"机构午餐","无统一供餐"),"差旅状态；无统一日程")))))) | E2563: =IF(C2563=Options!$B$9,Options!$C$21,0) | F2563: =IF(AND(A2563<>"",C2563<Options!$B$10),B2563*Options!$X$8,0) | G2563: =F2563*12% | H2563: =IF(A2563="",0,B2563*(92*IF(OR(C2563=Options!$B$9,C2563=Options!$B$10),75%,100%)-IF(C2563=DATE(2026,11,29),26+IF(Options!$B$8="是",23,0),0)-IF(C2563=DATE(2026,11,30),26,0)-IF(C2563=DATE(2026,12,1),64,0)-IF(C2563=DATE(2026,11,28),38,0)-IF(C2563=DATE(2026,12,2),26,0))) | I2563: =IF(AND(C2563>=DATE(2026,11,29),C2563<=DATE(2026,12,1)),B2563*60,0) | J2563: =IF(A2563="",0,B2563*(IF(C2563=DATE(2026,11,28),38,0)+IF(C2563=DATE(2026,12,1),38,0)+IF(C2563=DATE(2026,12,2),26,0))) | K2563: =IF(C2563=Options!$B$9,B2563*12,0) | L2563: =IF(C2563=Options!$B$9,B2563*Options!$Z$8,0) | M2563: 0 | N2563: =SUM(E2563:M2563)
A2564: =IF(AND(C2564>=Options!$B$9,C2564<=Options!$B$10),"Boston","") | B2564: =IF(A2564="","",24) | C2564: 46300 | D2564: =IF(A2564="","",IF(C2564=DATE(2026,11,29),"培训；注册午餐；早餐参数",IF(C2564=DATE(2026,11,30),"培训；注册午餐",IF(C2564=DATE(2026,12,1),"培训；注册午餐；机构晚餐",IF(C2564=Options!$B$9,"抵达；"&IF(C2564=DATE(2026,11,28),"机构晚餐","无统一供餐"),IF(C2564=Options!$B$10,"返程；"&IF(C2564=DATE(2026,12,2),"机构午餐","无统一供餐"),"差旅状态；无统一日程")))))) | E2564: =IF(C2564=Options!$B$9,Options!$C$21,0) | F2564: =IF(AND(A2564<>"",C2564<Options!$B$10),B2564*Options!$X$8,0) | G2564: =F2564*12% | H2564: =IF(A2564="",0,B2564*(92*IF(OR(C2564=Options!$B$9,C2564=Options!$B$10),75%,100%)-IF(C2564=DATE(2026,11,29),26+IF(Options!$B$8="是",23,0),0)-IF(C2564=DATE(2026,11,30),26,0)-IF(C2564=DATE(2026,12,1),64,0)-IF(C2564=DATE(2026,11,28),38,0)-IF(C2564=DATE(2026,12,2),26,0))) | I2564: =IF(AND(C2564>=DATE(2026,11,29),C2564<=DATE(2026,12,1)),B2564*60,0) | J2564: =IF(A2564="",0,B2564*(IF(C2564=DATE(2026,11,28),38,0)+IF(C2564=DATE(2026,12,1),38,0)+IF(C2564=DATE(2026,12,2),26,0))) | K2564: =IF(C2564=Options!$B$9,B2564*12,0) | L2564: =IF(C2564=Options!$B$9,B2564*Options!$Z$8,0) | M2564: 0 | N2564: =SUM(E2564:M2564)
A2565: =IF(AND(C2565>=Options!$B$9,C2565<=Options!$B$10),"Boston","") | B2565: =IF(A2565="","",24) | C2565: 46301 | D2565: =IF(A2565="","",IF(C2565=DATE(2026,11,29),"培训；注册午餐；早餐参数",IF(C2565=DATE(2026,11,30),"培训；注册午餐",IF(C2565=DATE(2026,12,1),"培训；注册午餐；机构晚餐",IF(C2565=Options!$B$9,"抵达；"&IF(C2565=DATE(2026,11,28),"机构晚餐","无统一供餐"),IF(C2565=Options!$B$10,"返程；"&IF(C2565=DATE(2026,12,2),"机构午餐","无统一供餐"),"差旅状态；无统一日程")))))) | E2565: =IF(C2565=Options!$B$9,Options!$C$21,0) | F2565: =IF(AND(A2565<>"",C2565<Options!$B$10),B2565*Options!$X$8,0) | G2565: =F2565*12% | H2565: =IF(A2565="",0,B2565*(92*IF(OR(C2565=Options!$B$9,C2565=Options!$B$10),75%,100%)-IF(C2565=DATE(2026,11,29),26+IF(Options!$B$8="是",23,0),0)-IF(C2565=DATE(2026,11,30),26,0)-IF(C2565=DATE(2026,12,1),64,0)-IF(C2565=DATE(2026,11,28),38,0)-IF(C2565=DATE(2026,12,2),26,0))) | I2565: =IF(AND(C2565>=DATE(2026,11,29),C2565<=DATE(2026,12,1)),B2565*60,0) | J2565: =IF(A2565="",0,B2565*(IF(C2565=DATE(2026,11,28),38,0)+IF(C2565=DATE(2026,12,1),38,0)+IF(C2565=DATE(2026,12,2),26,0))) | K2565: =IF(C2565=Options!$B$9,B2565*12,0) | L2565: =IF(C2565=Options!$B$9,B2565*Options!$Z$8,0) | M2565: 0 | N2565: =SUM(E2565:M2565)
...

Sheet Sources
A1: 资料依据与预算口径
A4: ID | B4: 主题 | C4: 来源/文件 | D4: 条款/页/条件 | E4: 查询时间 | F4: 金额/口径 | G4: 适用方案 | H4: 状态
A5: FL-ORD | B5: 机票 | C5: https://www.google.com/travel/flights?hl=en&curr=USD | D5: DCA–ORD; 2026-11-28/12-02; 1 adult economy; American 6:00–7:32, nonstop; American 15:00–18:04, nonstop. Google称必需税费已含，行李等可另收。 | E5: 2026-10-23 14:00 UTC | F5: USD 271.00/人往返 | G5: Chicago | H5: 动态估算；未预订
A6: HT-ORD | B6: 住宿 | C6: https://www.google.com/travel/search?hl=en&gl=us&curr=USD | D6: Embassy Suites by Hilton Chicago O'Hare Rosemont; 2026-11-28至12-02；页面默认2旅客/1房（作为每房起价代理，非单人已确认报价）；页面卡片标Free breakfast。税费、房型、单人入住价格、团体房量待酒店书面确认。 | E6: 2026-10-23 14:00 UTC | F6: USD 126.00/房夜起 | G6: Chicago | H6: 动态估算；未预订
A7: FL-DEN | B7: 机票 | C7: https://www.google.com/travel/flights?hl=en&curr=USD | D7: DCA–DEN; 2026-11-28/12-02; 1 adult economy; Frontier 7:00–9:16, nonstop; Frontier 7:30–12:48, nonstop. Google称必需税费已含，行李等可另收。 | E7: 2026-10-23 14:00 UTC | F7: USD 466.00/人往返 | G7: Denver | H7: 动态估算；未预订
A8: HT-DEN | B8: 住宿 | C8: https://www.google.com/travel/search?hl=en&gl=us&curr=USD | D8: Holiday Inn Express Denver Downtown by IHG; 2026-11-28至12-02；页面默认2旅客/1房（作为每房起价代理，非单人已确认报价）；页面卡片标Free breakfast。税费、房型、单人入住价格、团体房量待酒店书面确认。 | E8: 2026-10-23 14:00 UTC | F8: USD 75.00/房夜起 | G8: Denver | H8: 动态估算；未预订
A9: FL-PHX | B9: 机票 | C9: https://www.google.com/travel/flights?hl=en&curr=USD | D9: DCA–PHX; 2026-11-28/12-02; 1 adult economy; American 10:32–13:51, nonstop; American 12:49–19:00, nonstop. Google称必需税费已含，行李等可另收。 | E9: 2026-10-23 14:00 UTC | F9: USD 581.00/人往返 | G9: Phoenix | H9: 动态估算；未预订
A10: HT-PHX | B10: 住宿 | C10: https://www.google.com/travel/search?hl=en&gl=us&curr=USD | D10: SureStay InnSuites Phoenix Hotel & Suites by Best Western; 2026-11-28至12-02；页面默认2旅客/1房（作为每房起价代理，非单人已确认报价）；页面卡片标Free breakfast。税费、房型、单人入住价格、团体房量待酒店书面确认。 | E10: 2026-10-23 14:00 UTC | F10: USD 93.00/房夜起 | G10: Phoenix | H10: 动态估算；未预订
A11: FL-BOS | B11: 机票 | C11: https://www.google.com/travel/flights?hl=en&curr=USD | D11: DCA–BOS; 2026-11-28/12-02; 1 adult economy; Delta 6:00–7:38, nonstop; Delta 16:00–17:59, nonstop. Google称必需税费已含，行李等可另收。 | E11: 2026-10-23 14:00 UTC | F11: USD 330.00/人往返 | G11: Boston | H11: 动态估算；未预订
A12: HT-BOS | B12: 住宿 | C12: https://www.google.com/travel/search?hl=en&gl=us&curr=USD | D12: Hyatt Place Boston / Seaport District; 2026-11-28至12-02；页面默认2旅客/1房（作为每房起价代理，非单人已确认报价）；页面卡片标Free breakfast。税费、房型、单人入住价格、团体房量待酒店书面确认。 | E12: 2026-10-23 14:00 UTC | F12: USD 202.00/房夜起 | G12: Boston | H12: 动态估算；未预订
A13: FL-SEA | B13: 机票 | C13: https://www.google.com/travel/flights?hl=en&curr=USD | D13: DCA–SEA; 2026-11-28/12-02; 1 adult economy; Alaska 8:00–11:06, nonstop; Alaska 14:02–21:59, nonstop. Google称必需税费已含，行李等可另收。 | E13: 2026-10-23 14:00 UTC | F13: USD 977.00/人往返 | G13: Seattle | H13: 动态估算；未预订
A14: HT-SEA | B14: 住宿 | C14: https://www.google.com/travel/search?hl=en&gl=us&curr=USD | D14: Hyatt House Seattle/Downtown; 2026-11-28至12-02；页面默认2旅客/1房（作为每房起价代理，非单人已确认报价）；页面卡片标Free breakfast。税费、房型、单人入住价格、团体房量待酒店书面确认。 | E14: 2026-10-23 14:00 UTC | F14: USD 170.00/房夜起 | G14: Seattle | H14: 动态估算；未预订
A15: GSA27 | B15: 住宿/M&IE | C15: FY2027_PerDiemRates_Validated090126.xlsx | D15: FY2027，生效2026-10-01；按县和季节。Chicago 11/28-30 $232、12/1 $148；Denver $170；Phoenix $165；Boston $213；Seattle $188。M&IE：Phoenix $86，其余$92。 | E15: 附件版本 | F15: 住宿上限/房夜；M&IE/日 | G15: 全部 | H15: 适用
... A27: APP | B27: 审批字段 | C27: Conference-Attendance-fillable-Approval-Template.pdf | D27: 需事件目的、任务关联、人数理由、替代方式、议程、地点成本估算、参会者明细、财务/POC等；模板不替代批准。 | E27: 附件版本 | F27: 无金额 | G27: 全部 | H27: 需补证
