Workbook

Sheet ControlPanel
A1: 命名输入 | B1: 可编辑值 | C1: 说明
A2: WF_BUDGET | B2: 53000 | C2: 批准总额上限（含储备）
A3: WF_AIR_MULTIPLIER | B3: 1 | C3: 题设票价的当前倍率，压力在此基础上再涨20%
A4: WF_RESERVE_RATE | B4: 0.05 | C4: 应急储备率
A5: WF_GOV_BREAKFAST_0929 | B5: 0 | C5: 09-29政府另供早餐：0否/1是；酒店免费早餐不受此开关影响
A6: WF_ARRIVAL | B6: 20250928 | C6: 到达日YYYYMMDD：20250927/28/29；10-02返回及原供餐日历不变

Sheet Dashboard
A1: 命名输出 | B1: 当前结果 | C1: 说明
A2: WF_SELECTED_CITY | B2: =IFERROR(INDEX(Options!$A$2:$A$7,MATCH(1,Options!$T$2:$T$7,0)),"NONE") -> Phoenix | C2: 按人数、费用、城市名优先
A3: WF_SELECTED_N | B3: =IFERROR(INDEX(Options!$B$2:$B$7,MATCH(1,Options!$T$2:$T$7,0)),0) -> 24 | C3: 无可行方案为0
A4: WF_SNAPSHOT_CURRENT | B4: =AND(WF_BUDGET=53000,WF_AIR_MULTIPLIER=1,WF_RESERVE_RATE=0.05,WF_GOV_BREAKFAST_0929=0,WF_ARRIVAL=20250928) -> TRUE | C4: 五项输入均为默认值才与Word/CSV快照一致
A5: 文档版次状态 | B5: =IF(WF_SNAPSHOT_CURRENT,"Word/CSV与默认参数一致","参数已改：Word/CSV是默认快照，需重新导出") -> Word/CSV与默认参数一致 | C5: 未声称静态文档自动更新
A6: 压力下可行城市 | B6: =IFERROR(INDEX(Options!$A$2:$A$7,MATCH(1,Options!$V$2:$V$7,0)),"NONE") -> Phoenix | C6: 当前票价基础上再涨20%，按同一人数/费用目标排序
A7: 压力下可行人数 | B7: =IFERROR(INDEX(Options!$B$2:$B$7,MATCH(1,Options!$V$2:$V$7,0)),0) -> 18 | C7: 0表示需追加资金或另行调整

Sheet Daily
A1: city | B1: date | C1: fiscal_year | D1: source | E1: excel_row | F1: lodging_cap | G1: lodging_quote | H1: paid_lodging | I1: lodging_tax | J1: MIE_full | K1: travel_factor | L1: government_meals | M1: meal_deduction | N1: incidental_floor | O1: MIE_payable | P1: hotel_breakfast_deduction | Q1: refreshment_deduction | R1: lodging_compliant | S1: baseline_meal_deduction | T1: baseline_government_meals | U1: date_code | V1: travel_active
A2: Chicago | B2: 2025-09-28 | C2: 2025 | D2: FY2025_PerDiemMasterRatesFile.xlsx | E2: 258 | F2: 223 | G2: 218 | H2: =IF(AND(V2,U2<20251002),G2,0) -> 218 | I2: =H2*0.12 -> 26.16 | J2: 92 | K2: =IF(V2,IF(OR(U2=WF_ARRIVAL,U2=20251002),0.75,1),0) -> 0.75 | L2: =IF(V2,T2&IF(AND(B2="2025-09-29",WF_GOV_BREAKFAST_0929=1),",breakfast",""),"未旅行") -> dinner | M2: =IF(V2,S2+IF(B2="2025-09-29",WF_GOV_BREAKFAST_0929*VLOOKUP(J2,MealBreakdown!$A$2:$E$6,2,0),0),0) -> 38 | N2: 5 | O2: =IF(V2,MAX(N2,J2*K2-M2),0) -> 31 | P2: 0 | Q2: 0 | R2: =TRUE() -> TRUE | S2: 38 | T2: dinner | U2: 20250928 | V2: =AND(U2>=WF_ARRIVAL,U2<=20251002) -> TRUE
A3: Chicago | B3: 2025-09-29 | C3: 2025 | D3: FY2025_PerDiemMasterRatesFile.xlsx | E3: 258 | F3: 223 | G3: 218 | H3: =IF(AND(V3,U3<20251002),G3,0) -> 218 | I3: =H3*0.12 -> 26.16 | J3: 92 | K3: =IF(V3,IF(OR(U3=WF_ARRIVAL,U3=20251002),0.75,1),0) -> 1 | L3: =IF(V3,T3&IF(AND(B3="2025-09-29",WF_GOV_BREAKFAST_0929=1),",breakfast",""),"未旅行") -> lunch | M3: =IF(V3,S3+IF(B3="2025-09-29",WF_GOV_BREAKFAST_0929*VLOOKUP(J3,MealBreakdown!$A$2:$E$6,2,0),0),0) -> 26 | N3: 5 | O3: =IF(V3,MAX(N3,J3*K3-M3),0) -> 66 | P3: 0 | Q3: 0 | R3: =TRUE() -> TRUE | S3: 26 | T3: lunch | U3: 20250929 | V3: =AND(U3>=WF_ARRIVAL,U3<=20251002) -> TRUE
A4: Chicago | B4: 2025-09-30 | C4: 2025 | D4: FY2025_PerDiemMasterRatesFile.xlsx | E4: 258 | F4: 223 | G4: 218 | H4: =IF(AND(V4,U4<20251002),G4,0) -> 218 | I4: =H4*0.12 -> 26.16 | J4: 92 | K4: =IF(V4,IF(OR(U4=WF_ARRIVAL,U4=20251002),0.75,1),0) -> 1 | L4: =IF(V4,T4&IF(AND(B4="2025-09-29",WF_GOV_BREAKFAST_0929=1),",breakfast",""),"未旅行") -> lunch | M4: =IF(V4,S4+IF(B4="2025-09-29",WF_GOV_BREAKFAST_0929*VLOOKUP(J4,MealBreakdown!$A$2:$E$6,2,0),0),0) -> 26 | N4: 5 | O4: =IF(V4,MAX(N4,J4*K4-M4),0) -> 66 | P4: 0 | Q4: 0 | R4: =TRUE() -> TRUE | S4: 26 | T4: lunch | U4: 20250930 | V4: =AND(U4>=WF_ARRIVAL,U4<=20251002) -> TRUE
A5: Chicago | B5: 2025-10-01 | C5: 2026 | D5: FY2026_PerDiemMasterRatesFile.xlsx | E5: 254 | F5: 223 | G5: 218 | H5: =IF(AND(V5,U5<20251002),G5,0) -> 218 | I5: =H5*0.12 -> 26.16 | J5: 92 | K5: =IF(V5,IF(OR(U5=WF_ARRIVAL,U5=20251002),0.75,1),0) -> 1 | L5: =IF(V5,T5&IF(AND(B5="2025-09-29",WF_GOV_BREAKFAST_0929=1),",breakfast",""),"未旅行") -> lunch,dinner | M5: =IF(V5,S5+IF(B5="2025-09-29",WF_GOV_BREAKFAST_0929*VLOOKUP(J5,MealBreakdown!$A$2:$E$6,2,0),0),0) -> 64 | N5: 5 | O5: =IF(V5,MAX(N5,J5*K5-M5),0) -> 28 | P5: 0 | Q5: 0 | R5: =TRUE() -> TRUE | S5: 64 | T5: lunch,dinner | U5: 20251001 | V5: =AND(U5>=WF_ARRIVAL,U5<=20251002) -> TRUE
A6: Chicago | B6: 2025-10-02 | C6: 2026 | D6: FY2026_PerDiemMasterRatesFile.xlsx | E6: 254 | F6: 223 | G6: 218 | H6: =IF(AND(V6,U6<20251002),G6,0) -> 0 | I6: =H6*0.12 -> 0 | J6: 92 | K6: =IF(V6,IF(OR(U6=WF_ARRIVAL,U6=20251002),0.75,1),0) -> 0.75 | L6: =IF(V6,T6&IF(AND(B6="2025-09-29",WF_GOV_BREAKFAST_0929=1),",breakfast",""),"未旅行") -> lunch | M6: =IF(V6,S6+IF(B6="2025-09-29",WF_GOV_BREAKFAST_0929*VLOOKUP(J6,MealBreakdown!$A$2:$E$6,2,0),0),0) -> 26 | N6: 5 | O6: =IF(V6,MAX(N6,J6*K6-M6),0) -> 43 | P6: 0 | Q6: 0 | R6: =TRUE() -> TRUE | S6: 26 | T6: lunch | U6: 20251002 | V6: =AND(U6>=WF_ARRIVAL,U6<=20251002) -> TRUE
A7: Denver | B7: 2025-09-28 | C7: 2025 | D7: FY2025_PerDiemMasterRatesFile.xlsx | E7: 109 | F7: 215 | G7: 209 | H7: =IF(AND(V7,U7<20251002),G7,0) -> 209 | I7: =H7*0.12 -> 25.08 | J7: 92 | K7: =IF(V7,IF(OR(U7=WF_ARRIVAL,U7=20251002),0.75,1),0) -> 0.75 | L7: =IF(V7,T7&IF(AND(B7="2025-09-29",WF_GOV_BREAKFAST_0929=1),",breakfast",""),"未旅行") -> dinner | M7: =IF(V7,S7+IF(B7="2025-09-29",WF_GOV_BREAKFAST_0929*VLOOKUP(J7,MealBreakdown!$A$2:$E$6,2,0),0),0) -> 38 | N7: 5 | O7: =IF(V7,MAX(N7,J7*K7-M7),0) -> 31 | P7: 0 | Q7: 0 | R7: =TRUE() -> TRUE | S7: 38 | T7: dinner | U7: 20250928 | V7: =AND(U7>=WF_ARRIVAL,U7<=20251002) -> TRUE
A8: Denver | B8: 2025-09-29 | C8: 2025 | D8: FY2025_PerDiemMasterRatesFile.xlsx | E8: 109 | F8: 215 | G8: 209 | H8: =IF(AND(V8,U8<20251002),G8,0) -> 209 | I8: =H8*0.12 -> 25.08 | J8: 92 | K8: =IF(V8,IF(OR(U8=WF_ARRIVAL,U8=20251002),0.75,1),0) -> 1 | L8: =IF(V8,T8&IF(AND(B8="2025-09-29",WF_GOV_BREAKFAST_0929=1),",breakfast",""),"未旅行") -> lunch | M8: =IF(V8,S8+IF(B8="2025-09-29",WF_GOV_BREAKFAST_0929*VLOOKUP(J8,MealBreakdown!$A$2:$E$6,2,0),0),0) -> 26 | N8: 5 | O8: =IF(V8,MAX(N8,J8*K8-M8),0) -> 66 | P8: 0 | Q8: 0 | R8: =TRUE() -> TRUE | S8: 26 | T8: lunch | U8: 20250929 | V8: =AND(U8>=WF_ARRIVAL,U8<=20251002) -> TRUE
A9: Denver | B9: 2025-09-30 | C9: 2025 | D9: FY2025_PerDiemMasterRatesFile.xlsx | E9: 109 | F9: 215 | G9: 209 | H9: =IF(AND(V9,U9<20251002),G9,0) -> 209 | I9: =H9*0.12 -> 25.08 | J9: 92 | K9: =IF(V9,IF(OR(U9=WF_ARRIVAL,U9=20251002),0.75,1),0) -> 1 | L9: =IF(V9,T9&IF(AND(B9="2025-09-29",WF_GOV_BREAKFAST_0929=1),",breakfast",""),"未旅行") -> lunch | M9: =IF(V9,S9+IF(B9="2025-09-29",WF_GOV_BREAKFAST_0929*VLOOKUP(J9,MealBreakdown!$A$2:$E$6,2,0),0),0) -> 26 | N9: 5 | O9: =IF(V9,MAX(N9,J9*K9-M9),0) -> 66 | P9: 0 | Q9: 0 | R9: =TRUE() -> TRUE | S9: 26 | T9: lunch | U9: 20250930 | V9: =AND(U9>=WF_ARRIVAL,U9<=20251002) -> TRUE
A10: Denver | B10: 2025-10-01 | C10: 2026 | D10: FY2026_PerDiemMasterRatesFile.xlsx | E10: 107 | F10: 215 | G10: 209 | H10: =IF(AND(V10,U10<20251002),G10,0) -> 209 | I10: =H10*0.12 -> 25.08 | J10: 92 | K10: =IF(V10,IF(OR(U10=WF_ARRIVAL,U10=20251002),0.75,1),0) -> 1 | L10: =IF(V10,T10&IF(AND(B10="2025-09-29",WF_GOV_BREAKFAST_0929=1),",breakfast",""),"未旅行") -> lunch,dinner | M10: =IF(V10,S10+IF(B10="2025-09-29",WF_GOV_BREAKFAST_0929*VLOOKUP(J10,MealBreakdown!$A$2:$E$6,2,0),0),0) -> 64 | N10: 5 | O10: =IF(V10,MAX(N10,J10*K10-M10),0) -> 28 | P10: 0 | Q10: 0 | R10: =TRUE() -> TRUE | S10: 64 | T10: lunch,dinner | U10: 20251001 | V10: =AND(U10>=WF_ARRIVAL,U10<=20251002) -> TRUE
A11: Denver | B11: 2025-10-02 | C11: 2026 | D11: FY2026_PerDiemMasterRatesFile.xlsx | E11: 107 | F11: 215 | G11: 209 | H11: =IF(AND(V11,U11<20251002),G11,0) -> 0 | I11: =H11*0.12 -> 0 | J11: 92 | K11: =IF(V11,IF(OR(U11=WF_ARRIVAL,U11=20251002),0.75,1),0) -> 0.75 | L11: =IF(V11,T11&IF(AND(B11="2025-09-29",WF_GOV_BREAKFAST_0929=1),",breakfast",""),"未旅行") -> lunch | M11: =IF(V11,S11+IF(B11="2025-09-29",WF_GOV_BREAKFAST_0929*VLOOKUP(J11,MealBreakdown!$A$2:$E$6,2,0),0),0) -> 26 | N11: 5 | O11: =IF(V11,MAX(N11,J11*K11-M11),0) -> 43 | P11: 0 | Q11: 0 | R11: =TRUE() -> TRUE | S11: 26 | T11: lunch | U11: 20251002 | V11: =AND(U11>=WF_ARRIVAL,U11<=20251002) -> TRUE
A12: Phoenix | B12: 2025-09-28 | C12: 2025 | D12: FY2025_PerDiemMasterRatesFile.xlsx | E12: 22 | F12: 160 | G12: 155 | H12: =IF(AND(V12,U12<20251002),G12,0) -> 155 | I12: =H12*0.12 -> 18.6 | J12: 86 | K12: =IF(V12,IF(OR(U12=WF_ARRIVAL,U12=20251002),0.75,1),0) -> 0.75 | L12: =IF(V12,T12&IF(AND(B12="2025-09-29",WF_GOV_BREAKFAST_0929=1),",breakfast",""),"未旅行") -> dinner | M12: =IF(V12,S12+IF(B12="2025-09-29",WF_GOV_BREAKFAST_0929*VLOOKUP(J12,MealBreakdown!$A$2:$E$6,2,0),0),0) -> 36 | N12: 5 | O12: =IF(V12,MAX(N12,J12*K12-M12),0) -> 28.5 | P12: 0 | Q12: 0 | R12: =TRUE() -> TRUE | S12: 36 | T12: dinner | U12: 20250928 | V12: =AND(U12>=WF_ARRIVAL,U12<=20251002) -> TRUE
A13: Phoenix | B13: 2025-09-29 | C13: 2025 | D13: FY2025_PerDiemMasterRatesFile.xlsx | E13: 22 | F13: 160 | G13: 155 | H13: =IF(AND(V13,U13<20251002),G13,0) -> 155 | I13: =H13*0.12 -> 18.6 | J13: 86 | K13: =IF(V13,IF(OR(U13=WF_ARRIVAL,U13=20251002),0.75,1),0) -> 1 | L13: =IF(V13,T13&IF(AND(B13="2025-09-29",WF_GOV_BREAKFAST_0929=1),",breakfast",""),"未旅行") -> lunch | M13: =IF(V13,S13+IF(B13="2025-09-29",WF_GOV_BREAKFAST_0929*VLOOKUP(J13,MealBreakdown!$A$2:$E$6,2,0),0),0) -> 23 | N13: 5 | O13: =IF(V13,MAX(N13,J13*K13-M13),0) -> 63 | P13: 0 | Q13: 0 | R13: =TRUE() -> TRUE | S13: 23 | T13: lunch | U13: 20250929 | V13: =AND(U13>=WF_ARRIVAL,U13<=20251002) -> TRUE
... A16: Phoenix | B16: 2025-10-02 | C16: 2026 | D16: FY2026_PerDiemMasterRatesFile.xlsx | E16: 18 | F16: 160 | G16: 155 | H16: =IF(AND(V16,U16<20251002),G16,0) -> 0 | I16: =H16*0.12 -> 0 | J16: 86 | K16: =IF(V16,IF(OR(U16=WF_ARRIVAL,U16=20251002),0.75,1),0) -> 0.75 | L16: =IF(V16,T16&IF(AND(B16="2025-09-29",WF_GOV_BREAKFAST_0929=1),",breakfast",""),"未旅行") -> lunch | M16: =IF(V16,S16+IF(B16="2025-09-29",WF_GOV_BREAKFAST_0929*VLOOKUP(J16,MealBreakdown!$A$2:$E$6,2,0),0),0) -> 23 | N16: 5 | O16: =IF(V16,MAX(N16,J16*K16-M16),0) -> 41.5 | P16: 0 | Q16: 0 | R16: =TRUE() -> TRUE | S16: 23 | T16: lunch | U16: 20251002 | V16: =AND(U16>=WF_ARRIVAL,U16<=20251002) -> TRUE
A17: Chicago | B17: 2025-09-27 | C17: 2025 | D17: FY2025_PerDiemMasterRatesFile.xlsx | E17: 258 | F17: 223 | G17: 218 | H17: =IF(AND(V17,U17<20251002),G17,0) -> 0 | I17: =H17*0.12 -> 0 | J17: 92 | K17: =IF(V17,IF(OR(U17=WF_ARRIVAL,U17=20251002),0.75,1),0) -> 0 | L17: =IF(V17,T17&IF(AND(B17="2025-09-29",WF_GOV_BREAKFAST_0929=1),",breakfast",""),"未旅行") -> 未旅行 | M17: =IF(V17,S17+IF(B17="2025-09-29",WF_GOV_BREAKFAST_0929*VLOOKUP(J17,MealBreakdown!$A$2:$E$6,2,0),0),0) -> 0 | N17: 5 | O17: =IF(V17,MAX(N17,J17*K17-M17),0) -> 0 | P17: 0 | Q17: 0 | R17: =TRUE() -> TRUE | S17: 0 | U17: 20250927 | V17: =AND(U17>=WF_ARRIVAL,U17<=20251002) -> FALSE
A18: Denver | B18: 2025-09-27 | C18: 2025 | D18: FY2025_PerDiemMasterRatesFile.xlsx | E18: 109 | F18: 215 | G18: 209 | H18: =IF(AND(V18,U18<20251002),G18,0) -> 0 | I18: =H18*0.12 -> 0 | J18: 92 | K18: =IF(V18,IF(OR(U18=WF_ARRIVAL,U18=20251002),0.75,1),0) -> 0 | L18: =IF(V18,T18&IF(AND(B18="2025-09-29",WF_GOV_BREAKFAST_0929=1),",breakfast",""),"未旅行") -> 未旅行 | M18: =IF(V18,S18+IF(B18="2025-09-29",WF_GOV_BREAKFAST_0929*VLOOKUP(J18,MealBreakdown!$A$2:$E$6,2,0),0),0) -> 0 | N18: 5 | O18: =IF(V18,MAX(N18,J18*K18-M18),0) -> 0 | P18: 0 | Q18: 0 | R18: =TRUE() -> TRUE | S18: 0 | U18: 20250927 | V18: =AND(U18>=WF_ARRIVAL,U18<=20251002) -> FALSE
A19: Phoenix | B19: 2025-09-27 | C19: 2025 | D19: FY2025_PerDiemMasterRatesFile.xlsx | E19: 22 | F19: 160 | G19: 155 | H19: =IF(AND(V19,U19<20251002),G19,0) -> 0 | I19: =H19*0.12 -> 0 | J19: 86 | K19: =IF(V19,IF(OR(U19=WF_ARRIVAL,U19=20251002),0.75,1),0) -> 0 | L19: =IF(V19,T19&IF(AND(B19="2025-09-29",WF_GOV_BREAKFAST_0929=1),",breakfast",""),"未旅行") -> 未旅行 | M19: =IF(V19,S19+IF(B19="2025-09-29",WF_GOV_BREAKFAST_0929*VLOOKUP(J19,MealBreakdown!$A$2:$E$6,2,0),0),0) -> 0 | N19: 5 | O19: =IF(V19,MAX(N19,J19*K19-M19),0) -> 0 | P19: 0 | Q19: 0 | R19: =TRUE() -> TRUE | S19: 0 | U19: 20250927 | V19: =AND(U19>=WF_ARRIVAL,U19<=20251002) -> FALSE

Sheet Options
A1: city | B1: attendees | C1: paid_lodging | D1: lodging_tax | E1: MIE_payable | F1: air_per_person | G1: local_per_person | H1: registration_per_person | I1: per_person | J1: venue | K1: base | L1: reserve | M1: total | N1: headroom | O1: compliant | P1: eligible | Q1: stress_base | R1: stress_total | S1: stress_headroom | T1: selection_rank | U1: stress_eligible | V1: stress_selection_rank
A2: Chicago | B2: 18 | C2: =SUMIF(Daily!$A$2:$A$19,A2,Daily!$H$2:$H$19) -> 872 | D2: =SUMIF(Daily!$A$2:$A$19,A2,Daily!$I$2:$I$19) -> 104.64 | E2: =SUMIF(Daily!$A$2:$A$19,A2,Daily!$O$2:$O$19) -> 234 | F2: 410 | G2: 80 | H2: 180 | I2: =C2+D2+E2+F2*WF_AIR_MULTIPLIER+G2+H2 -> 1880.64 | J2: 9500 | K2: =I2*B2+J2 -> 43351.52 | L2: =K2*WF_RESERVE_RATE -> 2167.576 | M2: =K2+L2 -> 45519.096 | N2: =WF_BUDGET-M2 -> 7480.904 | O2: =TRUE() -> TRUE | P2: =AND(O2,M2<=WF_BUDGET) -> TRUE | Q2: =K2+0.2*F2*WF_AIR_MULTIPLIER*B2 -> 44827.52 | R2: =Q2*(1+WF_RESERVE_RATE) -> 47068.896 | S2: =WF_BUDGET-R2 -> 5931.104 | T2: =IF(P2,COUNTIFS($P$2:$P$7,TRUE(),$B$2:$B$7,">"&B2)+COUNTIFS($P$2:$P$7,TRUE(),$B$2:$B$7,B2,$M$2:$M$7,"<"&M2)+COUNTIFS($P$2:$P$7,TRUE(),$B$2:$B$7,B2,$M$2:$M$7,M2,$A$2:$A$7,"<"&A2)+1,999) -> 4 | U2: =AND(O2,R2<=WF_BUDGET) -> TRUE | V2: =IF(U2,COUNTIFS($U$2:$U$7,TRUE(),$B$2:$B$7,">"&B2)+COUNTIFS($U$2:$U$7,TRUE(),$B$2:$B$7,B2,$R$2:$R$7,"<"&R2)+COUNTIFS($U$2:$U$7,TRUE(),$B$2:$B$7,B2,$R$2:$R$7,R2,$A$2:$A$7,"<"&A2)+1,999) -> 3
A3: Chicago | B3: 24 | C3: =SUMIF(Daily!$A$2:$A$19,A3,Daily!$H$2:$H$19) -> 872 | D3: =SUMIF(Daily!$A$2:$A$19,A3,Daily!$I$2:$I$19) -> 104.64 | E3: =SUMIF(Daily!$A$2:$A$19,A3,Daily!$O$2:$O$19) -> 234 | F3: 410 | G3: 80 | H3: 180 | I3: =C3+D3+E3+F3*WF_AIR_MULTIPLIER+G3+H3 -> 1880.64 | J3: 9500 | K3: =I3*B3+J3 -> 54635.36 | L3: =K3*WF_RESERVE_RATE -> 2731.768 | M3: =K3+L3 -> 57367.128 | N3: =WF_BUDGET-M3 -> -4367.128 | O3: =TRUE() -> TRUE | P3: =AND(O3,M3<=WF_BUDGET) -> FALSE | Q3: =K3+0.2*F3*WF_AIR_MULTIPLIER*B3 -> 56603.36 | R3: =Q3*(1+WF_RESERVE_RATE) -> 59433.528 | S3: =WF_BUDGET-R3 -> -6433.528 | T3: =IF(P3,COUNTIFS($P$2:$P$7,TRUE(),$B$2:$B$7,">"&B3)+COUNTIFS($P$2:$P$7,TRUE(),$B$2:$B$7,B3,$M$2:$M$7,"<"&M3)+COUNTIFS($P$2:$P$7,TRUE(),$B$2:$B$7,B3,$M$2:$M$7,M3,$A$2:$A$7,"<"&A3)+1,999) -> 999 | U3: =AND(O3,R3<=WF_BUDGET) -> FALSE | V3: =IF(U3,COUNTIFS($U$2:$U$7,TRUE(),$B$2:$B$7,">"&B3)+COUNTIFS($U$2:$U$7,TRUE(),$B$2:$B$7,B3,$R$2:$R$7,"<"&R3)+COUNTIFS($U$2:$U$7,TRUE(),$B$2:$B$7,B3,$R$2:$R$7,R3,$A$2:$A$7,"<"&A3)+1,999) -> 999
A4: Denver | B4: 18 | C4: =SUMIF(Daily!$A$2:$A$19,A4,Daily!$H$2:$H$19) -> 836 | D4: =SUMIF(Daily!$A$2:$A$19,A4,Daily!$I$2:$I$19) -> 100.32 | E4: =SUMIF(Daily!$A$2:$A$19,A4,Daily!$O$2:$O$19) -> 234 | F4: 340 | G4: 70 | H4: 180 | I4: =C4+D4+E4+F4*WF_AIR_MULTIPLIER+G4+H4 -> 1760.32 | J4: 10500 | K4: =I4*B4+J4 -> 42185.76 | L4: =K4*WF_RESERVE_RATE -> 2109.288 | M4: =K4+L4 -> 44295.048 | N4: =WF_BUDGET-M4 -> 8704.952 | O4: =TRUE() -> TRUE | P4: =AND(O4,M4<=WF_BUDGET) -> TRUE | Q4: =K4+0.2*F4*WF_AIR_MULTIPLIER*B4 -> 43409.76 | R4: =Q4*(1+WF_RESERVE_RATE) -> 45580.248 | S4: =WF_BUDGET-R4 -> 7419.752 | T4: =IF(P4,COUNTIFS($P$2:$P$7,TRUE(),$B$2:$B$7,">"&B4)+COUNTIFS($P$2:$P$7,TRUE(),$B$2:$B$7,B4,$M$2:$M$7,"<"&M4)+COUNTIFS($P$2:$P$7,TRUE(),$B$2:$B$7,B4,$M$2:$M$7,M4,$A$2:$A$7,"<"&A4)+1,999) -> 3 | U4: =AND(O4,R4<=WF_BUDGET) -> TRUE | V4: =IF(U4,COUNTIFS($U$2:$U$7,TRUE(),$B$2:$B$7,">"&B4)+COUNTIFS($U$2:$U$7,TRUE(),$B$2:$B$7,B4,$R$2:$R$7,"<"&R4)+COUNTIFS($U$2:$U$7,TRUE(),$B$2:$B$7,B4,$R$2:$R$7,R4,$A$2:$A$7,"<"&A4)+1,999) -> 2
A5: Denver | B5: 24 | C5: =SUMIF(Daily!$A$2:$A$19,A5,Daily!$H$2:$H$19) -> 836 | D5: =SUMIF(Daily!$A$2:$A$19,A5,Daily!$I$2:$I$19) -> 100.32 | E5: =SUMIF(Daily!$A$2:$A$19,A5,Daily!$O$2:$O$19) -> 234 | F5: 340 | G5: 70 | H5: 180 | I5: =C5+D5+E5+F5*WF_AIR_MULTIPLIER+G5+H5 -> 1760.32 | J5: 10500 | K5: =I5*B5+J5 -> 52747.68 | L5: =K5*WF_RESERVE_RATE -> 2637.384 | M5: =K5+L5 -> 55385.064 | N5: =WF_BUDGET-M5 -> -2385.064 | O5: =TRUE() -> TRUE | P5: =AND(O5,M5<=WF_BUDGET) -> FALSE | Q5: =K5+0.2*F5*WF_AIR_MULTIPLIER*B5 -> 54379.68 | R5: =Q5*(1+WF_RESERVE_RATE) -> 57098.664 | S5: =WF_BUDGET-R5 -> -4098.664 | T5: =IF(P5,COUNTIFS($P$2:$P$7,TRUE(),$B$2:$B$7,">"&B5)+COUNTIFS($P$2:$P$7,TRUE(),$B$2:$B$7,B5,$M$2:$M$7,"<"&M5)+COUNTIFS($P$2:$P$7,TRUE(),$B$2:$B$7,B5,$M$2:$M$7,M5,$A$2:$A$7,"<"&A5)+1,999) -> 999 | U5: =AND(O5,R5<=WF_BUDGET) -> FALSE | V5: =IF(U5,COUNTIFS($U$2:$U$7,TRUE(),$B$2:$B$7,">"&B5)+COUNTIFS($U$2:$U$7,TRUE(),$B$2:$B$7,B5,$R$2:$R$7,"<"&R5)+COUNTIFS($U$2:$U$7,TRUE(),$B$2:$B$7,B5,$R$2:$R$7,R5,$A$2:$A$7,"<"&A5)+1,999) -> 999
A6: Phoenix | B6: 18 | C6: =SUMIF(Daily!$A$2:$A$19,A6,Daily!$H$2:$H$19) -> 620 | D6: =SUMIF(Daily!$A$2:$A$19,A6,Daily!$I$2:$I$19) -> 74.4 | E6: =SUMIF(Daily!$A$2:$A$19,A6,Daily!$O$2:$O$19) -> 223 | F6: 510 | G6: 90 | H6: 180 | I6: =C6+D6+E6+F6*WF_AIR_MULTIPLIER+G6+H6 -> 1697.4 | J6: 8000 | K6: =I6*B6+J6 -> 38553.2 | L6: =K6*WF_RESERVE_RATE -> 1927.66 | M6: =K6+L6 -> 40480.86 | N6: =WF_BUDGET-M6 -> 12519.14 | O6: =TRUE() -> TRUE | P6: =AND(O6,M6<=WF_BUDGET) -> TRUE | Q6: =K6+0.2*F6*WF_AIR_MULTIPLIER*B6 -> 40389.2 | R6: =Q6*(1+WF_RESERVE_RATE) -> 42408.66 | S6: =WF_BUDGET-R6 -> 10591.34 | T6: =IF(P6,COUNTIFS($P$2:$P$7,TRUE(),$B$2:$B$7,">"&B6)+COUNTIFS($P$2:$P$7,TRUE(),$B$2:$B$7,B6,$M$2:$M$7,"<"&M6)+COUNTIFS($P$2:$P$7,TRUE(),$B$2:$B$7,B6,$M$2:$M$7,M6,$A$2:$A$7,"<"&A6)+1,999) -> 2 | U6: =AND(O6,R6<=WF_BUDGET) -> TRUE | V6: =IF(U6,COUNTIFS($U$2:$U$7,TRUE(),$B$2:$B$7,">"&B6)+COUNTIFS($U$2:$U$7,TRUE(),$B$2:$B$7,B6,$R$2:$R$7,"<"&R6)+COUNTIFS($U$2:$U$7,TRUE(),$B$2:$B$7,B6,$R$2:$R$7,R6,$A$2:$A$7,"<"&A6)+1,999) -> 1
A7: Phoenix | B7: 24 | C7: =SUMIF(Daily!$A$2:$A$19,A7,Daily!$H$2:$H$19) -> 620 | D7: =SUMIF(Daily!$A$2:$A$19,A7,Daily!$I$2:$I$19) -> 74.4 | E7: =SUMIF(Daily!$A$2:$A$19,A7,Daily!$O$2:$O$19) -> 223 | F7: 510 | G7: 90 | H7: 180 | I7: =C7+D7+E7+F7*WF_AIR_MULTIPLIER+G7+H7 -> 1697.4 | J7: 8000 | K7: =I7*B7+J7 -> 48737.6 | L7: =K7*WF_RESERVE_RATE -> 2436.88 | M7: =K7+L7 -> 51174.48 | N7: =WF_BUDGET-M7 -> 1825.52 | O7: =TRUE() -> TRUE | P7: =AND(O7,M7<=WF_BUDGET) -> TRUE | Q7: =K7+0.2*F7*WF_AIR_MULTIPLIER*B7 -> 51185.6 | R7: =Q7*(1+WF_RESERVE_RATE) -> 53744.88 | S7: =WF_BUDGET-R7 -> -744.88 | T7: =IF(P7,COUNTIFS($P$2:$P$7,TRUE(),$B$2:$B$7,">"&B7)+COUNTIFS($P$2:$P$7,TRUE(),$B$2:$B$7,B7,$M$2:$M$7,"<"&M7)+COUNTIFS($P$2:$P$7,TRUE(),$B$2:$B$7,B7,$M$2:$M$7,M7,$A$2:$A$7,"<"&A7)+1,999) -> 1 | U7: =AND(O7,R7<=WF_BUDGET) -> FALSE | V7: =IF(U7,COUNTIFS($U$2:$U$7,TRUE(),$B$2:$B$7,">"&B7)+COUNTIFS($U$2:$U$7,TRUE(),$B$2:$B$7,B7,$R$2:$R$7,"<"&R7)+COUNTIFS($U$2:$U$7,TRUE(),$B$2:$B$7,B7,$R$2:$R$7,R7,$A$2:$A$7,"<"&A7)+1,999) -> 999

Sheet Sources
A1: source | B1: locator | C1: reference | D1: use
A2: gsa_per_diem_files.html | B2: FY 26 Per Diem Rates [XLSX - 41 KB] | C2: https://www.gsa.gov/system/files/FY2026_PerDiemMasterRatesFile.xlsx | D2: 网页实际引用；下游材料用于本题同一业务决定。
A3: FY2025_PerDiemMasterRatesFile.xlsx | B3: 258,258,258 | C3: Chicago | D3: 按旅行日财政年度和季节匹配；报价计费，上限仅用于合规比较。
A4: FY2026_PerDiemMasterRatesFile.xlsx | B4: 254,254 | C4: Chicago | D4: 按旅行日财政年度和季节匹配；报价计费，上限仅用于合规比较。
A5: FY2025_PerDiemMasterRatesFile.xlsx | B5: 109,109,109 | C5: Denver | D5: 按旅行日财政年度和季节匹配；报价计费，上限仅用于合规比较。
A6: FY2026_PerDiemMasterRatesFile.xlsx | B6: 107,107 | C6: Denver | D6: 按旅行日财政年度和季节匹配；报价计费，上限仅用于合规比较。
A7: FY2025_PerDiemMasterRatesFile.xlsx | B7: 22,22,22 | C7: Phoenix | D7: 按旅行日财政年度和季节匹配；报价计费，上限仅用于合规比较。
A8: FY2026_PerDiemMasterRatesFile.xlsx | B8: 18,18 | C8: Phoenix | D8: 按旅行日财政年度和季节匹配；报价计费，上限仅用于合规比较。
A9: eCFR_41_CFR_301-11.xml | B9: 301-11.17/.18/.27/.101 | C9: 2025-01-01冻结版 | D9: 免费早餐不扣；政府供餐从首末日75%额扣整餐；最低杂费保护；税另计。
A10: eCFR_41_CFR_301-74.xml | B10: 301-74.7/.9/.21 | C10: 2025-01-01冻结版 | D10: 茶歇与住宿安全/会议审批边界。
A11: instruction.md | B11: 场景假设表及预算条件 | C11: 非真实报价、税率或已审批采购 | D11: 12%税、5%储备、53000上限、人数与机票等。

Sheet MealBreakdown
A1: MIE | B1: Breakfast | C1: Lunch | D1: Dinner | E1: Incidentals
A2: 68 | B2: 16 | C2: 19 | D2: 28 | E2: 5
A3: 74 | B3: 18 | C3: 20 | D3: 31 | E3: 5
A4: 80 | B4: 20 | C4: 22 | D4: 33 | E4: 5
A5: 86 | B5: 22 | C5: 23 | D5: 36 | E5: 5
A6: 92 | B6: 23 | C6: 26 | D6: 38 | E6: 5
