Workbook

Sheet Parameters
A1: CONTROL PANEL | B1: Value | C1: Allowed / effect
A2: Budget cap | B2: 53000 | C2: $0–$100,000; includes reserve
A3: Airfare factor | B3: 1 | C3: 0.5–2.0; stress adds 20% to adjusted fare
A4: Reserve rate | B4: 0.05 | C4: 0%–20% of base subtotal
A5: Gov breakfast 11/29 | B5: No | C5: Yes/No; Yes does not add procurement cost
A6: Arrival date | B6: 46354 | C6: Must be 2026-11-28 for quoted snapshots
A7: Return date | B7: 46358 | C7: Must be 2026-12-02 for quoted snapshots
A8: Selected city | B8: Chicago | C8: Decision output; options calculate independently
A9: Selected attendance | B9: 24 | C9: 18 or 24
A10: NOTICE | B10: Changing dates invalidates market quotes and requires new DOCX/PPT/PDF/CSV exports. | C10: Snapshot files do not auto-refresh.

Sheet Options
A1: City | B1: People | C1: Air/pp raw | D1: Air adj/pp | E1: Hotel | F1: Room/night | G1: Nights | H1: Lodging tax | I1: M&IE/pp | J1: Registration/pp | K1: HQ↔DCA/pp est. | L1: Airport↔hotel/pp est. | M1: Quoted/estimated base | N1: Venue TBD | O1: Meals TBD | P1: Breaks TBD | Q1: Other TBD | R1: Base subtotal | S1: Reserve | T1: Total incl reserve | U1: 20% air stress total | V1: Cap status | W1: Quote validity | X1: Decision status | Y1: Unquoted max @base | Z1: Unquoted max @+20%
A2: Chicago | B2: 18 | C2: 270 | D2: =C2*Parameters!$B$3 -> 270 | E2: Staybridge Suites Chicago—Glenview by IHG | F2: 134 | G2: 4 | H2: =F2*G2*12% -> 64.32 | I2: =234-IF(Parameters!$B$5="Yes",23,0) -> 234 | J2: 180 | K2: 12 | L2: 12 | M2: =B2*(D2+F2*G2+H2+I2+J2+K2+L2) -> 23549.76 | N2: 0 | O2: 0 | P2: 0 | Q2: 0 | R2: =M2+SUM(N2:Q2) -> 23549.76 | S2: =R2*Parameters!$B$4 -> 1177.488 | T2: =R2+S2 -> 24727.248 | U2: =(M2+B2*D2*20%+SUM(N2:Q2))*(1+Parameters!$B$4) -> 25747.848 | V2: =IF(OR(C2=0,F2=0),"NO QUOTE",IF(T2<=Parameters!$B$2,"WITHIN CAP","OVER CAP")) -> WITHIN CAP | W2: =IF(AND(Parameters!$B$6=DATE(2026,11,28),Parameters!$B$7=DATE(2026,12,2)),"Date match","RE-QUOTE") -> Date match | X2: CONDITIONAL: review count/recent issue scan, breakfast, inventory, venue/RFP pending | Y2: =MAX(0,Parameters!$B$2/(1+Parameters!$B$4)-M2) -> 26926.43 | Z2: =MAX(0,Parameters!$B$2/(1+Parameters!$B$4)-M2-B2*D2*20%) -> 25954.43
A3: Chicago | B3: 24 | C3: 270 | D3: =C3*Parameters!$B$3 -> 270 | E3: Staybridge Suites Chicago—Glenview by IHG | F3: 134 | G3: 4 | H3: =F3*G3*12% -> 64.32 | I3: =234-IF(Parameters!$B$5="Yes",23,0) -> 234 | J3: 180 | K3: 12 | L3: 12 | M3: =B3*(D3+F3*G3+H3+I3+J3+K3+L3) -> 31399.68 | N3: 0 | O3: 0 | P3: 0 | Q3: 0 | R3: =M3+SUM(N3:Q3) -> 31399.68 | S3: =R3*Parameters!$B$4 -> 1569.984 | T3: =R3+S3 -> 32969.664 | U3: =(M3+B3*D3*20%+SUM(N3:Q3))*(1+Parameters!$B$4) -> 34330.464 | V3: =IF(OR(C3=0,F3=0),"NO QUOTE",IF(T3<=Parameters!$B$2,"WITHIN CAP","OVER CAP")) -> WITHIN CAP | W3: =IF(AND(Parameters!$B$6=DATE(2026,11,28),Parameters!$B$7=DATE(2026,12,2)),"Date match","RE-QUOTE") -> Date match | X3: CONDITIONAL: review count/recent issue scan, breakfast, inventory, venue/RFP pending | Y3: =MAX(0,Parameters!$B$2/(1+Parameters!$B$4)-M3) -> 19076.51 | Z3: =MAX(0,Parameters!$B$2/(1+Parameters!$B$4)-M3-B3*D3*20%) -> 17780.51
A4: Denver | B4: 18 | C4: 574 | D4: =C4*Parameters!$B$3 -> 574 | E4: Staybridge Suites Denver Downtown by IHG | F4: 103 | G4: 4 | H4: =F4*G4*12% -> 49.44 | I4: =234-IF(Parameters!$B$5="Yes",23,0) -> 234 | J4: 180 | K4: 12 | L4: 20.5 | M4: =B4*(D4+F4*G4+H4+I4+J4+K4+L4) -> 26674.92 | N4: 0 | O4: 0 | P4: 0 | Q4: 0 | R4: =M4+SUM(N4:Q4) -> 26674.92 | S4: =R4*Parameters!$B$4 -> 1333.746 | T4: =R4+S4 -> 28008.666 | U4: =(M4+B4*D4*20%+SUM(N4:Q4))*(1+Parameters!$B$4) -> 30178.386 | V4: =IF(OR(C4=0,F4=0),"NO QUOTE",IF(T4<=Parameters!$B$2,"WITHIN CAP","OVER CAP")) -> WITHIN CAP | W4: =IF(AND(Parameters!$B$6=DATE(2026,11,28),Parameters!$B$7=DATE(2026,12,2)),"Date match","RE-QUOTE") -> Date match | X4: CONDITIONAL: quality detail, breakfast, inventory, venue/RFP pending | Y4: =MAX(0,Parameters!$B$2/(1+Parameters!$B$4)-M4) -> 23801.27 | Z4: =MAX(0,Parameters!$B$2/(1+Parameters!$B$4)-M4-B4*D4*20%) -> 21734.87
A5: Denver | B5: 24 | C5: 574 | D5: =C5*Parameters!$B$3 -> 574 | E5: Staybridge Suites Denver Downtown by IHG | F5: 103 | G5: 4 | H5: =F5*G5*12% -> 49.44 | I5: =234-IF(Parameters!$B$5="Yes",23,0) -> 234 | J5: 180 | K5: 12 | L5: 20.5 | M5: =B5*(D5+F5*G5+H5+I5+J5+K5+L5) -> 35566.56 | N5: 0 | O5: 0 | P5: 0 | Q5: 0 | R5: =M5+SUM(N5:Q5) -> 35566.56 | S5: =R5*Parameters!$B$4 -> 1778.328 | T5: =R5+S5 -> 37344.888 | U5: =(M5+B5*D5*20%+SUM(N5:Q5))*(1+Parameters!$B$4) -> 40237.848 | V5: =IF(OR(C5=0,F5=0),"NO QUOTE",IF(T5<=Parameters!$B$2,"WITHIN CAP","OVER CAP")) -> WITHIN CAP | W5: =IF(AND(Parameters!$B$6=DATE(2026,11,28),Parameters!$B$7=DATE(2026,12,2)),"Date match","RE-QUOTE") -> Date match | X5: CONDITIONAL: quality detail, breakfast, inventory, venue/RFP pending | Y5: =MAX(0,Parameters!$B$2/(1+Parameters!$B$4)-M5) -> 14909.63 | Z5: =MAX(0,Parameters!$B$2/(1+Parameters!$B$4)-M5-B5*D5*20%) -> 12154.43
A6: Phoenix | B6: 18 | C6: 581 | D6: =C6*Parameters!$B$3 -> 581 | E6: La Quinta Inn & Suites by Wyndham Phoenix Chandler | F6: 100 | G6: 4 | H6: =F6*G6*12% -> 48 | I6: =223-IF(Parameters!$B$5="Yes",22,0) -> 223 | J6: 180 | K6: 12 | L6: 4 | M6: =B6*(D6+F6*G6+H6+I6+J6+K6+L6) -> 26064 | N6: 0 | O6: 0 | P6: 0 | Q6: 0 | R6: =M6+SUM(N6:Q6) -> 26064 | S6: =R6*Parameters!$B$4 -> 1303.2 | T6: =R6+S6 -> 27367.2 | U6: =(M6+B6*D6*20%+SUM(N6:Q6))*(1+Parameters!$B$4) -> 29563.38 | V6: =IF(OR(C6=0,F6=0),"NO QUOTE",IF(T6<=Parameters!$B$2,"WITHIN CAP","OVER CAP")) -> WITHIN CAP | W6: =IF(AND(Parameters!$B$6=DATE(2026,11,28),Parameters!$B$7=DATE(2026,12,2)),"Date match","RE-QUOTE") -> Date match | X6: CONDITIONAL: quality detail, breakfast, inventory, venue/RFP pending | Y6: =MAX(0,Parameters!$B$2/(1+Parameters!$B$4)-M6) -> 24412.19 | Z6: =MAX(0,Parameters!$B$2/(1+Parameters!$B$4)-M6-B6*D6*20%) -> 22320.59
A7: Phoenix | B7: 24 | C7: 581 | D7: =C7*Parameters!$B$3 -> 581 | E7: La Quinta Inn & Suites by Wyndham Phoenix Chandler | F7: 100 | G7: 4 | H7: =F7*G7*12% -> 48 | I7: =223-IF(Parameters!$B$5="Yes",22,0) -> 223 | J7: 180 | K7: 12 | L7: 4 | M7: =B7*(D7+F7*G7+H7+I7+J7+K7+L7) -> 34752 | N7: 0 | O7: 0 | P7: 0 | Q7: 0 | R7: =M7+SUM(N7:Q7) -> 34752 | S7: =R7*Parameters!$B$4 -> 1737.6 | T7: =R7+S7 -> 36489.6 | U7: =(M7+B7*D7*20%+SUM(N7:Q7))*(1+Parameters!$B$4) -> 39417.84 | V7: =IF(OR(C7=0,F7=0),"NO QUOTE",IF(T7<=Parameters!$B$2,"WITHIN CAP","OVER CAP")) -> WITHIN CAP | W7: =IF(AND(Parameters!$B$6=DATE(2026,11,28),Parameters!$B$7=DATE(2026,12,2)),"Date match","RE-QUOTE") -> Date match | X7: CONDITIONAL: quality detail, breakfast, inventory, venue/RFP pending | Y7: =MAX(0,Parameters!$B$2/(1+Parameters!$B$4)-M7) -> 15724.19 | Z7: =MAX(0,Parameters!$B$2/(1+Parameters!$B$4)-M7-B7*D7*20%) -> 12935.39
A8: Boston | B8: 18 | C8: 316 | D8: =C8*Parameters!$B$3 -> 316 | E8: Studio Allston Hotel | F8: 155.5 | G8: 4 | H8: =F8*G8*12% -> 74.64 | I8: =234-IF(Parameters!$B$5="Yes",23,0) -> 234 | J8: 180 | K8: 12 | L8: 4.8 | M8: =B8*(D8+F8*G8+H8+I8+J8+K8+L8) -> 25981.92 | N8: 0 | O8: 0 | P8: 0 | Q8: 0 | R8: =M8+SUM(N8:Q8) -> 25981.92 | S8: =R8*Parameters!$B$4 -> 1299.096 | T8: =R8+S8 -> 27281.016 | U8: =(M8+B8*D8*20%+SUM(N8:Q8))*(1+Parameters!$B$4) -> 28475.496 | V8: =IF(OR(C8=0,F8=0),"NO QUOTE",IF(T8<=Parameters!$B$2,"WITHIN CAP","OVER CAP")) -> WITHIN CAP | W8: =IF(AND(Parameters!$B$6=DATE(2026,11,28),Parameters!$B$7=DATE(2026,12,2)),"Date match","RE-QUOTE") -> Date match | X8: CONDITIONAL: total-price tax basis, breakfast, quality detail, inventory, venue/RFP pending | Y8: =MAX(0,Parameters!$B$2/(1+Parameters!$B$4)-M8) -> 24494.27 | Z8: =MAX(0,Parameters!$B$2/(1+Parameters!$B$4)-M8-B8*D8*20%) -> 23356.67
A9: Boston | B9: 24 | C9: 316 | D9: =C9*Parameters!$B$3 -> 316 | E9: Studio Allston Hotel | F9: 155.5 | G9: 4 | H9: =F9*G9*12% -> 74.64 | I9: =234-IF(Parameters!$B$5="Yes",23,0) -> 234 | J9: 180 | K9: 12 | L9: 4.8 | M9: =B9*(D9+F9*G9+H9+I9+J9+K9+L9) -> 34642.56 | N9: 0 | O9: 0 | P9: 0 | Q9: 0 | R9: =M9+SUM(N9:Q9) -> 34642.56 | S9: =R9*Parameters!$B$4 -> 1732.128 | T9: =R9+S9 -> 36374.688 | U9: =(M9+B9*D9*20%+SUM(N9:Q9))*(1+Parameters!$B$4) -> 37967.328 | V9: =IF(OR(C9=0,F9=0),"NO QUOTE",IF(T9<=Parameters!$B$2,"WITHIN CAP","OVER CAP")) -> WITHIN CAP | W9: =IF(AND(Parameters!$B$6=DATE(2026,11,28),Parameters!$B$7=DATE(2026,12,2)),"Date match","RE-QUOTE") -> Date match | X9: CONDITIONAL: total-price tax basis, breakfast, quality detail, inventory, venue/RFP pending | Y9: =MAX(0,Parameters!$B$2/(1+Parameters!$B$4)-M9) -> 15833.63 | Z9: =MAX(0,Parameters!$B$2/(1+Parameters!$B$4)-M9-B9*D9*20%) -> 14316.83
A10: Seattle | B10: 18 | C10: 0 | D10: =C10*Parameters!$B$3 -> 0 | E10: No usable dated quote | F10: 0 | G10: 4 | H10: =F10*G10*12% -> 0 | I10: =234-IF(Parameters!$B$5="Yes",23,0) -> 234 | J10: 180 | K10: 12 | L10: 6 | M10: =B10*(D10+F10*G10+H10+I10+J10+K10+L10) -> 7776 | N10: 0 | O10: 0 | P10: 0 | Q10: 0 | R10: =M10+SUM(N10:Q10) -> 7776 | S10: =R10*Parameters!$B$4 -> 388.8 | T10: =R10+S10 -> 8164.8 | U10: =(M10+B10*D10*20%+SUM(N10:Q10))*(1+Parameters!$B$4) -> 8164.8 | V10: =IF(OR(C10=0,F10=0),"NO QUOTE",IF(T10<=Parameters!$B$2,"WITHIN CAP","OVER CAP")) -> NO QUOTE | W10: =IF(AND(Parameters!$B$6=DATE(2026,11,28),Parameters!$B$7=DATE(2026,12,2)),"Date match","RE-QUOTE") -> Date match | X10: EXCLUDED: no verifiable airfare/hotel quote; re-query required | Y10: =MAX(0,Parameters!$B$2/(1+Parameters!$B$4)-M10) -> 42700.19 | Z10: =MAX(0,Parameters!$B$2/(1+Parameters!$B$4)-M10-B10*D10*20%) -> 42700.19
A11: Seattle | B11: 24 | C11: 0 | D11: =C11*Parameters!$B$3 -> 0 | E11: No usable dated quote | F11: 0 | G11: 4 | H11: =F11*G11*12% -> 0 | I11: =234-IF(Parameters!$B$5="Yes",23,0) -> 234 | J11: 180 | K11: 12 | L11: 6 | M11: =B11*(D11+F11*G11+H11+I11+J11+K11+L11) -> 10368 | N11: 0 | O11: 0 | P11: 0 | Q11: 0 | R11: =M11+SUM(N11:Q11) -> 10368 | S11: =R11*Parameters!$B$4 -> 518.4 | T11: =R11+S11 -> 10886.4 | U11: =(M11+B11*D11*20%+SUM(N11:Q11))*(1+Parameters!$B$4) -> 10886.4 | V11: =IF(OR(C11=0,F11=0),"NO QUOTE",IF(T11<=Parameters!$B$2,"WITHIN CAP","OVER CAP")) -> NO QUOTE | W11: =IF(AND(Parameters!$B$6=DATE(2026,11,28),Parameters!$B$7=DATE(2026,12,2)),"Date match","RE-QUOTE") -> Date match | X11: EXCLUDED: no verifiable airfare/hotel quote; re-query required | Y11: =MAX(0,Parameters!$B$2/(1+Parameters!$B$4)-M11) -> 40108.19 | Z11: =MAX(0,Parameters!$B$2/(1+Parameters!$B$4)-M11-B11*D11*20%) -> 40108.19

Sheet Daily
A1: Date | B1: Day / provision | C1: Lodging nights | D1: Lodging | E1: Lodging tax (12%) | F1: M&IE basis | G1: Meal deductions | H1: M&IE | I1: Airfare | J1: Registration | K1: Ground transport | L1: Unknowns allocation | M1: Daily total | N1: Source/condition
A2: 46354 | B2: Travel; government dinner | C2: 1 | D2: =C2*INDEX(Options!$F$2:$F$11,MATCH(1,(Options!$A$2:$A$11=Parameters!$B$8)*(Options!$B$2:$B$11=Parameters!$B$9),0))*Parameters!$B$9 -> 3216 | E2: =D2*12% -> 385.92 | F2: 75% rate | G2: Dinner | H2: =(IF(Parameters!$B$8="Phoenix",28.5,31))*Parameters!$B$9 -> 744 | I2: =IF(ROW()=2,INDEX(Options!$D$2:$D$11,MATCH(1,(Options!$A$2:$A$11=Parameters!$B$8)*(Options!$B$2:$B$11=Parameters!$B$9),0))*Parameters!$B$9,0) -> 6480 | J2: =IF(ROW()=3,180*Parameters!$B$9,0) -> 0 | K2: =IF(ROW()=2,INDEX(Options!$K$2:$K$11,MATCH(1,(Options!$A$2:$A$11=Parameters!$B$8)*(Options!$B$2:$B$11=Parameters!$B$9),0))*Parameters!$B$9,IF(ROW()=6,INDEX(Options!$L$2:$L$11,MATCH(1,(Options!$A$2:$A$11=Parameters!$B$8)*(Options!$B$2:$B$11=Parameters!$B$9),0))*Parameters!$B$9,0)) -> 288 | L2: =IF(ROW()=3,SUM(INDEX(Options!$N$2:$Q$11,MATCH(1,(Options!$A$2:$A$11=Parameters!$B$8)*(Options!$B$2:$B$11=Parameters!$B$9),0),0)),0) -> 0 | M2: =SUM(D2:E2)+SUM(H2:L2) -> 11113.92 | N2: Hotel quote is single room snapshot; meals/venue pending
A3: 46355 | B3: Training; registration lunch | C3: 1 | D3: =C3*INDEX(Options!$F$2:$F$11,MATCH(1,(Options!$A$2:$A$11=Parameters!$B$8)*(Options!$B$2:$B$11=Parameters!$B$9),0))*Parameters!$B$9 -> 3216 | E3: =D3*12% -> 385.92 | F3: 100% rate | G3: Lunch | H3: =(IF(Parameters!$B$8="Phoenix",63,66)-IF(Parameters!$B$5="Yes",IF(Parameters!$B$8="Phoenix",22,23),0))*Parameters!$B$9 -> 1584 | I3: =IF(ROW()=2,INDEX(Options!$D$2:$D$11,MATCH(1,(Options!$A$2:$A$11=Parameters!$B$8)*(Options!$B$2:$B$11=Parameters!$B$9),0))*Parameters!$B$9,0) -> 0 | J3: =IF(ROW()=3,180*Parameters!$B$9,0) -> 4320 | K3: =IF(ROW()=2,INDEX(Options!$K$2:$K$11,MATCH(1,(Options!$A$2:$A$11=Parameters!$B$8)*(Options!$B$2:$B$11=Parameters!$B$9),0))*Parameters!$B$9,IF(ROW()=6,INDEX(Options!$L$2:$L$11,MATCH(1,(Options!$A$2:$A$11=Parameters!$B$8)*(Options!$B$2:$B$11=Parameters!$B$9),0))*Parameters!$B$9,0)) -> 0 | L3: =IF(ROW()=3,SUM(INDEX(Options!$N$2:$Q$11,MATCH(1,(Options!$A$2:$A$11=Parameters!$B$8)*(Options!$B$2:$B$11=Parameters!$B$9),0),0)),0) -> 0 | M3: =SUM(D3:E3)+SUM(H3:L3) -> 9505.92 | N3: Hotel quote is single room snapshot; meals/venue pending
A4: 46356 | B4: Training; registration lunch | C4: 1 | D4: =C4*INDEX(Options!$F$2:$F$11,MATCH(1,(Options!$A$2:$A$11=Parameters!$B$8)*(Options!$B$2:$B$11=Parameters!$B$9),0))*Parameters!$B$9 -> 3216 | E4: =D4*12% -> 385.92 | F4: 100% rate | G4: Lunch | H4: =(IF(Parameters!$B$8="Phoenix",63,66))*Parameters!$B$9 -> 1584 | I4: =IF(ROW()=2,INDEX(Options!$D$2:$D$11,MATCH(1,(Options!$A$2:$A$11=Parameters!$B$8)*(Options!$B$2:$B$11=Parameters!$B$9),0))*Parameters!$B$9,0) -> 0 | J4: =IF(ROW()=3,180*Parameters!$B$9,0) -> 0 | K4: =IF(ROW()=2,INDEX(Options!$K$2:$K$11,MATCH(1,(Options!$A$2:$A$11=Parameters!$B$8)*(Options!$B$2:$B$11=Parameters!$B$9),0))*Parameters!$B$9,IF(ROW()=6,INDEX(Options!$L$2:$L$11,MATCH(1,(Options!$A$2:$A$11=Parameters!$B$8)*(Options!$B$2:$B$11=Parameters!$B$9),0))*Parameters!$B$9,0)) -> 0 | L4: =IF(ROW()=3,SUM(INDEX(Options!$N$2:$Q$11,MATCH(1,(Options!$A$2:$A$11=Parameters!$B$8)*(Options!$B$2:$B$11=Parameters!$B$9),0),0)),0) -> 0 | M4: =SUM(D4:E4)+SUM(H4:L4) -> 5185.92 | N4: Hotel quote is single room snapshot; meals/venue pending
A5: 46357 | B5: Training; registration lunch + government dinner | C5: 1 | D5: =C5*INDEX(Options!$F$2:$F$11,MATCH(1,(Options!$A$2:$A$11=Parameters!$B$8)*(Options!$B$2:$B$11=Parameters!$B$9),0))*Parameters!$B$9 -> 3216 | E5: =D5*12% -> 385.92 | F5: 100% rate | G5: Lunch + dinner | H5: =(IF(Parameters!$B$8="Phoenix",27,28))*Parameters!$B$9 -> 672 | I5: =IF(ROW()=2,INDEX(Options!$D$2:$D$11,MATCH(1,(Options!$A$2:$A$11=Parameters!$B$8)*(Options!$B$2:$B$11=Parameters!$B$9),0))*Parameters!$B$9,0) -> 0 | J5: =IF(ROW()=3,180*Parameters!$B$9,0) -> 0 | K5: =IF(ROW()=2,INDEX(Options!$K$2:$K$11,MATCH(1,(Options!$A$2:$A$11=Parameters!$B$8)*(Options!$B$2:$B$11=Parameters!$B$9),0))*Parameters!$B$9,IF(ROW()=6,INDEX(Options!$L$2:$L$11,MATCH(1,(Options!$A$2:$A$11=Parameters!$B$8)*(Options!$B$2:$B$11=Parameters!$B$9),0))*Parameters!$B$9,0)) -> 0 | L5: =IF(ROW()=3,SUM(INDEX(Options!$N$2:$Q$11,MATCH(1,(Options!$A$2:$A$11=Parameters!$B$8)*(Options!$B$2:$B$11=Parameters!$B$9),0),0)),0) -> 0 | M5: =SUM(D5:E5)+SUM(H5:L5) -> 4273.92 | N5: Hotel quote is single room snapshot; meals/venue pending
A6: 46358 | B6: Return; government lunch | C6: 0 | D6: =C6*INDEX(Options!$F$2:$F$11,MATCH(1,(Options!$A$2:$A$11=Parameters!$B$8)*(Options!$B$2:$B$11=Parameters!$B$9),0))*Parameters!$B$9 -> 0 | E6: =D6*12% -> 0 | F6: 75% rate | G6: Lunch | H6: =(IF(Parameters!$B$8="Phoenix",41.5,43))*Parameters!$B$9 -> 1032 | I6: =IF(ROW()=2,INDEX(Options!$D$2:$D$11,MATCH(1,(Options!$A$2:$A$11=Parameters!$B$8)*(Options!$B$2:$B$11=Parameters!$B$9),0))*Parameters!$B$9,0) -> 0 | J6: =IF(ROW()=3,180*Parameters!$B$9,0) -> 0 | K6: =IF(ROW()=2,INDEX(Options!$K$2:$K$11,MATCH(1,(Options!$A$2:$A$11=Parameters!$B$8)*(Options!$B$2:$B$11=Parameters!$B$9),0))*Parameters!$B$9,IF(ROW()=6,INDEX(Options!$L$2:$L$11,MATCH(1,(Options!$A$2:$A$11=Parameters!$B$8)*(Options!$B$2:$B$11=Parameters!$B$9),0))*Parameters!$B$9,0)) -> 288 | L6: =IF(ROW()=3,SUM(INDEX(Options!$N$2:$Q$11,MATCH(1,(Options!$A$2:$A$11=Parameters!$B$8)*(Options!$B$2:$B$11=Parameters!$B$9),0),0)),0) -> 0 | M6: =SUM(D6:E6)+SUM(H6:L6) -> 1320 | N6: Hotel quote is single room snapshot; meals/venue pending
A8: Base subtotal | B8: =SUM(M2:M6) -> 31399.68
A9: Reserve | B9: =B8*Parameters!B4 -> 1569.984
A10: Total | B10: =SUM(B8:B9) -> 32969.664
A11: Reconciliation | B11: =B10-INDEX(Options!T2:T11,MATCH(1,(Options!A2:A11=Parameters!B8)*(Options!B2:B11=Parameters!B9),0)) -> 0

Sheet Itineraries_Hotels
A1: City | B1: Airport | C1: Outbound 11/28 | D1: Return 12/2 | E1: Fare | F1: Primary hotel | G1: Primary price basis | H1: Score | I1: Reviews | J1: Alternative | K1: Alt price | L1: Alt score | M1: Quality admission | N1: Trade-off / exclusion
A2: Chicago | B2: ORD | C2: DCA 06:00–ORD 07:32 nonstop | D2: ORD 16:59–DCA 19:59 nonstop | E2: 270 | F2: Staybridge Suites Chicago—Glenview by IHG | G2: $134.00/night, 1 room, 4 nights | H2: 8.5 | I2: not displayed | J2: Hampton Inn & Suites Chicago/Hoffman Estates | K2: 96 | L2: 8.1 | M2: NOT YET ADMITTED | N2: Threshold: score ≥8.0/10, ≥100 reviews, and no unresolved recent cleanliness/noise/maintenance pattern. Review count and recent issue evidence were not displayed; breakfast/refund terms and group stock pending.
A3: Denver | B3: DEN | C3: DCA 07:00–DEN 09:16 nonstop | D3: DEN 16:40–DCA 21:55 nonstop | E3: 574 | F3: Staybridge Suites Denver Downtown by IHG | G3: $103.00/night, 1 room, 4 nights | H3: 8.3 | I3: not displayed | J3: Hyatt House Denver/Downtown | K3: 116 | L3: 8.7 | M3: NOT YET ADMITTED | N3: Threshold: score ≥8.0/10, ≥100 reviews, and no unresolved recent cleanliness/noise/maintenance pattern. Review count and recent issue evidence were not displayed; breakfast/refund terms and group stock pending.
A4: Phoenix | B4: PHX | C4: DCA 10:32–PHX 13:51 nonstop | D4: PHX 14:46–DCA 20:59 nonstop | E4: 581 | F4: La Quinta Inn & Suites by Wyndham Phoenix Chandler | G4: $100.00/night, 1 room, 4 nights | H4: 8.3 | I4: not displayed | J4: Radisson Hotel Phoenix Airport | K4: 118 | L4: 8 | M4: NOT YET ADMITTED | N4: Threshold: score ≥8.0/10, ≥100 reviews, and no unresolved recent cleanliness/noise/maintenance pattern. Review count and recent issue evidence were not displayed; breakfast/refund terms and group stock pending.
A5: Boston | B5: BOS | C5: DCA 07:00–BOS 08:50 nonstop | D5: BOS 17:17–DCA 19:13 nonstop | E5: 316 | F5: Studio Allston Hotel | G5: $155.50/night, 1 room, 4 nights | H5: 8.2 | I5: not displayed | J5: DoubleTree by Hilton Boston-Downtown | K5: 165.5 | L5: 8.4 | M5: NOT YET ADMITTED | N5: Threshold: score ≥8.0/10, ≥100 reviews, and no unresolved recent cleanliness/noise/maintenance pattern. Review count and recent issue evidence were not displayed; breakfast/refund terms and group stock pending.
A6: Seattle | B6: SEA | C6: DCA–SEA: re-quote required | D6: SEA–DCA: re-quote required | E6: 0 | F6: No usable dated quote | G6: None | H6: 0 | I6: — | J6: No usable second dated quote | K6: 0 | L6: 0 | M6: EXCLUDED—no dated quotes | N6: EXCLUDED: no verifiable airfare/hotel quote; re-query required

Sheet Historical_Rates
A1: City | B1: FY | C1: Nov lodging cap | D1: Dec lodging cap | E1: M&IE | F1: Chosen market room | G1: Nov compliant | H1: Dec compliant | I1: Budget delta vs FY27 | J1: Selection effect
A2: Chicago | B2: 2025 | C2: 223 | D2: 142 | E2: 92 | F2: 134 | G2: Yes | H2: Yes | I2: 0 | J2: No modeled cost change: market quote/M&IE held constant; only compliance caps compared.
A3: Chicago | B3: 2026 | C3: 223 | D3: 142 | E3: 92 | F3: 134 | G3: Yes | H3: Yes | I3: 0 | J3: No modeled cost change: market quote/M&IE held constant; only compliance caps compared.
A4: Chicago | B4: 2027 | C4: 232 | D4: 148 | E4: 92 | F4: 134 | G4: Yes | H4: Yes | I4: 0 | J4: No modeled cost change: market quote/M&IE held constant; only compliance caps compared.
A5: Denver | B5: 2025 | C5: 165 | D5: 165 | E5: 92 | F5: 103 | G5: Yes | H5: Yes | I5: 0 | J5: No modeled cost change: market quote/M&IE held constant; only compliance caps compared.
A6: Denver | B6: 2026 | C6: 165 | D6: 165 | E6: 92 | F6: 103 | G6: Yes | H6: Yes | I6: 0 | J6: No modeled cost change: market quote/M&IE held constant; only compliance caps compared.
A7: Denver | B7: 2027 | C7: 170 | D7: 170 | E7: 92 | F7: 103 | G7: Yes | H7: Yes | I7: 0 | J7: No modeled cost change: market quote/M&IE held constant; only compliance caps compared.
A8: Phoenix | B8: 2025 | C8: 160 | D8: 160 | E8: 86 | F8: 100 | G8: Yes | H8: Yes | I8: 0 | J8: No modeled cost change: market quote/M&IE held constant; only compliance caps compared.
A9: Phoenix | B9: 2026 | C9: 160 | D9: 160 | E9: 86 | F9: 100 | G9: Yes | H9: Yes | I9: 0 | J9: No modeled cost change: market quote/M&IE held constant; only compliance caps compared.
A10: Phoenix | B10: 2027 | C10: 165 | D10: 165 | E10: 86 | F10: 100 | G10: Yes | H10: Yes | I10: 0 | J10: No modeled cost change: market quote/M&IE held constant; only compliance caps compared.
A11: Boston | B11: 2025 | C11: 209 | D11: 209 | E11: 92 | F11: 155.5 | G11: Yes | H11: Yes | I11: 0 | J11: No modeled cost change: market quote/M&IE held constant; only compliance caps compared.
A12: Boston | B12: 2026 | C12: 209 | D12: 209 | E12: 92 | F12: 155.5 | G12: Yes | H12: Yes | I12: 0 | J12: No modeled cost change: market quote/M&IE held constant; only compliance caps compared.
A13: Boston | B13: 2027 | C13: 213 | D13: 213 | E13: 92 | F13: 155.5 | G13: Yes | H13: Yes | I13: 0 | J13: No modeled cost change: market quote/M&IE held constant; only compliance caps compared.
... A16: Seattle | B16: 2027 | C16: 188 | D16: 188 | E16: 92 | F16: 0 | G16: N/A—no quote | H16: N/A—no quote | I16: 0 | J16: No modeled cost change: market quote/M&IE held constant; only compliance caps compared.

Sheet Thresholds_Actions
A1: Decision question | B1: Formula / boundary | C1: Current result | D1: Action
A2: Recommended baseline | B2: Priority: max attendance; then lowest total; valid/quality conditions required | C2: =INDEX(Options!A2:A9,MATCH(MIN(Options!T3,Options!T5,Options!T7,Options!T9),Options!T2:T9,0))&" / 24 (conditional)" -> Chicago / 24 (conditional) | D2: Use Chicago only after blockers close.
A3: Chicago 24 vs Boston 24 airfare increase 0–20% | B3: Chicago stays cheaper because both intercept and airfare slope are lower. | C3: No switch in [0%,20%]. | D3: Switch only if Chicago-specific unknown cost exceeds Boston-specific unknown by break-even.
A4: Unknown-cost break-even: Chicago→Boston at airfare increase g | B4: U_CHI − U_BOS > 24*[(316−270)*(1+g)+(4*155.5+74.64+4.8)−(4*134+64.32+12)] | C4: =24*((316-270)*Parameters!B3+(622+74.64+4.8)-(536+64.32+12)) -> 3242.88 | D4: If exceeded and Boston blockers close, select Boston.
A5: 24→18 threshold (same city) | B5: 24-person total > cap while 18-person total ≤ cap | C5: See Options columns T/U/Y/Z. | D5: Reduce only after all compliant 24-person alternatives exceed cap.
A6: Both sizes infeasible | B6: 18-person total > cap | C6: Compare Options total with cap. | D6: Do not approve; seek scope/funding changes.
A7: Unknown max excluding reserve, baseline | B7: Cap/(1+reserve) − quoted/estimated base | C7: =INDEX(Options!Y2:Y11,MATCH(1,(Options!A2:A11="Chicago")*(Options!B2:B11=24),0)) -> 19076.51 | D7: Combined Chicago venue/meals/breaks/other must not exceed.
A8: Unknown max excluding reserve, +20% airfare | B8: Cap/(1+reserve) − known base − 20% adjusted airfare | C8: =INDEX(Options!Z2:Z11,MATCH(1,(Options!A2:A11="Chicago")*(Options!B2:B11=24),0)) -> 17780.51 | D8: Re-price or move/reduce if exceeded.
A9: Date validity | B9: Arrival/return must equal quote dates | C9: =IF(AND(Parameters!B6=DATE(2026,11,28),Parameters!B7=DATE(2026,12,2)),"VALID SNAPSHOT","RE-QUOTE ALL") -> VALID SNAPSHOT | D9: Re-export all snapshot files after any parameter change.

Sheet Sources
A1: ID | B1: Subject | C1: Source / URL or file | D1: Retrieved / frozen | E1: Applies to | F1: Evidence / limitation
A2: S1 | B2: Fares and hotel cards | C2: https://www.kayak.com/flights/DCA-ORD/2026-11-28/2026-12-02?sort=bestflight_a | D2: 2026-10-24 04:30 UTC | E2: Chicago | F2: Screenshots: route/dates/times/fare/class; hotel cards show dates/name/rating/price, not breakfast/tax/refund/review count.
A3: S2 | B3: Fares and hotel cards | C3: https://www.kayak.com/flights/DCA-DEN/2026-11-28/2026-12-02?sort=bestflight_a | D3: 2026-10-24 04:30 UTC | E3: Denver | F3: Same limitation.
A4: S3 | B4: Fares and hotel cards | C4: https://www.kayak.com/flights/DCA-PHX/2026-11-28/2026-12-02?sort=bestflight_a | D4: 2026-10-24 04:30 UTC | E4: Phoenix | F4: Same limitation.
A5: S4 | B5: Fares and hotel cards | C5: https://www.cheapflights.com/flight-search/DCA-BOS/2026-11-28/2026-12-02?sort=bestflight_a | D5: 2026-10-24 04:30 UTC | E5: Boston | F5: Hotel prices displayed as 4-night total; tax basis not identified.
A6: S5 | B6: Seattle search attempts | C6: Kayak/Cheapflights/Priceline dated search URLs (see evidence deck) | D6: 2026-10-24 04:30 UTC | E6: Seattle | F6: Anti-bot challenge; no usable quote, excluded.
A7: S6 | B7: FY2025 rates | C7: /app/input_files/FY2025_PerDiemMasterRatesFile.xlsx | D7: provided; effective 2024-10-01 | E7: Historical only | F7: City/county and seasonal lodging/M&IE.
A8: S7 | B8: FY2026 rates | C8: /app/input_files/FY2026_PerDiemMasterRatesFile.xlsx | D8: provided; effective 2025-10-01 | E8: Historical only | F8: City/county and seasonal lodging/M&IE.
A9: S8 | B9: FY2027 rates | C9: /app/input_files/FY2027_PerDiemRates_Validated090126.xlsx | D9: provided; effective 2026-10-01 | E9: Actual trip | F9: Validated file supplied.
A10: S9 | B10: M&IE breakdown | C10: /app/input_files/GSA_FY2025_MIE_Breakdown.docx | D10: provided | E10: Meal deductions | F10: Breakdowns 86/92; assumed unchanged because supplied FY27 city M&IE totals match categories; verify current GSA breakdown before authorization.
A11: S10 | B11: FTR 301-11 | C11: /app/input_files/eCFR_41_CFR_301-11.xml | D11: frozen 2025-01-01 | E11: Per diem | F11: §§301-11.7,.9,.17,.18,.27,.101,.300; current applicability must be checked.
A12: S11 | B12: FTR 301-74 | C12: /app/input_files/eCFR_41_CFR_301-74.xml | D12: frozen 2025-01-01 | E12: Conference planning | F12: §§301-74.1-.5,.21-.22.
... A15: S14 | B15: Hotel quality rule | C15: Internal uniform admission rule | D15: 2026-10-24 | E15: All hotels | F15: ≥8.0/10, ≥100 reviews, no unresolved recent cleanliness/noise/maintenance pattern. Missing evidence prevents admission.
