Workbook
Name CEILING: Parameters!$B$5
Name FFAC: Parameters!$B$6
Name RESRATE: Parameters!$B$7
Name NOV29BF: Parameters!$B$8
Name HEADCOUNT: Parameters!$B$9
Name NIGHTS: Parameters!$B$10
Name TAXRATE: Parameters!$B$11
Name REGFEE: Parameters!$B$12
Name VENUEDAY: CityData!$B$26
Name VENUEDAYS: CityData!$B$27
Name REFRPP: CityData!$B$28
Name REFRDAYS: CityData!$B$29

Sheet Parameters
A1: USDA RURAL DEVELOPMENT — CENTRALIZED TRAINING BUDGET (Nov 29 – Dec 1, 2026)
A2: Adjust the yellow cells. Daily, Options, Historical and Thresholds sheets recompute automatically. No internet pricing is pulled; quotes are a 2026-10-24 snapshot.
A4: Parameter | B4: Value | C4: Allowed range / note | D4: Unit
A5: Approved budget ceiling (incl. reserve) | B5: 53000 | C5: 0 – 100,000 (incl. reserve) | D5: USD
A6: Airfare adjustment factor | B6: 1 | C6: 0.5 – 2.0; stress scenario = factor × 1.20
A7: Contingency reserve rate | B7: 0.05 | C7: 0 – 20% of base subtotal
A8: Nov 29 breakfast provided by government? | B8: No | C8: Yes/No — 'Yes' adds NO new purchase
A9: Attendee count (headcount) | B9: 24 | C9: 18 or 24
A10: Lodging nights | B10: 4 | C10: Nov 28/29/30/Dec 1 (checkout Dec 2) | D10: nights
A11: Internal lodging-tax rate (budget est.) | B11: 0.12 | C11: 12% of reimbursable lodging — planning only
A12: Registration fee per person | B12: 180 | C12: Incl. lunches Nov 29/30 & Dec 1 | D12: USD
A13: Arrival date | B13: 2026-11-28 | C13: Day before training; must fully attend
A14: Departure date | B14: 2026-12-02 | C14: Day after training
A15: Training dates (fixed) | B15: 2026-11-29 → 2026-12-01 | C15: Catered dates unchanged
A18: Key regulatory basis:
A19: • 41 CFR 301-11.100 / 301-74.6: lodging reimbursed at actual cost not exceeding locality per-diem cap (per night).
A20: • 41 CFR 301-74.1/.3/.4/.5: minimize cost; compare ≥ sites using established per-diem rates.
A21: • 41 CFR 301-74.7: light refreshments (coffee/fruit/water) allowed; no M&IE deduction (301-74.21(b)).
A22: • 41 CFR 301-11.18 / 301-74.21(a): furnished meals deducted from traveler M&IE (not applicable to this agency-funded catering budget).
A23: • RD Instruction 2036-A (eff. 2024-07-19): RD travel policy — attendee travel kept to minimum necessary; per-diem compliance required.
A24: • Over-cap hotels are NOT compliant recommendations without written actual-expense authorization (301-11.300/.301); none is held.
A30: SNAPSHOT NOTICE: Word/CSV/PPT/PDF deliverables reflect the itinerary & parameters above as of 2026-10-24. If any yellow parameter or date changes, re-check whether quotes still apply, distinguish executable vs. re-quote-pending estimates, and re-export the affected files.

Sheet CityData
A1: CITY ANCHOR DATA — real market quotes (ITA Matrix flights; Trip.com hotels) queried 2026-10-24, USD
A2: City | B2: Dest airport | C2: Flight RT (nonstop, DCA) | D2: Flight airline | E2: Hotel (budgeted) | F2: Hotel nightly (excl tax) | G2: Hotel rating /10 | H2: Reviews | I2: Breakfast incl? | J2: FY27 cap Nov night | K2: FY27 cap Dec1 night | L2: MIE (FY27)
A3: Boston | B3: BOS | C3: 358 | D3: American | E3: DoubleTree by Hilton Boston Bayside | F3: 108 | G3: 8.6 | H3: 449 | I3: Yes | J3: 213 | K3: 213 | L3: 92
A4: Chicago | B4: ORD | C4: 270 | D4: American | E4: Warwick Allerton Chicago | F4: 145 | G4: 8.6 | H4: 399 | I4: No | J4: 232 | K4: 148 | L4: 92
A5: Denver | B5: DEN | C5: 741 | D5: Frontier | E5: Home2 Suites by Hilton Denver Downtown | F5: 109 | G5: 9 | H5: 94 | I5: Yes | J5: 170 | K5: 170 | L5: 92
A6: Phoenix | B6: PHX | C6: 581 | D6: American | E6: Hampton Inn & Suites Phoenix | F6: 150 | G6: 9.4 | H6: 116 | I6: Yes | J6: 165 | K6: 165 | L6: 86
A7: Seattle | B7: SEA | C7: 977 | D7: Multiple carriers | E7: Belltown BF-incl (SpringHill-class) | F7: 103 | G7: 8.6 | H7: 114 | I7: Yes | J7: 188 | K7: 188 | L7: 92
A9: Meal planning rates (GSA FY2027 M&IE components, internal catering estimate):
A10: City | B10: Breakfast $ | C10: Lunch $ | D10: Dinner $
A11: Boston | B11: 23 | C11: 26 | D11: 38
A12: Chicago | B12: 23 | C12: 26 | D12: 38
A13: Denver | B13: 23 | C13: 26 | D13: 38
A14: Phoenix | B14: 22 | C14: 23 | D14: 36
A15: Seattle | B15: 23 | C15: 26 | D15: 38
A17: Ground transport RT per person (dest airport↔hotel) + home↔DCA (est). Boston DoubleTree offers free airport shuttle.
A18: City | B18: Airport↔hotel RT $ | C18: Home↔DCA RT $
A19: Boston | B19: 0 | C19: 40
A20: Chicago | B20: 40 | C20: 40
A21: Denver | B21: 60 | C21: 40
A22: Phoenix | B22: 50 | C22: 40
A23: Seattle | B23: 60 | C23: 40
A25: Shared/fixed & light-refreshment planning inputs (to be quoted — see Sources):
A26: Meeting venue per day (est., TBQ) | B26: 1200
A27: Venue days | B27: 3
A28: Light refreshments per person/day (301-74.7) | B28: 15
A29: Refreshment days | B29: 3

Sheet Daily
A1: DAILY PER-PERSON COST DETAIL — driven by recommended city & parameters
A2: Recommended city: | B2: Boston | C2: (change to Boston/Chicago/Denver/Phoenix/Seattle — pulls that city's anchor data)
A4: Per-person building blocks
A5: Round-trip airfare (× airfare factor) | B5: =INDEX(CityData!$C:$C,MATCH(Daily!$B$2,CityData!$A:$A,0))*FFAC
A6: Lodging — room only (nightly × nights) | B6: =INDEX(CityData!$F:$F,MATCH(Daily!$B$2,CityData!$A:$A,0))*NIGHTS
A7: Lodging tax (internal est.) | B7: =B6*TAXRATE
A8: Registration fee (incl. 3 lunches) | B8: =REGFEE
A9: Agency dinners (Nov 28 & Dec 1) | B9: =2*INDEX(CityData!$D$11:$D$15,MATCH(Daily!$B$2,CityData!$A$11:$A$15,0))
A10: Agency lunch (Dec 2 travel-home day) | B10: =INDEX(CityData!$C$11:$C$15,MATCH(Daily!$B$2,CityData!$A$11:$A$15,0))
A11: Breakfast (4 nights) — $0 if hotel-included | B11: =IF(INDEX(CityData!$I:$I,MATCH(Daily!$B$2,CityData!$A:$A,0))="Yes",0,INDEX(CityData!$B$11:$B$15,MATCH(Daily!$B$2,CityData!$A$11:$A$15,0))*NIGHTS)
A12: Nov 29 breakfast adj. (param; no new purchase) | B12: =0
A13: Light refreshments (coffee/fruit/water) | B13: =REFRPP*REFRDAYS
A14: Ground transport (airport↔hotel + home↔DCA) | B14: =INDEX(CityData!$B$19:$B$23,MATCH(Daily!$B$2,CityData!$A$19:$A$23,0))+INDEX(CityData!$C$19:$C$23,MATCH(Daily!$B$2,CityData!$A$19:$A$23,0))
A15: PER-PERSON SUBTOTAL | B15: =SUM(B5:B14)
A17: Shared / fixed costs (per event)
A18: Meeting venue (days × daily rate) — TBQ | B18: =VENUEDAY*VENUEDAYS
A19: FIXED SUBTOTAL | B19: =B18
A21: EVENT TOTALS (at chosen headcount)
A22: Headcount (param) | B22: =HEADCOUNT
A23: Variable total (per-person × headcount) | B23: =B15*HEADCOUNT
A24: Base subtotal (variable + fixed) | B24: =B23+B19
A25: Contingency reserve | B25: =B24*RESRATE
A26: GRAND TOTAL (base + reserve) | B26: =B24+B25
A27: Budget ceiling | B27: =CEILING
A28: Within budget? | B28: =IF(B26<=CEILING,"YES — within ceiling","NO — exceeds ceiling")
A29: Headroom for unquoted/TBD base costs | B29: =CEILING/(1+RESRATE)-B24

Sheet Options
A1: OPTIONS COMPARISON — 5 candidate cities × 18/24 attendees (base & +20% airfare stress)
A2: Per-person & event totals built from the same formulas as Daily. 'Stress' applies airfare ×1.20 on top of the airfare factor. Decision rule: fit ceiling → more people → lower total-with-reserve → alphabetical.
A4: City | B4: Head-count | C4: Airfare RT×fac | D4: Lodging+tax (4n) | E4: Reg | F4: Agency meals+bkfst | G4: Refresh. | H4: Ground | I4: Per-person | J4: Variable ×N | K4: Venue (fixed) | L4: Base subtotal | M4: Reserve | N4: TOTAL (base+res)
A5: Boston | B5: 24 | C5: =INDEX(CityData!$C:$C,MATCH(A5,CityData!$A:$A,0))*FFAC | D5: =INDEX(CityData!$F:$F,MATCH(A5,CityData!$A:$A,0))*NIGHTS*(1+TAXRATE) | E5: =REGFEE | F5: =2*INDEX(CityData!$D$11:$D$15,MATCH(A5,CityData!$A$11:$A$15,0))+INDEX(CityData!$C$11:$C$15,MATCH(A5,CityData!$A$11:$A$15,0))+IF(INDEX(CityData!$I:$I,MATCH(A5,CityData!$A:$A,0))="Yes",0,INDEX(CityData!$B$11:$B$15,MATCH(A5,CityData!$A$11:$A$15,0))*NIGHTS) | G5: =REFRPP*REFRDAYS | H5: =INDEX(CityData!$B$19:$B$23,MATCH(A5,CityData!$A$19:$A$23,0))+INDEX(CityData!$C$19:$C$23,MATCH(A5,CityData!$A$19:$A$23,0)) | I5: =C5+D5+E5+F5+G5+H5 | J5: =I5*B5 | K5: =VENUEDAY*VENUEDAYS | L5: =J5+K5 | M5: =L5*RESRATE | N5: =L5+M5
A6: Boston | B6: 18 | C6: =INDEX(CityData!$C:$C,MATCH(A6,CityData!$A:$A,0))*FFAC | D6: =INDEX(CityData!$F:$F,MATCH(A6,CityData!$A:$A,0))*NIGHTS*(1+TAXRATE) | E6: =REGFEE | F6: =2*INDEX(CityData!$D$11:$D$15,MATCH(A6,CityData!$A$11:$A$15,0))+INDEX(CityData!$C$11:$C$15,MATCH(A6,CityData!$A$11:$A$15,0))+IF(INDEX(CityData!$I:$I,MATCH(A6,CityData!$A:$A,0))="Yes",0,INDEX(CityData!$B$11:$B$15,MATCH(A6,CityData!$A$11:$A$15,0))*NIGHTS) | G6: =REFRPP*REFRDAYS | H6: =INDEX(CityData!$B$19:$B$23,MATCH(A6,CityData!$A$19:$A$23,0))+INDEX(CityData!$C$19:$C$23,MATCH(A6,CityData!$A$19:$A$23,0)) | I6: =C6+D6+E6+F6+G6+H6 | J6: =I6*B6 | K6: =VENUEDAY*VENUEDAYS | L6: =J6+K6 | M6: =L6*RESRATE | N6: =L6+M6
A7: Chicago | B7: 24 | C7: =INDEX(CityData!$C:$C,MATCH(A7,CityData!$A:$A,0))*FFAC | D7: =INDEX(CityData!$F:$F,MATCH(A7,CityData!$A:$A,0))*NIGHTS*(1+TAXRATE) | E7: =REGFEE | F7: =2*INDEX(CityData!$D$11:$D$15,MATCH(A7,CityData!$A$11:$A$15,0))+INDEX(CityData!$C$11:$C$15,MATCH(A7,CityData!$A$11:$A$15,0))+IF(INDEX(CityData!$I:$I,MATCH(A7,CityData!$A:$A,0))="Yes",0,INDEX(CityData!$B$11:$B$15,MATCH(A7,CityData!$A$11:$A$15,0))*NIGHTS) | G7: =REFRPP*REFRDAYS | H7: =INDEX(CityData!$B$19:$B$23,MATCH(A7,CityData!$A$19:$A$23,0))+INDEX(CityData!$C$19:$C$23,MATCH(A7,CityData!$A$19:$A$23,0)) | I7: =C7+D7+E7+F7+G7+H7 | J7: =I7*B7 | K7: =VENUEDAY*VENUEDAYS | L7: =J7+K7 | M7: =L7*RESRATE | N7: =L7+M7
A8: Chicago | B8: 18 | C8: =INDEX(CityData!$C:$C,MATCH(A8,CityData!$A:$A,0))*FFAC | D8: =INDEX(CityData!$F:$F,MATCH(A8,CityData!$A:$A,0))*NIGHTS*(1+TAXRATE) | E8: =REGFEE | F8: =2*INDEX(CityData!$D$11:$D$15,MATCH(A8,CityData!$A$11:$A$15,0))+INDEX(CityData!$C$11:$C$15,MATCH(A8,CityData!$A$11:$A$15,0))+IF(INDEX(CityData!$I:$I,MATCH(A8,CityData!$A:$A,0))="Yes",0,INDEX(CityData!$B$11:$B$15,MATCH(A8,CityData!$A$11:$A$15,0))*NIGHTS) | G8: =REFRPP*REFRDAYS | H8: =INDEX(CityData!$B$19:$B$23,MATCH(A8,CityData!$A$19:$A$23,0))+INDEX(CityData!$C$19:$C$23,MATCH(A8,CityData!$A$19:$A$23,0)) | I8: =C8+D8+E8+F8+G8+H8 | J8: =I8*B8 | K8: =VENUEDAY*VENUEDAYS | L8: =J8+K8 | M8: =L8*RESRATE | N8: =L8+M8
A9: Denver | B9: 24 | C9: =INDEX(CityData!$C:$C,MATCH(A9,CityData!$A:$A,0))*FFAC | D9: =INDEX(CityData!$F:$F,MATCH(A9,CityData!$A:$A,0))*NIGHTS*(1+TAXRATE) | E9: =REGFEE | F9: =2*INDEX(CityData!$D$11:$D$15,MATCH(A9,CityData!$A$11:$A$15,0))+INDEX(CityData!$C$11:$C$15,MATCH(A9,CityData!$A$11:$A$15,0))+IF(INDEX(CityData!$I:$I,MATCH(A9,CityData!$A:$A,0))="Yes",0,INDEX(CityData!$B$11:$B$15,MATCH(A9,CityData!$A$11:$A$15,0))*NIGHTS) | G9: =REFRPP*REFRDAYS | H9: =INDEX(CityData!$B$19:$B$23,MATCH(A9,CityData!$A$19:$A$23,0))+INDEX(CityData!$C$19:$C$23,MATCH(A9,CityData!$A$19:$A$23,0)) | I9: =C9+D9+E9+F9+G9+H9 | J9: =I9*B9 | K9: =VENUEDAY*VENUEDAYS | L9: =J9+K9 | M9: =L9*RESRATE | N9: =L9+M9
A10: Denver | B10: 18 | C10: =INDEX(CityData!$C:$C,MATCH(A10,CityData!$A:$A,0))*FFAC | D10: =INDEX(CityData!$F:$F,MATCH(A10,CityData!$A:$A,0))*NIGHTS*(1+TAXRATE) | E10: =REGFEE | F10: =2*INDEX(CityData!$D$11:$D$15,MATCH(A10,CityData!$A$11:$A$15,0))+INDEX(CityData!$C$11:$C$15,MATCH(A10,CityData!$A$11:$A$15,0))+IF(INDEX(CityData!$I:$I,MATCH(A10,CityData!$A:$A,0))="Yes",0,INDEX(CityData!$B$11:$B$15,MATCH(A10,CityData!$A$11:$A$15,0))*NIGHTS) | G10: =REFRPP*REFRDAYS | H10: =INDEX(CityData!$B$19:$B$23,MATCH(A10,CityData!$A$19:$A$23,0))+INDEX(CityData!$C$19:$C$23,MATCH(A10,CityData!$A$19:$A$23,0)) | I10: =C10+D10+E10+F10+G10+H10 | J10: =I10*B10 | K10: =VENUEDAY*VENUEDAYS | L10: =J10+K10 | M10: =L10*RESRATE | N10: =L10+M10
A11: Phoenix | B11: 24 | C11: =INDEX(CityData!$C:$C,MATCH(A11,CityData!$A:$A,0))*FFAC | D11: =INDEX(CityData!$F:$F,MATCH(A11,CityData!$A:$A,0))*NIGHTS*(1+TAXRATE) | E11: =REGFEE | F11: =2*INDEX(CityData!$D$11:$D$15,MATCH(A11,CityData!$A$11:$A$15,0))+INDEX(CityData!$C$11:$C$15,MATCH(A11,CityData!$A$11:$A$15,0))+IF(INDEX(CityData!$I:$I,MATCH(A11,CityData!$A:$A,0))="Yes",0,INDEX(CityData!$B$11:$B$15,MATCH(A11,CityData!$A$11:$A$15,0))*NIGHTS) | G11: =REFRPP*REFRDAYS | H11: =INDEX(CityData!$B$19:$B$23,MATCH(A11,CityData!$A$19:$A$23,0))+INDEX(CityData!$C$19:$C$23,MATCH(A11,CityData!$A$19:$A$23,0)) | I11: =C11+D11+E11+F11+G11+H11 | J11: =I11*B11 | K11: =VENUEDAY*VENUEDAYS | L11: =J11+K11 | M11: =L11*RESRATE | N11: =L11+M11
A12: Phoenix | B12: 18 | C12: =INDEX(CityData!$C:$C,MATCH(A12,CityData!$A:$A,0))*FFAC | D12: =INDEX(CityData!$F:$F,MATCH(A12,CityData!$A:$A,0))*NIGHTS*(1+TAXRATE) | E12: =REGFEE | F12: =2*INDEX(CityData!$D$11:$D$15,MATCH(A12,CityData!$A$11:$A$15,0))+INDEX(CityData!$C$11:$C$15,MATCH(A12,CityData!$A$11:$A$15,0))+IF(INDEX(CityData!$I:$I,MATCH(A12,CityData!$A:$A,0))="Yes",0,INDEX(CityData!$B$11:$B$15,MATCH(A12,CityData!$A$11:$A$15,0))*NIGHTS) | G12: =REFRPP*REFRDAYS | H12: =INDEX(CityData!$B$19:$B$23,MATCH(A12,CityData!$A$19:$A$23,0))+INDEX(CityData!$C$19:$C$23,MATCH(A12,CityData!$A$19:$A$23,0)) | I12: =C12+D12+E12+F12+G12+H12 | J12: =I12*B12 | K12: =VENUEDAY*VENUEDAYS | L12: =J12+K12 | M12: =L12*RESRATE | N12: =L12+M12
A13: Seattle | B13: 24 | C13: =INDEX(CityData!$C:$C,MATCH(A13,CityData!$A:$A,0))*FFAC | D13: =INDEX(CityData!$F:$F,MATCH(A13,CityData!$A:$A,0))*NIGHTS*(1+TAXRATE) | E13: =REGFEE | F13: =2*INDEX(CityData!$D$11:$D$15,MATCH(A13,CityData!$A$11:$A$15,0))+INDEX(CityData!$C$11:$C$15,MATCH(A13,CityData!$A$11:$A$15,0))+IF(INDEX(CityData!$I:$I,MATCH(A13,CityData!$A:$A,0))="Yes",0,INDEX(CityData!$B$11:$B$15,MATCH(A13,CityData!$A$11:$A$15,0))*NIGHTS) | G13: =REFRPP*REFRDAYS | H13: =INDEX(CityData!$B$19:$B$23,MATCH(A13,CityData!$A$19:$A$23,0))+INDEX(CityData!$C$19:$C$23,MATCH(A13,CityData!$A$19:$A$23,0)) | I13: =C13+D13+E13+F13+G13+H13 | J13: =I13*B13 | K13: =VENUEDAY*VENUEDAYS | L13: =J13+K13 | M13: =L13*RESRATE | N13: =L13+M13
A14: Seattle | B14: 18 | C14: =INDEX(CityData!$C:$C,MATCH(A14,CityData!$A:$A,0))*FFAC | D14: =INDEX(CityData!$F:$F,MATCH(A14,CityData!$A:$A,0))*NIGHTS*(1+TAXRATE) | E14: =REGFEE | F14: =2*INDEX(CityData!$D$11:$D$15,MATCH(A14,CityData!$A$11:$A$15,0))+INDEX(CityData!$C$11:$C$15,MATCH(A14,CityData!$A$11:$A$15,0))+IF(INDEX(CityData!$I:$I,MATCH(A14,CityData!$A:$A,0))="Yes",0,INDEX(CityData!$B$11:$B$15,MATCH(A14,CityData!$A$11:$A$15,0))*NIGHTS) | G14: =REFRPP*REFRDAYS | H14: =INDEX(CityData!$B$19:$B$23,MATCH(A14,CityData!$A$19:$A$23,0))+INDEX(CityData!$C$19:$C$23,MATCH(A14,CityData!$A$19:$A$23,0)) | I14: =C14+D14+E14+F14+G14+H14 | J14: =I14*B14 | K14: =VENUEDAY*VENUEDAYS | L14: =J14+K14 | M14: =L14*RESRATE | N14: =L14+M14
A17: STRESS: airfare × 1.20 (on top of airfare factor)
A18: City | B18: Headcount | C18: Per-person (stress) | D18: Base (stress) | E18: TOTAL (stress) | F18: Within ceiling?
A19: Boston | B19: 24 | C19: =I5+C5*0.2 | D19: =(I5+C5*0.2)*B19+VENUEDAY*VENUEDAYS | E19: =D19*(1+RESRATE) | F19: =IF(E19<=CEILING,"YES","NO")
A20: Boston | B20: 18 | C20: =I6+C6*0.2 | D20: =(I6+C6*0.2)*B20+VENUEDAY*VENUEDAYS | E20: =D20*(1+RESRATE) | F20: =IF(E20<=CEILING,"YES","NO")
A21: Chicago | B21: 24 | C21: =I7+C7*0.2 | D21: =(I7+C7*0.2)*B21+VENUEDAY*VENUEDAYS | E21: =D21*(1+RESRATE) | F21: =IF(E21<=CEILING,"YES","NO")
A22: Chicago | B22: 18 | C22: =I8+C8*0.2 | D22: =(I8+C8*0.2)*B22+VENUEDAY*VENUEDAYS | E22: =D22*(1+RESRATE) | F22: =IF(E22<=CEILING,"YES","NO")
A23: Denver | B23: 24 | C23: =I9+C9*0.2 | D23: =(I9+C9*0.2)*B23+VENUEDAY*VENUEDAYS | E23: =D23*(1+RESRATE) | F23: =IF(E23<=CEILING,"YES","NO")
A24: Denver | B24: 18 | C24: =I10+C10*0.2 | D24: =(I10+C10*0.2)*B24+VENUEDAY*VENUEDAYS | E24: =D24*(1+RESRATE) | F24: =IF(E24<=CEILING,"YES","NO")
A25: Phoenix | B25: 24 | C25: =I11+C11*0.2 | D25: =(I11+C11*0.2)*B25+VENUEDAY*VENUEDAYS | E25: =D25*(1+RESRATE) | F25: =IF(E25<=CEILING,"YES","NO")
A26: Phoenix | B26: 18 | C26: =I12+C12*0.2 | D26: =(I12+C12*0.2)*B26+VENUEDAY*VENUEDAYS | E26: =D26*(1+RESRATE) | F26: =IF(E26<=CEILING,"YES","NO")
A27: Seattle | B27: 24 | C27: =I13+C13*0.2 | D27: =(I13+C13*0.2)*B27+VENUEDAY*VENUEDAYS | E27: =D27*(1+RESRATE) | F27: =IF(E27<=CEILING,"YES","NO")
A28: Seattle | B28: 18 | C28: =I14+C14*0.2 | D28: =(I14+C14*0.2)*B28+VENUEDAY*VENUEDAYS | E28: =D28*(1+RESRATE) | F28: =IF(E28<=CEILING,"YES","NO")

Sheet Historical
A1: HISTORICAL PER-DIEM CROSS-CHECK — FY2025 / FY2026 / FY2027 (same month/day, same market rates)
A2: Historical reference only (not actual past quotes, not for this reimbursement). Shows how each FY's lodging cap and M&IE would affect lodging compliance and the per-diem comparison, holding headcount, dates and market quotes constant.
A4: City | B4: Market room/night (held) | C4: FY | D4: Lodging cap — Nov night | E4: Lodging cap — Dec 1 night | F4: M&IE | G4: 4-night cap sum | H4: Compliant each night? | I4: Room 4n vs cap sum | J4: Notes
A5: Boston | B5: 108 | C5: FY2025 | D5: 209 | E5: 209 | F5: 92 | G5: 836 | H5: Yes | I5: 432 vs 836
A6: Boston | B6: 108 | C6: FY2026 | D6: 209 | E6: 209 | F6: 92 | G6: 836 | H6: Yes | I6: 432 vs 836
A7: Boston | B7: 108 | C7: FY2027 | D7: 213 | E7: 213 | F7: 92 | G7: 852 | H7: Yes | I7: 432 vs 852
A8: Chicago | B8: 145 | C8: FY2025 | D8: 223 | E8: 142 | F8: 92 | G8: 811 | H8: NO | I8: 580 vs 811 | J8: Dec-1 cap < $145 → NON-compliant this FY (FY27 only compliant)
A9: Chicago | B9: 145 | C9: FY2026 | D9: 223 | E9: 142 | F9: 92 | G9: 811 | H9: NO | I9: 580 vs 811 | J9: Dec-1 cap < $145 → NON-compliant this FY (FY27 only compliant)
A10: Chicago | B10: 145 | C10: FY2027 | D10: 232 | E10: 148 | F10: 92 | G10: 844 | H10: Yes | I10: 580 vs 844
A11: Denver | B11: 109 | C11: FY2025 | D11: 165 | E11: 165 | F11: 92 | G11: 660 | H11: Yes | I11: 436 vs 660
A12: Denver | B12: 109 | C12: FY2026 | D12: 165 | E12: 165 | F12: 92 | G12: 660 | H12: Yes | I12: 436 vs 660
A13: Denver | B13: 109 | C13: FY2027 | D13: 170 | E13: 170 | F13: 92 | G13: 680 | H13: Yes | I13: 436 vs 680
A14: Phoenix | B14: 150 | C14: FY2025 | D14: 160 | E14: 160 | F14: 86 | G14: 640 | H14: Yes | I14: 600 vs 640 | J14: Rate $150 ≤ cap but little headroom
A15: Phoenix | B15: 150 | C15: FY2026 | D15: 160 | E15: 160 | F15: 86 | G15: 640 | H15: Yes | I15: 600 vs 640 | J15: Rate $150 ≤ cap but little headroom
A16: Phoenix | B16: 150 | C16: FY2027 | D16: 165 | E16: 165 | F16: 86 | G16: 660 | H16: Yes | I16: 600 vs 660 | J16: Rate $150 ≤ cap but little headroom
A17: Seattle | B17: 103 | C17: FY2025 | D17: 188 | E17: 188 | F17: 92 | G17: 752 | H17: Yes | I17: 412 vs 752
A18: Seattle | B18: 103 | C18: FY2026 | D18: 188 | E18: 188 | F18: 92 | G18: 752 | H18: Yes | I18: 412 vs 752
A19: Seattle | B19: 103 | C19: FY2027 | D19: 188 | E19: 188 | F19: 92 | G19: 752 | H19: Yes | I19: 412 vs 752
A21: Impact summary:
A22: • Lodging caps rose modestly FY25→FY27 (Boston +4, Chicago +9/+6, Denver +5, Phoenix +5, Seattle flat). M&IE unchanged.
A23: • Recommended Boston $108 room is compliant under ALL three FY caps — selection is robust to rate-year.
A24: • Chicago $145 room would be NON-compliant on the Dec-1 night under FY25/FY26 ($142 cap); compliant only under FY27 ($148).
A25: • Because quotes & dates are held constant, event $ totals do not change by FY; only compliance & per-diem benchmarks move.
A26: • FY2027 is the applicable year (travel Nov 29–Dec 1 2026 = FY27, eff. Oct 1 2026). FY25/26 shown for historical contrast only.

Sheet Thresholds
A1: THRESHOLDS, STRESS & SEGMENTED ACTIONS
A2: Decision metrics for airfare increases (0–20%) and unquoted-cost movements. Recomputes from Options/Daily.
A4: Metric | B4: Value | C4: Basis / condition
A5: Recommended option | B5: Boston — 24 attendees | C5: Lowest total-with-reserve that fits ceiling at max headcount
A6: Recommended grand total (base) | B6: =Options!N5 | C6: Boston 24, airfare factor 1.0
A7: Recommended grand total (+20% airfare) | B7: =Options!E19 | C7: Stress table Boston 24
A8: Budget ceiling | B8: =CEILING | C8: Parameter
A9: Headroom, base scenario (for unquoted costs, excl. reserve) | B9: =CEILING/(1+RESRATE)-Options!L5 | C9: Max added base before ceiling (keeps reserve)
A10: Headroom, +20% airfare (excl. reserve) | B10: =CEILING/(1+RESRATE)-(Options!L5+Options!C5*0.2*24) | C10: After stress
A11: Nearest competitive alternative | B11: Chicago — 24 attendees | C11: 2nd-lowest 24-person total
A12: Boston vs Chicago total gap (base) | B12: =Options!N7-Options!N5 | C12: Chicago24 − Boston24
A13: Airfare factor that lifts Boston-24 to ceiling | B13: =((CEILING/(1+RESRATE))-(Options!L5-Options!C5*24))/(Options!C5*24) | C13: Solve total=ceiling for Boston airfare | D13: =B13
A14: → equivalent airfare increase to reach ceiling | B14: =B13-1 | C14: (factor−1); far beyond +20% band
A17: SEGMENTED ACTION TABLE
A18: Trigger / condition | B18: Action
A19: Airfare 0% to +20% (base band) | B19: KEEP recommendation: Boston 24. It stays lowest-cost and ~$16.9–17.9k under ceiling (ex-reserve). No switch.
A20: Airfare > +20% but total still ≤ ceiling | B20: KEEP Boston 24; monitor. Boston reaches ceiling only near +200% airfare — not a realistic trigger.
A21: Unquoted base costs (venue/ground) rise, Boston 24 total ≤ ceiling | B21: KEEP Boston 24. Absorb within $17.9k base headroom (ex-reserve).
A22: Unquoted base costs push Boston 24 over ceiling | B22: First drop to Boston 18 (total ≈ $26.6k) — large headroom; only then reconsider city.
A23: Boston becomes infeasible/unavailable (venue or block) | B23: SWITCH to Chicago 24 (next lowest, $39.5k base). Note Chicago hotel compliant only under FY27 cap.
A24: Both 24 and 18 exceed ceiling for all cities | B24: Escalate: reduce scope/nights, seek actual-expense authorization, or request higher ceiling. Record in register.

Sheet Itinerary
A1: ITINERARY & HOTEL LINKAGE — recommended Boston option (connectivity check)
A2: All times from ITA Matrix (DCA↔BOS, queried 2026-10-24). Arrival Nov 28 (day before); depart Dec 2 (day after). Hotel check-in Nov 28 / checkout Dec 2 = 4 nights, covering full training Nov 29–Dec 1.
A4: Item | B4: Detail | C4: Date | D4: Connects to
A5: Outbound flight | B5: DCA → BOS, American nonstop (~1h30) | C5: 2026-11-28 | D5: Arrive BOS afternoon → hotel check-in same day
A6: Hotel check-in | B6: DoubleTree by Hilton Boston Bayside | C6: 2026-11-28 | D6: Free airport shuttle (noted on Trip.com)
A7: Training Day 1 | B7: Full day (lunch via registration) | C7: 2026-11-29 | D7: On-site; breakfast at hotel
A8: Training Day 2 | B8: Full day (lunch via registration) | C8: 2026-11-30 | D8: On-site
A9: Training Day 3 | B9: Full day (lunch via registration) | C9: 2026-12-01 | D9: Agency dinner Dec 1 evening
A10: Return flight | B10: BOS → DCA, American nonstop | C10: 2026-12-02 | D10: Checkout Dec 2 → BOS airport → DCA
A11: Agency catered | B11: Dinner Nov 28, Dinner Dec 1, Lunch Dec 2 | C11: various | D11: Budgeted in Daily/Options
A13: Execution conditions (venue/date/capacity not yet verified):
A14: • Meeting venue address & 24-seat capacity for Nov 29–Dec 1 NOT yet confirmed — list as execution condition (see Register).
A15: • Hotel room block of 24 single rooms at quoted rate NOT confirmed; single-occupancy quote used as whole-group estimate only.
A16: • Flight fares are per-person public quotes (single seat); group inventory at same fare not guaranteed.
A17: • Cheapest fares may be Basic Economy (restrictive changes); brief recommends a changeable fare — may raise airfare (stress band covers +20%).

Sheet Sources
A1: SOURCES, QUERY TIMES & APPLICABILITY
A3: # | B3: Item | C3: Source / platform | D3: URL | E3: Queried (UTC) | F3: Applicable dates / notes
A4: 1 | B4: Flights DCA↔ORD (Chicago) $270 AA nonstop | C4: ITA Matrix (Google) | D4: https://matrix.itasoftware.com | E4: 2026-10-24 | F4: RT Nov 28–Dec 2 2026, 1 adult; public fare, basic econ possible
A5: 2 | B5: Flights DCA↔BOS (Boston) $358 AA nonstop | C5: ITA Matrix (Google) | D5: https://matrix.itasoftware.com | E5: 2026-10-24 | F5: RT Nov 28–Dec 2 2026, 1 adult
A6: 3 | B6: Flights DCA↔PHX (Phoenix) $581 AA nonstop | C6: ITA Matrix (Google) | D6: https://matrix.itasoftware.com | E6: 2026-10-24 | F6: RT Nov 28–Dec 2 2026, 1 adult
A7: 4 | B7: Flights DCA↔DEN (Denver) $741 Frontier / $940 United | C7: ITA Matrix (Google) | D7: https://matrix.itasoftware.com | E7: 2026-10-24 | F7: RT; Frontier basic; United more flexible
A8: 5 | B8: Flights DCA↔SEA (Seattle) $977 nonstop / $982 1-stop | C8: ITA Matrix (Google) | D8: https://matrix.itasoftware.com | E8: 2026-10-24 | F8: RT Nov 28–Dec 2 2026, 1 adult
A9: 6 | B9: Boston hotel — DoubleTree Hilton Boston Bayside $108/n, 8.6/10 (449 rev), breakfast | C9: Trip.com (US) | D9: https://us.trip.com/hotels/list?cityId=26848 | E9: 2026-10-24 | F9: 4 nights, 1 room/1 adult; total $501 incl taxes&fees
A10: 7 | B10: Boston alt — Hilton Boston Park Plaza $205/n, 8.8 (170), breakfast | C10: Trip.com (US) | D10: https://us.trip.com/hotels/list?cityId=26848 | E10: 2026-10-24 | F10: Central; ≤$213 FY27 cap
A11: 8 | B11: Chicago hotel — Warwick Allerton $145/n, 8.6 (399) | C11: Trip.com (US) | D11: https://us.trip.com/hotels/list?cityId=549 | E11: 2026-10-24 | F11: ≤ $148 Dec-1 FY27 cap; total $668 incl tax
A12: 9 | B12: Denver hotel — Home2 Suites Hilton Downtown $109/n, 9.0 (94), breakfast | C12: Trip.com (US) | D12: https://us.trip.com/hotels/list?cityId=20099 | E12: 2026-10-24 | F12: ≤$170 cap
A13: 10 | B13: Phoenix hotel — Hampton Inn & Suites $150/n, 9.4 (116), breakfast | C13: Trip.com (US) | D13: https://us.trip.com/hotels/list?cityId=25938 | E13: 2026-10-24 | F13: ≤$165 cap (thin margin)
A14: 11 | B14: Seattle hotel — Belltown BF-incl $103/n, 8.6 (114), breakfast | C14: Trip.com (US) | D14: https://us.trip.com/hotels/list?cityId=511 | E14: 2026-10-24 | F14: ≤$188 cap
A15: 12 | B15: FY2027 per-diem (lodging & M&IE) | C15: GSA / input file | D15: FY2027_PerDiemRates_Validated090126.xlsx | E15: file (read) | F15: Eff. Oct 1 2026 — APPLICABLE year
... A21: 18 | B21: FX note | C21: N/A — all prices captured in USD | D21: ITA Matrix & us.trip.com default USD | E21: 2026-10-24 | F21: No currency conversion applied
A23: Pricing/tax口径: ITA Matrix fares are total incl. taxes/carrier fees per ticket. Trip.com hotel 'Total price' is incl. taxes & fees; nightly figure excl. taxes & fees. Internal 12% lodging-tax line is a planning estimate, NOT the local statutory rate.
