Workbook

Sheet ControlPanel
A1: Conference Budget Control Panel
A2: Yellow cells are the only scenario inputs. Word and CSV are static default-parameter delivery snapshots; after any input change, re-export them. Excel Daily, Options, eligibility, selection, and stress actions recalculate.
A4: Named input | B4: Current value | C4: Default | D4: Allowed values / business meaning | E4: Status
A5: WF_BUDGET | B5: 53000 | C5: 53000 | D5: $0–$100,000; approved total ceiling including reserve | E5: =IF(B5=C5,"DEFAULT","CHANGED") -> DEFAULT
A6: WF_AIR_MULTIPLIER | B6: 1 | C6: 1 | D6: 0.5–2.0; multiplies each city round-trip fare | E6: =IF(B6=C6,"DEFAULT","CHANGED") -> DEFAULT
A7: WF_RESERVE_RATE | B7: 0.05 | C7: 0.05 | D7: 0%–20%; applied separately to current and stress bases | E7: =IF(B7=C7,"DEFAULT","CHANGED") -> DEFAULT
A8: WF_GOV_BREAKFAST_0929 | B8: 0 | C8: 0 | D8: 0 or 1; 1 means Government-furnished breakfast on 09/29 | E8: =IF(B8=C8,"DEFAULT","CHANGED") -> DEFAULT
A9: WF_ARRIVAL | B9: 20250928 | C9: 20250928 | D9: Integer 20250927, 20250928, or 20250929; return remains 20251002 | E9: =IF(B9=C9,"DEFAULT","CHANGED") -> DEFAULT
A12: Live outputs
A13: Snapshot current | B13: =AND(B5=C5,B6=C6,B7=C7,B8=C8,B9=C9) -> TRUE
A14: Selected city | B14: =IF(COUNTIF(Options!O5:O10,"YES")=0,"NONE",INDEX(Options!A5:A10,MATCH(MIN(Options!V5:V10),Options!V5:V10,0))) -> Phoenix
A15: Selected attendance | B15: =IF(COUNTIF(Options!O5:O10,"YES")=0,0,INDEX(Options!B5:B10,MATCH(MIN(Options!V5:V10),Options!V5:V10,0))) -> 24
A16: Selected approval note | B16: =IF(B15=0,"No scenario is within the current ceiling.",IF(INDEX(Options!T5:T10,MATCH(MIN(Options!V5:V10),Options!V5:V10,0))="YES","Current selection also passes the 20% airfare stress.","Current selection passes baseline only; execute the stress action in Options if fares rise.")) -> Current selection passes baseline only; execute the stress action in Options if fares rise.
A18: Model boundaries
A19: • | B19: Only the five yellow inputs vary. Official rates, return date, training/meal calendar, attendance choices, quotes, and city choices are fixed exercise facts.
A20: • | B20: Actual lodging reimbursement uses quoted room cost capped by the applicable lodging maximum; the cap is not treated as spending. Tax is 12% of reimbursable lodging only.
A21: • | B21: First/last-day M&IE is reduced to 75% first, then full allocated Government meal amounts are deducted, with a $5 incidental-expense floor.
A22: • | B22: Hotel complimentary breakfast is not deducted; Government meals and registration-included lunches are deducted; coffee/fruit breaks are not deducted.
A23: • | B23: Quoted facilities are not approved merely because their rates fit the model. Safety, acquisition, travel authorization, and funds checks remain approval gates.

Sheet Daily
A1: Daily Per-Person Detail
A2: Rows update for the selected arrival date and Government breakfast toggle. 09/27 is reserved for scenario use; inactive dates show zero reimbursable amounts.
A4: City | B4: Date | C4: Fiscal year | D4: GSA Master row | E4: Travel day active? | F4: Lodging night? | G4: Lodging cap / night | H4: Untaxed quote / night | I4: Reimbursable lodging | J4: Estimated lodging tax (12%) | K4: Full M&IE | L4: Day factor | M4: M&IE before meal deductions | N4: Gov breakfast deduction | O4: Gov lunch deduction | P4: Gov dinner deduction | Q4: Incidental floor | R4: Final M&IE | S4: Meal treatment / notes
A5: Chicago | B5: 20250927 | C5: FY2025 | D5: 258 | E5: =IF(AND(B5>=WF_ARRIVAL,B5<=20251002),"YES","NO") -> NO | F5: =IF(AND(E5="YES",B5<=20251001),"YES","NO") -> NO | G5: 223 | H5: 218 | I5: =IF(F5="YES",MIN(G5,H5),0) -> 0 | J5: =I5*12% -> 0 | K5: 92 | L5: =IF(E5="NO",0,IF(OR(B5=WF_ARRIVAL,B5=20251002),75%,100%)) -> 0 | M5: =K5*L5 -> 0 | N5: =IF(AND(E5="YES",B5=20250929,WF_GOV_BREAKFAST_0929=1),23,0) -> 0 | O5: =IF(AND(E5="YES",OR(B5=20250929,B5=20250930,B5=20251001,B5=20251002)),26,0) -> 0 | P5: =IF(AND(E5="YES",OR(B5=20250928,B5=20251001)),38,0) -> 0 | Q5: 5 | R5: =IF(E5="NO",0,MAX(Q5,M5-N5-O5-P5)) -> 0 | S5: No scheduled Government meal; hotel breakfast (if any) is complimentary, not deducted.
A6: Chicago | B6: 20250928 | C6: FY2025 | D6: 258 | E6: =IF(AND(B6>=WF_ARRIVAL,B6<=20251002),"YES","NO") -> YES | F6: =IF(AND(E6="YES",B6<=20251001),"YES","NO") -> YES | G6: 223 | H6: 218 | I6: =IF(F6="YES",MIN(G6,H6),0) -> 218 | J6: =I6*12% -> 26.16 | K6: 92 | L6: =IF(E6="NO",0,IF(OR(B6=WF_ARRIVAL,B6=20251002),75%,100%)) -> 0.75 | M6: =K6*L6 -> 69 | N6: =IF(AND(E6="YES",B6=20250929,WF_GOV_BREAKFAST_0929=1),23,0) -> 0 | O6: =IF(AND(E6="YES",OR(B6=20250929,B6=20250930,B6=20251001,B6=20251002)),26,0) -> 0 | P6: =IF(AND(E6="YES",OR(B6=20250928,B6=20251001)),38,0) -> 38 | Q6: 5 | R6: =IF(E6="NO",0,MAX(Q6,M6-N6-O6-P6)) -> 31 | S6: Welcome dinner deducted; hotel breakfast is complimentary, not deducted.
A7: Chicago | B7: 20250929 | C7: FY2025 | D7: 258 | E7: =IF(AND(B7>=WF_ARRIVAL,B7<=20251002),"YES","NO") -> YES | F7: =IF(AND(E7="YES",B7<=20251001),"YES","NO") -> YES | G7: 223 | H7: 218 | I7: =IF(F7="YES",MIN(G7,H7),0) -> 218 | J7: =I7*12% -> 26.16 | K7: 92 | L7: =IF(E7="NO",0,IF(OR(B7=WF_ARRIVAL,B7=20251002),75%,100%)) -> 1 | M7: =K7*L7 -> 92 | N7: =IF(AND(E7="YES",B7=20250929,WF_GOV_BREAKFAST_0929=1),23,0) -> 0 | O7: =IF(AND(E7="YES",OR(B7=20250929,B7=20250930,B7=20251001,B7=20251002)),26,0) -> 26 | P7: =IF(AND(E7="YES",OR(B7=20250928,B7=20251001)),38,0) -> 0 | Q7: 5 | R7: =IF(E7="NO",0,MAX(Q7,M7-N7-O7-P7)) -> 66 | S7: Registration lunch deducted; Government breakfast deducted only when toggle = 1; hotel breakfast alone is not deducted.
A8: Chicago | B8: 20250930 | C8: FY2025 | D8: 258 | E8: =IF(AND(B8>=WF_ARRIVAL,B8<=20251002),"YES","NO") -> YES | F8: =IF(AND(E8="YES",B8<=20251001),"YES","NO") -> YES | G8: 223 | H8: 218 | I8: =IF(F8="YES",MIN(G8,H8),0) -> 218 | J8: =I8*12% -> 26.16 | K8: 92 | L8: =IF(E8="NO",0,IF(OR(B8=WF_ARRIVAL,B8=20251002),75%,100%)) -> 1 | M8: =K8*L8 -> 92 | N8: =IF(AND(E8="YES",B8=20250929,WF_GOV_BREAKFAST_0929=1),23,0) -> 0 | O8: =IF(AND(E8="YES",OR(B8=20250929,B8=20250930,B8=20251001,B8=20251002)),26,0) -> 26 | P8: =IF(AND(E8="YES",OR(B8=20250928,B8=20251001)),38,0) -> 0 | Q8: 5 | R8: =IF(E8="NO",0,MAX(Q8,M8-N8-O8-P8)) -> 66 | S8: Registration lunch deducted; coffee/fruit breaks are light refreshments, not deducted.
A9: Chicago | B9: 20251001 | C9: FY2026 | D9: 254 | E9: =IF(AND(B9>=WF_ARRIVAL,B9<=20251002),"YES","NO") -> YES | F9: =IF(AND(E9="YES",B9<=20251001),"YES","NO") -> YES | G9: 223 | H9: 218 | I9: =IF(F9="YES",MIN(G9,H9),0) -> 218 | J9: =I9*12% -> 26.16 | K9: 92 | L9: =IF(E9="NO",0,IF(OR(B9=WF_ARRIVAL,B9=20251002),75%,100%)) -> 1 | M9: =K9*L9 -> 92 | N9: =IF(AND(E9="YES",B9=20250929,WF_GOV_BREAKFAST_0929=1),23,0) -> 0 | O9: =IF(AND(E9="YES",OR(B9=20250929,B9=20250930,B9=20251001,B9=20251002)),26,0) -> 26 | P9: =IF(AND(E9="YES",OR(B9=20250928,B9=20251001)),38,0) -> 38 | Q9: 5 | R9: =IF(E9="NO",0,MAX(Q9,M9-N9-O9-P9)) -> 28 | S9: Registration lunch and Government dinner deducted; light refreshments not deducted.
A10: Chicago | B10: 20251002 | C10: FY2026 | D10: 254 | E10: =IF(AND(B10>=WF_ARRIVAL,B10<=20251002),"YES","NO") -> YES | F10: =IF(AND(E10="YES",B10<=20251001),"YES","NO") -> NO | G10: 223 | H10: 218 | I10: =IF(F10="YES",MIN(G10,H10),0) -> 0 | J10: =I10*12% -> 0 | K10: 92 | L10: =IF(E10="NO",0,IF(OR(B10=WF_ARRIVAL,B10=20251002),75%,100%)) -> 0.75 | M10: =K10*L10 -> 69 | N10: =IF(AND(E10="YES",B10=20250929,WF_GOV_BREAKFAST_0929=1),23,0) -> 0 | O10: =IF(AND(E10="YES",OR(B10=20250929,B10=20250930,B10=20251001,B10=20251002)),26,0) -> 26 | P10: =IF(AND(E10="YES",OR(B10=20250928,B10=20251001)),38,0) -> 0 | Q10: 5 | R10: =IF(E10="NO",0,MAX(Q10,M10-N10-O10-P10)) -> 43 | S10: Departure lunch deducted; first/last-day 75% applies before full lunch deduction.
A11: Denver | B11: 20250927 | C11: FY2025 | D11: 109 | E11: =IF(AND(B11>=WF_ARRIVAL,B11<=20251002),"YES","NO") -> NO | F11: =IF(AND(E11="YES",B11<=20251001),"YES","NO") -> NO | G11: 215 | H11: 209 | I11: =IF(F11="YES",MIN(G11,H11),0) -> 0 | J11: =I11*12% -> 0 | K11: 92 | L11: =IF(E11="NO",0,IF(OR(B11=WF_ARRIVAL,B11=20251002),75%,100%)) -> 0 | M11: =K11*L11 -> 0 | N11: =IF(AND(E11="YES",B11=20250929,WF_GOV_BREAKFAST_0929=1),23,0) -> 0 | O11: =IF(AND(E11="YES",OR(B11=20250929,B11=20250930,B11=20251001,B11=20251002)),26,0) -> 0 | P11: =IF(AND(E11="YES",OR(B11=20250928,B11=20251001)),38,0) -> 0 | Q11: 5 | R11: =IF(E11="NO",0,MAX(Q11,M11-N11-O11-P11)) -> 0 | S11: No scheduled Government meal; hotel breakfast (if any) is complimentary, not deducted.
A12: Denver | B12: 20250928 | C12: FY2025 | D12: 109 | E12: =IF(AND(B12>=WF_ARRIVAL,B12<=20251002),"YES","NO") -> YES | F12: =IF(AND(E12="YES",B12<=20251001),"YES","NO") -> YES | G12: 215 | H12: 209 | I12: =IF(F12="YES",MIN(G12,H12),0) -> 209 | J12: =I12*12% -> 25.08 | K12: 92 | L12: =IF(E12="NO",0,IF(OR(B12=WF_ARRIVAL,B12=20251002),75%,100%)) -> 0.75 | M12: =K12*L12 -> 69 | N12: =IF(AND(E12="YES",B12=20250929,WF_GOV_BREAKFAST_0929=1),23,0) -> 0 | O12: =IF(AND(E12="YES",OR(B12=20250929,B12=20250930,B12=20251001,B12=20251002)),26,0) -> 0 | P12: =IF(AND(E12="YES",OR(B12=20250928,B12=20251001)),38,0) -> 38 | Q12: 5 | R12: =IF(E12="NO",0,MAX(Q12,M12-N12-O12-P12)) -> 31 | S12: Welcome dinner deducted; hotel breakfast is complimentary, not deducted.
A13: Denver | B13: 20250929 | C13: FY2025 | D13: 109 | E13: =IF(AND(B13>=WF_ARRIVAL,B13<=20251002),"YES","NO") -> YES | F13: =IF(AND(E13="YES",B13<=20251001),"YES","NO") -> YES | G13: 215 | H13: 209 | I13: =IF(F13="YES",MIN(G13,H13),0) -> 209 | J13: =I13*12% -> 25.08 | K13: 92 | L13: =IF(E13="NO",0,IF(OR(B13=WF_ARRIVAL,B13=20251002),75%,100%)) -> 1 | M13: =K13*L13 -> 92 | N13: =IF(AND(E13="YES",B13=20250929,WF_GOV_BREAKFAST_0929=1),23,0) -> 0 | O13: =IF(AND(E13="YES",OR(B13=20250929,B13=20250930,B13=20251001,B13=20251002)),26,0) -> 26 | P13: =IF(AND(E13="YES",OR(B13=20250928,B13=20251001)),38,0) -> 0 | Q13: 5 | R13: =IF(E13="NO",0,MAX(Q13,M13-N13-O13-P13)) -> 66 | S13: Registration lunch deducted; Government breakfast deducted only when toggle = 1; hotel breakfast alone is not deducted.
A14: Denver | B14: 20250930 | C14: FY2025 | D14: 109 | E14: =IF(AND(B14>=WF_ARRIVAL,B14<=20251002),"YES","NO") -> YES | F14: =IF(AND(E14="YES",B14<=20251001),"YES","NO") -> YES | G14: 215 | H14: 209 | I14: =IF(F14="YES",MIN(G14,H14),0) -> 209 | J14: =I14*12% -> 25.08 | K14: 92 | L14: =IF(E14="NO",0,IF(OR(B14=WF_ARRIVAL,B14=20251002),75%,100%)) -> 1 | M14: =K14*L14 -> 92 | N14: =IF(AND(E14="YES",B14=20250929,WF_GOV_BREAKFAST_0929=1),23,0) -> 0 | O14: =IF(AND(E14="YES",OR(B14=20250929,B14=20250930,B14=20251001,B14=20251002)),26,0) -> 26 | P14: =IF(AND(E14="YES",OR(B14=20250928,B14=20251001)),38,0) -> 0 | Q14: 5 | R14: =IF(E14="NO",0,MAX(Q14,M14-N14-O14-P14)) -> 66 | S14: Registration lunch deducted; coffee/fruit breaks are light refreshments, not deducted.
A15: Denver | B15: 20251001 | C15: FY2026 | D15: 107 | E15: =IF(AND(B15>=WF_ARRIVAL,B15<=20251002),"YES","NO") -> YES | F15: =IF(AND(E15="YES",B15<=20251001),"YES","NO") -> YES | G15: 215 | H15: 209 | I15: =IF(F15="YES",MIN(G15,H15),0) -> 209 | J15: =I15*12% -> 25.08 | K15: 92 | L15: =IF(E15="NO",0,IF(OR(B15=WF_ARRIVAL,B15=20251002),75%,100%)) -> 1 | M15: =K15*L15 -> 92 | N15: =IF(AND(E15="YES",B15=20250929,WF_GOV_BREAKFAST_0929=1),23,0) -> 0 | O15: =IF(AND(E15="YES",OR(B15=20250929,B15=20250930,B15=20251001,B15=20251002)),26,0) -> 26 | P15: =IF(AND(E15="YES",OR(B15=20250928,B15=20251001)),38,0) -> 38 | Q15: 5 | R15: =IF(E15="NO",0,MAX(Q15,M15-N15-O15-P15)) -> 28 | S15: Registration lunch and Government dinner deducted; light refreshments not deducted.
A16: Denver | B16: 20251002 | C16: FY2026 | D16: 107 | E16: =IF(AND(B16>=WF_ARRIVAL,B16<=20251002),"YES","NO") -> YES | F16: =IF(AND(E16="YES",B16<=20251001),"YES","NO") -> NO | G16: 215 | H16: 209 | I16: =IF(F16="YES",MIN(G16,H16),0) -> 0 | J16: =I16*12% -> 0 | K16: 92 | L16: =IF(E16="NO",0,IF(OR(B16=WF_ARRIVAL,B16=20251002),75%,100%)) -> 0.75 | M16: =K16*L16 -> 69 | N16: =IF(AND(E16="YES",B16=20250929,WF_GOV_BREAKFAST_0929=1),23,0) -> 0 | O16: =IF(AND(E16="YES",OR(B16=20250929,B16=20250930,B16=20251001,B16=20251002)),26,0) -> 26 | P16: =IF(AND(E16="YES",OR(B16=20250928,B16=20251001)),38,0) -> 0 | Q16: 5 | R16: =IF(E16="NO",0,MAX(Q16,M16-N16-O16-P16)) -> 43 | S16: Departure lunch deducted; first/last-day 75% applies before full lunch deduction.
A17: Phoenix | B17: 20250927 | C17: FY2025 | D17: 22 | E17: =IF(AND(B17>=WF_ARRIVAL,B17<=20251002),"YES","NO") -> NO | F17: =IF(AND(E17="YES",B17<=20251001),"YES","NO") -> NO | G17: 160 | H17: 155 | I17: =IF(F17="YES",MIN(G17,H17),0) -> 0 | J17: =I17*12% -> 0 | K17: 86 | L17: =IF(E17="NO",0,IF(OR(B17=WF_ARRIVAL,B17=20251002),75%,100%)) -> 0 | M17: =K17*L17 -> 0 | N17: =IF(AND(E17="YES",B17=20250929,WF_GOV_BREAKFAST_0929=1),22,0) -> 0 | O17: =IF(AND(E17="YES",OR(B17=20250929,B17=20250930,B17=20251001,B17=20251002)),23,0) -> 0 | P17: =IF(AND(E17="YES",OR(B17=20250928,B17=20251001)),36,0) -> 0 | Q17: 5 | R17: =IF(E17="NO",0,MAX(Q17,M17-N17-O17-P17)) -> 0 | S17: No scheduled Government meal; hotel breakfast (if any) is complimentary, not deducted.
A18: Phoenix | B18: 20250928 | C18: FY2025 | D18: 22 | E18: =IF(AND(B18>=WF_ARRIVAL,B18<=20251002),"YES","NO") -> YES | F18: =IF(AND(E18="YES",B18<=20251001),"YES","NO") -> YES | G18: 160 | H18: 155 | I18: =IF(F18="YES",MIN(G18,H18),0) -> 155 | J18: =I18*12% -> 18.6 | K18: 86 | L18: =IF(E18="NO",0,IF(OR(B18=WF_ARRIVAL,B18=20251002),75%,100%)) -> 0.75 | M18: =K18*L18 -> 64.5 | N18: =IF(AND(E18="YES",B18=20250929,WF_GOV_BREAKFAST_0929=1),22,0) -> 0 | O18: =IF(AND(E18="YES",OR(B18=20250929,B18=20250930,B18=20251001,B18=20251002)),23,0) -> 0 | P18: =IF(AND(E18="YES",OR(B18=20250928,B18=20251001)),36,0) -> 36 | Q18: 5 | R18: =IF(E18="NO",0,MAX(Q18,M18-N18-O18-P18)) -> 28.5 | S18: Welcome dinner deducted; hotel breakfast is complimentary, not deducted.
A19: Phoenix | B19: 20250929 | C19: FY2025 | D19: 22 | E19: =IF(AND(B19>=WF_ARRIVAL,B19<=20251002),"YES","NO") -> YES | F19: =IF(AND(E19="YES",B19<=20251001),"YES","NO") -> YES | G19: 160 | H19: 155 | I19: =IF(F19="YES",MIN(G19,H19),0) -> 155 | J19: =I19*12% -> 18.6 | K19: 86 | L19: =IF(E19="NO",0,IF(OR(B19=WF_ARRIVAL,B19=20251002),75%,100%)) -> 1 | M19: =K19*L19 -> 86 | N19: =IF(AND(E19="YES",B19=20250929,WF_GOV_BREAKFAST_0929=1),22,0) -> 0 | O19: =IF(AND(E19="YES",OR(B19=20250929,B19=20250930,B19=20251001,B19=20251002)),23,0) -> 23 | P19: =IF(AND(E19="YES",OR(B19=20250928,B19=20251001)),36,0) -> 0 | Q19: 5 | R19: =IF(E19="NO",0,MAX(Q19,M19-N19-O19-P19)) -> 63 | S19: Registration lunch deducted; Government breakfast deducted only when toggle = 1; hotel breakfast alone is not deducted.
A20: Phoenix | B20: 20250930 | C20: FY2025 | D20: 22 | E20: =IF(AND(B20>=WF_ARRIVAL,B20<=20251002),"YES","NO") -> YES | F20: =IF(AND(E20="YES",B20<=20251001),"YES","NO") -> YES | G20: 160 | H20: 155 | I20: =IF(F20="YES",MIN(G20,H20),0) -> 155 | J20: =I20*12% -> 18.6 | K20: 86 | L20: =IF(E20="NO",0,IF(OR(B20=WF_ARRIVAL,B20=20251002),75%,100%)) -> 1 | M20: =K20*L20 -> 86 | N20: =IF(AND(E20="YES",B20=20250929,WF_GOV_BREAKFAST_0929=1),22,0) -> 0 | O20: =IF(AND(E20="YES",OR(B20=20250929,B20=20250930,B20=20251001,B20=20251002)),23,0) -> 23 | P20: =IF(AND(E20="YES",OR(B20=20250928,B20=20251001)),36,0) -> 0 | Q20: 5 | R20: =IF(E20="NO",0,MAX(Q20,M20-N20-O20-P20)) -> 63 | S20: Registration lunch deducted; coffee/fruit breaks are light refreshments, not deducted.
A21: Phoenix | B21: 20251001 | C21: FY2026 | D21: 18 | E21: =IF(AND(B21>=WF_ARRIVAL,B21<=20251002),"YES","NO") -> YES | F21: =IF(AND(E21="YES",B21<=20251001),"YES","NO") -> YES | G21: 160 | H21: 155 | I21: =IF(F21="YES",MIN(G21,H21),0) -> 155 | J21: =I21*12% -> 18.6 | K21: 86 | L21: =IF(E21="NO",0,IF(OR(B21=WF_ARRIVAL,B21=20251002),75%,100%)) -> 1 | M21: =K21*L21 -> 86 | N21: =IF(AND(E21="YES",B21=20250929,WF_GOV_BREAKFAST_0929=1),22,0) -> 0 | O21: =IF(AND(E21="YES",OR(B21=20250929,B21=20250930,B21=20251001,B21=20251002)),23,0) -> 23 | P21: =IF(AND(E21="YES",OR(B21=20250928,B21=20251001)),36,0) -> 36 | Q21: 5 | R21: =IF(E21="NO",0,MAX(Q21,M21-N21-O21-P21)) -> 27 | S21: Registration lunch and Government dinner deducted; light refreshments not deducted.
A22: Phoenix | B22: 20251002 | C22: FY2026 | D22: 18 | E22: =IF(AND(B22>=WF_ARRIVAL,B22<=20251002),"YES","NO") -> YES | F22: =IF(AND(E22="YES",B22<=20251001),"YES","NO") -> NO | G22: 160 | H22: 155 | I22: =IF(F22="YES",MIN(G22,H22),0) -> 0 | J22: =I22*12% -> 0 | K22: 86 | L22: =IF(E22="NO",0,IF(OR(B22=WF_ARRIVAL,B22=20251002),75%,100%)) -> 0.75 | M22: =K22*L22 -> 64.5 | N22: =IF(AND(E22="YES",B22=20250929,WF_GOV_BREAKFAST_0929=1),22,0) -> 0 | O22: =IF(AND(E22="YES",OR(B22=20250929,B22=20250930,B22=20251001,B22=20251002)),23,0) -> 23 | P22: =IF(AND(E22="YES",OR(B22=20250928,B22=20251001)),36,0) -> 0 | Q22: 5 | R22: =IF(E22="NO",0,MAX(Q22,M22-N22-O22-P22)) -> 41.5 | S22: Departure lunch deducted; first/last-day 75% applies before full lunch deduction.
A23: Chicago active-trip total | I23: =SUMIF(A$5:A$22,"Chicago",I$5:I$22) -> 872 | J23: =SUMIF(A$5:A$22,"Chicago",J$5:J$22) -> 104.64 | R23: =SUMIF(A$5:A$22,"Chicago",R$5:R$22) -> 234
A24: Denver active-trip total | I24: =SUMIF(A$5:A$23,"Denver",I$5:I$23) -> 836 | J24: =SUMIF(A$5:A$23,"Denver",J$5:J$23) -> 100.32 | R24: =SUMIF(A$5:A$23,"Denver",R$5:R$23) -> 234
A25: Phoenix active-trip total | I25: =SUMIF(A$5:A$24,"Phoenix",I$5:I$24) -> 620 | J25: =SUMIF(A$5:A$24,"Phoenix",J$5:J$24) -> 74.4 | R25: =SUMIF(A$5:A$24,"Phoenix",R$5:R$24) -> 223

Sheet Options
A1: Option Comparison
A2: Objective: maximize eligible attendance, then minimize current total; exact ties follow English city name. Stress applies another 20% to the current airfare and independently applies reserve.
A4: City | B4: Travelers | C4: Airfare | D4: Local transport | E4: Registration | F4: Lodging | G4: Lodging tax | H4: M&IE | I4: Venue | J4: Current base | K4: Reserve | L4: Current total | M4: Budget margin | N4: Lodging compliance | O4: Current eligible? | P4: Stress airfare (+20%) | Q4: Stress base | R4: Stress reserve | S4: Stress total | T4: Stress eligible? | U4: Stress execution measure | V4: Selection score
A5: Chicago | B5: 18 | C5: =410*WF_AIR_MULTIPLIER*B5 -> 7380 | D5: 1440 | E5: 3240 | F5: =SUM(Daily!I5:I10)*B5 -> 15696 | G5: =SUM(Daily!J5:J10)*B5 -> 1883.52 | H5: =SUM(Daily!R5:R10)*B5 -> 4212 | I5: 9500 | J5: =SUM(C5:I5) -> 43351.52 | K5: =J5*WF_RESERVE_RATE -> 2167.576 | L5: =J5+K5 -> 45519.096 | M5: =WF_BUDGET-L5 -> 7480.904 | N5: =IF(MAX(Daily!H5:H10)<=MIN(Daily!G5:G10),"WITHIN CAP","OVER CAP") -> WITHIN CAP | O5: =IF(AND(L5<=WF_BUDGET,N5="WITHIN CAP"),"YES","NO") -> YES | P5: =C5*1.2 -> 8856 | Q5: =J5-C5+P5 -> 44827.52 | R5: =Q5*WF_RESERVE_RATE -> 2241.376 | S5: =Q5+R5 -> 47068.896 | T5: =IF(S5<=WF_BUDGET,"YES","NO") -> YES | U5: =IF(T5="YES","Proceed within current ceiling.","Do not obligate: reprice airfare, move to an eligible option, reduce attendance where authorized, or obtain a higher approved ceiling.") -> Proceed within current ceiling. | V5: =IF(O5="YES",(24-B5)*1000000000+L5+ROW()/1000000,1000000000000000) -> 6.0000455e+09
A6: Chicago | B6: 24 | C6: =410*WF_AIR_MULTIPLIER*B6 -> 9840 | D6: 1920 | E6: 4320 | F6: =SUM(Daily!I5:I10)*B6 -> 20928 | G6: =SUM(Daily!J5:J10)*B6 -> 2511.36 | H6: =SUM(Daily!R5:R10)*B6 -> 5616 | I6: 9500 | J6: =SUM(C6:I6) -> 54635.36 | K6: =J6*WF_RESERVE_RATE -> 2731.768 | L6: =J6+K6 -> 57367.128 | M6: =WF_BUDGET-L6 -> -4367.128 | N6: =IF(MAX(Daily!H5:H10)<=MIN(Daily!G5:G10),"WITHIN CAP","OVER CAP") -> WITHIN CAP | O6: =IF(AND(L6<=WF_BUDGET,N6="WITHIN CAP"),"YES","NO") -> NO | P6: =C6*1.2 -> 11808 | Q6: =J6-C6+P6 -> 56603.36 | R6: =Q6*WF_RESERVE_RATE -> 2830.168 | S6: =Q6+R6 -> 59433.528 | T6: =IF(S6<=WF_BUDGET,"YES","NO") -> NO | U6: =IF(T6="YES","Proceed within current ceiling.","Do not obligate: reprice airfare, move to an eligible option, reduce attendance where authorized, or obtain a higher approved ceiling.") -> Do not obligate: reprice airfare, move to an eligible option, reduce attendance where authorized, or obtain a higher approved ceiling. | V6: =IF(O6="YES",(24-B6)*1000000000+L6+ROW()/1000000,1000000000000000) -> 1e+15
A7: Denver | B7: 18 | C7: =340*WF_AIR_MULTIPLIER*B7 -> 6120 | D7: 1260 | E7: 3240 | F7: =SUM(Daily!I11:I16)*B7 -> 15048 | G7: =SUM(Daily!J11:J16)*B7 -> 1805.76 | H7: =SUM(Daily!R11:R16)*B7 -> 4212 | I7: 10500 | J7: =SUM(C7:I7) -> 42185.76 | K7: =J7*WF_RESERVE_RATE -> 2109.288 | L7: =J7+K7 -> 44295.048 | M7: =WF_BUDGET-L7 -> 8704.952 | N7: =IF(MAX(Daily!H11:H16)<=MIN(Daily!G11:G16),"WITHIN CAP","OVER CAP") -> WITHIN CAP | O7: =IF(AND(L7<=WF_BUDGET,N7="WITHIN CAP"),"YES","NO") -> YES | P7: =C7*1.2 -> 7344 | Q7: =J7-C7+P7 -> 43409.76 | R7: =Q7*WF_RESERVE_RATE -> 2170.488 | S7: =Q7+R7 -> 45580.248 | T7: =IF(S7<=WF_BUDGET,"YES","NO") -> YES | U7: =IF(T7="YES","Proceed within current ceiling.","Do not obligate: reprice airfare, move to an eligible option, reduce attendance where authorized, or obtain a higher approved ceiling.") -> Proceed within current ceiling. | V7: =IF(O7="YES",(24-B7)*1000000000+L7+ROW()/1000000,1000000000000000) -> 6.0000443e+09
A8: Denver | B8: 24 | C8: =340*WF_AIR_MULTIPLIER*B8 -> 8160 | D8: 1680 | E8: 4320 | F8: =SUM(Daily!I11:I16)*B8 -> 20064 | G8: =SUM(Daily!J11:J16)*B8 -> 2407.68 | H8: =SUM(Daily!R11:R16)*B8 -> 5616 | I8: 10500 | J8: =SUM(C8:I8) -> 52747.68 | K8: =J8*WF_RESERVE_RATE -> 2637.384 | L8: =J8+K8 -> 55385.064 | M8: =WF_BUDGET-L8 -> -2385.064 | N8: =IF(MAX(Daily!H11:H16)<=MIN(Daily!G11:G16),"WITHIN CAP","OVER CAP") -> WITHIN CAP | O8: =IF(AND(L8<=WF_BUDGET,N8="WITHIN CAP"),"YES","NO") -> NO | P8: =C8*1.2 -> 9792 | Q8: =J8-C8+P8 -> 54379.68 | R8: =Q8*WF_RESERVE_RATE -> 2718.984 | S8: =Q8+R8 -> 57098.664 | T8: =IF(S8<=WF_BUDGET,"YES","NO") -> NO | U8: =IF(T8="YES","Proceed within current ceiling.","Do not obligate: reprice airfare, move to an eligible option, reduce attendance where authorized, or obtain a higher approved ceiling.") -> Do not obligate: reprice airfare, move to an eligible option, reduce attendance where authorized, or obtain a higher approved ceiling. | V8: =IF(O8="YES",(24-B8)*1000000000+L8+ROW()/1000000,1000000000000000) -> 1e+15
A9: Phoenix | B9: 18 | C9: =510*WF_AIR_MULTIPLIER*B9 -> 9180 | D9: 1620 | E9: 3240 | F9: =SUM(Daily!I17:I22)*B9 -> 11160 | G9: =SUM(Daily!J17:J22)*B9 -> 1339.2 | H9: =SUM(Daily!R17:R22)*B9 -> 4014 | I9: 8000 | J9: =SUM(C9:I9) -> 38553.2 | K9: =J9*WF_RESERVE_RATE -> 1927.66 | L9: =J9+K9 -> 40480.86 | M9: =WF_BUDGET-L9 -> 12519.14 | N9: =IF(MAX(Daily!H17:H22)<=MIN(Daily!G17:G22),"WITHIN CAP","OVER CAP") -> WITHIN CAP | O9: =IF(AND(L9<=WF_BUDGET,N9="WITHIN CAP"),"YES","NO") -> YES | P9: =C9*1.2 -> 11016 | Q9: =J9-C9+P9 -> 40389.2 | R9: =Q9*WF_RESERVE_RATE -> 2019.46 | S9: =Q9+R9 -> 42408.66 | T9: =IF(S9<=WF_BUDGET,"YES","NO") -> YES | U9: =IF(T9="YES","Proceed within current ceiling.","Do not obligate: reprice airfare, move to an eligible option, reduce attendance where authorized, or obtain a higher approved ceiling.") -> Proceed within current ceiling. | V9: =IF(O9="YES",(24-B9)*1000000000+L9+ROW()/1000000,1000000000000000) -> 6.0000405e+09
A10: Phoenix | B10: 24 | C10: =510*WF_AIR_MULTIPLIER*B10 -> 12240 | D10: 2160 | E10: 4320 | F10: =SUM(Daily!I17:I22)*B10 -> 14880 | G10: =SUM(Daily!J17:J22)*B10 -> 1785.6 | H10: =SUM(Daily!R17:R22)*B10 -> 5352 | I10: 8000 | J10: =SUM(C10:I10) -> 48737.6 | K10: =J10*WF_RESERVE_RATE -> 2436.88 | L10: =J10+K10 -> 51174.48 | M10: =WF_BUDGET-L10 -> 1825.52 | N10: =IF(MAX(Daily!H17:H22)<=MIN(Daily!G17:G22),"WITHIN CAP","OVER CAP") -> WITHIN CAP | O10: =IF(AND(L10<=WF_BUDGET,N10="WITHIN CAP"),"YES","NO") -> YES | P10: =C10*1.2 -> 14688 | Q10: =J10-C10+P10 -> 51185.6 | R10: =Q10*WF_RESERVE_RATE -> 2559.28 | S10: =Q10+R10 -> 53744.88 | T10: =IF(S10<=WF_BUDGET,"YES","NO") -> NO | U10: =IF(T10="YES","Proceed within current ceiling.","Do not approve stressed fare at this headcount: obtain average round-trip airfare at or below "&TEXT(MAX(0,(WF_BUDGET/(1+WF_RESERVE_RATE)-(J10-C10))/B10),"$#,##0.00")&" per traveler, reduce to an eligible 18-person option, or obtain a higher approved ceiling before obligation.") -> Do not approve stressed fare at this headcount: obtain average round-trip airfare at or below $582.44 per traveler, reduce to an eligible 18-person option, or obtain a higher approved ceiling before obligation. | V10: =IF(O10="YES",(24-B10)*1000000000+L10+ROW()/1000000,1000000000000000) -> 51174.48

Sheet Sources
A1: Sources, Rules, and Assumptions
A2: Offline source package controls this exercise. Website links below are citations captured in the supplied GSA page, not live retrievals or hotel approvals.
A4: Category | B4: Source / citation | C4: Sheet row or section | D4: Location / date | E4: Value / rule used | F4: How it enters model | G4: Link captured in supplied GSA HTML | H4: Approval significance
A5: Official rate | B5: FY2025_PerDiemMasterRatesFile.xlsx | C5: Master Excel row 258 | D5: Chicago, IL; Cook; 2025-09-27 through 2025-09-30 | E5: Lodging cap $223.00; M&IE $92.00 | F5: Daily matches fiscal year (FY begins Oct. 1), county/destination, and seasonal row; cap tests quote and full M&IE drives meal deductions. | G5: https://www.gsa.gov/system/files/FY2025_PerDiemMasterRatesFile.xlsx | H5: Rate evidence only; does not approve facility.
A6: Official rate | B6: FY2026_PerDiemMasterRatesFile.xlsx | C6: Master Excel row 254 | D6: Chicago, IL; Cook; 2025-10-01 through 2025-10-02 | E6: Lodging cap $223.00; M&IE $92.00 | F6: Daily matches fiscal year (FY begins Oct. 1), county/destination, and seasonal row; cap tests quote and full M&IE drives meal deductions. | G6: https://www.gsa.gov/system/files/FY2026_PerDiemMasterRatesFile.xlsx | H6: Rate evidence only; does not approve facility.
A7: Official rate | B7: FY2025_PerDiemMasterRatesFile.xlsx | C7: Master Excel row 109 | D7: Denver, CO; Denver; 2025-09-27 through 2025-09-30 | E7: Lodging cap $215.00; M&IE $92.00 | F7: Daily matches fiscal year (FY begins Oct. 1), county/destination, and seasonal row; cap tests quote and full M&IE drives meal deductions. | G7: https://www.gsa.gov/system/files/FY2025_PerDiemMasterRatesFile.xlsx | H7: Rate evidence only; does not approve facility.
A8: Official rate | B8: FY2026_PerDiemMasterRatesFile.xlsx | C8: Master Excel row 107 | D8: Denver, CO; Denver; 2025-10-01 through 2025-10-02 | E8: Lodging cap $215.00; M&IE $92.00 | F8: Daily matches fiscal year (FY begins Oct. 1), county/destination, and seasonal row; cap tests quote and full M&IE drives meal deductions. | G8: https://www.gsa.gov/system/files/FY2026_PerDiemMasterRatesFile.xlsx | H8: Rate evidence only; does not approve facility.
A9: Official rate | B9: FY2025_PerDiemMasterRatesFile.xlsx | C9: Master Excel row 22 | D9: Phoenix, AZ; Maricopa; 2025-09-27 through 2025-09-30 | E9: Lodging cap $160.00; M&IE $86.00 | F9: Daily matches fiscal year (FY begins Oct. 1), county/destination, and seasonal row; cap tests quote and full M&IE drives meal deductions. | G9: https://www.gsa.gov/system/files/FY2025_PerDiemMasterRatesFile.xlsx | H9: Rate evidence only; does not approve facility.
A10: Official rate | B10: FY2026_PerDiemMasterRatesFile.xlsx | C10: Master Excel row 18 | D10: Phoenix, AZ; Maricopa; 2025-10-01 through 2025-10-02 | E10: Lodging cap $160.00; M&IE $86.00 | F10: Daily matches fiscal year (FY begins Oct. 1), county/destination, and seasonal row; cap tests quote and full M&IE drives meal deductions. | G10: https://www.gsa.gov/system/files/FY2026_PerDiemMasterRatesFile.xlsx | H10: Rate evidence only; does not approve facility.
A11: Meal allocation | B11: GSA_FY2025_MIE_Breakdown.docx | C11: FY2025–present table | D11: CONUS; applicable throughout trip | E11: $92: breakfast 23, lunch 26, dinner 38, incidentals 5, first/last 69; $86: 22/23/36/5/64.50 | F11: Allocates furnished-meal deductions and 75% first/last-day amount. | G11: https://www.gsa.gov/system/files/FY%202025%20MIE%20Breakdown.docx | H11: Supports deduction arithmetic.
A12: FTR | B12: 41 CFR 301-11.18 | C12: §301-11.18 | D12: Government-furnished or registration-included meals | E12: Deduct full allocated meal amount; on first/last day deduct from reduced M&IE; deductions cannot reduce below incidentals. | F12: Daily applies 75% first, then breakfast/lunch/dinner deductions, then $5 floor. | G12: https://www.gsa.gov/mie | H12: Binding calculation rule in supplied frozen eCFR.
A13: FTR | B13: 41 CFR 301-11.17 and GSA M&IE breakdown note | C13: §301-11.17; document introduction | D13: Complimentary hotel breakfast | E13: No M&IE reduction. | F13: Daily notes breakfast but does not deduct it. | H13: Binding treatment; verify breakfast is truly complimentary.
A14: FTR | B14: 41 CFR 301-74.21 | C14: §301-74.21 | D14: Meals and light refreshments | E14: Meals require deduction; light refreshments do not. | F14: Registration lunches and Government dinners/lunch are deducted; coffee and fruit breaks are not. | H14: Binding treatment in supplied frozen eCFR.
A15: FTR | B15: 41 CFR 301-11.100, 301-11.27 | C15: §§301-11.100, 301-11.27 | D15: Lodging and lodging tax | E15: Actual lodging reimbursed up to cap; tax is outside per diem and limited to tax on reimbursable lodging. | F15: Model uses MIN(quote, cap), then 12% internal estimated tax. The cap is never booked as spending. | H15: Tax rate is an exercise assumption, not local tax law.
A16: FTR | B16: 41 CFR 301-11.101–102 | C16: §§301-11.101–102 | D16: Travel-day M&IE | E16: 75% on departure and return days; full rate on full days; location rule applies. | F16: Arrival input determines actual first travel day; return remains 10/02. | H16: Binding day-rate method.
A17: FTR | B17: 41 CFR 301-11.11; 301-74.9–10 | C17: §§301-11.11, 301-74.9–10 | D17: Booking and accommodation safety | E17: Use agency travel management service; fire-safe / approved accommodation requirements, unless proper waiver. | F17: Not priced; carried as blocking approval evidence. | H17: Facility status remains unverified.
A18: FTR | B18: 41 CFR 301-74.5 | C18: §301-74.5 | D18: Site selection | E18: Exercise strict fiscal responsibility; compare relevant costs using established per diem rates. | F18: Options compares all six scenarios and includes rates in lodging/M&IE logic. | H18: Cost comparison does not replace acquisition review.
A19: FTR | B19: 41 CFR 301-74.22; 301-11.300–302 | C19: §301-74.22; §§301-11.300–302 | D19: Actual expense | E19: May be authorized if lodging rate inadequate; designated official; request in advance. | F19: No actual-expense amount assumed because all quotes are within cap; any later excess requires authorization. | H19: Blocking if an over-cap booking is proposed.
A20: Exercise assumption | B20: User-provided facts | C20: N/A | D20: All cities / dates | E20: 12% tax; fixed quotes and meal calendar; single rooms; no extras; 5% default reserve; $53,000 default ceiling. | F20: ControlPanel and formulas. | H20: Internal budgeting assumptions, not FTR text.
A21: Internal control (recommended) | B21: Approval register / agency procedure | C21: Not represented as FTR text | D21: Procurement, funds, conference approval | E21: Obtain contracting and funds evidence before obligation; follow agency-specific conference approvals. | F21: Shown as approval gates; no claim that these workflow details are prescribed verbatim by FTR. | H21: Required for an approvable package under agency controls.
